Workbook

Sheet README
A1: ANTEPARO — CALL SHEET
A2: Run 20260903T230309Z-e5fb2e · generated 2026-09-03 · 54 leads ≥ R$200k · 17 pooling leads (R$100–200k) · 40 source documents · 32 cases
A4: WHAT EACH ROW IS
A5: One company × one recovery case. The company holds class III (trade) credit against the debtor, admitted in the court's own creditor list. All establishments of the company (same 8-digit CNPJ root) are summed.
A7: THE NUMBER
A8: 'Class III face' is the admitted value AS PRINTED in the court document — what the company is OWED, updated only to the filing date (art. 9 II). It is NOT what will be paid.
A9: 'OUR QUOTE' is a model: face → assumed plan terms → discounted at the investor IRR → fund price → our share. Edit the Assumptions tab. It is not court data.
A11: PROOF OF CLAIM (green columns)
A12: Click 'PROOF: source document', go to the page/row listed, and read the value as printed. If a seller asks 'how did you get this?', that link is the answer.
A13: 'Reconciled' = OK means the document's extracted class totals matched its own printed totals within 0.5%. OK_NO_TOTALS means the document prints no totals — the number was read from its own row but could not be cross-checked; quote with that caveat.
A15: DECISION-MAKER
A16: From the Receita Federal partner register (sócio-administrador / administrador / diretor / presidente). Phone and email are the company's registry contact. Confidence LOW = registry only; nothing here was guessed or looked up from memory.
... A22: Individuals (CPF), banks (CNAE 64–66), public entities, inactive companies, foreign-currency claims, extraconcursal sections, quarantined documents. They remain in the CSV tables with flags.

Sheet Assumptions
A1: PRICING ASSUMPTIONS — edit the yellow cells; every quote on the call sheet recalculates
A3: Target investor IRR (annual) | B3: 0.25 | F3: Fund price = face × recovery% ÷ (1+IRR)^(years to payment). A fund needing 25% IRR on a plan paying 30% over years 3–10 pays ~8 cents, not 25 — check the 7 buyers' real numbers against this.
A4: Buy price as share of fund price (we pay 60% → 0.60) | B4: 0.6 | F4: Our quote = fund price × this share. The doc rule is 60% of mandate price; expected 55–70% once Gate 6 data exists.
A6: Plan status | B6: Class III recovery % of face | C6: Grace (years) | D6: Term (years) | E6: Note
A7: CONFIRMED | B7: 0.4 | C7: 2 | D7: 8 | E7: A plan/homologation document exists for the case. ASSUMED terms until plan parsing lands — replace with the plan's own class III terms.
A8: ESTIMATED | B8: 0.3 | C8: 2 | D8: 8 | E8: No plan document found; case is live in DataJud. ASSUMED typical Brazilian class III terms.
A9: UNKNOWN | B9: 0.25 | C9: 3 | D9: 8 | E9: Case not matched to DataJud. ASSUMED, conservative.
A10: CONVERTED_TO_BANKRUPTCY | B10: 0.05 | C10: 4 | D10: 4 | E10: Falência decreed. Class III ranks behind labour and secured; assume near-zero.
A13: Everything in this tab is an ASSUMPTION, not court data. The face value on the call sheet IS court data — it links to the page.

Sheet Call List
A1: Rank | B1: Status | C1: Owner | D1: Attempts | E1: Last touch | F1: Next action | G1: Next date | H1: Notes | I1: Company (RFB) | J1: Name as printed | K1: CNPJ root | L1: Establishment CNPJs | M1: Class III face (R$) | N1: Claims | O1: Plan status | P1: Stage | Q1: Case filed | R1: Years since filing | S1: Est. recovery % | T1: Years to payment (est.) | U1: Fund price @ IRR (R$) | V1: Fund price (cents) | W1: OUR QUOTE (R$) | X1: Quote (cents) | Y1: Debtor | Z1: Case number | AA1: Court | AB1: Administrator (site) | AC1: Decision-maker | AD1: Role | AE1: Phone | AF1: Phone 2 | AG1: Email | AH1: UF | AI1: City | AJ1: CNAE | AK1: Porte | AL1: Situação | AM1: PROOF: source document | AN1: Page / row | AO1: Value as printed | AP1: Which list | AQ1: Published | AR1: Reconciled | AS1: Data flags | AT1: Doc id
A2: 1 | B2: NEW | D2: 0 | I2: TAG INDUSTRIA E LAMINACAO LTDA | J2: TAG INDUSTRIA E LAMINACAO LTDA | K2: 33233778 | L2: 33233778000108 | M2: 64713515 | N2: 2 | O2: UNKNOWN | R2: =IF(Q2="","",ROUND((TODAY()-Q2)/365.25,1)) | S2: =VLOOKUP(O2,Assumptions!$A$7:$E$10,2,FALSE) | T2: =MAX(0.5,VLOOKUP(O2,Assumptions!$A$7:$E$10,3,FALSE)+VLOOKUP(O2,Assumptions!$A$7:$E$10,4,FALSE)/2-IF(R2="",0,R2)) | U2: =M2*S2/(1+Assumptions!$B$3)^T2 | V2: =IF(M2=0,"",ROUND(U2/M2*100,1)) | W2: =U2*Assumptions!$B$4 | X2: =IF(M2=0,"",ROUND(W2/M2*100,1)) | Y2: Conduscabos Brasil Indústria Comércio de | Z2: 8005129-09.2023.8.05.0039 | AB2: assistjud.com.br | AC2: TIAGO RODRIGO DETTILIO | AD2: Administrador | AE2: (11) 4463-4833 | AH2: SP | AI2: SAO PAULO | AJ2: Outras atividades profissionais, científicas e técnicas não especificadas anteriormente | AK2: DEMAIS | AL2: ATIVA | AM2: https://assistjud.com.br/wp-content/uploads/elementor/forms/65098c80a5824.pdf | AN2: p10 r4; p19 r8 | AO2: p10: R$ 32.731.819,08; p19: R$ 31.981.695,98 | AP2: AJ_LIST | AQ2: 2023-09-18 | AR2: OK_NO_TOTALS | AS2: ROWS:p10r4,p19r8 UNRECONCILED_SOURCE | AT2: a0ae32a59c29
A3: 2 | B3: NEW | D3: 0 | J3: FUNDO DE INVESTIMENTO EM DIREITOS CREDITÓRIOS NÃO PADRONIZADOS MULTISSETORIA L BS NP | K3: 12428086 | L3: 12428086000137 | M3: 14857605 | N3: 3 | O3: UNKNOWN | R3: =IF(Q3="","",ROUND((TODAY()-Q3)/365.25,1)) | S3: =VLOOKUP(O3,Assumptions!$A$7:$E$10,2,FALSE) | T3: =MAX(0.5,VLOOKUP(O3,Assumptions!$A$7:$E$10,3,FALSE)+VLOOKUP(O3,Assumptions!$A$7:$E$10,4,FALSE)/2-IF(R3="",0,R3)) | U3: =M3*S3/(1+Assumptions!$B$3)^T3 | V3: =IF(M3=0,"",ROUND(U3/M3*100,1)) | W3: =U3*Assumptions!$B$4 | X3: =IF(M3=0,"",ROUND(W3/M3*100,1)) | Y3: Conduscabos Brasil Indústria Comércio de | Z3: 8005129-09.2023.8.05.0039 | AB3: assistjud.com.br | AM3: https://assistjud.com.br/wp-content/uploads/elementor/forms/65098c80a5824.pdf | AN3: p7 r8; p10 r1; p18 r2 | AO3: p7: R$ 10.954.112,61; p10: R$ 1.455.516,44; p18: R$ 2.447.975,63 | AP3: AJ_LIST | AQ3: 2023-09-18 | AR3: OK_NO_TOTALS | AS3: ROWS:p7r8,p10r1,p18r2 UNRECONCILED_SOURCE | AT3: a0ae32a59c29
A4: 3 | B4: NEW | D4: 0 | I4: FRESENIUS MEDICAL CARE LTDA | J4: FRESENIUS MEDICAL CARE LTDA | K4: 01440590 | L4: 01440590000136 | M4: 14567734 | N4: 1 | O4: UNKNOWN | R4: =IF(Q4="","",ROUND((TODAY()-Q4)/365.25,1)) | S4: =VLOOKUP(O4,Assumptions!$A$7:$E$10,2,FALSE) | T4: =MAX(0.5,VLOOKUP(O4,Assumptions!$A$7:$E$10,3,FALSE)+VLOOKUP(O4,Assumptions!$A$7:$E$10,4,FALSE)/2-IF(R4="",0,R4)) | U4: =M4*S4/(1+Assumptions!$B$3)^T4 | V4: =IF(M4=0,"",ROUND(U4/M4*100,1)) | W4: =U4*Assumptions!$B$4 | X4: =IF(M4=0,"",ROUND(W4/M4*100,1)) | Z4: (not found in document) | AB4: bernardobicalho.com.br | AC4: ANA LUCIA ZENKNER PERCIA | AD4: Administrador | AE4: (19) 3847-9700 | AF4: (19) 3847-9700 | AH4: SP | AI4: JAGUARIUNA | AJ4: Fabricação de medicamentos alopáticos para uso humano | AK4: DEMAIS | AL4: ATIVA | AM4: http://bernardobicalho.com.br/login/app/documents/Rela%C3%A7%C3%A3o%20de%20Credores/6.%20RVC-%20Nutricium%20-%20simplificada.pdf | AN4: p3 r16 | AO4: p3: R$ 14.567.733,99 | AP4: AJ_LIST | AR4: OK | AS4: CASE_NUMBER_MISSING ROWS:p3r16 | AT4: 6a92d74da333
A5: 4 | B5: NEW | D5: 0 | I5: VINICOLA CAMPESTRE LTDA | J5: VINICOLA CAMPESTRE LTDA | K5: 98521909 | L5: 98521909000190, 98521909000270 | M5: 13980346 | N5: 2 | O5: UNKNOWN | R5: =IF(Q5="","",ROUND((TODAY()-Q5)/365.25,1)) | S5: =VLOOKUP(O5,Assumptions!$A$7:$E$10,2,FALSE) | T5: =MAX(0.5,VLOOKUP(O5,Assumptions!$A$7:$E$10,3,FALSE)+VLOOKUP(O5,Assumptions!$A$7:$E$10,4,FALSE)/2-IF(R5="",0,R5)) | U5: =M5*S5/(1+Assumptions!$B$3)^T5 | V5: =IF(M5=0,"",ROUND(U5/M5*100,1)) | W5: =U5*Assumptions!$B$4 | X5: =IF(M5=0,"",ROUND(W5/M5*100,1)) | Y5: ARRUDA & MELO COMERCIO E DISTRIBUICAO DE ALIMENTOS E BEBIDAS LTDA | Z5: 0008526-45.2025.8.17.2001 | AB5: diligence.adm.br | AC5: CESAR AUGUSTO ZANOTTO | AD5: Sócio-Administrador | AE5: (54) 3511-6050 | AF5: (54) 3511-6052 | AH5: RS | AI5: CAMPESTRE DA SERRA | AJ5: Fabricação de vinho | AK5: DEMAIS | AL5: ATIVA | AM5: https://diligence.adm.br/wp-content/uploads/2025/06/Edital-1a-Lista-de-Credores.pdf | AN5: p5 r60; p5 r61 | AO5: p5: R$ 4.421.862,65; p5: R$ 9.558.482,85 | AP5: DEBTOR_LIST | AQ5: 2025-06-10 | AR5: OK | AS5: ROWS:p5r60,p5r61 | AT5: 1658892fa167
A6: 5 | B6: NEW | D6: 0 | I6: ALBAUGH AGRO BRASIL LTDA. | J6: ALBAUGH AGRO BRASIL LTDA | K6: 01789121 | L6: 01789121000470, 01789121000984, 01789121001107 | M6: 11525550 | N6: 1 | O6: UNKNOWN | R6: =IF(Q6="","",ROUND((TODAY()-Q6)/365.25,1)) | S6: =VLOOKUP(O6,Assumptions!$A$7:$E$10,2,FALSE) | T6: =MAX(0.5,VLOOKUP(O6,Assumptions!$A$7:$E$10,3,FALSE)+VLOOKUP(O6,Assumptions!$A$7:$E$10,4,FALSE)/2-IF(R6="",0,R6)) | U6: =M6*S6/(1+Assumptions!$B$3)^T6 | V6: =IF(M6=0,"",ROUND(U6/M6*100,1)) | W6: =U6*Assumptions!$B$4 | X6: =IF(M6=0,"",ROUND(W6/M6*100,1)) | Y6: SOJAL COMERCIAL AGRICOLA | Z6: 0804401-51.2025.8.14.0039 | AB6: lrflideres.com.br | AC6: CESAR EMILIANO ROJAS RUIZ | AD6: Administrador | AE6: (11) 3076-4243 | AH6: SP | AI6: SAO PAULO | AJ6: Fabricação de defensivos agrícolas | AK6: DEMAIS | AL6: ATIVA | AM6: https://lrflideres.com.br/wp-content/plugins/download-attachments/includes/download.php?id=6879 | AN6: p1 r4 | AO6: p1: R$ 11.525.550,26 | AP6: AJ_LIST | AQ6: 2026-01-15 | AR6: OK | AS6: ROWS:p1r4 | AT6: c56751547323
A7: 6 | B7: NEW | D7: 0 | I7: ADDIANTE S.A | J7: ADDIANTE S.A | K7: 48430290 | L7: 48430290000130 | M7: 7135517 | N7: 1 | O7: UNKNOWN | R7: =IF(Q7="","",ROUND((TODAY()-Q7)/365.25,1)) | S7: =VLOOKUP(O7,Assumptions!$A$7:$E$10,2,FALSE) | T7: =MAX(0.5,VLOOKUP(O7,Assumptions!$A$7:$E$10,3,FALSE)+VLOOKUP(O7,Assumptions!$A$7:$E$10,4,FALSE)/2-IF(R7="",0,R7)) | U7: =M7*S7/(1+Assumptions!$B$3)^T7 | V7: =IF(M7=0,"",ROUND(U7/M7*100,1)) | W7: =U7*Assumptions!$B$4 | X7: =IF(M7=0,"",ROUND(W7/M7*100,1)) | Y7: SOJAL COMERCIAL AGRICOLA | Z7: 0804401-51.2025.8.14.0039 | AB7: lrflideres.com.br | AC7: FABIO ROBERTO LEITE | AD7: Presidente | AE7: (41) 9571-0152 | AH7: PR | AI7: CURITIBA | AJ7: Locação de outros meios de transporte não especificados anteriormente, sem condutor | AK7: DEMAIS | AL7: ATIVA | AM7: https://lrflideres.com.br/wp-content/plugins/download-attachments/includes/download.php?id=6879 | AN7: p1 r2 | AO7: p1: R$ 7.135.516,97 | AP7: AJ_LIST | AQ7: 2026-01-15 | AR7: OK | AS7: ROWS:p1r2 | AT7: c56751547323
A8: 7 | B8: NEW | D8: 0 | I8: SOLUS DO BRASIL LTDA | J8: SOLUS INDUSTRIA QUIMICA LTDA | K8: 21203489 | L8: 21203489000764, 21203489000926 | M8: 7058181.5 | N8: 1 | O8: UNKNOWN | R8: =IF(Q8="","",ROUND((TODAY()-Q8)/365.25,1)) | S8: =VLOOKUP(O8,Assumptions!$A$7:$E$10,2,FALSE) | T8: =MAX(0.5,VLOOKUP(O8,Assumptions!$A$7:$E$10,3,FALSE)+VLOOKUP(O8,Assumptions!$A$7:$E$10,4,FALSE)/2-IF(R8="",0,R8)) | U8: =M8*S8/(1+Assumptions!$B$3)^T8 | V8: =IF(M8=0,"",ROUND(U8/M8*100,1)) | W8: =U8*Assumptions!$B$4 | X8: =IF(M8=0,"",ROUND(W8/M8*100,1)) | Y8: SOJAL COMERCIAL AGRICOLA | Z8: 0804401-51.2025.8.14.0039 | AB8: lrflideres.com.br | AC8: ANDERSON JOSE FAUSTINO | AD8: Administrador | AE8: (43) 3162-2715 | AH8: PR | AI8: APUCARANA | AJ8: Fabricação de defensivos agrícolas | AK8: DEMAIS | AL8: ATIVA | AM8: https://lrflideres.com.br/wp-content/plugins/download-attachments/includes/download.php?id=6879 | AN8: p2 r10 | AO8: p2: R$ 7.058.181,50 | AP8: AJ_LIST | AQ8: 2026-01-15 | AR8: OK | AS8: ROWS:p2r10 | AT8: c56751547323
A9: 8 | B9: NEW | D9: 0 | I9: NORTESUL COMERCIAL AGRICOLA LTDA EM RECUPERACAO JUDICIAL | J9: NORTESUL COMERCIAL AGRICOLA LTDA | K9: 15626673 | L9: 15626673000129, 15626673000390, 15626673000552 | M9: 6258845.3 | N9: 1 | O9: UNKNOWN | R9: =IF(Q9="","",ROUND((TODAY()-Q9)/365.25,1)) | S9: =VLOOKUP(O9,Assumptions!$A$7:$E$10,2,FALSE) | T9: =MAX(0.5,VLOOKUP(O9,Assumptions!$A$7:$E$10,3,FALSE)+VLOOKUP(O9,Assumptions!$A$7:$E$10,4,FALSE)/2-IF(R9="",0,R9)) | U9: =M9*S9/(1+Assumptions!$B$3)^T9 | V9: =IF(M9=0,"",ROUND(U9/M9*100,1)) | W9: =U9*Assumptions!$B$4 | X9: =IF(M9=0,"",ROUND(W9/M9*100,1)) | Y9: SOJAL COMERCIAL AGRICOLA | Z9: 0804401-51.2025.8.14.0039 | AB9: lrflideres.com.br | AC9: JULIANO MENDES DOS SANTOS | AD9: Sócio-Administrador | AE9: (63) 3602-4239 | AH9: TO | AI9: PALMAS | AJ9: Comércio atacadista de matérias-primas agrícolas não especificadas anteriormente | AK9: DEMAIS | AL9: ATIVA | AM9: https://lrflideres.com.br/wp-content/plugins/download-attachments/includes/download.php?id=6879 | AN9: p2 r5 | AO9: p2: R$ 6.258.845,34 | AP9: AJ_LIST | AQ9: 2026-01-15 | AR9: OK | AS9: ROWS:p2r5 | AT9: c56751547323
A10: 9 | B10: NEW | D10: 0 | J10: FARM TECH IBBA I FIDC | K10: 47151680 | L10: 31652424000164, 47151680000108 | M10: 5767665.6 | N10: 1 | O10: UNKNOWN | R10: =IF(Q10="","",ROUND((TODAY()-Q10)/365.25,1)) | S10: =VLOOKUP(O10,Assumptions!$A$7:$E$10,2,FALSE) | T10: =MAX(0.5,VLOOKUP(O10,Assumptions!$A$7:$E$10,3,FALSE)+VLOOKUP(O10,Assumptions!$A$7:$E$10,4,FALSE)/2-IF(R10="",0,R10)) | U10: =M10*S10/(1+Assumptions!$B$3)^T10 | V10: =IF(M10=0,"",ROUND(U10/M10*100,1)) | W10: =U10*Assumptions!$B$4 | X10: =IF(M10=0,"",ROUND(W10/M10*100,1)) | Y10: SOJAL COMERCIAL AGRICOLA | Z10: 0804401-51.2025.8.14.0039 | AB10: lrflideres.com.br | AM10: https://lrflideres.com.br/wp-content/plugins/download-attachments/includes/download.php?id=6879 | AN10: p1 r13 | AO10: p1: R$ 5.767.665,60 | AP10: AJ_LIST | AQ10: 2026-01-15 | AR10: OK | AS10: MULTI_ROOT ROWS:p1r13 | AT10: c56751547323
A11: 10 | B11: NEW | D11: 0 | I11: JF PASQUA CONDUTORES ELETRICOS LTDA | J11: JF PASQUA CONDUTORES ELETRICOS LTDA | K11: 03981899 | L11: 03981899000169 | M11: 4940520.9 | N11: 2 | O11: UNKNOWN | R11: =IF(Q11="","",ROUND((TODAY()-Q11)/365.25,1)) | S11: =VLOOKUP(O11,Assumptions!$A$7:$E$10,2,FALSE) | T11: =MAX(0.5,VLOOKUP(O11,Assumptions!$A$7:$E$10,3,FALSE)+VLOOKUP(O11,Assumptions!$A$7:$E$10,4,FALSE)/2-IF(R11="",0,R11)) | U11: =M11*S11/(1+Assumptions!$B$3)^T11 | V11: =IF(M11=0,"",ROUND(U11/M11*100,1)) | W11: =U11*Assumptions!$B$4 | X11: =IF(M11=0,"",ROUND(W11/M11*100,1)) | Y11: Conduscabos Brasil Indústria Comércio de | Z11: 8005129-09.2023.8.05.0039 | AB11: assistjud.com.br | AC11: REGINA MARIA PASQUA SANTOS | AD11: Administrador | AE11: (35) 3559-6789 | AH11: MG | AI11: GUAXUPE | AJ11: Metalurgia do cobre | AK11: DEMAIS | AL11: ATIVA | AM11: https://assistjud.com.br/wp-content/uploads/elementor/forms/65098c80a5824.pdf | AN11: p8 r4; p18 r6 | AO11: p8: R$ 2.217.364,91; p18: R$ 2.723.156,00 | AP11: AJ_LIST | AQ11: 2023-09-18 | AR11: OK_NO_TOTALS | AS11: ROWS:p8r4,p18r6 UNRECONCILED_SOURCE | AT11: a0ae32a59c29
A12: 11 | B12: NEW | D12: 0 | I12: COMPANHIA DE AGUA E ESGOTOS DA PARAIBA CAGEPA | J12: COMPANHIA DE ÁGUA E ESGOTOS DA PARAIBA CAGEPA | K12: 09123654 | L12: 09123654000187 | M12: 3641949.7 | N12: 1 | O12: UNKNOWN | R12: =IF(Q12="","",ROUND((TODAY()-Q12)/365.25,1)) | S12: =VLOOKUP(O12,Assumptions!$A$7:$E$10,2,FALSE) | T12: =MAX(0.5,VLOOKUP(O12,Assumptions!$A$7:$E$10,3,FALSE)+VLOOKUP(O12,Assumptions!$A$7:$E$10,4,FALSE)/2-IF(R12="",0,R12)) | U12: =M12*S12/(1+Assumptions!$B$3)^T12 | V12: =IF(M12=0,"",ROUND(U12/M12*100,1)) | W12: =U12*Assumptions!$B$4 | X12: =IF(M12=0,"",ROUND(W12/M12*100,1)) | Y12: DR. ALLAN DE QUEIROZ RAMOS – OAB/PB 20.574 | Z12: 0829315-43.2023.8.15.0001 | AB12: lrflideres.com.br | AC12: MARCUS VINICIUS FERNANDES NEVES | AD12: Presidente | AE12: (83) 3218-1200 | AF12: (83) 3218-1225 | AH12: PB | AI12: JOAO PESSOA | AJ12: Captação, tratamento e distribuição de água | AK12: DEMAIS | AL12: ATIVA | AM12: https://lrflideres.com.br/wp-content/plugins/download-attachments/includes/download.php?id=5828 | AN12: p3 r16 | AO12: p3: R$ 3.641.949,67 | AP12: AJ_LIST | AQ12: 2024-04-18 | AR12: OK | AS12: ROWS:p3r16 | AT12: 47e92e4db6f8
A13: 12 | B13: NEW | D13: 0 | I13: VEGETAL AGRONEGOCIOS LTDA | J13: VEGETAL AGRONEGOCIOS LTDA | K13: 05429994 | L13: 05429994001313 | M13: 3014807.2 | N13: 1 | O13: UNKNOWN | R13: =IF(Q13="","",ROUND((TODAY()-Q13)/365.25,1)) | S13: =VLOOKUP(O13,Assumptions!$A$7:$E$10,2,FALSE) | T13: =MAX(0.5,VLOOKUP(O13,Assumptions!$A$7:$E$10,3,FALSE)+VLOOKUP(O13,Assumptions!$A$7:$E$10,4,FALSE)/2-IF(R13="",0,R13)) | U13: =M13*S13/(1+Assumptions!$B$3)^T13 | V13: =IF(M13=0,"",ROUND(U13/M13*100,1)) | W13: =U13*Assumptions!$B$4 | X13: =IF(M13=0,"",ROUND(W13/M13*100,1)) | Y13: SOJAL COMERCIAL AGRICOLA | Z13: 0804401-51.2025.8.14.0039 | AB13: lrflideres.com.br | AC13: ALDAIR REMUSSI | AD13: Sócio-Administrador | AE13: (61) 3234-8485 | AH13: DF | AI13: BRASILIA | AJ13: Comércio atacadista de defensivos agrícolas, adubos, fertilizantes e corretivos do solo | AK13: DEMAIS | AL13: ATIVA | AM13: https://lrflideres.com.br/wp-content/plugins/download-attachments/includes/download.php?id=6879 | AN13: p2 r13 | AO13: p2: R$ 3.014.807,20 | AP13: AJ_LIST | AQ13: 2026-01-15 | AR13: OK | AS13: ROWS:p2r13 | AT13: c56751547323
A14: 13 | B14: NEW | D14: 0 | I14: CROMO INDUSTRIA QUIMICA S.A. | J14: CROMO INDUSTRIA QUIMICA S.A | K14: 31281962 | L14: 31281962000190, 31281962000270 | M14: 2406485.6 | N14: 1 | O14: UNKNOWN | R14: =IF(Q14="","",ROUND((TODAY()-Q14)/365.25,1)) | S14: =VLOOKUP(O14,Assumptions!$A$7:$E$10,2,FALSE) | T14: =MAX(0.5,VLOOKUP(O14,Assumptions!$A$7:$E$10,3,FALSE)+VLOOKUP(O14,Assumptions!$A$7:$E$10,4,FALSE)/2-IF(R14="",0,R14)) | U14: =M14*S14/(1+Assumptions!$B$3)^T14 | V14: =IF(M14=0,"",ROUND(U14/M14*100,1)) | W14: =U14*Assumptions!$B$4 | X14: =IF(M14=0,"",ROUND(W14/M14*100,1)) | Y14: SOJAL COMERCIAL AGRICOLA | Z14: 0804401-51.2025.8.14.0039 | AB14: lrflideres.com.br | AC14: JOSIR NEULS | AD14: Presidente | AE14: (11) 4130-8138 | AH14: RS | AI14: ESTRELA | AJ14: Fabricação de outros produtos químicos não especificados anteriormente | AK14: DEMAIS | AL14: ATIVA | AM14: https://lrflideres.com.br/wp-content/plugins/download-attachments/includes/download.php?id=6879 | AN14: p1 r11 | AO14: p1: R$ 2.406.485,64 | AP14: AJ_LIST | AQ14: 2026-01-15 | AR14: OK | AS14: ROWS:p1r11 | AT14: c56751547323
A15: 14 | B15: NEW | D15: 0 | J15: GAVEA FIDC | K15: 12910431 | L15: 12910431000174 | M15: 2327494.5 | N15: 3 | O15: UNKNOWN | R15: =IF(Q15="","",ROUND((TODAY()-Q15)/365.25,1)) | S15: =VLOOKUP(O15,Assumptions!$A$7:$E$10,2,FALSE) | T15: =MAX(0.5,VLOOKUP(O15,Assumptions!$A$7:$E$10,3,FALSE)+VLOOKUP(O15,Assumptions!$A$7:$E$10,4,FALSE)/2-IF(R15="",0,R15)) | U15: =M15*S15/(1+Assumptions!$B$3)^T15 | V15: =IF(M15=0,"",ROUND(U15/M15*100,1)) | W15: =U15*Assumptions!$B$4 | X15: =IF(M15=0,"",ROUND(W15/M15*100,1)) | Y15: Conduscabos Brasil Indústria Comércio de | Z15: 8005129-09.2023.8.05.0039 | AB15: assistjud.com.br | AM15: https://assistjud.com.br/wp-content/uploads/elementor/forms/65098c80a5824.pdf | AN15: p7 r9; p8 r18; p9 r15 | AO15: p7: R$ 775.620,94; p8: R$ 462.653,52; p9: R$ 1.089.220,04 | AP15: AJ_LIST | AQ15: 2023-09-18 | AR15: OK_NO_TOTALS | AS15: ROWS:p7r9,p8r18,p9r15 UNRECONCILED_SOURCE | AT15: a0ae32a59c29
A16: 15 | B16: NEW | D16: 0 | J16: BANCO INDUSTRIAL DO BRASIL S/A | K16: 31895683 | L16: 31895683000116 | M16: 2056998.2 | N16: 2 | O16: UNKNOWN | R16: =IF(Q16="","",ROUND((TODAY()-Q16)/365.25,1)) | S16: =VLOOKUP(O16,Assumptions!$A$7:$E$10,2,FALSE) | T16: =MAX(0.5,VLOOKUP(O16,Assumptions!$A$7:$E$10,3,FALSE)+VLOOKUP(O16,Assumptions!$A$7:$E$10,4,FALSE)/2-IF(R16="",0,R16)) | U16: =M16*S16/(1+Assumptions!$B$3)^T16 | V16: =IF(M16=0,"",ROUND(U16/M16*100,1)) | W16: =U16*Assumptions!$B$4 | X16: =IF(M16=0,"",ROUND(W16/M16*100,1)) | Y16: Conduscabos Brasil Indústria Comércio de | Z16: 8005129-09.2023.8.05.0039 | AB16: assistjud.com.br | AM16: https://assistjud.com.br/wp-content/uploads/elementor/forms/65098c80a5824.pdf | AN16: p5 r11; p17 r5 | AO16: p5: R$ 1.047.741,53; p17: R$ 1.009.256,67 | AP16: AJ_LIST | AQ16: 2023-09-18 | AR16: OK_NO_TOTALS | AS16: ROWS:p5r11,p17r5 UNRECONCILED_SOURCE VALUE_COL:Valor_Do_Crédito_2º_Edital_De_Credores | AT16: a0ae32a59c29
A17: 16 | B17: NEW | D17: 0 | I17: SEMPRE AGTECH LTDA | J17: SEMPRE AGTECH LTDA | K17: 09536120 | L17: 09536120000263 | M17: 2037617 | N17: 1 | O17: UNKNOWN | R17: =IF(Q17="","",ROUND((TODAY()-Q17)/365.25,1)) | S17: =VLOOKUP(O17,Assumptions!$A$7:$E$10,2,FALSE) | T17: =MAX(0.5,VLOOKUP(O17,Assumptions!$A$7:$E$10,3,FALSE)+VLOOKUP(O17,Assumptions!$A$7:$E$10,4,FALSE)/2-IF(R17="",0,R17)) | U17: =M17*S17/(1+Assumptions!$B$3)^T17 | V17: =IF(M17=0,"",ROUND(U17/M17*100,1)) | W17: =U17*Assumptions!$B$4 | X17: =IF(M17=0,"",ROUND(W17/M17*100,1)) | Y17: SOJAL COMERCIAL AGRICOLA | Z17: 0804401-51.2025.8.14.0039 | AB17: lrflideres.com.br | AC17: FERNANDO JOAO PREZZOTTO | AD17: Sócio-Administrador | AE17: (49) 3441-8200 | AH17: SC | AI17: CHAPECO | AJ17: Produção de sementes certificadas, exceto de forrageiras para pasto | AK17: DEMAIS | AL17: ATIVA | AM17: https://lrflideres.com.br/wp-content/plugins/download-attachments/includes/download.php?id=6879 | AN17: p2 r7 | AO17: p2: R$ 2.037.616,99 | AP17: AJ_LIST | AQ17: 2026-01-15 | AR17: OK | AS17: ROWS:p2r7 | AT17: c56751547323
A18: 17 | B18: NEW | D18: 0 | I18: FERTILIZANTES TOCANTINS S.A | J18: FERTILIZANTES TOCANTINS S.A | K18: 05571228 | L18: 05571228000155 | M18: 2016948.6 | N18: 1 | O18: UNKNOWN | R18: =IF(Q18="","",ROUND((TODAY()-Q18)/365.25,1)) | S18: =VLOOKUP(O18,Assumptions!$A$7:$E$10,2,FALSE) | T18: =MAX(0.5,VLOOKUP(O18,Assumptions!$A$7:$E$10,3,FALSE)+VLOOKUP(O18,Assumptions!$A$7:$E$10,4,FALSE)/2-IF(R18="",0,R18)) | U18: =M18*S18/(1+Assumptions!$B$3)^T18 | V18: =IF(M18=0,"",ROUND(U18/M18*100,1)) | W18: =U18*Assumptions!$B$4 | X18: =IF(M18=0,"",ROUND(W18/M18*100,1)) | Y18: SOJAL COMERCIAL AGRICOLA | Z18: 0804401-51.2025.8.14.0039 | AB18: lrflideres.com.br | AC18: DMITRY CHERNYKH | AD18: Presidente | AE18: (62) 3414-6300 | AH18: TO | AI18: PORTO NACIONAL | AJ18: Fabricação de adubos e fertilizantes, exceto organo-minerais | AK18: DEMAIS | AL18: ATIVA | AM18: https://lrflideres.com.br/wp-content/plugins/download-attachments/includes/download.php?id=6879 | AN18: p2 r1 | AO18: p2: R$ 2.016.948,56 | AP18: AJ_LIST | AQ18: 2026-01-15 | AR18: OK | AS18: ROWS:p2r1 | AT18: c56751547323
A19: 18 | B19: NEW | D19: 0 | I19: REICHENBACH EQUIPAMENTOS INDUSTRIA E COMERCIO LTDA | J19: REICHENBACH EQUIP IND.COM. LTDA | K19: 71799001 | L19: 71799001000196 | M19: 2002544.3 | N19: 1 | O19: UNKNOWN | R19: =IF(Q19="","",ROUND((TODAY()-Q19)/365.25,1)) | S19: =VLOOKUP(O19,Assumptions!$A$7:$E$10,2,FALSE) | T19: =MAX(0.5,VLOOKUP(O19,Assumptions!$A$7:$E$10,3,FALSE)+VLOOKUP(O19,Assumptions!$A$7:$E$10,4,FALSE)/2-IF(R19="",0,R19)) | U19: =M19*S19/(1+Assumptions!$B$3)^T19 | V19: =IF(M19=0,"",ROUND(U19/M19*100,1)) | W19: =U19*Assumptions!$B$4 | X19: =IF(M19=0,"",ROUND(W19/M19*100,1)) | Y19: Conduscabos Brasil Indústria Comércio de | Z19: 8005129-09.2023.8.05.0039 | AB19: assistjud.com.br | AC19: ALLAN WERNER REICHENBACH | AD19: Sócio-Administrador | AE19: (11) 4181-5054 | AH19: SP | AI19: CARAPICUIBA | AJ19: Fabricação de outras máquinas e equipamentos de uso geral não especificados anteriormente, peças e acessórios | AK19: DEMAIS | AL19: ATIVA | AM19: https://assistjud.com.br/wp-content/uploads/elementor/forms/65098c80a5824.pdf | AN19: p19 r6 | AO19: p19: R$ 2.002.544,34 | AP19: AJ_LIST | AQ19: 2023-09-18 | AR19: OK_NO_TOTALS | AS19: ROWS:p19r6 UNRECONCILED_SOURCE | AT19: a0ae32a59c29
A20: 19 | B20: NEW | D20: 0 | J20: URA AGRO FUNDO DE INVESTIMENTO EM DIREIT | K20: 25382606 | L20: 25382606000160 | M20: 1849551 | N20: 1 | O20: UNKNOWN | R20: =IF(Q20="","",ROUND((TODAY()-Q20)/365.25,1)) | S20: =VLOOKUP(O20,Assumptions!$A$7:$E$10,2,FALSE) | T20: =MAX(0.5,VLOOKUP(O20,Assumptions!$A$7:$E$10,3,FALSE)+VLOOKUP(O20,Assumptions!$A$7:$E$10,4,FALSE)/2-IF(R20="",0,R20)) | U20: =M20*S20/(1+Assumptions!$B$3)^T20 | V20: =IF(M20=0,"",ROUND(U20/M20*100,1)) | W20: =U20*Assumptions!$B$4 | X20: =IF(M20=0,"",ROUND(W20/M20*100,1)) | Y20: SOJAL COMERCIAL AGRICOLA | Z20: 0804401-51.2025.8.14.0039 | AB20: lrflideres.com.br | AM20: https://lrflideres.com.br/wp-content/plugins/download-attachments/includes/download.php?id=6879 | AN20: p2 r12 | AO20: p2: R$ 1.849.550,98 | AP20: AJ_LIST | AQ20: 2026-01-15 | AR20: OK | AS20: ROWS:p2r12 | AT20: c56751547323
A21: 20 | B21: NEW | D21: 0 | J21: RED FIDC | K21: 08632394 | L21: 08632394000102 | M21: 1841470 | N21: 2 | O21: UNKNOWN | R21: =IF(Q21="","",ROUND((TODAY()-Q21)/365.25,1)) | S21: =VLOOKUP(O21,Assumptions!$A$7:$E$10,2,FALSE) | T21: =MAX(0.5,VLOOKUP(O21,Assumptions!$A$7:$E$10,3,FALSE)+VLOOKUP(O21,Assumptions!$A$7:$E$10,4,FALSE)/2-IF(R21="",0,R21)) | U21: =M21*S21/(1+Assumptions!$B$3)^T21 | V21: =IF(M21=0,"",ROUND(U21/M21*100,1)) | W21: =U21*Assumptions!$B$4 | X21: =IF(M21=0,"",ROUND(W21/M21*100,1)) | Y21: Conduscabos Brasil Indústria Comércio de | Z21: 8005129-09.2023.8.05.0039 | AB21: assistjud.com.br | AM21: https://assistjud.com.br/wp-content/uploads/elementor/forms/65098c80a5824.pdf | AN21: p9 r10; p19 r5 | AO21: p9: R$ 1.565.337,07; p19: R$ 276.132,92 | AP21: AJ_LIST | AQ21: 2023-09-18 | AR21: OK_NO_TOTALS | AS21: ROWS:p9r10,p19r5 UNRECONCILED_SOURCE | AT21: a0ae32a59c29
A22: 21 | B22: NEW | D22: 0 | I22: DACARTO INDUSTRIA E COMERCIO DE PLASTICOS LTDA | J22: DACARTO BENVIC LTDA | K22: 62143847 | L22: 62143847000182, 62143847000263 | M22: 1624039.2 | N22: 2 | O22: UNKNOWN | R22: =IF(Q22="","",ROUND((TODAY()-Q22)/365.25,1)) | S22: =VLOOKUP(O22,Assumptions!$A$7:$E$10,2,FALSE) | T22: =MAX(0.5,VLOOKUP(O22,Assumptions!$A$7:$E$10,3,FALSE)+VLOOKUP(O22,Assumptions!$A$7:$E$10,4,FALSE)/2-IF(R22="",0,R22)) | U22: =M22*S22/(1+Assumptions!$B$3)^T22 | V22: =IF(M22=0,"",ROUND(U22/M22*100,1)) | W22: =U22*Assumptions!$B$4 | X22: =IF(M22=0,"",ROUND(W22/M22*100,1)) | Y22: Conduscabos Brasil Indústria Comércio de | Z22: 8005129-09.2023.8.05.0039 | AB22: assistjud.com.br | AC22: AMILTON DAL POZ DE ALMEIDA | AD22: Administrador | AE22: (11) 3658-9459 | AH22: SP | AI22: OSASCO | AJ22: Fabricação de artefatos de material plástico para outros usos não especificados anteriormente | AK22: DEMAIS | AL22: ATIVA | AM22: https://assistjud.com.br/wp-content/uploads/elementor/forms/65098c80a5824.pdf | AN22: p6 r12; p6 r13 | AO22: p6: R$ 534.318,75; p6: R$ 1.089.720,44 | AP22: AJ_LIST | AQ22: 2023-09-18 | AR22: OK_NO_TOTALS | AS22: ROWS:p6r12,p6r13 UNRECONCILED_SOURCE | AT22: a0ae32a59c29
A23: 22 | B23: NEW | D23: 0 | I23: KARINA PLASTICOS LTDA | J23: KARINA IND E COM DE PLASTICOS LTDA | K23: 51254159 | L23: 51254159000173 | M23: 1557723.7 | N23: 1 | O23: UNKNOWN | R23: =IF(Q23="","",ROUND((TODAY()-Q23)/365.25,1)) | S23: =VLOOKUP(O23,Assumptions!$A$7:$E$10,2,FALSE) | T23: =MAX(0.5,VLOOKUP(O23,Assumptions!$A$7:$E$10,3,FALSE)+VLOOKUP(O23,Assumptions!$A$7:$E$10,4,FALSE)/2-IF(R23="",0,R23)) | U23: =M23*S23/(1+Assumptions!$B$3)^T23 | V23: =IF(M23=0,"",ROUND(U23/M23*100,1)) | W23: =U23*Assumptions!$B$4 | X23: =IF(M23=0,"",ROUND(W23/M23*100,1)) | Y23: Conduscabos Brasil Indústria Comércio de | Z23: 8005129-09.2023.8.05.0039 | AB23: assistjud.com.br | AC23: DIANA GUEREKMEZIAN ATRA | AD23: Sócio-Administrador | AE23: (11) 2440-8477 | AF23: (11) 2463-2920 | AH23: SP | AI23: GUARULHOS | AJ23: Fabricação de resinas termoplásticas | AK23: DEMAIS | AL23: ATIVA | AM23: https://assistjud.com.br/wp-content/uploads/elementor/forms/65098c80a5824.pdf | AN23: p8 r5 | AO23: p8: R$ 1.557.723,71 | AP23: AJ_LIST | AQ23: 2023-09-18 | AR23: OK_NO_TOTALS | AS23: ROWS:p8r5 UNRECONCILED_SOURCE | AT23: a0ae32a59c29
A24: 23 | B24: NEW | D24: 0 | I24: CASA BUGRE GOIAS COMERCIO E REPRESENTACAO LTDA | J24: CASA BUGRE GOIAS COMERCIO E REPRESENTACA | K24: 20366728 | L24: 20366728000149 | M24: 1367818 | N24: 1 | O24: UNKNOWN | R24: =IF(Q24="","",ROUND((TODAY()-Q24)/365.25,1)) | S24: =VLOOKUP(O24,Assumptions!$A$7:$E$10,2,FALSE) | T24: =MAX(0.5,VLOOKUP(O24,Assumptions!$A$7:$E$10,3,FALSE)+VLOOKUP(O24,Assumptions!$A$7:$E$10,4,FALSE)/2-IF(R24="",0,R24)) | U24: =M24*S24/(1+Assumptions!$B$3)^T24 | V24: =IF(M24=0,"",ROUND(U24/M24*100,1)) | W24: =U24*Assumptions!$B$4 | X24: =IF(M24=0,"",ROUND(W24/M24*100,1)) | Y24: SOJAL COMERCIAL AGRICOLA | Z24: 0804401-51.2025.8.14.0039 | AB24: lrflideres.com.br | AC24: FLAVIO DE MEDEIROS MAIA | AD24: Sócio-Administrador | AE24: (61) 3770-0199 | AH24: GO | AI24: ANAPOLIS | AJ24: Comércio atacadista de sementes, flores, plantas e gramas | AK24: DEMAIS | AL24: ATIVA | AM24: https://lrflideres.com.br/wp-content/plugins/download-attachments/includes/download.php?id=6879 | AN24: p1 r9 | AO24: p1: R$ 1.367.817,98 | AP24: AJ_LIST | AQ24: 2026-01-15 | AR24: OK | AS24: ROWS:p1r9 | AT24: c56751547323
A25: 24 | B25: NEW | D25: 0 | I25: IBRAME INDUSTRIA BRASILEIRA DE METAIS S/A | J25: IBRAME INDUST RIA BRASILEIRA DE METAIS S | K25: 60846599 | L25: 60846599000534 | M25: 1359881.3 | N25: 2 | O25: UNKNOWN | R25: =IF(Q25="","",ROUND((TODAY()-Q25)/365.25,1)) | S25: =VLOOKUP(O25,Assumptions!$A$7:$E$10,2,FALSE) | T25: =MAX(0.5,VLOOKUP(O25,Assumptions!$A$7:$E$10,3,FALSE)+VLOOKUP(O25,Assumptions!$A$7:$E$10,4,FALSE)/2-IF(R25="",0,R25)) | U25: =M25*S25/(1+Assumptions!$B$3)^T25 | V25: =IF(M25=0,"",ROUND(U25/M25*100,1)) | W25: =U25*Assumptions!$B$4 | X25: =IF(M25=0,"",ROUND(W25/M25*100,1)) | Y25: Conduscabos Brasil Indústria Comércio de | Z25: 8005129-09.2023.8.05.0039 | AB25: assistjud.com.br | AC25: LUIZ OSVALDO PASTORE | AD25: Presidente | AE25: (47) 2101-0049 | AH25: ES | AI25: VITORIA | AJ25: Comércio atacadista de mercadorias em geral, sem predominância de alimentos ou de insumos agropecuários | AK25: DEMAIS | AL25: ATIVA | AM25: https://assistjud.com.br/wp-content/uploads/elementor/forms/65098c80a5824.pdf | AN25: p7 r11; p18 r3 | AO25: p7: R$ 815.928,78; p18: R$ 543.952,52 | AP25: AJ_LIST | AQ25: 2023-09-18 | AR25: OK_NO_TOTALS | AS25: ROWS:p7r11,p18r3 UNRECONCILED_SOURCE | AT25: a0ae32a59c29
A26: 25 | B26: NEW | D26: 0 | J26: CREDMEI SECURITIZADORA II SPE S.A | K26: 50202890 | L26: 50202890000192 | M26: 1135255.2 | N26: 1 | O26: UNKNOWN | R26: =IF(Q26="","",ROUND((TODAY()-Q26)/365.25,1)) | S26: =VLOOKUP(O26,Assumptions!$A$7:$E$10,2,FALSE) | T26: =MAX(0.5,VLOOKUP(O26,Assumptions!$A$7:$E$10,3,FALSE)+VLOOKUP(O26,Assumptions!$A$7:$E$10,4,FALSE)/2-IF(R26="",0,R26)) | U26: =M26*S26/(1+Assumptions!$B$3)^T26 | V26: =IF(M26=0,"",ROUND(U26/M26*100,1)) | W26: =U26*Assumptions!$B$4 | X26: =IF(M26=0,"",ROUND(W26/M26*100,1)) | Y26: ARRUDA & MELO COMERCIO E DISTRIBUICAO DE ALIMENTOS E BEBIDAS LTDA | Z26: 0008526-45.2025.8.17.2001 | AB26: diligence.adm.br | AM26: https://diligence.adm.br/wp-content/uploads/2025/06/Edital-1a-Lista-de-Credores.pdf | AN26: p5 r54 | AO26: p5: R$ 1.135.255,25 | AP26: DEBTOR_LIST | AQ26: 2025-06-10 | AR26: OK | AS26: ROWS:p5r54 | AT26: 1658892fa167
A27: 26 | B27: NEW | D27: 0 | I27: ARRUDA & MELO COMERCIO E DISTRIBUICAO DE ALIMENTOS E BEBIDAS LTDA - EM RECUPERACAO JUDICIAL | J27: ARRUDA & MELO COMERCIO E DISTRIBUICAO DE ALIMENTOS E BEBIDAS LTDA | K27: 21877243 | L27: 21877243000182 | M27: 1068252.9 | N27: 1 | O27: UNKNOWN | R27: =IF(Q27="","",ROUND((TODAY()-Q27)/365.25,1)) | S27: =VLOOKUP(O27,Assumptions!$A$7:$E$10,2,FALSE) | T27: =MAX(0.5,VLOOKUP(O27,Assumptions!$A$7:$E$10,3,FALSE)+VLOOKUP(O27,Assumptions!$A$7:$E$10,4,FALSE)/2-IF(R27="",0,R27)) | U27: =M27*S27/(1+Assumptions!$B$3)^T27 | V27: =IF(M27=0,"",ROUND(U27/M27*100,1)) | W27: =U27*Assumptions!$B$4 | X27: =IF(M27=0,"",ROUND(W27/M27*100,1)) | Y27: ARRUDA & MELO COMERCIO E DISTRIBUICAO DE ALIMENTOS E BEBIDAS LTDA | Z27: 0008526-45.2025.8.17.2001 | AB27: diligence.adm.br | AC27: MAURO CESAR DE MELO ARRUDA | AD27: Sócio-Administrador | AE27: (81) 3314-2120 | AH27: PE | AI27: RECIFE | AJ27: Comércio atacadista de produtos alimentícios em geral | AK27: DEMAIS | AL27: ATIVA | AM27: https://diligence.adm.br/wp-content/uploads/2025/06/Edital-1a-Lista-de-Credores.pdf | AN27: p5 r48 | AO27: p5: R$ 1.068.252,89 | AP27: DEBTOR_LIST | AQ27: 2025-06-10 | AR27: OK | AS27: ROWS:p5r48 | AT27: 1658892fa167
A28: 27 | B28: NEW | D28: 0 | I28: MINERAX - MINERACAO XAMBIOA LTDA | J28: MINERACAO XAMBIOA LTDA | K28: 08886407 | L28: 08886407000170 | M28: 962991.9 | N28: 1 | O28: UNKNOWN | R28: =IF(Q28="","",ROUND((TODAY()-Q28)/365.25,1)) | S28: =VLOOKUP(O28,Assumptions!$A$7:$E$10,2,FALSE) | T28: =MAX(0.5,VLOOKUP(O28,Assumptions!$A$7:$E$10,3,FALSE)+VLOOKUP(O28,Assumptions!$A$7:$E$10,4,FALSE)/2-IF(R28="",0,R28)) | U28: =M28*S28/(1+Assumptions!$B$3)^T28 | V28: =IF(M28=0,"",ROUND(U28/M28*100,1)) | W28: =U28*Assumptions!$B$4 | X28: =IF(M28=0,"",ROUND(W28/M28*100,1)) | Y28: SOJAL COMERCIAL AGRICOLA | Z28: 0804401-51.2025.8.14.0039 | AB28: lrflideres.com.br | AC28: FRANCISCO MIGUEL HENDGES | AD28: Administrador | AE28: (63) 3415-8500 | AH28: TO | AI28: XAMBIOA | AJ28: Extração de calcário e dolomita e beneficiamento associado | AK28: DEMAIS | AL28: ATIVA | AM28: https://lrflideres.com.br/wp-content/plugins/download-attachments/includes/download.php?id=6879 | AN28: p2 r4 | AO28: p2: R$ 962.991,90 | AP28: AJ_LIST | AQ28: 2026-01-15 | AR28: OK | AS28: ROWS:p2r4 | AT28: c56751547323
A29: 28 | B29: NEW | D29: 0 | J29: DANIELE MÚLTIPLO FUNDO DE INVESTIMENTO EM DIREITOS CREDITÓRIOS – NÃO PADRONIZADOS | K29: 09414255 | L29: 09414255000175 | M29: 926408.5 | N29: 1 | O29: UNKNOWN | R29: =IF(Q29="","",ROUND((TODAY()-Q29)/365.25,1)) | S29: =VLOOKUP(O29,Assumptions!$A$7:$E$10,2,FALSE) | T29: =MAX(0.5,VLOOKUP(O29,Assumptions!$A$7:$E$10,3,FALSE)+VLOOKUP(O29,Assumptions!$A$7:$E$10,4,FALSE)/2-IF(R29="",0,R29)) | U29: =M29*S29/(1+Assumptions!$B$3)^T29 | V29: =IF(M29=0,"",ROUND(U29/M29*100,1)) | W29: =U29*Assumptions!$B$4 | X29: =IF(M29=0,"",ROUND(W29/M29*100,1)) | Y29: Conduscabos Brasil Indústria Comércio de | Z29: 8005129-09.2023.8.05.0039 | AB29: assistjud.com.br | AM29: https://assistjud.com.br/wp-content/uploads/elementor/forms/65098c80a5824.pdf | AN29: p7 r1 | AO29: p7: R$ 926.408,50 | AP29: AJ_LIST | AQ29: 2023-09-18 | AR29: OK_NO_TOTALS | AS29: ROWS:p7r1 UNRECONCILED_SOURCE | AT29: a0ae32a59c29
A30: 29 | B30: NEW | D30: 0 | I30: RG COPPER INDUSTRIA E COMERCIO DE CONDUTORES ELETRICOS LTDA | J30: RG COPPER INDUSTRIA E COMERCIO DE CONDUT | K30: 21044682 | L30: 21044682000104 | M30: 864147.01 | N30: 1 | O30: UNKNOWN | R30: =IF(Q30="","",ROUND((TODAY()-Q30)/365.25,1)) | S30: =VLOOKUP(O30,Assumptions!$A$7:$E$10,2,FALSE) | T30: =MAX(0.5,VLOOKUP(O30,Assumptions!$A$7:$E$10,3,FALSE)+VLOOKUP(O30,Assumptions!$A$7:$E$10,4,FALSE)/2-IF(R30="",0,R30)) | U30: =M30*S30/(1+Assumptions!$B$3)^T30 | V30: =IF(M30=0,"",ROUND(U30/M30*100,1)) | W30: =U30*Assumptions!$B$4 | X30: =IF(M30=0,"",ROUND(W30/M30*100,1)) | Y30: Conduscabos Brasil Indústria Comércio de | Z30: 8005129-09.2023.8.05.0039 | AB30: assistjud.com.br | AC30: GERSON GOMES DA SILVA | AD30: Sócio-Administrador | AE30: (11) 2507-5535 | AH30: SP | AI30: JARDINOPOLIS | AJ30: Fabricação de fios, cabos e condutores elétricos isolados | AK30: DEMAIS | AL30: ATIVA | AM30: https://assistjud.com.br/wp-content/uploads/elementor/forms/65098c80a5824.pdf | AN30: p9 r14 | AO30: p9: R$ 864.147,01 | AP30: AJ_LIST | AQ30: 2023-09-18 | AR30: OK_NO_TOTALS | AS30: ROWS:p9r14 UNRECONCILED_SOURCE | AT30: a0ae32a59c29
A31: 30 | B31: NEW | D31: 0 | J31: ASIA FIDC | K31: 09172117 | L31: 09172117000127 | M31: 758759.36 | N31: 1 | O31: UNKNOWN | R31: =IF(Q31="","",ROUND((TODAY()-Q31)/365.25,1)) | S31: =VLOOKUP(O31,Assumptions!$A$7:$E$10,2,FALSE) | T31: =MAX(0.5,VLOOKUP(O31,Assumptions!$A$7:$E$10,3,FALSE)+VLOOKUP(O31,Assumptions!$A$7:$E$10,4,FALSE)/2-IF(R31="",0,R31)) | U31: =M31*S31/(1+Assumptions!$B$3)^T31 | V31: =IF(M31=0,"",ROUND(U31/M31*100,1)) | W31: =U31*Assumptions!$B$4 | X31: =IF(M31=0,"",ROUND(W31/M31*100,1)) | Y31: Conduscabos Brasil Indústria Comércio de | Z31: 8005129-09.2023.8.05.0039 | AB31: assistjud.com.br | AM31: https://assistjud.com.br/wp-content/uploads/elementor/forms/65098c80a5824.pdf | AN31: p5 r5 | AO31: p5: R$ 758.759,36 | AP31: AJ_LIST | AQ31: 2023-09-18 | AR31: OK_NO_TOTALS | AS31: ROWS:p5r5 UNRECONCILED_SOURCE VALUE_COL:Valor_Do_Crédito_2º_Edital_De_Credores | AT31: a0ae32a59c29
A32: 31 | B32: NEW | D32: 0 | I32: MAGNUM DISTRIBUIDORA DE PNEUS S/A | J32: MAGNUM DISTRIBUIDORA DE PNEUS S/A | K32: 19403406 | L32: 19403406001549 | M32: 644893.08 | N32: 1 | O32: UNKNOWN | R32: =IF(Q32="","",ROUND((TODAY()-Q32)/365.25,1)) | S32: =VLOOKUP(O32,Assumptions!$A$7:$E$10,2,FALSE) | T32: =MAX(0.5,VLOOKUP(O32,Assumptions!$A$7:$E$10,3,FALSE)+VLOOKUP(O32,Assumptions!$A$7:$E$10,4,FALSE)/2-IF(R32="",0,R32)) | U32: =M32*S32/(1+Assumptions!$B$3)^T32 | V32: =IF(M32=0,"",ROUND(U32/M32*100,1)) | W32: =U32*Assumptions!$B$4 | X32: =IF(M32=0,"",ROUND(W32/M32*100,1)) | Y32: DR. ALYSSON CORREIA MACIEL – OAB/PB 11.841, DRA. CAROL DE ALMEIDA LIMA | Z32: 0804204-35.2022.8.15.0731 | AB32: lrflideres.com.br | AC32: ANTONIO CARLOS CAVALCANTI DE ARAUJO FILHO | AD32: Presidente | AE32: (81) 3797-6245 | AF32: (81) 3797-6246 | AH32: PE | AI32: JABOATAO DOS GUARARAPES | AJ32: Comércio por atacado de pneumáticos e câmaras-de-ar | AK32: DEMAIS | AL32: ATIVA | AM32: https://lrflideres.com.br/wp-content/uploads/2022/08/4.-EDITAL-2a-LISTA-DE-CREDORES.pdf | AN32: p1 r21 | AO32: p1: R$ 644.893,08 | AP32: AJ_LIST | AQ32: 2023-12-04 | AR32: OK | AS32: ROWS:p1r21 | AT32: 1355f93a13cd
A33: 32 | B33: NEW | D33: 0 | I33: SOTIN SOLUCOES TECNICAS, INDUSTRIA E COMERCIO LTDA | J33: SOTIN SOLUÇÕES TECNICAS IND E COMERCIO LTDA | K33: 38733545 | L33: 38733545000180 | M33: 611207.1 | N33: 1 | O33: UNKNOWN | R33: =IF(Q33="","",ROUND((TODAY()-Q33)/365.25,1)) | S33: =VLOOKUP(O33,Assumptions!$A$7:$E$10,2,FALSE) | T33: =MAX(0.5,VLOOKUP(O33,Assumptions!$A$7:$E$10,3,FALSE)+VLOOKUP(O33,Assumptions!$A$7:$E$10,4,FALSE)/2-IF(R33="",0,R33)) | U33: =M33*S33/(1+Assumptions!$B$3)^T33 | V33: =IF(M33=0,"",ROUND(U33/M33*100,1)) | W33: =U33*Assumptions!$B$4 | X33: =IF(M33=0,"",ROUND(W33/M33*100,1)) | Y33: DR. ALYSSON CORREIA MACIEL – OAB/PB 11.841, DRA. CAROL DE ALMEIDA LIMA | Z33: 0804204-35.2022.8.15.0731 | AB33: lrflideres.com.br | AC33: SPENCER WILLIAM STELLA JUNIOR | AD33: Sócio-Administrador | AE33: (11) 4496-8888 | AH33: SP | AI33: JUNDIAI | AJ33: Fabricação de outros produtos de metal não especificados anteriormente | AK33: DEMAIS | AL33: ATIVA | AM33: https://lrflideres.com.br/wp-content/uploads/2022/08/4.-EDITAL-2a-LISTA-DE-CREDORES.pdf | AN33: p2 r9 | AO33: p2: R$ 611.207,10 | AP33: AJ_LIST | AQ33: 2023-12-04 | AR33: OK | AS33: ROWS:p2r9 | AT33: 1355f93a13cd
A34: 33 | B34: NEW | D34: 0 | I34: COBREMACK INDUSTRIA DE CONDUTORES ELETRICOS LIMITADA EM RECUPERACAO JUDICIAL EM RECUPERACAO JUDICIAL | J34: COBREMACK INDUSTRIA DE CONDUTORES ELETRI | K34: 11065453 | L34: 11065453000201 | M34: 611009.25 | N34: 2 | O34: UNKNOWN | R34: =IF(Q34="","",ROUND((TODAY()-Q34)/365.25,1)) | S34: =VLOOKUP(O34,Assumptions!$A$7:$E$10,2,FALSE) | T34: =MAX(0.5,VLOOKUP(O34,Assumptions!$A$7:$E$10,3,FALSE)+VLOOKUP(O34,Assumptions!$A$7:$E$10,4,FALSE)/2-IF(R34="",0,R34)) | U34: =M34*S34/(1+Assumptions!$B$3)^T34 | V34: =IF(M34=0,"",ROUND(U34/M34*100,1)) | W34: =U34*Assumptions!$B$4 | X34: =IF(M34=0,"",ROUND(W34/M34*100,1)) | Y34: Conduscabos Brasil Indústria Comércio de | Z34: 8005129-09.2023.8.05.0039 | AB34: assistjud.com.br | AC34: JOSE CARLOS MENDES MATUIAMA | AD34: Sócio-Administrador | AE34: (11) 4156-5531 | AH34: BA | AI34: LAURO DE FREITAS | AJ34: Fabricação de fios, cabos e condutores elétricos isolados | AK34: DEMAIS | AL34: ATIVA | AM34: https://assistjud.com.br/wp-content/uploads/elementor/forms/65098c80a5824.pdf | AN34: p6 r8; p17 r10 | AO34: p6: R$ 420.273,65; p17: R$ 190.735,60 | AP34: AJ_LIST | AQ34: 2023-09-18 | AR34: OK_NO_TOTALS | AS34: ROWS:p6r8,p17r10 UNRECONCILED_SOURCE VALUE_COL:Valor_Do_Crédito_2º_Edital_De_Credores | AT34: a0ae32a59c29
A35: 34 | B35: NEW | D35: 0 | I35: BIOBASE INDUSTRIA E COMERCIO LTDA | J35: BIOBASE INDUSTRIA E COMERCIO LTDA | K35: 05216859 | L35: 05216859000156 | M35: 569654.02 | N35: 1 | O35: UNKNOWN | R35: =IF(Q35="","",ROUND((TODAY()-Q35)/365.25,1)) | S35: =VLOOKUP(O35,Assumptions!$A$7:$E$10,2,FALSE) | T35: =MAX(0.5,VLOOKUP(O35,Assumptions!$A$7:$E$10,3,FALSE)+VLOOKUP(O35,Assumptions!$A$7:$E$10,4,FALSE)/2-IF(R35="",0,R35)) | U35: =M35*S35/(1+Assumptions!$B$3)^T35 | V35: =IF(M35=0,"",ROUND(U35/M35*100,1)) | W35: =U35*Assumptions!$B$4 | X35: =IF(M35=0,"",ROUND(W35/M35*100,1)) | Z35: (not found in document) | AB35: bernardobicalho.com.br | AC35: RICHARD REIS FARIAS | AD35: Sócio-Administrador | AE35: (35) 3427-7000 | AF35: (35) 3427-7012 | AH35: MG | AI35: POUSO ALEGRE | AJ35: Fabricação de materiais para medicina e odontologia | AK35: DEMAIS | AL35: ATIVA | AM35: http://bernardobicalho.com.br/login/app/documents/Rela%C3%A7%C3%A3o%20de%20Credores/6.%20RVC-%20Nutricium%20-%20simplificada.pdf | AN35: p3 r7 | AO35: p3: R$ 569.654,02 | AP35: AJ_LIST | AR35: OK | AS35: CASE_NUMBER_MISSING ROWS:p3r7 | AT35: 6a92d74da333
A36: 35 | B36: NEW | D36: 0 | J36: CREDIT PARTNERS FUNDO DE INVESTIMENTO EM DIREITOS CREDITÓRIOS NÃO PADRONIZADOS | K36: 32274874 | L36: 32274874000123 | M36: 547127.35 | N36: 2 | O36: UNKNOWN | R36: =IF(Q36="","",ROUND((TODAY()-Q36)/365.25,1)) | S36: =VLOOKUP(O36,Assumptions!$A$7:$E$10,2,FALSE) | T36: =MAX(0.5,VLOOKUP(O36,Assumptions!$A$7:$E$10,3,FALSE)+VLOOKUP(O36,Assumptions!$A$7:$E$10,4,FALSE)/2-IF(R36="",0,R36)) | U36: =M36*S36/(1+Assumptions!$B$3)^T36 | V36: =IF(M36=0,"",ROUND(U36/M36*100,1)) | W36: =U36*Assumptions!$B$4 | X36: =IF(M36=0,"",ROUND(W36/M36*100,1)) | Y36: Conduscabos Brasil Indústria Comércio de | Z36: 8005129-09.2023.8.05.0039 | AB36: assistjud.com.br | AM36: https://assistjud.com.br/wp-content/uploads/elementor/forms/65098c80a5824.pdf | AN36: p6 r11; p17 r11 | AO36: p6: R$ 333.437,35; p17: R$ 213.690,00 | AP36: AJ_LIST | AQ36: 2023-09-18 | AR36: OK_NO_TOTALS | AS36: ROWS:p6r11,p17r11 UNRECONCILED_SOURCE VALUE_COL:Valor_Do_Crédito_2º_Edital_De_Credores | AT36: a0ae32a59c29
A37: 36 | B37: NEW | D37: 0 | I37: CALMAP INDUSTRIA DE CALCARIO LTDA | J37: CALMAP INDUSTRIA DE CALCARIO LTDA | K37: 10962529 | L37: 10962529000140 | M37: 526042.93 | N37: 1 | O37: UNKNOWN | R37: =IF(Q37="","",ROUND((TODAY()-Q37)/365.25,1)) | S37: =VLOOKUP(O37,Assumptions!$A$7:$E$10,2,FALSE) | T37: =MAX(0.5,VLOOKUP(O37,Assumptions!$A$7:$E$10,3,FALSE)+VLOOKUP(O37,Assumptions!$A$7:$E$10,4,FALSE)/2-IF(R37="",0,R37)) | U37: =M37*S37/(1+Assumptions!$B$3)^T37 | V37: =IF(M37=0,"",ROUND(U37/M37*100,1)) | W37: =U37*Assumptions!$B$4 | X37: =IF(M37=0,"",ROUND(W37/M37*100,1)) | Y37: SOJAL COMERCIAL AGRICOLA | Z37: 0804401-51.2025.8.14.0039 | AB37: lrflideres.com.br | AC37: ANTONIO HOLANDA DE OLIVEIRA NETO | AD37: Sócio-Administrador | AE37: (85) 3082-0505 | AH37: PA | AI37: SAO GERALDO DO ARAGUAIA | AJ37: Extração de minerais para fabricação de adubos, fertilizantes e outros produtos químicos | AK37: DEMAIS | AL37: ATIVA | AM37: https://lrflideres.com.br/wp-content/plugins/download-attachments/includes/download.php?id=6879 | AN37: p1 r8 | AO37: p1: R$ 526.042,93 | AP37: AJ_LIST | AQ37: 2026-01-15 | AR37: OK | AS37: ROWS:p1r8 | AT37: c56751547323
A38: 37 | B38: NEW | D38: 0 | I38: COBB-VANTRESS BRASIL LTDA | J38: COBB - VANTRESS BRASIL LTDA | K38: 00466591 | L38: 00466591000197 | M38: 497078.85 | N38: 1 | O38: UNKNOWN | R38: =IF(Q38="","",ROUND((TODAY()-Q38)/365.25,1)) | S38: =VLOOKUP(O38,Assumptions!$A$7:$E$10,2,FALSE) | T38: =MAX(0.5,VLOOKUP(O38,Assumptions!$A$7:$E$10,3,FALSE)+VLOOKUP(O38,Assumptions!$A$7:$E$10,4,FALSE)/2-IF(R38="",0,R38)) | U38: =M38*S38/(1+Assumptions!$B$3)^T38 | V38: =IF(M38=0,"",ROUND(U38/M38*100,1)) | W38: =U38*Assumptions!$B$4 | X38: =IF(M38=0,"",ROUND(W38/M38*100,1)) | Y38: AGROPECUÁRIA SERROTE REDONDO | Z38: 0000206-69.2013.8.17.1340 | AB38: lrflideres.com.br | AC38: RODRIGO FERREIRA SIQUEIRA DE MELLO | AD38: Administrador | AH38: SP | AI38: GUAPIACU | AJ38: Produção de pintos de um dia | AK38: DEMAIS | AL38: ATIVA | AM38: https://lrflideres.com.br/wp-content/plugins/download-attachments/includes/download.php?id=5001 | AN38: p1 r23 | AO38: p1: R$ 497.078,85 | AP38: UNKNOWN | AR38: OK | AS38: ALT_VALUE:497.078,85 ROWS:p1r23 VALUE_COL:Valor_Atualizado | AT38: 7c0ce2830d0d
A39: 38 | B39: NEW | D39: 0 | I39: CROPFERT INDUSTRIA DE FERTILIZANTES E AGROQUIMICOS LTDA | J39: CROPFERT INDUSTRIA DE FERTILIZANTES E AG | K39: 18373437 | L39: 18373437000136 | M39: 467392 | N39: 1 | O39: UNKNOWN | R39: =IF(Q39="","",ROUND((TODAY()-Q39)/365.25,1)) | S39: =VLOOKUP(O39,Assumptions!$A$7:$E$10,2,FALSE) | T39: =MAX(0.5,VLOOKUP(O39,Assumptions!$A$7:$E$10,3,FALSE)+VLOOKUP(O39,Assumptions!$A$7:$E$10,4,FALSE)/2-IF(R39="",0,R39)) | U39: =M39*S39/(1+Assumptions!$B$3)^T39 | V39: =IF(M39=0,"",ROUND(U39/M39*100,1)) | W39: =U39*Assumptions!$B$4 | X39: =IF(M39=0,"",ROUND(W39/M39*100,1)) | Y39: SOJAL COMERCIAL AGRICOLA | Z39: 0804401-51.2025.8.14.0039 | AB39: lrflideres.com.br | AC39: ANDERSON JOSE FAUSTINO | AD39: Administrador | AE39: (43) 3162-2700 | AH39: PR | AI39: JANDAIA DO SUL | AJ39: Fabricação de defensivos agrícolas | AK39: DEMAIS | AL39: ATIVA | AM39: https://lrflideres.com.br/wp-content/plugins/download-attachments/includes/download.php?id=6879 | AN39: p1 r12 | AO39: p1: R$ 467.392,00 | AP39: AJ_LIST | AQ39: 2026-01-15 | AR39: OK | AS39: ROWS:p1r12 | AT39: c56751547323
A40: 39 | B40: NEW | D40: 0 | I40: COMARY INDUSTRIA DE BEBIDAS LTDA | J40: COMARY INDUSTRIA DE BEBIDAS LTDA | K40: 29588019 | L40: 29588019001316 | M40: 407241.98 | N40: 1 | O40: UNKNOWN | R40: =IF(Q40="","",ROUND((TODAY()-Q40)/365.25,1)) | S40: =VLOOKUP(O40,Assumptions!$A$7:$E$10,2,FALSE) | T40: =MAX(0.5,VLOOKUP(O40,Assumptions!$A$7:$E$10,3,FALSE)+VLOOKUP(O40,Assumptions!$A$7:$E$10,4,FALSE)/2-IF(R40="",0,R40)) | U40: =M40*S40/(1+Assumptions!$B$3)^T40 | V40: =IF(M40=0,"",ROUND(U40/M40*100,1)) | W40: =U40*Assumptions!$B$4 | X40: =IF(M40=0,"",ROUND(W40/M40*100,1)) | Y40: ARRUDA & MELO COMERCIO E DISTRIBUICAO DE ALIMENTOS E BEBIDAS LTDA | Z40: 0008526-45.2025.8.17.2001 | AB40: diligence.adm.br | AC40: MOZART RIBEIRO RODRIGUES | AD40: Sócio-Administrador | AE40: (21) 2152-4014 | AF40: (21) 2152-4000 | AH40: RJ | AI40: TERESOPOLIS | AJ40: Fabricação de vinho | AK40: DEMAIS | AL40: ATIVA | AM40: https://diligence.adm.br/wp-content/uploads/2025/06/Edital-1a-Lista-de-Credores.pdf | AN40: p5 r69 | AO40: p5: R$ 407.241,98 | AP40: DEBTOR_LIST | AQ40: 2025-06-10 | AR40: OK | AS40: ROWS:p5r69 | AT40: 1658892fa167
A41: 40 | B41: NEW | D41: 0 | I41: EPE - PRODUTOS AGROPECUARIOS LTDA | J41: EPE - PRODUTOS AGROPECUARIOS LTDA | K41: 05860157 | L41: 05860157000100 | M41: 399413.94 | N41: 1 | O41: UNKNOWN | R41: =IF(Q41="","",ROUND((TODAY()-Q41)/365.25,1)) | S41: =VLOOKUP(O41,Assumptions!$A$7:$E$10,2,FALSE) | T41: =MAX(0.5,VLOOKUP(O41,Assumptions!$A$7:$E$10,3,FALSE)+VLOOKUP(O41,Assumptions!$A$7:$E$10,4,FALSE)/2-IF(R41="",0,R41)) | U41: =M41*S41/(1+Assumptions!$B$3)^T41 | V41: =IF(M41=0,"",ROUND(U41/M41*100,1)) | W41: =U41*Assumptions!$B$4 | X41: =IF(M41=0,"",ROUND(W41/M41*100,1)) | Y41: AGROPECUÁRIA SERROTE REDONDO | Z41: 0000206-69.2013.8.17.1340 | AB41: lrflideres.com.br | AC41: EDIVAL VERAS DE BARROS CAMPELO FILHO | AD41: Sócio-Administrador | AE41: (81) 3465-3775 | AF41: (81) 8865-3037 | AH41: PE | AI41: GARANHUNS | AJ41: Comércio atacadista de mercadorias em geral, com predominância de insumos agropecuários | AK41: DEMAIS | AL41: ATIVA | AM41: https://lrflideres.com.br/wp-content/plugins/download-attachments/includes/download.php?id=5001 | AN41: p2 r4 | AO41: p2: R$ 399.413,94 | AP41: UNKNOWN | AR41: OK | AS41: ALT_VALUE:399.413,94 ROWS:p2r4 | AT41: 7c0ce2830d0d
A42: 41 | B42: NEW | D42: 0 | I42: L D NUNES | J42: L. D. NUNES LTDA | K42: 02291660 | L42: 02291660000102 | M42: 390081 | N42: 1 | O42: UNKNOWN | R42: =IF(Q42="","",ROUND((TODAY()-Q42)/365.25,1)) | S42: =VLOOKUP(O42,Assumptions!$A$7:$E$10,2,FALSE) | T42: =MAX(0.5,VLOOKUP(O42,Assumptions!$A$7:$E$10,3,FALSE)+VLOOKUP(O42,Assumptions!$A$7:$E$10,4,FALSE)/2-IF(R42="",0,R42)) | U42: =M42*S42/(1+Assumptions!$B$3)^T42 | V42: =IF(M42=0,"",ROUND(U42/M42*100,1)) | W42: =U42*Assumptions!$B$4 | X42: =IF(M42=0,"",ROUND(W42/M42*100,1)) | Y42: AGROPECUÁRIA SERROTE REDONDO | Z42: 0000206-69.2013.8.17.1340 | AB42: lrflideres.com.br | AH42: RN | AI42: MACAIBA | AJ42: Preparação de subprodutos do abate | AK42: EMPRESA DE PEQUENO PORTE | AL42: ATIVA | AM42: https://lrflideres.com.br/wp-content/plugins/download-attachments/includes/download.php?id=5001 | AN42: p2 r36 | AO42: p2: R$ 390.081,00 | AP42: UNKNOWN | AR42: OK | AS42: ALT_VALUE:390.081,00 ROWS:p2r36 | AT42: 7c0ce2830d0d
A43: 42 | B43: NEW | D43: 0 | J43: POLUX SECURITIZADORA DE RECEBÍVEIS COMERCIAIS S.A. | K43: 36238945 | L43: 36238945000193 | M43: 361043.83 | N43: 1 | O43: UNKNOWN | R43: =IF(Q43="","",ROUND((TODAY()-Q43)/365.25,1)) | S43: =VLOOKUP(O43,Assumptions!$A$7:$E$10,2,FALSE) | T43: =MAX(0.5,VLOOKUP(O43,Assumptions!$A$7:$E$10,3,FALSE)+VLOOKUP(O43,Assumptions!$A$7:$E$10,4,FALSE)/2-IF(R43="",0,R43)) | U43: =M43*S43/(1+Assumptions!$B$3)^T43 | V43: =IF(M43=0,"",ROUND(U43/M43*100,1)) | W43: =U43*Assumptions!$B$4 | X43: =IF(M43=0,"",ROUND(W43/M43*100,1)) | Y43: Conduscabos Brasil Indústria Comércio de | Z43: 8005129-09.2023.8.05.0039 | AB43: assistjud.com.br | AM43: https://assistjud.com.br/wp-content/uploads/elementor/forms/65098c80a5824.pdf | AN43: p9 r5 | AO43: p9: R$ 361.043,83 | AP43: AJ_LIST | AQ43: 2023-09-18 | AR43: OK_NO_TOTALS | AS43: ROWS:p9r5 UNRECONCILED_SOURCE | AT43: a0ae32a59c29
A44: 43 | B44: NEW | D44: 0 | I44: POLYEXCEL INDUSTRIA E COMERCIO DE COMPOSTOS POLIMERICOS LTDA | J44: POLYEXCEL IND E COM CP POLIMERICOS LTDA | K44: 14492564 | L44: 14492564000101 | M44: 341250 | N44: 1 | O44: UNKNOWN | R44: =IF(Q44="","",ROUND((TODAY()-Q44)/365.25,1)) | S44: =VLOOKUP(O44,Assumptions!$A$7:$E$10,2,FALSE) | T44: =MAX(0.5,VLOOKUP(O44,Assumptions!$A$7:$E$10,3,FALSE)+VLOOKUP(O44,Assumptions!$A$7:$E$10,4,FALSE)/2-IF(R44="",0,R44)) | U44: =M44*S44/(1+Assumptions!$B$3)^T44 | V44: =IF(M44=0,"",ROUND(U44/M44*100,1)) | W44: =U44*Assumptions!$B$4 | X44: =IF(M44=0,"",ROUND(W44/M44*100,1)) | Y44: Conduscabos Brasil Indústria Comércio de | Z44: 8005129-09.2023.8.05.0039 | AB44: assistjud.com.br | AC44: RODRIGO NACHLE BOREGGIO | AD44: Sócio-Administrador | AE44: (11) 4161-6775 | AH44: SP | AI44: BARUERI | AJ44: Fabricação de artefatos de material plástico para usos industriais | AK44: DEMAIS | AL44: ATIVA | AM44: https://assistjud.com.br/wp-content/uploads/elementor/forms/65098c80a5824.pdf | AN44: p9 r6 | AO44: p9: R$ 341.250,00 | AP44: AJ_LIST | AQ44: 2023-09-18 | AR44: OK_NO_TOTALS | AS44: ROWS:p9r6 UNRECONCILED_SOURCE | AT44: a0ae32a59c29
A45: 44 | B45: NEW | D45: 0 | I45: IRON COMEX LTDA | J45: IRON COMEX LTDA - Este documento foi gerado pelo usuário 031.***.***-17 em 10/06/2025 18:21:34 | K45: 43464332 | L45: 43464332000130, 43464332000210 | M45: 334279.01 | N45: 2 | O45: UNKNOWN | R45: =IF(Q45="","",ROUND((TODAY()-Q45)/365.25,1)) | S45: =VLOOKUP(O45,Assumptions!$A$7:$E$10,2,FALSE) | T45: =MAX(0.5,VLOOKUP(O45,Assumptions!$A$7:$E$10,3,FALSE)+VLOOKUP(O45,Assumptions!$A$7:$E$10,4,FALSE)/2-IF(R45="",0,R45)) | U45: =M45*S45/(1+Assumptions!$B$3)^T45 | V45: =IF(M45=0,"",ROUND(U45/M45*100,1)) | W45: =U45*Assumptions!$B$4 | X45: =IF(M45=0,"",ROUND(W45/M45*100,1)) | Y45: ARRUDA & MELO COMERCIO E DISTRIBUICAO DE ALIMENTOS E BEBIDAS LTDA | Z45: 0008526-45.2025.8.17.2001 | AB45: diligence.adm.br | AC45: SARI MARIANA COSTA GASPAR CORTE REAL | AD45: Sócio-Administrador | AE45: (81) 9707-8484 | AH45: PE | AI45: RECIFE | AJ45: Comércio atacadista de mercadorias em geral, sem predominância de alimentos ou de insumos agropecuários | AK45: DEMAIS | AL45: ATIVA | AM45: https://diligence.adm.br/wp-content/uploads/2025/06/Edital-1a-Lista-de-Credores.pdf | AN45: p5 r78; p5 r79 | AO45: p5: R$ 184.223,97; p5: R$ 150.055,04 | AP45: DEBTOR_LIST | AQ45: 2025-06-10 | AR45: OK | AS45: LONG_CHUNK ROWS:p5r78,p5r79 | AT45: 1658892fa167
A46: 45 | B46: NEW | D46: 0 | J46: COOPERATIVA DE CRÉDITO RURAL DO ALTO PAJEU LTDA. | K46: 03732359 | L46: 03732359000141 | M46: 334273.09 | N46: 1 | O46: UNKNOWN | R46: =IF(Q46="","",ROUND((TODAY()-Q46)/365.25,1)) | S46: =VLOOKUP(O46,Assumptions!$A$7:$E$10,2,FALSE) | T46: =MAX(0.5,VLOOKUP(O46,Assumptions!$A$7:$E$10,3,FALSE)+VLOOKUP(O46,Assumptions!$A$7:$E$10,4,FALSE)/2-IF(R46="",0,R46)) | U46: =M46*S46/(1+Assumptions!$B$3)^T46 | V46: =IF(M46=0,"",ROUND(U46/M46*100,1)) | W46: =U46*Assumptions!$B$4 | X46: =IF(M46=0,"",ROUND(W46/M46*100,1)) | Y46: AGROPECUÁRIA SERROTE REDONDO | Z46: 0000206-69.2013.8.17.1340 | AB46: lrflideres.com.br | AM46: https://lrflideres.com.br/wp-content/plugins/download-attachments/includes/download.php?id=5001 | AN46: p1 r29 | AO46: p1: R$ 334.273,09 | AP46: UNKNOWN | AR46: OK | AS46: ALT_VALUE:334.273,09 ROWS:p1r29 VALUE_COL:Valor_Atualizado | AT46: 7c0ce2830d0d
A47: 46 | B47: NEW | D47: 0 | I47: FLUMINENSE FOOTBALL CLUB | J47: FLUMINENSE FOOTBA LL CLUB | K47: 33647553 | L47: 33647553000190 | M47: 309484.78 | N47: 1 | O47: UNKNOWN | R47: =IF(Q47="","",ROUND((TODAY()-Q47)/365.25,1)) | S47: =VLOOKUP(O47,Assumptions!$A$7:$E$10,2,FALSE) | T47: =MAX(0.5,VLOOKUP(O47,Assumptions!$A$7:$E$10,3,FALSE)+VLOOKUP(O47,Assumptions!$A$7:$E$10,4,FALSE)/2-IF(R47="",0,R47)) | U47: =M47*S47/(1+Assumptions!$B$3)^T47 | V47: =IF(M47=0,"",ROUND(U47/M47*100,1)) | W47: =U47*Assumptions!$B$4 | X47: =IF(M47=0,"",ROUND(W47/M47*100,1)) | Z47: 0820780-23.2026.8.14.0301 | AB47: cdn.dol.com.br | AC47: MATTHEUS REIS E MONTENEGRO | AD47: Presidente | AH47: RJ | AI47: RIO DE JANEIRO | AJ47: Clubes sociais, esportivos e similares | AK47: DEMAIS | AL47: ATIVA | AM47: https://cdn.dol.com.br/img/attachmentinline/940000/6publicacao-2-edital-art-7-parag-2-da-lei-11101-20009467060.pdf?xid=3272528 | AN47: p3 r19 | AO47: p3: R$ 309.484,78 | AP47: AJ_LIST | AQ47: 2026-07-07 | AR47: QUARANTINED | AS47: PARTIAL_DOC_CLASS_III_RECONCILED ROWS:p3r19 | AT47: 38d930ab1caa
A48: 47 | B48: NEW | D48: 0 | I48: PLASKEM EMBALAGENS LTDA | J48: PLASKEM EMBALAGENS LTDA | K48: 05052443 | L48: 05052443000140 | M48: 286961.94 | N48: 1 | O48: UNKNOWN | R48: =IF(Q48="","",ROUND((TODAY()-Q48)/365.25,1)) | S48: =VLOOKUP(O48,Assumptions!$A$7:$E$10,2,FALSE) | T48: =MAX(0.5,VLOOKUP(O48,Assumptions!$A$7:$E$10,3,FALSE)+VLOOKUP(O48,Assumptions!$A$7:$E$10,4,FALSE)/2-IF(R48="",0,R48)) | U48: =M48*S48/(1+Assumptions!$B$3)^T48 | V48: =IF(M48=0,"",ROUND(U48/M48*100,1)) | W48: =U48*Assumptions!$B$4 | X48: =IF(M48=0,"",ROUND(W48/M48*100,1)) | Y48: AGROPECUÁRIA SERROTE REDONDO | Z48: 0000206-69.2013.8.17.1340 | AB48: lrflideres.com.br | AC48: AUGUSTO FERNANDO NUNES OLIVEIRA | AD48: Sócio-Administrador | AE48: (71) 3186-0354 | AH48: BA | AI48: LAURO DE FREITAS | AJ48: Fabricação de embalagens de material plástico | AK48: DEMAIS | AL48: ATIVA | AM48: https://lrflideres.com.br/wp-content/plugins/download-attachments/includes/download.php?id=5001 | AN48: p3 r15 | AO48: p3: R$ 286.961,94 | AP48: UNKNOWN | AR48: OK | AS48: ALT_VALUE:286.961,94 ROWS:p3r15 | AT48: 7c0ce2830d0d
A49: 48 | B49: NEW | D49: 0 | J49: CAPITAL ANNEX FUNDO DE INVESTIMENTO EM DIREITOS CREDITORIOS MULTISSETORIAL | K49: 12093804 | L49: 12093804000161 | M49: 286765.7 | N49: 1 | O49: UNKNOWN | R49: =IF(Q49="","",ROUND((TODAY()-Q49)/365.25,1)) | S49: =VLOOKUP(O49,Assumptions!$A$7:$E$10,2,FALSE) | T49: =MAX(0.5,VLOOKUP(O49,Assumptions!$A$7:$E$10,3,FALSE)+VLOOKUP(O49,Assumptions!$A$7:$E$10,4,FALSE)/2-IF(R49="",0,R49)) | U49: =M49*S49/(1+Assumptions!$B$3)^T49 | V49: =IF(M49=0,"",ROUND(U49/M49*100,1)) | W49: =U49*Assumptions!$B$4 | X49: =IF(M49=0,"",ROUND(W49/M49*100,1)) | Y49: ARRUDA & MELO COMERCIO E DISTRIBUICAO DE ALIMENTOS E BEBIDAS LTDA | Z49: 0008526-45.2025.8.17.2001 | AB49: diligence.adm.br | AM49: https://diligence.adm.br/wp-content/uploads/2025/06/Edital-1a-Lista-de-Credores.pdf | AN49: p5 r68 | AO49: p5: R$ 286.765,70 | AP49: DEBTOR_LIST | AQ49: 2025-06-10 | AR49: OK | AS49: ROWS:p5r68 | AT49: 1658892fa167
A50: 49 | B50: NEW | D50: 0 | I50: BRANDT SOLUCOES EM AGRICULTURA LTDA | J50: BRANDT SOLUCOES EM AGRICULTURA LTDA | K50: 11516792 | L50: 11516792000178 | M50: 282047 | N50: 1 | O50: UNKNOWN | R50: =IF(Q50="","",ROUND((TODAY()-Q50)/365.25,1)) | S50: =VLOOKUP(O50,Assumptions!$A$7:$E$10,2,FALSE) | T50: =MAX(0.5,VLOOKUP(O50,Assumptions!$A$7:$E$10,3,FALSE)+VLOOKUP(O50,Assumptions!$A$7:$E$10,4,FALSE)/2-IF(R50="",0,R50)) | U50: =M50*S50/(1+Assumptions!$B$3)^T50 | V50: =IF(M50=0,"",ROUND(U50/M50*100,1)) | W50: =U50*Assumptions!$B$4 | X50: =IF(M50=0,"",ROUND(W50/M50*100,1)) | Y50: SOJAL COMERCIAL AGRICOLA | Z50: 0804401-51.2025.8.14.0039 | AB50: lrflideres.com.br | AC50: WLADIMIR MASCHIO CARDOZO CHAGA | AD50: Sócio-Administrador | AE50: (43) 3345-2323 | AH50: PR | AI50: CAMBE | AJ50: Fabricação de adubos e fertilizantes, exceto organo-minerais | AK50: DEMAIS | AL50: ATIVA | AM50: https://lrflideres.com.br/wp-content/plugins/download-attachments/includes/download.php?id=6879 | AN50: p1 r7 | AO50: p1: R$ 282.047,00 | AP50: AJ_LIST | AQ50: 2026-01-15 | AR50: OK | AS50: ROWS:p1r7 | AT50: c56751547323
A51: 50 | B51: NEW | D51: 0 | I51: OPTIMUM CONSULTORIA EM GESTAO PUBLICA E EMPRESARIAL LTDA | J51: OPTIMUM CONSULTORIA EM GESTAO PUBLICA LTDA | K51: 10925045 | L51: 10925045000120 | M51: 267635.55 | N51: 1 | O51: UNKNOWN | R51: =IF(Q51="","",ROUND((TODAY()-Q51)/365.25,1)) | S51: =VLOOKUP(O51,Assumptions!$A$7:$E$10,2,FALSE) | T51: =MAX(0.5,VLOOKUP(O51,Assumptions!$A$7:$E$10,3,FALSE)+VLOOKUP(O51,Assumptions!$A$7:$E$10,4,FALSE)/2-IF(R51="",0,R51)) | U51: =M51*S51/(1+Assumptions!$B$3)^T51 | V51: =IF(M51=0,"",ROUND(U51/M51*100,1)) | W51: =U51*Assumptions!$B$4 | X51: =IF(M51=0,"",ROUND(W51/M51*100,1)) | Y51: DR. ALLAN DE QUEIROZ RAMOS – OAB/PB 20.574 | Z51: 0829315-43.2023.8.15.0001 | AB51: lrflideres.com.br | AC51: EOLO DE SOUZA SALES | AD51: Sócio-Administrador | AE51: (83) 9975-0001 | AH51: PB | AI51: CAMPINA GRANDE | AJ51: Atividades de consultoria em gestão empresarial, exceto consultoria técnica específica | AK51: MICRO EMPRESA | AL51: ATIVA | AM51: https://lrflideres.com.br/wp-content/plugins/download-attachments/includes/download.php?id=5828 | AN51: p3 r19 | AO51: p3: R$ 267.635,55 | AP51: AJ_LIST | AQ51: 2024-04-18 | AR51: OK | AS51: ROWS:p3r19 | AT51: 47e92e4db6f8
A52: 51 | B52: NEW | D52: 0 | I52: GUARARAPES PAINEIS S/A | J52: GUARARAPES PAINES LTDA, CNPJ | K52: 08810422 | L52: 08810422000134 | M52: 238085.39 | N52: 1 | O52: UNKNOWN | R52: =IF(Q52="","",ROUND((TODAY()-Q52)/365.25,1)) | S52: =VLOOKUP(O52,Assumptions!$A$7:$E$10,2,FALSE) | T52: =MAX(0.5,VLOOKUP(O52,Assumptions!$A$7:$E$10,3,FALSE)+VLOOKUP(O52,Assumptions!$A$7:$E$10,4,FALSE)/2-IF(R52="",0,R52)) | U52: =M52*S52/(1+Assumptions!$B$3)^T52 | V52: =IF(M52=0,"",ROUND(U52/M52*100,1)) | W52: =U52*Assumptions!$B$4 | X52: =IF(M52=0,"",ROUND(W52/M52*100,1)) | Y52: DICARLO MOVEIS E ACESSORIOS PARA CASA E LOJAS LTDA | Z52: 0301015-33.2016.8.24.0031 | AB52: administradorajudicialgs.com.br | AC52: RICARDO PEDROSO | AD52: Presidente | AE52: (41) 3099-1414 | AF52: (49) 3244-6813 | AH52: SC | AI52: CACADOR | AJ52: Fabricação de madeira laminada e de chapas de madeira compensada, prensada e aglomerada | AK52: DEMAIS | AL52: ATIVA | AM52: https://administradorajudicialgs.com.br/wp-content/uploads/2023/08/edital-quadro-geral-de-credores.pdf | AN52: p2 r68 | AO52: p2: R$ 238.085,39 | AP52: QGC | AQ52: 2024-07-05 | AR52: OK_NO_TOTALS | AS52: ROWS:p2r68 UNRECONCILED_SOURCE | AT52: 98f99945499b
A53: 52 | B53: NEW | D53: 0 | I53: DOREMUS ALIMENTOS LTDA | J53: DOREMUS ALIMENTOS LTDA | K53: 54289830 | L53: 54289830000100 | M53: 235792.34 | N53: 1 | O53: UNKNOWN | R53: =IF(Q53="","",ROUND((TODAY()-Q53)/365.25,1)) | S53: =VLOOKUP(O53,Assumptions!$A$7:$E$10,2,FALSE) | T53: =MAX(0.5,VLOOKUP(O53,Assumptions!$A$7:$E$10,3,FALSE)+VLOOKUP(O53,Assumptions!$A$7:$E$10,4,FALSE)/2-IF(R53="",0,R53)) | U53: =M53*S53/(1+Assumptions!$B$3)^T53 | V53: =IF(M53=0,"",ROUND(U53/M53*100,1)) | W53: =U53*Assumptions!$B$4 | X53: =IF(M53=0,"",ROUND(W53/M53*100,1)) | Z53: (not found in document) | AB53: bernardobicalho.com.br | AC53: JOSE AUGUSTO SCHITTKOWSKI | AD53: Administrador | AE53: (11) 2436-3333 | AH53: SP | AI53: GUARULHOS | AJ53: Fabricação de outros produtos alimentícios não especificados anteriormente | AK53: DEMAIS | AL53: ATIVA | AM53: http://bernardobicalho.com.br/login/app/documents/Rela%C3%A7%C3%A3o%20de%20Credores/6.%20RVC-%20Nutricium%20-%20simplificada.pdf | AN53: p3 r14 | AO53: p3: R$ 235.792,34 | AP53: AJ_LIST | AR53: OK | AS53: CASE_NUMBER_MISSING ROWS:p3r14 | AT53: 6a92d74da333
A54: 53 | B54: NEW | D54: 0 | I54: EDENTEC INDUSTRIA E COMERCIO LTDA | J54: EDENTEC INDUSTRIA E COMERCIO LTDA | K54: 47799028 | L54: 47799028000102 | M54: 219345.95 | N54: 1 | O54: UNKNOWN | R54: =IF(Q54="","",ROUND((TODAY()-Q54)/365.25,1)) | S54: =VLOOKUP(O54,Assumptions!$A$7:$E$10,2,FALSE) | T54: =MAX(0.5,VLOOKUP(O54,Assumptions!$A$7:$E$10,3,FALSE)+VLOOKUP(O54,Assumptions!$A$7:$E$10,4,FALSE)/2-IF(R54="",0,R54)) | U54: =M54*S54/(1+Assumptions!$B$3)^T54 | V54: =IF(M54=0,"",ROUND(U54/M54*100,1)) | W54: =U54*Assumptions!$B$4 | X54: =IF(M54=0,"",ROUND(W54/M54*100,1)) | Y54: Conduscabos Brasil Indústria Comércio de | Z54: 8005129-09.2023.8.05.0039 | AB54: assistjud.com.br | AC54: RUBENS RIZZARDO | AD54: Sócio-Administrador | AH54: SP | AI54: SOROCABA | AJ54: Fabricação de artefatos diversos de madeira, exceto móveis | AK54: DEMAIS | AL54: ATIVA | AM54: https://assistjud.com.br/wp-content/uploads/elementor/forms/65098c80a5824.pdf | AN54: p7 r3 | AO54: p7: R$ 219.345,95 | AP54: AJ_LIST | AQ54: 2023-09-18 | AR54: OK_NO_TOTALS | AS54: ROWS:p7r3 UNRECONCILED_SOURCE | AT54: a0ae32a59c29
A55: 54 | B55: NEW | D55: 0 | I55: NUTRANE NUTRICAO ANIMAL LTDA | J55: DURANCHO – NUTRIÇÃO ANIMAL | K55: 04591114 | L55: 04591114000104 | M55: 201080.88 | N55: 1 | O55: UNKNOWN | R55: =IF(Q55="","",ROUND((TODAY()-Q55)/365.25,1)) | S55: =VLOOKUP(O55,Assumptions!$A$7:$E$10,2,FALSE) | T55: =MAX(0.5,VLOOKUP(O55,Assumptions!$A$7:$E$10,3,FALSE)+VLOOKUP(O55,Assumptions!$A$7:$E$10,4,FALSE)/2-IF(R55="",0,R55)) | U55: =M55*S55/(1+Assumptions!$B$3)^T55 | V55: =IF(M55=0,"",ROUND(U55/M55*100,1)) | W55: =U55*Assumptions!$B$4 | X55: =IF(M55=0,"",ROUND(W55/M55*100,1)) | Y55: AGROPECUÁRIA SERROTE REDONDO | Z55: 0000206-69.2013.8.17.1340 | AB55: lrflideres.com.br | AC55: OTAVIO BEZERRA DO REGO BARROS | AD55: Sócio-Administrador | AE55: (87) 3835-3486 | AH55: PE | AI55: PESQUEIRA | AJ55: Fabricação de alimentos para animais | AK55: DEMAIS | AL55: ATIVA | AM55: https://lrflideres.com.br/wp-content/plugins/download-attachments/includes/download.php?id=5001 | AN55: p2 r1 | AO55: p2: R$ 201.080,88 | AP55: UNKNOWN | AR55: OK | AS55: ALT_VALUE:49.140,00 ROWS:p2r1 | AT55: 7c0ce2830d0d

Sheet Pooling (100-200k)
A1: Rank | B1: Status | C1: Owner | D1: Attempts | E1: Last touch | F1: Next action | G1: Next date | H1: Notes | I1: Company (RFB) | J1: Name as printed | K1: CNPJ root | L1: Establishment CNPJs | M1: Class III face (R$) | N1: Claims | O1: Plan status | P1: Stage | Q1: Case filed | R1: Years since filing | S1: Est. recovery % | T1: Years to payment (est.) | U1: Fund price @ IRR (R$) | V1: Fund price (cents) | W1: OUR QUOTE (R$) | X1: Quote (cents) | Y1: Debtor | Z1: Case number | AA1: Court | AB1: Administrator (site) | AC1: Decision-maker | AD1: Role | AE1: Phone | AF1: Phone 2 | AG1: Email | AH1: UF | AI1: City | AJ1: CNAE | AK1: Porte | AL1: Situação | AM1: PROOF: source document | AN1: Page / row | AO1: Value as printed | AP1: Which list | AQ1: Published | AR1: Reconciled | AS1: Data flags | AT1: Doc id
A2: 1 | B2: NEW | D2: 0 | J2: ALVAREZ & MARSAL REESTRUTURACAO E ASSESS ORIA FINANCEIRA PARA SIT ESP LTDA | K2: 32282989 | L2: 32282989000160 | M2: 188233.36 | N2: 1 | O2: UNKNOWN | R2: =IF(Q2="","",ROUND((TODAY()-Q2)/365.25,1)) | S2: =VLOOKUP(O2,Assumptions!$A$7:$E$10,2,FALSE) | T2: =MAX(0.5,VLOOKUP(O2,Assumptions!$A$7:$E$10,3,FALSE)+VLOOKUP(O2,Assumptions!$A$7:$E$10,4,FALSE)/2-IF(R2="",0,R2)) | U2: =M2*S2/(1+Assumptions!$B$3)^T2 | V2: =IF(M2=0,"",ROUND(U2/M2*100,1)) | W2: =U2*Assumptions!$B$4 | X2: =IF(M2=0,"",ROUND(W2/M2*100,1)) | Z2: 0820780-23.2026.8.14.0301 | AB2: cdn.dol.com.br | AM2: https://cdn.dol.com.br/img/attachmentinline/940000/6publicacao-2-edital-art-7-parag-2-da-lei-11101-20009467060.pdf?xid=3272528 | AN2: p3 r13 | AO2: p3: R$ 188.233,36 | AP2: AJ_LIST | AQ2: 2026-07-07 | AR2: QUARANTINED | AS2: PARTIAL_DOC_CLASS_III_RECONCILED ROWS:p3r13 | AT2: 38d930ab1caa
A3: 2 | B3: NEW | D3: 0 | J3: MULTIPLO FUNDO DE INVESTIMENTO EM DIREITOS CREDITÓRIOS NÃO PADRONIZADOS MULTISSETORIA L | K3: 10842374 | L3: 10842374000108 | M3: 160996.26 | N3: 1 | O3: UNKNOWN | R3: =IF(Q3="","",ROUND((TODAY()-Q3)/365.25,1)) | S3: =VLOOKUP(O3,Assumptions!$A$7:$E$10,2,FALSE) | T3: =MAX(0.5,VLOOKUP(O3,Assumptions!$A$7:$E$10,3,FALSE)+VLOOKUP(O3,Assumptions!$A$7:$E$10,4,FALSE)/2-IF(R3="",0,R3)) | U3: =M3*S3/(1+Assumptions!$B$3)^T3 | V3: =IF(M3=0,"",ROUND(U3/M3*100,1)) | W3: =U3*Assumptions!$B$4 | X3: =IF(M3=0,"",ROUND(W3/M3*100,1)) | Y3: Conduscabos Brasil Indústria Comércio de | Z3: 8005129-09.2023.8.05.0039 | AB3: assistjud.com.br | AM3: https://assistjud.com.br/wp-content/uploads/elementor/forms/65098c80a5824.pdf | AN3: p19 r1 | AO3: p19: R$ 160.996,26 | AP3: AJ_LIST | AQ3: 2023-09-18 | AR3: OK_NO_TOTALS | AS3: ROWS:p19r1 UNRECONCILED_SOURCE | AT3: a0ae32a59c29
A4: 3 | B4: NEW | D4: 0 | I4: SIAGRI SISTEMAS DE GESTAO LTDA | J4: SIAGRI SISTEMAS DE GESTAO LTDA | K4: 02435301 | L4: 02435301000416 | M4: 155266.23 | N4: 1 | O4: UNKNOWN | R4: =IF(Q4="","",ROUND((TODAY()-Q4)/365.25,1)) | S4: =VLOOKUP(O4,Assumptions!$A$7:$E$10,2,FALSE) | T4: =MAX(0.5,VLOOKUP(O4,Assumptions!$A$7:$E$10,3,FALSE)+VLOOKUP(O4,Assumptions!$A$7:$E$10,4,FALSE)/2-IF(R4="",0,R4)) | U4: =M4*S4/(1+Assumptions!$B$3)^T4 | V4: =IF(M4=0,"",ROUND(U4/M4*100,1)) | W4: =U4*Assumptions!$B$4 | X4: =IF(M4=0,"",ROUND(W4/M4*100,1)) | Y4: SOJAL COMERCIAL AGRICOLA | Z4: 0804401-51.2025.8.14.0039 | AB4: lrflideres.com.br | AC4: CARLOS ANTONIO BARBOSA | AD4: Administrador | AE4: (64) 3620-1550 | AF4: (64) 3620-1500 | AH4: GO | AI4: RIO VERDE | AJ4: Desenvolvimento e licenciamento de programas de computador customizáveis | AK4: DEMAIS | AL4: ATIVA | AM4: https://lrflideres.com.br/wp-content/plugins/download-attachments/includes/download.php?id=6879 | AN4: p2 r8 | AO4: p2: R$ 155.266,23 | AP4: AJ_LIST | AQ4: 2026-01-15 | AR4: OK | AS4: ROWS:p2r8 | AT4: c56751547323
A5: 4 | B5: NEW | D5: 0 | I5: JUAREZ DE OLIVEIRA | J5: JUAREZ DE OLIVEIRA M E | K5: 69915536 | L5: 69915536000133 | M5: 151663.31 | N5: 1 | O5: UNKNOWN | R5: =IF(Q5="","",ROUND((TODAY()-Q5)/365.25,1)) | S5: =VLOOKUP(O5,Assumptions!$A$7:$E$10,2,FALSE) | T5: =MAX(0.5,VLOOKUP(O5,Assumptions!$A$7:$E$10,3,FALSE)+VLOOKUP(O5,Assumptions!$A$7:$E$10,4,FALSE)/2-IF(R5="",0,R5)) | U5: =M5*S5/(1+Assumptions!$B$3)^T5 | V5: =IF(M5=0,"",ROUND(U5/M5*100,1)) | W5: =U5*Assumptions!$B$4 | X5: =IF(M5=0,"",ROUND(W5/M5*100,1)) | Y5: AGROPECUÁRIA SERROTE REDONDO | Z5: 0000206-69.2013.8.17.1340 | AB5: lrflideres.com.br | AH5: PE | AI5: ARCOVERDE | AJ5: Comércio varejista de outros produtos não especificados anteriormente | AK5: MICRO EMPRESA | AL5: ATIVA | AM5: https://lrflideres.com.br/wp-content/plugins/download-attachments/includes/download.php?id=5001 | AN5: p2 r32 | AO5: p2: R$ 151.663,31 | AP5: UNKNOWN | AR5: OK | AS5: ALT_VALUE:67.051,58 ROWS:p2r32 | AT5: 7c0ce2830d0d
A6: 5 | B6: NEW | D6: 0 | I6: JC SOCCER TALENTS MARKETING ESPORTIVO LTDA | J6: JC SOCCER TALENTS | K6: 12073848 | L6: 12073848000120 | M6: 151585.39 | N6: 1 | O6: UNKNOWN | R6: =IF(Q6="","",ROUND((TODAY()-Q6)/365.25,1)) | S6: =VLOOKUP(O6,Assumptions!$A$7:$E$10,2,FALSE) | T6: =MAX(0.5,VLOOKUP(O6,Assumptions!$A$7:$E$10,3,FALSE)+VLOOKUP(O6,Assumptions!$A$7:$E$10,4,FALSE)/2-IF(R6="",0,R6)) | U6: =M6*S6/(1+Assumptions!$B$3)^T6 | V6: =IF(M6=0,"",ROUND(U6/M6*100,1)) | W6: =U6*Assumptions!$B$4 | X6: =IF(M6=0,"",ROUND(W6/M6*100,1)) | Z6: 0820780-23.2026.8.14.0301 | AB6: cdn.dol.com.br | AC6: ALEXANDRE BASTOS LOPES | AD6: Sócio-Administrador | AE6: (21) 3970-8940 | AH6: RJ | AI6: RIO DE JANEIRO | AJ6: Agenciamento de profissionais para atividades esportivas, culturais e artísticas | AK6: DEMAIS | AL6: ATIVA | AM6: https://cdn.dol.com.br/img/attachmentinline/940000/6publicacao-2-edital-art-7-parag-2-da-lei-11101-20009467060.pdf?xid=3272528 | AN6: p3 r22 | AO6: p3: R$ 151.585,39 | AP6: AJ_LIST | AQ6: 2026-07-07 | AR6: QUARANTINED | AS6: PARTIAL_DOC_CLASS_III_RECONCILED ROWS:p3r22 | AT6: 38d930ab1caa
A7: 6 | B7: NEW | D7: 0 | I7: SULPECAS COMERCIO E REPRESENTACOES LTDA | J7: SULPEÇAS COM E REPRES LTDA | K7: 52068491 | L7: 52068491000106 | M7: 135239.5 | N7: 1 | O7: UNKNOWN | R7: =IF(Q7="","",ROUND((TODAY()-Q7)/365.25,1)) | S7: =VLOOKUP(O7,Assumptions!$A$7:$E$10,2,FALSE) | T7: =MAX(0.5,VLOOKUP(O7,Assumptions!$A$7:$E$10,3,FALSE)+VLOOKUP(O7,Assumptions!$A$7:$E$10,4,FALSE)/2-IF(R7="",0,R7)) | U7: =M7*S7/(1+Assumptions!$B$3)^T7 | V7: =IF(M7=0,"",ROUND(U7/M7*100,1)) | W7: =U7*Assumptions!$B$4 | X7: =IF(M7=0,"",ROUND(W7/M7*100,1)) | Y7: DR. ALYSSON CORREIA MACIEL – OAB/PB 11.841, DRA. CAROL DE ALMEIDA LIMA | Z7: 0804204-35.2022.8.15.0731 | AB7: lrflideres.com.br | AC7: MARCELO DE SOUZA GUERINI | AD7: Sócio-Administrador | AE7: (11) 3829-9900 | AH7: SP | AI7: SAO PAULO | AJ7: Comércio atacadista de máquinas, equipamentos para terraplenagem, mineração e construção; partes e peças | AK7: DEMAIS | AL7: ATIVA | AM7: https://lrflideres.com.br/wp-content/uploads/2022/08/4.-EDITAL-2a-LISTA-DE-CREDORES.pdf | AN7: p2 r10 | AO7: p2: R$ 135.239,50 | AP7: AJ_LIST | AQ7: 2023-12-04 | AR7: OK | AS7: ROWS:p2r10 | AT7: 1355f93a13cd
A8: 7 | B8: NEW | D8: 0 | I8: M CASSAB COMERCIO E INDUSTRIA LTDA | J8: M CASSAB COMERCIO E INDUSTRIA LTDA | K8: 49698723 | L8: 49698723000103 | M8: 131926.28 | N8: 1 | O8: UNKNOWN | R8: =IF(Q8="","",ROUND((TODAY()-Q8)/365.25,1)) | S8: =VLOOKUP(O8,Assumptions!$A$7:$E$10,2,FALSE) | T8: =MAX(0.5,VLOOKUP(O8,Assumptions!$A$7:$E$10,3,FALSE)+VLOOKUP(O8,Assumptions!$A$7:$E$10,4,FALSE)/2-IF(R8="",0,R8)) | U8: =M8*S8/(1+Assumptions!$B$3)^T8 | V8: =IF(M8=0,"",ROUND(U8/M8*100,1)) | W8: =U8*Assumptions!$B$4 | X8: =IF(M8=0,"",ROUND(W8/M8*100,1)) | Z8: (not found in document) | AB8: bernardobicalho.com.br | AC8: MARIO SERGIO CUTAIT | AD8: Administrador | AE8: (11) 2162-7700 | AF8: (11) 2162-7751 | AH8: SP | AI8: SAO PAULO | AJ8: Comércio atacadista especializado em outros produtos intermediários não especificados anteriormente | AK8: DEMAIS | AL8: ATIVA | AM8: http://bernardobicalho.com.br/login/app/documents/Rela%C3%A7%C3%A3o%20de%20Credores/6.%20RVC-%20Nutricium%20-%20simplificada.pdf | AN8: p3 r23 | AO8: p3: R$ 131.926,28 | AP8: AJ_LIST | AR8: OK | AS8: CASE_NUMBER_MISSING ROWS:p3r23 | AT8: 6a92d74da333
A9: 8 | B9: NEW | D9: 0 | I9: COMPANHIA DE ALIMENTOS DO NORDESTE CIALNE | J9: COMPANHIA DE ALIMENTOSDO NORDESTE CIALNE | K9: 07220874 | L9: 07220874000101 | M9: 131836.89 | N9: 1 | O9: UNKNOWN | R9: =IF(Q9="","",ROUND((TODAY()-Q9)/365.25,1)) | S9: =VLOOKUP(O9,Assumptions!$A$7:$E$10,2,FALSE) | T9: =MAX(0.5,VLOOKUP(O9,Assumptions!$A$7:$E$10,3,FALSE)+VLOOKUP(O9,Assumptions!$A$7:$E$10,4,FALSE)/2-IF(R9="",0,R9)) | U9: =M9*S9/(1+Assumptions!$B$3)^T9 | V9: =IF(M9=0,"",ROUND(U9/M9*100,1)) | W9: =U9*Assumptions!$B$4 | X9: =IF(M9=0,"",ROUND(W9/M9*100,1)) | Y9: AGROPECUÁRIA SERROTE REDONDO | Z9: 0000206-69.2013.8.17.1340 | AB9: lrflideres.com.br | AC9: IVAN ANTONIO PERUZZO | AD9: Presidente | AE9: (85) 3477-2700 | AH9: CE | AI9: FORTALEZA | AJ9: Produção de pintos de um dia | AK9: DEMAIS | AL9: ATIVA | AM9: https://lrflideres.com.br/wp-content/plugins/download-attachments/includes/download.php?id=5001 | AN9: p1 r27 | AO9: p1: R$ 131.836,89 | AP9: UNKNOWN | AR9: OK | AS9: ALT_VALUE:131.836,89 ROWS:p1r27 VALUE_COL:Valor_Atualizado | AT9: 7c0ce2830d0d
A10: 9 | B10: NEW | D10: 0 | I10: MARTINS CONFECCAO E COMERCIO DE ARTIGOS DO VESTUARIO E ACESSORIOS LTDA | J10: MARTINS INDUSTRIA TEXTIL, CNPJ | K10: 82165010 | L10: 82165010000141 | M10: 127861.62 | N10: 1 | O10: UNKNOWN | R10: =IF(Q10="","",ROUND((TODAY()-Q10)/365.25,1)) | S10: =VLOOKUP(O10,Assumptions!$A$7:$E$10,2,FALSE) | T10: =MAX(0.5,VLOOKUP(O10,Assumptions!$A$7:$E$10,3,FALSE)+VLOOKUP(O10,Assumptions!$A$7:$E$10,4,FALSE)/2-IF(R10="",0,R10)) | U10: =M10*S10/(1+Assumptions!$B$3)^T10 | V10: =IF(M10=0,"",ROUND(U10/M10*100,1)) | W10: =U10*Assumptions!$B$4 | X10: =IF(M10=0,"",ROUND(W10/M10*100,1)) | Y10: DICARLO MOVEIS E ACESSORIOS PARA CASA E LOJAS LTDA | Z10: 0301015-33.2016.8.24.0031 | AB10: administradorajudicialgs.com.br | AC10: ILMA FEUSER MARTINS | AD10: Sócio-Administrador | AE10: (47) 2123-2500 | AH10: SC | AI10: INDAIAL | AJ10: Tecelagem de fios de algodão | AK10: DEMAIS | AL10: ATIVA | AM10: https://administradorajudicialgs.com.br/wp-content/uploads/2023/08/edital-quadro-geral-de-credores.pdf | AN10: p3 r12 | AO10: p3: R$ 127.861,62 | AP10: QGC | AQ10: 2024-07-05 | AR10: OK_NO_TOTALS | AS10: ROWS:p3r12 UNRECONCILED_SOURCE | AT10: 98f99945499b
A11: 10 | B11: NEW | D11: 0 | J11: SOFISA RECEBÍVEIS FUNDO DE INVESTIMENTO EM DIREITOS CREDITÓRIOS PADRONIZADOS | K11: 28075236 | L11: 28075236000106 | M11: 126832.55 | N11: 1 | O11: UNKNOWN | R11: =IF(Q11="","",ROUND((TODAY()-Q11)/365.25,1)) | S11: =VLOOKUP(O11,Assumptions!$A$7:$E$10,2,FALSE) | T11: =MAX(0.5,VLOOKUP(O11,Assumptions!$A$7:$E$10,3,FALSE)+VLOOKUP(O11,Assumptions!$A$7:$E$10,4,FALSE)/2-IF(R11="",0,R11)) | U11: =M11*S11/(1+Assumptions!$B$3)^T11 | V11: =IF(M11=0,"",ROUND(U11/M11*100,1)) | W11: =U11*Assumptions!$B$4 | X11: =IF(M11=0,"",ROUND(W11/M11*100,1)) | Y11: Conduscabos Brasil Indústria Comércio de | Z11: 8005129-09.2023.8.05.0039 | AB11: assistjud.com.br | AM11: https://assistjud.com.br/wp-content/uploads/elementor/forms/65098c80a5824.pdf | AN11: p10 r3 | AO11: p10: R$ 126.832,55 | AP11: AJ_LIST | AQ11: 2023-09-18 | AR11: OK_NO_TOTALS | AS11: ROWS:p10r3 UNRECONCILED_SOURCE | AT11: a0ae32a59c29
A12: 11 | B12: NEW | D12: 0 | I12: PETROSTAR COMBUSTIVEIS LTDA | J12: PETROSTAR COMBUSTIVEIS LTDA | K12: 29736901 | L12: 29736901000128 | M12: 120950 | N12: 1 | O12: UNKNOWN | R12: =IF(Q12="","",ROUND((TODAY()-Q12)/365.25,1)) | S12: =VLOOKUP(O12,Assumptions!$A$7:$E$10,2,FALSE) | T12: =MAX(0.5,VLOOKUP(O12,Assumptions!$A$7:$E$10,3,FALSE)+VLOOKUP(O12,Assumptions!$A$7:$E$10,4,FALSE)/2-IF(R12="",0,R12)) | U12: =M12*S12/(1+Assumptions!$B$3)^T12 | V12: =IF(M12=0,"",ROUND(U12/M12*100,1)) | W12: =U12*Assumptions!$B$4 | X12: =IF(M12=0,"",ROUND(W12/M12*100,1)) | Y12: DR. ALYSSON CORREIA MACIEL – OAB/PB 11.841, DRA. CAROL DE ALMEIDA LIMA | Z12: 0804204-35.2022.8.15.0731 | AB12: lrflideres.com.br | AC12: CRISTIANO LINS NOGUEIRA DE ARAUJO | AD12: Sócio-Administrador | AE12: (81) 9197-4902 | AH12: PE | AI12: CABO DE SANTO AGOSTINHO | AJ12: Comércio atacadista de combustíveis realizado por transportador retalhista (T.R.R.) | AK12: DEMAIS | AL12: ATIVA | AM12: https://lrflideres.com.br/wp-content/uploads/2022/08/4.-EDITAL-2a-LISTA-DE-CREDORES.pdf | AN12: p1 r24 | AO12: p1: R$ 120.950,00 | AP12: AJ_LIST | AQ12: 2023-12-04 | AR12: OK | AS12: ROWS:p1r24 | AT12: 1355f93a13cd
A13: 12 | B13: NEW | D13: 0 | I13: MASTERSENSE INGREDIENTES ALIMENTICIOS LTDA | J13: MASTERSENSE INGREDIENTES ALIMENTICIOS LTDA | K13: 03161388 | L13: 03161388000109 | M13: 119306.11 | N13: 1 | O13: UNKNOWN | R13: =IF(Q13="","",ROUND((TODAY()-Q13)/365.25,1)) | S13: =VLOOKUP(O13,Assumptions!$A$7:$E$10,2,FALSE) | T13: =MAX(0.5,VLOOKUP(O13,Assumptions!$A$7:$E$10,3,FALSE)+VLOOKUP(O13,Assumptions!$A$7:$E$10,4,FALSE)/2-IF(R13="",0,R13)) | U13: =M13*S13/(1+Assumptions!$B$3)^T13 | V13: =IF(M13=0,"",ROUND(U13/M13*100,1)) | W13: =U13*Assumptions!$B$4 | X13: =IF(M13=0,"",ROUND(W13/M13*100,1)) | Z13: (not found in document) | AB13: bernardobicalho.com.br | AC13: GUSTAVO ASSIS RODRIGUES | AD13: Sócio-Administrador | AE13: (11) 3109-3108 | AH13: SP | AI13: JUNDIAI | AJ13: Comércio atacadista de produtos alimentícios em geral | AK13: DEMAIS | AL13: ATIVA | AM13: http://bernardobicalho.com.br/login/app/documents/Rela%C3%A7%C3%A3o%20de%20Credores/6.%20RVC-%20Nutricium%20-%20simplificada.pdf | AN13: p3 r25 | AO13: p3: R$ 119.306,11 | AP13: AJ_LIST | AR13: OK | AS13: CASE_NUMBER_MISSING ROWS:p3r25 | AT13: 6a92d74da333
A14: 13 | B14: NEW | D14: 0 | I14: CP COMERCIAL S/A | J14: CP COMERCIAL S.A | K14: 08888040 | L14: 08888040000123 | M14: 108000 | N14: 1 | O14: UNKNOWN | R14: =IF(Q14="","",ROUND((TODAY()-Q14)/365.25,1)) | S14: =VLOOKUP(O14,Assumptions!$A$7:$E$10,2,FALSE) | T14: =MAX(0.5,VLOOKUP(O14,Assumptions!$A$7:$E$10,3,FALSE)+VLOOKUP(O14,Assumptions!$A$7:$E$10,4,FALSE)/2-IF(R14="",0,R14)) | U14: =M14*S14/(1+Assumptions!$B$3)^T14 | V14: =IF(M14=0,"",ROUND(U14/M14*100,1)) | W14: =U14*Assumptions!$B$4 | X14: =IF(M14=0,"",ROUND(W14/M14*100,1)) | Y14: DR. ALYSSON CORREIA MACIEL – OAB/PB 11.841, DRA. CAROL DE ALMEIDA LIMA | Z14: 0804204-35.2022.8.15.0731 | AB14: lrflideres.com.br | AC14: HUMBERTO GABRIEL CANTU | AD14: Presidente | AE14: (47) 3046-2550 | AH14: SC | AI14: ITAJAI | AJ14: Comércio por atacado de pneumáticos e câmaras-de-ar | AK14: DEMAIS | AL14: ATIVA | AM14: https://lrflideres.com.br/wp-content/uploads/2022/08/4.-EDITAL-2a-LISTA-DE-CREDORES.pdf | AN14: p1 r10 | AO14: p1: R$ 108.000,00 | AP14: AJ_LIST | AQ14: 2023-12-04 | AR14: OK | AS14: ROWS:p1r10 | AT14: 1355f93a13cd
A15: 14 | B15: NEW | D15: 0 | I15: CAVALO MARINHO COMBUSTIVEIS PERNAMBUCO LTDA | J15: CAVALO MARINHO COMBUSTIVEIS PERNAMBUCO | K15: 06974793 | L15: 06974793000126 | M15: 107850 | N15: 1 | O15: UNKNOWN | R15: =IF(Q15="","",ROUND((TODAY()-Q15)/365.25,1)) | S15: =VLOOKUP(O15,Assumptions!$A$7:$E$10,2,FALSE) | T15: =MAX(0.5,VLOOKUP(O15,Assumptions!$A$7:$E$10,3,FALSE)+VLOOKUP(O15,Assumptions!$A$7:$E$10,4,FALSE)/2-IF(R15="",0,R15)) | U15: =M15*S15/(1+Assumptions!$B$3)^T15 | V15: =IF(M15=0,"",ROUND(U15/M15*100,1)) | W15: =U15*Assumptions!$B$4 | X15: =IF(M15=0,"",ROUND(W15/M15*100,1)) | Y15: DR. ALYSSON CORREIA MACIEL – OAB/PB 11.841, DRA. CAROL DE ALMEIDA LIMA | Z15: 0804204-35.2022.8.15.0731 | AB15: lrflideres.com.br | AC15: ARMANDO MONTEIRO DA FONSECA FILHO | AD15: Sócio-Administrador | AE15: (81) 3106-5102 | AH15: PE | AI15: JABOATAO DOS GUARARAPES | AJ15: Comércio atacadista de combustíveis realizado por transportador retalhista (T.R.R.) | AK15: DEMAIS | AL15: ATIVA | AM15: https://lrflideres.com.br/wp-content/uploads/2022/08/4.-EDITAL-2a-LISTA-DE-CREDORES.pdf | AN15: p1 r8 | AO15: p1: R$ 107.850,00 | AP15: AJ_LIST | AQ15: 2023-12-04 | AR15: OK | AS15: ROWS:p1r8 | AT15: 1355f93a13cd
A16: 15 | B16: NEW | D16: 0 | I16: M.C. ARRUDA ADMINISTRADORA DE BENS S.A. | J16: M.C. ARRUDA ADMINISTRADORA DE BENS S.A | K16: 14724478 | L16: 14724478000179 | M16: 107500 | N16: 1 | O16: UNKNOWN | R16: =IF(Q16="","",ROUND((TODAY()-Q16)/365.25,1)) | S16: =VLOOKUP(O16,Assumptions!$A$7:$E$10,2,FALSE) | T16: =MAX(0.5,VLOOKUP(O16,Assumptions!$A$7:$E$10,3,FALSE)+VLOOKUP(O16,Assumptions!$A$7:$E$10,4,FALSE)/2-IF(R16="",0,R16)) | U16: =M16*S16/(1+Assumptions!$B$3)^T16 | V16: =IF(M16=0,"",ROUND(U16/M16*100,1)) | W16: =U16*Assumptions!$B$4 | X16: =IF(M16=0,"",ROUND(W16/M16*100,1)) | Y16: ARRUDA & MELO COMERCIO E DISTRIBUICAO DE ALIMENTOS E BEBIDAS LTDA | Z16: 0008526-45.2025.8.17.2001 | AB16: diligence.adm.br | AC16: AMANDA MARILIA SALDANHA ARRUDA | AD16: Diretor | AE16: (81) 3314-2110 | AH16: PE | AI16: RECIFE | AJ16: Gestão e administração da propriedade imobiliária | AK16: DEMAIS | AL16: ATIVA | AM16: https://diligence.adm.br/wp-content/uploads/2025/06/Edital-1a-Lista-de-Credores.pdf | AN16: p5 r57 | AO16: p5: R$ 107.500,00 | AP16: DEBTOR_LIST | AQ16: 2025-06-10 | AR16: OK | AS16: ROWS:p5r57 | AT16: 1658892fa167
A17: 16 | B17: NEW | D17: 0 | J17: BANCO JHON DEERE S.A | K17: 91884981 | L17: 91884981000132 | M17: 103498.23 | N17: 1 | O17: UNKNOWN | R17: =IF(Q17="","",ROUND((TODAY()-Q17)/365.25,1)) | S17: =VLOOKUP(O17,Assumptions!$A$7:$E$10,2,FALSE) | T17: =MAX(0.5,VLOOKUP(O17,Assumptions!$A$7:$E$10,3,FALSE)+VLOOKUP(O17,Assumptions!$A$7:$E$10,4,FALSE)/2-IF(R17="",0,R17)) | U17: =M17*S17/(1+Assumptions!$B$3)^T17 | V17: =IF(M17=0,"",ROUND(U17/M17*100,1)) | W17: =U17*Assumptions!$B$4 | X17: =IF(M17=0,"",ROUND(W17/M17*100,1)) | Y17: SOJAL COMERCIAL AGRICOLA | Z17: 0804401-51.2025.8.14.0039 | AB17: lrflideres.com.br | AM17: https://lrflideres.com.br/wp-content/plugins/download-attachments/includes/download.php?id=6879 | AN17: p1 r6 | AO17: p1: R$ 103.498,23 | AP17: AJ_LIST | AQ17: 2026-01-15 | AR17: OK | AS17: ROWS:p1r6 | AT17: c56751547323
A18: 17 | B18: NEW | D18: 0 | I18: PLANALTO COMERCIO DE COMBUSTIVEIS E LUBRIFICANTES LTDA | J18: PLANALTO COMERCIO DE COMBUSTIVEIS E LUBRIFICANTES LTDA | K18: 14547859 | L18: 14547859000120 | M18: 100000 | N18: 1 | O18: UNKNOWN | R18: =IF(Q18="","",ROUND((TODAY()-Q18)/365.25,1)) | S18: =VLOOKUP(O18,Assumptions!$A$7:$E$10,2,FALSE) | T18: =MAX(0.5,VLOOKUP(O18,Assumptions!$A$7:$E$10,3,FALSE)+VLOOKUP(O18,Assumptions!$A$7:$E$10,4,FALSE)/2-IF(R18="",0,R18)) | U18: =M18*S18/(1+Assumptions!$B$3)^T18 | V18: =IF(M18=0,"",ROUND(U18/M18*100,1)) | W18: =U18*Assumptions!$B$4 | X18: =IF(M18=0,"",ROUND(W18/M18*100,1)) | Y18: DR. ALYSSON CORREIA MACIEL – OAB/PB 11.841, DRA. CAROL DE ALMEIDA LIMA | Z18: 0804204-35.2022.8.15.0731 | AB18: lrflideres.com.br | AC18: ELIZABETH DA SILVA PONTES ROZENDO | AD18: Administrador | AE18: (83) 9984-3530 | AF18: (83) 8783-8545 | AH18: PB | AI18: SANTA RITA | AJ18: Comércio varejista de combustíveis para veículos automotores | AK18: DEMAIS | AL18: ATIVA | AM18: https://lrflideres.com.br/wp-content/uploads/2022/08/4.-EDITAL-2a-LISTA-DE-CREDORES.pdf | AN18: p2 r2 | AO18: p2: R$ 100.000,00 | AP18: AJ_LIST | AQ18: 2023-12-04 | AR18: OK | AS18: ROWS:p2r2 | AT18: 1355f93a13cd

Sheet Needs CNPJ (name only)
A1: Name as printed | B1: Class III value (R$) | C1: Debtor | D1: Case number | E1: Which list | F1: Reconciled | G1: PROOF: source document | H1: Page / row | I1: Flags
A2: IMOBILIARIA ROCHA LTDA | B2: 2698172.1 | C2: ABF ENGENHARIA, SERVIÇOS E COMÉRCIO LTDA – LRF Líderes em Recuperação Judicial e Falência | D2: 0000742-29.2017.8.17.3090 | E2: UNKNOWN | F2: OK_NO_TOTALS | G2: https://lrflideres.com.br/wp-content/plugins/download-attachments/includes/download.php?id=3469 | H2: p11 r32 | I2: NO_DOCUMENT ALT_VALUE:2.698.172,09
A3: IMOBILIARIA ROCHA LTDA | B3: 2698172.1 | C3: ABF ENGENHARIA, SERVIÇOS E COMÉRCIO LTDA – LRF Líderes em Recuperação Judicial e Falência | D3: 0000742-29.2017.8.17.3090 | E3: UNKNOWN | F3: OK_NO_TOTALS | G3: https://lrflideres.com.br/wp-content/plugins/download-attachments/includes/download.php?id=3469 | H3: p19 r32 | I3: NO_DOCUMENT ALT_VALUE:2.698.172,09
A4: INTER LOCAÇÕES LTDA. | B4: 857288.82 | C4: ABF ENGENHARIA, SERVIÇOS E COMÉRCIO LTDA – LRF Líderes em Recuperação Judicial e Falência | D4: 0000742-29.2017.8.17.3090 | E4: UNKNOWN | F4: OK_NO_TOTALS | G4: https://lrflideres.com.br/wp-content/plugins/download-attachments/includes/download.php?id=3469 | H4: p11 r35 | I4: NO_DOCUMENT ALT_VALUE:857.288,82
A5: INTER LOCAÇÕES LTDA. | B5: 857288.82 | C5: ABF ENGENHARIA, SERVIÇOS E COMÉRCIO LTDA – LRF Líderes em Recuperação Judicial e Falência | D5: 0000742-29.2017.8.17.3090 | E5: UNKNOWN | F5: OK_NO_TOTALS | G5: https://lrflideres.com.br/wp-content/plugins/download-attachments/includes/download.php?id=3469 | H5: p19 r35 | I5: NO_DOCUMENT ALT_VALUE:857.288,82
A6: AMERICA LOCACAO E SERVICOS LTDA | B6: 486100.94 | C6: ABF ENGENHARIA, SERVIÇOS E COMÉRCIO LTDA – LRF Líderes em Recuperação Judicial e Falência | D6: 0000742-29.2017.8.17.3090 | E6: UNKNOWN | F6: OK_NO_TOTALS | G6: https://lrflideres.com.br/wp-content/plugins/download-attachments/includes/download.php?id=3469 | H6: p10 r7 | I6: NO_DOCUMENT ALT_VALUE:486.100,94
A7: AMERICA LOCACAO E SERVICOS LTDA | B7: 486100.94 | C7: ABF ENGENHARIA, SERVIÇOS E COMÉRCIO LTDA – LRF Líderes em Recuperação Judicial e Falência | D7: 0000742-29.2017.8.17.3090 | E7: UNKNOWN | F7: OK_NO_TOTALS | G7: https://lrflideres.com.br/wp-content/plugins/download-attachments/includes/download.php?id=3469 | H7: p18 r7 | I7: NO_DOCUMENT ALT_VALUE:486.100,94
A8: TICKET SERVICOS S/A | B8: 444535.38 | C8: ABF ENGENHARIA, SERVIÇOS E COMÉRCIO LTDA – LRF Líderes em Recuperação Judicial e Falência | D8: 0000742-29.2017.8.17.3090 | E8: UNKNOWN | F8: OK_NO_TOTALS | G8: https://lrflideres.com.br/wp-content/plugins/download-attachments/includes/download.php?id=3469 | H8: p13 r10 | I8: NO_DOCUMENT ALT_VALUE:444.535,38
A9: TICKET SERVICOS S/A | B9: 444535.38 | C9: ABF ENGENHARIA, SERVIÇOS E COMÉRCIO LTDA – LRF Líderes em Recuperação Judicial e Falência | D9: 0000742-29.2017.8.17.3090 | E9: UNKNOWN | F9: OK_NO_TOTALS | G9: https://lrflideres.com.br/wp-content/plugins/download-attachments/includes/download.php?id=3469 | H9: p21 r10 | I9: NO_DOCUMENT ALT_VALUE:444.535,38
A10: ACQUA PLAN ESTUDOS, PROJETOS E CONSULTORIA | B10: 341525 | C10: ABF ENGENHARIA, SERVIÇOS E COMÉRCIO LTDA – LRF Líderes em Recuperação Judicial e Falência | D10: 0000742-29.2017.8.17.3090 | E10: UNKNOWN | F10: OK_NO_TOTALS | G10: https://lrflideres.com.br/wp-content/plugins/download-attachments/includes/download.php?id=3469 | H10: p10 r3 | I10: NO_DOCUMENT ALT_VALUE:341.525,00
A11: ACQUA PLAN ESTUDOS, PROJETOS E CONSULTORIA | B11: 341525 | C11: ABF ENGENHARIA, SERVIÇOS E COMÉRCIO LTDA – LRF Líderes em Recuperação Judicial e Falência | D11: 0000742-29.2017.8.17.3090 | E11: UNKNOWN | F11: OK_NO_TOTALS | G11: https://lrflideres.com.br/wp-content/plugins/download-attachments/includes/download.php?id=3469 | H11: p18 r3 | I11: NO_DOCUMENT ALT_VALUE:341.525,00
A12: MARQUISE ENGENHARIA LTDA | B12: 339686.42 | C12: ABF ENGENHARIA, SERVIÇOS E COMÉRCIO LTDA – LRF Líderes em Recuperação Judicial e Falência | D12: 0000742-29.2017.8.17.3090 | E12: UNKNOWN | F12: OK_NO_TOTALS | G12: https://lrflideres.com.br/wp-content/plugins/download-attachments/includes/download.php?id=3469 | H12: p12 r3 | I12: NO_DOCUMENT ALT_VALUE:339.686,42
A13: MARQUISE ENGENHARIA LTDA | B13: 339686.42 | C13: ABF ENGENHARIA, SERVIÇOS E COMÉRCIO LTDA – LRF Líderes em Recuperação Judicial e Falência | D13: 0000742-29.2017.8.17.3090 | E13: UNKNOWN | F13: OK_NO_TOTALS | G13: https://lrflideres.com.br/wp-content/plugins/download-attachments/includes/download.php?id=3469 | H13: p20 r3 | I13: NO_DOCUMENT ALT_VALUE:339.686,42
... A46: Tacaruna Participacoes e Empreendimentos Ltda | B46: 220519.5 | C46: e Falência | D46: 0003283-70.2015.8.17.2810 | E46: UNKNOWN | F46: OK_NO_TOTALS | G46: https://lrflideres.com.br/wp-content/uploads/2021/09/LISTA-DE-CREDORES-FALENCIA.pdf | H46: p10 r5 | I46: NO_DOCUMENT

Sheet Sources
A1: Doc id | B1: Case number | C1: Type | D1: Status | E1: Pages | F1: Strategy | G1: Layout | H1: Reconcile checks | I1: Published | J1: Debtor (hint) | K1: Administrator | L1: URL
A2: 9e27c1a81224 | B2: 0001217-89.2020.8.16.0185 | C2: AJ_LIST | D2: NO_ROWS | E2: 3 | F2: TABLE | G2: TABLE_BANDS | I2: 2017-08-25 | J2: que lhe possibilitará replanejar o perfil de seus compromissos e sa | K2: credibilita.com.br | L2: https://credibilita.com.br/wp-content/uploads/2023/08/0046Sentencarecup.judicial.pdf
A3: 958a9351a970 | B3: 0818837-44.2021.8.15.0001 | C3: AJ_LIST | D3: NO_ROWS | E3: 2 | F3: PROSE | G3: PROSE | I3: 2024-08-05 | J3: convolada em Falência | K3: lrflideres.com.br | L3: https://lrflideres.com.br/wp-content/uploads/2021/12/10.-EDITAL-PUBLICACAO-2a-RELACAO-DE-CREDORES-MASSA-FALIDA-.pdf
A4: 0a24cd833119 | B4: 0808677-83.2017.8.18.0140 | C4: AJ_LIST | D4: NO_ROWS | E4: 2 | F4: TABLE | G4: TABLE_BANDS | I4: 2019-11-08 | J4: empresa | K4: recuperacaojudicial.servi-san.com.br | L4: https://recuperacaojudicial.servi-san.com.br/assets/Documentos/Processuais/PROC-10.pdf
A5: 8420efd56f55 | B5: 1102669-23.2014.8.26.0100 | C5: QGC | D5: NO_ROWS | E5: 2 | F5: TABLE | G5: TABLE_BANDS | I5: 2020-09-24 | J5: e Falência | K5: brasiltrustee.com.br | L5: https://brasiltrustee.com.br/wp-content/uploads/falencias/gran/Gran-Industria-Certidao-de-publicacao-do-edital-de-encerramento-da-falencia.pdf
A6: 561af3a175ea | B6: 0074372-48.1999.8.26.0100 | C6: QGC | D6: NO_ROWS | E6: 2 | F6: TABLE | G6: TABLE_BANDS | I6: 2024-11-19 | J6: de Massa | K6: gatekeeperaj.com.br | L6: https://gatekeeperaj.com.br/wp-content/uploads/2025/03/BULLGUER-EDITAL-DE-CONVOCACAO-DE-CREDORES-PARA-APRESENTACAO-DE-DADOSBANCARIOS-DIRETAMENTE-AS-RECUPERANDAS.pdf
A7: e0941a59d43d | C7: UNKNOWN | D7: NO_TEXT_LAYER | E7: 10 | F7: NONE | K7: diligence.adm.br | L7: https://diligence.adm.br/wp-content/plugins/download-attachments/includes/download.php?id=4294
A8: 6a92d74da333 | C8: AJ_LIST | D8: OK | E8: 4 | F8: TABLE | G8: TABLE_RULED | H8: I/BRL#s0: PASS Δ0.00 · III/BRL#s1: PASS Δ0.00 · IV/BRL#s2: PASS Δ0.00 | K8: bernardobicalho.com.br | L8: http://bernardobicalho.com.br/login/app/documents/Rela%C3%A7%C3%A3o%20de%20Credores/6.%20RVC-%20Nutricium%20-%20simplificada.pdf
A9: 47e92e4db6f8 | B9: 0829315-43.2023.8.15.0001 | C9: AJ_LIST | D9: OK | E9: 3 | F9: PROSE | G9: PROSE | H9: I/BRL#s1: PASS Δ0.00 · III/BRL#s2: PASS Δ0.00 | I9: 2024-04-18 | K9: lrflideres.com.br | L9: https://lrflideres.com.br/wp-content/plugins/download-attachments/includes/download.php?id=5828
A10: c56751547323 | B10: 0804401-51.2025.8.14.0039 | C10: AJ_LIST | D10: OK | E10: 2 | F10: PROSE | G10: PROSE | H10: II/BRL#s1: PASS Δ0.00 · III/BRL#s2: PASS Δ0.00 · IV/BRL#s3: PASS Δ0.00 | I10: 2026-01-15 | J10: SOJAL COMERCIA | K10: lrflideres.com.br | L10: https://lrflideres.com.br/wp-content/plugins/download-attachments/includes/download.php?id=6879
A11: 1355f93a13cd | B11: 0804204-35.2022.8.15.0731 | C11: AJ_LIST | D11: OK | E11: 2 | F11: PROSE | G11: PROSE | H11: III/BRL#s3: PASS Δ0.00 · IV/BRL#s4: PASS Δ0.00 | I11: 2023-12-04 | J11: SECULAR COMERCIO CONSTRUÇÃO E REPRESENTAÇÃO LTDA | K11: lrflideres.com.br | L11: https://lrflideres.com.br/wp-content/uploads/2022/08/4.-EDITAL-2a-LISTA-DE-CREDORES.pdf
A12: 49e767732638 | B12: 0824037-95.2022.8.15.0001 | C12: AJ_LIST | D12: OK | E12: 3 | F12: PROSE | G12: PROSE | H12: I/BRL#s1: PASS Δ0.04 · III/BRL#s2: PASS Δ0.00 | I12: 2023-11-24 | J12: em questão. FAZ SA | K12: lrflideres.com.br | L12: https://lrflideres.com.br/wp-content/uploads/2023/01/4.-EDITAL-2a-LISTA-DE-CREDORES-1.pdf
A13: e7a1e923dae2 | B13: 0829315-43.2023.8.15.0001 | C13: AJ_LIST | D13: OK | E13: 22 | F13: PROSE | G13: PROSE | H13: I/BRL#s166: PASS Δ0.00 · III/BRL#s167: PASS Δ0.00 | I13: 2024-03-21 | J13: consta no Doc 04 aqui acostado, servindo a Rua Padre Carapuceiro, 706, Empresa | K13: lrflideres.com.br | L13: https://lrflideres.com.br/wp-content/uploads/2023/12/3.1-PROTOCOLO-DA-2a-LISTA-DE-CREDORES.pdf
A14: 1658892fa167 | B14: 0008526-45.2025.8.17.2001 | C14: DEBTOR_LIST | D14: OK | E14: 7 | F14: PROSE | G14: PROSE | H14: I/BRL#s1: PASS Δ-0.02 · III/BRL#s2: PASS Δ0.01 · III/USD#s3: PASS Δ0.00 · IV/BRL#s4: PASS Δ0.00 | I14: 2025-06-10 | J14: E FALENCIA | K14: diligence.adm.br | L14: https://diligence.adm.br/wp-content/uploads/2025/06/Edital-1a-Lista-de-Credores.pdf
A15: 2f90c773d04b | B15: 0022066-39.2018.8.19.0001 | C15: QGC | D15: OK | E15: 1 | F15: TABLE | G15: TABLE_RULED | H15: I/BRL#s1: PASS Δ0.00 · III/BRL#s3: PASS Δ0.00 | J15: SOCIEDADE RECICLYN COMERCIO E INDÚSTRIA DE METAIS LTDA | K15: inova-aj.com.br | L15: https://inova-aj.com.br/wp-content/uploads/2021/08/Reciclyn-Quadro-Geral-de-Credores.xlsx.pdf
A16: 5ab9c6b6d223 | B16: 0000206-69.2013.8.17.1340 | C16: UNKNOWN | D16: OK | E16: 3 | F16: TABLE | G16: TABLE_RULED | H16: I/BRL#s1: PASS Δ0.00 | J16: AGROPECUÁRIA SERROTE REDONDO – LRF Líderes em Recuperação Judicial e Falência | K16: lrflideres.com.br | L16: https://lrflideres.com.br/wp-content/plugins/download-attachments/includes/download.php?id=4999
A17: ab7097a8638d | B17: 0000206-69.2013.8.17.1340 | C17: UNKNOWN | D17: OK | E17: 1 | F17: TABLE | G17: TABLE_RULED | H17: II/BRL#s1: PASS Δ0.00 | J17: AGROPECUÁRIA SERROTE REDONDO – LRF Líderes em Recuperação Judicial e Falência | K17: lrflideres.com.br | L17: https://lrflideres.com.br/wp-content/plugins/download-attachments/includes/download.php?id=5000
A18: 7c0ce2830d0d | B18: 0000206-69.2013.8.17.1340 | C18: UNKNOWN | D18: OK | E18: 4 | F18: TABLE | G18: TABLE_RULED | H18: III/BRL#s1: PASS Δ0.01 | J18: AGROPECUÁRIA SERROTE REDONDO – LRF Líderes em Recuperação Judicial e Falência | K18: lrflideres.com.br | L18: https://lrflideres.com.br/wp-content/plugins/download-attachments/includes/download.php?id=5001
A19: 572e76f00aa7 | B19: 0652260-87.2018.8.04.0001 | C19: AJ_LIST | D19: OK_NO_TOTALS | E19: 7 | F19: TABLE | G19: TABLE_BANDS | J19: empresa | K19: ajbrajalveiga.com.br | L19: https://ajbrajalveiga.com.br/processos/download/grupo-galo/4%20-%20Edital.pdf
A20: a0ae32a59c29 | B20: 8005129-09.2023.8.05.0039 | C20: AJ_LIST | D20: OK_NO_TOTALS | E20: 23 | F20: TABLE | G20: TABLE_RULED | I20: 2023-09-18 | J20: e na falência | K20: assistjud.com.br | L20: https://assistjud.com.br/wp-content/uploads/elementor/forms/65098c80a5824.pdf
A21: 6dff863c25a0 | B21: 5028800-87.2023.8.24.0038 | C21: DEBTOR_LIST | D21: OK_NO_TOTALS | E21: 2 | F21: PROSE | G21: PROSE | I21: 2024-11-21 | J21: e Extrajudicia | K21: bbsadvogados.com.br | L21: https://bbsadvogados.com.br/wp-content/uploads/2024/11/Delicatesse-Relacao-de-credores-da-recuperanda-Delicatesse-e-Mr.-Struderia.pdf
A22: 30f82df3abf4 | B22: 0019289-97.2025.8.06.0001 | C22: DEBTOR_LIST | D22: OK_NO_TOTALS | E22: 8 | F22: TABLE | G22: TABLE_BANDS | J22: SIGNUS CONSTRUÇÕES E ASSESSORIA TÉCNICA LTDA | K22: lrflideres.com.br | L22: https://lrflideres.com.br/wp-content/plugins/download-attachments/includes/download.php?id=6471
A23: a12d198cfa3d | B23: 0037082-72.2016.8.17.2001 | C23: DEBTOR_LIST | D23: OK_NO_TOTALS | E23: 6 | F23: TABLE | G23: TABLE_BANDS | I23: 2021-09-23 | J23: SERVOP COMÉRCIO LTDA | K23: lrflideres.com.br | L23: https://lrflideres.com.br/wp-content/uploads/2021/09/2.1-PUBLICAC%CC%A7A%CC%83O-DO-DEFERIMENTO-5.pdf
A24: 85a47dd934b1 | B24: 0000869-62.2019.8.17.2001 | C24: DEBTOR_LIST | D24: OK_NO_TOTALS | E24: 6 | F24: TABLE | G24: TABLE_BANDS | I24: 2021-09-24 | J24: processo tombado sob o no 0000869-62.2019.8.17.2001, requerida pelas empresa | K24: lrflideres.com.br | L24: https://lrflideres.com.br/wp-content/uploads/2022/03/3.-EDITAL-1a-LISTA-DE-CREDORES.pdf
A25: 5586da5070a3 | B25: 0212099-02.2025.8.06.0001 | C25: DEBTOR_LIST | D25: OK_NO_TOTALS | E25: 5 | F25: TABLE | G25: TABLE_BANDS | I25: 2025-06-25 | J25: ARENA COMBUSTÍVEIS LTDA | K25: lrflideres.com.br | L25: https://lrflideres.com.br/wp-content/uploads/2025/08/2.-DEFERIMENTO-1.pdf
A26: 83c5c4ade09b | B26: 5315944-66.2023.8.13.0024 | C26: QGC | D26: OK_NO_TOTALS | E26: 12 | F26: TABLE | G26: TABLE_RULED | J26: e na falência | K26: 3fmodas.madgav.com.br | L26: https://3fmodas.madgav.com.br/wp-content/uploads/2025/05/Quadro-Geral-de-Credores.pdf
A27: 98f99945499b | B27: 0301015-33.2016.8.24.0031 | C27: QGC | D27: OK_NO_TOTALS | E27: 4 | F27: PROSE | G27: PROSE | I27: 2024-07-05 | J27: e Extrajudicia | K27: administradorajudicialgs.com.br | L27: https://administradorajudicialgs.com.br/wp-content/uploads/2023/08/edital-quadro-geral-de-credores.pdf
A28: 260709460920 | B28: 0010173-64.2023.8.17.2480 | C28: QGC | D28: OK_NO_TOTALS | E28: 4 | F28: PROSE | G28: PROSE | I28: 2025-06-26 | J28: E FALENCIA | K28: diligence.adm.br | L28: https://diligence.adm.br/wp-content/uploads/2024/05/Apresentacao-do-edital-QGC.pdf
A29: 7d03c9d4861a | B29: 0000742-29.2017.8.17.3090 | C29: UNKNOWN | D29: OK_NO_TOTALS | E29: 23 | F29: TABLE | G29: TABLE_RULED | I29: 2021-09-10 | J29: ABF ENGENHARIA, SERVIÇOS E COMÉRCIO LTDA – LRF Líderes em Recuperação Judicial e Falência | K29: lrflideres.com.br | L29: https://lrflideres.com.br/wp-content/plugins/download-attachments/includes/download.php?id=3469
A30: 306dd46ee538 | B30: 3289322-33.2013.8.13.0024 | C30: UNKNOWN | D30: OK_NO_TOTALS | E30: 8 | F30: TABLE | G30: TABLE_BANDS | I30: 2023-03-01 | J30: e Falência | K30: bernardobicalho.com.br | L30: http://bernardobicalho.com.br/login/app/documents/Editais/Edital%20do%20Art.%2099%20%C2%A7%201%20da%20Lei%2011.101-05%20-%20Locplan.pdf
A31: a03dea18f259 | C31: UNKNOWN | D31: OK_NO_TOTALS | E31: 81 | F31: TABLE | G31: TABLE_BANDS | I31: 2009-11-04 | K31: diario.tjrr.jus.br | L31: https://diario.tjrr.jus.br/dpj/dpj-20091105.pdf
A32: bff0950df595 | C32: UNKNOWN | D32: OK_NO_TOTALS | E32: 120 | F32: TABLE | G32: TABLE_RULED | I32: 2009-12-15 | K32: diario.tjrr.jus.br | L32: https://diario.tjrr.jus.br/dpj/dpj-20091216.pdf
A33: 85feaf9ec486 | B33: 0003283-70.2015.8.17.2810 | C33: UNKNOWN | D33: OK_NO_TOTALS | E33: 11 | F33: TABLE | G33: TABLE_RULED | I33: 2021-09-30 | J33: e Falência | K33: lrflideres.com.br | L33: https://lrflideres.com.br/wp-content/uploads/2021/09/LISTA-DE-CREDORES-FALENCIA.pdf
A34: fcd4aec0367b | B34: 0802656-15.2026.8.18.0031 | C34: UNKNOWN | D34: OK_NO_TOTALS | E34: 33 | F34: TABLE | G34: TABLE_BANDS | I34: 2026-07-07 | K34: lrflideres.com.br | L34: https://lrflideres.com.br/wp-content/uploads/2026/03/6.-PLANO-DE-RECUPERACAO-JUDICIAL.pdf
A35: 7501ec99fc8e | B35: 0800778-16.2023.8.20.5104 | C35: AJ_LIST | D35: QUARANTINED | E35: 8 | F35: TABLE | G35: TABLE_RULED | H35: III/BRL#s6: FAIL Δ9388945.97 · I/BRL: PASS Δ0.00 | I35: 2024-10-04 | J35: e Falência | K35: recuperacaojudicial.squarespace.com | L35: http://recuperacaojudicial.squarespace.com/s/LISTA-DE-CREDORES-CONSOLIDADA-ATE-04102024.pdf
A36: 38d930ab1caa | B36: 0820780-23.2026.8.14.0301 | C36: AJ_LIST | D36: QUARANTINED | E36: 4 | F36: PROSE | G36: PROSE | H36: I/BRL#s1: FAIL Δ-381984.70 · III/BRL#s3: PASS Δ0.00 · IV/BRL#s4: PASS Δ0.00 | I36: 2026-07-07 | J36: e mpresa | K36: cdn.dol.com.br | L36: https://cdn.dol.com.br/img/attachmentinline/940000/6publicacao-2-edital-art-7-parag-2-da-lei-11101-20009467060.pdf?xid=3272528
A37: fe8c5f1b0eca | B37: 0871065-72.2024.8.12.0001 | C37: DEBTOR_LIST | D37: QUARANTINED | E37: 4 | F37: TABLE | G37: TABLE_BANDS | H37: II/BRL: FAIL Δ-269952.28 | J37: interessa | K37: csh.adv.br | L37: https://csh.adv.br/wp-content/uploads/2025/03/Edital-Art.-52-1.pdf
A38: e10381e6ac9c | B38: 0214287-36.2023.8.06.0001 | C38: QGC | D38: QUARANTINED | E38: 3 | F38: TABLE | G38: TABLE_BANDS | H38: IV/BRL#s6: FAIL Δ13820.70 · IV/BRL#s10: PASS Δ0.00 | J38: Assunto Concurso de Credores Requerente Pminas Brasil Construção Civil e Serviços Ltda | K38: bugarimecoelho.com.br | L38: https://bugarimecoelho.com.br/ws/media-library/5637e4df77a44cee9a27c6fa2c0a9d96/15.2--edital-01o-aditivo-qgc.pdf
A39: 1aeb10c3e145 | B39: 0016474-19.2022.8.03.0001 | C39: QGC | D39: QUARANTINED | E39: 24 | F39: TABLE | G39: TABLE_BANDS | H39: III/BRL#s14: FAIL Δ-224860.05 | I39: 2024-09-05 | J39: Empresa | K39: realbrasil.com.br | L39: https://realbrasil.com.br/wp-content/uploads/2024/10/2.QUADRO-DE-CREDORES-DO-AJ.pdf
A40: c9ded76ba27f | B40: 0000742-29.2017.8.17.3090 | C40: UNKNOWN | D40: QUARANTINED | E40: 31 | F40: TABLE | G40: TABLE_BANDS | H40: I/BRL: FAIL Δ-49576.56 · III/BRL: FAIL Δ-5802914.47 · IV/BRL: FAIL Δ-842955.22 | I40: 2021-09-10 | J40: ABF ENGENHARIA, SERVIÇOS E COMÉRCIO LTDA – LRF Líderes em Recuperação Judicial e Falência | K40: lrflideres.com.br | L40: https://lrflideres.com.br/wp-content/plugins/download-attachments/includes/download.php?id=3468
A41: 12e6f4e0aae9 | B41: 5281407-42.2021.8.09.0051 | C41: UNKNOWN | D41: QUARANTINED | E41: 6 | F41: TABLE | G41: TABLE_BANDS | H41: I/BRL#s6: PASS Δ0.00 · II/BRL#s8: PASS Δ0.00 · IV/BRL#s14: FAIL Δ-2137482.09 · III/BRL: FAIL Δ-741097.28 | I41: 2024-12-16 | K41: arquivos.integrawebsites.com.br | L41: https://arquivos.integrawebsites.com.br/66886/9170dba63d72405b67b006af1763ed17.pdf

Sheet Diff vs Drive sheet
A1: Creditor (old sheet) | B1: CNPJ (old) | C1: Case | D1: OLD amount (R$) | E1: NEW class III face, root sum (R$) | F1: Delta (R$) | G1: Verdict | H1: Old status | I1: Why
A2: VINICOLA CAMPESTRE LTDA | B2: 98521909000270 | C2: 0008526-45.2025.8.17.2001 | D2: 9558482.8 | E2: 13980346 | F2: 4421862.7 | G2: CHANGED | I2: 2 claims summed on the 8-digit root (2 establishments)
A3: ADDIANTE S.A | B3: 48430290000130 | C3: 0804401-51.2025.8.14.0039 | D3: 7135517 | E3: 7135517 | F3: 0 | G3: SAME
A4: SEMPRE AGTECH LTDA | B4: 09536120000263 | C4: 0804401-51.2025.8.14.0039 | D4: 2037617 | E4: 2037617 | F4: 0 | G4: SAME | H4: E-mailed
A5: FERTILIZANTES TOCANTINS S.A | B5: 05571228000155 | C5: 0804401-51.2025.8.14.0039 | D5: 2016948.6 | E5: 2016948.6 | F5: 0 | G5: SAME | H5: E-mailed
A6: TAG INDUSTRIA E LAMINACAO LTDA | B6: 33233778000108 | C6: 8005129-09.2023.8.05.0039 | D6: 1981696 | E6: 64713515 | F6: 62731819 | G6: CHANGED | H6: CALLED | I6: 2 claims summed on the 8-digit root (1 establishments); likely dropped leading digit in old parse
A7: IBRAME INDUSTRIA BRASILEIRA DE METAIS S/A | B7: 60846599000534 | C7: 8005129-09.2023.8.05.0039 | D7: 815928.78 | E7: 1359881.3 | F7: 543952.52 | G7: CHANGED | H7: E-mailed | I7: 2 claims summed on the 8-digit root (1 establishments)
A8: COMARY INDUSTRIA DE BEBIDAS LTDA | B8: 29588019001316 | C8: 0008526-45.2025.8.17.2001 | D8: 407241.98 | E8: 407241.98 | F8: 0 | G8: SAME | H8: E-mailed
A9: REDE FAMILIA DE COMUNICACAO LTDA | B9: 48393755000120 | D9: 325723.67 | G9: NOT_IN_NEW_RUN | I9: case/document not harvested or below floor in this run
A10: MTC INCORPORACOES IMOBILIARIAS LTDA | B10: 12749549000162 | D10: 309000 | G10: NOT_IN_NEW_RUN | I10: case/document not harvested or below floor in this run
A11: OPTIMUM CONSULTORIA EM GESTAO PUBLICA E EMPRESARIAL LTDA | B11: 10925045000120 | C11: 0829315-43.2023.8.15.0001 | D11: 267635.55 | E11: 267635.55 | F11: 0 | G11: SAME
A12: SAFEGOLD GERENCIAMENTO DE CAPITAL LTDA | B12: 13177802000113 | D12: 203501.15 | G12: NOT_IN_NEW_RUN | I12: case/document not harvested or below floor in this run
A13: IRON COMEX LTDA | B13: 43464332000130 | C13: 0008526-45.2025.8.17.2001 | D13: 184223.97 | E13: 334279.01 | F13: 150055.04 | G13: CHANGED | I13: 2 claims summed on the 8-digit root (2 establishments)
A14: GEDOZ COMERCIO DE FERROS LTDA | B14: 87821278000299 | D14: 178822.7 | G14: NOT_IN_NEW_RUN | I14: case/document not harvested or below floor in this run
A15: BELMAN COMERCIO DE ACOS LTDA | B15: 02925166000144 | D15: 152754.49 | G15: NOT_IN_NEW_RUN | I15: case/document not harvested or below floor in this run
A16: M.C. ARRUDA ADMINISTRADORA DE BENS S.A. | B16: 14724478000179 | C16: 0008526-45.2025.8.17.2001 | D16: 107500 | E16: 107500 | F16: 0 | G16: SAME
A17: ATEM'S DISTRIBUIDORA DE PETROLEO S.A. | B17: 03987364000103 | C17: 0652260-87.2018.8.04.0001 | D17: 103343.93 | G17: NOT_IN_NEW_RUN | I17: case/document not harvested or below floor in this run
A18: ACO CEARENSE INDUSTRIAL LTDA | B18: 00990842000308 | C18: 0800778-16.2023.8.20.5104 | D18: 99326.74 | G18: NOT_IN_NEW_RUN | I18: case/document not harvested or below floor in this run
A19: EMPRESA DE TERMOPLASTICOS DO NORDESTE ETENO LTDA | B19: 08516950000185 | C19: 0800778-16.2023.8.20.5104 | D19: 96123.94 | G19: NOT_IN_NEW_RUN | I19: case/document not harvested or below floor in this run
A20: VEX PAINEIS LTDA | B20: 08142786000193 | C20: 8005129-09.2023.8.05.0039 | D20: 90775 | G20: NOT_IN_NEW_RUN | I20: case/document not harvested or below floor in this run
A21: HABILIS SERVICOS E TREINAMENTOS EM TECNOLOGIA LTDA | B21: 34720351000199 | C21: 0008526-45.2025.8.17.2001 | D21: 88848.14 | G21: NOT_IN_NEW_RUN | I21: case/document not harvested or below floor in this run
A22: MEGA PACK PLASTICOS S.A | B22: 19631376000203 | C22: 0800778-16.2023.8.20.5104 | D22: 84000 | G22: NOT_IN_NEW_RUN | I22: case/document not harvested or below floor in this run
A23: AVANTE ADMINISTRACAO E COBRANCA LTDA | B23: 07918102000130 | C23: 8005129-09.2023.8.05.0039 | D23: 82500 | G23: NOT_IN_NEW_RUN | I23: case/document not harvested or below floor in this run
A24: SIND DOS TRABS NAS INDS MET MEC E DE MAT ELETRIC DE CXS | B24: 88662267000195 | D24: 72683.87 | G24: NOT_IN_NEW_RUN | I24: case/document not harvested or below floor in this run
A25: ATENA OPERADORA TURISTICA LTDA. | B25: 21575389000173 | C25: 0820780-23.2026.8.14.0301 | D25: 59285.71 | G25: NOT_IN_NEW_RUN | I25: case/document not harvested or below floor in this run
A26: DOMINIK COMERCIO E INDUSTRIA DE METAIS E EQUIPAMENTOS LTDA | B26: 72332794000363 | C26: 8005129-09.2023.8.05.0039 | D26: 56421.22 | G26: NOT_IN_NEW_RUN | I26: case/document not harvested or below floor in this run
A27: FUSOPAR PARAFUSOS LTDA | B27: 89135073000102 | D27: 55215.92 | G27: NOT_IN_NEW_RUN | I27: case/document not harvested or below floor in this run
A28: BRASKEM S.A | B28: 42150391003005 | C28: 0800778-16.2023.8.20.5104 | D28: 46729.62 | G28: NOT_IN_NEW_RUN | I28: case/document not harvested or below floor in this run
A29: TRICHES FERRO E ACO LTDA | B29: 88610605000145 | D29: 41683.03 | G29: NOT_IN_NEW_RUN | I29: case/document not harvested or below floor in this run
A30: SIDERURGICA NORTE BRASIL S/A | B30: 07933914000154 | C30: 0800778-16.2023.8.20.5104 | D30: 40552.92 | G30: NOT_IN_NEW_RUN | I30: case/document not harvested or below floor in this run
A31: MULTIPLAX INDUSTRIA E COMERCIO DE PLASTICOS LTDA | B31: 09665178000550 | C31: 0800778-16.2023.8.20.5104 | D31: 38625 | G31: NOT_IN_NEW_RUN | I31: case/document not harvested or below floor in this run
A32: INDUSTRIA DE TRANSFORMADORES AMAZONAS LTDA | B32: 15815491000104 | C32: 0532018-89.2024.8.04.0001 | D32: 37576.45 | G32: NOT_IN_NEW_RUN | I32: case/document not harvested or below floor in this run
A33: GRAFICA E EDITORA 3 DE MAIO LTDA | B33: 76817808000128 | D33: 33089.33 | G33: NOT_IN_NEW_RUN | I33: case/document not harvested or below floor in this run
A34: POLIMAQUINAS INDUSTRIA E COMERCIO LIMITADA | B34: 46142725000115 | C34: 0800778-16.2023.8.20.5104 | D34: 32399.97 | G34: NOT_IN_NEW_RUN | I34: case/document not harvested or below floor in this run
A35: ROTA SUL TRANSPORTE DE CARGAS LTDA | B35: 02442313000125 | D35: 31955.15 | G35: NOT_IN_NEW_RUN | I35: case/document not harvested or below floor in this run
A36: GEOFUSION SISTEMAS E SERVICOS DE INFORMATICA LTDA | B36: 10502273000198 | C36: 0008526-45.2025.8.17.2001 | D36: 30854.72 | G36: NOT_IN_NEW_RUN | I36: case/document not harvested or below floor in this run
A37: ELENKO SPORTS LTDA | B37: 21317529000103 | C37: 0820780-23.2026.8.14.0301 | D37: 27613.14 | G37: NOT_IN_NEW_RUN | I37: case/document not harvested or below floor in this run
A38: VALGROUP AM INDUSTRIA DE MASTERBATCH LTDA. | B38: 03071894000360 | C38: 0800778-16.2023.8.20.5104 | D38: 26655 | G38: NOT_IN_NEW_RUN | I38: case/document not harvested or below floor in this run
A39: FEDERAL EXPRESS CORPORATION | B39: 00676486000182 | D39: 26451.14 | G39: NOT_IN_NEW_RUN | I39: case/document not harvested or below floor in this run
A40: UNIONLOG TRANSPORTES LTDA | B40: 20919807000130 | D40: 26280.65 | G40: NOT_IN_NEW_RUN | I40: case/document not harvested or below floor in this run
A41: D'MARI - LOCACAO, TRANSPORTES E LOGISTICA LTDA | B41: 11970436000120 | C41: 0008526-45.2025.8.17.2001 | D41: 25714.19 | G41: NOT_IN_NEW_RUN | I41: case/document not harvested or below floor in this run
A42: ALUVID - INDUSTRIA E COMERCIO DE ALUMINIO E VIDROS LTDA | B42: 13158783000188 | C42: 0800778-16.2023.8.20.5104 | D42: 25178.72 | G42: NOT_IN_NEW_RUN | I42: case/document not harvested or below floor in this run
A43: TRANSPORTES CRISTOFOLI LTDA | B43: 88670104000154 | D43: 22603.62 | G43: NOT_IN_NEW_RUN | I43: case/document not harvested or below floor in this run
A44: IBOPE REPUCOM PESQUISAS ESPORTIVAS LTDA. | B44: 04618228000109 | C44: 0820780-23.2026.8.14.0301 | D44: 22145.1 | G44: NOT_IN_NEW_RUN | I44: case/document not harvested or below floor in this run
A45: SERVICO SOCIAL DA INDUSTRIA DA CONSTRUCAO C DE MANAUS | B45: 63692321000114 | C45: 0532018-89.2024.8.04.0001 | D45: 20755.62 | G45: NOT_IN_NEW_RUN | I45: case/document not harvested or below floor in this run
A46: SERASA S.A. | B46: 62173620009306 | D46: 20283.11 | G46: NOT_IN_NEW_RUN | I46: case/document not harvested or below floor in this run
A47: GRECCHI ADVOGADOS ASSOCIADOS | B47: 06119227000137 | D47: 20000 | G47: NOT_IN_NEW_RUN | I47: case/document not harvested or below floor in this run
A48: DANIEL ARRUDA ARQUITETOS SS LTDA | B48: 13384111000190 | C48: 0532018-89.2024.8.04.0001 | D48: 18750 | G48: NOT_IN_NEW_RUN | I48: case/document not harvested or below floor in this run
A49: SKA AUTOMACAO DE ENGENHARIAS LTDA | B49: 81329823000167 | D49: 17678.32 | G49: NOT_IN_NEW_RUN | I49: case/document not harvested or below floor in this run
A50: POLYBRAS - POLIMEROS BRASILEIROS LTDA | B50: 17799898000102 | C50: 0800778-16.2023.8.20.5104 | D50: 17457.66 | G50: NOT_IN_NEW_RUN | I50: case/document not harvested or below floor in this run
A51: DELL COMPUTADORES DO BRASIL LTDA | B51: 72381189001001 | C51: 0532018-89.2024.8.04.0001 | D51: 17118.62 | G51: NOT_IN_NEW_RUN | I51: case/document not harvested or below floor in this run
A52: WIRECARD BRAZIL TECNOLOGIA LTDA | B52: 08718431000108 | D52: 16692.2 | G52: NOT_IN_NEW_RUN | I52: case/document not harvested or below floor in this run
A53: AVALARA BRASIL - ASSESSORIA E CONSULTORIA TRIBUTARIA E TECNOLOGICA LTDA | B53: 24918171000162 | C53: 0008526-45.2025.8.17.2001 | D53: 16537.5 | G53: NOT_IN_NEW_RUN | I53: case/document not harvested or below floor in this run
A54: TINTAS IQUINE LTDA. | B54: 09722463000131 | C54: 0800778-16.2023.8.20.5104 | D54: 16320.88 | G54: NOT_IN_NEW_RUN | I54: case/document not harvested or below floor in this run
A55: NOVA TRIGO RESINAS TERMOPLASTICAS LTDA. | B55: 07094272000147 | D55: 16275 | G55: NOT_IN_NEW_RUN | I55: case/document not harvested or below floor in this run
A56: BRASIL QUIMICA E MINERACAO INDUSTRIAL LTDA | B56: 24373276000183 | C56: 0800778-16.2023.8.20.5104 | D56: 13973.5 | G56: NOT_IN_NEW_RUN | I56: case/document not harvested or below floor in this run
A57: MARTINELLI ADVOCACIA EMPRESARIAL | B57: 01650515000108 | D57: 12843.96 | G57: NOT_IN_NEW_RUN | I57: case/document not harvested or below floor in this run
A58: CERAMICA SERRA AZUL LTDA | B58: 07378783000190 | C58: 0800778-16.2023.8.20.5104 | D58: 12517.38 | G58: NOT_IN_NEW_RUN | I58: case/document not harvested or below floor in this run
A59: CONDOMINIO INDUSTRIAL DO RIBEIRAO | B59: 05646097000128 | C59: 8005129-09.2023.8.05.0039 | D59: 12317.46 | G59: NOT_IN_NEW_RUN | I59: case/document not harvested or below floor in this run
A60: CLARO S.A. | B60: 40432544000147 | C60: 0652260-87.2018.8.04.0001 | D60: 12152.61 | G60: NOT_IN_NEW_RUN | I60: case/document not harvested or below floor in this run
A61: CASA DO ELETRICISTA LTDA | B61: 04415154000103 | C61: 0652260-87.2018.8.04.0001 | D61: 12152.61 | G61: NOT_IN_NEW_RUN | I61: case/document not harvested or below floor in this run
A62: MACROPECAS COMERCIAL LTDA | B62: 10179869000107 | C62: 0652260-87.2018.8.04.0001 | D62: 11986.75 | G62: NOT_IN_NEW_RUN | I62: case/document not harvested or below floor in this run
A63: GEOFUSION SISTEMAS E SERVICOS DE INFORMATICA LTDA | B63: 10502273000198 | C63: 0532018-89.2024.8.04.0001 | D63: 10785.17 | G63: NOT_IN_NEW_RUN | I63: case/document not harvested or below floor in this run
A64: CONDOMINIO LEVE-CASTANHEIRA RESIDENCIAL PARK | B64: 30686394000144 | C64: 0532018-89.2024.8.04.0001 | D64: 10707.09 | G64: NOT_IN_NEW_RUN | I64: case/document not harvested or below floor in this run
A65: RESIDENCIAL PREDILETTO PARQUE DEZ | B65: 43916601000151 | C65: 0532018-89.2024.8.04.0001 | D65: 10222.25 | G65: NOT_IN_NEW_RUN | I65: case/document not harvested or below floor in this run
A66: MUDANCAS SAMUCA LTDA | B66: 04559137000131 | D66: 9900 | G66: NOT_IN_NEW_RUN | I66: case/document not harvested or below floor in this run
A67: RECOM ETIQUETAS E EMBALAGENS LTDA | B67: 53797932000173 | C67: 8005129-09.2023.8.05.0039 | D67: 9764.48 | G67: NOT_IN_NEW_RUN | I67: case/document not harvested or below floor in this run
A68: TRANSPORTES MOBILINE LTDA | B68: 03341775000119 | D68: 9698.61 | G68: NOT_IN_NEW_RUN | I68: case/document not harvested or below floor in this run
A69: LOCALIZA FLEET S.A. | B69: 02286479000108 | C69: 8005129-09.2023.8.05.0039 | D69: 9529.6 | G69: NOT_IN_NEW_RUN | I69: case/document not harvested or below floor in this run
A70: AIR LIQUIDE BRASIL LTDA | B70: 00331788005420 | D70: 9171.65 | G70: NOT_IN_NEW_RUN | I70: case/document not harvested or below floor in this run
A71: ATUAL CARGAS TRANSPORTES LTDA | B71: 08848231001133 | D71: 8912.48 | G71: NOT_IN_NEW_RUN | I71: case/document not harvested or below floor in this run
A72: FRANCIMAR REPRESENTACOES LTDA | B72: 76823467000284 | D72: 8471.35 | G72: NOT_IN_NEW_RUN | I72: case/document not harvested or below floor in this run
A73: SERRA BRASIL TRANSPORTES LTDA | B73: 15334893000189 | D73: 8329.34 | G73: NOT_IN_NEW_RUN | I73: case/document not harvested or below floor in this run
A74: GOUVEA & CAMPANA LTDA | B74: 11949543000176 | D74: 7772 | G74: NOT_IN_NEW_RUN | I74: case/document not harvested or below floor in this run
A75: TELEFONICA CLOUD E TECNOLOGIA DO BRASIL S.A. | B75: 35473014000107 | C75: 0804401-51.2025.8.14.0039 | D75: 7694.61 | G75: NOT_IN_NEW_RUN | I75: case/document not harvested or below floor in this run
A76: ACO CEARENSE COMERCIAL LTDA | B76: 07557333001056 | C76: 0800778-16.2023.8.20.5104 | D76: 7605.9 | G76: NOT_IN_NEW_RUN | I76: case/document not harvested or below floor in this run
A77: GPBR PARTICIPACOES LTDA. | B77: 15664649000184 | C77: 0008526-45.2025.8.17.2001 | D77: 7338.93 | G77: NOT_IN_NEW_RUN | I77: case/document not harvested or below floor in this run
A78: TRANSPORTES RODOVIA SUL LTDA | B78: 90863325000190 | D78: 6981.59 | G78: NOT_IN_NEW_RUN | I78: case/document not harvested or below floor in this run
A79: PLANAC I. T. - COMERCIO DIGITAL LTDA | B79: 05592445000121 | C79: 0532018-89.2024.8.04.0001 | D79: 6971.81 | G79: NOT_IN_NEW_RUN | I79: case/document not harvested or below floor in this run
A80: BAKOF PLASTICOS LTDA EM RECUPERACAO JUDICIAL | B80: 91967067000317 | C80: 0800778-16.2023.8.20.5104 | D80: 6483 | G80: NOT_IN_NEW_RUN | I80: case/document not harvested or below floor in this run
A81: NANO EMBALAGENS LTDA | B81: 04577829000102 | D81: 5589.04 | G81: NOT_IN_NEW_RUN | I81: case/document not harvested or below floor in this run
A82: DECORACAO CASA 4 COMERCIO DE MOVEIS LTDA. | B82: 16604239000100 | D82: 5038.28 | G82: NOT_IN_NEW_RUN | I82: case/document not harvested or below floor in this run
A83: ALUSUPRA ALUMINIO LTDA | B83: 08329905000111 | D83: 5024.32 | G83: NOT_IN_NEW_RUN | I83: case/document not harvested or below floor in this run
A84: CL SUL TRANSPORTES LTDA | B84: 08025373000390 | C84: 8005129-09.2023.8.05.0039 | D84: 4900 | G84: NOT_IN_NEW_RUN | I84: case/document not harvested or below floor in this run
A85: DISMAFER DISTRIBUIDORA DE MAQUINAS E FERRAMENTAS LTDA | B85: 04112126000109 | D85: 4783.1 | G85: NOT_IN_NEW_RUN | I85: case/document not harvested or below floor in this run
A86: BUSARELLO COMERCIO ATACADISTA DE EMBALAGENS LTDA | B86: 09037969000101 | D86: 4717.5 | G86: NOT_IN_NEW_RUN | I86: case/document not harvested or below floor in this run
A87: NEOGRID INFORMATICA LTDA | B87: 05794609000101 | C87: 0008526-45.2025.8.17.2001 | D87: 4699.29 | G87: NOT_IN_NEW_RUN | I87: case/document not harvested or below floor in this run
A88: CROPFERT INDUSTRIA DE FERTILIZANTES E AGROQUIMICOS LTDA | B88: 18373437000136 | C88: 0804401-51.2025.8.14.0039 | D88: 467392 | E88: 467392 | F88: 0 | G88: SAME | H88: 18373437000136
A89: FRETEFY TECNOLOGIA S.A. | B89: 32998118000147 | C89: 0008526-45.2025.8.17.2001 | D89: 4317.08 | G89: NOT_IN_NEW_RUN | H89: 32998118000147 | I89: case/document not harvested or below floor in this run
A90: COLLEONY PRODUTOS E SISTEMAS PARA HIGIENIZACAO LTDA | B90: 02200306000117 | D90: 4085 | G90: NOT_IN_NEW_RUN | H90: 02200306000117 | I90: case/document not harvested or below floor in this run
A91: COMERCIAL DE BORRACHAS FASISA LTDA | B91: 88827555000152 | D91: 3764.8 | G91: NOT_IN_NEW_RUN | H91: 88827555000152 | I91: case/document not harvested or below floor in this run
A92: METALURGICA SCHIOPPA LTDA | B92: 61174652000137 | D92: 3297.2 | G92: NOT_IN_NEW_RUN | H92: 61174652000137 | I92: case/document not harvested or below floor in this run
A93: LEITZ FERRAMENTAS PARA MADEIRA LTDA | B93: 90815150000146 | D93: 3005.66 | G93: NOT_IN_NEW_RUN | H93: 90815150000146 | I93: case/document not harvested or below floor in this run
A94: ID CARGO BRASIL LTDA | B94: 20306967000103 | D94: 2991.7 | G94: NOT_IN_NEW_RUN | H94: 20306967000103 | I94: case/document not harvested or below floor in this run
A95: INDUSTRIAS ESPLANADA LTDA | B95: 04534459000126 | C95: 0652260-87.2018.8.04.0001 | D95: 2945 | G95: NOT_IN_NEW_RUN | H95: 04534459000126 | I95: case/document not harvested or below floor in this run
A96: DOMINALOG EXPRESS LOGISTICA INTEGRADA LTDA | B96: 18247063000102 | D96: 2892.1 | G96: NOT_IN_NEW_RUN | H96: 18247063000102 | I96: case/document not harvested or below floor in this run
A97: SOLIDES TECNOLOGIA S/A | B97: 10461302000110 | C97: 0008526-45.2025.8.17.2001 | D97: 2857.35 | G97: NOT_IN_NEW_RUN | H97: 10461302000110 | I97: case/document not harvested or below floor in this run
A98: MOVIDA LOCACAO DE VEICULOS S.A. | B98: 07976147000160 | D98: 2807.36 | G98: NOT_IN_NEW_RUN | H98: 07976147000160 | I98: case/document not harvested or below floor in this run
A99: TELEFONICA BRASIL S.A. | B99: 02558157001720 | D99: 2784.27 | G99: NOT_IN_NEW_RUN | H99: 02558157001720 | I99: case/document not harvested or below floor in this run
A100: ARQUIVEI SERVICOS ON LINE LTDA | B100: 19427033000140 | C100: 0008526-45.2025.8.17.2001 | D100: 2671.65 | G100: NOT_IN_NEW_RUN | H100: 19427033000140 | I100: case/document not harvested or below floor in this run
...
