Workbook

Sheet README
A1: ANTEPARO — CALL SHEET
A2: Run 20260903T230425Z-e7c9a7 · generated 2026-09-05 · 559 leads ≥ R$200k · 236 pooling leads (R$100–200k) · 1199 source documents · 527 cases
A4: WHAT EACH ROW IS
A5: One company × one recovery case. The company holds class III (trade) credit against the debtor, admitted in the court's own creditor list. All establishments of the company (same 8-digit CNPJ root) are summed.
A7: THE NUMBER
A8: 'Class III face' is the admitted value AS PRINTED in the court document — what the company is OWED, updated only to the filing date (art. 9 II). It is NOT what will be paid.
A9: 'OUR QUOTE' is a model: face → assumed plan terms → discounted at the investor IRR → fund price → our share. Edit the Assumptions tab. It is not court data.
A11: PROOF OF CLAIM (green columns)
A12: Click 'PROOF: source document', go to the page/row listed, and read the value as printed. If a seller asks 'how did you get this?', that link is the answer.
A13: 'Reconciled' = OK means the document's extracted class totals matched its own printed totals within 0.5%. OK_NO_TOTALS means the document prints no totals — the number was read from its own row but could not be cross-checked; quote with that caveat.
A15: DECISION-MAKER
A16: From the Receita Federal partner register (sócio-administrador / administrador / diretor / presidente). Phone and email are the company's registry contact. Confidence LOW = registry only; nothing here was guessed or looked up from memory.
... A22: Individuals (CPF), banks (CNAE 64–66), public entities, inactive companies, foreign-currency claims, extraconcursal sections, quarantined documents. They remain in the CSV tables with flags.

Sheet Assumptions
A1: PRICING ASSUMPTIONS — edit the yellow cells; every quote on the call sheet recalculates
A3: Target investor IRR (annual) | B3: 0.25 | F3: Fund price = face × recovery% ÷ (1+IRR)^(years to payment). A fund needing 25% IRR on a plan paying 30% over years 3–10 pays ~8 cents, not 25 — check the 7 buyers' real numbers against this.
A4: Buy price as share of fund price (we pay 60% → 0.60) | B4: 0.6 | F4: Our quote = fund price × this share. The doc rule is 60% of mandate price; expected 55–70% once Gate 6 data exists.
A6: Debtor band | B6: Class III recovery % of face | C6: Grace (years) | D6: Term (years) | E6: Plan lag (years) | F6: Note
A7: A | B7: 0.4 | C7: 2 | D7: 8 | E7: 1.5 | F7: Recovery GRANTED (art. 58): plan approved by the creditors and granted by the court; payments run from the grant
A8: B | B8: 0.3 | C8: 2 | D8: 8 | E8: 1.5 | F8: Live case filed within the last 2 years, plan filed (art. 53) or pending — not yet granted; the payment clock has not started
A9: C | B9: 0.15 | C9: 3 | D9: 10 | E9: 2.5 | F9: Older case (filed >2 y ago) or dormant/closed with no grant seen: a plan very probably exists but is not in our documents — check the docket before quoting
A10: D | B10: 0.03 | C10: 0 | D10: 0 | E10: 6 | F10: Not in the book: falência decreed, RJ extinguished, or the company is closed (baixada) at RFB — rows go to EXCLUDED (review)
A11: U | B11: 0.25 | C11: 3 | D11: 8 | E11: 2.5 | F11: Unresolved: debtor or case not identified — kept on PRICING HOLD (zero quote) until the case is found
A13: Everything in this tab is an ASSUMPTION, not court data. The face value on the call sheet IS court data — it links to the page.

Sheet Call List
A1: Rank | B1: Status | C1: Owner | D1: Attempts | E1: Last touch | F1: Next action | G1: Next date | H1: Notes | I1: Company (RFB) | J1: Name as printed | K1: CNPJ root | L1: Establishment CNPJs | M1: Class III face (R$) | N1: Claims | O1: Debtor band | P1: Stage | Q1: Case filed | R1: Years since filing | S1: Est. recovery % | T1: Years to payment (est.) | U1: Fund price @ IRR (R$) | V1: Fund price (cents) | W1: OUR QUOTE (R$) | X1: Quote (cents) | Y1: Debtor | Z1: Case number | AA1: Court | AB1: Administrator (site) | AC1: Decision-maker | AD1: Role | AE1: Phone | AF1: Phone 2 | AG1: Email | AH1: UF | AI1: City | AJ1: CNAE | AK1: Porte | AL1: Situação | AM1: PROOF: source document | AN1: Page / row | AO1: Value as printed | AP1: Which list | AQ1: Published | AR1: Reconciled | AS1: Data flags | AT1: Doc id
A2: 1 | B2: NEW | D2: 0 | I2: PETROLEO BRASILEIRO S A PETROBRAS | J2: Petróleo Brasileiro S.A. (Petrobras) | K2: 33000167 | L2: 33000167000101 | M2: 3.3005476e+08 | N2: 1 | O2: B | Q2: 45756 | R2: =IF(Q2="","",ROUND((TODAY()-Q2)/365.25,1)) | S2: =IFERROR(VLOOKUP(O2,Assumptions!$A$7:$F$11,2,FALSE),0.25) | T2: =IF(O2="A",MAX(1,IFERROR(VLOOKUP(O2,Assumptions!$A$7:$F$11,3,FALSE),3)+IFERROR(VLOOKUP(O2,Assumptions!$A$7:$F$11,4,FALSE),8)/2-MAX(0,IF(R2="",0,R2)-IFERROR(VLOOKUP(O2,Assumptions!$A$7:$F$11,5,FALSE),1.5))),IFERROR(VLOOKUP(O2,Assumptions!$A$7:$F$11,5,FALSE),2.5)+IFERROR(VLOOKUP(O2,Assumptions!$A$7:$F$11,3,FALSE),3)+IFERROR(VLOOKUP(O2,Assumptions!$A$7:$F$11,4,FALSE),8)/2) | U2: =M2*S2/(1+Assumptions!$B$3)^T2 | V2: =IF(M2=0,"",ROUND(U2/M2*100,1)) | W2: =U2*Assumptions!$B$4 | X2: =IF(M2=0,"",ROUND(W2/M2*100,1)) | Y2: GRUPO EGESA (EGESA ENG S.A, EGESUR PART E EMP S.A, MATRIX INFRA LTDA, BEMVIVER ENG AMBIENTAL E SERV LTDA, DKF CONST E EMP LTDA, EGEPEL LTDA, ETR ASSESSORIA EMP E PART LTDA, MVT ENG E SERV LTDA, PARQUES DO VALE LTDA, ELMO RIBEIRO E ANA RIBEIRO) | Z2: 5088952-81.2025.8.13.0024 | AA2: TJMG | AB2: scalzilliaj.com.br | AC2: MAGDA MARIA DE REGINA CHAMBRIARD | AD2: Presidente | AE2: (21) 2166-0000 | AH2: RJ | AI2: RIO DE JANEIRO | AJ2: Extração de petróleo e gás natural | AK2: DEMAIS | AL2: ATIVA | AM2: https://scalzilliaj.com.br/sgc/download.php?file=files/processo_documento/processo_documento09514021082025_1_.pdf&nome=04 - Relação de credores das Recuperandas | AN2: p71 r9 | AO2: p71: R$ 330.054.762,86 | AP2: DEBTOR_LIST | AR2: OK | AS2: ROWS:p71r9 VALUE_COL:Valor_Atualizado CASE_NUMBER_CORRECTED CASE_FROM_PORTAL | AT2: 24ed98480a57
A3: 2 | B3: NEW | D3: 0 | I3: DM CONSTRUTORA DE OBRAS LTDA | J3: DM Construtora de Obras LTDA | K3: 76483726 | L3: 76483726000194 | M3: 1.7805218e+08 | N3: 1 | O3: B | P3: ACTIVE | Q3: 45833 | R3: =IF(Q3="","",ROUND((TODAY()-Q3)/365.25,1)) | S3: =IFERROR(VLOOKUP(O3,Assumptions!$A$7:$F$11,2,FALSE),0.25) | T3: =IF(O3="A",MAX(1,IFERROR(VLOOKUP(O3,Assumptions!$A$7:$F$11,3,FALSE),3)+IFERROR(VLOOKUP(O3,Assumptions!$A$7:$F$11,4,FALSE),8)/2-MAX(0,IF(R3="",0,R3)-IFERROR(VLOOKUP(O3,Assumptions!$A$7:$F$11,5,FALSE),1.5))),IFERROR(VLOOKUP(O3,Assumptions!$A$7:$F$11,5,FALSE),2.5)+IFERROR(VLOOKUP(O3,Assumptions!$A$7:$F$11,3,FALSE),3)+IFERROR(VLOOKUP(O3,Assumptions!$A$7:$F$11,4,FALSE),8)/2) | U3: =M3*S3/(1+Assumptions!$B$3)^T3 | V3: =IF(M3=0,"",ROUND(U3/M3*100,1)) | W3: =U3*Assumptions!$B$4 | X3: =IF(M3=0,"",ROUND(W3/M3*100,1)) | Y3: GRUPO MARINGÁ PARK | Z3: 0016033-22.2025.8.16.0017 | AA3: TJPR | AB3: marquesadmjudicial.com.br | AC3: DENIZ ALBINO FANTIN | AD3: Sócio-Administrador | AE3: (41) 3313-8000 | AF3: (41) 3313-8090 | AH3: PR | AI3: CURITIBA | AJ3: Construção de rodovias e ferrovias | AK3: DEMAIS | AL3: ATIVA | AM3: https://marquesadmjudicial.com.br/sgc/download.php?file=files/processo_documento/processo_documento19270817122025_1_.pdf&nome=Relação Nominal de Credores AJ | AN3: p4 r8 | AO3: p4: R$ 178.052.183,86 | AP3: AJ_LIST | AQ3: 2025-12-17 | AR3: OK | AS3: ROWS:p4r8 | AT3: fcb10a251582
A4: 3 | B4: NEW | D4: 0 | I4: TAG INDUSTRIA E LAMINACAO LTDA | J4: TAG INDUSTRIA E LAMINACAO LTDA | K4: 33233778 | L4: 33233778000108 | M4: 64713515 | N4: 2 | O4: C | P4: ACTIVE | Q4: 45068 | R4: =IF(Q4="","",ROUND((TODAY()-Q4)/365.25,1)) | S4: =IFERROR(VLOOKUP(O4,Assumptions!$A$7:$F$11,2,FALSE),0.25) | T4: =IF(O4="A",MAX(1,IFERROR(VLOOKUP(O4,Assumptions!$A$7:$F$11,3,FALSE),3)+IFERROR(VLOOKUP(O4,Assumptions!$A$7:$F$11,4,FALSE),8)/2-MAX(0,IF(R4="",0,R4)-IFERROR(VLOOKUP(O4,Assumptions!$A$7:$F$11,5,FALSE),1.5))),IFERROR(VLOOKUP(O4,Assumptions!$A$7:$F$11,5,FALSE),2.5)+IFERROR(VLOOKUP(O4,Assumptions!$A$7:$F$11,3,FALSE),3)+IFERROR(VLOOKUP(O4,Assumptions!$A$7:$F$11,4,FALSE),8)/2) | U4: =M4*S4/(1+Assumptions!$B$3)^T4 | V4: =IF(M4=0,"",ROUND(U4/M4*100,1)) | W4: =U4*Assumptions!$B$4 | X4: =IF(M4=0,"",ROUND(W4/M4*100,1)) | Y4: Grupo Conduscabos | Z4: 8005129-09.2023.8.05.0039 | AA4: TJBA | AB4: assistjud.com.br | AC4: TIAGO RODRIGO DETTILIO | AD4: Administrador | AE4: (11) 4463-4833 | AH4: SP | AI4: SAO PAULO | AJ4: Outras atividades profissionais, científicas e técnicas não especificadas anteriormente | AK4: DEMAIS | AL4: ATIVA | AM4: https://assistjud.com.br/wp-content/uploads/elementor/forms/65098c80a5824.pdf | AN4: p10 r4; p19 r8 | AO4: p10: R$ 32.731.819,08; p19: R$ 31.981.695,98 | AP4: AJ_LIST | AQ4: 2023-09-18 | AR4: OK_NO_TOTALS | AS4: ROWS:p10r4,p19r8 UNRECONCILED_SOURCE | AT4: a0ae32a59c29
A5: 4 | B5: NEW | D5: 0 | I5: IBIPORA NEGOCIOS IMOBILIARIOS S.A. | J5: IBIPORA NEGOCIOS IMOBILIARIOS S.A. | K5: 19256534 | L5: 19256534000101 | M5: 45075483 | N5: 1 | O5: B | Q5: 45756 | R5: =IF(Q5="","",ROUND((TODAY()-Q5)/365.25,1)) | S5: =IFERROR(VLOOKUP(O5,Assumptions!$A$7:$F$11,2,FALSE),0.25) | T5: =IF(O5="A",MAX(1,IFERROR(VLOOKUP(O5,Assumptions!$A$7:$F$11,3,FALSE),3)+IFERROR(VLOOKUP(O5,Assumptions!$A$7:$F$11,4,FALSE),8)/2-MAX(0,IF(R5="",0,R5)-IFERROR(VLOOKUP(O5,Assumptions!$A$7:$F$11,5,FALSE),1.5))),IFERROR(VLOOKUP(O5,Assumptions!$A$7:$F$11,5,FALSE),2.5)+IFERROR(VLOOKUP(O5,Assumptions!$A$7:$F$11,3,FALSE),3)+IFERROR(VLOOKUP(O5,Assumptions!$A$7:$F$11,4,FALSE),8)/2) | U5: =M5*S5/(1+Assumptions!$B$3)^T5 | V5: =IF(M5=0,"",ROUND(U5/M5*100,1)) | W5: =U5*Assumptions!$B$4 | X5: =IF(M5=0,"",ROUND(W5/M5*100,1)) | Y5: GRUPO EGESA (EGESA ENG S.A, EGESUR PART E EMP S.A, MATRIX INFRA LTDA, BEMVIVER ENG AMBIENTAL E SERV LTDA, DKF CONST E EMP LTDA, EGEPEL LTDA, ETR ASSESSORIA EMP E PART LTDA, MVT ENG E SERV LTDA, PARQUES DO VALE LTDA, ELMO RIBEIRO E ANA RIBEIRO) | Z5: 5088952-81.2025.8.13.0024 | AA5: TJMG | AB5: scalzilliaj.com.br | AC5: JOSE JULIO COSTA NETO | AD5: Presidente | AE5: (31) 3586-9418 | AH5: MG | AI5: NOVA LIMA | AJ5: Compra e venda de imóveis próprios | AK5: DEMAIS | AL5: ATIVA | AM5: https://scalzilliaj.com.br/sgc/download.php?file=files/processo_documento/processo_documento09514021082025_1_.pdf&nome=04 - Relação de credores das Recuperandas | AN5: p68 r4 | AO5: p68: R$ 45.075.482,57 | AP5: DEBTOR_LIST | AR5: OK | AS5: ROWS:p68r4 VALUE_COL:Valor_Atualizado CASE_NUMBER_CORRECTED CASE_FROM_PORTAL | AT5: 24ed98480a57
A6: 5 | B6: NEW | D6: 0 | I6: COMPANHIA ESTADUAL DE DISTRIBUICAO DE ENERGIA ELETRICA - CEEE-D | J6: CIA.EST.DE ENERG.ELETRICA-CEE ( | K6: 08467115 | L6: 08467115000100 | M6: 31446844 | N6: 1 | O6: C | P6: ACTIVE | Q6: 44735 | R6: =IF(Q6="","",ROUND((TODAY()-Q6)/365.25,1)) | S6: =IFERROR(VLOOKUP(O6,Assumptions!$A$7:$F$11,2,FALSE),0.25) | T6: =IF(O6="A",MAX(1,IFERROR(VLOOKUP(O6,Assumptions!$A$7:$F$11,3,FALSE),3)+IFERROR(VLOOKUP(O6,Assumptions!$A$7:$F$11,4,FALSE),8)/2-MAX(0,IF(R6="",0,R6)-IFERROR(VLOOKUP(O6,Assumptions!$A$7:$F$11,5,FALSE),1.5))),IFERROR(VLOOKUP(O6,Assumptions!$A$7:$F$11,5,FALSE),2.5)+IFERROR(VLOOKUP(O6,Assumptions!$A$7:$F$11,3,FALSE),3)+IFERROR(VLOOKUP(O6,Assumptions!$A$7:$F$11,4,FALSE),8)/2) | U6: =M6*S6/(1+Assumptions!$B$3)^T6 | V6: =IF(M6=0,"",ROUND(U6/M6*100,1)) | W6: =U6*Assumptions!$B$4 | X6: =IF(M6=0,"",ROUND(W6/M6*100,1)) | Y6: ASSOCIAÇÃO DE CARIDADE SANTA CASA DO RIO GRANDE | Z6: 5012306-16.2022.8.21.0023 | AA6: TJRS | AB6: scalzilliaj.com.br | AC6: RIBERTO JOSE BARBANERA | AD6: Presidente | AE6: (98) 3217-8000 | AH6: RS | AI6: PORTO ALEGRE | AJ6: Distribuição de energia elétrica | AK6: DEMAIS | AL6: ATIVA | AM6: https://scalzilliaj.com.br/sgc/download.php?file=files/processo_documento/processo_documento09120721032023_1_.pdf&nome=15 - Edital do art. 7º, §2º e 53 da Lei 11.101/2005 (segunda lista de credores e recebimento do plano)) | AN6: p26 r26 | AO6: p26: R$ 31.446.843,91 | AP6: AJ_LIST | AQ6: 2023-03-21 | AR6: OK_NO_TOTALS | AS6: ROWS:p26r26 UNRECONCILED_SOURCE | AT6: ebfb999b457c
A7: 6 | B7: NEW | D7: 0 | I7: HYPERA S.A. | J7: Hypera S/A | K7: 02932074 | L7: 02932074004260 | M7: 25912508 | N7: 1 | O7: C | P7: ACTIVE | Q7: 44987 | R7: =IF(Q7="","",ROUND((TODAY()-Q7)/365.25,1)) | S7: =IFERROR(VLOOKUP(O7,Assumptions!$A$7:$F$11,2,FALSE),0.25) | T7: =IF(O7="A",MAX(1,IFERROR(VLOOKUP(O7,Assumptions!$A$7:$F$11,3,FALSE),3)+IFERROR(VLOOKUP(O7,Assumptions!$A$7:$F$11,4,FALSE),8)/2-MAX(0,IF(R7="",0,R7)-IFERROR(VLOOKUP(O7,Assumptions!$A$7:$F$11,5,FALSE),1.5))),IFERROR(VLOOKUP(O7,Assumptions!$A$7:$F$11,5,FALSE),2.5)+IFERROR(VLOOKUP(O7,Assumptions!$A$7:$F$11,3,FALSE),3)+IFERROR(VLOOKUP(O7,Assumptions!$A$7:$F$11,4,FALSE),8)/2) | U7: =M7*S7/(1+Assumptions!$B$3)^T7 | V7: =IF(M7=0,"",ROUND(U7/M7*100,1)) | W7: =U7*Assumptions!$B$4 | X7: =IF(M7=0,"",ROUND(W7/M7*100,1)) | Y7: GRUPO DP4 | Z7: 0005010-98.2023.8.16.0001 | AA7: TJPR | AB7: marquesadmjudicial.com.br | AC7: BRENO TOLEDO PIRES DE OLIVEIRA | AD7: Presidente | AE7: (62) 3878-8150 | AH7: SP | AI7: SAO PAULO | AJ7: Comércio atacadista de medicamentos e drogas de uso humano | AK7: DEMAIS | AL7: ATIVA | AM7: https://marquesadmjudicial.com.br/sgc/download.php?file=files/processo_documento/processo_documento15293208032024_1_.pdf&nome=Relação Nominal de Credores da AJ-Sintética | AN7: p26 r9 | AO7: p26: R$ 25.912.507,68 | AP7: AJ_LIST | AQ7: 2023-03-02 | AR7: QUARANTINED | AS7: PARTIAL_DOC_CLASS_III_RECONCILED ROWS:p26r9 | AT7: b465a5d11eec
A8: 7 | B8: NEW | D8: 0 | I8: ADLIM-TERCEIRIZACAO EM SERVICOS LTDA - EM RECUPERACAO JUDICIAL | J8: ADLIM TERCEIRIZACAO EM SERVICOS LTDA, CPF/CNPJ/OAB nº | K8: 11436813 | L8: 11436813000145 | M8: 20647588 | N8: 2 | O8: B | P8: ACTIVE | Q8: 45349 | R8: =IF(Q8="","",ROUND((TODAY()-Q8)/365.25,1)) | S8: =IFERROR(VLOOKUP(O8,Assumptions!$A$7:$F$11,2,FALSE),0.25) | T8: =IF(O8="A",MAX(1,IFERROR(VLOOKUP(O8,Assumptions!$A$7:$F$11,3,FALSE),3)+IFERROR(VLOOKUP(O8,Assumptions!$A$7:$F$11,4,FALSE),8)/2-MAX(0,IF(R8="",0,R8)-IFERROR(VLOOKUP(O8,Assumptions!$A$7:$F$11,5,FALSE),1.5))),IFERROR(VLOOKUP(O8,Assumptions!$A$7:$F$11,5,FALSE),2.5)+IFERROR(VLOOKUP(O8,Assumptions!$A$7:$F$11,3,FALSE),3)+IFERROR(VLOOKUP(O8,Assumptions!$A$7:$F$11,4,FALSE),8)/2) | U8: =M8*S8/(1+Assumptions!$B$3)^T8 | V8: =IF(M8=0,"",ROUND(U8/M8*100,1)) | W8: =U8*Assumptions!$B$4 | X8: =IF(M8=0,"",ROUND(W8/M8*100,1)) | Y8: GRUPO ADLIM | Z8: 0019761-43.2024.8.17.2001 | AA8: TJPE | AB8: lrflideres.com.br | AC8: JONAS ALVARENGA DA SILVA | AD8: Sócio-Administrador | AH8: PE | AI8: BEZERROS | AJ8: Fornecimento e gestão de recursos humanos para terceiros | AK8: DEMAIS | AL8: ATIVA | AM8: https://lrflideres.com.br/wp-content/plugins/download-attachments/includes/download.php?id=6051 | AN8: p85 r37; p97 r26 | AO8: p85: R$ 13674501,07; p97: R$ 6973087,07 | AP8: AJ_LIST | AQ8: 2024-08-12 | AR8: QUARANTINED | AS8: PARTIAL_DOC_CLASS_III_RECONCILED ROWS:p85r37,p97r26 | AT8: a32497797bac
A9: 8 | B9: NEW | D9: 0 | I9: SPC BRASIL S.A. | J9: BRASIL S.A | K9: 29341643 | L9: 29341643000342 | M9: 18875474 | N9: 1 | O9: B | P9: ACTIVE | Q9: 46048 | R9: =IF(Q9="","",ROUND((TODAY()-Q9)/365.25,1)) | S9: =IFERROR(VLOOKUP(O9,Assumptions!$A$7:$F$11,2,FALSE),0.25) | T9: =IF(O9="A",MAX(1,IFERROR(VLOOKUP(O9,Assumptions!$A$7:$F$11,3,FALSE),3)+IFERROR(VLOOKUP(O9,Assumptions!$A$7:$F$11,4,FALSE),8)/2-MAX(0,IF(R9="",0,R9)-IFERROR(VLOOKUP(O9,Assumptions!$A$7:$F$11,5,FALSE),1.5))),IFERROR(VLOOKUP(O9,Assumptions!$A$7:$F$11,5,FALSE),2.5)+IFERROR(VLOOKUP(O9,Assumptions!$A$7:$F$11,3,FALSE),3)+IFERROR(VLOOKUP(O9,Assumptions!$A$7:$F$11,4,FALSE),8)/2) | U9: =M9*S9/(1+Assumptions!$B$3)^T9 | V9: =IF(M9=0,"",ROUND(U9/M9*100,1)) | W9: =U9*Assumptions!$B$4 | X9: =IF(M9=0,"",ROUND(W9/M9*100,1)) | Y9: GRUPO GLP | Z9: 0001639-09.2026.8.17.2810 | AA9: TJPE | AB9: recuperasolucoes.com | AC9: ROQUE PELLIZZARO JUNIOR | AD9: Presidente | AE9: (11) 3549-6800 | AH9: SP | AI9: BARUERI | AJ9: Portais, provedores de conteúdo e outros serviços de informação na internet | AK9: DEMAIS | AL9: ATIVA | AM9: https://recuperasolucoes.com/wp-content/plugins/download-attachments/includes/download.php?id=1597 | AN9: p13 r8 | AO9: p13: R$ 18.875.473,82 | AP9: DEBTOR_LIST | AQ9: 2026-05-21 | AR9: OK | AS9: ROWS:p13r8 | AT9: 5da7b77bb569
A10: 9 | B10: NEW | D10: 0 | I10: COMPANHIA RIOGRANDENSE DE SANEAMENTO - CORSAN | J10: CIA.RIOGRANDENSE SANEAMENTO CORSAN ( | K10: 92802784 | L10: 92802784000190 | M10: 18555955 | N10: 1 | O10: C | P10: ACTIVE | Q10: 44735 | R10: =IF(Q10="","",ROUND((TODAY()-Q10)/365.25,1)) | S10: =IFERROR(VLOOKUP(O10,Assumptions!$A$7:$F$11,2,FALSE),0.25) | T10: =IF(O10="A",MAX(1,IFERROR(VLOOKUP(O10,Assumptions!$A$7:$F$11,3,FALSE),3)+IFERROR(VLOOKUP(O10,Assumptions!$A$7:$F$11,4,FALSE),8)/2-MAX(0,IF(R10="",0,R10)-IFERROR(VLOOKUP(O10,Assumptions!$A$7:$F$11,5,FALSE),1.5))),IFERROR(VLOOKUP(O10,Assumptions!$A$7:$F$11,5,FALSE),2.5)+IFERROR(VLOOKUP(O10,Assumptions!$A$7:$F$11,3,FALSE),3)+IFERROR(VLOOKUP(O10,Assumptions!$A$7:$F$11,4,FALSE),8)/2) | U10: =M10*S10/(1+Assumptions!$B$3)^T10 | V10: =IF(M10=0,"",ROUND(U10/M10*100,1)) | W10: =U10*Assumptions!$B$4 | X10: =IF(M10=0,"",ROUND(W10/M10*100,1)) | Y10: ASSOCIAÇÃO DE CARIDADE SANTA CASA DO RIO GRANDE | Z10: 5012306-16.2022.8.21.0023 | AA10: TJRS | AB10: scalzilliaj.com.br | AC10: ANGELO AUGUSTO MENDES | AD10: Diretor | AE10: (05) 1215-5789 | AH10: RS | AI10: PORTO ALEGRE | AJ10: Captação, tratamento e distribuição de água | AK10: DEMAIS | AL10: ATIVA | AM10: https://scalzilliaj.com.br/sgc/download.php?file=files/processo_documento/processo_documento09120721032023_1_.pdf&nome=15 - Edital do art. 7º, §2º e 53 da Lei 11.101/2005 (segunda lista de credores e recebimento do plano)) | AN10: p26 r27 | AO10: p26: R$ 18.555.954,55 | AP10: AJ_LIST | AQ10: 2023-03-21 | AR10: OK_NO_TOTALS | AS10: ROWS:p26r27 UNRECONCILED_SOURCE | AT10: ebfb999b457c
A11: 10 | B11: NEW | D11: 0 | I11: DREYMOOR BRASIL COMERCIO DE FERTILIZANTES LTDA | J11: DREYMOOR BRASIL COMÉRCIO DE FERTILIZANTES LTDA | K11: 26419229 | L11: 26419229000159 | M11: 15134865 | N11: 1 | O11: D | Q11: 45862 | R11: =IF(Q11="","",ROUND((TODAY()-Q11)/365.25,1)) | S11: =IFERROR(VLOOKUP(O11,Assumptions!$A$7:$F$11,2,FALSE),0.25) | T11: =IF(O11="A",MAX(1,IFERROR(VLOOKUP(O11,Assumptions!$A$7:$F$11,3,FALSE),3)+IFERROR(VLOOKUP(O11,Assumptions!$A$7:$F$11,4,FALSE),8)/2-MAX(0,IF(R11="",0,R11)-IFERROR(VLOOKUP(O11,Assumptions!$A$7:$F$11,5,FALSE),1.5))),IFERROR(VLOOKUP(O11,Assumptions!$A$7:$F$11,5,FALSE),2.5)+IFERROR(VLOOKUP(O11,Assumptions!$A$7:$F$11,3,FALSE),3)+IFERROR(VLOOKUP(O11,Assumptions!$A$7:$F$11,4,FALSE),8)/2) | U11: =M11*S11/(1+Assumptions!$B$3)^T11 | V11: =IF(M11=0,"",ROUND(U11/M11*100,1)) | W11: =U11*Assumptions!$B$4 | X11: =IF(M11=0,"",ROUND(W11/M11*100,1)) | Y11: JOB FERTILIZANTES LTDA | Z11: 5000561-63.2025.8.24.0536 | AA11: TJSC | AB11: scalzilliaj.com.br | AC11: MAURICIO GIORDANI BODANESE | AD11: Administrador | AE11: (41) 3209-6613 | AH11: PR | AI11: CURITIBA | AJ11: Comércio atacadista de defensivos agrícolas, adubos, fertilizantes e corretivos do solo | AK11: DEMAIS | AL11: ATIVA | AM11: https://scalzilliaj.com.br/sgc/download.php?file=files/processo_documento/processo_documento13183320052026_1_.pdf&nome=10 - QGC Provisório - atualizado até Maio de 2026 | AN11: p1 r9 | AO11: p1: R$ 15.134.865,10 | AP11: QGC | AR11: OK_NO_TOTALS | AS11: CASE_NUMBER_MISSING ROWS:p1r9 UNRECONCILED_SOURCE VALUE_COL:Valor_Do_Crédito CASE_FROM_PORTAL | AT11: 8b4c169de629
A12: 11 | B12: NEW | D12: 0 | I12: FRESENIUS MEDICAL CARE LTDA | J12: FRESENIUS MEDICAL CARE LTDA | K12: 01440590 | L12: 01440590000136 | M12: 14567734 | N12: 1 | O12: U | R12: =IF(Q12="","",ROUND((TODAY()-Q12)/365.25,1)) | S12: =IFERROR(VLOOKUP(O12,Assumptions!$A$7:$F$11,2,FALSE),0.25) | T12: =IF(O12="A",MAX(1,IFERROR(VLOOKUP(O12,Assumptions!$A$7:$F$11,3,FALSE),3)+IFERROR(VLOOKUP(O12,Assumptions!$A$7:$F$11,4,FALSE),8)/2-MAX(0,IF(R12="",0,R12)-IFERROR(VLOOKUP(O12,Assumptions!$A$7:$F$11,5,FALSE),1.5))),IFERROR(VLOOKUP(O12,Assumptions!$A$7:$F$11,5,FALSE),2.5)+IFERROR(VLOOKUP(O12,Assumptions!$A$7:$F$11,3,FALSE),3)+IFERROR(VLOOKUP(O12,Assumptions!$A$7:$F$11,4,FALSE),8)/2) | U12: =M12*S12/(1+Assumptions!$B$3)^T12 | V12: =IF(M12=0,"",ROUND(U12/M12*100,1)) | W12: =U12*Assumptions!$B$4 | X12: =IF(M12=0,"",ROUND(W12/M12*100,1)) | Z12: (not found in document) | AB12: bernardobicalho.com.br | AC12: ANA LUCIA ZENKNER PERCIA | AD12: Administrador | AE12: (19) 3847-9700 | AF12: (19) 3847-9700 | AH12: SP | AI12: JAGUARIUNA | AJ12: Fabricação de medicamentos alopáticos para uso humano | AK12: DEMAIS | AL12: ATIVA | AM12: http://bernardobicalho.com.br/login/app/documents/Rela%C3%A7%C3%A3o%20de%20Credores/6.%20RVC-%20Nutricium%20-%20simplificada.pdf | AN12: p3 r16 | AO12: p3: R$ 14.567.733,99 | AP12: AJ_LIST | AR12: OK | AS12: CASE_NUMBER_MISSING ROWS:p3r16 | AT12: 6a92d74da333
A13: 12 | B13: NEW | D13: 0 | I13: VINICOLA CAMPESTRE LTDA | J13: VINICOLA CAMPESTRE LTDA | K13: 98521909 | L13: 98521909000190, 98521909000270 | M13: 13980346 | N13: 2 | O13: B | P13: ACTIVE | Q13: 45685 | R13: =IF(Q13="","",ROUND((TODAY()-Q13)/365.25,1)) | S13: =IFERROR(VLOOKUP(O13,Assumptions!$A$7:$F$11,2,FALSE),0.25) | T13: =IF(O13="A",MAX(1,IFERROR(VLOOKUP(O13,Assumptions!$A$7:$F$11,3,FALSE),3)+IFERROR(VLOOKUP(O13,Assumptions!$A$7:$F$11,4,FALSE),8)/2-MAX(0,IF(R13="",0,R13)-IFERROR(VLOOKUP(O13,Assumptions!$A$7:$F$11,5,FALSE),1.5))),IFERROR(VLOOKUP(O13,Assumptions!$A$7:$F$11,5,FALSE),2.5)+IFERROR(VLOOKUP(O13,Assumptions!$A$7:$F$11,3,FALSE),3)+IFERROR(VLOOKUP(O13,Assumptions!$A$7:$F$11,4,FALSE),8)/2) | U13: =M13*S13/(1+Assumptions!$B$3)^T13 | V13: =IF(M13=0,"",ROUND(U13/M13*100,1)) | W13: =U13*Assumptions!$B$4 | X13: =IF(M13=0,"",ROUND(W13/M13*100,1)) | Y13: Grupo Arruda (ARRUDA & MELO REPRESENTACAO DE ALIMENTOS E BEBIDAS LTDA, ARRUDA & MELO COMERCIO E DISTRIBUICAO DE ALIMENTOS E BEBIDAS LTDA, ARRUDA & MELO COMERCIO E DISTRIBUICAO DE ALIMENTOS E BEBIDAS DA BAHIA LTDA) | Z13: 0008526-45.2025.8.17.2001 | AA13: TJPE | AB13: diligence.adm.br | AC13: CESAR AUGUSTO ZANOTTO | AD13: Sócio-Administrador | AE13: (54) 3511-6050 | AF13: (54) 3511-6052 | AH13: RS | AI13: CAMPESTRE DA SERRA | AJ13: Fabricação de vinho | AK13: DEMAIS | AL13: ATIVA | AM13: https://diligence.adm.br/wp-content/uploads/2025/06/Edital-1a-Lista-de-Credores.pdf | AN13: p5 r60; p5 r61 | AO13: p5: R$ 4.421.862,65; p5: R$ 9.558.482,85 | AP13: DEBTOR_LIST | AQ13: 2025-06-10 | AR13: OK | AS13: ROWS:p5r60,p5r61 | AT13: 1658892fa167
A14: 13 | B14: NEW | D14: 0 | I14: AGUIA SERVICOS DE VIGILANCIA LTDA - EM RECUPERACAO JUDICIAL | J14: AGUIA SERVICOS DE VIGILANCIA LTDA, CPF/CNPJ/OAB nº | K14: 11516861 | L14: 11516861000143 | M14: 13645092 | N14: 1 | O14: B | P14: ACTIVE | Q14: 45349 | R14: =IF(Q14="","",ROUND((TODAY()-Q14)/365.25,1)) | S14: =IFERROR(VLOOKUP(O14,Assumptions!$A$7:$F$11,2,FALSE),0.25) | T14: =IF(O14="A",MAX(1,IFERROR(VLOOKUP(O14,Assumptions!$A$7:$F$11,3,FALSE),3)+IFERROR(VLOOKUP(O14,Assumptions!$A$7:$F$11,4,FALSE),8)/2-MAX(0,IF(R14="",0,R14)-IFERROR(VLOOKUP(O14,Assumptions!$A$7:$F$11,5,FALSE),1.5))),IFERROR(VLOOKUP(O14,Assumptions!$A$7:$F$11,5,FALSE),2.5)+IFERROR(VLOOKUP(O14,Assumptions!$A$7:$F$11,3,FALSE),3)+IFERROR(VLOOKUP(O14,Assumptions!$A$7:$F$11,4,FALSE),8)/2) | U14: =M14*S14/(1+Assumptions!$B$3)^T14 | V14: =IF(M14=0,"",ROUND(U14/M14*100,1)) | W14: =U14*Assumptions!$B$4 | X14: =IF(M14=0,"",ROUND(W14/M14*100,1)) | Y14: GRUPO ADLIM | Z14: 0019761-43.2024.8.17.2001 | AA14: TJPE | AB14: lrflideres.com.br | AC14: JONAS ALVARENGA DA SILVA | AD14: Sócio-Administrador | AE14: (81) 3252-6115 | AF14: (81) 3252-6117 | AH14: PE | AI14: RECIFE | AJ14: Atividades de vigilância e segurança privada | AK14: DEMAIS | AL14: ATIVA | AM14: https://lrflideres.com.br/wp-content/plugins/download-attachments/includes/download.php?id=6051 | AN14: p97 r27 | AO14: p97: R$ 13645091,92 | AP14: AJ_LIST | AQ14: 2024-08-12 | AR14: QUARANTINED | AS14: PARTIAL_DOC_CLASS_III_RECONCILED ROWS:p97r27 | AT14: a32497797bac
A15: 14 | B15: NEW | D15: 0 | I15: GREE ELECTRIC APPLIANCES DO BRASIL LTDA. | J15: Avenida dos Oitis, Distrito Industrial, Distr Industrial 2, Manaus/AM - CEP 69007002 | K15: 03519135 | L15: 03519135000156 | M15: 13499976 | N15: 1 | O15: C | R15: =IF(Q15="","",ROUND((TODAY()-Q15)/365.25,1)) | S15: =IFERROR(VLOOKUP(O15,Assumptions!$A$7:$F$11,2,FALSE),0.25) | T15: =IF(O15="A",MAX(1,IFERROR(VLOOKUP(O15,Assumptions!$A$7:$F$11,3,FALSE),3)+IFERROR(VLOOKUP(O15,Assumptions!$A$7:$F$11,4,FALSE),8)/2-MAX(0,IF(R15="",0,R15)-IFERROR(VLOOKUP(O15,Assumptions!$A$7:$F$11,5,FALSE),1.5))),IFERROR(VLOOKUP(O15,Assumptions!$A$7:$F$11,5,FALSE),2.5)+IFERROR(VLOOKUP(O15,Assumptions!$A$7:$F$11,3,FALSE),3)+IFERROR(VLOOKUP(O15,Assumptions!$A$7:$F$11,4,FALSE),8)/2) | U15: =M15*S15/(1+Assumptions!$B$3)^T15 | V15: =IF(M15=0,"",ROUND(U15/M15*100,1)) | W15: =U15*Assumptions!$B$4 | X15: =IF(M15=0,"",ROUND(W15/M15*100,1)) | Y15: REAL DISTRIBUIDORA ÚNICA RIO COMÉRCIO DE REFRIGERAÇÃO LTDA. | Z15: 0873061-47.2023.8.19.0001 | AB15: inova-aj.com.br | AC15: QUNBING ZHAO | AD15: Administrador | AE15: (92) 2123-6900 | AH15: AM | AI15: MANAUS | AJ15: Fabricação de aparelhos e equipamentos de ar condicionado para uso não-industrial | AK15: DEMAIS | AL15: ATIVA | AM15: https://inova-aj.com.br/wp-content/uploads/2026/08/1a-Relacao-de-Credores-Real.pdf | AN15: p1 r32 | AO15: p1: R$ 13.499.976,37 | AP15: AJ_LIST | AQ15: 2023-06-05 | AR15: OK | AS15: ALT_VALUE:R$9.815.941,50 ROWS:p1r32 | AT15: 8eb5d0d64353
A16: 15 | B16: NEW | D16: 0 | I16: LOUIS DREYFUS COMPANY SUCOS S.A | J16: AV. BRIGADEIRO FARIA LIMA, 1355 CJ. 1401 | K16: 00831373 | L16: 00831373000104 | M16: 13129218 | N16: 1 | O16: C | Q16: 44720 | R16: =IF(Q16="","",ROUND((TODAY()-Q16)/365.25,1)) | S16: =IFERROR(VLOOKUP(O16,Assumptions!$A$7:$F$11,2,FALSE),0.25) | T16: =IF(O16="A",MAX(1,IFERROR(VLOOKUP(O16,Assumptions!$A$7:$F$11,3,FALSE),3)+IFERROR(VLOOKUP(O16,Assumptions!$A$7:$F$11,4,FALSE),8)/2-MAX(0,IF(R16="",0,R16)-IFERROR(VLOOKUP(O16,Assumptions!$A$7:$F$11,5,FALSE),1.5))),IFERROR(VLOOKUP(O16,Assumptions!$A$7:$F$11,5,FALSE),2.5)+IFERROR(VLOOKUP(O16,Assumptions!$A$7:$F$11,3,FALSE),3)+IFERROR(VLOOKUP(O16,Assumptions!$A$7:$F$11,4,FALSE),8)/2) | U16: =M16*S16/(1+Assumptions!$B$3)^T16 | V16: =IF(M16=0,"",ROUND(U16/M16*100,1)) | W16: =U16*Assumptions!$B$4 | X16: =IF(M16=0,"",ROUND(W16/M16*100,1)) | Y16: PAULO CÉSAR SOMILIO (produtor rural, pessoa física) | Z16: 1001087-02.2022.8.26.0390 | AA16: TJSP | AB16: brasiltrustee.com.br | AC16: LEONARDO OLIVEIRA D ELIA | AD16: Diretor | AE16: (11) 3039-7160 | AF16: (13) 2127-9893 | AH16: SP | AI16: SAO PAULO | AJ16: Fabricação de sucos concentrados de frutas, hortaliças e legumes | AK16: DEMAIS | AL16: ATIVA | AM16: https://violet-wolf-754008.hostingersite.com/wp-content/uploads/2022/10/Primeiro-Edital-de-Credores-Integral-com-creditos.pdf | AN16: p4 r1 | AO16: p4: R$ 13.129.217,80 | AP16: UNKNOWN | AR16: OK | AS16: ROWS:p4r1 VALUE_COL:Valor CASE_NUMBER_CORRECTED | AT16: cefc6f1f4e0b
A17: 16 | B17: NEW | D17: 0 | I17: TABLEROS IND. E COM. DE PAINEIS LTDA | J17: Tableros Indústria e e Comércio de Painéis Ltda | K17: 09402999 | L17: 09402999000170 | M17: 12966350 | N17: 1 | O17: C | P17: ACTIVE | Q17: 44218 | R17: =IF(Q17="","",ROUND((TODAY()-Q17)/365.25,1)) | S17: =IFERROR(VLOOKUP(O17,Assumptions!$A$7:$F$11,2,FALSE),0.25) | T17: =IF(O17="A",MAX(1,IFERROR(VLOOKUP(O17,Assumptions!$A$7:$F$11,3,FALSE),3)+IFERROR(VLOOKUP(O17,Assumptions!$A$7:$F$11,4,FALSE),8)/2-MAX(0,IF(R17="",0,R17)-IFERROR(VLOOKUP(O17,Assumptions!$A$7:$F$11,5,FALSE),1.5))),IFERROR(VLOOKUP(O17,Assumptions!$A$7:$F$11,5,FALSE),2.5)+IFERROR(VLOOKUP(O17,Assumptions!$A$7:$F$11,3,FALSE),3)+IFERROR(VLOOKUP(O17,Assumptions!$A$7:$F$11,4,FALSE),8)/2) | U17: =M17*S17/(1+Assumptions!$B$3)^T17 | V17: =IF(M17=0,"",ROUND(U17/M17*100,1)) | W17: =U17*Assumptions!$B$4 | X17: =IF(M17=0,"",ROUND(W17/M17*100,1)) | Y17: FORMAPLAN FORMAS PLANEJADAS INDÚSTRIA E COMÉRCIO LTDA | Z17: 0000410-68.2021.8.16.0174 | AA17: TJPR | AB17: marquesadmjudicial.com.br | AC17: MARCIO GERALDO ROSA | AD17: Sócio-Administrador | AE17: (46) 3263-8500 | AH17: PR | AI17: PALMAS | AJ17: Fabricação de madeira laminada e de chapas de madeira compensada, prensada e aglomerada | AK17: DEMAIS | AL17: ATIVA | AM17: https://marquesadmjudicial.com.br/sgc/download.php?file=files/processo_documento/processo_documento15232121112024_1_.pdf&nome=Relação de Credores | AN17: p16 r3 | AO17: p16: R$ 12.966.349,62 | AP17: AJ_LIST | AQ17: 2021-01-22 | AR17: QUARANTINED | AS17: PARTIAL_DOC_CLASS_III_RECONCILED ROWS:p16r3 | AT17: b1a9f73b4c11
A18: 17 | B18: NEW | D18: 0 | I18: GRANELES BRASIL COMERCIAL IMPORTADORA EXPORTADORA AGRICOLA S.A EM RECUPERACAO JUDICIAL | J18: GRANELES BRASIL COMERC IMPORT EXPORTADORA AGRICO | K18: 24785274 | L18: 24785274000444 | M18: 11676960 | N18: 1 | O18: D | Q18: 45862 | R18: =IF(Q18="","",ROUND((TODAY()-Q18)/365.25,1)) | S18: =IFERROR(VLOOKUP(O18,Assumptions!$A$7:$F$11,2,FALSE),0.25) | T18: =IF(O18="A",MAX(1,IFERROR(VLOOKUP(O18,Assumptions!$A$7:$F$11,3,FALSE),3)+IFERROR(VLOOKUP(O18,Assumptions!$A$7:$F$11,4,FALSE),8)/2-MAX(0,IF(R18="",0,R18)-IFERROR(VLOOKUP(O18,Assumptions!$A$7:$F$11,5,FALSE),1.5))),IFERROR(VLOOKUP(O18,Assumptions!$A$7:$F$11,5,FALSE),2.5)+IFERROR(VLOOKUP(O18,Assumptions!$A$7:$F$11,3,FALSE),3)+IFERROR(VLOOKUP(O18,Assumptions!$A$7:$F$11,4,FALSE),8)/2) | U18: =M18*S18/(1+Assumptions!$B$3)^T18 | V18: =IF(M18=0,"",ROUND(U18/M18*100,1)) | W18: =U18*Assumptions!$B$4 | X18: =IF(M18=0,"",ROUND(W18/M18*100,1)) | Y18: JOB FERTILIZANTES LTDA | Z18: 5000561-63.2025.8.24.0536 | AA18: TJSC | AB18: scalzilliaj.com.br | AC18: GABRIEL DE FREITAS MACHADO | AD18: Presidente | AE18: (41) 9539-0828 | AH18: SP | AI18: SAO PAULO | AJ18: Comércio atacadista de produtos alimentícios em geral | AK18: DEMAIS | AL18: ATIVA | AM18: https://scalzilliaj.com.br/sgc/download.php?file=files/processo_documento/processo_documento13183320052026_1_.pdf&nome=10 - QGC Provisório - atualizado até Maio de 2026 | AN18: p1 r10 | AO18: p1: R$ 11.676.960,19 | AP18: QGC | AR18: OK_NO_TOTALS | AS18: CASE_NUMBER_MISSING ROWS:p1r10 UNRECONCILED_SOURCE VALUE_COL:Valor_Do_Crédito CASE_FROM_PORTAL | AT18: 8b4c169de629
A19: 18 | B19: NEW | D19: 0 | I19: ALBAUGH AGRO BRASIL LTDA. | J19: ALBAUGH AGRO BRASIL LTDA | K19: 01789121 | L19: 01789121000470, 01789121000984, 01789121001107 | M19: 11525550 | N19: 1 | O19: B | P19: ACTIVE | Q19: 45845 | R19: =IF(Q19="","",ROUND((TODAY()-Q19)/365.25,1)) | S19: =IFERROR(VLOOKUP(O19,Assumptions!$A$7:$F$11,2,FALSE),0.25) | T19: =IF(O19="A",MAX(1,IFERROR(VLOOKUP(O19,Assumptions!$A$7:$F$11,3,FALSE),3)+IFERROR(VLOOKUP(O19,Assumptions!$A$7:$F$11,4,FALSE),8)/2-MAX(0,IF(R19="",0,R19)-IFERROR(VLOOKUP(O19,Assumptions!$A$7:$F$11,5,FALSE),1.5))),IFERROR(VLOOKUP(O19,Assumptions!$A$7:$F$11,5,FALSE),2.5)+IFERROR(VLOOKUP(O19,Assumptions!$A$7:$F$11,3,FALSE),3)+IFERROR(VLOOKUP(O19,Assumptions!$A$7:$F$11,4,FALSE),8)/2) | U19: =M19*S19/(1+Assumptions!$B$3)^T19 | V19: =IF(M19=0,"",ROUND(U19/M19*100,1)) | W19: =U19*Assumptions!$B$4 | X19: =IF(M19=0,"",ROUND(W19/M19*100,1)) | Y19: SOJAL COMERCIAL AGRICOLA LTDA e OUTROS | Z19: 0804401-51.2025.8.14.0039 | AA19: TJPA | AB19: lrflideres.com.br | AC19: CESAR EMILIANO ROJAS RUIZ | AD19: Administrador | AE19: (11) 3076-4243 | AH19: SP | AI19: SAO PAULO | AJ19: Fabricação de defensivos agrícolas | AK19: DEMAIS | AL19: ATIVA | AM19: https://lrflideres.com.br/wp-content/plugins/download-attachments/includes/download.php?id=6879 | AN19: p1 r4 | AO19: p1: R$ 11.525.550,26 | AP19: AJ_LIST | AQ19: 2026-01-15 | AR19: OK | AS19: ROWS:p1r4 | AT19: c56751547323
A20: 19 | B20: NEW | D20: 0 | I20: DC COMERCIO, REPRESENTACOES, INVESTIMENTOS E PARTICIPACOES LTDA. | J20: DC COMERCIO, REPRESENTACOES, INVESTIMENTOS E PARTICIPACOES LTDA | K20: 09036221 | L20: 09036221000194 | M20: 11125000 | N20: 3 | O20: C | P20: ACTIVE | Q20: 44571 | R20: =IF(Q20="","",ROUND((TODAY()-Q20)/365.25,1)) | S20: =IFERROR(VLOOKUP(O20,Assumptions!$A$7:$F$11,2,FALSE),0.25) | T20: =IF(O20="A",MAX(1,IFERROR(VLOOKUP(O20,Assumptions!$A$7:$F$11,3,FALSE),3)+IFERROR(VLOOKUP(O20,Assumptions!$A$7:$F$11,4,FALSE),8)/2-MAX(0,IF(R20="",0,R20)-IFERROR(VLOOKUP(O20,Assumptions!$A$7:$F$11,5,FALSE),1.5))),IFERROR(VLOOKUP(O20,Assumptions!$A$7:$F$11,5,FALSE),2.5)+IFERROR(VLOOKUP(O20,Assumptions!$A$7:$F$11,3,FALSE),3)+IFERROR(VLOOKUP(O20,Assumptions!$A$7:$F$11,4,FALSE),8)/2) | U20: =M20*S20/(1+Assumptions!$B$3)^T20 | V20: =IF(M20=0,"",ROUND(U20/M20*100,1)) | W20: =U20*Assumptions!$B$4 | X20: =IF(M20=0,"",ROUND(W20/M20*100,1)) | Y20: GRUPO CATTAN | Z20: 0002484-82.2022.8.17.2001 | AA20: TJPE | AB20: lrflideres.com.br | AC20: FERNANDO MELO CATAO | AD20: Sócio-Administrador | AE20: (81) 3032-8400 | AF20: (81) 3419-8550 | AH20: PE | AI20: RECIFE | AJ20: Aluguel de imóveis próprios | AK20: DEMAIS | AL20: ATIVA | AM20: https://lrflideres.com.br/wp-content/plugins/download-attachments/includes/download.php?id=4023 | AN20: p4 r68; p7 r92; p9 r68 | AO20: p4: R$ 1.150.000,00; p7: R$ 9.715.000,00; p9: R$ 260.000,00 | AP20: DEBTOR_LIST | AR20: QUARANTINED | AS20: PARTIAL_DOC_CLASS_III_RECONCILED ROWS:p4r68,p7r92,p9r68 | AT20: f3b6182e3aa2
A21: 20 | B21: NEW | D21: 0 | I21: SANDOZ DO BRASIL INDUSTRIA FARMACEUTICA LTDA. | J21: Sandoz do Brasil Industria Farmaceutica Ltda | K21: 61286647 | L21: 61286647001007 | M21: 10696834 | N21: 1 | O21: C | P21: ACTIVE | Q21: 44987 | R21: =IF(Q21="","",ROUND((TODAY()-Q21)/365.25,1)) | S21: =IFERROR(VLOOKUP(O21,Assumptions!$A$7:$F$11,2,FALSE),0.25) | T21: =IF(O21="A",MAX(1,IFERROR(VLOOKUP(O21,Assumptions!$A$7:$F$11,3,FALSE),3)+IFERROR(VLOOKUP(O21,Assumptions!$A$7:$F$11,4,FALSE),8)/2-MAX(0,IF(R21="",0,R21)-IFERROR(VLOOKUP(O21,Assumptions!$A$7:$F$11,5,FALSE),1.5))),IFERROR(VLOOKUP(O21,Assumptions!$A$7:$F$11,5,FALSE),2.5)+IFERROR(VLOOKUP(O21,Assumptions!$A$7:$F$11,3,FALSE),3)+IFERROR(VLOOKUP(O21,Assumptions!$A$7:$F$11,4,FALSE),8)/2) | U21: =M21*S21/(1+Assumptions!$B$3)^T21 | V21: =IF(M21=0,"",ROUND(U21/M21*100,1)) | W21: =U21*Assumptions!$B$4 | X21: =IF(M21=0,"",ROUND(W21/M21*100,1)) | Y21: GRUPO DP4 | Z21: 0005010-98.2023.8.16.0001 | AA21: TJPR | AB21: marquesadmjudicial.com.br | AC21: BRUNO PETENUCI | AD21: Administrador | AE21: (43) 3174-8000 | AH21: PR | AI21: CAMBE | AJ21: Fabricação de medicamentos alopáticos para uso humano | AK21: DEMAIS | AL21: ATIVA | AM21: https://marquesadmjudicial.com.br/sgc/download.php?file=files/processo_documento/processo_documento15293208032024_1_.pdf&nome=Relação Nominal de Credores da AJ-Sintética | AN21: p31 r4 | AO21: p31: R$ 10.696.833,99 | AP21: AJ_LIST | AQ21: 2023-03-02 | AR21: QUARANTINED | AS21: PARTIAL_DOC_CLASS_III_RECONCILED ROWS:p31r4 | AT21: b465a5d11eec
A22: 21 | B22: NEW | D22: 0 | I22: BASTON INDUSTRIA DE AEROSSOIS LTDA | J22: Baston Industria de Aerossois Ltda | K22: 05855974 | L22: 05855974000170 | M22: 10636330 | N22: 1 | O22: C | P22: ACTIVE | Q22: 44987 | R22: =IF(Q22="","",ROUND((TODAY()-Q22)/365.25,1)) | S22: =IFERROR(VLOOKUP(O22,Assumptions!$A$7:$F$11,2,FALSE),0.25) | T22: =IF(O22="A",MAX(1,IFERROR(VLOOKUP(O22,Assumptions!$A$7:$F$11,3,FALSE),3)+IFERROR(VLOOKUP(O22,Assumptions!$A$7:$F$11,4,FALSE),8)/2-MAX(0,IF(R22="",0,R22)-IFERROR(VLOOKUP(O22,Assumptions!$A$7:$F$11,5,FALSE),1.5))),IFERROR(VLOOKUP(O22,Assumptions!$A$7:$F$11,5,FALSE),2.5)+IFERROR(VLOOKUP(O22,Assumptions!$A$7:$F$11,3,FALSE),3)+IFERROR(VLOOKUP(O22,Assumptions!$A$7:$F$11,4,FALSE),8)/2) | U22: =M22*S22/(1+Assumptions!$B$3)^T22 | V22: =IF(M22=0,"",ROUND(U22/M22*100,1)) | W22: =U22*Assumptions!$B$4 | X22: =IF(M22=0,"",ROUND(W22/M22*100,1)) | Y22: GRUPO DP4 | Z22: 0005010-98.2023.8.16.0001 | AA22: TJPR | AB22: marquesadmjudicial.com.br | AC22: LUIS GUSTAVO MALUCELLI BACILA | AD22: Administrador | AE22: (42) 3252-8120 | AF22: (42) 3252-1705 | AH22: PR | AI22: PALMEIRA | AJ22: Fabricação de outros produtos químicos não especificados anteriormente | AK22: DEMAIS | AL22: ATIVA | AM22: https://marquesadmjudicial.com.br/sgc/download.php?file=files/processo_documento/processo_documento15293208032024_1_.pdf&nome=Relação Nominal de Credores da AJ-Sintética | AN22: p21 r8 | AO22: p21: R$ 10.636.330,31 | AP22: AJ_LIST | AQ22: 2023-03-02 | AR22: QUARANTINED | AS22: PARTIAL_DOC_CLASS_III_RECONCILED ROWS:p21r8 | AT22: b465a5d11eec
A23: 22 | B23: NEW | D23: 0 | I23: ENVTECH DO BRASIL DESCONTAMINACOES INDUSTRIAIS LTDA | J23: Envtech do Brasil Descontaminações Industriais Ltda | K23: 11486977 | L23: 11486977000187 | M23: 10310429 | N23: 1 | O23: B | Q23: 45756 | R23: =IF(Q23="","",ROUND((TODAY()-Q23)/365.25,1)) | S23: =IFERROR(VLOOKUP(O23,Assumptions!$A$7:$F$11,2,FALSE),0.25) | T23: =IF(O23="A",MAX(1,IFERROR(VLOOKUP(O23,Assumptions!$A$7:$F$11,3,FALSE),3)+IFERROR(VLOOKUP(O23,Assumptions!$A$7:$F$11,4,FALSE),8)/2-MAX(0,IF(R23="",0,R23)-IFERROR(VLOOKUP(O23,Assumptions!$A$7:$F$11,5,FALSE),1.5))),IFERROR(VLOOKUP(O23,Assumptions!$A$7:$F$11,5,FALSE),2.5)+IFERROR(VLOOKUP(O23,Assumptions!$A$7:$F$11,3,FALSE),3)+IFERROR(VLOOKUP(O23,Assumptions!$A$7:$F$11,4,FALSE),8)/2) | U23: =M23*S23/(1+Assumptions!$B$3)^T23 | V23: =IF(M23=0,"",ROUND(U23/M23*100,1)) | W23: =U23*Assumptions!$B$4 | X23: =IF(M23=0,"",ROUND(W23/M23*100,1)) | Y23: GRUPO EGESA (EGESA ENG S.A, EGESUR PART E EMP S.A, MATRIX INFRA LTDA, BEMVIVER ENG AMBIENTAL E SERV LTDA, DKF CONST E EMP LTDA, EGEPEL LTDA, ETR ASSESSORIA EMP E PART LTDA, MVT ENG E SERV LTDA, PARQUES DO VALE LTDA, ELMO RIBEIRO E ANA RIBEIRO) | Z23: 5088952-81.2025.8.13.0024 | AA23: TJMG | AB23: scalzilliaj.com.br | AC23: FREDDY VLADIMIR RADA COVALOVA | AD23: Sócio-Administrador | AE23: (31) 8447-7021 | AH23: RJ | AI23: PETROPOLIS | AJ23: Manutenção e reparação de outras máquinas e equipamentos para usos industriais não especificados anteriormente | AK23: DEMAIS | AL23: ATIVA | AM23: https://scalzilliaj.com.br/sgc/download.php?file=files/processo_documento/processo_documento09514021082025_1_.pdf&nome=04 - Relação de credores das Recuperandas | AN23: p66 r6 | AO23: p66: R$ 10.310.428,56 | AP23: DEBTOR_LIST | AR23: OK | AS23: ROWS:p66r6 VALUE_COL:Valor_Atualizado CASE_NUMBER_CORRECTED CASE_FROM_PORTAL | AT23: 24ed98480a57
A24: 23 | B24: NEW | D24: 0 | I24: DANONE LTDA | J24: Danone Ltda | K24: 23643315 | L24: 23643315014455 | M24: 9093937.7 | N24: 1 | O24: C | P24: ACTIVE | Q24: 44987 | R24: =IF(Q24="","",ROUND((TODAY()-Q24)/365.25,1)) | S24: =IFERROR(VLOOKUP(O24,Assumptions!$A$7:$F$11,2,FALSE),0.25) | T24: =IF(O24="A",MAX(1,IFERROR(VLOOKUP(O24,Assumptions!$A$7:$F$11,3,FALSE),3)+IFERROR(VLOOKUP(O24,Assumptions!$A$7:$F$11,4,FALSE),8)/2-MAX(0,IF(R24="",0,R24)-IFERROR(VLOOKUP(O24,Assumptions!$A$7:$F$11,5,FALSE),1.5))),IFERROR(VLOOKUP(O24,Assumptions!$A$7:$F$11,5,FALSE),2.5)+IFERROR(VLOOKUP(O24,Assumptions!$A$7:$F$11,3,FALSE),3)+IFERROR(VLOOKUP(O24,Assumptions!$A$7:$F$11,4,FALSE),8)/2) | U24: =M24*S24/(1+Assumptions!$B$3)^T24 | V24: =IF(M24=0,"",ROUND(U24/M24*100,1)) | W24: =U24*Assumptions!$B$4 | X24: =IF(M24=0,"",ROUND(W24/M24*100,1)) | Y24: GRUPO DP4 | Z24: 0005010-98.2023.8.16.0001 | AA24: TJPR | AB24: marquesadmjudicial.com.br | AC24: GEOVANI VIEIRA MANZANO | AD24: Administrador | AE24: (35) 3729-7901 | AH24: SP | AI24: SAO PAULO | AJ24: Fabricação de laticínios | AK24: DEMAIS | AL24: ATIVA | AM24: https://marquesadmjudicial.com.br/sgc/download.php?file=files/processo_documento/processo_documento15293208032024_1_.pdf&nome=Relação Nominal de Credores da AJ-Sintética | AN24: p24 r6 | AO24: p24: R$ 9.093.937,71 | AP24: AJ_LIST | AQ24: 2023-03-02 | AR24: QUARANTINED | AS24: PARTIAL_DOC_CLASS_III_RECONCILED ROWS:p24r6 | AT24: b465a5d11eec
A25: 24 | B25: NEW | D25: 0 | I25: COPA ENERGIA S.A. | J25: COPA ENERGIA DISTRIBUIDORA DE GÁS S.A | K25: 03237583 | L25: 03237583000167 | M25: 9000000 | N25: 1 | O25: B | P25: ACTIVE | Q25: 46048 | R25: =IF(Q25="","",ROUND((TODAY()-Q25)/365.25,1)) | S25: =IFERROR(VLOOKUP(O25,Assumptions!$A$7:$F$11,2,FALSE),0.25) | T25: =IF(O25="A",MAX(1,IFERROR(VLOOKUP(O25,Assumptions!$A$7:$F$11,3,FALSE),3)+IFERROR(VLOOKUP(O25,Assumptions!$A$7:$F$11,4,FALSE),8)/2-MAX(0,IF(R25="",0,R25)-IFERROR(VLOOKUP(O25,Assumptions!$A$7:$F$11,5,FALSE),1.5))),IFERROR(VLOOKUP(O25,Assumptions!$A$7:$F$11,5,FALSE),2.5)+IFERROR(VLOOKUP(O25,Assumptions!$A$7:$F$11,3,FALSE),3)+IFERROR(VLOOKUP(O25,Assumptions!$A$7:$F$11,4,FALSE),8)/2) | U25: =M25*S25/(1+Assumptions!$B$3)^T25 | V25: =IF(M25=0,"",ROUND(U25/M25*100,1)) | W25: =U25*Assumptions!$B$4 | X25: =IF(M25=0,"",ROUND(W25/M25*100,1)) | Y25: GRUPO GLP | Z25: 0001639-09.2026.8.17.2810 | AA25: TJPE | AB25: recuperasolucoes.com | AC25: PEDRO JOAO ZAHRAN TURQUETO | AD25: Presidente | AE25: (11) 5505-4077 | AH25: SP | AI25: SAO PAULO | AJ25: Comércio atacadista de gás liqüefeito de petróleo (GLP) | AK25: DEMAIS | AL25: ATIVA | AM25: https://recuperasolucoes.com/wp-content/plugins/download-attachments/includes/download.php?id=1597 | AN25: p13 r12 | AO25: p13: R$ 9.000.000,00 | AP25: DEBTOR_LIST | AQ25: 2026-05-21 | AR25: OK | AS25: ROWS:p13r12 | AT25: 5da7b77bb569
A26: 25 | B26: NEW | D26: 0 | I26: MINERACAO AURORA LTDA | J26: MINERACAO AURORA LTDA | K26: 10509915 | L26: 10509915000180 | M26: 8433590 | N26: 1 | O26: C | P26: ACTIVE | Q26: 43838 | R26: =IF(Q26="","",ROUND((TODAY()-Q26)/365.25,1)) | S26: =IFERROR(VLOOKUP(O26,Assumptions!$A$7:$F$11,2,FALSE),0.25) | T26: =IF(O26="A",MAX(1,IFERROR(VLOOKUP(O26,Assumptions!$A$7:$F$11,3,FALSE),3)+IFERROR(VLOOKUP(O26,Assumptions!$A$7:$F$11,4,FALSE),8)/2-MAX(0,IF(R26="",0,R26)-IFERROR(VLOOKUP(O26,Assumptions!$A$7:$F$11,5,FALSE),1.5))),IFERROR(VLOOKUP(O26,Assumptions!$A$7:$F$11,5,FALSE),2.5)+IFERROR(VLOOKUP(O26,Assumptions!$A$7:$F$11,3,FALSE),3)+IFERROR(VLOOKUP(O26,Assumptions!$A$7:$F$11,4,FALSE),8)/2) | U26: =M26*S26/(1+Assumptions!$B$3)^T26 | V26: =IF(M26=0,"",ROUND(U26/M26*100,1)) | W26: =U26*Assumptions!$B$4 | X26: =IF(M26=0,"",ROUND(W26/M26*100,1)) | Y26: CONSTRUTORA ANDRADE GUEDES LTDA | Z26: 0000880-57.2020.8.17.2001 | AA26: TJPE | AB26: diligence.adm.br | AC26: SHIRLEY MONTEIRO REBOCHO SILVA | AD26: Sócio-Administrador | AE26: (81) 3972-4964 | AH26: PE | AI26: JABOATAO DOS GUARARAPES | AJ26: Extração e britamento de pedras e outros materiais para construção e beneficiamento associado | AK26: DEMAIS | AL26: ATIVA | AM26: https://diligence.adm.br/wp-content/plugins/download-attachments/includes/download.php?id=4599 | AN26: p10 r60 | AO26: p10: R$ 8.433.590,01 | AP26: AJ_LIST | AQ26: 2024-06-25 | AR26: OK_NO_TOTALS | AS26: ALT_VALUE:R$2.710.146,67 ALT_VALUE:R$5.723.443,34 ROWS:p10r60 UNRECONCILED_SOURCE VALUE_COL:2ª_Lista | AT26: 44ecd0afa707
A27: 26 | B27: NEW | D27: 0 | I27: FIRST S/A | J27: PENDENTE DE REGULARIZAÇÃO | K27: 00802235 | L27: 00802235000105 | M27: 8354815.1 | N27: 1 | O27: B | R27: =IF(Q27="","",ROUND((TODAY()-Q27)/365.25,1)) | S27: =IFERROR(VLOOKUP(O27,Assumptions!$A$7:$F$11,2,FALSE),0.25) | T27: =IF(O27="A",MAX(1,IFERROR(VLOOKUP(O27,Assumptions!$A$7:$F$11,3,FALSE),3)+IFERROR(VLOOKUP(O27,Assumptions!$A$7:$F$11,4,FALSE),8)/2-MAX(0,IF(R27="",0,R27)-IFERROR(VLOOKUP(O27,Assumptions!$A$7:$F$11,5,FALSE),1.5))),IFERROR(VLOOKUP(O27,Assumptions!$A$7:$F$11,5,FALSE),2.5)+IFERROR(VLOOKUP(O27,Assumptions!$A$7:$F$11,3,FALSE),3)+IFERROR(VLOOKUP(O27,Assumptions!$A$7:$F$11,4,FALSE),8)/2) | U27: =M27*S27/(1+Assumptions!$B$3)^T27 | V27: =IF(M27=0,"",ROUND(U27/M27*100,1)) | W27: =U27*Assumptions!$B$4 | X27: =IF(M27=0,"",ROUND(W27/M27*100,1)) | Y27: Grupo Rech | Z27: 5057720-48.2025.8.24.0023 | AB27: credibilita.com.br | AC27: NATANAEL SANTOS DE SOUZA | AD27: Presidente | AE27: (11) 5054-8110 | AH27: SP | AI27: SAO PAULO | AJ27: Comércio atacadista especializado em outros produtos intermediários não especificados anteriormente | AK27: DEMAIS | AL27: ATIVA | AM27: https://credibilita.com.br/wp-content/uploads/2025/09/Relacao-Credores-29.04.2026.pdf | AN27: p1 r23 | AO27: p1: R$ 8.354.815,13 | AP27: QUORUM_LIST | AR27: OK_NO_TOTALS | AS27: ROWS:p1r23 UNRECONCILED_SOURCE VALUE_COL:Valor_Após_Analise CASE_NUMBER_CORRECTED | AT27: cf92cff797d2
A28: 27 | B28: NEW | D28: 0 | I28: IPESA DO BRASIL COMERCIO DE PRODUTOS PLASTICOS LTDA | J28: NÃO | K28: 05607230 | L28: 05607230000480 | M28: 8353250 | N28: 1 | O28: B | R28: =IF(Q28="","",ROUND((TODAY()-Q28)/365.25,1)) | S28: =IFERROR(VLOOKUP(O28,Assumptions!$A$7:$F$11,2,FALSE),0.25) | T28: =IF(O28="A",MAX(1,IFERROR(VLOOKUP(O28,Assumptions!$A$7:$F$11,3,FALSE),3)+IFERROR(VLOOKUP(O28,Assumptions!$A$7:$F$11,4,FALSE),8)/2-MAX(0,IF(R28="",0,R28)-IFERROR(VLOOKUP(O28,Assumptions!$A$7:$F$11,5,FALSE),1.5))),IFERROR(VLOOKUP(O28,Assumptions!$A$7:$F$11,5,FALSE),2.5)+IFERROR(VLOOKUP(O28,Assumptions!$A$7:$F$11,3,FALSE),3)+IFERROR(VLOOKUP(O28,Assumptions!$A$7:$F$11,4,FALSE),8)/2) | U28: =M28*S28/(1+Assumptions!$B$3)^T28 | V28: =IF(M28=0,"",ROUND(U28/M28*100,1)) | W28: =U28*Assumptions!$B$4 | X28: =IF(M28=0,"",ROUND(W28/M28*100,1)) | Y28: Grupo Rech | Z28: 5057720-48.2025.8.24.0023 | AB28: credibilita.com.br | AC28: VIRGINIA KUMVICH | AD28: Administrador | AE28: (11) 5524-2877 | AH28: SP | AI28: SAO PAULO | AJ28: Comércio atacadista especializado em outros produtos intermediários não especificados anteriormente | AK28: DEMAIS | AL28: ATIVA | AM28: https://credibilita.com.br/wp-content/uploads/2025/09/Relacao-Credores-29.04.2026.pdf | AN28: p1 r27 | AO28: p1: R$ 8.353.250,00 | AP28: QUORUM_LIST | AR28: OK_NO_TOTALS | AS28: ROWS:p1r27 UNRECONCILED_SOURCE VALUE_COL:Valor_Após_Analise CASE_NUMBER_CORRECTED | AT28: cf92cff797d2
A29: 28 | B29: NEW | D29: 0 | I29: CLIMAZON INDUSTRIAL LTDA | J29: Avenida Torquato Tapajos, 7937, Lote 14, 14B, Taruma, Manaus/ AM - CEP 69041025 | K29: 04222931 | L29: 04222931000195 | M29: 8012248.6 | N29: 1 | O29: C | R29: =IF(Q29="","",ROUND((TODAY()-Q29)/365.25,1)) | S29: =IFERROR(VLOOKUP(O29,Assumptions!$A$7:$F$11,2,FALSE),0.25) | T29: =IF(O29="A",MAX(1,IFERROR(VLOOKUP(O29,Assumptions!$A$7:$F$11,3,FALSE),3)+IFERROR(VLOOKUP(O29,Assumptions!$A$7:$F$11,4,FALSE),8)/2-MAX(0,IF(R29="",0,R29)-IFERROR(VLOOKUP(O29,Assumptions!$A$7:$F$11,5,FALSE),1.5))),IFERROR(VLOOKUP(O29,Assumptions!$A$7:$F$11,5,FALSE),2.5)+IFERROR(VLOOKUP(O29,Assumptions!$A$7:$F$11,3,FALSE),3)+IFERROR(VLOOKUP(O29,Assumptions!$A$7:$F$11,4,FALSE),8)/2) | U29: =M29*S29/(1+Assumptions!$B$3)^T29 | V29: =IF(M29=0,"",ROUND(U29/M29*100,1)) | W29: =U29*Assumptions!$B$4 | X29: =IF(M29=0,"",ROUND(W29/M29*100,1)) | Y29: REAL DISTRIBUIDORA ÚNICA RIO COMÉRCIO DE REFRIGERAÇÃO LTDA. | Z29: 0873061-47.2023.8.19.0001 | AB29: inova-aj.com.br | AC29: ADRIANO ZACCARI FORTUNA | AD29: Administrador | AE29: (51) 3477-9873 | AF29: (51) 3477-9684 | AH29: AM | AI29: MANAUS | AJ29: Fabricação de aparelhos e equipamentos de ar condicionado para uso não-industrial | AK29: DEMAIS | AL29: ATIVA | AM29: https://inova-aj.com.br/wp-content/uploads/2026/08/1a-Relacao-de-Credores-Real.pdf | AN29: p1 r25 | AO29: p1: R$ 8.012.248,57 | AP29: AJ_LIST | AQ29: 2023-06-05 | AR29: OK | AS29: ALT_VALUE:R$5.825.770,44 ROWS:p1r25 | AT29: 8eb5d0d64353
A30: 29 | B30: NEW | D30: 0 | I30: COOPERATIVA DOS PLANTADORES DE CANA DO ESTADO SAO PAULO | J30: TITULARES DE CRÉDITOS QUIROGRAFÁRIOS SEQUENCIA EMPRESA CREDOR CNPJ / CPF ENDEREÇO BAIRRO CEP CIDADE UF ENDEREÇO ELETRONICO NATUREZA DOCUMENTO VALOR EM R$ 1 PRODUTOR RURAL (TAIKI MORIOKA) COOPERATIVA DOS PLANTADORES DE CANA DO ESTADO SÃO PAULO | K30: 54366547 | L30: 00000000000191, 02398976000190, 28138113004164, 54366547000134, 54366547003400, 60701190481609 | M30: 8000000 | N30: 1 | O30: B | P30: ACTIVE | Q30: 46184 | R30: =IF(Q30="","",ROUND((TODAY()-Q30)/365.25,1)) | S30: =IFERROR(VLOOKUP(O30,Assumptions!$A$7:$F$11,2,FALSE),0.25) | T30: =IF(O30="A",MAX(1,IFERROR(VLOOKUP(O30,Assumptions!$A$7:$F$11,3,FALSE),3)+IFERROR(VLOOKUP(O30,Assumptions!$A$7:$F$11,4,FALSE),8)/2-MAX(0,IF(R30="",0,R30)-IFERROR(VLOOKUP(O30,Assumptions!$A$7:$F$11,5,FALSE),1.5))),IFERROR(VLOOKUP(O30,Assumptions!$A$7:$F$11,5,FALSE),2.5)+IFERROR(VLOOKUP(O30,Assumptions!$A$7:$F$11,3,FALSE),3)+IFERROR(VLOOKUP(O30,Assumptions!$A$7:$F$11,4,FALSE),8)/2) | U30: =M30*S30/(1+Assumptions!$B$3)^T30 | V30: =IF(M30=0,"",ROUND(U30/M30*100,1)) | W30: =U30*Assumptions!$B$4 | X30: =IF(M30=0,"",ROUND(W30/M30*100,1)) | Y30: NAIR AKICO NAWAKAMI MORIOKA, TAIKI FELIPE MORIOKA e TIEZO FERNANDO MORIOKA (produtores rurais) | Z30: 4000807-49.2026.8.26.0354 | AA30: TJSP | AB30: vtladm.com.br | AC30: MARCOS FARHAT | AD30: Presidente | AE30: (19) 3401-2200 | AH30: SP | AI30: PIRACICABA | AJ30: Comércio atacadista de defensivos agrícolas, adubos, fertilizantes e corretivos do solo | AK30: DEMAIS | AL30: ATIVA | AM30: https://vtladm.com.br/wp-content/uploads/2026/06/02-–-Relacao-de-Credores-–-NAIR-AKICO-KAWAKAMI-MORIOKA-E-OUTROS.pdf | AN30: p4 r1 | AO30: p4: R$ 8.000.000,00 | AP30: UNKNOWN | AR30: OK_NO_TOTALS | AS30: LONG_CHUNK MULTI_ROOT ROWS:p4r1 UNRECONCILED_SOURCE | AT30: abf6f46571cf
A31: 30 | B31: NEW | D31: 0 | I31: LEGRAND PHARMA INDUSTRIA FARMACEUTICA LTDA | J31: Legrand Pharma Industria Farmaceutica Ltda | K31: 05044984 | L31: 05044984000126 | M31: 7715049.7 | N31: 1 | O31: C | P31: ACTIVE | Q31: 44987 | R31: =IF(Q31="","",ROUND((TODAY()-Q31)/365.25,1)) | S31: =IFERROR(VLOOKUP(O31,Assumptions!$A$7:$F$11,2,FALSE),0.25) | T31: =IF(O31="A",MAX(1,IFERROR(VLOOKUP(O31,Assumptions!$A$7:$F$11,3,FALSE),3)+IFERROR(VLOOKUP(O31,Assumptions!$A$7:$F$11,4,FALSE),8)/2-MAX(0,IF(R31="",0,R31)-IFERROR(VLOOKUP(O31,Assumptions!$A$7:$F$11,5,FALSE),1.5))),IFERROR(VLOOKUP(O31,Assumptions!$A$7:$F$11,5,FALSE),2.5)+IFERROR(VLOOKUP(O31,Assumptions!$A$7:$F$11,3,FALSE),3)+IFERROR(VLOOKUP(O31,Assumptions!$A$7:$F$11,4,FALSE),8)/2) | U31: =M31*S31/(1+Assumptions!$B$3)^T31 | V31: =IF(M31=0,"",ROUND(U31/M31*100,1)) | W31: =U31*Assumptions!$B$4 | X31: =IF(M31=0,"",ROUND(W31/M31*100,1)) | Y31: GRUPO DP4 | Z31: 0005010-98.2023.8.16.0001 | AA31: TJPR | AB31: marquesadmjudicial.com.br | AC31: GUSTAVO ANDRE REGIS DUTRA SVENSSON | AD31: Administrador | AE31: (19) 3887-9800 | AH31: SP | AI31: HORTOLANDIA | AJ31: Fabricação de medicamentos alopáticos para uso humano | AK31: DEMAIS | AL31: ATIVA | AM31: https://marquesadmjudicial.com.br/sgc/download.php?file=files/processo_documento/processo_documento15293208032024_1_.pdf&nome=Relação Nominal de Credores da AJ-Sintética | AN31: p28 r5 | AO31: p28: R$ 7.715.049,72 | AP31: AJ_LIST | AQ31: 2023-03-02 | AR31: QUARANTINED | AS31: PARTIAL_DOC_CLASS_III_RECONCILED ROWS:p28r5 | AT31: b465a5d11eec
A32: 31 | B32: NEW | D32: 0 | I32: BRASIL ASFALTOS LTDA | J32: BRASIL ASFALTOS LTDA | K32: 12447077 | L32: 12447077000193 | M32: 7707516.4 | N32: 1 | O32: C | P32: ACTIVE | Q32: 43838 | R32: =IF(Q32="","",ROUND((TODAY()-Q32)/365.25,1)) | S32: =IFERROR(VLOOKUP(O32,Assumptions!$A$7:$F$11,2,FALSE),0.25) | T32: =IF(O32="A",MAX(1,IFERROR(VLOOKUP(O32,Assumptions!$A$7:$F$11,3,FALSE),3)+IFERROR(VLOOKUP(O32,Assumptions!$A$7:$F$11,4,FALSE),8)/2-MAX(0,IF(R32="",0,R32)-IFERROR(VLOOKUP(O32,Assumptions!$A$7:$F$11,5,FALSE),1.5))),IFERROR(VLOOKUP(O32,Assumptions!$A$7:$F$11,5,FALSE),2.5)+IFERROR(VLOOKUP(O32,Assumptions!$A$7:$F$11,3,FALSE),3)+IFERROR(VLOOKUP(O32,Assumptions!$A$7:$F$11,4,FALSE),8)/2) | U32: =M32*S32/(1+Assumptions!$B$3)^T32 | V32: =IF(M32=0,"",ROUND(U32/M32*100,1)) | W32: =U32*Assumptions!$B$4 | X32: =IF(M32=0,"",ROUND(W32/M32*100,1)) | Y32: CONSTRUTORA ANDRADE GUEDES LTDA | Z32: 0000880-57.2020.8.17.2001 | AA32: TJPE | AB32: diligence.adm.br | AC32: ALBERTO GARRIDO PINON | AD32: Administrador | AE32: (71) 3118-2100 | AF32: (71) 3176-2828 | AH32: BA | AI32: CANDEIAS | AJ32: Fabricação de outros produtos de minerais não-metálicos não especificados anteriormente | AK32: DEMAIS | AL32: ATIVA | AM32: https://diligence.adm.br/wp-content/plugins/download-attachments/includes/download.php?id=4599 | AN32: p10 r9 | AO32: p10: R$ 7.707.516,40 | AP32: AJ_LIST | AQ32: 2024-06-25 | AR32: OK_NO_TOTALS | AS32: ALT_VALUE:R$613.244,70 ALT_VALUE:R$7.094.271,70 ROWS:p10r9 UNRECONCILED_SOURCE VALUE_COL:2ª_Lista | AT32: 44ecd0afa707
A33: 32 | B33: NEW | D33: 0 | I33: TITAN PNEUS DO BRASIL LTDA | J33: SIM | K33: 11385941 | L33: 11385941000107 | M33: 7525940 | N33: 1 | O33: B | R33: =IF(Q33="","",ROUND((TODAY()-Q33)/365.25,1)) | S33: =IFERROR(VLOOKUP(O33,Assumptions!$A$7:$F$11,2,FALSE),0.25) | T33: =IF(O33="A",MAX(1,IFERROR(VLOOKUP(O33,Assumptions!$A$7:$F$11,3,FALSE),3)+IFERROR(VLOOKUP(O33,Assumptions!$A$7:$F$11,4,FALSE),8)/2-MAX(0,IF(R33="",0,R33)-IFERROR(VLOOKUP(O33,Assumptions!$A$7:$F$11,5,FALSE),1.5))),IFERROR(VLOOKUP(O33,Assumptions!$A$7:$F$11,5,FALSE),2.5)+IFERROR(VLOOKUP(O33,Assumptions!$A$7:$F$11,3,FALSE),3)+IFERROR(VLOOKUP(O33,Assumptions!$A$7:$F$11,4,FALSE),8)/2) | U33: =M33*S33/(1+Assumptions!$B$3)^T33 | V33: =IF(M33=0,"",ROUND(U33/M33*100,1)) | W33: =U33*Assumptions!$B$4 | X33: =IF(M33=0,"",ROUND(W33/M33*100,1)) | Y33: Grupo Rech | Z33: 5057720-48.2025.8.24.0023 | AB33: credibilita.com.br | AC33: WALTER JOSE CHIOSINI | AD33: Administrador | AE33: (11) 2177-7360 | AF33: (11) 2177-7201 | AH33: SP | AI33: SAO PAULO | AJ33: Fabricação de pneumáticos e de câmaras-de-ar | AK33: DEMAIS | AL33: ATIVA | AM33: https://credibilita.com.br/wp-content/uploads/2025/09/Relacao-Credores-29.04.2026.pdf | AN33: p2 r23 | AO33: p2: R$ 7.525.940,00 | AP33: QUORUM_LIST | AR33: OK_NO_TOTALS | AS33: ROWS:p2r23 UNRECONCILED_SOURCE VALUE_COL:Valor_Após_Analise CASE_NUMBER_CORRECTED | AT33: cf92cff797d2
A34: 33 | B34: NEW | D34: 0 | I34: FEDERACAO PERNAMBUCANA DE FUTEBOL | J34: FEDERACAO PERNAMBUCANA DE FUTEBOL, CPF/CNPJ Nº | K34: 10956258 | L34: 10956258000110 | M34: 7251967.1 | N34: 1 | O34: C | P34: ACTIVE | Q34: 44966 | R34: =IF(Q34="","",ROUND((TODAY()-Q34)/365.25,1)) | S34: =IFERROR(VLOOKUP(O34,Assumptions!$A$7:$F$11,2,FALSE),0.25) | T34: =IF(O34="A",MAX(1,IFERROR(VLOOKUP(O34,Assumptions!$A$7:$F$11,3,FALSE),3)+IFERROR(VLOOKUP(O34,Assumptions!$A$7:$F$11,4,FALSE),8)/2-MAX(0,IF(R34="",0,R34)-IFERROR(VLOOKUP(O34,Assumptions!$A$7:$F$11,5,FALSE),1.5))),IFERROR(VLOOKUP(O34,Assumptions!$A$7:$F$11,5,FALSE),2.5)+IFERROR(VLOOKUP(O34,Assumptions!$A$7:$F$11,3,FALSE),3)+IFERROR(VLOOKUP(O34,Assumptions!$A$7:$F$11,4,FALSE),8)/2) | U34: =M34*S34/(1+Assumptions!$B$3)^T34 | V34: =IF(M34=0,"",ROUND(U34/M34*100,1)) | W34: =U34*Assumptions!$B$4 | X34: =IF(M34=0,"",ROUND(W34/M34*100,1)) | Y34: CLUBE NÁUTICO CAPIBARIBE | Z34: 0011283-80.2023.8.17.2001 | AA34: TJPE | AB34: lrflideres.com.br | AC34: EVANDRO BARROS DE CARVALHO | AD34: Presidente | AH34: PE | AI34: RECIFE | AJ34: Produção e promoção de eventos esportivos | AK34: DEMAIS | AL34: ATIVA | AM34: https://lrflideres.com.br/wp-content/plugins/download-attachments/includes/download.php?id=5589 | AN34: p12 r9 | AO34: p12: R$ 7.251.967,09 | AP34: AJ_LIST | AQ34: 2023-11-27 | AR34: QUARANTINED | AS34: PARTIAL_DOC_CLASS_III_RECONCILED ROWS:p12r9 | AT34: 677be5783c06
A35: 34 | B35: NEW | D35: 0 | I35: ADDIANTE S.A | J35: ADDIANTE S.A | K35: 48430290 | L35: 48430290000130 | M35: 7135517 | N35: 1 | O35: B | P35: ACTIVE | Q35: 45845 | R35: =IF(Q35="","",ROUND((TODAY()-Q35)/365.25,1)) | S35: =IFERROR(VLOOKUP(O35,Assumptions!$A$7:$F$11,2,FALSE),0.25) | T35: =IF(O35="A",MAX(1,IFERROR(VLOOKUP(O35,Assumptions!$A$7:$F$11,3,FALSE),3)+IFERROR(VLOOKUP(O35,Assumptions!$A$7:$F$11,4,FALSE),8)/2-MAX(0,IF(R35="",0,R35)-IFERROR(VLOOKUP(O35,Assumptions!$A$7:$F$11,5,FALSE),1.5))),IFERROR(VLOOKUP(O35,Assumptions!$A$7:$F$11,5,FALSE),2.5)+IFERROR(VLOOKUP(O35,Assumptions!$A$7:$F$11,3,FALSE),3)+IFERROR(VLOOKUP(O35,Assumptions!$A$7:$F$11,4,FALSE),8)/2) | U35: =M35*S35/(1+Assumptions!$B$3)^T35 | V35: =IF(M35=0,"",ROUND(U35/M35*100,1)) | W35: =U35*Assumptions!$B$4 | X35: =IF(M35=0,"",ROUND(W35/M35*100,1)) | Y35: SOJAL COMERCIAL AGRICOLA LTDA e OUTROS | Z35: 0804401-51.2025.8.14.0039 | AA35: TJPA | AB35: lrflideres.com.br | AC35: FABIO ROBERTO LEITE | AD35: Presidente | AE35: (41) 9571-0152 | AH35: PR | AI35: CURITIBA | AJ35: Locação de outros meios de transporte não especificados anteriormente, sem condutor | AK35: DEMAIS | AL35: ATIVA | AM35: https://lrflideres.com.br/wp-content/plugins/download-attachments/includes/download.php?id=6879 | AN35: p1 r2 | AO35: p1: R$ 7.135.516,97 | AP35: AJ_LIST | AQ35: 2026-01-15 | AR35: OK | AS35: ROWS:p1r2 | AT35: c56751547323
A36: 35 | B36: NEW | D36: 0 | I36: SOLUS DO BRASIL LTDA | J36: SOLUS INDUSTRIA QUIMICA LTDA | K36: 21203489 | L36: 21203489000764, 21203489000926 | M36: 7058181.5 | N36: 1 | O36: B | P36: ACTIVE | Q36: 45845 | R36: =IF(Q36="","",ROUND((TODAY()-Q36)/365.25,1)) | S36: =IFERROR(VLOOKUP(O36,Assumptions!$A$7:$F$11,2,FALSE),0.25) | T36: =IF(O36="A",MAX(1,IFERROR(VLOOKUP(O36,Assumptions!$A$7:$F$11,3,FALSE),3)+IFERROR(VLOOKUP(O36,Assumptions!$A$7:$F$11,4,FALSE),8)/2-MAX(0,IF(R36="",0,R36)-IFERROR(VLOOKUP(O36,Assumptions!$A$7:$F$11,5,FALSE),1.5))),IFERROR(VLOOKUP(O36,Assumptions!$A$7:$F$11,5,FALSE),2.5)+IFERROR(VLOOKUP(O36,Assumptions!$A$7:$F$11,3,FALSE),3)+IFERROR(VLOOKUP(O36,Assumptions!$A$7:$F$11,4,FALSE),8)/2) | U36: =M36*S36/(1+Assumptions!$B$3)^T36 | V36: =IF(M36=0,"",ROUND(U36/M36*100,1)) | W36: =U36*Assumptions!$B$4 | X36: =IF(M36=0,"",ROUND(W36/M36*100,1)) | Y36: SOJAL COMERCIAL AGRICOLA LTDA e OUTROS | Z36: 0804401-51.2025.8.14.0039 | AA36: TJPA | AB36: lrflideres.com.br | AC36: ANDERSON JOSE FAUSTINO | AD36: Administrador | AE36: (43) 3162-2715 | AH36: PR | AI36: APUCARANA | AJ36: Fabricação de defensivos agrícolas | AK36: DEMAIS | AL36: ATIVA | AM36: https://lrflideres.com.br/wp-content/plugins/download-attachments/includes/download.php?id=6879 | AN36: p2 r10 | AO36: p2: R$ 7.058.181,50 | AP36: AJ_LIST | AQ36: 2026-01-15 | AR36: OK | AS36: ROWS:p2r10 | AT36: c56751547323
A37: 36 | B37: NEW | D37: 0 | I37: COMERCIO RACOES BEM BOM LTDA | J37: Fabrica De Ração | K37: 41324359 | L37: 41324359000100 | M37: 6642119 | N37: 1 | O37: B | P37: ACTIVE | Q37: 46130 | R37: =IF(Q37="","",ROUND((TODAY()-Q37)/365.25,1)) | S37: =IFERROR(VLOOKUP(O37,Assumptions!$A$7:$F$11,2,FALSE),0.25) | T37: =IF(O37="A",MAX(1,IFERROR(VLOOKUP(O37,Assumptions!$A$7:$F$11,3,FALSE),3)+IFERROR(VLOOKUP(O37,Assumptions!$A$7:$F$11,4,FALSE),8)/2-MAX(0,IF(R37="",0,R37)-IFERROR(VLOOKUP(O37,Assumptions!$A$7:$F$11,5,FALSE),1.5))),IFERROR(VLOOKUP(O37,Assumptions!$A$7:$F$11,5,FALSE),2.5)+IFERROR(VLOOKUP(O37,Assumptions!$A$7:$F$11,3,FALSE),3)+IFERROR(VLOOKUP(O37,Assumptions!$A$7:$F$11,4,FALSE),8)/2) | U37: =M37*S37/(1+Assumptions!$B$3)^T37 | V37: =IF(M37=0,"",ROUND(U37/M37*100,1)) | W37: =U37*Assumptions!$B$4 | X37: =IF(M37=0,"",ROUND(W37/M37*100,1)) | Y37: GRUPO 3E | Z37: 5341375-33.2026.8.09.0049 | AA37: TJGO | AB37: stenius.com.br | AC37: EDSON VIANDELLI LOPES | AD37: Sócio-Administrador | AE37: (62) 3389-9200 | AF37: (62) 8115-0283 | AH37: GO | AI37: GOIANESIA | AJ37: Fabricação de alimentos para animais | AK37: DEMAIS | AL37: ATIVA | AM37: https://stenius.com.br/wp-content/uploads/2026/06/EDITAL-GRUPO-3E.pdf | AN37: p13 r19 | AO37: p13: R$ 6.642.118,99 | AP37: DEBTOR_LIST | AQ37: 2026-06-22 | AR37: OK_NO_TOTALS | AS37: ROWS:p13r19 UNRECONCILED_SOURCE | AT37: 8e8832093a15
A38: 37 | B38: NEW | D38: 0 | I38: MISTRAS SOUTH AMERICA COMERCIO E SERVICOS LTDA | J38: NDT do Brasil Ltda | K38: 61615191 | L38: 61615191000190 | M38: 6623625.2 | N38: 1 | O38: B | Q38: 45756 | R38: =IF(Q38="","",ROUND((TODAY()-Q38)/365.25,1)) | S38: =IFERROR(VLOOKUP(O38,Assumptions!$A$7:$F$11,2,FALSE),0.25) | T38: =IF(O38="A",MAX(1,IFERROR(VLOOKUP(O38,Assumptions!$A$7:$F$11,3,FALSE),3)+IFERROR(VLOOKUP(O38,Assumptions!$A$7:$F$11,4,FALSE),8)/2-MAX(0,IF(R38="",0,R38)-IFERROR(VLOOKUP(O38,Assumptions!$A$7:$F$11,5,FALSE),1.5))),IFERROR(VLOOKUP(O38,Assumptions!$A$7:$F$11,5,FALSE),2.5)+IFERROR(VLOOKUP(O38,Assumptions!$A$7:$F$11,3,FALSE),3)+IFERROR(VLOOKUP(O38,Assumptions!$A$7:$F$11,4,FALSE),8)/2) | U38: =M38*S38/(1+Assumptions!$B$3)^T38 | V38: =IF(M38=0,"",ROUND(U38/M38*100,1)) | W38: =U38*Assumptions!$B$4 | X38: =IF(M38=0,"",ROUND(W38/M38*100,1)) | Y38: GRUPO EGESA (EGESA ENG S.A, EGESUR PART E EMP S.A, MATRIX INFRA LTDA, BEMVIVER ENG AMBIENTAL E SERV LTDA, DKF CONST E EMP LTDA, EGEPEL LTDA, ETR ASSESSORIA EMP E PART LTDA, MVT ENG E SERV LTDA, PARQUES DO VALE LTDA, ELMO RIBEIRO E ANA RIBEIRO) | Z38: 5088952-81.2025.8.13.0024 | AA38: TJMG | AB38: scalzilliaj.com.br | AC38: FABIO AUGUSTO TORATTI DE PAULA | AD38: Administrador | AE38: (11) 2061-8626 | AH38: SP | AI38: SAO PAULO | AJ38: Testes e análises técnicas | AK38: DEMAIS | AL38: ATIVA | AM38: https://scalzilliaj.com.br/sgc/download.php?file=files/processo_documento/processo_documento09514021082025_1_.pdf&nome=04 - Relação de credores das Recuperandas | AN38: p70 r9 | AO38: p70: R$ 6.623.625,24 | AP38: DEBTOR_LIST | AR38: OK | AS38: ROWS:p70r9 VALUE_COL:Valor_Atualizado CASE_NUMBER_CORRECTED CASE_FROM_PORTAL | AT38: 24ed98480a57
A39: 38 | B39: NEW | D39: 0 | I39: AGROFIELD ASSESSORIA ADMINISTRATIVA LTDA | J39: AGROFIELD COMÉRCIO E REPRESENTAÇÕES DE PRODUTOS AGRÍCOLAS | K39: 06284974 | L39: 06284974000635 | M39: 6434083.2 | N39: 1 | O39: D | R39: =IF(Q39="","",ROUND((TODAY()-Q39)/365.25,1)) | S39: =IFERROR(VLOOKUP(O39,Assumptions!$A$7:$F$11,2,FALSE),0.25) | T39: =IF(O39="A",MAX(1,IFERROR(VLOOKUP(O39,Assumptions!$A$7:$F$11,3,FALSE),3)+IFERROR(VLOOKUP(O39,Assumptions!$A$7:$F$11,4,FALSE),8)/2-MAX(0,IF(R39="",0,R39)-IFERROR(VLOOKUP(O39,Assumptions!$A$7:$F$11,5,FALSE),1.5))),IFERROR(VLOOKUP(O39,Assumptions!$A$7:$F$11,5,FALSE),2.5)+IFERROR(VLOOKUP(O39,Assumptions!$A$7:$F$11,3,FALSE),3)+IFERROR(VLOOKUP(O39,Assumptions!$A$7:$F$11,4,FALSE),8)/2) | U39: =M39*S39/(1+Assumptions!$B$3)^T39 | V39: =IF(M39=0,"",ROUND(U39/M39*100,1)) | W39: =U39*Assumptions!$B$4 | X39: =IF(M39=0,"",ROUND(W39/M39*100,1)) | Y39: COPA FRUIT IMPORTAÇÃO E EXPORTAÇÃO S.A | Z39: 0032731-52.2010.8.17.0001 | AB39: diligence.adm.br | AC39: SERGIO LUIZ SILVA DA FONSECA LINS | AD39: Sócio-Administrador | AE39: (81) 3339-1977 | AH39: PE | AI39: RECIFE | AJ39: Atividades de intermediação e agenciamento de serviços e negócios em geral, exceto imobiliários | AK39: DEMAIS | AL39: ATIVA | AM39: https://diligence.adm.br/wp-content/plugins/download-attachments/includes/download.php?id=4579 | AN39: p8 r2 | AO39: p8: R$ 6.434.083,18 | AP39: AJ_LIST | AQ39: 2024-06-11 | AR39: OK_NO_TOTALS | AS39: ROWS:p8r2 UNRECONCILED_SOURCE VALUE_COL:Crédito_1ª_Lista | AT39: bf3c4e448c3e
A40: 39 | B40: NEW | D40: 0 | I40: NORTESUL COMERCIAL AGRICOLA LTDA EM RECUPERACAO JUDICIAL | J40: NORTESUL COMERCIAL AGRICOLA LTDA | K40: 15626673 | L40: 15626673000129, 15626673000390, 15626673000552 | M40: 6258845.3 | N40: 1 | O40: B | P40: ACTIVE | Q40: 45845 | R40: =IF(Q40="","",ROUND((TODAY()-Q40)/365.25,1)) | S40: =IFERROR(VLOOKUP(O40,Assumptions!$A$7:$F$11,2,FALSE),0.25) | T40: =IF(O40="A",MAX(1,IFERROR(VLOOKUP(O40,Assumptions!$A$7:$F$11,3,FALSE),3)+IFERROR(VLOOKUP(O40,Assumptions!$A$7:$F$11,4,FALSE),8)/2-MAX(0,IF(R40="",0,R40)-IFERROR(VLOOKUP(O40,Assumptions!$A$7:$F$11,5,FALSE),1.5))),IFERROR(VLOOKUP(O40,Assumptions!$A$7:$F$11,5,FALSE),2.5)+IFERROR(VLOOKUP(O40,Assumptions!$A$7:$F$11,3,FALSE),3)+IFERROR(VLOOKUP(O40,Assumptions!$A$7:$F$11,4,FALSE),8)/2) | U40: =M40*S40/(1+Assumptions!$B$3)^T40 | V40: =IF(M40=0,"",ROUND(U40/M40*100,1)) | W40: =U40*Assumptions!$B$4 | X40: =IF(M40=0,"",ROUND(W40/M40*100,1)) | Y40: SOJAL COMERCIAL AGRICOLA LTDA e OUTROS | Z40: 0804401-51.2025.8.14.0039 | AA40: TJPA | AB40: lrflideres.com.br | AC40: JULIANO MENDES DOS SANTOS | AD40: Sócio-Administrador | AE40: (63) 3602-4239 | AH40: TO | AI40: PALMAS | AJ40: Comércio atacadista de matérias-primas agrícolas não especificadas anteriormente | AK40: DEMAIS | AL40: ATIVA | AM40: https://lrflideres.com.br/wp-content/plugins/download-attachments/includes/download.php?id=6879 | AN40: p2 r5 | AO40: p2: R$ 6.258.845,34 | AP40: AJ_LIST | AQ40: 2026-01-15 | AR40: OK | AS40: ROWS:p2r5 | AT40: c56751547323
A41: 40 | B41: NEW | D41: 0 | I41: L'OREAL BRASIL COMERCIAL DE COSMETICOS LTDA | J41: L'Oreal Brasil Comercio de Cosmeticos Ltda | K41: 30278428 | L41: 30278428000323 | M41: 5955264.1 | N41: 1 | O41: C | P41: ACTIVE | Q41: 44987 | R41: =IF(Q41="","",ROUND((TODAY()-Q41)/365.25,1)) | S41: =IFERROR(VLOOKUP(O41,Assumptions!$A$7:$F$11,2,FALSE),0.25) | T41: =IF(O41="A",MAX(1,IFERROR(VLOOKUP(O41,Assumptions!$A$7:$F$11,3,FALSE),3)+IFERROR(VLOOKUP(O41,Assumptions!$A$7:$F$11,4,FALSE),8)/2-MAX(0,IF(R41="",0,R41)-IFERROR(VLOOKUP(O41,Assumptions!$A$7:$F$11,5,FALSE),1.5))),IFERROR(VLOOKUP(O41,Assumptions!$A$7:$F$11,5,FALSE),2.5)+IFERROR(VLOOKUP(O41,Assumptions!$A$7:$F$11,3,FALSE),3)+IFERROR(VLOOKUP(O41,Assumptions!$A$7:$F$11,4,FALSE),8)/2) | U41: =M41*S41/(1+Assumptions!$B$3)^T41 | V41: =IF(M41=0,"",ROUND(U41/M41*100,1)) | W41: =U41*Assumptions!$B$4 | X41: =IF(M41=0,"",ROUND(W41/M41*100,1)) | Y41: GRUPO DP4 | Z41: 0005010-98.2023.8.16.0001 | AA41: TJPR | AB41: marquesadmjudicial.com.br | AC41: MARCELO ZIMET | AD41: Administrador | AE41: (21) 4505-9616 | AH41: RJ | AI41: RIO DE JANEIRO | AJ41: Comércio atacadista de cosméticos e produtos de perfumaria | AK41: DEMAIS | AL41: ATIVA | AM41: https://marquesadmjudicial.com.br/sgc/download.php?file=files/processo_documento/processo_documento15293208032024_1_.pdf&nome=Relação Nominal de Credores da AJ-Sintética | AN41: p28 r10 | AO41: p28: R$ 5.955.264,10 | AP41: AJ_LIST | AQ41: 2023-03-02 | AR41: QUARANTINED | AS41: PARTIAL_DOC_CLASS_III_RECONCILED ROWS:p28r10 | AT41: b465a5d11eec
A42: 41 | B42: NEW | D42: 0 | I42: INVISTA LOTEADORA E INCORPORADORA LTDA | J42: NÃO | K42: 18871750 | L42: 18871750000102 | M42: 5875236.1 | N42: 1 | O42: B | R42: =IF(Q42="","",ROUND((TODAY()-Q42)/365.25,1)) | S42: =IFERROR(VLOOKUP(O42,Assumptions!$A$7:$F$11,2,FALSE),0.25) | T42: =IF(O42="A",MAX(1,IFERROR(VLOOKUP(O42,Assumptions!$A$7:$F$11,3,FALSE),3)+IFERROR(VLOOKUP(O42,Assumptions!$A$7:$F$11,4,FALSE),8)/2-MAX(0,IF(R42="",0,R42)-IFERROR(VLOOKUP(O42,Assumptions!$A$7:$F$11,5,FALSE),1.5))),IFERROR(VLOOKUP(O42,Assumptions!$A$7:$F$11,5,FALSE),2.5)+IFERROR(VLOOKUP(O42,Assumptions!$A$7:$F$11,3,FALSE),3)+IFERROR(VLOOKUP(O42,Assumptions!$A$7:$F$11,4,FALSE),8)/2) | U42: =M42*S42/(1+Assumptions!$B$3)^T42 | V42: =IF(M42=0,"",ROUND(U42/M42*100,1)) | W42: =U42*Assumptions!$B$4 | X42: =IF(M42=0,"",ROUND(W42/M42*100,1)) | Y42: Grupo Rech | Z42: 5057720-48.2025.8.24.0023 | AB42: credibilita.com.br | AC42: JONES FERNANDES | AD42: Sócio-Administrador | AE42: (55) 3524-1044 | AF42: (55) 3524-1143 | AH42: RS | AI42: HORIZONTINA | AJ42: Incorporação de empreendimentos imobiliários | AK42: MICRO EMPRESA | AL42: ATIVA | AM42: https://credibilita.com.br/wp-content/uploads/2025/09/Relacao-Credores-29.04.2026.pdf | AN42: p1 r26 | AO42: p1: R$ 5.875.236,13 | AP42: QUORUM_LIST | AR42: OK_NO_TOTALS | AS42: ROWS:p1r26 UNRECONCILED_SOURCE VALUE_COL:Valor_Após_Analise CASE_NUMBER_CORRECTED | AT42: cf92cff797d2
A43: 42 | B43: NEW | D43: 0 | I43: CATAO CONFECCOES LTDA - EM RECUPERACAO JUDICIAL | J43: CATAO CONFECCOES LTDA | K43: 10775286 | L43: 10775286000807 | M43: 5843155.8 | N43: 2 | O43: C | P43: ACTIVE | Q43: 44571 | R43: =IF(Q43="","",ROUND((TODAY()-Q43)/365.25,1)) | S43: =IFERROR(VLOOKUP(O43,Assumptions!$A$7:$F$11,2,FALSE),0.25) | T43: =IF(O43="A",MAX(1,IFERROR(VLOOKUP(O43,Assumptions!$A$7:$F$11,3,FALSE),3)+IFERROR(VLOOKUP(O43,Assumptions!$A$7:$F$11,4,FALSE),8)/2-MAX(0,IF(R43="",0,R43)-IFERROR(VLOOKUP(O43,Assumptions!$A$7:$F$11,5,FALSE),1.5))),IFERROR(VLOOKUP(O43,Assumptions!$A$7:$F$11,5,FALSE),2.5)+IFERROR(VLOOKUP(O43,Assumptions!$A$7:$F$11,3,FALSE),3)+IFERROR(VLOOKUP(O43,Assumptions!$A$7:$F$11,4,FALSE),8)/2) | U43: =M43*S43/(1+Assumptions!$B$3)^T43 | V43: =IF(M43=0,"",ROUND(U43/M43*100,1)) | W43: =U43*Assumptions!$B$4 | X43: =IF(M43=0,"",ROUND(W43/M43*100,1)) | Y43: GRUPO CATTAN | Z43: 0002484-82.2022.8.17.2001 | AA43: TJPE | AB43: lrflideres.com.br | AC43: FLAVIO DANTAS CATAO | AD43: Sócio-Administrador | AE43: 000000000000 | AH43: PE | AI43: RECIFE | AJ43: Comércio varejista de artigos do vestuário e acessórios | AK43: DEMAIS | AL43: ATIVA | AM43: https://lrflideres.com.br/wp-content/plugins/download-attachments/includes/download.php?id=4023 | AN43: p4 r60; p9 r62 | AO43: p4: R$ 1.447.463,41; p9: R$ 4.395.692,34 | AP43: DEBTOR_LIST | AR43: QUARANTINED | AS43: PARTIAL_DOC_CLASS_III_RECONCILED ROWS:p4r60,p9r62 | AT43: f3b6182e3aa2
A44: 43 | B44: NEW | D44: 0 | I44: SUZANO S.A. | J44: Av. Brg. Faria Lima, 1355 - Pinheiros, São Paulo - SP - CEP 01452-002 | K44: 16404287 | L44: 16404287057009 | M44: 5686333.3 | N44: 1 | O44: U | R44: =IF(Q44="","",ROUND((TODAY()-Q44)/365.25,1)) | S44: =IFERROR(VLOOKUP(O44,Assumptions!$A$7:$F$11,2,FALSE),0.25) | T44: =IF(O44="A",MAX(1,IFERROR(VLOOKUP(O44,Assumptions!$A$7:$F$11,3,FALSE),3)+IFERROR(VLOOKUP(O44,Assumptions!$A$7:$F$11,4,FALSE),8)/2-MAX(0,IF(R44="",0,R44)-IFERROR(VLOOKUP(O44,Assumptions!$A$7:$F$11,5,FALSE),1.5))),IFERROR(VLOOKUP(O44,Assumptions!$A$7:$F$11,5,FALSE),2.5)+IFERROR(VLOOKUP(O44,Assumptions!$A$7:$F$11,3,FALSE),3)+IFERROR(VLOOKUP(O44,Assumptions!$A$7:$F$11,4,FALSE),8)/2) | U44: =M44*S44/(1+Assumptions!$B$3)^T44 | V44: =IF(M44=0,"",ROUND(U44/M44*100,1)) | W44: =U44*Assumptions!$B$4 | X44: =IF(M44=0,"",ROUND(W44/M44*100,1)) | Y44: Base | Z44: (not found in document) | AB44: ajruiz.com.br | AC44: JOAO ALBERTO FERNANDEZ DE ABREU | AD44: Presidente | AE44: (11) 3636-5000 | AH44: BA | AI44: SALVADOR | AJ44: Fabricação de celulose e outras pastas para a fabricação de papel | AK44: DEMAIS | AL44: ATIVA | AM44: https://ajruiz.com.br/sites/default/files/public/arquivos-processos/2023-11/4_relacao_de_credores_analitica_art._51_iii_da_lre.pdf | AN44: p4 r14 | AO44: p4: R$ 5.686.333,34 | AP44: UNKNOWN | AR44: OK | AS44: ROWS:p4r14 CASE_NUMBER_CORRECTED | AT44: 2407a56c3502
A45: 44 | B45: NEW | D45: 0 | I45: BOSCH HOME COMFORT DO BRASIL LTDA | J45: Rod. Presidente Dutra, Km 141, s/n, Km 141, Eugenio de Mello, São Paulo CEP 12247901 | K45: 33284522 | L45: 33284522000626 | M45: 5064633.8 | N45: 1 | O45: C | R45: =IF(Q45="","",ROUND((TODAY()-Q45)/365.25,1)) | S45: =IFERROR(VLOOKUP(O45,Assumptions!$A$7:$F$11,2,FALSE),0.25) | T45: =IF(O45="A",MAX(1,IFERROR(VLOOKUP(O45,Assumptions!$A$7:$F$11,3,FALSE),3)+IFERROR(VLOOKUP(O45,Assumptions!$A$7:$F$11,4,FALSE),8)/2-MAX(0,IF(R45="",0,R45)-IFERROR(VLOOKUP(O45,Assumptions!$A$7:$F$11,5,FALSE),1.5))),IFERROR(VLOOKUP(O45,Assumptions!$A$7:$F$11,5,FALSE),2.5)+IFERROR(VLOOKUP(O45,Assumptions!$A$7:$F$11,3,FALSE),3)+IFERROR(VLOOKUP(O45,Assumptions!$A$7:$F$11,4,FALSE),8)/2) | U45: =M45*S45/(1+Assumptions!$B$3)^T45 | V45: =IF(M45=0,"",ROUND(U45/M45*100,1)) | W45: =U45*Assumptions!$B$4 | X45: =IF(M45=0,"",ROUND(W45/M45*100,1)) | Y45: REAL DISTRIBUIDORA ÚNICA RIO COMÉRCIO DE REFRIGERAÇÃO LTDA. | Z45: 0873061-47.2023.8.19.0001 | AB45: inova-aj.com.br | AC45: FERNANDO LUIZ LAGUNA CUNHA | AD45: Administrador | AE45: (92) 3301-5000 | AH45: AM | AI45: MANAUS | AJ45: Serviços combinados de escritório e apoio administrativo | AK45: DEMAIS | AL45: ATIVA | AM45: https://inova-aj.com.br/wp-content/uploads/2026/08/1a-Relacao-de-Credores-Real.pdf | AN45: p1 r35 | AO45: p1: R$ 5.064.633,83 | AP45: AJ_LIST | AQ45: 2023-06-05 | AR45: OK | AS45: ALT_VALUE:R$3.682.536,03 ROWS:p1r35 | AT45: 8eb5d0d64353
A46: 45 | B46: NEW | D46: 0 | I46: VIBRA ENERGIA S.A | J46: PETRÓLEO BRASILEIRO S.A. - PETROBRÁS e Vibra Energia S.A | K46: 34274233 | L46: 34274233000102 | M46: 5004769.6 | N46: 2 | O46: B | Q46: 45756 | R46: =IF(Q46="","",ROUND((TODAY()-Q46)/365.25,1)) | S46: =IFERROR(VLOOKUP(O46,Assumptions!$A$7:$F$11,2,FALSE),0.25) | T46: =IF(O46="A",MAX(1,IFERROR(VLOOKUP(O46,Assumptions!$A$7:$F$11,3,FALSE),3)+IFERROR(VLOOKUP(O46,Assumptions!$A$7:$F$11,4,FALSE),8)/2-MAX(0,IF(R46="",0,R46)-IFERROR(VLOOKUP(O46,Assumptions!$A$7:$F$11,5,FALSE),1.5))),IFERROR(VLOOKUP(O46,Assumptions!$A$7:$F$11,5,FALSE),2.5)+IFERROR(VLOOKUP(O46,Assumptions!$A$7:$F$11,3,FALSE),3)+IFERROR(VLOOKUP(O46,Assumptions!$A$7:$F$11,4,FALSE),8)/2) | U46: =M46*S46/(1+Assumptions!$B$3)^T46 | V46: =IF(M46=0,"",ROUND(U46/M46*100,1)) | W46: =U46*Assumptions!$B$4 | X46: =IF(M46=0,"",ROUND(W46/M46*100,1)) | Y46: GRUPO EGESA (EGESA ENG S.A, EGESUR PART E EMP S.A, MATRIX INFRA LTDA, BEMVIVER ENG AMBIENTAL E SERV LTDA, DKF CONST E EMP LTDA, EGEPEL LTDA, ETR ASSESSORIA EMP E PART LTDA, MVT ENG E SERV LTDA, PARQUES DO VALE LTDA, ELMO RIBEIRO E ANA RIBEIRO) | Z46: 5088952-81.2025.8.13.0024 | AA46: TJMG | AB46: scalzilliaj.com.br | AC46: ERNESTO PERES POUSADA JUNIOR | AD46: Presidente | AE46: (21) 2354-3151 | AF46: (21) 2354-3146 | AH46: RJ | AI46: RIO DE JANEIRO | AJ46: Comércio atacadista de álcool carburante, biodiesel, gasolina e demais derivados de petróleo, exceto lubrificantes, não realizado por transportador re | AK46: DEMAIS | AL46: ATIVA | AM46: https://scalzilliaj.com.br/sgc/download.php?file=files/processo_documento/processo_documento09514021082025_1_.pdf&nome=04 - Relação de credores das Recuperandas | AN46: p71 r8; p76 r5 | AO46: p71: R$ 396.274,51; p76: R$ 4.608.495,09 | AP46: DEBTOR_LIST | AR46: OK | AS46: ROWS:p71r8,p76r5 VALUE_COL:Valor_Atualizado CASE_NUMBER_CORRECTED CASE_FROM_PORTAL | AT46: 24ed98480a57
A47: 46 | B47: NEW | D47: 0 | I47: JF PASQUA CONDUTORES ELETRICOS LTDA | J47: JF PASQUA CONDUTORES ELETRICOS LTDA | K47: 03981899 | L47: 03981899000169 | M47: 4940520.9 | N47: 2 | O47: C | P47: ACTIVE | Q47: 45068 | R47: =IF(Q47="","",ROUND((TODAY()-Q47)/365.25,1)) | S47: =IFERROR(VLOOKUP(O47,Assumptions!$A$7:$F$11,2,FALSE),0.25) | T47: =IF(O47="A",MAX(1,IFERROR(VLOOKUP(O47,Assumptions!$A$7:$F$11,3,FALSE),3)+IFERROR(VLOOKUP(O47,Assumptions!$A$7:$F$11,4,FALSE),8)/2-MAX(0,IF(R47="",0,R47)-IFERROR(VLOOKUP(O47,Assumptions!$A$7:$F$11,5,FALSE),1.5))),IFERROR(VLOOKUP(O47,Assumptions!$A$7:$F$11,5,FALSE),2.5)+IFERROR(VLOOKUP(O47,Assumptions!$A$7:$F$11,3,FALSE),3)+IFERROR(VLOOKUP(O47,Assumptions!$A$7:$F$11,4,FALSE),8)/2) | U47: =M47*S47/(1+Assumptions!$B$3)^T47 | V47: =IF(M47=0,"",ROUND(U47/M47*100,1)) | W47: =U47*Assumptions!$B$4 | X47: =IF(M47=0,"",ROUND(W47/M47*100,1)) | Y47: Grupo Conduscabos | Z47: 8005129-09.2023.8.05.0039 | AA47: TJBA | AB47: assistjud.com.br | AC47: REGINA MARIA PASQUA SANTOS | AD47: Administrador | AE47: (35) 3559-6789 | AH47: MG | AI47: GUAXUPE | AJ47: Metalurgia do cobre | AK47: DEMAIS | AL47: ATIVA | AM47: https://assistjud.com.br/wp-content/uploads/elementor/forms/65098c80a5824.pdf | AN47: p8 r4; p18 r6 | AO47: p8: R$ 2.217.364,91; p18: R$ 2.723.156,00 | AP47: AJ_LIST | AQ47: 2023-09-18 | AR47: OK_NO_TOTALS | AS47: ROWS:p8r4,p18r6 UNRECONCILED_SOURCE | AT47: a0ae32a59c29
A48: 47 | B48: NEW | D48: 0 | I48: TRANSPORTADORA MARCAN LTDA. | J48: Transporte Coletivo San Remo Ltda, Transnew do Vale Transportes LTDA e Transportadora Marcan LTDA | K48: 19709369 | L48: 19709369000104 | M48: 4757313 | N48: 1 | O48: B | Q48: 45756 | R48: =IF(Q48="","",ROUND((TODAY()-Q48)/365.25,1)) | S48: =IFERROR(VLOOKUP(O48,Assumptions!$A$7:$F$11,2,FALSE),0.25) | T48: =IF(O48="A",MAX(1,IFERROR(VLOOKUP(O48,Assumptions!$A$7:$F$11,3,FALSE),3)+IFERROR(VLOOKUP(O48,Assumptions!$A$7:$F$11,4,FALSE),8)/2-MAX(0,IF(R48="",0,R48)-IFERROR(VLOOKUP(O48,Assumptions!$A$7:$F$11,5,FALSE),1.5))),IFERROR(VLOOKUP(O48,Assumptions!$A$7:$F$11,5,FALSE),2.5)+IFERROR(VLOOKUP(O48,Assumptions!$A$7:$F$11,3,FALSE),3)+IFERROR(VLOOKUP(O48,Assumptions!$A$7:$F$11,4,FALSE),8)/2) | U48: =M48*S48/(1+Assumptions!$B$3)^T48 | V48: =IF(M48=0,"",ROUND(U48/M48*100,1)) | W48: =U48*Assumptions!$B$4 | X48: =IF(M48=0,"",ROUND(W48/M48*100,1)) | Y48: GRUPO EGESA (EGESA ENG S.A, EGESUR PART E EMP S.A, MATRIX INFRA LTDA, BEMVIVER ENG AMBIENTAL E SERV LTDA, DKF CONST E EMP LTDA, EGEPEL LTDA, ETR ASSESSORIA EMP E PART LTDA, MVT ENG E SERV LTDA, PARQUES DO VALE LTDA, ELMO RIBEIRO E ANA RIBEIRO) | Z48: 5088952-81.2025.8.13.0024 | AA48: TJMG | AB48: scalzilliaj.com.br | AC48: GERVASIO TASSI FILHO | AD48: Sócio-Administrador | AE48: (81) 3543-0330 | AF48: (81) 9267-7488 | AH48: PE | AI48: IGARASSU | AJ48: Transporte rodoviário coletivo de passageiros, com itinerário fixo, intermunicipal em região metropolitana | AK48: DEMAIS | AL48: ATIVA | AM48: https://scalzilliaj.com.br/sgc/download.php?file=files/processo_documento/processo_documento09514021082025_1_.pdf&nome=04 - Relação de credores das Recuperandas | AN48: p74 r13 | AO48: p74: R$ 4.757.312,99 | AP48: DEBTOR_LIST | AR48: OK | AS48: ROWS:p74r13 VALUE_COL:Valor_Atualizado CASE_NUMBER_CORRECTED CASE_FROM_PORTAL | AT48: 24ed98480a57
A49: 48 | B49: NEW | D49: 0 | I49: PRO NOVA DISTRIBUIDORA E COMERCIO DE COSMETICOS LTDA | J49: Pro Nova Distribuidora e Comercio de Cosmeticos Ltda | K49: 21998451 | L49: 21998451001373 | M49: 4694462.5 | N49: 1 | O49: C | P49: ACTIVE | Q49: 44987 | R49: =IF(Q49="","",ROUND((TODAY()-Q49)/365.25,1)) | S49: =IFERROR(VLOOKUP(O49,Assumptions!$A$7:$F$11,2,FALSE),0.25) | T49: =IF(O49="A",MAX(1,IFERROR(VLOOKUP(O49,Assumptions!$A$7:$F$11,3,FALSE),3)+IFERROR(VLOOKUP(O49,Assumptions!$A$7:$F$11,4,FALSE),8)/2-MAX(0,IF(R49="",0,R49)-IFERROR(VLOOKUP(O49,Assumptions!$A$7:$F$11,5,FALSE),1.5))),IFERROR(VLOOKUP(O49,Assumptions!$A$7:$F$11,5,FALSE),2.5)+IFERROR(VLOOKUP(O49,Assumptions!$A$7:$F$11,3,FALSE),3)+IFERROR(VLOOKUP(O49,Assumptions!$A$7:$F$11,4,FALSE),8)/2) | U49: =M49*S49/(1+Assumptions!$B$3)^T49 | V49: =IF(M49=0,"",ROUND(U49/M49*100,1)) | W49: =U49*Assumptions!$B$4 | X49: =IF(M49=0,"",ROUND(W49/M49*100,1)) | Y49: GRUPO DP4 | Z49: 0005010-98.2023.8.16.0001 | AA49: TJPR | AB49: marquesadmjudicial.com.br | AC49: ANA CLAUDIA GALVAO CARICATI | AD49: Sócio-Administrador | AE49: (11) 4772-8024 | AH49: SP | AI49: JANDIRA | AJ49: Comércio atacadista de cosméticos e produtos de perfumaria | AK49: DEMAIS | AL49: ATIVA | AM49: https://marquesadmjudicial.com.br/sgc/download.php?file=files/processo_documento/processo_documento15293208032024_1_.pdf&nome=Relação Nominal de Credores da AJ-Sintética | AN49: p30 r9 | AO49: p30: R$ 4.694.462,47 | AP49: AJ_LIST | AQ49: 2023-03-02 | AR49: QUARANTINED | AS49: PARTIAL_DOC_CLASS_III_RECONCILED ROWS:p30r9 | AT49: b465a5d11eec
A50: 49 | B50: NEW | D50: 0 | I50: BALDAN IMPLEMENTOS AGRICOLAS S A | J50: NÃO | K50: 52311347 | L50: 52311347000906 | M50: 4681142.4 | N50: 1 | O50: B | R50: =IF(Q50="","",ROUND((TODAY()-Q50)/365.25,1)) | S50: =IFERROR(VLOOKUP(O50,Assumptions!$A$7:$F$11,2,FALSE),0.25) | T50: =IF(O50="A",MAX(1,IFERROR(VLOOKUP(O50,Assumptions!$A$7:$F$11,3,FALSE),3)+IFERROR(VLOOKUP(O50,Assumptions!$A$7:$F$11,4,FALSE),8)/2-MAX(0,IF(R50="",0,R50)-IFERROR(VLOOKUP(O50,Assumptions!$A$7:$F$11,5,FALSE),1.5))),IFERROR(VLOOKUP(O50,Assumptions!$A$7:$F$11,5,FALSE),2.5)+IFERROR(VLOOKUP(O50,Assumptions!$A$7:$F$11,3,FALSE),3)+IFERROR(VLOOKUP(O50,Assumptions!$A$7:$F$11,4,FALSE),8)/2) | U50: =M50*S50/(1+Assumptions!$B$3)^T50 | V50: =IF(M50=0,"",ROUND(U50/M50*100,1)) | W50: =U50*Assumptions!$B$4 | X50: =IF(M50=0,"",ROUND(W50/M50*100,1)) | Y50: Grupo Rech | Z50: 5057720-48.2025.8.24.0023 | AB50: credibilita.com.br | AC50: CAIO FRANCO GIARETTA | AD50: Diretor | AE50: (16) 3221-6500 | AF50: (16) 3221-6581 | AH50: SP | AI50: MATAO | AJ50: Fabricação de máquinas e equipamentos para a agricultura e pecuária, peças e acessórios, exceto para irrigação | AK50: DEMAIS | AL50: ATIVA | AM50: https://credibilita.com.br/wp-content/uploads/2025/09/Relacao-Credores-29.04.2026.pdf | AN50: p1 r3 | AO50: p1: R$ 4.681.142,41 | AP50: QUORUM_LIST | AR50: OK_NO_TOTALS | AS50: ROWS:p1r3 UNRECONCILED_SOURCE VALUE_COL:Valor_Após_Analise CASE_NUMBER_CORRECTED | AT50: cf92cff797d2
A51: 50 | B51: NEW | D51: 0 | I51: NORTEBAG INDUSTRIA DE EMBALAGENS S.A. | J51: 05399071000122 | K51: 05399071 | L51: 05399071000122 | M51: 4680282.8 | N51: 1 | O51: C | P51: ACTIVE | Q51: 45057 | R51: =IF(Q51="","",ROUND((TODAY()-Q51)/365.25,1)) | S51: =IFERROR(VLOOKUP(O51,Assumptions!$A$7:$F$11,2,FALSE),0.25) | T51: =IF(O51="A",MAX(1,IFERROR(VLOOKUP(O51,Assumptions!$A$7:$F$11,3,FALSE),3)+IFERROR(VLOOKUP(O51,Assumptions!$A$7:$F$11,4,FALSE),8)/2-MAX(0,IF(R51="",0,R51)-IFERROR(VLOOKUP(O51,Assumptions!$A$7:$F$11,5,FALSE),1.5))),IFERROR(VLOOKUP(O51,Assumptions!$A$7:$F$11,5,FALSE),2.5)+IFERROR(VLOOKUP(O51,Assumptions!$A$7:$F$11,3,FALSE),3)+IFERROR(VLOOKUP(O51,Assumptions!$A$7:$F$11,4,FALSE),8)/2) | U51: =M51*S51/(1+Assumptions!$B$3)^T51 | V51: =IF(M51=0,"",ROUND(U51/M51*100,1)) | W51: =U51*Assumptions!$B$4 | X51: =IF(M51=0,"",ROUND(W51/M51*100,1)) | Y51: TOP TEXTIL EMBALAGENS LTDA | Z51: 5011460-87.2023.8.24.0020 | AA51: TJSC | AB51: cataliseaj.com.br | AC51: MARCO ANTONIO GARCIA | AD51: Diretor | AE51: (92) 3396-6621 | AH51: AM | AI51: MANAUS | AJ51: Fabricação de outros produtos têxteis não especificados anteriormente | AK51: DEMAIS | AL51: ATIVA | AM51: https://cataliseaj.com.br/sgc/download.php?file=files/processo_documento/processo_documento15092204102024_1_.pdf&nome=02. RELAÇÃO DE CREDORES | AN51: p2 r66 | AO51: p2: R$ 4.680.282,82 | AP51: DEBTOR_LIST | AR51: OK_NO_TOTALS | AS51: ROWS:p2r66 UNRECONCILED_SOURCE | AT51: 741aed48dd00
A52: 51 | B52: NEW | D52: 0 | I52: SERRINHA AMBIENTAL TRANSPORTES LTDA | J52: SERRINHA AMBIENTAL TRANSPORTES LTDA | K52: 32851823 | L52: 32851823000117 | M52: 4672725.1 | N52: 1 | O52: C | P52: ACTIVE | Q52: 45264 | R52: =IF(Q52="","",ROUND((TODAY()-Q52)/365.25,1)) | S52: =IFERROR(VLOOKUP(O52,Assumptions!$A$7:$F$11,2,FALSE),0.25) | T52: =IF(O52="A",MAX(1,IFERROR(VLOOKUP(O52,Assumptions!$A$7:$F$11,3,FALSE),3)+IFERROR(VLOOKUP(O52,Assumptions!$A$7:$F$11,4,FALSE),8)/2-MAX(0,IF(R52="",0,R52)-IFERROR(VLOOKUP(O52,Assumptions!$A$7:$F$11,5,FALSE),1.5))),IFERROR(VLOOKUP(O52,Assumptions!$A$7:$F$11,5,FALSE),2.5)+IFERROR(VLOOKUP(O52,Assumptions!$A$7:$F$11,3,FALSE),3)+IFERROR(VLOOKUP(O52,Assumptions!$A$7:$F$11,4,FALSE),8)/2) | U52: =M52*S52/(1+Assumptions!$B$3)^T52 | V52: =IF(M52=0,"",ROUND(U52/M52*100,1)) | W52: =U52*Assumptions!$B$4 | X52: =IF(M52=0,"",ROUND(W52/M52*100,1)) | Y52: Alto Uruguai Indústria e Comércio de Óleos Ltda | Z52: 5012743-51.2023.8.24.0019 | AA52: TJSC | AB52: ajruiz.com.br | AC52: VOLNEI DOS SANTOS | AD52: Administrador | AE52: (49) 9914-4317 | AH52: SC | AI52: CHAPECO | AJ52: Transporte rodoviário de carga, exceto produtos perigosos e mudanças, intermunicipal, interestadual e internacional | AK52: DEMAIS | AL52: ATIVA | AM52: https://ajruiz.com.br/sites/default/files/public/arquivos-processos/2026-06/alto_uruguai_qgc_junho.2026.pdf | AN52: p1 r35 | AO52: p1: R$ 4.672.725,10 | AP52: UNKNOWN | AR52: OK | AS52: ROWS:p1r35 VALUE_COL:Valor_Do_Crédito | AT52: 75336e98f447
A53: 52 | B53: NEW | D53: 0 | I53: YARA BRASIL FERTILIZANTES S/A | J53: YARA BRASIL FERTILIZANTES S/A | K53: 92660604 | L53: 92660604014132 | M53: 4591380 | N53: 1 | O53: B | P53: ACTIVE | Q53: 46030 | R53: =IF(Q53="","",ROUND((TODAY()-Q53)/365.25,1)) | S53: =IFERROR(VLOOKUP(O53,Assumptions!$A$7:$F$11,2,FALSE),0.25) | T53: =IF(O53="A",MAX(1,IFERROR(VLOOKUP(O53,Assumptions!$A$7:$F$11,3,FALSE),3)+IFERROR(VLOOKUP(O53,Assumptions!$A$7:$F$11,4,FALSE),8)/2-MAX(0,IF(R53="",0,R53)-IFERROR(VLOOKUP(O53,Assumptions!$A$7:$F$11,5,FALSE),1.5))),IFERROR(VLOOKUP(O53,Assumptions!$A$7:$F$11,5,FALSE),2.5)+IFERROR(VLOOKUP(O53,Assumptions!$A$7:$F$11,3,FALSE),3)+IFERROR(VLOOKUP(O53,Assumptions!$A$7:$F$11,4,FALSE),8)/2) | U53: =M53*S53/(1+Assumptions!$B$3)^T53 | V53: =IF(M53=0,"",ROUND(U53/M53*100,1)) | W53: =U53*Assumptions!$B$4 | X53: =IF(M53=0,"",ROUND(W53/M53*100,1)) | Y53: GRUPO FERRARI (ALEX, ALEXANDRE , ANDRIELLE FERRARI MANTELLI, ARCIR LUIS, ERICA SANTOS ASSIS LIMA, FERNANDO MANTELLI, IDELSI, TALITA LEITE SILVA, AGROPECUARIA FERRARI LTDA E FERRARI ARMAZENS GERAIS) | Z53: 5011369-81.2026.8.09.0093 | AA53: TJGO | AB53: scalzilliaj.com.br | AC53: ADRIANA DEL CARMEN NUNEZ ARANGUREN | AD53: Diretor | AE53: (51) 3230-1300 | AH53: RS | AI53: PORTO ALEGRE | AJ53: Fabricação de adubos e fertilizantes, exceto organo-minerais | AK53: DEMAIS | AL53: ATIVA | AM53: https://scalzilliaj.com.br/sgc/download.php?file=files/processo_documento/processo_documento11421222052026_1_.pdf&nome=08. Lista de credores do edital do art. 52, §1º da LREF | AN53: p3 r7 | AO53: p3: R$ 4.591.380,00 | AP53: UNKNOWN | AR53: OK_NO_TOTALS | AS53: ROWS:p3r7 UNRECONCILED_SOURCE | AT53: c536a2fa4da3
A54: 53 | B54: NEW | D54: 0 | I54: IPIRANGA PRODUTOS DE PETROLEO S.A. | J54: AV SIDNEY CARDON DE OLIVEIRA,1879 - PAULINIA-SP - CEP 13140-000 | K54: 33337122 | L54: 33337122005358 | M54: 4589364.3 | N54: 1 | O54: U | R54: =IF(Q54="","",ROUND((TODAY()-Q54)/365.25,1)) | S54: =IFERROR(VLOOKUP(O54,Assumptions!$A$7:$F$11,2,FALSE),0.25) | T54: =IF(O54="A",MAX(1,IFERROR(VLOOKUP(O54,Assumptions!$A$7:$F$11,3,FALSE),3)+IFERROR(VLOOKUP(O54,Assumptions!$A$7:$F$11,4,FALSE),8)/2-MAX(0,IF(R54="",0,R54)-IFERROR(VLOOKUP(O54,Assumptions!$A$7:$F$11,5,FALSE),1.5))),IFERROR(VLOOKUP(O54,Assumptions!$A$7:$F$11,5,FALSE),2.5)+IFERROR(VLOOKUP(O54,Assumptions!$A$7:$F$11,3,FALSE),3)+IFERROR(VLOOKUP(O54,Assumptions!$A$7:$F$11,4,FALSE),8)/2) | U54: =M54*S54/(1+Assumptions!$B$3)^T54 | V54: =IF(M54=0,"",ROUND(U54/M54*100,1)) | W54: =U54*Assumptions!$B$4 | X54: =IF(M54=0,"",ROUND(W54/M54*100,1)) | Y54: Base | Z54: (not found in document) | AB54: ajruiz.com.br | AC54: CARLOS FREDERICO RESENDE | AD54: Administrador | AE54: (21) 2574-5858 | AH54: RJ | AI54: RIO DE JANEIRO | AJ54: Comércio atacadista de álcool carburante, biodiesel, gasolina e demais derivados de petróleo, exceto lubrificantes, não realizado por transportador re | AK54: DEMAIS | AL54: ATIVA | AM54: https://ajruiz.com.br/sites/default/files/public/arquivos-processos/2023-11/4_relacao_de_credores_analitica_art._51_iii_da_lre.pdf | AN54: p3 r20 | AO54: p3: R$ 4.589.364,33 | AP54: UNKNOWN | AR54: OK | AS54: ROWS:p3r20 CASE_NUMBER_CORRECTED | AT54: 2407a56c3502
A55: 54 | B55: NEW | D55: 0 | I55: BACUPARI AGROINDUSTRIA LTDA | J55: Bacupari Agroindustria - Lakes Fish | K55: 19907274 | L55: 19907274000197 | M55: 4500000 | N55: 1 | O55: B | P55: ACTIVE | Q55: 46130 | R55: =IF(Q55="","",ROUND((TODAY()-Q55)/365.25,1)) | S55: =IFERROR(VLOOKUP(O55,Assumptions!$A$7:$F$11,2,FALSE),0.25) | T55: =IF(O55="A",MAX(1,IFERROR(VLOOKUP(O55,Assumptions!$A$7:$F$11,3,FALSE),3)+IFERROR(VLOOKUP(O55,Assumptions!$A$7:$F$11,4,FALSE),8)/2-MAX(0,IF(R55="",0,R55)-IFERROR(VLOOKUP(O55,Assumptions!$A$7:$F$11,5,FALSE),1.5))),IFERROR(VLOOKUP(O55,Assumptions!$A$7:$F$11,5,FALSE),2.5)+IFERROR(VLOOKUP(O55,Assumptions!$A$7:$F$11,3,FALSE),3)+IFERROR(VLOOKUP(O55,Assumptions!$A$7:$F$11,4,FALSE),8)/2) | U55: =M55*S55/(1+Assumptions!$B$3)^T55 | V55: =IF(M55=0,"",ROUND(U55/M55*100,1)) | W55: =U55*Assumptions!$B$4 | X55: =IF(M55=0,"",ROUND(W55/M55*100,1)) | Y55: GRUPO 3E | Z55: 5341375-33.2026.8.09.0049 | AA55: TJGO | AB55: stenius.com.br | AC55: ANA PAOLA BRANDAO RAZEM ABRAO | AD55: Sócio-Administrador | AE55: (61) 9655-6611 | AH55: DF | AI55: BRASILIA | AJ55: Compra e venda de imóveis próprios | AK55: DEMAIS | AL55: ATIVA | AM55: https://stenius.com.br/wp-content/uploads/2026/06/EDITAL-GRUPO-3E.pdf | AN55: p10 r29 | AO55: p10: R$ 4.500.000,00 | AP55: DEBTOR_LIST | AQ55: 2026-06-22 | AR55: OK_NO_TOTALS | AS55: ROWS:p10r29 UNRECONCILED_SOURCE | AT55: 8e8832093a15
A56: 55 | B56: NEW | D56: 0 | I56: CENTRO AVANCADO DE NEUROLOGIA E NEUROCIRURGIA S/S | J56: CENTRO AVANCADO DE NEUROLOGIA E NEUROCIRURGIA S/S ( | K56: 18331491 | L56: 18331491000119 | M56: 3947275.5 | N56: 1 | O56: C | P56: ACTIVE | Q56: 44735 | R56: =IF(Q56="","",ROUND((TODAY()-Q56)/365.25,1)) | S56: =IFERROR(VLOOKUP(O56,Assumptions!$A$7:$F$11,2,FALSE),0.25) | T56: =IF(O56="A",MAX(1,IFERROR(VLOOKUP(O56,Assumptions!$A$7:$F$11,3,FALSE),3)+IFERROR(VLOOKUP(O56,Assumptions!$A$7:$F$11,4,FALSE),8)/2-MAX(0,IF(R56="",0,R56)-IFERROR(VLOOKUP(O56,Assumptions!$A$7:$F$11,5,FALSE),1.5))),IFERROR(VLOOKUP(O56,Assumptions!$A$7:$F$11,5,FALSE),2.5)+IFERROR(VLOOKUP(O56,Assumptions!$A$7:$F$11,3,FALSE),3)+IFERROR(VLOOKUP(O56,Assumptions!$A$7:$F$11,4,FALSE),8)/2) | U56: =M56*S56/(1+Assumptions!$B$3)^T56 | V56: =IF(M56=0,"",ROUND(U56/M56*100,1)) | W56: =U56*Assumptions!$B$4 | X56: =IF(M56=0,"",ROUND(W56/M56*100,1)) | Y56: ASSOCIAÇÃO DE CARIDADE SANTA CASA DO RIO GRANDE | Z56: 5012306-16.2022.8.21.0023 | AA56: TJRS | AB56: scalzilliaj.com.br | AC56: GUSTAVO RASSIER ISOLAN | AD56: Sócio-Administrador | AE56: (51) 3276-7818 | AH56: RS | AI56: PORTO ALEGRE | AJ56: Atividades de atenção ambulatorial não especificadas anteriormente | AK56: DEMAIS | AL56: ATIVA | AM56: https://scalzilliaj.com.br/sgc/download.php?file=files/processo_documento/processo_documento09120721032023_1_.pdf&nome=15 - Edital do art. 7º, §2º e 53 da Lei 11.101/2005 (segunda lista de credores e recebimento do plano)) | AN56: p26 r23 | AO56: p26: R$ 3.947.275,50 | AP56: AJ_LIST | AQ56: 2023-03-21 | AR56: OK_NO_TOTALS | AS56: ROWS:p26r23 UNRECONCILED_SOURCE | AT56: ebfb999b457c
A57: 56 | B57: NEW | D57: 0 | I57: BRASQUIMICA PRODUTOS ASFALTICOS LTDA | J57: BRASQUIMICA PRODUTOS ASFALTICOS LTDA | K57: 13829957 | L57: 13829957000782 | M57: 3879789.5 | N57: 1 | O57: C | P57: ACTIVE | Q57: 43838 | R57: =IF(Q57="","",ROUND((TODAY()-Q57)/365.25,1)) | S57: =IFERROR(VLOOKUP(O57,Assumptions!$A$7:$F$11,2,FALSE),0.25) | T57: =IF(O57="A",MAX(1,IFERROR(VLOOKUP(O57,Assumptions!$A$7:$F$11,3,FALSE),3)+IFERROR(VLOOKUP(O57,Assumptions!$A$7:$F$11,4,FALSE),8)/2-MAX(0,IF(R57="",0,R57)-IFERROR(VLOOKUP(O57,Assumptions!$A$7:$F$11,5,FALSE),1.5))),IFERROR(VLOOKUP(O57,Assumptions!$A$7:$F$11,5,FALSE),2.5)+IFERROR(VLOOKUP(O57,Assumptions!$A$7:$F$11,3,FALSE),3)+IFERROR(VLOOKUP(O57,Assumptions!$A$7:$F$11,4,FALSE),8)/2) | U57: =M57*S57/(1+Assumptions!$B$3)^T57 | V57: =IF(M57=0,"",ROUND(U57/M57*100,1)) | W57: =U57*Assumptions!$B$4 | X57: =IF(M57=0,"",ROUND(W57/M57*100,1)) | Y57: CONSTRUTORA ANDRADE GUEDES LTDA | Z57: 0000880-57.2020.8.17.2001 | AA57: TJPE | AB57: diligence.adm.br | AC57: ALBERTO GARRIDO PINON | AD57: Administrador | AE57: (71) 3118-2100 | AH57: BA | AI57: SALVADOR | AJ57: Comércio atacadista de outros produtos químicos e petroquímicos não especificados anteriormente | AK57: DEMAIS | AL57: ATIVA | AM57: https://diligence.adm.br/wp-content/plugins/download-attachments/includes/download.php?id=4599 | AN57: p10 r10 | AO57: p10: R$ 3.879.789,49 | AP57: AJ_LIST | AQ57: 2024-06-25 | AR57: OK_NO_TOTALS | AS57: ALT_VALUE:R$3.849.447,97 ALT_VALUE:R$30.341,52 ROWS:p10r10 UNRECONCILED_SOURCE VALUE_COL:2ª_Lista | AT57: 44ecd0afa707
A58: 57 | B58: NEW | D58: 0 | I58: COMPANHIA DE AGUA E ESGOTOS DA PARAIBA CAGEPA | J58: COMPANHIA DE ÁGUA E ESGOTOS DA PARAIBA CAGEPA | K58: 09123654 | L58: 09123654000187 | M58: 3641949.7 | N58: 1 | O58: C | P58: ACTIVE | Q58: 45174 | R58: =IF(Q58="","",ROUND((TODAY()-Q58)/365.25,1)) | S58: =IFERROR(VLOOKUP(O58,Assumptions!$A$7:$F$11,2,FALSE),0.25) | T58: =IF(O58="A",MAX(1,IFERROR(VLOOKUP(O58,Assumptions!$A$7:$F$11,3,FALSE),3)+IFERROR(VLOOKUP(O58,Assumptions!$A$7:$F$11,4,FALSE),8)/2-MAX(0,IF(R58="",0,R58)-IFERROR(VLOOKUP(O58,Assumptions!$A$7:$F$11,5,FALSE),1.5))),IFERROR(VLOOKUP(O58,Assumptions!$A$7:$F$11,5,FALSE),2.5)+IFERROR(VLOOKUP(O58,Assumptions!$A$7:$F$11,3,FALSE),3)+IFERROR(VLOOKUP(O58,Assumptions!$A$7:$F$11,4,FALSE),8)/2) | U58: =M58*S58/(1+Assumptions!$B$3)^T58 | V58: =IF(M58=0,"",ROUND(U58/M58*100,1)) | W58: =U58*Assumptions!$B$4 | X58: =IF(M58=0,"",ROUND(W58/M58*100,1)) | Y58: TREZE FUTEBOL CLUBE | Z58: 0829315-43.2023.8.15.0001 | AA58: TJPB | AB58: lrflideres.com.br | AC58: MARCUS VINICIUS FERNANDES NEVES | AD58: Presidente | AE58: (83) 3218-1200 | AF58: (83) 3218-1225 | AH58: PB | AI58: JOAO PESSOA | AJ58: Captação, tratamento e distribuição de água | AK58: DEMAIS | AL58: ATIVA | AM58: https://lrflideres.com.br/wp-content/plugins/download-attachments/includes/download.php?id=5828 | AN58: p3 r16 | AO58: p3: R$ 3.641.949,67 | AP58: AJ_LIST | AQ58: 2024-04-18 | AR58: OK | AS58: ROWS:p3r16 | AT58: 47e92e4db6f8
A59: 58 | B59: NEW | D59: 0 | I59: A GERADORA ALUGUEL DE MAQUINAS S.A. | J59: A Geradora Aluguel de Maquinas S.A | K59: 33845322 | L59: 33845322000190, 33845322001081 | M59: 3379805.9 | N59: 6 | O59: B | Q59: 45756 | R59: =IF(Q59="","",ROUND((TODAY()-Q59)/365.25,1)) | S59: =IFERROR(VLOOKUP(O59,Assumptions!$A$7:$F$11,2,FALSE),0.25) | T59: =IF(O59="A",MAX(1,IFERROR(VLOOKUP(O59,Assumptions!$A$7:$F$11,3,FALSE),3)+IFERROR(VLOOKUP(O59,Assumptions!$A$7:$F$11,4,FALSE),8)/2-MAX(0,IF(R59="",0,R59)-IFERROR(VLOOKUP(O59,Assumptions!$A$7:$F$11,5,FALSE),1.5))),IFERROR(VLOOKUP(O59,Assumptions!$A$7:$F$11,5,FALSE),2.5)+IFERROR(VLOOKUP(O59,Assumptions!$A$7:$F$11,3,FALSE),3)+IFERROR(VLOOKUP(O59,Assumptions!$A$7:$F$11,4,FALSE),8)/2) | U59: =M59*S59/(1+Assumptions!$B$3)^T59 | V59: =IF(M59=0,"",ROUND(U59/M59*100,1)) | W59: =U59*Assumptions!$B$4 | X59: =IF(M59=0,"",ROUND(W59/M59*100,1)) | Y59: GRUPO EGESA (EGESA ENG S.A, EGESUR PART E EMP S.A, MATRIX INFRA LTDA, BEMVIVER ENG AMBIENTAL E SERV LTDA, DKF CONST E EMP LTDA, EGEPEL LTDA, ETR ASSESSORIA EMP E PART LTDA, MVT ENG E SERV LTDA, PARQUES DO VALE LTDA, ELMO RIBEIRO E ANA RIBEIRO) | Z59: 5088952-81.2025.8.13.0024 | AA59: TJMG | AB59: scalzilliaj.com.br | AC59: JOSE CANDIDO TERCEIRO JUNIOR | AD59: Diretor | AE59: (71) 3418-2600 | AH59: BA | AI59: SALVADOR | AJ59: Aluguel de outras máquinas e equipamentos comerciais e industriais não especificados anteriormente, sem operador | AK59: DEMAIS | AL59: ATIVA | AM59: https://scalzilliaj.com.br/sgc/download.php?file=files/processo_documento/processo_documento09514021082025_1_.pdf&nome=04 - Relação de credores das Recuperandas | AN59: p61 r2; p61 r3; p61 r4; p61 r5; p61 r6; p61 r7 | AO59: p61: R$ 157.495,18; p61: R$ 78.391,92; p61: R$ 608.384,03; p61: R$ 589.125,42; p61: R$ 1.879.005,92; p61: R$ 67.403,41 | AP59: DEBTOR_LIST | AR59: OK | AS59: ROWS:p61r2,p61r3,p61r4,p61r5,p61r6,p61r7 VALUE_COL:Valor_Atualizado CASE_NUMBER_CORRECTED CASE_FROM_PORTAL | AT59: 24ed98480a57
A60: 59 | B60: NEW | D60: 0 | I60: SALESFORCE TECNOLOGIA LTDA | J60: NÃO | K60: 01080512 | L60: 01080512000178 | M60: 3349893.5 | N60: 1 | O60: B | R60: =IF(Q60="","",ROUND((TODAY()-Q60)/365.25,1)) | S60: =IFERROR(VLOOKUP(O60,Assumptions!$A$7:$F$11,2,FALSE),0.25) | T60: =IF(O60="A",MAX(1,IFERROR(VLOOKUP(O60,Assumptions!$A$7:$F$11,3,FALSE),3)+IFERROR(VLOOKUP(O60,Assumptions!$A$7:$F$11,4,FALSE),8)/2-MAX(0,IF(R60="",0,R60)-IFERROR(VLOOKUP(O60,Assumptions!$A$7:$F$11,5,FALSE),1.5))),IFERROR(VLOOKUP(O60,Assumptions!$A$7:$F$11,5,FALSE),2.5)+IFERROR(VLOOKUP(O60,Assumptions!$A$7:$F$11,3,FALSE),3)+IFERROR(VLOOKUP(O60,Assumptions!$A$7:$F$11,4,FALSE),8)/2) | U60: =M60*S60/(1+Assumptions!$B$3)^T60 | V60: =IF(M60=0,"",ROUND(U60/M60*100,1)) | W60: =U60*Assumptions!$B$4 | X60: =IF(M60=0,"",ROUND(W60/M60*100,1)) | Y60: Grupo Rech | Z60: 5057720-48.2025.8.24.0023 | AB60: credibilita.com.br | AC60: ALEXANDRE ANDRADE DA COSTA | AD60: Administrador | AE60: (11) 2110-3141 | AH60: SP | AI60: SAO PAULO | AJ60: Desenvolvimento e licenciamento de programas de computador customizáveis | AK60: DEMAIS | AL60: ATIVA | AM60: https://credibilita.com.br/wp-content/uploads/2025/09/Relacao-Credores-29.04.2026.pdf | AN60: p2 r16 | AO60: p2: R$ 3.349.893,45 | AP60: QUORUM_LIST | AR60: OK_NO_TOTALS | AS60: ROWS:p2r16 UNRECONCILED_SOURCE VALUE_COL:Valor_Após_Analise CASE_NUMBER_CORRECTED | AT60: cf92cff797d2
A61: 60 | B61: NEW | D61: 0 | I61: M.K. GALONE CONFECCOES E COMERCIO DE ROUPAS LTDA | J61: M.K. GALONE CONFECCOES E COMERCIO DE ROUPAS LTDA | K61: 05784234 | L61: 05784234000190 | M61: 3309751.3 | N61: 3 | O61: C | P61: ACTIVE | Q61: 44571 | R61: =IF(Q61="","",ROUND((TODAY()-Q61)/365.25,1)) | S61: =IFERROR(VLOOKUP(O61,Assumptions!$A$7:$F$11,2,FALSE),0.25) | T61: =IF(O61="A",MAX(1,IFERROR(VLOOKUP(O61,Assumptions!$A$7:$F$11,3,FALSE),3)+IFERROR(VLOOKUP(O61,Assumptions!$A$7:$F$11,4,FALSE),8)/2-MAX(0,IF(R61="",0,R61)-IFERROR(VLOOKUP(O61,Assumptions!$A$7:$F$11,5,FALSE),1.5))),IFERROR(VLOOKUP(O61,Assumptions!$A$7:$F$11,5,FALSE),2.5)+IFERROR(VLOOKUP(O61,Assumptions!$A$7:$F$11,3,FALSE),3)+IFERROR(VLOOKUP(O61,Assumptions!$A$7:$F$11,4,FALSE),8)/2) | U61: =M61*S61/(1+Assumptions!$B$3)^T61 | V61: =IF(M61=0,"",ROUND(U61/M61*100,1)) | W61: =U61*Assumptions!$B$4 | X61: =IF(M61=0,"",ROUND(W61/M61*100,1)) | Y61: GRUPO CATTAN | Z61: 0002484-82.2022.8.17.2001 | AA61: TJPE | AB61: lrflideres.com.br | AC61: LEANDRO AKIYOSHI HASHIGUTI | AD61: Sócio-Administrador | AE61: (11) 7213-9030 | AH61: SP | AI61: SAO PAULO | AJ61: Confecção de peças de vestuário, exceto roupas íntimas e as confeccionadas sob medida | AK61: DEMAIS | AL61: ATIVA | AM61: https://lrflideres.com.br/wp-content/plugins/download-attachments/includes/download.php?id=4023 | AN61: p4 r87; p7 r111; p9 r84 | AO61: p4: R$ 2.265.469,65; p7: R$ 879.396,72; p9: R$ 164.884,92 | AP61: DEBTOR_LIST | AR61: QUARANTINED | AS61: PARTIAL_DOC_CLASS_III_RECONCILED ROWS:p4r87,p7r111,p9r84 | AT61: f3b6182e3aa2
A62: 61 | B62: NEW | D62: 0 | I62: DIVINA INDUSTRIA DE COURO LTDA - EM RECUPERACAO JUDICIAL | J62: DIVINA INDUSTRIA DE COURO LTDA | K62: 08785522 | L62: 08785522000158 | M62: 3206338.8 | N62: 1 | O62: B | P62: ACTIVE | Q62: 45425 | R62: =IF(Q62="","",ROUND((TODAY()-Q62)/365.25,1)) | S62: =IFERROR(VLOOKUP(O62,Assumptions!$A$7:$F$11,2,FALSE),0.25) | T62: =IF(O62="A",MAX(1,IFERROR(VLOOKUP(O62,Assumptions!$A$7:$F$11,3,FALSE),3)+IFERROR(VLOOKUP(O62,Assumptions!$A$7:$F$11,4,FALSE),8)/2-MAX(0,IF(R62="",0,R62)-IFERROR(VLOOKUP(O62,Assumptions!$A$7:$F$11,5,FALSE),1.5))),IFERROR(VLOOKUP(O62,Assumptions!$A$7:$F$11,5,FALSE),2.5)+IFERROR(VLOOKUP(O62,Assumptions!$A$7:$F$11,3,FALSE),3)+IFERROR(VLOOKUP(O62,Assumptions!$A$7:$F$11,4,FALSE),8)/2) | U62: =M62*S62/(1+Assumptions!$B$3)^T62 | V62: =IF(M62=0,"",ROUND(U62/M62*100,1)) | W62: =U62*Assumptions!$B$4 | X62: =IF(M62=0,"",ROUND(W62/M62*100,1)) | Y62: GRUPO DIVINA | Z62: 0000721-61.2024.8.17.2620 | AA62: TJPE | AB62: lrflideres.com.br | AC62: ADRIANO FERRAZ GOMES | AD62: Sócio-Administrador | AE62: (81) 9411-3643 | AH62: PE | AI62: FLORESTA | AJ62: Fabricação de calçados de couro | AK62: DEMAIS | AL62: ATIVA | AM62: https://lrflideres.com.br/wp-content/plugins/download-attachments/includes/download.php?id=6252 | AN62: p2 r34 | AO62: p2: R$ 3.206.338,81 | AP62: AJ_LIST | AQ62: 2024-11-27 | AR62: QUARANTINED | AS62: PARTIAL_DOC_CLASS_III_RECONCILED ROWS:p2r34 | AT62: 38f0c15b8a2d
A63: 62 | B63: NEW | D63: 0 | I63: LOROTTI EMPREENDIMENTOS IMOBILIARIOS LTDA | J63: Lorotti Empreendimentos Imobiliarios | K63: 10505803 | L63: 10505803000151 | M63: 3159739.6 | N63: 1 | O63: B | P63: ACTIVE | Q63: 46130 | R63: =IF(Q63="","",ROUND((TODAY()-Q63)/365.25,1)) | S63: =IFERROR(VLOOKUP(O63,Assumptions!$A$7:$F$11,2,FALSE),0.25) | T63: =IF(O63="A",MAX(1,IFERROR(VLOOKUP(O63,Assumptions!$A$7:$F$11,3,FALSE),3)+IFERROR(VLOOKUP(O63,Assumptions!$A$7:$F$11,4,FALSE),8)/2-MAX(0,IF(R63="",0,R63)-IFERROR(VLOOKUP(O63,Assumptions!$A$7:$F$11,5,FALSE),1.5))),IFERROR(VLOOKUP(O63,Assumptions!$A$7:$F$11,5,FALSE),2.5)+IFERROR(VLOOKUP(O63,Assumptions!$A$7:$F$11,3,FALSE),3)+IFERROR(VLOOKUP(O63,Assumptions!$A$7:$F$11,4,FALSE),8)/2) | U63: =M63*S63/(1+Assumptions!$B$3)^T63 | V63: =IF(M63=0,"",ROUND(U63/M63*100,1)) | W63: =U63*Assumptions!$B$4 | X63: =IF(M63=0,"",ROUND(W63/M63*100,1)) | Y63: GRUPO 3E | Z63: 5341375-33.2026.8.09.0049 | AA63: TJGO | AB63: stenius.com.br | AC63: ALINE RAZEM ABRAO | AD63: Sócio-Administrador | AE63: (61) 3366-4288 | AH63: DF | AI63: BRASILIA | AJ63: Construção de edifícios | AK63: DEMAIS | AL63: ATIVA | AM63: https://stenius.com.br/wp-content/uploads/2026/06/EDITAL-GRUPO-3E.pdf | AN63: p15 r31 | AO63: p15: R$ 3.159.739,59 | AP63: DEBTOR_LIST | AQ63: 2026-06-22 | AR63: OK_NO_TOTALS | AS63: ROWS:p15r31 UNRECONCILED_SOURCE | AT63: 8e8832093a15
A64: 63 | B64: NEW | D64: 0 | I64: ALFANI CONFECCOES E COMERCIO LTDA - EM RECUPERACAO JUDICIAL | J64: ALFANI CONFECCOES E COMERCIO LTDA | K64: 02524216 | L64: 02524216000181 | M64: 3140000 | N64: 1 | O64: C | P64: ACTIVE | Q64: 44571 | R64: =IF(Q64="","",ROUND((TODAY()-Q64)/365.25,1)) | S64: =IFERROR(VLOOKUP(O64,Assumptions!$A$7:$F$11,2,FALSE),0.25) | T64: =IF(O64="A",MAX(1,IFERROR(VLOOKUP(O64,Assumptions!$A$7:$F$11,3,FALSE),3)+IFERROR(VLOOKUP(O64,Assumptions!$A$7:$F$11,4,FALSE),8)/2-MAX(0,IF(R64="",0,R64)-IFERROR(VLOOKUP(O64,Assumptions!$A$7:$F$11,5,FALSE),1.5))),IFERROR(VLOOKUP(O64,Assumptions!$A$7:$F$11,5,FALSE),2.5)+IFERROR(VLOOKUP(O64,Assumptions!$A$7:$F$11,3,FALSE),3)+IFERROR(VLOOKUP(O64,Assumptions!$A$7:$F$11,4,FALSE),8)/2) | U64: =M64*S64/(1+Assumptions!$B$3)^T64 | V64: =IF(M64=0,"",ROUND(U64/M64*100,1)) | W64: =U64*Assumptions!$B$4 | X64: =IF(M64=0,"",ROUND(W64/M64*100,1)) | Y64: GRUPO CATTAN | Z64: 0002484-82.2022.8.17.2001 | AA64: TJPE | AB64: lrflideres.com.br | AC64: FLAVIO DANTAS CATAO | AD64: Sócio-Administrador | AE64: (81) 3419-8550 | AF64: (81) 3032-8400 | AH64: PE | AI64: RECIFE | AJ64: Comércio varejista de artigos do vestuário e acessórios | AK64: DEMAIS | AL64: ATIVA | AM64: https://lrflideres.com.br/wp-content/plugins/download-attachments/includes/download.php?id=4023 | AN64: p9 r52 | AO64: p9: R$ 3.140.000,00 | AP64: DEBTOR_LIST | AR64: QUARANTINED | AS64: PARTIAL_DOC_CLASS_III_RECONCILED ROWS:p9r52 | AT64: f3b6182e3aa2
A65: 64 | B65: NEW | D65: 0 | I65: VIANMAQ EQUIPAMENTOS LTDA | J65: Vianmaq Equipamentos LTDA (CNPJ nº | K65: 01631022 | L65: 01631022000465, 90400888000142 | M65: 3083893.6 | N65: 1 | O65: C | P65: ACTIVE | Q65: 44882 | R65: =IF(Q65="","",ROUND((TODAY()-Q65)/365.25,1)) | S65: =IFERROR(VLOOKUP(O65,Assumptions!$A$7:$F$11,2,FALSE),0.25) | T65: =IF(O65="A",MAX(1,IFERROR(VLOOKUP(O65,Assumptions!$A$7:$F$11,3,FALSE),3)+IFERROR(VLOOKUP(O65,Assumptions!$A$7:$F$11,4,FALSE),8)/2-MAX(0,IF(R65="",0,R65)-IFERROR(VLOOKUP(O65,Assumptions!$A$7:$F$11,5,FALSE),1.5))),IFERROR(VLOOKUP(O65,Assumptions!$A$7:$F$11,5,FALSE),2.5)+IFERROR(VLOOKUP(O65,Assumptions!$A$7:$F$11,3,FALSE),3)+IFERROR(VLOOKUP(O65,Assumptions!$A$7:$F$11,4,FALSE),8)/2) | U65: =M65*S65/(1+Assumptions!$B$3)^T65 | V65: =IF(M65=0,"",ROUND(U65/M65*100,1)) | W65: =U65*Assumptions!$B$4 | X65: =IF(M65=0,"",ROUND(W65/M65*100,1)) | Y65: CARAVAGGIO CONSTRUTORA LTDA | Z65: 0037411-27.2022.8.16.0021 | AA65: TJPR | AB65: marquesadmjudicial.com.br | AC65: CEDRIC ALBERT VIAN | AD65: Sócio-Administrador | AE65: (41) 3555-2161 | AF65: (41) 9707-0679 | AH65: PR | AI65: CAMPO LARGO | AJ65: Comércio atacadista de outras máquinas e equipamentos não especificados anteriormente; partes e peças | AK65: DEMAIS | AL65: ATIVA | AM65: https://marquesadmjudicial.com.br/sgc/download.php?file=files/processo_documento/processo_documento16562707032024_1_.pdf&nome=2º Edital-Relação de Credores do art. 7, §2 da LREF e do Plano de Recuperação Judicial | AN65: p1 r45 | AO65: p1: R$ 3.083.893,62 | AP65: AJ_LIST | AQ65: 2022-11-17 | AR65: OK_NO_TOTALS | AS65: MULTI_ROOT ROWS:p1r45 UNRECONCILED_SOURCE | AT65: 437e79745649
A66: 65 | B66: NEW | D66: 0 | I66: VEGETAL AGRONEGOCIOS LTDA | J66: VEGETAL AGRONEGOCIOS LTDA | K66: 05429994 | L66: 05429994001313 | M66: 3014807.2 | N66: 1 | O66: B | P66: ACTIVE | Q66: 45845 | R66: =IF(Q66="","",ROUND((TODAY()-Q66)/365.25,1)) | S66: =IFERROR(VLOOKUP(O66,Assumptions!$A$7:$F$11,2,FALSE),0.25) | T66: =IF(O66="A",MAX(1,IFERROR(VLOOKUP(O66,Assumptions!$A$7:$F$11,3,FALSE),3)+IFERROR(VLOOKUP(O66,Assumptions!$A$7:$F$11,4,FALSE),8)/2-MAX(0,IF(R66="",0,R66)-IFERROR(VLOOKUP(O66,Assumptions!$A$7:$F$11,5,FALSE),1.5))),IFERROR(VLOOKUP(O66,Assumptions!$A$7:$F$11,5,FALSE),2.5)+IFERROR(VLOOKUP(O66,Assumptions!$A$7:$F$11,3,FALSE),3)+IFERROR(VLOOKUP(O66,Assumptions!$A$7:$F$11,4,FALSE),8)/2) | U66: =M66*S66/(1+Assumptions!$B$3)^T66 | V66: =IF(M66=0,"",ROUND(U66/M66*100,1)) | W66: =U66*Assumptions!$B$4 | X66: =IF(M66=0,"",ROUND(W66/M66*100,1)) | Y66: SOJAL COMERCIAL AGRICOLA LTDA e OUTROS | Z66: 0804401-51.2025.8.14.0039 | AA66: TJPA | AB66: lrflideres.com.br | AC66: ALDAIR REMUSSI | AD66: Sócio-Administrador | AE66: (61) 3234-8485 | AH66: DF | AI66: BRASILIA | AJ66: Comércio atacadista de defensivos agrícolas, adubos, fertilizantes e corretivos do solo | AK66: DEMAIS | AL66: ATIVA | AM66: https://lrflideres.com.br/wp-content/plugins/download-attachments/includes/download.php?id=6879 | AN66: p2 r13 | AO66: p2: R$ 3.014.807,20 | AP66: AJ_LIST | AQ66: 2026-01-15 | AR66: OK | AS66: ROWS:p2r13 | AT66: c56751547323
A67: 66 | B67: NEW | D67: 0 | I67: NUTRIEN SOLUCOES AGRICOLAS LTDA | J67: Nutrien Solucoes Agricolas | K67: 88305859 | L67: 88305859002012 | M67: 3009813.4 | N67: 1 | O67: B | P67: ACTIVE | Q67: 46130 | R67: =IF(Q67="","",ROUND((TODAY()-Q67)/365.25,1)) | S67: =IFERROR(VLOOKUP(O67,Assumptions!$A$7:$F$11,2,FALSE),0.25) | T67: =IF(O67="A",MAX(1,IFERROR(VLOOKUP(O67,Assumptions!$A$7:$F$11,3,FALSE),3)+IFERROR(VLOOKUP(O67,Assumptions!$A$7:$F$11,4,FALSE),8)/2-MAX(0,IF(R67="",0,R67)-IFERROR(VLOOKUP(O67,Assumptions!$A$7:$F$11,5,FALSE),1.5))),IFERROR(VLOOKUP(O67,Assumptions!$A$7:$F$11,5,FALSE),2.5)+IFERROR(VLOOKUP(O67,Assumptions!$A$7:$F$11,3,FALSE),3)+IFERROR(VLOOKUP(O67,Assumptions!$A$7:$F$11,4,FALSE),8)/2) | U67: =M67*S67/(1+Assumptions!$B$3)^T67 | V67: =IF(M67=0,"",ROUND(U67/M67*100,1)) | W67: =U67*Assumptions!$B$4 | X67: =IF(M67=0,"",ROUND(W67/M67*100,1)) | Y67: GRUPO 3E | Z67: 5341375-33.2026.8.09.0049 | AA67: TJGO | AB67: stenius.com.br | AC67: CARLOS EDUARDO FAZZIO DE BRITO | AD67: Administrador | AE67: (11) 5400-0021 | AH67: SP | AI67: SAO PAULO | AJ67: Comércio atacadista de defensivos agrícolas, adubos, fertilizantes e corretivos do solo | AK67: DEMAIS | AL67: ATIVA | AM67: https://stenius.com.br/wp-content/uploads/2026/06/EDITAL-GRUPO-3E.pdf | AN67: p16 r30 | AO67: p16: R$ 3.009.813,42 | AP67: DEBTOR_LIST | AQ67: 2026-06-22 | AR67: OK_NO_TOTALS | AS67: ROWS:p16r30 UNRECONCILED_SOURCE | AT67: 8e8832093a15
A68: 67 | B68: NEW | D68: 0 | I68: BRACELL SP CELULOSE LTDA | J68: ROD JULIANO LORENZETTI KM 04 MARECHAL RONDOM DISTRO INDUSTRIAL - LENÇOIS PAULISTA - SP - CEP 18685-900 | K68: 53943098 | L68: 53943098000187 | M68: 3000000 | N68: 1 | O68: U | R68: =IF(Q68="","",ROUND((TODAY()-Q68)/365.25,1)) | S68: =IFERROR(VLOOKUP(O68,Assumptions!$A$7:$F$11,2,FALSE),0.25) | T68: =IF(O68="A",MAX(1,IFERROR(VLOOKUP(O68,Assumptions!$A$7:$F$11,3,FALSE),3)+IFERROR(VLOOKUP(O68,Assumptions!$A$7:$F$11,4,FALSE),8)/2-MAX(0,IF(R68="",0,R68)-IFERROR(VLOOKUP(O68,Assumptions!$A$7:$F$11,5,FALSE),1.5))),IFERROR(VLOOKUP(O68,Assumptions!$A$7:$F$11,5,FALSE),2.5)+IFERROR(VLOOKUP(O68,Assumptions!$A$7:$F$11,3,FALSE),3)+IFERROR(VLOOKUP(O68,Assumptions!$A$7:$F$11,4,FALSE),8)/2) | U68: =M68*S68/(1+Assumptions!$B$3)^T68 | V68: =IF(M68=0,"",ROUND(U68/M68*100,1)) | W68: =U68*Assumptions!$B$4 | X68: =IF(M68=0,"",ROUND(W68/M68*100,1)) | Y68: Base | Z68: (not found in document) | AB68: ajruiz.com.br | AC68: ARTHUR RIZZARDO ZANARDI | AD68: Administrador | AE68: (14) 3269-5100 | AH68: SP | AI68: LENCOIS PAULISTA | AJ68: Fabricação de celulose e outras pastas para a fabricação de papel | AK68: DEMAIS | AL68: ATIVA | AM68: https://ajruiz.com.br/sites/default/files/public/arquivos-processos/2023-11/4_relacao_de_credores_analitica_art._51_iii_da_lre.pdf | AN68: p2 r21 | AO68: p2: R$ 3.000.000,00 | AP68: UNKNOWN | AR68: OK | AS68: ALT_VALUE:cliente ROWS:p2r21 VALUE_COL:Valor_Do_Crédito CASE_NUMBER_CORRECTED | AT68: 2407a56c3502
A69: 68 | B69: NEW | D69: 0 | I69: IRANY COMERCIO EXTERIOR LTDA | J69: Irany Comércio Exterior Ltda (CNPJ nº | K69: 47320705 | L69: 47320705000150 | M69: 2916553.7 | N69: 1 | O69: B | P69: ACTIVE | Q69: 45912 | R69: =IF(Q69="","",ROUND((TODAY()-Q69)/365.25,1)) | S69: =IFERROR(VLOOKUP(O69,Assumptions!$A$7:$F$11,2,FALSE),0.25) | T69: =IF(O69="A",MAX(1,IFERROR(VLOOKUP(O69,Assumptions!$A$7:$F$11,3,FALSE),3)+IFERROR(VLOOKUP(O69,Assumptions!$A$7:$F$11,4,FALSE),8)/2-MAX(0,IF(R69="",0,R69)-IFERROR(VLOOKUP(O69,Assumptions!$A$7:$F$11,5,FALSE),1.5))),IFERROR(VLOOKUP(O69,Assumptions!$A$7:$F$11,5,FALSE),2.5)+IFERROR(VLOOKUP(O69,Assumptions!$A$7:$F$11,3,FALSE),3)+IFERROR(VLOOKUP(O69,Assumptions!$A$7:$F$11,4,FALSE),8)/2) | U69: =M69*S69/(1+Assumptions!$B$3)^T69 | V69: =IF(M69=0,"",ROUND(U69/M69*100,1)) | W69: =U69*Assumptions!$B$4 | X69: =IF(M69=0,"",ROUND(W69/M69*100,1)) | Y69: B1 COMÉRCIO DE MANUFATURADOS LTDA | Z69: 0043030-30.2025.8.16.0021 | AA69: TJPR | AB69: marquesadmjudicial.com.br | AC69: IRANY GASPAR PACHECO DOS SANTOS | AD69: Sócio-Administrador | AE69: (42) 9871-7035 | AH69: SC | AI69: ITAPOA | AJ69: Comércio atacadista de cereais e leguminosas beneficiados | AK69: DEMAIS | AL69: ATIVA | AM69: https://marquesadmjudicial.com.br/sgc/download.php?file=files/processo_documento/processo_documento18581929042026_1_.pdf&nome=3º Edital - Relação de Credores e PRJ | AN69: p1 r46 | AO69: p1: R$ 2.916.553,74 | AP69: AJ_LIST | AQ69: 2025-09-12 | AR69: OK_NO_TOTALS | AS69: ROWS:p1r46 UNRECONCILED_SOURCE | AT69: 9846e4c0bb37
A70: 69 | B70: NEW | D70: 0 | I70: NNC NORTE E NORDESTE COMMODITIES LTDA | J70: NNC NORTE E NORDESTE COMMODITIES LTDA | K70: 40910399 | L70: 40910399000162 | M70: 2859701.3 | N70: 1 | O70: B | P70: ACTIVE | Q70: 46030 | R70: =IF(Q70="","",ROUND((TODAY()-Q70)/365.25,1)) | S70: =IFERROR(VLOOKUP(O70,Assumptions!$A$7:$F$11,2,FALSE),0.25) | T70: =IF(O70="A",MAX(1,IFERROR(VLOOKUP(O70,Assumptions!$A$7:$F$11,3,FALSE),3)+IFERROR(VLOOKUP(O70,Assumptions!$A$7:$F$11,4,FALSE),8)/2-MAX(0,IF(R70="",0,R70)-IFERROR(VLOOKUP(O70,Assumptions!$A$7:$F$11,5,FALSE),1.5))),IFERROR(VLOOKUP(O70,Assumptions!$A$7:$F$11,5,FALSE),2.5)+IFERROR(VLOOKUP(O70,Assumptions!$A$7:$F$11,3,FALSE),3)+IFERROR(VLOOKUP(O70,Assumptions!$A$7:$F$11,4,FALSE),8)/2) | U70: =M70*S70/(1+Assumptions!$B$3)^T70 | V70: =IF(M70=0,"",ROUND(U70/M70*100,1)) | W70: =U70*Assumptions!$B$4 | X70: =IF(M70=0,"",ROUND(W70/M70*100,1)) | Y70: GRUPO FERRARI (ALEX, ALEXANDRE , ANDRIELLE FERRARI MANTELLI, ARCIR LUIS, ERICA SANTOS ASSIS LIMA, FERNANDO MANTELLI, IDELSI, TALITA LEITE SILVA, AGROPECUARIA FERRARI LTDA E FERRARI ARMAZENS GERAIS) | Z70: 5011369-81.2026.8.09.0093 | AA70: TJGO | AB70: scalzilliaj.com.br | AC70: OZILDE LOPES | AD70: Administrador | AE70: (37) 3271-9801 | AH70: MA | AI70: BALSAS | AJ70: Comércio atacadista de cereais e leguminosas beneficiados | AK70: DEMAIS | AL70: ATIVA | AM70: https://scalzilliaj.com.br/sgc/download.php?file=files/processo_documento/processo_documento11421222052026_1_.pdf&nome=08. Lista de credores do edital do art. 52, §1º da LREF | AN70: p3 r9 | AO70: p3: R$ 2.859.701,32 | AP70: UNKNOWN | AR70: OK_NO_TOTALS | AS70: ROWS:p3r9 UNRECONCILED_SOURCE | AT70: c536a2fa4da3
A71: 70 | B71: NEW | D71: 0 | I71: SPORT CLUB CORINTHIANS PAULISTA | J71: SPORT CLUB CORINTHIANS PAULISTA, CPF/CNPJ Nº | K71: 61902722 | L71: 61902722000126 | M71: 2823611.8 | N71: 1 | O71: C | P71: ACTIVE | Q71: 44966 | R71: =IF(Q71="","",ROUND((TODAY()-Q71)/365.25,1)) | S71: =IFERROR(VLOOKUP(O71,Assumptions!$A$7:$F$11,2,FALSE),0.25) | T71: =IF(O71="A",MAX(1,IFERROR(VLOOKUP(O71,Assumptions!$A$7:$F$11,3,FALSE),3)+IFERROR(VLOOKUP(O71,Assumptions!$A$7:$F$11,4,FALSE),8)/2-MAX(0,IF(R71="",0,R71)-IFERROR(VLOOKUP(O71,Assumptions!$A$7:$F$11,5,FALSE),1.5))),IFERROR(VLOOKUP(O71,Assumptions!$A$7:$F$11,5,FALSE),2.5)+IFERROR(VLOOKUP(O71,Assumptions!$A$7:$F$11,3,FALSE),3)+IFERROR(VLOOKUP(O71,Assumptions!$A$7:$F$11,4,FALSE),8)/2) | U71: =M71*S71/(1+Assumptions!$B$3)^T71 | V71: =IF(M71=0,"",ROUND(U71/M71*100,1)) | W71: =U71*Assumptions!$B$4 | X71: =IF(M71=0,"",ROUND(W71/M71*100,1)) | Y71: CLUBE NÁUTICO CAPIBARIBE | Z71: 0011283-80.2023.8.17.2001 | AA71: TJPE | AB71: lrflideres.com.br | AC71: OSMAR STABILE | AD71: Presidente | AH71: SP | AI71: SAO PAULO | AJ71: Clubes sociais, esportivos e similares | AK71: DEMAIS | AL71: ATIVA | AM71: https://lrflideres.com.br/wp-content/plugins/download-attachments/includes/download.php?id=5589 | AN71: p12 r44 | AO71: p12: R$ 2.823.611,80 | AP71: AJ_LIST | AQ71: 2023-11-27 | AR71: QUARANTINED | AS71: PARTIAL_DOC_CLASS_III_RECONCILED ROWS:p12r44 | AT71: 677be5783c06
A72: 71 | B72: NEW | D72: 0 | I72: CARGILL AGRICOLA S A | J72: CARGILL AGRICOLA S.A | K72: 60498706 | L72: 60498706006600 | M72: 2748939.5 | N72: 4 | O72: B | P72: ACTIVE | Q72: 46079 | R72: =IF(Q72="","",ROUND((TODAY()-Q72)/365.25,1)) | S72: =IFERROR(VLOOKUP(O72,Assumptions!$A$7:$F$11,2,FALSE),0.25) | T72: =IF(O72="A",MAX(1,IFERROR(VLOOKUP(O72,Assumptions!$A$7:$F$11,3,FALSE),3)+IFERROR(VLOOKUP(O72,Assumptions!$A$7:$F$11,4,FALSE),8)/2-MAX(0,IF(R72="",0,R72)-IFERROR(VLOOKUP(O72,Assumptions!$A$7:$F$11,5,FALSE),1.5))),IFERROR(VLOOKUP(O72,Assumptions!$A$7:$F$11,5,FALSE),2.5)+IFERROR(VLOOKUP(O72,Assumptions!$A$7:$F$11,3,FALSE),3)+IFERROR(VLOOKUP(O72,Assumptions!$A$7:$F$11,4,FALSE),8)/2) | U72: =M72*S72/(1+Assumptions!$B$3)^T72 | V72: =IF(M72=0,"",ROUND(U72/M72*100,1)) | W72: =U72*Assumptions!$B$4 | X72: =IF(M72=0,"",ROUND(W72/M72*100,1)) | Y72: Grupo GE (Condomínio Agropecuário GE) | Z72: 5164979-18.2026.8.09.0110 | AA72: TJGO | AB72: stenius.com.br | AC72: PAULO HUMBERTO ALVES DE SOUSA | AD72: Presidente | AE72: (11) 5099-3311 | AH72: SP | AI72: SAO PAULO | AJ72: Fabricação de óleos vegetais refinados, exceto óleo de milho | AK72: DEMAIS | AL72: ATIVA | AM72: https://stenius.com.br/wp-content/uploads/2026/07/EDITAL-1-RELACAO-DE-CREDORES-GRUPO-GE.pdf | AN72: p5 r10; p5 r11; p5 r12; p5 r13; p5 r14; p5 r15; p5 r16; p5 r17 | AO72: p5: R$ 518.664,47; p5: R$ 1.308.950,00; p5: R$ 1.308.950,00; p5: R$ 682.325,00; p5: R$ 682.325,00; p5: R$ 239.000,00; p5: R$ 239.000,00; p5: R$ 239.000,00 | AP72: DEBTOR_LIST | AQ72: 2026-07-01 | AR72: OK_NO_TOTALS | AS72: ROWS:p5r10,p5r11,p5r13,p5r15 UNRECONCILED_SOURCE | AT72: 9eb5be419208
A73: 72 | B73: NEW | D73: 0 | I73: VR BENEFICIOS E SERVICOS DE PROCESSAMENTO INSTITUICAO DE PAGAMENTO S.A. | J73: VR BENEFÍCIOS E SERVIÇOS DE | K73: 02535864 | L73: 02535864000133 | M73: 2731258.5 | N73: 1 | O73: D | R73: =IF(Q73="","",ROUND((TODAY()-Q73)/365.25,1)) | S73: =IFERROR(VLOOKUP(O73,Assumptions!$A$7:$F$11,2,FALSE),0.25) | T73: =IF(O73="A",MAX(1,IFERROR(VLOOKUP(O73,Assumptions!$A$7:$F$11,3,FALSE),3)+IFERROR(VLOOKUP(O73,Assumptions!$A$7:$F$11,4,FALSE),8)/2-MAX(0,IF(R73="",0,R73)-IFERROR(VLOOKUP(O73,Assumptions!$A$7:$F$11,5,FALSE),1.5))),IFERROR(VLOOKUP(O73,Assumptions!$A$7:$F$11,5,FALSE),2.5)+IFERROR(VLOOKUP(O73,Assumptions!$A$7:$F$11,3,FALSE),3)+IFERROR(VLOOKUP(O73,Assumptions!$A$7:$F$11,4,FALSE),8)/2) | U73: =M73*S73/(1+Assumptions!$B$3)^T73 | V73: =IF(M73=0,"",ROUND(U73/M73*100,1)) | W73: =U73*Assumptions!$B$4 | X73: =IF(M73=0,"",ROUND(W73/M73*100,1)) | Y73: EQUIP SEG INTELIGÊNCIA EM SEGURANÇA LTDA. E EQUIP SEG SERVIÇOS ESPECIALIZADOS LTDA. | Z73: 0033736-15.2023.8.16.0185 | AB73: bbsadvogados.com.br | AC73: ANDRE TAKEMOTO | AD73: Diretor | AE73: (11) 4134-4100 | AH73: SP | AI73: SAO PAULO | AJ73: Emissão de vales-alimentação, vales-transporte e similares | AK73: DEMAIS | AL73: ATIVA | AM73: https://bbsadvogados.com.br/wp-content/uploads/2025/04/Equipseg-Edital-Relacao-de-Credores-da-Administradora-Judicial-art.-7o2o-da-LRF.pdf | AN73: p42 r8 | AO73: p42: R$ 2.731.258,45 | AP73: AJ_LIST | AQ73: 2025-04-08 | AR73: OK_NO_TOTALS | AS73: ROWS:p42r8 UNRECONCILED_SOURCE | AT73: b9895d3bab05
A74: 73 | B74: NEW | D74: 0 | I74: MAXLIFT LOCADORA DE EQUIPAMENTOS LTDA. | J74: Maxlift Locadora de Equipamentos Ltda | K74: 08992890 | L74: 08992890000177 | M74: 2680302.4 | N74: 1 | O74: B | Q74: 45756 | R74: =IF(Q74="","",ROUND((TODAY()-Q74)/365.25,1)) | S74: =IFERROR(VLOOKUP(O74,Assumptions!$A$7:$F$11,2,FALSE),0.25) | T74: =IF(O74="A",MAX(1,IFERROR(VLOOKUP(O74,Assumptions!$A$7:$F$11,3,FALSE),3)+IFERROR(VLOOKUP(O74,Assumptions!$A$7:$F$11,4,FALSE),8)/2-MAX(0,IF(R74="",0,R74)-IFERROR(VLOOKUP(O74,Assumptions!$A$7:$F$11,5,FALSE),1.5))),IFERROR(VLOOKUP(O74,Assumptions!$A$7:$F$11,5,FALSE),2.5)+IFERROR(VLOOKUP(O74,Assumptions!$A$7:$F$11,3,FALSE),3)+IFERROR(VLOOKUP(O74,Assumptions!$A$7:$F$11,4,FALSE),8)/2) | U74: =M74*S74/(1+Assumptions!$B$3)^T74 | V74: =IF(M74=0,"",ROUND(U74/M74*100,1)) | W74: =U74*Assumptions!$B$4 | X74: =IF(M74=0,"",ROUND(W74/M74*100,1)) | Y74: GRUPO EGESA (EGESA ENG S.A, EGESUR PART E EMP S.A, MATRIX INFRA LTDA, BEMVIVER ENG AMBIENTAL E SERV LTDA, DKF CONST E EMP LTDA, EGEPEL LTDA, ETR ASSESSORIA EMP E PART LTDA, MVT ENG E SERV LTDA, PARQUES DO VALE LTDA, ELMO RIBEIRO E ANA RIBEIRO) | Z74: 5088952-81.2025.8.13.0024 | AA74: TJMG | AB74: scalzilliaj.com.br | AC74: MARIA RACHEL LUNA DI CAVALCANTI | AD74: Sócio-Administrador | AE74: (11) 4191-4480 | AF74: (11) 4152-2907 | AH74: SP | AI74: SAO PAULO | AJ74: Aluguel de outras máquinas e equipamentos comerciais e industriais não especificados anteriormente, sem operador | AK74: DEMAIS | AL74: ATIVA | AM74: https://scalzilliaj.com.br/sgc/download.php?file=files/processo_documento/processo_documento09514021082025_1_.pdf&nome=04 - Relação de credores das Recuperandas | AN74: p69 r16 | AO74: p69: R$ 2.680.302,42 | AP74: DEBTOR_LIST | AR74: OK | AS74: ROWS:p69r16 VALUE_COL:Valor_Atualizado CASE_NUMBER_CORRECTED CASE_FROM_PORTAL | AT74: 24ed98480a57
A75: 74 | B75: NEW | D75: 0 | I75: GALVANI ENGENHARIA E PARTICIPACOES LTDA | J75: Galvani Mineração e Participações Ltda | K75: 09422727 | L75: 09422727000131 | M75: 2654550.9 | N75: 2 | O75: B | Q75: 45756 | R75: =IF(Q75="","",ROUND((TODAY()-Q75)/365.25,1)) | S75: =IFERROR(VLOOKUP(O75,Assumptions!$A$7:$F$11,2,FALSE),0.25) | T75: =IF(O75="A",MAX(1,IFERROR(VLOOKUP(O75,Assumptions!$A$7:$F$11,3,FALSE),3)+IFERROR(VLOOKUP(O75,Assumptions!$A$7:$F$11,4,FALSE),8)/2-MAX(0,IF(R75="",0,R75)-IFERROR(VLOOKUP(O75,Assumptions!$A$7:$F$11,5,FALSE),1.5))),IFERROR(VLOOKUP(O75,Assumptions!$A$7:$F$11,5,FALSE),2.5)+IFERROR(VLOOKUP(O75,Assumptions!$A$7:$F$11,3,FALSE),3)+IFERROR(VLOOKUP(O75,Assumptions!$A$7:$F$11,4,FALSE),8)/2) | U75: =M75*S75/(1+Assumptions!$B$3)^T75 | V75: =IF(M75=0,"",ROUND(U75/M75*100,1)) | W75: =U75*Assumptions!$B$4 | X75: =IF(M75=0,"",ROUND(W75/M75*100,1)) | Y75: GRUPO EGESA (EGESA ENG S.A, EGESUR PART E EMP S.A, MATRIX INFRA LTDA, BEMVIVER ENG AMBIENTAL E SERV LTDA, DKF CONST E EMP LTDA, EGEPEL LTDA, ETR ASSESSORIA EMP E PART LTDA, MVT ENG E SERV LTDA, PARQUES DO VALE LTDA, ELMO RIBEIRO E ANA RIBEIRO) | Z75: 5088952-81.2025.8.13.0024 | AA75: TJMG | AB75: scalzilliaj.com.br | AC75: SERGIO GALVANI | AD75: Sócio-Administrador | AE75: (19) 3844-9900 | AF75: (19) 3844-9667 | AH75: SP | AI75: PAULINIA | AJ75: Obras de urbanização - ruas, praças e calçadas | AK75: DEMAIS | AL75: ATIVA | AM75: https://scalzilliaj.com.br/sgc/download.php?file=files/processo_documento/processo_documento09514021082025_1_.pdf&nome=04 - Relação de credores das Recuperandas | AN75: p67 r2; p67 r3 | AO75: p67: R$ 2.209.334,79; p67: R$ 445.216,07 | AP75: DEBTOR_LIST | AR75: OK | AS75: ROWS:p67r2,p67r3 VALUE_COL:Valor_Atualizado CASE_NUMBER_CORRECTED CASE_FROM_PORTAL | AT75: 24ed98480a57
A76: 75 | B76: NEW | D76: 0 | I76: FLEXIVEL INDUSTRIA E COMERCIO LTDA | J76: FLEXIVEL IND COM LTDA | K76: 03076832 | L76: 03076832000180 | M76: 2550639.6 | N76: 1 | O76: D | R76: =IF(Q76="","",ROUND((TODAY()-Q76)/365.25,1)) | S76: =IFERROR(VLOOKUP(O76,Assumptions!$A$7:$F$11,2,FALSE),0.25) | T76: =IF(O76="A",MAX(1,IFERROR(VLOOKUP(O76,Assumptions!$A$7:$F$11,3,FALSE),3)+IFERROR(VLOOKUP(O76,Assumptions!$A$7:$F$11,4,FALSE),8)/2-MAX(0,IF(R76="",0,R76)-IFERROR(VLOOKUP(O76,Assumptions!$A$7:$F$11,5,FALSE),1.5))),IFERROR(VLOOKUP(O76,Assumptions!$A$7:$F$11,5,FALSE),2.5)+IFERROR(VLOOKUP(O76,Assumptions!$A$7:$F$11,3,FALSE),3)+IFERROR(VLOOKUP(O76,Assumptions!$A$7:$F$11,4,FALSE),8)/2) | U76: =M76*S76/(1+Assumptions!$B$3)^T76 | V76: =IF(M76=0,"",ROUND(U76/M76*100,1)) | W76: =U76*Assumptions!$B$4 | X76: =IF(M76=0,"",ROUND(W76/M76*100,1)) | Y76: Mannes | Z76: 0005010-50.2013.8.24.0026 | AB76: administradorajudicialgs.com.br | AC76: ANGELA VILMA GADOTTI JUNKES | AD76: Administrador | AE76: (47) 3270-1900 | AH76: SC | AI76: JARAGUA DO SUL | AJ76: Fabricação de outros produtos químicos não especificados anteriormente | AK76: DEMAIS | AL76: ATIVA | AM76: https://administradorajudicialgs.com.br/wp-content/uploads/2024/12/relacao-de-credores-da-falida.pdf | AN76: p14 r49 | AO76: p14: R$ 2.550.639,65 | AP76: OTHER | AQ76: 2025-03-25 | AR76: OK_NO_TOTALS | AS76: ROWS:p14r49 UNRECONCILED_SOURCE CASE_NUMBER_CORRECTED | AT76: ea17ba43b261
A77: 76 | B77: NEW | D77: 0 | I77: CROMO INDUSTRIA QUIMICA S.A. | J77: CROMO INDUSTRIA QUIMICA S.A | K77: 31281962 | L77: 31281962000190, 31281962000270 | M77: 2406485.6 | N77: 1 | O77: B | P77: ACTIVE | Q77: 45845 | R77: =IF(Q77="","",ROUND((TODAY()-Q77)/365.25,1)) | S77: =IFERROR(VLOOKUP(O77,Assumptions!$A$7:$F$11,2,FALSE),0.25) | T77: =IF(O77="A",MAX(1,IFERROR(VLOOKUP(O77,Assumptions!$A$7:$F$11,3,FALSE),3)+IFERROR(VLOOKUP(O77,Assumptions!$A$7:$F$11,4,FALSE),8)/2-MAX(0,IF(R77="",0,R77)-IFERROR(VLOOKUP(O77,Assumptions!$A$7:$F$11,5,FALSE),1.5))),IFERROR(VLOOKUP(O77,Assumptions!$A$7:$F$11,5,FALSE),2.5)+IFERROR(VLOOKUP(O77,Assumptions!$A$7:$F$11,3,FALSE),3)+IFERROR(VLOOKUP(O77,Assumptions!$A$7:$F$11,4,FALSE),8)/2) | U77: =M77*S77/(1+Assumptions!$B$3)^T77 | V77: =IF(M77=0,"",ROUND(U77/M77*100,1)) | W77: =U77*Assumptions!$B$4 | X77: =IF(M77=0,"",ROUND(W77/M77*100,1)) | Y77: SOJAL COMERCIAL AGRICOLA LTDA e OUTROS | Z77: 0804401-51.2025.8.14.0039 | AA77: TJPA | AB77: lrflideres.com.br | AC77: JOSIR NEULS | AD77: Presidente | AE77: (11) 4130-8138 | AH77: RS | AI77: ESTRELA | AJ77: Fabricação de outros produtos químicos não especificados anteriormente | AK77: DEMAIS | AL77: ATIVA | AM77: https://lrflideres.com.br/wp-content/plugins/download-attachments/includes/download.php?id=6879 | AN77: p1 r11 | AO77: p1: R$ 2.406.485,64 | AP77: AJ_LIST | AQ77: 2026-01-15 | AR77: OK | AS77: ROWS:p1r11 | AT77: c56751547323
A78: 77 | B78: NEW | D78: 0 | I78: TRESBOMM COMERCIO E EXPORTACAO DE GRAOS LTDA EM RECUPERACAO JUDICIAL | J78: 2.30TRESBOMM COMERCIO E EXPORTACAO DE GRAOS LTDA | K78: 15660513 | L78: 15660513000104 | M78: 2398511.3 | N78: 1 | O78: B | P78: ACTIVE | Q78: 45534 | R78: =IF(Q78="","",ROUND((TODAY()-Q78)/365.25,1)) | S78: =IFERROR(VLOOKUP(O78,Assumptions!$A$7:$F$11,2,FALSE),0.25) | T78: =IF(O78="A",MAX(1,IFERROR(VLOOKUP(O78,Assumptions!$A$7:$F$11,3,FALSE),3)+IFERROR(VLOOKUP(O78,Assumptions!$A$7:$F$11,4,FALSE),8)/2-MAX(0,IF(R78="",0,R78)-IFERROR(VLOOKUP(O78,Assumptions!$A$7:$F$11,5,FALSE),1.5))),IFERROR(VLOOKUP(O78,Assumptions!$A$7:$F$11,5,FALSE),2.5)+IFERROR(VLOOKUP(O78,Assumptions!$A$7:$F$11,3,FALSE),3)+IFERROR(VLOOKUP(O78,Assumptions!$A$7:$F$11,4,FALSE),8)/2) | U78: =M78*S78/(1+Assumptions!$B$3)^T78 | V78: =IF(M78=0,"",ROUND(U78/M78*100,1)) | W78: =U78*Assumptions!$B$4 | X78: =IF(M78=0,"",ROUND(W78/M78*100,1)) | Y78: SUINOCULTURA KUNZLER | Z78: 5009149-92.2024.8.24.0019 | AA78: TJSC | AB78: rlg-aj.com.br | AC78: ERI CESAR TRES | AD78: Sócio-Administrador | AE78: (44) 3649-1240 | AH78: PR | AI78: PALOTINA | AJ78: Comércio atacadista de matérias-primas agrícolas não especificadas anteriormente | AK78: DEMAIS | AL78: ATIVA | AM78: https://rlg-aj.com.br/wp-content/uploads/2024/11/07.-Relação-de-credores.pdf | AN78: p1 r36 | AO78: p1: R$ 2.398.511,33 | AP78: UNKNOWN | AR78: OK_NO_TOTALS | AS78: ROWS:p1r36 UNRECONCILED_SOURCE | AT78: a62ac8ee0458
A79: 78 | B79: NEW | D79: 0 | I79: ITM LATIN AMERICA INDUSTRIA DE PECAS PARA TRATORES LTDA. | J79: PENDENTE DE REGULARIZAÇÃO | K79: 61352050 | L79: 61352050000122 | M79: 2360226.7 | N79: 1 | O79: B | R79: =IF(Q79="","",ROUND((TODAY()-Q79)/365.25,1)) | S79: =IFERROR(VLOOKUP(O79,Assumptions!$A$7:$F$11,2,FALSE),0.25) | T79: =IF(O79="A",MAX(1,IFERROR(VLOOKUP(O79,Assumptions!$A$7:$F$11,3,FALSE),3)+IFERROR(VLOOKUP(O79,Assumptions!$A$7:$F$11,4,FALSE),8)/2-MAX(0,IF(R79="",0,R79)-IFERROR(VLOOKUP(O79,Assumptions!$A$7:$F$11,5,FALSE),1.5))),IFERROR(VLOOKUP(O79,Assumptions!$A$7:$F$11,5,FALSE),2.5)+IFERROR(VLOOKUP(O79,Assumptions!$A$7:$F$11,3,FALSE),3)+IFERROR(VLOOKUP(O79,Assumptions!$A$7:$F$11,4,FALSE),8)/2) | U79: =M79*S79/(1+Assumptions!$B$3)^T79 | V79: =IF(M79=0,"",ROUND(U79/M79*100,1)) | W79: =U79*Assumptions!$B$4 | X79: =IF(M79=0,"",ROUND(W79/M79*100,1)) | Y79: Grupo Rech | Z79: 5057720-48.2025.8.24.0023 | AB79: credibilita.com.br | AC79: ANDERSON FLAVIANO DE MIRANDA | AD79: Administrador | AE79: (11) 4417-7700 | AH79: SP | AI79: ATIBAIA | AJ79: Fabricação de outras peças e acessórios para veículos automotores não especificadas anteriormente | AK79: DEMAIS | AL79: ATIVA | AM79: https://credibilita.com.br/wp-content/uploads/2025/09/Relacao-Credores-29.04.2026.pdf | AN79: p1 r29 | AO79: p1: R$ 2.360.226,69 | AP79: QUORUM_LIST | AR79: OK_NO_TOTALS | AS79: ROWS:p1r29 UNRECONCILED_SOURCE VALUE_COL:Valor_Após_Analise CASE_NUMBER_CORRECTED | AT79: cf92cff797d2
A80: 79 | B80: NEW | D80: 0 | I80: BIOTRONIK COMERCIAL MEDICA LTDA. | J80: BIOTRONIK COMERCIAL MEDICA LTDA ( | K80: 50595271 | L80: 50595271000105 | M80: 2311648.4 | N80: 1 | O80: C | P80: ACTIVE | Q80: 44735 | R80: =IF(Q80="","",ROUND((TODAY()-Q80)/365.25,1)) | S80: =IFERROR(VLOOKUP(O80,Assumptions!$A$7:$F$11,2,FALSE),0.25) | T80: =IF(O80="A",MAX(1,IFERROR(VLOOKUP(O80,Assumptions!$A$7:$F$11,3,FALSE),3)+IFERROR(VLOOKUP(O80,Assumptions!$A$7:$F$11,4,FALSE),8)/2-MAX(0,IF(R80="",0,R80)-IFERROR(VLOOKUP(O80,Assumptions!$A$7:$F$11,5,FALSE),1.5))),IFERROR(VLOOKUP(O80,Assumptions!$A$7:$F$11,5,FALSE),2.5)+IFERROR(VLOOKUP(O80,Assumptions!$A$7:$F$11,3,FALSE),3)+IFERROR(VLOOKUP(O80,Assumptions!$A$7:$F$11,4,FALSE),8)/2) | U80: =M80*S80/(1+Assumptions!$B$3)^T80 | V80: =IF(M80=0,"",ROUND(U80/M80*100,1)) | W80: =U80*Assumptions!$B$4 | X80: =IF(M80=0,"",ROUND(W80/M80*100,1)) | Y80: ASSOCIAÇÃO DE CARIDADE SANTA CASA DO RIO GRANDE | Z80: 5012306-16.2022.8.21.0023 | AA80: TJRS | AB80: scalzilliaj.com.br | AC80: CARLOS EDUARDO CAUTERUCCI FIGUEIREDO | AD80: Administrador | AE80: (11) 5694-7755 | AH80: SP | AI80: SAO PAULO | AJ80: Comércio atacadista de instrumentos e materiais para uso médico, cirúrgico, hospitalar e de laboratórios | AK80: DEMAIS | AL80: ATIVA | AM80: https://scalzilliaj.com.br/sgc/download.php?file=files/processo_documento/processo_documento09120721032023_1_.pdf&nome=15 - Edital do art. 7º, §2º e 53 da Lei 11.101/2005 (segunda lista de credores e recebimento do plano)) | AN80: p26 r10 | AO80: p26: R$ 2.311.648,44 | AP80: AJ_LIST | AQ80: 2023-03-21 | AR80: OK_NO_TOTALS | AS80: ROWS:p26r10 UNRECONCILED_SOURCE | AT80: ebfb999b457c
A81: 80 | B81: NEW | D81: 0 | I81: RAIZEN S.A. | J81: RODOVIA CASTELO BRANCO,2186, KM 21,5 - BARUERI-SP - CEP 06463-420 | K81: 33453598 | L81: 33453598017794 | M81: 2280760.7 | N81: 1 | O81: U | R81: =IF(Q81="","",ROUND((TODAY()-Q81)/365.25,1)) | S81: =IFERROR(VLOOKUP(O81,Assumptions!$A$7:$F$11,2,FALSE),0.25) | T81: =IF(O81="A",MAX(1,IFERROR(VLOOKUP(O81,Assumptions!$A$7:$F$11,3,FALSE),3)+IFERROR(VLOOKUP(O81,Assumptions!$A$7:$F$11,4,FALSE),8)/2-MAX(0,IF(R81="",0,R81)-IFERROR(VLOOKUP(O81,Assumptions!$A$7:$F$11,5,FALSE),1.5))),IFERROR(VLOOKUP(O81,Assumptions!$A$7:$F$11,5,FALSE),2.5)+IFERROR(VLOOKUP(O81,Assumptions!$A$7:$F$11,3,FALSE),3)+IFERROR(VLOOKUP(O81,Assumptions!$A$7:$F$11,4,FALSE),8)/2) | U81: =M81*S81/(1+Assumptions!$B$3)^T81 | V81: =IF(M81=0,"",ROUND(U81/M81*100,1)) | W81: =U81*Assumptions!$B$4 | X81: =IF(M81=0,"",ROUND(W81/M81*100,1)) | Y81: Base | Z81: (not found in document) | AB81: ajruiz.com.br | AC81: NELSON ROSEIRA GOMES NETO | AD81: Presidente | AE81: (19) 3423-8000 | AH81: RJ | AI81: RIO DE JANEIRO | AJ81: Comércio atacadista de álcool carburante, biodiesel, gasolina e demais derivados de petróleo, exceto lubrificantes, não realizado por transportador re | AK81: DEMAIS | AL81: ATIVA | AM81: https://ajruiz.com.br/sites/default/files/public/arquivos-processos/2023-11/4_relacao_de_credores_analitica_art._51_iii_da_lre.pdf | AN81: p3 r49 | AO81: p3: R$ 2.280.760,72 | AP81: UNKNOWN | AR81: OK | AS81: ROWS:p3r49 CASE_NUMBER_CORRECTED | AT81: 2407a56c3502
A82: 81 | B82: NEW | D82: 0 | I82: ASK CRIOS PRODUTOS QUIMICOS DO BRASIL LTDA | J82: SI Group Crios Resinas e S.A. | K82: 44246528 | L82: 44246528000110 | M82: 2270274.7 | N82: 1 | O82: C | P82: ACTIVE | Q82: 44218 | R82: =IF(Q82="","",ROUND((TODAY()-Q82)/365.25,1)) | S82: =IFERROR(VLOOKUP(O82,Assumptions!$A$7:$F$11,2,FALSE),0.25) | T82: =IF(O82="A",MAX(1,IFERROR(VLOOKUP(O82,Assumptions!$A$7:$F$11,3,FALSE),3)+IFERROR(VLOOKUP(O82,Assumptions!$A$7:$F$11,4,FALSE),8)/2-MAX(0,IF(R82="",0,R82)-IFERROR(VLOOKUP(O82,Assumptions!$A$7:$F$11,5,FALSE),1.5))),IFERROR(VLOOKUP(O82,Assumptions!$A$7:$F$11,5,FALSE),2.5)+IFERROR(VLOOKUP(O82,Assumptions!$A$7:$F$11,3,FALSE),3)+IFERROR(VLOOKUP(O82,Assumptions!$A$7:$F$11,4,FALSE),8)/2) | U82: =M82*S82/(1+Assumptions!$B$3)^T82 | V82: =IF(M82=0,"",ROUND(U82/M82*100,1)) | W82: =U82*Assumptions!$B$4 | X82: =IF(M82=0,"",ROUND(W82/M82*100,1)) | Y82: FORMAPLAN FORMAS PLANEJADAS INDÚSTRIA E COMÉRCIO LTDA | Z82: 0000410-68.2021.8.16.0174 | AA82: TJPR | AB82: marquesadmjudicial.com.br | AC82: LUIS ROBERTO OLIVEIRA DEGASPARI | AD82: Administrador | AE82: (19) 9953-9805 | AH82: SP | AI82: RIO CLARO | AJ82: Fabricação de resinas termofixas | AK82: DEMAIS | AL82: ATIVA | AM82: https://marquesadmjudicial.com.br/sgc/download.php?file=files/processo_documento/processo_documento15232121112024_1_.pdf&nome=Relação de Credores | AN82: p15 r19 | AO82: p15: R$ 2.270.274,68 | AP82: AJ_LIST | AQ82: 2021-01-22 | AR82: QUARANTINED | AS82: PARTIAL_DOC_CLASS_III_RECONCILED ROWS:p15r19 | AT82: b1a9f73b4c11
A83: 82 | B83: NEW | D83: 0 | I83: ESMALTEC S/A | J83: 02.948.030/0002-30 | K83: 02948030 | L83: 02948030000230 | M83: 2210242.8 | N83: 1 | O83: C | P83: ACTIVE | Q83: 43894 | R83: =IF(Q83="","",ROUND((TODAY()-Q83)/365.25,1)) | S83: =IFERROR(VLOOKUP(O83,Assumptions!$A$7:$F$11,2,FALSE),0.25) | T83: =IF(O83="A",MAX(1,IFERROR(VLOOKUP(O83,Assumptions!$A$7:$F$11,3,FALSE),3)+IFERROR(VLOOKUP(O83,Assumptions!$A$7:$F$11,4,FALSE),8)/2-MAX(0,IF(R83="",0,R83)-IFERROR(VLOOKUP(O83,Assumptions!$A$7:$F$11,5,FALSE),1.5))),IFERROR(VLOOKUP(O83,Assumptions!$A$7:$F$11,5,FALSE),2.5)+IFERROR(VLOOKUP(O83,Assumptions!$A$7:$F$11,3,FALSE),3)+IFERROR(VLOOKUP(O83,Assumptions!$A$7:$F$11,4,FALSE),8)/2) | U83: =M83*S83/(1+Assumptions!$B$3)^T83 | V83: =IF(M83=0,"",ROUND(U83/M83*100,1)) | W83: =U83*Assumptions!$B$4 | X83: =IF(M83=0,"",ROUND(W83/M83*100,1)) | Y83: CREDIMÓVEIS NOVOLAR LTDA. | Z83: 0007565-40.2020.8.17.2370 | AA83: TJPE | AB83: recuperacaojudicial.squarespace.com | AC83: CARLOS HENRIQUE STELLA ROTELLA | AD83: Presidente | AE83: (85) 3466-8540 | AH83: CE | AI83: FORTALEZA | AJ83: Fabricação de fogões, refrigeradores e máquinas de lavar e secar para uso doméstico, peças e acessórios | AK83: DEMAIS | AL83: ATIVA | AM83: https://recuperacaojudicial.squarespace.com/s/RJ-Credimoveis-QGC-01082025.pdf | AN83: p15 r42 | AO83: p15: R$ 2.210.242,75 | AP83: QGC | AQ83: 2026-01-28 | AR83: OK | AS83: ROWS:p15r42 | AT83: 849d4fe5adce
A84: 83 | B84: NEW | D84: 0 | I84: FALCON DISTRIBUICAO, ARMAZENAMENTO E TRANSPORTES S.A. | J84: Falcon Distribuição, Armazenamento e Transportes S/A | K84: 23191831 | L84: 23191831000193 | M84: 2199541.2 | N84: 1 | O84: C | P84: ACTIVE | Q84: 44987 | R84: =IF(Q84="","",ROUND((TODAY()-Q84)/365.25,1)) | S84: =IFERROR(VLOOKUP(O84,Assumptions!$A$7:$F$11,2,FALSE),0.25) | T84: =IF(O84="A",MAX(1,IFERROR(VLOOKUP(O84,Assumptions!$A$7:$F$11,3,FALSE),3)+IFERROR(VLOOKUP(O84,Assumptions!$A$7:$F$11,4,FALSE),8)/2-MAX(0,IF(R84="",0,R84)-IFERROR(VLOOKUP(O84,Assumptions!$A$7:$F$11,5,FALSE),1.5))),IFERROR(VLOOKUP(O84,Assumptions!$A$7:$F$11,5,FALSE),2.5)+IFERROR(VLOOKUP(O84,Assumptions!$A$7:$F$11,3,FALSE),3)+IFERROR(VLOOKUP(O84,Assumptions!$A$7:$F$11,4,FALSE),8)/2) | U84: =M84*S84/(1+Assumptions!$B$3)^T84 | V84: =IF(M84=0,"",ROUND(U84/M84*100,1)) | W84: =U84*Assumptions!$B$4 | X84: =IF(M84=0,"",ROUND(W84/M84*100,1)) | Y84: GRUPO DP4 | Z84: 0005010-98.2023.8.16.0001 | AA84: TJPR | AB84: marquesadmjudicial.com.br | AC84: ADRIANO DE CONTI BERNARDI | AD84: Diretor | AE84: (11) 9177-5953 | AH84: GO | AI84: GOIANIA | AJ84: Comércio atacadista de produtos de higiene pessoal | AK84: DEMAIS | AL84: ATIVA | AM84: https://marquesadmjudicial.com.br/sgc/download.php?file=files/processo_documento/processo_documento15293208032024_1_.pdf&nome=Relação Nominal de Credores da AJ-Sintética | AN84: p25 r5 | AO84: p25: R$ 2.199.541,23 | AP84: AJ_LIST | AQ84: 2023-03-02 | AR84: QUARANTINED | AS84: PARTIAL_DOC_CLASS_III_RECONCILED ROWS:p25r5 | AT84: b465a5d11eec
A85: 84 | B85: NEW | D85: 0 | I85: STRATURA ASFALTOS LTDA. | J85: STRATURA ASFALTOS S.A. | K85: 59128553 | L85: 59128553002110 | M85: 2146226.5 | N85: 1 | O85: C | P85: ACTIVE | Q85: 43838 | R85: =IF(Q85="","",ROUND((TODAY()-Q85)/365.25,1)) | S85: =IFERROR(VLOOKUP(O85,Assumptions!$A$7:$F$11,2,FALSE),0.25) | T85: =IF(O85="A",MAX(1,IFERROR(VLOOKUP(O85,Assumptions!$A$7:$F$11,3,FALSE),3)+IFERROR(VLOOKUP(O85,Assumptions!$A$7:$F$11,4,FALSE),8)/2-MAX(0,IF(R85="",0,R85)-IFERROR(VLOOKUP(O85,Assumptions!$A$7:$F$11,5,FALSE),1.5))),IFERROR(VLOOKUP(O85,Assumptions!$A$7:$F$11,5,FALSE),2.5)+IFERROR(VLOOKUP(O85,Assumptions!$A$7:$F$11,3,FALSE),3)+IFERROR(VLOOKUP(O85,Assumptions!$A$7:$F$11,4,FALSE),8)/2) | U85: =M85*S85/(1+Assumptions!$B$3)^T85 | V85: =IF(M85=0,"",ROUND(U85/M85*100,1)) | W85: =U85*Assumptions!$B$4 | X85: =IF(M85=0,"",ROUND(W85/M85*100,1)) | Y85: CONSTRUTORA ANDRADE GUEDES LTDA | Z85: 0000880-57.2020.8.17.2001 | AA85: TJPE | AB85: diligence.adm.br | AC85: CARLOS ALBERTO DE AQUINO PINHEIRO JUNIOR | AD85: Administrador | AE85: (11) 3513-4260 | AH85: SP | AI85: SAO PAULO | AJ85: Serviços combinados de escritório e apoio administrativo | AK85: DEMAIS | AL85: ATIVA | AM85: https://diligence.adm.br/wp-content/plugins/download-attachments/includes/download.php?id=4599 | AN85: p10 r77 | AO85: p10: R$ 2.146.226,53 | AP85: AJ_LIST | AQ85: 2024-06-25 | AR85: OK_NO_TOTALS | AS85: ALT_VALUE:R$1.615.549,86 ALT_VALUE:R$530.676,67 ROWS:p10r77 UNRECONCILED_SOURCE VALUE_COL:2ª_Lista | AT85: 44ecd0afa707
A86: 85 | B86: NEW | D86: 0 | I86: VENTISOL DA AMAZONIA INDUSTRIA DE APARELHOS ELETRICOS LTDA | J86: Rua Azaleia, 2421, Distrito Industrial, Manaus - CEP 69075845 | K86: 17417928 | L86: 17417928000179 | M86: 2121705.9 | N86: 1 | O86: C | R86: =IF(Q86="","",ROUND((TODAY()-Q86)/365.25,1)) | S86: =IFERROR(VLOOKUP(O86,Assumptions!$A$7:$F$11,2,FALSE),0.25) | T86: =IF(O86="A",MAX(1,IFERROR(VLOOKUP(O86,Assumptions!$A$7:$F$11,3,FALSE),3)+IFERROR(VLOOKUP(O86,Assumptions!$A$7:$F$11,4,FALSE),8)/2-MAX(0,IF(R86="",0,R86)-IFERROR(VLOOKUP(O86,Assumptions!$A$7:$F$11,5,FALSE),1.5))),IFERROR(VLOOKUP(O86,Assumptions!$A$7:$F$11,5,FALSE),2.5)+IFERROR(VLOOKUP(O86,Assumptions!$A$7:$F$11,3,FALSE),3)+IFERROR(VLOOKUP(O86,Assumptions!$A$7:$F$11,4,FALSE),8)/2) | U86: =M86*S86/(1+Assumptions!$B$3)^T86 | V86: =IF(M86=0,"",ROUND(U86/M86*100,1)) | W86: =U86*Assumptions!$B$4 | X86: =IF(M86=0,"",ROUND(W86/M86*100,1)) | Y86: REAL DISTRIBUIDORA ÚNICA RIO COMÉRCIO DE REFRIGERAÇÃO LTDA. | Z86: 0873061-47.2023.8.19.0001 | AB86: inova-aj.com.br | AC86: ALEXIS SUREN TCHOLAKIAN MORALES | AD86: Sócio-Administrador | AE86: (92) 3029-1000 | AH86: AM | AI86: MANAUS | AJ86: Fabricação de aparelhos e equipamentos de ar condicionado para uso industrial | AK86: DEMAIS | AL86: ATIVA | AM86: https://inova-aj.com.br/wp-content/uploads/2026/08/1a-Relacao-de-Credores-Real.pdf | AN86: p2 r16 | AO86: p2: R$ 2.121.705,89 | AP86: AJ_LIST | AQ86: 2023-06-05 | AR86: OK | AS86: ALT_VALUE:R$1.542.709,43 ROWS:p2r16 | AT86: 8eb5d0d64353
A87: 86 | B87: NEW | D87: 0 | I87: FRONTEIRA COMERCIO E REPRESENTACAO DE PRODUTOS AGROPECUARIOS LTDA | J87: Nutrien Solucoes Agricolas | K87: 36854495 | L87: 36854495002298 | M87: 2120225.1 | N87: 1 | O87: B | P87: ACTIVE | Q87: 46130 | R87: =IF(Q87="","",ROUND((TODAY()-Q87)/365.25,1)) | S87: =IFERROR(VLOOKUP(O87,Assumptions!$A$7:$F$11,2,FALSE),0.25) | T87: =IF(O87="A",MAX(1,IFERROR(VLOOKUP(O87,Assumptions!$A$7:$F$11,3,FALSE),3)+IFERROR(VLOOKUP(O87,Assumptions!$A$7:$F$11,4,FALSE),8)/2-MAX(0,IF(R87="",0,R87)-IFERROR(VLOOKUP(O87,Assumptions!$A$7:$F$11,5,FALSE),1.5))),IFERROR(VLOOKUP(O87,Assumptions!$A$7:$F$11,5,FALSE),2.5)+IFERROR(VLOOKUP(O87,Assumptions!$A$7:$F$11,3,FALSE),3)+IFERROR(VLOOKUP(O87,Assumptions!$A$7:$F$11,4,FALSE),8)/2) | U87: =M87*S87/(1+Assumptions!$B$3)^T87 | V87: =IF(M87=0,"",ROUND(U87/M87*100,1)) | W87: =U87*Assumptions!$B$4 | X87: =IF(M87=0,"",ROUND(W87/M87*100,1)) | Y87: GRUPO 3E | Z87: 5341375-33.2026.8.09.0049 | AA87: TJGO | AB87: stenius.com.br | AC87: CARLOS EDUARDO FAZZIO DE BRITO | AD87: Administrador | AE87: (11) 5400-0021 | AH87: GO | AI87: RIO VERDE | AJ87: Comércio atacadista de mercadorias em geral, com predominância de insumos agropecuários | AK87: DEMAIS | AL87: ATIVA | AM87: https://stenius.com.br/wp-content/uploads/2026/06/EDITAL-GRUPO-3E.pdf | AN87: p16 r31 | AO87: p16: R$ 2.120.225,10 | AP87: DEBTOR_LIST | AQ87: 2026-06-22 | AR87: OK_NO_TOTALS | AS87: ROWS:p16r31 UNRECONCILED_SOURCE | AT87: 8e8832093a15
A88: 87 | B88: NEW | D88: 0 | I88: SRJ INDUSTRIA COMERCIO E EXPORTACAO DE CONFECCOES LTDA | J88: SRJ INDUSTRIA COMERCIO E EXPORTACAO DE CONFECCOES LTDA | K88: 05554669 | L88: 05554669000149 | M88: 2113920 | N88: 1 | O88: C | P88: ACTIVE | Q88: 44571 | R88: =IF(Q88="","",ROUND((TODAY()-Q88)/365.25,1)) | S88: =IFERROR(VLOOKUP(O88,Assumptions!$A$7:$F$11,2,FALSE),0.25) | T88: =IF(O88="A",MAX(1,IFERROR(VLOOKUP(O88,Assumptions!$A$7:$F$11,3,FALSE),3)+IFERROR(VLOOKUP(O88,Assumptions!$A$7:$F$11,4,FALSE),8)/2-MAX(0,IF(R88="",0,R88)-IFERROR(VLOOKUP(O88,Assumptions!$A$7:$F$11,5,FALSE),1.5))),IFERROR(VLOOKUP(O88,Assumptions!$A$7:$F$11,5,FALSE),2.5)+IFERROR(VLOOKUP(O88,Assumptions!$A$7:$F$11,3,FALSE),3)+IFERROR(VLOOKUP(O88,Assumptions!$A$7:$F$11,4,FALSE),8)/2) | U88: =M88*S88/(1+Assumptions!$B$3)^T88 | V88: =IF(M88=0,"",ROUND(U88/M88*100,1)) | W88: =U88*Assumptions!$B$4 | X88: =IF(M88=0,"",ROUND(W88/M88*100,1)) | Y88: GRUPO CATTAN | Z88: 0002484-82.2022.8.17.2001 | AA88: TJPE | AB88: lrflideres.com.br | AC88: JOAQUIM COELHO DE MAGALHAES | AD88: Administrador | AH88: PE | AI88: CARUARU | AJ88: Confecção de peças de vestuário, exceto roupas íntimas e as confeccionadas sob medida | AK88: DEMAIS | AL88: ATIVA | AM88: https://lrflideres.com.br/wp-content/plugins/download-attachments/includes/download.php?id=4023 | AN88: p4 r92; p7 r121 | AO88: p4: R$ 2.113.920,00; p7: R$ 2.113.920,00 | AP88: DEBTOR_LIST | AR88: QUARANTINED | AS88: PARTIAL_DOC_CLASS_III_RECONCILED ROWS:p4r92 | AT88: f3b6182e3aa2
A89: 88 | B89: NEW | D89: 0 | I89: ADM DO BRASIL LTDA | J89: 2.15ADM DO BRASIL LTDA | K89: 02003402 | L89: 02003402004677 | M89: 2086675 | N89: 1 | O89: B | P89: ACTIVE | Q89: 45534 | R89: =IF(Q89="","",ROUND((TODAY()-Q89)/365.25,1)) | S89: =IFERROR(VLOOKUP(O89,Assumptions!$A$7:$F$11,2,FALSE),0.25) | T89: =IF(O89="A",MAX(1,IFERROR(VLOOKUP(O89,Assumptions!$A$7:$F$11,3,FALSE),3)+IFERROR(VLOOKUP(O89,Assumptions!$A$7:$F$11,4,FALSE),8)/2-MAX(0,IF(R89="",0,R89)-IFERROR(VLOOKUP(O89,Assumptions!$A$7:$F$11,5,FALSE),1.5))),IFERROR(VLOOKUP(O89,Assumptions!$A$7:$F$11,5,FALSE),2.5)+IFERROR(VLOOKUP(O89,Assumptions!$A$7:$F$11,3,FALSE),3)+IFERROR(VLOOKUP(O89,Assumptions!$A$7:$F$11,4,FALSE),8)/2) | U89: =M89*S89/(1+Assumptions!$B$3)^T89 | V89: =IF(M89=0,"",ROUND(U89/M89*100,1)) | W89: =U89*Assumptions!$B$4 | X89: =IF(M89=0,"",ROUND(W89/M89*100,1)) | Y89: SUINOCULTURA KUNZLER | Z89: 5009149-92.2024.8.24.0019 | AA89: TJSC | AB89: rlg-aj.com.br | AC89: ANDREIELI RIBEIRO PINTO | AD89: Administrador | AE89: (11) 5185-3500 | AF89: (11) 5185-3649 | AH89: ES | AI89: VITORIA | AJ89: Comércio atacadista de matérias-primas agrícolas não especificadas anteriormente | AK89: DEMAIS | AL89: ATIVA | AM89: https://rlg-aj.com.br/wp-content/uploads/2024/11/07.-Relação-de-credores.pdf | AN89: p1 r21 | AO89: p1: R$ 2.086.675,04 | AP89: UNKNOWN | AR89: OK_NO_TOTALS | AS89: ROWS:p1r21 UNRECONCILED_SOURCE | AT89: a62ac8ee0458
A90: 89 | B90: NEW | D90: 0 | I90: TRES TENTOS AGROINDUSTRIAL S/A | J90: 2.14TRES TENTOS AGROINDUSTRIAL S/A | K90: 94813102 | L90: 94813102000846 | M90: 2076705.8 | N90: 1 | O90: B | P90: ACTIVE | Q90: 45534 | R90: =IF(Q90="","",ROUND((TODAY()-Q90)/365.25,1)) | S90: =IFERROR(VLOOKUP(O90,Assumptions!$A$7:$F$11,2,FALSE),0.25) | T90: =IF(O90="A",MAX(1,IFERROR(VLOOKUP(O90,Assumptions!$A$7:$F$11,3,FALSE),3)+IFERROR(VLOOKUP(O90,Assumptions!$A$7:$F$11,4,FALSE),8)/2-MAX(0,IF(R90="",0,R90)-IFERROR(VLOOKUP(O90,Assumptions!$A$7:$F$11,5,FALSE),1.5))),IFERROR(VLOOKUP(O90,Assumptions!$A$7:$F$11,5,FALSE),2.5)+IFERROR(VLOOKUP(O90,Assumptions!$A$7:$F$11,3,FALSE),3)+IFERROR(VLOOKUP(O90,Assumptions!$A$7:$F$11,4,FALSE),8)/2) | U90: =M90*S90/(1+Assumptions!$B$3)^T90 | V90: =IF(M90=0,"",ROUND(U90/M90*100,1)) | W90: =U90*Assumptions!$B$4 | X90: =IF(M90=0,"",ROUND(W90/M90*100,1)) | Y90: SUINOCULTURA KUNZLER | Z90: 5009149-92.2024.8.24.0019 | AA90: TJSC | AB90: rlg-aj.com.br | AC90: JOAO MARCELO DUMONCEL | AD90: Presidente | AE90: (55) 3372-3700 | AF90: (55) 3372-3718 | AH90: RS | AI90: SANTA BARBARA DO SUL | AJ90: Comércio atacadista de cereais e leguminosas beneficiados | AK90: DEMAIS | AL90: ATIVA | AM90: https://rlg-aj.com.br/wp-content/uploads/2024/11/07.-Relação-de-credores.pdf | AN90: p1 r20 | AO90: p1: R$ 2.076.705,80 | AP90: UNKNOWN | AR90: OK_NO_TOTALS | AS90: ROWS:p1r20 UNRECONCILED_SOURCE | AT90: a62ac8ee0458
A91: 90 | B91: NEW | D91: 0 | I91: SEMPRE AGTECH LTDA | J91: SEMPRE AGTECH LTDA | K91: 09536120 | L91: 09536120000263 | M91: 2037617 | N91: 1 | O91: B | P91: ACTIVE | Q91: 45845 | R91: =IF(Q91="","",ROUND((TODAY()-Q91)/365.25,1)) | S91: =IFERROR(VLOOKUP(O91,Assumptions!$A$7:$F$11,2,FALSE),0.25) | T91: =IF(O91="A",MAX(1,IFERROR(VLOOKUP(O91,Assumptions!$A$7:$F$11,3,FALSE),3)+IFERROR(VLOOKUP(O91,Assumptions!$A$7:$F$11,4,FALSE),8)/2-MAX(0,IF(R91="",0,R91)-IFERROR(VLOOKUP(O91,Assumptions!$A$7:$F$11,5,FALSE),1.5))),IFERROR(VLOOKUP(O91,Assumptions!$A$7:$F$11,5,FALSE),2.5)+IFERROR(VLOOKUP(O91,Assumptions!$A$7:$F$11,3,FALSE),3)+IFERROR(VLOOKUP(O91,Assumptions!$A$7:$F$11,4,FALSE),8)/2) | U91: =M91*S91/(1+Assumptions!$B$3)^T91 | V91: =IF(M91=0,"",ROUND(U91/M91*100,1)) | W91: =U91*Assumptions!$B$4 | X91: =IF(M91=0,"",ROUND(W91/M91*100,1)) | Y91: SOJAL COMERCIAL AGRICOLA LTDA e OUTROS | Z91: 0804401-51.2025.8.14.0039 | AA91: TJPA | AB91: lrflideres.com.br | AC91: FERNANDO JOAO PREZZOTTO | AD91: Sócio-Administrador | AE91: (49) 3441-8200 | AH91: SC | AI91: CHAPECO | AJ91: Produção de sementes certificadas, exceto de forrageiras para pasto | AK91: DEMAIS | AL91: ATIVA | AM91: https://lrflideres.com.br/wp-content/plugins/download-attachments/includes/download.php?id=6879 | AN91: p2 r7 | AO91: p2: R$ 2.037.616,99 | AP91: AJ_LIST | AQ91: 2026-01-15 | AR91: OK | AS91: ROWS:p2r7 | AT91: c56751547323
A92: 91 | B92: NEW | D92: 0 | I92: FERTILIZANTES TOCANTINS S.A | J92: FERTILIZANTES TOCANTINS S.A | K92: 05571228 | L92: 05571228000155 | M92: 2016948.6 | N92: 1 | O92: B | P92: ACTIVE | Q92: 45845 | R92: =IF(Q92="","",ROUND((TODAY()-Q92)/365.25,1)) | S92: =IFERROR(VLOOKUP(O92,Assumptions!$A$7:$F$11,2,FALSE),0.25) | T92: =IF(O92="A",MAX(1,IFERROR(VLOOKUP(O92,Assumptions!$A$7:$F$11,3,FALSE),3)+IFERROR(VLOOKUP(O92,Assumptions!$A$7:$F$11,4,FALSE),8)/2-MAX(0,IF(R92="",0,R92)-IFERROR(VLOOKUP(O92,Assumptions!$A$7:$F$11,5,FALSE),1.5))),IFERROR(VLOOKUP(O92,Assumptions!$A$7:$F$11,5,FALSE),2.5)+IFERROR(VLOOKUP(O92,Assumptions!$A$7:$F$11,3,FALSE),3)+IFERROR(VLOOKUP(O92,Assumptions!$A$7:$F$11,4,FALSE),8)/2) | U92: =M92*S92/(1+Assumptions!$B$3)^T92 | V92: =IF(M92=0,"",ROUND(U92/M92*100,1)) | W92: =U92*Assumptions!$B$4 | X92: =IF(M92=0,"",ROUND(W92/M92*100,1)) | Y92: SOJAL COMERCIAL AGRICOLA LTDA e OUTROS | Z92: 0804401-51.2025.8.14.0039 | AA92: TJPA | AB92: lrflideres.com.br | AC92: DMITRY CHERNYKH | AD92: Presidente | AE92: (62) 3414-6300 | AH92: TO | AI92: PORTO NACIONAL | AJ92: Fabricação de adubos e fertilizantes, exceto organo-minerais | AK92: DEMAIS | AL92: ATIVA | AM92: https://lrflideres.com.br/wp-content/plugins/download-attachments/includes/download.php?id=6879 | AN92: p2 r1 | AO92: p2: R$ 2.016.948,56 | AP92: AJ_LIST | AQ92: 2026-01-15 | AR92: OK | AS92: ROWS:p2r1 | AT92: c56751547323
A93: 92 | B93: NEW | D93: 0 | I93: STRATURA ASFALTOS LTDA. | J93: Stratura Asfaltos S/A | K93: 59128553 | L93: 59128553000177 | M93: 2010640.8 | N93: 1 | O93: B | Q93: 45756 | R93: =IF(Q93="","",ROUND((TODAY()-Q93)/365.25,1)) | S93: =IFERROR(VLOOKUP(O93,Assumptions!$A$7:$F$11,2,FALSE),0.25) | T93: =IF(O93="A",MAX(1,IFERROR(VLOOKUP(O93,Assumptions!$A$7:$F$11,3,FALSE),3)+IFERROR(VLOOKUP(O93,Assumptions!$A$7:$F$11,4,FALSE),8)/2-MAX(0,IF(R93="",0,R93)-IFERROR(VLOOKUP(O93,Assumptions!$A$7:$F$11,5,FALSE),1.5))),IFERROR(VLOOKUP(O93,Assumptions!$A$7:$F$11,5,FALSE),2.5)+IFERROR(VLOOKUP(O93,Assumptions!$A$7:$F$11,3,FALSE),3)+IFERROR(VLOOKUP(O93,Assumptions!$A$7:$F$11,4,FALSE),8)/2) | U93: =M93*S93/(1+Assumptions!$B$3)^T93 | V93: =IF(M93=0,"",ROUND(U93/M93*100,1)) | W93: =U93*Assumptions!$B$4 | X93: =IF(M93=0,"",ROUND(W93/M93*100,1)) | Y93: GRUPO EGESA (EGESA ENG S.A, EGESUR PART E EMP S.A, MATRIX INFRA LTDA, BEMVIVER ENG AMBIENTAL E SERV LTDA, DKF CONST E EMP LTDA, EGEPEL LTDA, ETR ASSESSORIA EMP E PART LTDA, MVT ENG E SERV LTDA, PARQUES DO VALE LTDA, ELMO RIBEIRO E ANA RIBEIRO) | Z93: 5088952-81.2025.8.13.0024 | AA93: TJMG | AB93: scalzilliaj.com.br | AC93: CARLOS ALBERTO DE AQUINO PINHEIRO JUNIOR | AD93: Administrador | AE93: (11) 3513-4260 | AH93: SP | AI93: SAO PAULO | AJ93: Serviços combinados de escritório e apoio administrativo | AK93: DEMAIS | AL93: ATIVA | AM93: https://scalzilliaj.com.br/sgc/download.php?file=files/processo_documento/processo_documento09514021082025_1_.pdf&nome=04 - Relação de credores das Recuperandas | AN93: p73 r13 | AO93: p73: R$ 2.010.640,78 | AP93: DEBTOR_LIST | AR93: OK | AS93: ROWS:p73r13 VALUE_COL:Valor_Atualizado CASE_NUMBER_CORRECTED CASE_FROM_PORTAL | AT93: 24ed98480a57
A94: 93 | B94: NEW | D94: 0 | I94: REICHENBACH EQUIPAMENTOS INDUSTRIA E COMERCIO LTDA | J94: REICHENBACH EQUIP IND.COM. LTDA | K94: 71799001 | L94: 71799001000196 | M94: 2002544.3 | N94: 1 | O94: C | P94: ACTIVE | Q94: 45068 | R94: =IF(Q94="","",ROUND((TODAY()-Q94)/365.25,1)) | S94: =IFERROR(VLOOKUP(O94,Assumptions!$A$7:$F$11,2,FALSE),0.25) | T94: =IF(O94="A",MAX(1,IFERROR(VLOOKUP(O94,Assumptions!$A$7:$F$11,3,FALSE),3)+IFERROR(VLOOKUP(O94,Assumptions!$A$7:$F$11,4,FALSE),8)/2-MAX(0,IF(R94="",0,R94)-IFERROR(VLOOKUP(O94,Assumptions!$A$7:$F$11,5,FALSE),1.5))),IFERROR(VLOOKUP(O94,Assumptions!$A$7:$F$11,5,FALSE),2.5)+IFERROR(VLOOKUP(O94,Assumptions!$A$7:$F$11,3,FALSE),3)+IFERROR(VLOOKUP(O94,Assumptions!$A$7:$F$11,4,FALSE),8)/2) | U94: =M94*S94/(1+Assumptions!$B$3)^T94 | V94: =IF(M94=0,"",ROUND(U94/M94*100,1)) | W94: =U94*Assumptions!$B$4 | X94: =IF(M94=0,"",ROUND(W94/M94*100,1)) | Y94: Grupo Conduscabos | Z94: 8005129-09.2023.8.05.0039 | AA94: TJBA | AB94: assistjud.com.br | AC94: ALLAN WERNER REICHENBACH | AD94: Sócio-Administrador | AE94: (11) 4181-5054 | AH94: SP | AI94: CARAPICUIBA | AJ94: Fabricação de outras máquinas e equipamentos de uso geral não especificados anteriormente, peças e acessórios | AK94: DEMAIS | AL94: ATIVA | AM94: https://assistjud.com.br/wp-content/uploads/elementor/forms/65098c80a5824.pdf | AN94: p19 r6 | AO94: p19: R$ 2.002.544,34 | AP94: AJ_LIST | AQ94: 2023-09-18 | AR94: OK_NO_TOTALS | AS94: ROWS:p19r6 UNRECONCILED_SOURCE | AT94: a0ae32a59c29
A95: 94 | B95: NEW | D95: 0 | I95: AGRO INDUSTRIA NUTRIHORTO LTDA | J95: AGRO INDUSTRIA NUTRIHORTO LTDA | K95: 29652131 | L95: 29652131000135 | M95: 1993755.4 | N95: 1 | O95: C | P95: ACTIVE | Q95: 45264 | R95: =IF(Q95="","",ROUND((TODAY()-Q95)/365.25,1)) | S95: =IFERROR(VLOOKUP(O95,Assumptions!$A$7:$F$11,2,FALSE),0.25) | T95: =IF(O95="A",MAX(1,IFERROR(VLOOKUP(O95,Assumptions!$A$7:$F$11,3,FALSE),3)+IFERROR(VLOOKUP(O95,Assumptions!$A$7:$F$11,4,FALSE),8)/2-MAX(0,IF(R95="",0,R95)-IFERROR(VLOOKUP(O95,Assumptions!$A$7:$F$11,5,FALSE),1.5))),IFERROR(VLOOKUP(O95,Assumptions!$A$7:$F$11,5,FALSE),2.5)+IFERROR(VLOOKUP(O95,Assumptions!$A$7:$F$11,3,FALSE),3)+IFERROR(VLOOKUP(O95,Assumptions!$A$7:$F$11,4,FALSE),8)/2) | U95: =M95*S95/(1+Assumptions!$B$3)^T95 | V95: =IF(M95=0,"",ROUND(U95/M95*100,1)) | W95: =U95*Assumptions!$B$4 | X95: =IF(M95=0,"",ROUND(W95/M95*100,1)) | Y95: Alto Uruguai Indústria e Comércio de Óleos Ltda | Z95: 5012743-51.2023.8.24.0019 | AA95: TJSC | AB95: ajruiz.com.br | AC95: OZEDIO ZUCA JUNIOR | AD95: Sócio-Administrador | AE95: (19) 3199-1270 | AH95: SP | AI95: MONTE MOR | AJ95: Recuperação de materiais não especificados anteriormente | AK95: DEMAIS | AL95: ATIVA | AM95: https://ajruiz.com.br/sites/default/files/public/arquivos-processos/2026-06/alto_uruguai_qgc_junho.2026.pdf | AN95: p1 r3 | AO95: p1: R$ 1.993.755,38 | AP95: UNKNOWN | AR95: OK | AS95: ROWS:p1r3 VALUE_COL:Valor_Do_Crédito | AT95: 75336e98f447
A96: 95 | B96: NEW | D96: 0 | I96: PROTEGO BRASIL VALVULAS E CORTA CHAMAS LTDA | J96: Protego Brasil Válvulas e Corya Chamas Ltda | K96: 14325185 | L96: 14325185000119 | M96: 1955788.1 | N96: 1 | O96: B | Q96: 45756 | R96: =IF(Q96="","",ROUND((TODAY()-Q96)/365.25,1)) | S96: =IFERROR(VLOOKUP(O96,Assumptions!$A$7:$F$11,2,FALSE),0.25) | T96: =IF(O96="A",MAX(1,IFERROR(VLOOKUP(O96,Assumptions!$A$7:$F$11,3,FALSE),3)+IFERROR(VLOOKUP(O96,Assumptions!$A$7:$F$11,4,FALSE),8)/2-MAX(0,IF(R96="",0,R96)-IFERROR(VLOOKUP(O96,Assumptions!$A$7:$F$11,5,FALSE),1.5))),IFERROR(VLOOKUP(O96,Assumptions!$A$7:$F$11,5,FALSE),2.5)+IFERROR(VLOOKUP(O96,Assumptions!$A$7:$F$11,3,FALSE),3)+IFERROR(VLOOKUP(O96,Assumptions!$A$7:$F$11,4,FALSE),8)/2) | U96: =M96*S96/(1+Assumptions!$B$3)^T96 | V96: =IF(M96=0,"",ROUND(U96/M96*100,1)) | W96: =U96*Assumptions!$B$4 | X96: =IF(M96=0,"",ROUND(W96/M96*100,1)) | Y96: GRUPO EGESA (EGESA ENG S.A, EGESUR PART E EMP S.A, MATRIX INFRA LTDA, BEMVIVER ENG AMBIENTAL E SERV LTDA, DKF CONST E EMP LTDA, EGEPEL LTDA, ETR ASSESSORIA EMP E PART LTDA, MVT ENG E SERV LTDA, PARQUES DO VALE LTDA, ELMO RIBEIRO E ANA RIBEIRO) | Z96: 5088952-81.2025.8.13.0024 | AA96: TJMG | AB96: scalzilliaj.com.br | AC96: FRANCISCO HUBERTUS GROSSE SIESTRUP | AD96: Sócio-Administrador | AE96: (21) 2112-5700 | AF96: (21) 2112-5717 | AH96: RJ | AI96: RIO DE JANEIRO | AJ96: Fabricação de válvulas, registros e dispositivos semelhantes, peças e acessórios | AK96: DEMAIS | AL96: ATIVA | AM96: https://scalzilliaj.com.br/sgc/download.php?file=files/processo_documento/processo_documento09514021082025_1_.pdf&nome=04 - Relação de credores das Recuperandas | AN96: p71 r18 | AO96: p71: R$ 1.955.788,12 | AP96: DEBTOR_LIST | AR96: OK | AS96: ROWS:p71r18 VALUE_COL:Valor_Atualizado CASE_NUMBER_CORRECTED CASE_FROM_PORTAL | AT96: 24ed98480a57
A97: 96 | B97: NEW | D97: 0 | I97: GEOLAB INDUSTRIA FARMACEUTICA S/A | J97: Geolab Industria Farmaceutica S/A | K97: 03485572 | L97: 03485572000104 | M97: 1918724.7 | N97: 1 | O97: C | P97: ACTIVE | Q97: 44987 | R97: =IF(Q97="","",ROUND((TODAY()-Q97)/365.25,1)) | S97: =IFERROR(VLOOKUP(O97,Assumptions!$A$7:$F$11,2,FALSE),0.25) | T97: =IF(O97="A",MAX(1,IFERROR(VLOOKUP(O97,Assumptions!$A$7:$F$11,3,FALSE),3)+IFERROR(VLOOKUP(O97,Assumptions!$A$7:$F$11,4,FALSE),8)/2-MAX(0,IF(R97="",0,R97)-IFERROR(VLOOKUP(O97,Assumptions!$A$7:$F$11,5,FALSE),1.5))),IFERROR(VLOOKUP(O97,Assumptions!$A$7:$F$11,5,FALSE),2.5)+IFERROR(VLOOKUP(O97,Assumptions!$A$7:$F$11,3,FALSE),3)+IFERROR(VLOOKUP(O97,Assumptions!$A$7:$F$11,4,FALSE),8)/2) | U97: =M97*S97/(1+Assumptions!$B$3)^T97 | V97: =IF(M97=0,"",ROUND(U97/M97*100,1)) | W97: =U97*Assumptions!$B$4 | X97: =IF(M97=0,"",ROUND(W97/M97*100,1)) | Y97: GRUPO DP4 | Z97: 0005010-98.2023.8.16.0001 | AA97: TJPR | AB97: marquesadmjudicial.com.br | AC97: GEORGES HAJJAR JUNIOR | AD97: Presidente | AE97: (62) 4015-4000 | AH97: GO | AI97: ANAPOLIS | AJ97: Fabricação de medicamentos alopáticos para uso humano | AK97: DEMAIS | AL97: ATIVA | AM97: https://marquesadmjudicial.com.br/sgc/download.php?file=files/processo_documento/processo_documento15293208032024_1_.pdf&nome=Relação Nominal de Credores da AJ-Sintética | AN97: p26 r3 | AO97: p26: R$ 1.918.724,72 | AP97: AJ_LIST | AQ97: 2023-03-02 | AR97: QUARANTINED | AS97: PARTIAL_DOC_CLASS_III_RECONCILED ROWS:p26r3 | AT97: b465a5d11eec
A98: 97 | B98: NEW | D98: 0 | I98: OLINDA INDUSTRIA E COMERCIO DE COLCHOES LTDA | J98: 02.748.323/0001-93 | K98: 02748323 | L98: 02748323000193 | M98: 1902217.4 | N98: 1 | O98: C | P98: ACTIVE | Q98: 43894 | R98: =IF(Q98="","",ROUND((TODAY()-Q98)/365.25,1)) | S98: =IFERROR(VLOOKUP(O98,Assumptions!$A$7:$F$11,2,FALSE),0.25) | T98: =IF(O98="A",MAX(1,IFERROR(VLOOKUP(O98,Assumptions!$A$7:$F$11,3,FALSE),3)+IFERROR(VLOOKUP(O98,Assumptions!$A$7:$F$11,4,FALSE),8)/2-MAX(0,IF(R98="",0,R98)-IFERROR(VLOOKUP(O98,Assumptions!$A$7:$F$11,5,FALSE),1.5))),IFERROR(VLOOKUP(O98,Assumptions!$A$7:$F$11,5,FALSE),2.5)+IFERROR(VLOOKUP(O98,Assumptions!$A$7:$F$11,3,FALSE),3)+IFERROR(VLOOKUP(O98,Assumptions!$A$7:$F$11,4,FALSE),8)/2) | U98: =M98*S98/(1+Assumptions!$B$3)^T98 | V98: =IF(M98=0,"",ROUND(U98/M98*100,1)) | W98: =U98*Assumptions!$B$4 | X98: =IF(M98=0,"",ROUND(W98/M98*100,1)) | Y98: CREDIMÓVEIS NOVOLAR LTDA. | Z98: 0007565-40.2020.8.17.2370 | AA98: TJPE | AB98: recuperacaojudicial.squarespace.com | AC98: ALEXANDRE MACEDO DIAS | AD98: Administrador | AE98: (81) 2128-5000 | AH98: PE | AI98: OLINDA | AJ98: Fabricação de colchões | AK98: DEMAIS | AL98: ATIVA | AM98: https://recuperacaojudicial.squarespace.com/s/RJ-Credimoveis-QGC-01082025.pdf | AN98: p16 r36 | AO98: p16: R$ 1.902.217,38 | AP98: QGC | AQ98: 2026-01-28 | AR98: OK | AS98: ROWS:p16r36 | AT98: 849d4fe5adce
A99: 98 | B99: NEW | D99: 0 | I99: BECK ACOS MANUFATURADOS LTDA | J99: Beck Aços Manufaturados Ltda | K99: 07651282 | L99: 07651282000136 | M99: 1886828.7 | N99: 1 | O99: B | Q99: 45756 | R99: =IF(Q99="","",ROUND((TODAY()-Q99)/365.25,1)) | S99: =IFERROR(VLOOKUP(O99,Assumptions!$A$7:$F$11,2,FALSE),0.25) | T99: =IF(O99="A",MAX(1,IFERROR(VLOOKUP(O99,Assumptions!$A$7:$F$11,3,FALSE),3)+IFERROR(VLOOKUP(O99,Assumptions!$A$7:$F$11,4,FALSE),8)/2-MAX(0,IF(R99="",0,R99)-IFERROR(VLOOKUP(O99,Assumptions!$A$7:$F$11,5,FALSE),1.5))),IFERROR(VLOOKUP(O99,Assumptions!$A$7:$F$11,5,FALSE),2.5)+IFERROR(VLOOKUP(O99,Assumptions!$A$7:$F$11,3,FALSE),3)+IFERROR(VLOOKUP(O99,Assumptions!$A$7:$F$11,4,FALSE),8)/2) | U99: =M99*S99/(1+Assumptions!$B$3)^T99 | V99: =IF(M99=0,"",ROUND(U99/M99*100,1)) | W99: =U99*Assumptions!$B$4 | X99: =IF(M99=0,"",ROUND(W99/M99*100,1)) | Y99: GRUPO EGESA (EGESA ENG S.A, EGESUR PART E EMP S.A, MATRIX INFRA LTDA, BEMVIVER ENG AMBIENTAL E SERV LTDA, DKF CONST E EMP LTDA, EGEPEL LTDA, ETR ASSESSORIA EMP E PART LTDA, MVT ENG E SERV LTDA, PARQUES DO VALE LTDA, ELMO RIBEIRO E ANA RIBEIRO) | Z99: 5088952-81.2025.8.13.0024 | AA99: TJMG | AB99: scalzilliaj.com.br | AC99: JOSE MAURICIO COSTA DE ALMEIDA | AD99: Sócio-Administrador | AE99: (31) 8896-6044 | AF99: (31) 8896-7549 | AH99: MG | AI99: VESPASIANO | AJ99: Fabricação de estruturas metálicas | AK99: DEMAIS | AL99: ATIVA | AM99: https://scalzilliaj.com.br/sgc/download.php?file=files/processo_documento/processo_documento09514021082025_1_.pdf&nome=04 - Relação de credores das Recuperandas | AN99: p63 r7 | AO99: p63: R$ 1.886.828,69 | AP99: DEBTOR_LIST | AR99: OK | AS99: ROWS:p63r7 VALUE_COL:Valor_Atualizado CASE_NUMBER_CORRECTED CASE_FROM_PORTAL | AT99: 24ed98480a57
A100: 99 | B100: NEW | D100: 0 | I100: SOCIEDADE ESPORTIVA PALMEIRAS | J100: SOCIEDADE ESPORTIVA PALMEIRAS, CPF/CNPJ Nº | K100: 61750345 | L100: 61750345000157 | M100: 1867912.2 | N100: 1 | O100: C | P100: ACTIVE | Q100: 44966 | R100: =IF(Q100="","",ROUND((TODAY()-Q100)/365.25,1)) | S100: =IFERROR(VLOOKUP(O100,Assumptions!$A$7:$F$11,2,FALSE),0.25) | T100: =IF(O100="A",MAX(1,IFERROR(VLOOKUP(O100,Assumptions!$A$7:$F$11,3,FALSE),3)+IFERROR(VLOOKUP(O100,Assumptions!$A$7:$F$11,4,FALSE),8)/2-MAX(0,IF(R100="",0,R100)-IFERROR(VLOOKUP(O100,Assumptions!$A$7:$F$11,5,FALSE),1.5))),IFERROR(VLOOKUP(O100,Assumptions!$A$7:$F$11,5,FALSE),2.5)+IFERROR(VLOOKUP(O100,Assumptions!$A$7:$F$11,3,FALSE),3)+IFERROR(VLOOKUP(O100,Assumptions!$A$7:$F$11,4,FALSE),8)/2) | U100: =M100*S100/(1+Assumptions!$B$3)^T100 | V100: =IF(M100=0,"",ROUND(U100/M100*100,1)) | W100: =U100*Assumptions!$B$4 | X100: =IF(M100=0,"",ROUND(W100/M100*100,1)) | Y100: CLUBE NÁUTICO CAPIBARIBE | Z100: 0011283-80.2023.8.17.2001 | AA100: TJPE | AB100: lrflideres.com.br | AC100: LEILA MEJDALANI PEREIRA | AD100: Presidente | AE100: (11) 3874-6500 | AF100: (11) 3679-7859 | AH100: SP | AI100: SAO PAULO | AJ100: Clubes sociais, esportivos e similares | AK100: DEMAIS | AL100: ATIVA | AM100: https://lrflideres.com.br/wp-content/plugins/download-attachments/includes/download.php?id=5589 | AN100: p12 r43 | AO100: p12: R$ 1.867.912,24 | AP100: AJ_LIST | AQ100: 2023-11-27 | AR100: QUARANTINED | AS100: PARTIAL_DOC_CLASS_III_RECONCILED ROWS:p12r43 | AT100: 677be5783c06
...

Sheet Pooling (100-200k)
A1: Rank | B1: Status | C1: Owner | D1: Attempts | E1: Last touch | F1: Next action | G1: Next date | H1: Notes | I1: Company (RFB) | J1: Name as printed | K1: CNPJ root | L1: Establishment CNPJs | M1: Class III face (R$) | N1: Claims | O1: Debtor band | P1: Stage | Q1: Case filed | R1: Years since filing | S1: Est. recovery % | T1: Years to payment (est.) | U1: Fund price @ IRR (R$) | V1: Fund price (cents) | W1: OUR QUOTE (R$) | X1: Quote (cents) | Y1: Debtor | Z1: Case number | AA1: Court | AB1: Administrator (site) | AC1: Decision-maker | AD1: Role | AE1: Phone | AF1: Phone 2 | AG1: Email | AH1: UF | AI1: City | AJ1: CNAE | AK1: Porte | AL1: Situação | AM1: PROOF: source document | AN1: Page / row | AO1: Value as printed | AP1: Which list | AQ1: Published | AR1: Reconciled | AS1: Data flags | AT1: Doc id
A2: 1 | B2: NEW | D2: 0 | I2: PRO SHOWS COMERCIO DE ELETRO ELETRONICOS S.A. | J2: Rodovia BR 101, nº 9.555, Setor C3, Cidade Nova, CEP nº 88.308-620, Itajaí/SC | K2: 06007513 | L2: 06007513000453 | M2: 199819.8 | N2: 2 | O2: B | P2: ACTIVE | Q2: 45644 | R2: =IF(Q2="","",ROUND((TODAY()-Q2)/365.25,1)) | S2: =IFERROR(VLOOKUP(O2,Assumptions!$A$7:$F$11,2,FALSE),0.25) | T2: =IF(O2="A",MAX(1,IFERROR(VLOOKUP(O2,Assumptions!$A$7:$F$11,3,FALSE),3)+IFERROR(VLOOKUP(O2,Assumptions!$A$7:$F$11,4,FALSE),8)/2-MAX(0,IF(R2="",0,R2)-IFERROR(VLOOKUP(O2,Assumptions!$A$7:$F$11,5,FALSE),1.5))),IFERROR(VLOOKUP(O2,Assumptions!$A$7:$F$11,5,FALSE),2.5)+IFERROR(VLOOKUP(O2,Assumptions!$A$7:$F$11,3,FALSE),3)+IFERROR(VLOOKUP(O2,Assumptions!$A$7:$F$11,4,FALSE),8)/2) | U2: =M2*S2/(1+Assumptions!$B$3)^T2 | V2: =IF(M2=0,"",ROUND(U2/M2*100,1)) | W2: =U2*Assumptions!$B$4 | X2: =IF(M2=0,"",ROUND(W2/M2*100,1)) | Y2: GRUPO RIVER MUSIC | Z2: 1001174-80.2024.8.26.0359 | AA2: TJSP | AB2: ativosajce.com.br | AC2: VLADIMIR DE SOUZA | AD2: Diretor | AE2: (51) 3034-8100 | AH2: RS | AI2: CANOAS | AJ2: Comércio atacadista de aparelhos eletrônicos de uso pessoal e doméstico | AK2: DEMAIS | AL2: ATIVA | AM2: https://ativosajce.com.br/admin/download.php?file=files/processo_documento/processo_documento18543908052025_1_.pdf&nome=Relação de Credores - art. 52, §1º da Lei 11.101/05 - 27/01/2025 | AN2: p3 r9; p3 r24 | AO2: p3: R$ 13.044,12; p3: R$ 186.775,68 | AP2: UNKNOWN | AR2: OK_NO_TOTALS | AS2: ROWS:p3r9,p3r24 UNRECONCILED_SOURCE VALUE_COL:Valor_Do_Créidto | AT2: 442539f948e0
A3: 2 | B3: NEW | D3: 0 | I3: VOTORANTIM CIMENTOS S.A. | J3: RUA ANTÔNIO LUCHIARI QUADRA7463 LOTE 003 C1-D1 1 DISTRITO INDUSTRIAL 13054700 | K3: 01637895 | L3: 01637895000728, 01637895001023, 01637895002852, 01637895008893, 01637895012300, 01637895015830, 01637895024074 | M3: 199439.99 | N3: 7 | O3: B | P3: ACTIVE | Q3: 45964 | R3: =IF(Q3="","",ROUND((TODAY()-Q3)/365.25,1)) | S3: =IFERROR(VLOOKUP(O3,Assumptions!$A$7:$F$11,2,FALSE),0.25) | T3: =IF(O3="A",MAX(1,IFERROR(VLOOKUP(O3,Assumptions!$A$7:$F$11,3,FALSE),3)+IFERROR(VLOOKUP(O3,Assumptions!$A$7:$F$11,4,FALSE),8)/2-MAX(0,IF(R3="",0,R3)-IFERROR(VLOOKUP(O3,Assumptions!$A$7:$F$11,5,FALSE),1.5))),IFERROR(VLOOKUP(O3,Assumptions!$A$7:$F$11,5,FALSE),2.5)+IFERROR(VLOOKUP(O3,Assumptions!$A$7:$F$11,3,FALSE),3)+IFERROR(VLOOKUP(O3,Assumptions!$A$7:$F$11,4,FALSE),8)/2) | U3: =M3*S3/(1+Assumptions!$B$3)^T3 | V3: =IF(M3=0,"",ROUND(U3/M3*100,1)) | W3: =U3*Assumptions!$B$4 | X3: =IF(M3=0,"",ROUND(W3/M3*100,1)) | Y3: CENTURY CONSTRUÇÕES COMÉRCIO E SERVIÇOS LTDA. | Z3: 4054599-35.2025.8.26.0100 | AA3: TJSP | AB3: ativosajce.com.br | AC3: OSVALDO AYRES FILHO | AD3: Presidente | AE3: (41) 3388-5292 | AH3: SP | AI3: SAO PAULO | AJ3: Fabricação de cimento | AK3: DEMAIS | AL3: ATIVA | AM3: https://ativosajce.com.br/admin/download.php?file=files/processo_documento/processo_documento16022716122025_1_.pdf&nome=Relação de credores - art. 52, §1º da Lei 11.101/05 - 15/12/2025 | AN3: p4 r73; p4 r74; p4 r75; p4 r76; p4 r77; p4 r78; p4 r79 | AO3: p4: R$ 111.357,19; p4: R$ 38.068,00; p4: R$ 19.069,20; p4: R$ 12.099,20; p4: R$ 9.304,40; p4: R$ 8.372,00; p4: R$ 1.170,00 | AP3: UNKNOWN | AR3: OK_NO_TOTALS | AS3: ROWS:p4r73,p4r74,p4r75,p4r76,p4r77,p4r78,p4r79 UNRECONCILED_SOURCE | AT3: 2fe04bf4466d
A4: 3 | B4: NEW | D4: 0 | I4: AUSTEX INDUSTRIA E COMERCIO LTDA | J4: AUSTEX IND E COM LTDA | K4: 53359089 | L4: 53359089000143 | M4: 199383.61 | N4: 1 | O4: D | R4: =IF(Q4="","",ROUND((TODAY()-Q4)/365.25,1)) | S4: =IFERROR(VLOOKUP(O4,Assumptions!$A$7:$F$11,2,FALSE),0.25) | T4: =IF(O4="A",MAX(1,IFERROR(VLOOKUP(O4,Assumptions!$A$7:$F$11,3,FALSE),3)+IFERROR(VLOOKUP(O4,Assumptions!$A$7:$F$11,4,FALSE),8)/2-MAX(0,IF(R4="",0,R4)-IFERROR(VLOOKUP(O4,Assumptions!$A$7:$F$11,5,FALSE),1.5))),IFERROR(VLOOKUP(O4,Assumptions!$A$7:$F$11,5,FALSE),2.5)+IFERROR(VLOOKUP(O4,Assumptions!$A$7:$F$11,3,FALSE),3)+IFERROR(VLOOKUP(O4,Assumptions!$A$7:$F$11,4,FALSE),8)/2) | U4: =M4*S4/(1+Assumptions!$B$3)^T4 | V4: =IF(M4=0,"",ROUND(U4/M4*100,1)) | W4: =U4*Assumptions!$B$4 | X4: =IF(M4=0,"",ROUND(W4/M4*100,1)) | Y4: Mannes | Z4: 0005010-50.2013.8.24.0026 | AB4: administradorajudicialgs.com.br | AC4: HARRY MIKLAUTZ | AD4: Sócio-Administrador | AE4: (11) 2167-2112 | AH4: SP | AI4: SAO PAULO | AJ4: Fabricação de tecidos especiais, inclusive artefatos | AK4: DEMAIS | AL4: ATIVA | AM4: https://administradorajudicialgs.com.br/wp-content/uploads/2024/12/relacao-de-credores-da-falida.pdf | AN4: p13 r1 | AO4: p13: R$ 199.383,61 | AP4: OTHER | AQ4: 2025-03-25 | AR4: OK_NO_TOTALS | AS4: ROWS:p13r1 UNRECONCILED_SOURCE CASE_NUMBER_CORRECTED | AT4: ea17ba43b261
A5: 4 | B5: NEW | D5: 0 | I5: BRITANIA ELETRONICOS S.A. | J5: 07.019.308/0001-28 | K5: 07019308 | L5: 07019308000128 | M5: 199134.45 | N5: 1 | O5: C | P5: ACTIVE | Q5: 43894 | R5: =IF(Q5="","",ROUND((TODAY()-Q5)/365.25,1)) | S5: =IFERROR(VLOOKUP(O5,Assumptions!$A$7:$F$11,2,FALSE),0.25) | T5: =IF(O5="A",MAX(1,IFERROR(VLOOKUP(O5,Assumptions!$A$7:$F$11,3,FALSE),3)+IFERROR(VLOOKUP(O5,Assumptions!$A$7:$F$11,4,FALSE),8)/2-MAX(0,IF(R5="",0,R5)-IFERROR(VLOOKUP(O5,Assumptions!$A$7:$F$11,5,FALSE),1.5))),IFERROR(VLOOKUP(O5,Assumptions!$A$7:$F$11,5,FALSE),2.5)+IFERROR(VLOOKUP(O5,Assumptions!$A$7:$F$11,3,FALSE),3)+IFERROR(VLOOKUP(O5,Assumptions!$A$7:$F$11,4,FALSE),8)/2) | U5: =M5*S5/(1+Assumptions!$B$3)^T5 | V5: =IF(M5=0,"",ROUND(U5/M5*100,1)) | W5: =U5*Assumptions!$B$4 | X5: =IF(M5=0,"",ROUND(W5/M5*100,1)) | Y5: CREDIMÓVEIS NOVOLAR LTDA. | Z5: 0007565-40.2020.8.17.2370 | AA5: TJPE | AB5: recuperacaojudicial.squarespace.com | AC5: CESAR EDUARDO ISAACSON BUFFARA | AD5: Presidente | AE5: (41) 3218-7700 | AH5: SC | AI5: JOINVILLE | AJ5: Comércio atacadista de aparelhos eletrônicos de uso pessoal e doméstico | AK5: DEMAIS | AL5: ATIVA | AM5: https://recuperacaojudicial.squarespace.com/s/RJ-Credimoveis-QGC-01082025.pdf | AN5: p15 r23 | AO5: p15: R$ 199.134,45 | AP5: QGC | AQ5: 2026-01-28 | AR5: OK | AS5: ROWS:p15r23 | AT5: 849d4fe5adce
A6: 5 | B6: NEW | D6: 0 | I6: SEARA ALIMENTOS LTDA | J6: Seara Alimentos Ltda | K6: 02914460 | L6: 02914460058230 | M6: 198390 | N6: 1 | O6: C | P6: ACTIVE | Q6: 45275 | R6: =IF(Q6="","",ROUND((TODAY()-Q6)/365.25,1)) | S6: =IFERROR(VLOOKUP(O6,Assumptions!$A$7:$F$11,2,FALSE),0.25) | T6: =IF(O6="A",MAX(1,IFERROR(VLOOKUP(O6,Assumptions!$A$7:$F$11,3,FALSE),3)+IFERROR(VLOOKUP(O6,Assumptions!$A$7:$F$11,4,FALSE),8)/2-MAX(0,IF(R6="",0,R6)-IFERROR(VLOOKUP(O6,Assumptions!$A$7:$F$11,5,FALSE),1.5))),IFERROR(VLOOKUP(O6,Assumptions!$A$7:$F$11,5,FALSE),2.5)+IFERROR(VLOOKUP(O6,Assumptions!$A$7:$F$11,3,FALSE),3)+IFERROR(VLOOKUP(O6,Assumptions!$A$7:$F$11,4,FALSE),8)/2) | U6: =M6*S6/(1+Assumptions!$B$3)^T6 | V6: =IF(M6=0,"",ROUND(U6/M6*100,1)) | W6: =U6*Assumptions!$B$4 | X6: =IF(M6=0,"",ROUND(W6/M6*100,1)) | Y6: Grupo Agromeal | Z6: 0003971-03.2023.8.16.0119 | AA6: TJPR | AB6: marquesadmjudicial.com.br | AC6: ELISEO SANTIAGO PEREZ FERNANDEZ | AD6: Administrador | AE6: (47) 3344-7424 | AH6: SC | AI6: ITAJAI | AJ6: Comércio atacadista de carnes bovinas e suínas e derivados | AK6: DEMAIS | AL6: ATIVA | AM6: https://marquesadmjudicial.com.br/sgc/download.php?file=files/processo_documento/processo_documento17040729052024_1_.pdf&nome=Relação Nominal de Credores AJ-Sintética | AN6: p13 r3 | AO6: p13: R$ 198.390,00 | AP6: AJ_LIST | AQ6: 2024-05-27 | AR6: QUARANTINED | AS6: PARTIAL_DOC_CLASS_III_RECONCILED ROWS:p13r3 | AT6: 1209dafe77b7
A7: 6 | B7: NEW | D7: 0 | I7: FUNDO DE PROMOCOES COLETIVAS DO MARINGA PARK SHOPPING CENTER | J7: Fundo de Promoções Coletivas do Maringá Park Shopping Center | K7: 01249612 | L7: 01249612000185 | M7: 198105.81 | N7: 1 | O7: B | P7: ACTIVE | Q7: 45833 | R7: =IF(Q7="","",ROUND((TODAY()-Q7)/365.25,1)) | S7: =IFERROR(VLOOKUP(O7,Assumptions!$A$7:$F$11,2,FALSE),0.25) | T7: =IF(O7="A",MAX(1,IFERROR(VLOOKUP(O7,Assumptions!$A$7:$F$11,3,FALSE),3)+IFERROR(VLOOKUP(O7,Assumptions!$A$7:$F$11,4,FALSE),8)/2-MAX(0,IF(R7="",0,R7)-IFERROR(VLOOKUP(O7,Assumptions!$A$7:$F$11,5,FALSE),1.5))),IFERROR(VLOOKUP(O7,Assumptions!$A$7:$F$11,5,FALSE),2.5)+IFERROR(VLOOKUP(O7,Assumptions!$A$7:$F$11,3,FALSE),3)+IFERROR(VLOOKUP(O7,Assumptions!$A$7:$F$11,4,FALSE),8)/2) | U7: =M7*S7/(1+Assumptions!$B$3)^T7 | V7: =IF(M7=0,"",ROUND(U7/M7*100,1)) | W7: =U7*Assumptions!$B$4 | X7: =IF(M7=0,"",ROUND(W7/M7*100,1)) | Y7: GRUPO MARINGÁ PARK | Z7: 0016033-22.2025.8.16.0017 | AA7: TJPR | AB7: marquesadmjudicial.com.br | AC7: JOAO BATISTA FERREIRA | AD7: Administrador | AH7: PR | AI7: MARINGA | AJ7: Atividades de associações de defesa de direitos sociais | AK7: DEMAIS | AL7: ATIVA | AM7: https://marquesadmjudicial.com.br/sgc/download.php?file=files/processo_documento/processo_documento19270817122025_1_.pdf&nome=Relação Nominal de Credores AJ | AN7: p4 r10 | AO7: p4: R$ 198.105,81 | AP7: AJ_LIST | AQ7: 2025-12-17 | AR7: OK | AS7: ROWS:p4r10 | AT7: fcb10a251582
A8: 7 | B8: NEW | D8: 0 | I8: MAQENGE - INDUSTRIA METALURGICA LTDA | J8: MAQENGE IND METALURGICA LTDA ( | K8: 05000896 | L8: 05000896000122 | M8: 197970.43 | N8: 1 | O8: C | P8: ACTIVE | Q8: 44354 | R8: =IF(Q8="","",ROUND((TODAY()-Q8)/365.25,1)) | S8: =IFERROR(VLOOKUP(O8,Assumptions!$A$7:$F$11,2,FALSE),0.25) | T8: =IF(O8="A",MAX(1,IFERROR(VLOOKUP(O8,Assumptions!$A$7:$F$11,3,FALSE),3)+IFERROR(VLOOKUP(O8,Assumptions!$A$7:$F$11,4,FALSE),8)/2-MAX(0,IF(R8="",0,R8)-IFERROR(VLOOKUP(O8,Assumptions!$A$7:$F$11,5,FALSE),1.5))),IFERROR(VLOOKUP(O8,Assumptions!$A$7:$F$11,5,FALSE),2.5)+IFERROR(VLOOKUP(O8,Assumptions!$A$7:$F$11,3,FALSE),3)+IFERROR(VLOOKUP(O8,Assumptions!$A$7:$F$11,4,FALSE),8)/2) | U8: =M8*S8/(1+Assumptions!$B$3)^T8 | V8: =IF(M8=0,"",ROUND(U8/M8*100,1)) | W8: =U8*Assumptions!$B$4 | X8: =IF(M8=0,"",ROUND(W8/M8*100,1)) | Y8: VECTOR INDÚSTRIA DE PRODUTOS METALÚRGICOS LTDA. | Z8: 5014104-85.2021.8.21.0010 | AA8: TJRS | AB8: scalzilliaj.com.br | AC8: JOSE LUIZ ZECHIN | AD8: Administrador | AE8: (54) 3535-3050 | AF8: (54) 3535-3061 | AH8: RS | AI8: CAXIAS DO SUL | AJ8: Fabricação de outras máquinas e equipamentos de uso geral não especificados anteriormente, peças e acessórios | AK8: DEMAIS | AL8: ATIVA | AM8: https://scalzilliaj.com.br/sgc/download.php?file=files/processo_documento/processo_documento15513401112022_1_.pdf&nome=15 - Edital do art. 7º, §2º (segunda lista de credores) e do art. 53 da Lei 11.101/2005 (recebimento do plano) | AN8: p8 r13 | AO8: p8: R$ 197.970,43 | AP8: AJ_LIST | AQ8: 2022-11-01 | AR8: OK_NO_TOTALS | AS8: ROWS:p8r13 UNRECONCILED_SOURCE | AT8: 84c586360a66
A9: 8 | B9: NEW | D9: 0 | I9: SOMAVE AGROINDUSTRIAL LTDA | J9: Somave Agroindustrial Ltda | K9: 06353241 | L9: 06353241000109 | M9: 197876 | N9: 1 | O9: C | P9: ACTIVE | Q9: 45275 | R9: =IF(Q9="","",ROUND((TODAY()-Q9)/365.25,1)) | S9: =IFERROR(VLOOKUP(O9,Assumptions!$A$7:$F$11,2,FALSE),0.25) | T9: =IF(O9="A",MAX(1,IFERROR(VLOOKUP(O9,Assumptions!$A$7:$F$11,3,FALSE),3)+IFERROR(VLOOKUP(O9,Assumptions!$A$7:$F$11,4,FALSE),8)/2-MAX(0,IF(R9="",0,R9)-IFERROR(VLOOKUP(O9,Assumptions!$A$7:$F$11,5,FALSE),1.5))),IFERROR(VLOOKUP(O9,Assumptions!$A$7:$F$11,5,FALSE),2.5)+IFERROR(VLOOKUP(O9,Assumptions!$A$7:$F$11,3,FALSE),3)+IFERROR(VLOOKUP(O9,Assumptions!$A$7:$F$11,4,FALSE),8)/2) | U9: =M9*S9/(1+Assumptions!$B$3)^T9 | V9: =IF(M9=0,"",ROUND(U9/M9*100,1)) | W9: =U9*Assumptions!$B$4 | X9: =IF(M9=0,"",ROUND(W9/M9*100,1)) | Y9: Grupo Agromeal | Z9: 0003971-03.2023.8.16.0119 | AA9: TJPR | AB9: marquesadmjudicial.com.br | AC9: ADEMIR PAULINO FERRARINI | AD9: Sócio-Administrador | AE9: (44) 3675-5000 | AH9: PR | AI9: CIDADE GAUCHA | AJ9: Abate de aves | AK9: DEMAIS | AL9: ATIVA | AM9: https://marquesadmjudicial.com.br/sgc/download.php?file=files/processo_documento/processo_documento17040729052024_1_.pdf&nome=Relação Nominal de Credores AJ-Sintética | AN9: p13 r6 | AO9: p13: R$ 197.876,00 | AP9: AJ_LIST | AQ9: 2024-05-27 | AR9: QUARANTINED | AS9: PARTIAL_DOC_CLASS_III_RECONCILED ROWS:p13r6 | AT9: 1209dafe77b7
A10: 9 | B10: NEW | D10: 0 | I10: SPORT CLUBE URBANISMO LTDA | J10: Alcar Techology In Business SC LTDA | K10: 05119723 | L10: 05119723000128 | M10: 197081.92 | N10: 1 | O10: B | Q10: 45756 | R10: =IF(Q10="","",ROUND((TODAY()-Q10)/365.25,1)) | S10: =IFERROR(VLOOKUP(O10,Assumptions!$A$7:$F$11,2,FALSE),0.25) | T10: =IF(O10="A",MAX(1,IFERROR(VLOOKUP(O10,Assumptions!$A$7:$F$11,3,FALSE),3)+IFERROR(VLOOKUP(O10,Assumptions!$A$7:$F$11,4,FALSE),8)/2-MAX(0,IF(R10="",0,R10)-IFERROR(VLOOKUP(O10,Assumptions!$A$7:$F$11,5,FALSE),1.5))),IFERROR(VLOOKUP(O10,Assumptions!$A$7:$F$11,5,FALSE),2.5)+IFERROR(VLOOKUP(O10,Assumptions!$A$7:$F$11,3,FALSE),3)+IFERROR(VLOOKUP(O10,Assumptions!$A$7:$F$11,4,FALSE),8)/2) | U10: =M10*S10/(1+Assumptions!$B$3)^T10 | V10: =IF(M10=0,"",ROUND(U10/M10*100,1)) | W10: =U10*Assumptions!$B$4 | X10: =IF(M10=0,"",ROUND(W10/M10*100,1)) | Y10: GRUPO EGESA (EGESA ENG S.A, EGESUR PART E EMP S.A, MATRIX INFRA LTDA, BEMVIVER ENG AMBIENTAL E SERV LTDA, DKF CONST E EMP LTDA, EGEPEL LTDA, ETR ASSESSORIA EMP E PART LTDA, MVT ENG E SERV LTDA, PARQUES DO VALE LTDA, ELMO RIBEIRO E ANA RIBEIRO) | Z10: 5088952-81.2025.8.13.0024 | AA10: TJMG | AB10: scalzilliaj.com.br | AC10: KAMILLA ALEXANDRE FERNANDES BARRETO | AD10: Administrador | AE10: (84) 3015-7888 | AH10: RN | AI10: EXTREMOZ | AJ10: Construção de edifícios | AK10: DEMAIS | AL10: ATIVA | AM10: https://scalzilliaj.com.br/sgc/download.php?file=files/processo_documento/processo_documento09514021082025_1_.pdf&nome=04 - Relação de credores das Recuperandas | AN10: p61 r15 | AO10: p61: R$ 197.081,92 | AP10: DEBTOR_LIST | AR10: OK | AS10: ROWS:p61r15 VALUE_COL:Valor_Atualizado CASE_NUMBER_CORRECTED CASE_FROM_PORTAL | AT10: 24ed98480a57
A11: 10 | B11: NEW | D11: 0 | I11: URBANO AGROINDUSTRIAL LTDA | J11: Urbano Agroindustrial Ltda | K11: 84432111 | L11: 84432111002100 | M11: 197064.84 | N11: 1 | O11: B | P11: ACTIVE | Q11: 46130 | R11: =IF(Q11="","",ROUND((TODAY()-Q11)/365.25,1)) | S11: =IFERROR(VLOOKUP(O11,Assumptions!$A$7:$F$11,2,FALSE),0.25) | T11: =IF(O11="A",MAX(1,IFERROR(VLOOKUP(O11,Assumptions!$A$7:$F$11,3,FALSE),3)+IFERROR(VLOOKUP(O11,Assumptions!$A$7:$F$11,4,FALSE),8)/2-MAX(0,IF(R11="",0,R11)-IFERROR(VLOOKUP(O11,Assumptions!$A$7:$F$11,5,FALSE),1.5))),IFERROR(VLOOKUP(O11,Assumptions!$A$7:$F$11,5,FALSE),2.5)+IFERROR(VLOOKUP(O11,Assumptions!$A$7:$F$11,3,FALSE),3)+IFERROR(VLOOKUP(O11,Assumptions!$A$7:$F$11,4,FALSE),8)/2) | U11: =M11*S11/(1+Assumptions!$B$3)^T11 | V11: =IF(M11=0,"",ROUND(U11/M11*100,1)) | W11: =U11*Assumptions!$B$4 | X11: =IF(M11=0,"",ROUND(W11/M11*100,1)) | Y11: GRUPO 3E | Z11: 5341375-33.2026.8.09.0049 | AA11: TJGO | AB11: stenius.com.br | AC11: ADENOR FRANZNER | AD11: Administrador | AE11: (47) 3372-7503 | AF11: (47) 3372-7500 | AH11: SC | AI11: JARAGUA DO SUL | AJ11: Beneficiamento de arroz | AK11: DEMAIS | AL11: ATIVA | AM11: https://stenius.com.br/wp-content/uploads/2026/06/EDITAL-GRUPO-3E.pdf | AN11: p18 r56 | AO11: p18: R$ 197.064,84 | AP11: DEBTOR_LIST | AQ11: 2026-06-22 | AR11: OK_NO_TOTALS | AS11: ROWS:p18r56 UNRECONCILED_SOURCE | AT11: 8e8832093a15
A12: 11 | B12: NEW | D12: 0 | I12: NEWMAQ ELETRODOMESTICOS LTDA | J12: 05.382.997/0001-05 | K12: 05382997 | L12: 05382997000105 | M12: 196076.08 | N12: 1 | O12: C | P12: ACTIVE | Q12: 43894 | R12: =IF(Q12="","",ROUND((TODAY()-Q12)/365.25,1)) | S12: =IFERROR(VLOOKUP(O12,Assumptions!$A$7:$F$11,2,FALSE),0.25) | T12: =IF(O12="A",MAX(1,IFERROR(VLOOKUP(O12,Assumptions!$A$7:$F$11,3,FALSE),3)+IFERROR(VLOOKUP(O12,Assumptions!$A$7:$F$11,4,FALSE),8)/2-MAX(0,IF(R12="",0,R12)-IFERROR(VLOOKUP(O12,Assumptions!$A$7:$F$11,5,FALSE),1.5))),IFERROR(VLOOKUP(O12,Assumptions!$A$7:$F$11,5,FALSE),2.5)+IFERROR(VLOOKUP(O12,Assumptions!$A$7:$F$11,3,FALSE),3)+IFERROR(VLOOKUP(O12,Assumptions!$A$7:$F$11,4,FALSE),8)/2) | U12: =M12*S12/(1+Assumptions!$B$3)^T12 | V12: =IF(M12=0,"",ROUND(U12/M12*100,1)) | W12: =U12*Assumptions!$B$4 | X12: =IF(M12=0,"",ROUND(W12/M12*100,1)) | Y12: CREDIMÓVEIS NOVOLAR LTDA. | Z12: 0007565-40.2020.8.17.2370 | AA12: TJPE | AB12: recuperacaojudicial.squarespace.com | AC12: JOSE RENATO PINHEIRO | AD12: Administrador | AE12: (19) 3113-1100 | AH12: SP | AI12: LIMEIRA | AJ12: Fabricação de fogões, refrigeradores e máquinas de lavar e secar para uso doméstico, peças e acessórios | AK12: DEMAIS | AL12: ATIVA | AM12: https://recuperacaojudicial.squarespace.com/s/RJ-Credimoveis-QGC-01082025.pdf | AN12: p16 r32 | AO12: p16: R$ 196.076,08 | AP12: QGC | AQ12: 2026-01-28 | AR12: OK | AS12: ROWS:p16r32 | AT12: 849d4fe5adce
A13: 12 | B13: NEW | D13: 0 | I13: FOZBRASIL COMERCIO IMPORTACAO E EXPORTACAO LTDA | J13: 06957870000130 | K13: 06957870 | L13: 06957870000130 | M13: 195852.64 | N13: 1 | O13: C | P13: ACTIVE | Q13: 45057 | R13: =IF(Q13="","",ROUND((TODAY()-Q13)/365.25,1)) | S13: =IFERROR(VLOOKUP(O13,Assumptions!$A$7:$F$11,2,FALSE),0.25) | T13: =IF(O13="A",MAX(1,IFERROR(VLOOKUP(O13,Assumptions!$A$7:$F$11,3,FALSE),3)+IFERROR(VLOOKUP(O13,Assumptions!$A$7:$F$11,4,FALSE),8)/2-MAX(0,IF(R13="",0,R13)-IFERROR(VLOOKUP(O13,Assumptions!$A$7:$F$11,5,FALSE),1.5))),IFERROR(VLOOKUP(O13,Assumptions!$A$7:$F$11,5,FALSE),2.5)+IFERROR(VLOOKUP(O13,Assumptions!$A$7:$F$11,3,FALSE),3)+IFERROR(VLOOKUP(O13,Assumptions!$A$7:$F$11,4,FALSE),8)/2) | U13: =M13*S13/(1+Assumptions!$B$3)^T13 | V13: =IF(M13=0,"",ROUND(U13/M13*100,1)) | W13: =U13*Assumptions!$B$4 | X13: =IF(M13=0,"",ROUND(W13/M13*100,1)) | Y13: TOP TEXTIL EMBALAGENS LTDA | Z13: 5011460-87.2023.8.24.0020 | AA13: TJSC | AB13: cataliseaj.com.br | AC13: NEREO PALUDO | AD13: Sócio-Administrador | AE13: (45) 3027-6122 | AH13: PR | AI13: FOZ DO IGUACU | AJ13: Comércio atacadista de cereais e leguminosas beneficiados, farinhas, amidos e féculas, com atividade de fracionamento e acondicionamento associada | AK13: DEMAIS | AL13: ATIVA | AM13: https://cataliseaj.com.br/sgc/download.php?file=files/processo_documento/processo_documento15092204102024_1_.pdf&nome=02. RELAÇÃO DE CREDORES | AN13: p2 r44 | AO13: p2: R$ 195.852,64 | AP13: DEBTOR_LIST | AR13: OK_NO_TOTALS | AS13: ROWS:p2r44 UNRECONCILED_SOURCE | AT13: 741aed48dd00
A14: 13 | B14: NEW | D14: 0 | I14: CL BRASIL ALIMENTOS LTDA | J14: Supermercado Brasil 400 | K14: 40693000 | L14: 40693000000139, 40693000000210 | M14: 194891.25 | N14: 2 | O14: B | P14: ACTIVE | Q14: 46130 | R14: =IF(Q14="","",ROUND((TODAY()-Q14)/365.25,1)) | S14: =IFERROR(VLOOKUP(O14,Assumptions!$A$7:$F$11,2,FALSE),0.25) | T14: =IF(O14="A",MAX(1,IFERROR(VLOOKUP(O14,Assumptions!$A$7:$F$11,3,FALSE),3)+IFERROR(VLOOKUP(O14,Assumptions!$A$7:$F$11,4,FALSE),8)/2-MAX(0,IF(R14="",0,R14)-IFERROR(VLOOKUP(O14,Assumptions!$A$7:$F$11,5,FALSE),1.5))),IFERROR(VLOOKUP(O14,Assumptions!$A$7:$F$11,5,FALSE),2.5)+IFERROR(VLOOKUP(O14,Assumptions!$A$7:$F$11,3,FALSE),3)+IFERROR(VLOOKUP(O14,Assumptions!$A$7:$F$11,4,FALSE),8)/2) | U14: =M14*S14/(1+Assumptions!$B$3)^T14 | V14: =IF(M14=0,"",ROUND(U14/M14*100,1)) | W14: =U14*Assumptions!$B$4 | X14: =IF(M14=0,"",ROUND(W14/M14*100,1)) | Y14: GRUPO 3E | Z14: 5341375-33.2026.8.09.0049 | AA14: TJGO | AB14: stenius.com.br | AC14: EDVALDO ANTONIO LOPES | AD14: Administrador | AE14: (62) 8115-0283 | AH14: GO | AI14: GOIANESIA | AJ14: Comércio varejista de mercadorias em geral, com predominância de produtos alimentícios - supermercados | AK14: EMPRESA DE PEQUENO PORTE | AL14: ATIVA | AM14: https://stenius.com.br/wp-content/uploads/2026/06/EDITAL-GRUPO-3E.pdf | AN14: p18 r20; p18 r21 | AO14: p18: R$ 194.613,00; p18: R$ 278,25 | AP14: DEBTOR_LIST | AQ14: 2026-06-22 | AR14: OK_NO_TOTALS | AS14: ROWS:p18r20,p18r21 UNRECONCILED_SOURCE | AT14: 8e8832093a15
A15: 14 | B15: NEW | D15: 0 | I15: SINDICATO EMPREG EMPRESAS SEG VIGILANCIA, TRANS VALORES SEG PESSOAL ORGANICA ESC ARMADA AG TATICO E MONIT CURSO FORM ESP VIGI E SIMIL DE CURITIBA E RE | J15: PRIVADA, EMPREGADOS DE EMPRESAS DE SEGURANÇA SINDICATO DOS EMPREGADOS EM EMPRESAS DE SEGURANÇA, | K15: 78232774 | L15: 78232774000135 | M15: 194886.53 | N15: 1 | O15: D | R15: =IF(Q15="","",ROUND((TODAY()-Q15)/365.25,1)) | S15: =IFERROR(VLOOKUP(O15,Assumptions!$A$7:$F$11,2,FALSE),0.25) | T15: =IF(O15="A",MAX(1,IFERROR(VLOOKUP(O15,Assumptions!$A$7:$F$11,3,FALSE),3)+IFERROR(VLOOKUP(O15,Assumptions!$A$7:$F$11,4,FALSE),8)/2-MAX(0,IF(R15="",0,R15)-IFERROR(VLOOKUP(O15,Assumptions!$A$7:$F$11,5,FALSE),1.5))),IFERROR(VLOOKUP(O15,Assumptions!$A$7:$F$11,5,FALSE),2.5)+IFERROR(VLOOKUP(O15,Assumptions!$A$7:$F$11,3,FALSE),3)+IFERROR(VLOOKUP(O15,Assumptions!$A$7:$F$11,4,FALSE),8)/2) | U15: =M15*S15/(1+Assumptions!$B$3)^T15 | V15: =IF(M15=0,"",ROUND(U15/M15*100,1)) | W15: =U15*Assumptions!$B$4 | X15: =IF(M15=0,"",ROUND(W15/M15*100,1)) | Y15: EQUIP SEG INTELIGÊNCIA EM SEGURANÇA LTDA. E EQUIP SEG SERVIÇOS ESPECIALIZADOS LTDA. | Z15: 0033736-15.2023.8.16.0185 | AB15: bbsadvogados.com.br | AE15: 004103329293 | AH15: PR | AI15: CURITIBA | AJ15: Atividades de organizações sindicais | AK15: DEMAIS | AL15: ATIVA | AM15: https://bbsadvogados.com.br/wp-content/uploads/2025/04/Equipseg-Edital-Relacao-de-Credores-da-Administradora-Judicial-art.-7o2o-da-LRF.pdf | AN15: p41 r4 | AO15: p41: R$ 194.886,53 | AP15: AJ_LIST | AQ15: 2025-04-08 | AR15: OK_NO_TOTALS | AS15: ROWS:p41r4 UNRECONCILED_SOURCE | AT15: b9895d3bab05
A16: 15 | B16: NEW | D16: 0 | I16: ENORD ENGENHARIA LTDA | J16: TELESIL ENGENHARIA LTDA | K16: 01637593 | L16: 01637593000164 | M16: 194494.22 | N16: 1 | O16: C | R16: =IF(Q16="","",ROUND((TODAY()-Q16)/365.25,1)) | S16: =IFERROR(VLOOKUP(O16,Assumptions!$A$7:$F$11,2,FALSE),0.25) | T16: =IF(O16="A",MAX(1,IFERROR(VLOOKUP(O16,Assumptions!$A$7:$F$11,3,FALSE),3)+IFERROR(VLOOKUP(O16,Assumptions!$A$7:$F$11,4,FALSE),8)/2-MAX(0,IF(R16="",0,R16)-IFERROR(VLOOKUP(O16,Assumptions!$A$7:$F$11,5,FALSE),1.5))),IFERROR(VLOOKUP(O16,Assumptions!$A$7:$F$11,5,FALSE),2.5)+IFERROR(VLOOKUP(O16,Assumptions!$A$7:$F$11,3,FALSE),3)+IFERROR(VLOOKUP(O16,Assumptions!$A$7:$F$11,4,FALSE),8)/2) | U16: =M16*S16/(1+Assumptions!$B$3)^T16 | V16: =IF(M16=0,"",ROUND(U16/M16*100,1)) | W16: =U16*Assumptions!$B$4 | X16: =IF(M16=0,"",ROUND(W16/M16*100,1)) | Y16: GRUPO ARNON DE MELLO | Z16: 0700256-03.2019.8.02.0066 | AB16: recuperacaojudicial.squarespace.com | AC16: ALFREDO GUTTENBERG DE MENDONCA BREDA | AD16: Sócio-Administrador | AE16: (82) 3336-1991 | AH16: AL | AI16: MACEIO | AJ16: Construção de edifícios | AK16: DEMAIS | AL16: ATIVA | AM16: https://recuperacaojudicial.squarespace.com/s/RJ-Grupo-Arnon-de-Melo-Lista-de-Credores-Consolidada-abril-2022.pdf | AN16: p9 r34 | AO16: p9: R$ 194.494,22 | AP16: AJ_LIST | AR16: OK_NO_TOTALS | AS16: ROWS:p9r34 UNRECONCILED_SOURCE | AT16: 60fd9c017d90
A17: 16 | B17: NEW | D17: 0 | I17: A.C.P. INDUSTRIA DE MOVEIS LTDA | J17: 30.746.945/0001-18 | K17: 30746945 | L17: 30746945000118 | M17: 193667.58 | N17: 1 | O17: C | P17: ACTIVE | Q17: 43894 | R17: =IF(Q17="","",ROUND((TODAY()-Q17)/365.25,1)) | S17: =IFERROR(VLOOKUP(O17,Assumptions!$A$7:$F$11,2,FALSE),0.25) | T17: =IF(O17="A",MAX(1,IFERROR(VLOOKUP(O17,Assumptions!$A$7:$F$11,3,FALSE),3)+IFERROR(VLOOKUP(O17,Assumptions!$A$7:$F$11,4,FALSE),8)/2-MAX(0,IF(R17="",0,R17)-IFERROR(VLOOKUP(O17,Assumptions!$A$7:$F$11,5,FALSE),1.5))),IFERROR(VLOOKUP(O17,Assumptions!$A$7:$F$11,5,FALSE),2.5)+IFERROR(VLOOKUP(O17,Assumptions!$A$7:$F$11,3,FALSE),3)+IFERROR(VLOOKUP(O17,Assumptions!$A$7:$F$11,4,FALSE),8)/2) | U17: =M17*S17/(1+Assumptions!$B$3)^T17 | V17: =IF(M17=0,"",ROUND(U17/M17*100,1)) | W17: =U17*Assumptions!$B$4 | X17: =IF(M17=0,"",ROUND(W17/M17*100,1)) | Y17: CREDIMÓVEIS NOVOLAR LTDA. | Z17: 0007565-40.2020.8.17.2370 | AA17: TJPE | AB17: recuperacaojudicial.squarespace.com | AC17: JAINA PESSOTI CAMARA CAVALCANTE | AD17: Sócio-Administrador | AE17: (27) 3371-0538 | AH17: ES | AI17: LINHARES | AJ17: Fabricação de móveis com predominância de madeira | AK17: DEMAIS | AL17: ATIVA | AM17: https://recuperacaojudicial.squarespace.com/s/RJ-Credimoveis-QGC-01082025.pdf | AN17: p15 r1 | AO17: p15: R$ 193.667,58 | AP17: QGC | AQ17: 2026-01-28 | AR17: OK | AS17: ROWS:p15r1 | AT17: 849d4fe5adce
A18: 17 | B18: NEW | D18: 0 | I18: AURIQUIMICA LTDA | J18: AURIQUIMICA FILIAL SC | K18: 54429345 | L18: 54429345000194, 54429345000356 | M18: 193371.73 | N18: 3 | O18: B | R18: =IF(Q18="","",ROUND((TODAY()-Q18)/365.25,1)) | S18: =IFERROR(VLOOKUP(O18,Assumptions!$A$7:$F$11,2,FALSE),0.25) | T18: =IF(O18="A",MAX(1,IFERROR(VLOOKUP(O18,Assumptions!$A$7:$F$11,3,FALSE),3)+IFERROR(VLOOKUP(O18,Assumptions!$A$7:$F$11,4,FALSE),8)/2-MAX(0,IF(R18="",0,R18)-IFERROR(VLOOKUP(O18,Assumptions!$A$7:$F$11,5,FALSE),1.5))),IFERROR(VLOOKUP(O18,Assumptions!$A$7:$F$11,5,FALSE),2.5)+IFERROR(VLOOKUP(O18,Assumptions!$A$7:$F$11,3,FALSE),3)+IFERROR(VLOOKUP(O18,Assumptions!$A$7:$F$11,4,FALSE),8)/2) | U18: =M18*S18/(1+Assumptions!$B$3)^T18 | V18: =IF(M18=0,"",ROUND(U18/M18*100,1)) | W18: =U18*Assumptions!$B$4 | X18: =IF(M18=0,"",ROUND(W18/M18*100,1)) | Y18: Base | Z18: 1022634-27.2024.8.26.0100 | AB18: ajruiz.com.br | AC18: LEANDRO AURICCHIO | AD18: Sócio-Administrador | AE18: (11) 2066-5600 | AH18: SP | AI18: SAO PAULO | AJ18: Comércio atacadista de outros produtos químicos e petroquímicos não especificados anteriormente | AK18: DEMAIS | AL18: ATIVA | AM18: https://ajruiz.com.br/sites/default/files/public/arquivos-processos/2024-04/relacao_de_credores_recuperanda_1.pdf | AN18: p3 r1; p3 r2; p3 r3 | AO18: p3: R$ 4.849,52; p3: R$ 120.522,21; p3: R$ 68.000,00 | AP18: QGC | AQ18: 2024-01-31 | AR18: OK | AS18: ROWS:p3r1,p3r2,p3r3 CASE_NUMBER_CORRECTED | AT18: 380922480f80
A19: 18 | B19: NEW | D19: 0 | I19: KAMYLUS MALHAS LTDA | J19: KAMYLUS MALHAS LTDA | K19: 82155870 | L19: 82155870000102 | M19: 192632.72 | N19: 3 | O19: C | P19: ACTIVE | Q19: 44571 | R19: =IF(Q19="","",ROUND((TODAY()-Q19)/365.25,1)) | S19: =IFERROR(VLOOKUP(O19,Assumptions!$A$7:$F$11,2,FALSE),0.25) | T19: =IF(O19="A",MAX(1,IFERROR(VLOOKUP(O19,Assumptions!$A$7:$F$11,3,FALSE),3)+IFERROR(VLOOKUP(O19,Assumptions!$A$7:$F$11,4,FALSE),8)/2-MAX(0,IF(R19="",0,R19)-IFERROR(VLOOKUP(O19,Assumptions!$A$7:$F$11,5,FALSE),1.5))),IFERROR(VLOOKUP(O19,Assumptions!$A$7:$F$11,5,FALSE),2.5)+IFERROR(VLOOKUP(O19,Assumptions!$A$7:$F$11,3,FALSE),3)+IFERROR(VLOOKUP(O19,Assumptions!$A$7:$F$11,4,FALSE),8)/2) | U19: =M19*S19/(1+Assumptions!$B$3)^T19 | V19: =IF(M19=0,"",ROUND(U19/M19*100,1)) | W19: =U19*Assumptions!$B$4 | X19: =IF(M19=0,"",ROUND(W19/M19*100,1)) | Y19: GRUPO CATTAN | Z19: 0002484-82.2022.8.17.2001 | AA19: TJPE | AB19: lrflideres.com.br | AC19: CAMILO VARGAS JUNIOR | AD19: Sócio-Administrador | AE19: (47) 3370-3366 | AH19: SC | AI19: JARAGUA DO SUL | AJ19: Confecção de peças de vestuário, exceto roupas íntimas e as confeccionadas sob medida | AK19: DEMAIS | AL19: ATIVA | AM19: https://lrflideres.com.br/wp-content/plugins/download-attachments/includes/download.php?id=4023 | AN19: p4 r84; p7 r108; p9 r82 | AO19: p4: R$ 69.793,25; p7: R$ 97.228,15; p9: R$ 25.611,32 | AP19: DEBTOR_LIST | AR19: QUARANTINED | AS19: PARTIAL_DOC_CLASS_III_RECONCILED ROWS:p4r84,p7r108,p9r82 | AT19: f3b6182e3aa2
A20: 19 | B20: NEW | D20: 0 | I20: FIACAO ALPINA LTDA | J20: FIACAO ALPINA LTDA | K20: 49418890 | L20: 49418890000498 | M20: 192324.58 | N20: 1 | O20: C | R20: =IF(Q20="","",ROUND((TODAY()-Q20)/365.25,1)) | S20: =IFERROR(VLOOKUP(O20,Assumptions!$A$7:$F$11,2,FALSE),0.25) | T20: =IF(O20="A",MAX(1,IFERROR(VLOOKUP(O20,Assumptions!$A$7:$F$11,3,FALSE),3)+IFERROR(VLOOKUP(O20,Assumptions!$A$7:$F$11,4,FALSE),8)/2-MAX(0,IF(R20="",0,R20)-IFERROR(VLOOKUP(O20,Assumptions!$A$7:$F$11,5,FALSE),1.5))),IFERROR(VLOOKUP(O20,Assumptions!$A$7:$F$11,5,FALSE),2.5)+IFERROR(VLOOKUP(O20,Assumptions!$A$7:$F$11,3,FALSE),3)+IFERROR(VLOOKUP(O20,Assumptions!$A$7:$F$11,4,FALSE),8)/2) | U20: =M20*S20/(1+Assumptions!$B$3)^T20 | V20: =IF(M20=0,"",ROUND(U20/M20*100,1)) | W20: =U20*Assumptions!$B$4 | X20: =IF(M20=0,"",ROUND(W20/M20*100,1)) | Y20: CONFECÇÕES ANDRIMALHAS LTDA | Z20: 0302174-63.2015.8.24.0025 | AB20: administradorajudicialgs.com.br | AC20: ANTONIO GRECO | AD20: Sócio-Administrador | AE20: (11) 4014-4104 | AH20: SP | AI20: MORUNGABA | AJ20: Fiação de fibras artificiais e sintéticas | AK20: DEMAIS | AL20: ATIVA | AM20: https://administradorajudicialgs.com.br/wp-content/uploads/2023/08/doc-06-relacao-credores-do-administrador-judicial-10-02-2015.pdf | AN20: p2 r6 | AO20: p2: R$ 192.324,58 | AP20: AJ_LIST | AR20: QUARANTINED | AS20: PARTIAL_DOC_CLASS_III_RECONCILED ROWS:p2r6 | AT20: d403116b357d
A21: 20 | B21: NEW | D21: 0 | I21: MIOLO WINE GROUP VITIVINICULTURA S.A. | J21: Miolo Wine Group Vitivinicultura S.A. (CNPJ n° | K21: 09357838 | L21: 09357838000101, 75315333000109 | M21: 192321.5 | N21: 1 | O21: B | P21: ACTIVE | Q21: 45303 | R21: =IF(Q21="","",ROUND((TODAY()-Q21)/365.25,1)) | S21: =IFERROR(VLOOKUP(O21,Assumptions!$A$7:$F$11,2,FALSE),0.25) | T21: =IF(O21="A",MAX(1,IFERROR(VLOOKUP(O21,Assumptions!$A$7:$F$11,3,FALSE),3)+IFERROR(VLOOKUP(O21,Assumptions!$A$7:$F$11,4,FALSE),8)/2-MAX(0,IF(R21="",0,R21)-IFERROR(VLOOKUP(O21,Assumptions!$A$7:$F$11,5,FALSE),1.5))),IFERROR(VLOOKUP(O21,Assumptions!$A$7:$F$11,5,FALSE),2.5)+IFERROR(VLOOKUP(O21,Assumptions!$A$7:$F$11,3,FALSE),3)+IFERROR(VLOOKUP(O21,Assumptions!$A$7:$F$11,4,FALSE),8)/2) | U21: =M21*S21/(1+Assumptions!$B$3)^T21 | V21: =IF(M21=0,"",ROUND(U21/M21*100,1)) | W21: =U21*Assumptions!$B$4 | X21: =IF(M21=0,"",ROUND(W21/M21*100,1)) | Y21: Grupo Battisti | Z21: 0000357-17.2024.8.16.0131 | AA21: TJPR | AB21: marquesadmjudicial.com.br | AC21: ADRIANO MIOLO | AD21: Diretor | AE21: (54) 2102-1500 | AH21: RS | AI21: BENTO GONCALVES | AJ21: Fabricação de vinho | AK21: DEMAIS | AL21: ATIVA | AM21: https://marquesadmjudicial.com.br/sgc/download.php?file=files/processo_documento/processo_documento10074612042024_1_.pdf&nome=2º Edital-Relação de Credores AJ e PRJ | AN21: p1 r22 | AO21: p1: R$ 192.321,50 | AP21: AJ_LIST | AQ21: 2024-01-12 | AR21: OK_NO_TOTALS | AS21: MULTI_ROOT ROWS:p1r22 UNRECONCILED_SOURCE | AT21: 96830f5ef11b
A22: 21 | B22: NEW | D22: 0 | I22: KOKUSAI DENKI ELECTRIC LINEAR S/A | J22: HITACHI KOKUSAI LINEAR EQUIP ELETRONICOS S/A | K22: 19690445 | L22: 19690445000179 | M22: 192117.25 | N22: 1 | O22: C | R22: =IF(Q22="","",ROUND((TODAY()-Q22)/365.25,1)) | S22: =IFERROR(VLOOKUP(O22,Assumptions!$A$7:$F$11,2,FALSE),0.25) | T22: =IF(O22="A",MAX(1,IFERROR(VLOOKUP(O22,Assumptions!$A$7:$F$11,3,FALSE),3)+IFERROR(VLOOKUP(O22,Assumptions!$A$7:$F$11,4,FALSE),8)/2-MAX(0,IF(R22="",0,R22)-IFERROR(VLOOKUP(O22,Assumptions!$A$7:$F$11,5,FALSE),1.5))),IFERROR(VLOOKUP(O22,Assumptions!$A$7:$F$11,5,FALSE),2.5)+IFERROR(VLOOKUP(O22,Assumptions!$A$7:$F$11,3,FALSE),3)+IFERROR(VLOOKUP(O22,Assumptions!$A$7:$F$11,4,FALSE),8)/2) | U22: =M22*S22/(1+Assumptions!$B$3)^T22 | V22: =IF(M22=0,"",ROUND(U22/M22*100,1)) | W22: =U22*Assumptions!$B$4 | X22: =IF(M22=0,"",ROUND(W22/M22*100,1)) | Y22: GRUPO ARNON DE MELLO | Z22: 0700256-03.2019.8.02.0066 | AB22: recuperacaojudicial.squarespace.com | AC22: MASAO ICHIKAWA | AD22: Presidente | AE22: (35) 3473-3473 | AF22: (35) 9722-2969 | AH22: MG | AI22: SANTA RITA DO SAPUCAI | AJ22: Fabricação de equipamentos transmissores de comunicação, peças e acessórios | AK22: DEMAIS | AL22: ATIVA | AM22: https://recuperacaojudicial.squarespace.com/s/RJ-Grupo-Arnon-de-Melo-Lista-de-Credores-Consolidada-abril-2022.pdf | AN22: p8 r21 | AO22: p8: R$ 192.117,25 | AP22: AJ_LIST | AR22: OK_NO_TOTALS | AS22: ROWS:p8r21 UNRECONCILED_SOURCE | AT22: 60fd9c017d90
A23: 22 | B23: NEW | D23: 0 | I23: COOPERATIVA AGROINDUSTRIAL DOS PRODUTORES RURAIS DO SUDOESTE GOIANO | J23: Comigo | K23: 02077618 | L23: 02077618000266 | M23: 191616 | N23: 1 | O23: B | P23: ACTIVE | Q23: 46130 | R23: =IF(Q23="","",ROUND((TODAY()-Q23)/365.25,1)) | S23: =IFERROR(VLOOKUP(O23,Assumptions!$A$7:$F$11,2,FALSE),0.25) | T23: =IF(O23="A",MAX(1,IFERROR(VLOOKUP(O23,Assumptions!$A$7:$F$11,3,FALSE),3)+IFERROR(VLOOKUP(O23,Assumptions!$A$7:$F$11,4,FALSE),8)/2-MAX(0,IF(R23="",0,R23)-IFERROR(VLOOKUP(O23,Assumptions!$A$7:$F$11,5,FALSE),1.5))),IFERROR(VLOOKUP(O23,Assumptions!$A$7:$F$11,5,FALSE),2.5)+IFERROR(VLOOKUP(O23,Assumptions!$A$7:$F$11,3,FALSE),3)+IFERROR(VLOOKUP(O23,Assumptions!$A$7:$F$11,4,FALSE),8)/2) | U23: =M23*S23/(1+Assumptions!$B$3)^T23 | V23: =IF(M23=0,"",ROUND(U23/M23*100,1)) | W23: =U23*Assumptions!$B$4 | X23: =IF(M23=0,"",ROUND(W23/M23*100,1)) | Y23: GRUPO 3E | Z23: 5341375-33.2026.8.09.0049 | AA23: TJGO | AB23: stenius.com.br | AC23: ANTONIO CHAVAGLIA | AD23: Presidente | AE23: (64) 3611-1500 | AH23: GO | AI23: RIO VERDE | AJ23: Comércio atacadista de mercadorias em geral, com predominância de insumos agropecuários | AK23: DEMAIS | AL23: ATIVA | AM23: https://stenius.com.br/wp-content/uploads/2026/06/EDITAL-GRUPO-3E.pdf | AN23: p12 r1 | AO23: p12: R$ 191.616,00 | AP23: DEBTOR_LIST | AQ23: 2026-06-22 | AR23: OK_NO_TOTALS | AS23: ROWS:p12r1 UNRECONCILED_SOURCE | AT23: 8e8832093a15
A24: 23 | B24: NEW | D24: 0 | I24: DEMOBILE - INDUSTRIA DE MOVEIS LTDA. | J24: 75.069.849/0001-10 | K24: 75069849 | L24: 75069849000110 | M24: 191561.33 | N24: 1 | O24: C | P24: ACTIVE | Q24: 43894 | R24: =IF(Q24="","",ROUND((TODAY()-Q24)/365.25,1)) | S24: =IFERROR(VLOOKUP(O24,Assumptions!$A$7:$F$11,2,FALSE),0.25) | T24: =IF(O24="A",MAX(1,IFERROR(VLOOKUP(O24,Assumptions!$A$7:$F$11,3,FALSE),3)+IFERROR(VLOOKUP(O24,Assumptions!$A$7:$F$11,4,FALSE),8)/2-MAX(0,IF(R24="",0,R24)-IFERROR(VLOOKUP(O24,Assumptions!$A$7:$F$11,5,FALSE),1.5))),IFERROR(VLOOKUP(O24,Assumptions!$A$7:$F$11,5,FALSE),2.5)+IFERROR(VLOOKUP(O24,Assumptions!$A$7:$F$11,3,FALSE),3)+IFERROR(VLOOKUP(O24,Assumptions!$A$7:$F$11,4,FALSE),8)/2) | U24: =M24*S24/(1+Assumptions!$B$3)^T24 | V24: =IF(M24=0,"",ROUND(U24/M24*100,1)) | W24: =U24*Assumptions!$B$4 | X24: =IF(M24=0,"",ROUND(W24/M24*100,1)) | Y24: CREDIMÓVEIS NOVOLAR LTDA. | Z24: 0007565-40.2020.8.17.2370 | AA24: TJPE | AB24: recuperacaojudicial.squarespace.com | AC24: DENISE OLIVE MARTINEZ DE MATOS | AD24: Sócio-Administrador | AE24: (43) 3275-0100 | AH24: PR | AI24: ARAPONGAS | AJ24: Fabricação de móveis com predominância de madeira | AK24: DEMAIS | AL24: ATIVA | AM24: https://recuperacaojudicial.squarespace.com/s/RJ-Credimoveis-QGC-01082025.pdf | AN24: p15 r37 | AO24: p15: R$ 191.561,33 | AP24: QGC | AQ24: 2026-01-28 | AR24: OK | AS24: ROWS:p15r37 | AT24: 849d4fe5adce
A25: 24 | B25: NEW | D25: 0 | I25: JAIME MANUEL DA CAMARA FIALHO FERNANDES | J25: JAIME EMANUEL DA CAMARA F.FERNANDES | K25: 35260058 | L25: 35260058000159 | M25: 190800 | N25: 1 | O25: C | R25: =IF(Q25="","",ROUND((TODAY()-Q25)/365.25,1)) | S25: =IFERROR(VLOOKUP(O25,Assumptions!$A$7:$F$11,2,FALSE),0.25) | T25: =IF(O25="A",MAX(1,IFERROR(VLOOKUP(O25,Assumptions!$A$7:$F$11,3,FALSE),3)+IFERROR(VLOOKUP(O25,Assumptions!$A$7:$F$11,4,FALSE),8)/2-MAX(0,IF(R25="",0,R25)-IFERROR(VLOOKUP(O25,Assumptions!$A$7:$F$11,5,FALSE),1.5))),IFERROR(VLOOKUP(O25,Assumptions!$A$7:$F$11,5,FALSE),2.5)+IFERROR(VLOOKUP(O25,Assumptions!$A$7:$F$11,3,FALSE),3)+IFERROR(VLOOKUP(O25,Assumptions!$A$7:$F$11,4,FALSE),8)/2) | U25: =M25*S25/(1+Assumptions!$B$3)^T25 | V25: =IF(M25=0,"",ROUND(U25/M25*100,1)) | W25: =U25*Assumptions!$B$4 | X25: =IF(M25=0,"",ROUND(W25/M25*100,1)) | Y25: GRUPO ARNON DE MELLO | Z25: 0700256-03.2019.8.02.0066 | AB25: recuperacaojudicial.squarespace.com | AH25: AL | AI25: SAO LUIS DO QUITUNDE | AJ25: Atividades de consultoria em gestão empresarial, exceto consultoria técnica específica | AK25: MICRO EMPRESA | AL25: ATIVA | AM25: https://recuperacaojudicial.squarespace.com/s/RJ-Grupo-Arnon-de-Melo-Lista-de-Credores-Consolidada-abril-2022.pdf | AN25: p8 r31 | AO25: p8: R$ 190.800,00 | AP25: AJ_LIST | AR25: OK_NO_TOTALS | AS25: ROWS:p8r31 UNRECONCILED_SOURCE | AT25: 60fd9c017d90
A26: 25 | B26: NEW | D26: 0 | I26: MAYA, PADILHA E DUARTE PINTO ADVOGADOS ASSOCIADOS | J26: MARANHÃO, MAYA, PADILHA, DUARTE & PRATA ADVOGADOS ASSOCIADOS | K26: 08215002 | L26: 08215002000100 | M26: 189412.96 | N26: 1 | O26: C | R26: =IF(Q26="","",ROUND((TODAY()-Q26)/365.25,1)) | S26: =IFERROR(VLOOKUP(O26,Assumptions!$A$7:$F$11,2,FALSE),0.25) | T26: =IF(O26="A",MAX(1,IFERROR(VLOOKUP(O26,Assumptions!$A$7:$F$11,3,FALSE),3)+IFERROR(VLOOKUP(O26,Assumptions!$A$7:$F$11,4,FALSE),8)/2-MAX(0,IF(R26="",0,R26)-IFERROR(VLOOKUP(O26,Assumptions!$A$7:$F$11,5,FALSE),1.5))),IFERROR(VLOOKUP(O26,Assumptions!$A$7:$F$11,5,FALSE),2.5)+IFERROR(VLOOKUP(O26,Assumptions!$A$7:$F$11,3,FALSE),3)+IFERROR(VLOOKUP(O26,Assumptions!$A$7:$F$11,4,FALSE),8)/2) | U26: =M26*S26/(1+Assumptions!$B$3)^T26 | V26: =IF(M26=0,"",ROUND(U26/M26*100,1)) | W26: =U26*Assumptions!$B$4 | X26: =IF(M26=0,"",ROUND(W26/M26*100,1)) | Y26: GRUPO ARNON DE MELLO | Z26: 0700256-03.2019.8.02.0066 | AB26: recuperacaojudicial.squarespace.com | AC26: DAVID ARAUJO PADILHA | AD26: Sócio-Administrador | AE26: (82) 3221-2990 | AH26: AL | AI26: MACEIO | AJ26: Serviços advocatícios | AK26: MICRO EMPRESA | AL26: ATIVA | AM26: https://recuperacaojudicial.squarespace.com/s/RJ-Grupo-Arnon-de-Melo-Lista-de-Credores-Consolidada-abril-2022.pdf | AN26: p8 r54 | AO26: p8: R$ 189.412,96 | AP26: AJ_LIST | AR26: OK_NO_TOTALS | AS26: ROWS:p8r54 UNRECONCILED_SOURCE | AT26: 60fd9c017d90
A27: 26 | B27: NEW | D27: 0 | I27: INTEGRADA COOPERATIVA AGROINDUSTRIAL | J27: INTEGRADA COOPERATIVA AGROINDUSTRIAL | K27: 00993264 | L27: 00993264000355 | M27: 189409.38 | N27: 1 | O27: C | R27: =IF(Q27="","",ROUND((TODAY()-Q27)/365.25,1)) | S27: =IFERROR(VLOOKUP(O27,Assumptions!$A$7:$F$11,2,FALSE),0.25) | T27: =IF(O27="A",MAX(1,IFERROR(VLOOKUP(O27,Assumptions!$A$7:$F$11,3,FALSE),3)+IFERROR(VLOOKUP(O27,Assumptions!$A$7:$F$11,4,FALSE),8)/2-MAX(0,IF(R27="",0,R27)-IFERROR(VLOOKUP(O27,Assumptions!$A$7:$F$11,5,FALSE),1.5))),IFERROR(VLOOKUP(O27,Assumptions!$A$7:$F$11,5,FALSE),2.5)+IFERROR(VLOOKUP(O27,Assumptions!$A$7:$F$11,3,FALSE),3)+IFERROR(VLOOKUP(O27,Assumptions!$A$7:$F$11,4,FALSE),8)/2) | U27: =M27*S27/(1+Assumptions!$B$3)^T27 | V27: =IF(M27=0,"",ROUND(U27/M27*100,1)) | W27: =U27*Assumptions!$B$4 | X27: =IF(M27=0,"",ROUND(W27/M27*100,1)) | Y27: CONFECÇÕES ANDRIMALHAS LTDA | Z27: 0302174-63.2015.8.24.0025 | AB27: administradorajudicialgs.com.br | AC27: JOAO FRANCISCO SANCHES FILHO | AD27: Presidente | AE27: (43) 3294-7000 | AF27: (43) 3294-7000 | AH27: PR | AI27: LONDRINA | AJ27: Comércio atacadista de matérias-primas agrícolas não especificadas anteriormente | AK27: DEMAIS | AL27: ATIVA | AM27: https://administradorajudicialgs.com.br/wp-content/uploads/2023/08/doc-06-relacao-credores-do-administrador-judicial-10-02-2015.pdf | AN27: p2 r20 | AO27: p2: R$ 189.409,38 | AP27: AJ_LIST | AR27: QUARANTINED | AS27: PARTIAL_DOC_CLASS_III_RECONCILED ROWS:p2r20 | AT27: d403116b357d
A28: 27 | B28: NEW | D28: 0 | I28: TRADE PACK COMERCIAL LTDA | J28: TRADE & PACK COMERCIAL LTDA | K28: 04205560 | L28: 04205560000133 | M28: 189260.69 | N28: 1 | O28: C | P28: ACTIVE | Q28: 45154 | R28: =IF(Q28="","",ROUND((TODAY()-Q28)/365.25,1)) | S28: =IFERROR(VLOOKUP(O28,Assumptions!$A$7:$F$11,2,FALSE),0.25) | T28: =IF(O28="A",MAX(1,IFERROR(VLOOKUP(O28,Assumptions!$A$7:$F$11,3,FALSE),3)+IFERROR(VLOOKUP(O28,Assumptions!$A$7:$F$11,4,FALSE),8)/2-MAX(0,IF(R28="",0,R28)-IFERROR(VLOOKUP(O28,Assumptions!$A$7:$F$11,5,FALSE),1.5))),IFERROR(VLOOKUP(O28,Assumptions!$A$7:$F$11,5,FALSE),2.5)+IFERROR(VLOOKUP(O28,Assumptions!$A$7:$F$11,3,FALSE),3)+IFERROR(VLOOKUP(O28,Assumptions!$A$7:$F$11,4,FALSE),8)/2) | U28: =M28*S28/(1+Assumptions!$B$3)^T28 | V28: =IF(M28=0,"",ROUND(U28/M28*100,1)) | W28: =U28*Assumptions!$B$4 | X28: =IF(M28=0,"",ROUND(W28/M28*100,1)) | Y28: AZEPLAST INDÚSTRIA E COMÉRCIO LTDA | Z28: 5008793-34.2023.8.24.0019 | AA28: TJSC | AB28: ajruiz.com.br | AC28: PAULO GUAITA GARNICA | AD28: Sócio-Administrador | AE28: (11) 4667-1382 | AH28: SP | AI28: ITAPECERICA DA SERRA | AJ28: Comércio atacadista de embalagens | AK28: DEMAIS | AL28: ATIVA | AM28: https://ajruiz.com.br/sites/default/files/public/arquivos-processos/2026-08/qgc_azeplast_julho_2026.pdf | AN28: p2 r12 | AO28: p2: R$ 189.260,69 | AP28: QGC | AR28: QUARANTINED | AS28: PARTIAL_DOC_CLASS_III_RECONCILED ROWS:p2r12 | AT28: 229081edb0ea
A29: 28 | B29: NEW | D29: 0 | I29: DNA SOLUCOES COMERCIO E IMPORTACAO DE PRODUTOS AGRICOLAS LTDA | J29: DNA SOLUCOES COM E IMPORTADAO DE PRODUTOS | K29: 21018796 | L29: 21018796000180 | M29: 188929.79 | N29: 1 | O29: B | P29: ACTIVE | Q29: 45425 | R29: =IF(Q29="","",ROUND((TODAY()-Q29)/365.25,1)) | S29: =IFERROR(VLOOKUP(O29,Assumptions!$A$7:$F$11,2,FALSE),0.25) | T29: =IF(O29="A",MAX(1,IFERROR(VLOOKUP(O29,Assumptions!$A$7:$F$11,3,FALSE),3)+IFERROR(VLOOKUP(O29,Assumptions!$A$7:$F$11,4,FALSE),8)/2-MAX(0,IF(R29="",0,R29)-IFERROR(VLOOKUP(O29,Assumptions!$A$7:$F$11,5,FALSE),1.5))),IFERROR(VLOOKUP(O29,Assumptions!$A$7:$F$11,5,FALSE),2.5)+IFERROR(VLOOKUP(O29,Assumptions!$A$7:$F$11,3,FALSE),3)+IFERROR(VLOOKUP(O29,Assumptions!$A$7:$F$11,4,FALSE),8)/2) | U29: =M29*S29/(1+Assumptions!$B$3)^T29 | V29: =IF(M29=0,"",ROUND(U29/M29*100,1)) | W29: =U29*Assumptions!$B$4 | X29: =IF(M29=0,"",ROUND(W29/M29*100,1)) | Y29: GRUPO DIVINA | Z29: 0000721-61.2024.8.17.2620 | AA29: TJPE | AB29: lrflideres.com.br | AC29: MUCIO SALES DE NOVAES FERREIRA | AD29: Sócio-Administrador | AE29: (87) 3864-7800 | AF29: (87) 3032-0412 | AH29: PE | AI29: PETROLINA | AJ29: Comércio atacadista de defensivos agrícolas, adubos, fertilizantes e corretivos do solo | AK29: EMPRESA DE PEQUENO PORTE | AL29: ATIVA | AM29: https://lrflideres.com.br/wp-content/plugins/download-attachments/includes/download.php?id=6252 | AN29: p2 r35 | AO29: p2: R$ 188.929,79 | AP29: AJ_LIST | AQ29: 2024-11-27 | AR29: QUARANTINED | AS29: PARTIAL_DOC_CLASS_III_RECONCILED ROWS:p2r35 | AT29: 38f0c15b8a2d
A30: 29 | B30: NEW | D30: 0 | I30: PBG S/A | J30: PBG S/A | K30: 83475913 | L30: 83475913004006 | M30: 188272.57 | N30: 1 | O30: B | Q30: 45785 | R30: =IF(Q30="","",ROUND((TODAY()-Q30)/365.25,1)) | S30: =IFERROR(VLOOKUP(O30,Assumptions!$A$7:$F$11,2,FALSE),0.25) | T30: =IF(O30="A",MAX(1,IFERROR(VLOOKUP(O30,Assumptions!$A$7:$F$11,3,FALSE),3)+IFERROR(VLOOKUP(O30,Assumptions!$A$7:$F$11,4,FALSE),8)/2-MAX(0,IF(R30="",0,R30)-IFERROR(VLOOKUP(O30,Assumptions!$A$7:$F$11,5,FALSE),1.5))),IFERROR(VLOOKUP(O30,Assumptions!$A$7:$F$11,5,FALSE),2.5)+IFERROR(VLOOKUP(O30,Assumptions!$A$7:$F$11,3,FALSE),3)+IFERROR(VLOOKUP(O30,Assumptions!$A$7:$F$11,4,FALSE),8)/2) | U30: =M30*S30/(1+Assumptions!$B$3)^T30 | V30: =IF(M30=0,"",ROUND(U30/M30*100,1)) | W30: =U30*Assumptions!$B$4 | X30: =IF(M30=0,"",ROUND(W30/M30*100,1)) | Y30: Grupo Pisebem | Z30: 0700707-87.2025.8.02.0043 | AA30: TJAL | AB30: recuperacaojudicial.squarespace.com | AC30: CESAR GOMES JUNIOR | AD30: Diretor | AE30: (48) 3279-2587 | AH30: SC | AI30: TIJUCAS | AJ30: Fabricação de azulejos e pisos | AK30: DEMAIS | AL30: ATIVA | AM30: https://recuperacaojudicial.squarespace.com/s/EDITAL-COM-A-2-LISTA-DE-CREDORES-E-INFORMANDO-A-APRESENTACO-DO-PRJ_1532.pdf | AN30: p2 r13 | AO30: p2: R$ 188.272,57 | AP30: AJ_LIST | AR30: OK_NO_TOTALS | AS30: ROWS:p2r13 UNRECONCILED_SOURCE CASE_NUMBER_CORRECTED | AT30: d7c426fbd475
