Workbook

Sheet DASHBOARD
A1: ANTEPARO — CALL DASHBOARD
A2: Live off the CALL SHEET tab · sorted by fund price (∝ our ágio) · 2026-09-04
A4: PIPELINE | E4: TOP 15 BY OUR ÁGIO | F4: Debtor | G4: Ágio (R$) | H4: Band | I4: Status | J4: Next date
A5: Leads on sheet | B5: =COUNTA('CALL SHEET'!$A$2:$A$560) | E5: =IFERROR(INDEX('CALL SHEET'!$A$2:$A$560,MATCH(G5,'CALL SHEET'!$AB$2:$AB$560,0)),"") | F5: =IFERROR(INDEX('CALL SHEET'!$C$2:$C$560,MATCH(G5,'CALL SHEET'!$AB$2:$AB$560,0)),"") | G5: =IFERROR(LARGE('CALL SHEET'!$AB$2:$AB$560,1),"") | H5: =IFERROR(INDEX('CALL SHEET'!$U$2:$U$560,MATCH(G5,'CALL SHEET'!$AB$2:$AB$560,0)),"") | I5: =IFERROR(INDEX('CALL SHEET'!$D$2:$D$560,MATCH(G5,'CALL SHEET'!$AB$2:$AB$560,0)),"") | J5: =IFERROR(INDEX('CALL SHEET'!$G$2:$G$560,MATCH(G5,'CALL SHEET'!$AB$2:$AB$560,0)),"")
A6: Total face (R$) | B6: =SUM('CALL SHEET'!$T$2:$T$560) | E6: =IFERROR(INDEX('CALL SHEET'!$A$2:$A$560,MATCH(G6,'CALL SHEET'!$AB$2:$AB$560,0)),"") | F6: =IFERROR(INDEX('CALL SHEET'!$C$2:$C$560,MATCH(G6,'CALL SHEET'!$AB$2:$AB$560,0)),"") | G6: =IFERROR(LARGE('CALL SHEET'!$AB$2:$AB$560,2),"") | H6: =IFERROR(INDEX('CALL SHEET'!$U$2:$U$560,MATCH(G6,'CALL SHEET'!$AB$2:$AB$560,0)),"") | I6: =IFERROR(INDEX('CALL SHEET'!$D$2:$D$560,MATCH(G6,'CALL SHEET'!$AB$2:$AB$560,0)),"") | J6: =IFERROR(INDEX('CALL SHEET'!$G$2:$G$560,MATCH(G6,'CALL SHEET'!$AB$2:$AB$560,0)),"")
A7: Fund price pipeline (R$) | B7: =SUM('CALL SHEET'!$X$2:$X$560) | E7: =IFERROR(INDEX('CALL SHEET'!$A$2:$A$560,MATCH(G7,'CALL SHEET'!$AB$2:$AB$560,0)),"") | F7: =IFERROR(INDEX('CALL SHEET'!$C$2:$C$560,MATCH(G7,'CALL SHEET'!$AB$2:$AB$560,0)),"") | G7: =IFERROR(LARGE('CALL SHEET'!$AB$2:$AB$560,3),"") | H7: =IFERROR(INDEX('CALL SHEET'!$U$2:$U$560,MATCH(G7,'CALL SHEET'!$AB$2:$AB$560,0)),"") | I7: =IFERROR(INDEX('CALL SHEET'!$D$2:$D$560,MATCH(G7,'CALL SHEET'!$AB$2:$AB$560,0)),"") | J7: =IFERROR(INDEX('CALL SHEET'!$G$2:$G$560,MATCH(G7,'CALL SHEET'!$AB$2:$AB$560,0)),"")
A8: OUR ÁGIO pipeline (R$) | B8: =SUM('CALL SHEET'!$AB$2:$AB$560) | E8: =IFERROR(INDEX('CALL SHEET'!$A$2:$A$560,MATCH(G8,'CALL SHEET'!$AB$2:$AB$560,0)),"") | F8: =IFERROR(INDEX('CALL SHEET'!$C$2:$C$560,MATCH(G8,'CALL SHEET'!$AB$2:$AB$560,0)),"") | G8: =IFERROR(LARGE('CALL SHEET'!$AB$2:$AB$560,4),"") | H8: =IFERROR(INDEX('CALL SHEET'!$U$2:$U$560,MATCH(G8,'CALL SHEET'!$AB$2:$AB$560,0)),"") | I8: =IFERROR(INDEX('CALL SHEET'!$D$2:$D$560,MATCH(G8,'CALL SHEET'!$AB$2:$AB$560,0)),"") | J8: =IFERROR(INDEX('CALL SHEET'!$G$2:$G$560,MATCH(G8,'CALL SHEET'!$AB$2:$AB$560,0)),"")
A9: Untouched (NEW) | B9: =COUNTIF('CALL SHEET'!$D$2:$D$560,"NEW") | E9: =IFERROR(INDEX('CALL SHEET'!$A$2:$A$560,MATCH(G9,'CALL SHEET'!$AB$2:$AB$560,0)),"") | F9: =IFERROR(INDEX('CALL SHEET'!$C$2:$C$560,MATCH(G9,'CALL SHEET'!$AB$2:$AB$560,0)),"") | G9: =IFERROR(LARGE('CALL SHEET'!$AB$2:$AB$560,5),"") | H9: =IFERROR(INDEX('CALL SHEET'!$U$2:$U$560,MATCH(G9,'CALL SHEET'!$AB$2:$AB$560,0)),"") | I9: =IFERROR(INDEX('CALL SHEET'!$D$2:$D$560,MATCH(G9,'CALL SHEET'!$AB$2:$AB$560,0)),"") | J9: =IFERROR(INDEX('CALL SHEET'!$G$2:$G$560,MATCH(G9,'CALL SHEET'!$AB$2:$AB$560,0)),"")
A10: Calls due today | B10: =COUNTIF('CALL SHEET'!$G$2:$G$560,TODAY()) | E10: =IFERROR(INDEX('CALL SHEET'!$A$2:$A$560,MATCH(G10,'CALL SHEET'!$AB$2:$AB$560,0)),"") | F10: =IFERROR(INDEX('CALL SHEET'!$C$2:$C$560,MATCH(G10,'CALL SHEET'!$AB$2:$AB$560,0)),"") | G10: =IFERROR(LARGE('CALL SHEET'!$AB$2:$AB$560,6),"") | H10: =IFERROR(INDEX('CALL SHEET'!$U$2:$U$560,MATCH(G10,'CALL SHEET'!$AB$2:$AB$560,0)),"") | I10: =IFERROR(INDEX('CALL SHEET'!$D$2:$D$560,MATCH(G10,'CALL SHEET'!$AB$2:$AB$560,0)),"") | J10: =IFERROR(INDEX('CALL SHEET'!$G$2:$G$560,MATCH(G10,'CALL SHEET'!$AB$2:$AB$560,0)),"")
A11: Overdue follow-ups | B11: =COUNTIFS('CALL SHEET'!$G$2:$G$560,"<"&TODAY(),'CALL SHEET'!$G$2:$G$560,"<>",'CALL SHEET'!$D$2:$D$560,"<>DEAD",'CALL SHEET'!$D$2:$D$560,"<>DEAL") | E11: =IFERROR(INDEX('CALL SHEET'!$A$2:$A$560,MATCH(G11,'CALL SHEET'!$AB$2:$AB$560,0)),"") | F11: =IFERROR(INDEX('CALL SHEET'!$C$2:$C$560,MATCH(G11,'CALL SHEET'!$AB$2:$AB$560,0)),"") | G11: =IFERROR(LARGE('CALL SHEET'!$AB$2:$AB$560,7),"") | H11: =IFERROR(INDEX('CALL SHEET'!$U$2:$U$560,MATCH(G11,'CALL SHEET'!$AB$2:$AB$560,0)),"") | I11: =IFERROR(INDEX('CALL SHEET'!$D$2:$D$560,MATCH(G11,'CALL SHEET'!$AB$2:$AB$560,0)),"") | J11: =IFERROR(INDEX('CALL SHEET'!$G$2:$G$560,MATCH(G11,'CALL SHEET'!$AB$2:$AB$560,0)),"")
A12: Interested + Deal — ágio (R$) | B12: =SUMIF('CALL SHEET'!$D$2:$D$560,"INTERESTED",'CALL SHEET'!$AB$2:$AB$560)+SUMIF('CALL SHEET'!$D$2:$D$560,"DEAL",'CALL SHEET'!$AB$2:$AB$560) | E12: =IFERROR(INDEX('CALL SHEET'!$A$2:$A$560,MATCH(G12,'CALL SHEET'!$AB$2:$AB$560,0)),"") | F12: =IFERROR(INDEX('CALL SHEET'!$C$2:$C$560,MATCH(G12,'CALL SHEET'!$AB$2:$AB$560,0)),"") | G12: =IFERROR(LARGE('CALL SHEET'!$AB$2:$AB$560,8),"") | H12: =IFERROR(INDEX('CALL SHEET'!$U$2:$U$560,MATCH(G12,'CALL SHEET'!$AB$2:$AB$560,0)),"") | I12: =IFERROR(INDEX('CALL SHEET'!$D$2:$D$560,MATCH(G12,'CALL SHEET'!$AB$2:$AB$560,0)),"") | J12: =IFERROR(INDEX('CALL SHEET'!$G$2:$G$560,MATCH(G12,'CALL SHEET'!$AB$2:$AB$560,0)),"")
E13: =IFERROR(INDEX('CALL SHEET'!$A$2:$A$560,MATCH(G13,'CALL SHEET'!$AB$2:$AB$560,0)),"") | F13: =IFERROR(INDEX('CALL SHEET'!$C$2:$C$560,MATCH(G13,'CALL SHEET'!$AB$2:$AB$560,0)),"") | G13: =IFERROR(LARGE('CALL SHEET'!$AB$2:$AB$560,9),"") | H13: =IFERROR(INDEX('CALL SHEET'!$U$2:$U$560,MATCH(G13,'CALL SHEET'!$AB$2:$AB$560,0)),"") | I13: =IFERROR(INDEX('CALL SHEET'!$D$2:$D$560,MATCH(G13,'CALL SHEET'!$AB$2:$AB$560,0)),"") | J13: =IFERROR(INDEX('CALL SHEET'!$G$2:$G$560,MATCH(G13,'CALL SHEET'!$AB$2:$AB$560,0)),"")
A14: FUNNEL | B14: leads | C14: ágio (R$) | E14: =IFERROR(INDEX('CALL SHEET'!$A$2:$A$560,MATCH(G14,'CALL SHEET'!$AB$2:$AB$560,0)),"") | F14: =IFERROR(INDEX('CALL SHEET'!$C$2:$C$560,MATCH(G14,'CALL SHEET'!$AB$2:$AB$560,0)),"") | G14: =IFERROR(LARGE('CALL SHEET'!$AB$2:$AB$560,10),"") | H14: =IFERROR(INDEX('CALL SHEET'!$U$2:$U$560,MATCH(G14,'CALL SHEET'!$AB$2:$AB$560,0)),"") | I14: =IFERROR(INDEX('CALL SHEET'!$D$2:$D$560,MATCH(G14,'CALL SHEET'!$AB$2:$AB$560,0)),"") | J14: =IFERROR(INDEX('CALL SHEET'!$G$2:$G$560,MATCH(G14,'CALL SHEET'!$AB$2:$AB$560,0)),"")
A15: NEW | B15: =COUNTIF('CALL SHEET'!$D$2:$D$560,"NEW") | C15: =SUMIF('CALL SHEET'!$D$2:$D$560,"NEW",'CALL SHEET'!$AB$2:$AB$560) | E15: =IFERROR(INDEX('CALL SHEET'!$A$2:$A$560,MATCH(G15,'CALL SHEET'!$AB$2:$AB$560,0)),"") | F15: =IFERROR(INDEX('CALL SHEET'!$C$2:$C$560,MATCH(G15,'CALL SHEET'!$AB$2:$AB$560,0)),"") | G15: =IFERROR(LARGE('CALL SHEET'!$AB$2:$AB$560,11),"") | H15: =IFERROR(INDEX('CALL SHEET'!$U$2:$U$560,MATCH(G15,'CALL SHEET'!$AB$2:$AB$560,0)),"") | I15: =IFERROR(INDEX('CALL SHEET'!$D$2:$D$560,MATCH(G15,'CALL SHEET'!$AB$2:$AB$560,0)),"") | J15: =IFERROR(INDEX('CALL SHEET'!$G$2:$G$560,MATCH(G15,'CALL SHEET'!$AB$2:$AB$560,0)),"")
A16: QUEUED | B16: =COUNTIF('CALL SHEET'!$D$2:$D$560,"QUEUED") | C16: =SUMIF('CALL SHEET'!$D$2:$D$560,"QUEUED",'CALL SHEET'!$AB$2:$AB$560) | E16: =IFERROR(INDEX('CALL SHEET'!$A$2:$A$560,MATCH(G16,'CALL SHEET'!$AB$2:$AB$560,0)),"") | F16: =IFERROR(INDEX('CALL SHEET'!$C$2:$C$560,MATCH(G16,'CALL SHEET'!$AB$2:$AB$560,0)),"") | G16: =IFERROR(LARGE('CALL SHEET'!$AB$2:$AB$560,12),"") | H16: =IFERROR(INDEX('CALL SHEET'!$U$2:$U$560,MATCH(G16,'CALL SHEET'!$AB$2:$AB$560,0)),"") | I16: =IFERROR(INDEX('CALL SHEET'!$D$2:$D$560,MATCH(G16,'CALL SHEET'!$AB$2:$AB$560,0)),"") | J16: =IFERROR(INDEX('CALL SHEET'!$G$2:$G$560,MATCH(G16,'CALL SHEET'!$AB$2:$AB$560,0)),"")
A17: EMAILED | B17: =COUNTIF('CALL SHEET'!$D$2:$D$560,"EMAILED") | C17: =SUMIF('CALL SHEET'!$D$2:$D$560,"EMAILED",'CALL SHEET'!$AB$2:$AB$560) | E17: =IFERROR(INDEX('CALL SHEET'!$A$2:$A$560,MATCH(G17,'CALL SHEET'!$AB$2:$AB$560,0)),"") | F17: =IFERROR(INDEX('CALL SHEET'!$C$2:$C$560,MATCH(G17,'CALL SHEET'!$AB$2:$AB$560,0)),"") | G17: =IFERROR(LARGE('CALL SHEET'!$AB$2:$AB$560,13),"") | H17: =IFERROR(INDEX('CALL SHEET'!$U$2:$U$560,MATCH(G17,'CALL SHEET'!$AB$2:$AB$560,0)),"") | I17: =IFERROR(INDEX('CALL SHEET'!$D$2:$D$560,MATCH(G17,'CALL SHEET'!$AB$2:$AB$560,0)),"") | J17: =IFERROR(INDEX('CALL SHEET'!$G$2:$G$560,MATCH(G17,'CALL SHEET'!$AB$2:$AB$560,0)),"")
A18: CALLED | B18: =COUNTIF('CALL SHEET'!$D$2:$D$560,"CALLED") | C18: =SUMIF('CALL SHEET'!$D$2:$D$560,"CALLED",'CALL SHEET'!$AB$2:$AB$560) | E18: =IFERROR(INDEX('CALL SHEET'!$A$2:$A$560,MATCH(G18,'CALL SHEET'!$AB$2:$AB$560,0)),"") | F18: =IFERROR(INDEX('CALL SHEET'!$C$2:$C$560,MATCH(G18,'CALL SHEET'!$AB$2:$AB$560,0)),"") | G18: =IFERROR(LARGE('CALL SHEET'!$AB$2:$AB$560,14),"") | H18: =IFERROR(INDEX('CALL SHEET'!$U$2:$U$560,MATCH(G18,'CALL SHEET'!$AB$2:$AB$560,0)),"") | I18: =IFERROR(INDEX('CALL SHEET'!$D$2:$D$560,MATCH(G18,'CALL SHEET'!$AB$2:$AB$560,0)),"") | J18: =IFERROR(INDEX('CALL SHEET'!$G$2:$G$560,MATCH(G18,'CALL SHEET'!$AB$2:$AB$560,0)),"")
A19: VOICEMAIL | B19: =COUNTIF('CALL SHEET'!$D$2:$D$560,"VOICEMAIL") | C19: =SUMIF('CALL SHEET'!$D$2:$D$560,"VOICEMAIL",'CALL SHEET'!$AB$2:$AB$560) | E19: =IFERROR(INDEX('CALL SHEET'!$A$2:$A$560,MATCH(G19,'CALL SHEET'!$AB$2:$AB$560,0)),"") | F19: =IFERROR(INDEX('CALL SHEET'!$C$2:$C$560,MATCH(G19,'CALL SHEET'!$AB$2:$AB$560,0)),"") | G19: =IFERROR(LARGE('CALL SHEET'!$AB$2:$AB$560,15),"") | H19: =IFERROR(INDEX('CALL SHEET'!$U$2:$U$560,MATCH(G19,'CALL SHEET'!$AB$2:$AB$560,0)),"") | I19: =IFERROR(INDEX('CALL SHEET'!$D$2:$D$560,MATCH(G19,'CALL SHEET'!$AB$2:$AB$560,0)),"") | J19: =IFERROR(INDEX('CALL SHEET'!$G$2:$G$560,MATCH(G19,'CALL SHEET'!$AB$2:$AB$560,0)),"")
A20: CONNECTED | B20: =COUNTIF('CALL SHEET'!$D$2:$D$560,"CONNECTED") | C20: =SUMIF('CALL SHEET'!$D$2:$D$560,"CONNECTED",'CALL SHEET'!$AB$2:$AB$560)
A21: INTERESTED | B21: =COUNTIF('CALL SHEET'!$D$2:$D$560,"INTERESTED") | C21: =SUMIF('CALL SHEET'!$D$2:$D$560,"INTERESTED",'CALL SHEET'!$AB$2:$AB$560) | E21: CASE OWNERSHIP — deepest debtors | F21: leads | G21: ágio (R$) | H21: called | I21: interested
A22: NOT INTERESTED | B22: =COUNTIF('CALL SHEET'!$D$2:$D$560,"NOT INTERESTED") | C22: =SUMIF('CALL SHEET'!$D$2:$D$560,"NOT INTERESTED",'CALL SHEET'!$AB$2:$AB$560) | E22: EGESA ENGENHARIA S/A (Consórcio ETDI) | F22: =COUNTIF('CALL SHEET'!$C$2:$C$560,"EGESA ENGENHARIA S/A (Consórcio ETDI)") | G22: =SUMIF('CALL SHEET'!$C$2:$C$560,"EGESA ENGENHARIA S/A (Consórcio ETDI)",'CALL SHEET'!$AB$2:$AB$560) | H22: =COUNTIFS('CALL SHEET'!$C$2:$C$560,"EGESA ENGENHARIA S/A (Consórcio ETDI)",'CALL SHEET'!$D$2:$D$560,"<>NEW") | I22: =COUNTIFS('CALL SHEET'!$C$2:$C$560,"EGESA ENGENHARIA S/A (Consórcio ETDI)",'CALL SHEET'!$D$2:$D$560,"INTERESTED")+COUNTIFS('CALL SHEET'!$C$2:$C$560,"EGESA ENGENHARIA S/A (Consórcio ETDI)",'CALL SHEET'!$D$2:$D$560,"DEAL")
A23: CALL BACK | B23: =COUNTIF('CALL SHEET'!$D$2:$D$560,"CALL BACK") | C23: =SUMIF('CALL SHEET'!$D$2:$D$560,"CALL BACK",'CALL SHEET'!$AB$2:$AB$560) | E23: COMERCIO RACOES BEM BOM LTDA | F23: =COUNTIF('CALL SHEET'!$C$2:$C$560,"COMERCIO RACOES BEM BOM LTDA") | G23: =SUMIF('CALL SHEET'!$C$2:$C$560,"COMERCIO RACOES BEM BOM LTDA",'CALL SHEET'!$AB$2:$AB$560) | H23: =COUNTIFS('CALL SHEET'!$C$2:$C$560,"COMERCIO RACOES BEM BOM LTDA",'CALL SHEET'!$D$2:$D$560,"<>NEW") | I23: =COUNTIFS('CALL SHEET'!$C$2:$C$560,"COMERCIO RACOES BEM BOM LTDA",'CALL SHEET'!$D$2:$D$560,"INTERESTED")+COUNTIFS('CALL SHEET'!$C$2:$C$560,"COMERCIO RACOES BEM BOM LTDA",'CALL SHEET'!$D$2:$D$560,"DEAL")
A24: DEAD | B24: =COUNTIF('CALL SHEET'!$D$2:$D$560,"DEAD") | C24: =SUMIF('CALL SHEET'!$D$2:$D$560,"DEAD",'CALL SHEET'!$AB$2:$AB$560) | E24: aludida empresa | F24: =COUNTIF('CALL SHEET'!$C$2:$C$560,"aludida empresa") | G24: =SUMIF('CALL SHEET'!$C$2:$C$560,"aludida empresa",'CALL SHEET'!$AB$2:$AB$560) | H24: =COUNTIFS('CALL SHEET'!$C$2:$C$560,"aludida empresa",'CALL SHEET'!$D$2:$D$560,"<>NEW") | I24: =COUNTIFS('CALL SHEET'!$C$2:$C$560,"aludida empresa",'CALL SHEET'!$D$2:$D$560,"INTERESTED")+COUNTIFS('CALL SHEET'!$C$2:$C$560,"aludida empresa",'CALL SHEET'!$D$2:$D$560,"DEAL")
A25: DEAL | B25: =COUNTIF('CALL SHEET'!$D$2:$D$560,"DEAL") | C25: =SUMIF('CALL SHEET'!$D$2:$D$560,"DEAL",'CALL SHEET'!$AB$2:$AB$560) | E25: R W CONSTRUCOES LTDA | F25: =COUNTIF('CALL SHEET'!$C$2:$C$560,"R W CONSTRUCOES LTDA") | G25: =SUMIF('CALL SHEET'!$C$2:$C$560,"R W CONSTRUCOES LTDA",'CALL SHEET'!$AB$2:$AB$560) | H25: =COUNTIFS('CALL SHEET'!$C$2:$C$560,"R W CONSTRUCOES LTDA",'CALL SHEET'!$D$2:$D$560,"<>NEW") | I25: =COUNTIFS('CALL SHEET'!$C$2:$C$560,"R W CONSTRUCOES LTDA",'CALL SHEET'!$D$2:$D$560,"INTERESTED")+COUNTIFS('CALL SHEET'!$C$2:$C$560,"R W CONSTRUCOES LTDA",'CALL SHEET'!$D$2:$D$560,"DEAL")
E26: VEV COMERCIO DE MEDICAMENTOS LTDA EM RECUPERACAO JUDICIAL | F26: =COUNTIF('CALL SHEET'!$C$2:$C$560,"VEV COMERCIO DE MEDICAMENTOS LTDA EM RECUPERACAO JUDICIAL") | G26: =SUMIF('CALL SHEET'!$C$2:$C$560,"VEV COMERCIO DE MEDICAMENTOS LTDA EM RECUPERACAO JUDICIAL",'CALL SHEET'!$AB$2:$AB$560) | H26: =COUNTIFS('CALL SHEET'!$C$2:$C$560,"VEV COMERCIO DE MEDICAMENTOS LTDA EM RECUPERACAO JUDICIAL",'CALL SHEET'!$D$2:$D$560,"<>NEW") | I26: =COUNTIFS('CALL SHEET'!$C$2:$C$560,"VEV COMERCIO DE MEDICAMENTOS LTDA EM RECUPERACAO JUDICIAL",'CALL SHEET'!$D$2:$D$560,"INTERESTED")+COUNTIFS('CALL SHEET'!$C$2:$C$560,"VEV COMERCIO DE MEDICAMENTOS LTDA EM RECUPERACAO JUDICIAL",'CALL SHEET'!$D$2:$D$560,"DEAL")
A27: DEBTOR BAND | B27: leads | C27: ágio (R$) | E27: ASSOCIACAO DE CARIDADE SANTA CASA DE RIO GRANDE | F27: =COUNTIF('CALL SHEET'!$C$2:$C$560,"ASSOCIACAO DE CARIDADE SANTA CASA DE RIO GRANDE") | G27: =SUMIF('CALL SHEET'!$C$2:$C$560,"ASSOCIACAO DE CARIDADE SANTA CASA DE RIO GRANDE",'CALL SHEET'!$AB$2:$AB$560) | H27: =COUNTIFS('CALL SHEET'!$C$2:$C$560,"ASSOCIACAO DE CARIDADE SANTA CASA DE RIO GRANDE",'CALL SHEET'!$D$2:$D$560,"<>NEW") | I27: =COUNTIFS('CALL SHEET'!$C$2:$C$560,"ASSOCIACAO DE CARIDADE SANTA CASA DE RIO GRANDE",'CALL SHEET'!$D$2:$D$560,"INTERESTED")+COUNTIFS('CALL SHEET'!$C$2:$C$560,"ASSOCIACAO DE CARIDADE SANTA CASA DE RIO GRANDE",'CALL SHEET'!$D$2:$D$560,"DEAL")
A28: A — Plan approved / homologation | B28: =COUNTIF('CALL SHEET'!$U$2:$U$560,"A") | C28: =SUMIF('CALL SHEET'!$U$2:$U$560,"A",'CALL SHEET'!$AB$2:$AB$560) | E28: ADVOCACIA WANDERLEI DE PAULA BARRETO | F28: =COUNTIF('CALL SHEET'!$C$2:$C$560,"ADVOCACIA WANDERLEI DE PAULA BARRETO") | G28: =SUMIF('CALL SHEET'!$C$2:$C$560,"ADVOCACIA WANDERLEI DE PAULA BARRETO",'CALL SHEET'!$AB$2:$AB$560) | H28: =COUNTIFS('CALL SHEET'!$C$2:$C$560,"ADVOCACIA WANDERLEI DE PAULA BARRETO",'CALL SHEET'!$D$2:$D$560,"<>NEW") | I28: =COUNTIFS('CALL SHEET'!$C$2:$C$560,"ADVOCACIA WANDERLEI DE PAULA BARRETO",'CALL SHEET'!$D$2:$D$560,"INTERESTED")+COUNTIFS('CALL SHEET'!$C$2:$C$560,"ADVOCACIA WANDERLEI DE PAULA BARRETO",'CALL SHEET'!$D$2:$D$560,"DEAL")
A29: B — Live case, no plan document | B29: =COUNTIF('CALL SHEET'!$U$2:$U$560,"B") | C29: =SUMIF('CALL SHEET'!$U$2:$U$560,"B",'CALL SHEET'!$AB$2:$AB$560) | E29: NORTESUL COMERCIAL AGRICOLA LTDA EM RECUPERACAO JUDICIAL | F29: =COUNTIF('CALL SHEET'!$C$2:$C$560,"NORTESUL COMERCIAL AGRICOLA LTDA EM RECUPERACAO JUDICIAL") | G29: =SUMIF('CALL SHEET'!$C$2:$C$560,"NORTESUL COMERCIAL AGRICOLA LTDA EM RECUPERACAO JUDICIAL",'CALL SHEET'!$AB$2:$AB$560) | H29: =COUNTIFS('CALL SHEET'!$C$2:$C$560,"NORTESUL COMERCIAL AGRICOLA LTDA EM RECUPERACAO JUDICIAL",'CALL SHEET'!$D$2:$D$560,"<>NEW") | I29: =COUNTIFS('CALL SHEET'!$C$2:$C$560,"NORTESUL COMERCIAL AGRICOLA LTDA EM RECUPERACAO JUDICIAL",'CALL SHEET'!$D$2:$D$560,"INTERESTED")+COUNTIFS('CALL SHEET'!$C$2:$C$560,"NORTESUL COMERCIAL AGRICOLA LTDA EM RECUPERACAO JUDICIAL",'CALL SHEET'!$D$2:$D$560,"DEAL")
A30: C — Stale: >4 years since filing | B30: =COUNTIF('CALL SHEET'!$U$2:$U$560,"C") | C30: =SUMIF('CALL SHEET'!$U$2:$U$560,"C",'CALL SHEET'!$AB$2:$AB$560) | E30: CLUBE NAUTICO CAPIBARIBE - EM RECUPERACAO JUDICIAL | F30: =COUNTIF('CALL SHEET'!$C$2:$C$560,"CLUBE NAUTICO CAPIBARIBE - EM RECUPERACAO JUDICIAL") | G30: =SUMIF('CALL SHEET'!$C$2:$C$560,"CLUBE NAUTICO CAPIBARIBE - EM RECUPERACAO JUDICIAL",'CALL SHEET'!$AB$2:$AB$560) | H30: =COUNTIFS('CALL SHEET'!$C$2:$C$560,"CLUBE NAUTICO CAPIBARIBE - EM RECUPERACAO JUDICIAL",'CALL SHEET'!$D$2:$D$560,"<>NEW") | I30: =COUNTIFS('CALL SHEET'!$C$2:$C$560,"CLUBE NAUTICO CAPIBARIBE - EM RECUPERACAO JUDICIAL",'CALL SHEET'!$D$2:$D$560,"INTERESTED")+COUNTIFS('CALL SHEET'!$C$2:$C$560,"CLUBE NAUTICO CAPIBARIBE - EM RECUPERACAO JUDICIAL",'CALL SHEET'!$D$2:$D$560,"DEAL")
A31: D — Avoid: falência decreed, or | B31: =COUNTIF('CALL SHEET'!$U$2:$U$560,"D") | C31: =SUMIF('CALL SHEET'!$U$2:$U$560,"D",'CALL SHEET'!$AB$2:$AB$560) | E31: Conduscabos Brasil Indústria Comércio de | F31: =COUNTIF('CALL SHEET'!$C$2:$C$560,"Conduscabos Brasil Indústria Comércio de") | G31: =SUMIF('CALL SHEET'!$C$2:$C$560,"Conduscabos Brasil Indústria Comércio de",'CALL SHEET'!$AB$2:$AB$560) | H31: =COUNTIFS('CALL SHEET'!$C$2:$C$560,"Conduscabos Brasil Indústria Comércio de",'CALL SHEET'!$D$2:$D$560,"<>NEW") | I31: =COUNTIFS('CALL SHEET'!$C$2:$C$560,"Conduscabos Brasil Indústria Comércio de",'CALL SHEET'!$D$2:$D$560,"INTERESTED")+COUNTIFS('CALL SHEET'!$C$2:$C$560,"Conduscabos Brasil Indústria Comércio de",'CALL SHEET'!$D$2:$D$560,"DEAL")
A32: ? — Debtor could not be resolved | B32: =COUNTIF('CALL SHEET'!$U$2:$U$560,"?") | C32: =SUMIF('CALL SHEET'!$U$2:$U$560,"?",'CALL SHEET'!$AB$2:$AB$560) | E32: Grupo Arnon de Mello — Lindoso e Araujo | F32: =COUNTIF('CALL SHEET'!$C$2:$C$560,"Grupo Arnon de Mello — Lindoso e Araujo") | G32: =SUMIF('CALL SHEET'!$C$2:$C$560,"Grupo Arnon de Mello — Lindoso e Araujo",'CALL SHEET'!$AB$2:$AB$560) | H32: =COUNTIFS('CALL SHEET'!$C$2:$C$560,"Grupo Arnon de Mello — Lindoso e Araujo",'CALL SHEET'!$D$2:$D$560,"<>NEW") | I32: =COUNTIFS('CALL SHEET'!$C$2:$C$560,"Grupo Arnon de Mello — Lindoso e Araujo",'CALL SHEET'!$D$2:$D$560,"INTERESTED")+COUNTIFS('CALL SHEET'!$C$2:$C$560,"Grupo Arnon de Mello — Lindoso e Araujo",'CALL SHEET'!$D$2:$D$560,"DEAL")
E33: REAL DISTRIBUIDORA ÚNICA RIO COMÉRCIO DE REFRIGERAÇÃO LTDA | F33: =COUNTIF('CALL SHEET'!$C$2:$C$560,"REAL DISTRIBUIDORA ÚNICA RIO COMÉRCIO DE REFRIGERAÇÃO LTDA") | G33: =SUMIF('CALL SHEET'!$C$2:$C$560,"REAL DISTRIBUIDORA ÚNICA RIO COMÉRCIO DE REFRIGERAÇÃO LTDA",'CALL SHEET'!$AB$2:$AB$560) | H33: =COUNTIFS('CALL SHEET'!$C$2:$C$560,"REAL DISTRIBUIDORA ÚNICA RIO COMÉRCIO DE REFRIGERAÇÃO LTDA",'CALL SHEET'!$D$2:$D$560,"<>NEW") | I33: =COUNTIFS('CALL SHEET'!$C$2:$C$560,"REAL DISTRIBUIDORA ÚNICA RIO COMÉRCIO DE REFRIGERAÇÃO LTDA",'CALL SHEET'!$D$2:$D$560,"INTERESTED")+COUNTIFS('CALL SHEET'!$C$2:$C$560,"REAL DISTRIBUIDORA ÚNICA RIO COMÉRCIO DE REFRIGERAÇÃO LTDA",'CALL SHEET'!$D$2:$D$560,"DEAL")
A34: How to use: work the CALL SHEET top-down (it is sorted by our ágio). Set STATUS and NEXT DATE on every touch; this tab updates itself.
A35: Bands: A plan approved · B live · C stale · D avoid. Quotes are a model off the Assumptions tab; the FACE VALUE and the PROOF link are court data. | E35: BY STATE | F35: leads | G35: ágio (R$)
E36: SP | F36: =COUNTIF('CALL SHEET'!$AQ$2:$AQ$560,"SP") | G36: =SUMIF('CALL SHEET'!$AQ$2:$AQ$560,"SP",'CALL SHEET'!$AB$2:$AB$560)
E37: PR | F37: =COUNTIF('CALL SHEET'!$AQ$2:$AQ$560,"PR") | G37: =SUMIF('CALL SHEET'!$AQ$2:$AQ$560,"PR",'CALL SHEET'!$AB$2:$AB$560)
E38: SC | F38: =COUNTIF('CALL SHEET'!$AQ$2:$AQ$560,"SC") | G38: =SUMIF('CALL SHEET'!$AQ$2:$AQ$560,"SC",'CALL SHEET'!$AB$2:$AB$560)
E39: RS | F39: =COUNTIF('CALL SHEET'!$AQ$2:$AQ$560,"RS") | G39: =SUMIF('CALL SHEET'!$AQ$2:$AQ$560,"RS",'CALL SHEET'!$AB$2:$AB$560)
E40: PE | F40: =COUNTIF('CALL SHEET'!$AQ$2:$AQ$560,"PE") | G40: =SUMIF('CALL SHEET'!$AQ$2:$AQ$560,"PE",'CALL SHEET'!$AB$2:$AB$560)
E41: GO | F41: =COUNTIF('CALL SHEET'!$AQ$2:$AQ$560,"GO") | G41: =SUMIF('CALL SHEET'!$AQ$2:$AQ$560,"GO",'CALL SHEET'!$AB$2:$AB$560)
E42: MG | F42: =COUNTIF('CALL SHEET'!$AQ$2:$AQ$560,"MG") | G42: =SUMIF('CALL SHEET'!$AQ$2:$AQ$560,"MG",'CALL SHEET'!$AB$2:$AB$560)
E43: RJ | F43: =COUNTIF('CALL SHEET'!$AQ$2:$AQ$560,"RJ") | G43: =SUMIF('CALL SHEET'!$AQ$2:$AQ$560,"RJ",'CALL SHEET'!$AB$2:$AB$560)
E44: BA | F44: =COUNTIF('CALL SHEET'!$AQ$2:$AQ$560,"BA") | G44: =SUMIF('CALL SHEET'!$AQ$2:$AQ$560,"BA",'CALL SHEET'!$AB$2:$AB$560)
E45: AM | F45: =COUNTIF('CALL SHEET'!$AQ$2:$AQ$560,"AM") | G45: =SUMIF('CALL SHEET'!$AQ$2:$AQ$560,"AM",'CALL SHEET'!$AB$2:$AB$560)

Sheet CALL SHEET
A1: CREDITOR — company owed money | B1: AMOUNT OWED (R$) | C1: DEBTOR — company in RJ | D1: STATUS | E1: LAST TOUCH | F1: NEXT ACTION | G1: NEXT DATE | H1: NOTES | I1: DECISION MAKER | J1: Role | K1: Phone 1 | L1: Phone 2 | M1: Mobile (Apollo) | N1: Email | O1: Email 2 | P1: BACKUP CONTACT | Q1: Backup role | R1: Backup phone | S1: Backup email | T1: FACE VALUE (as printed) | U1: DEBTOR BAND | V1: Exp. recovery % | W1: Years to payment | X1: FUND PRICE @ IRR (R$) | Y1: cents | Z1: OUR QUOTE (R$) | AA1: cents | AB1: OUR ÁGIO (R$) | AC1: Ágio pts of face | AD1: Plan status | AE1: PROOF: source document | AF1: Page / row | AG1: Value as printed | AH1: Which list | AI1: Published | AJ1: Reconciled | AK1: Case number | AL1: Court | AM1: Stage | AN1: Filed | AO1: Band reason | AP1: City | AQ1: UF | AR1: Sector | AS1: Size | AT1: Seller fit | AU1: CNPJ root | AV1: Claims | AW1: Flags
A2: DM CONSTRUTORA DE OBRAS LTDA | B2: 1.7805218e+08 | C2: KADIMA EMPREENDIMENTOS E PARTICIPACOES EM RECUPERACAO JUDICIAL | D2: NEW | I2: Giovano Fantin | J2: VP | K2: (41) 3313-8000 | L2: (41) 3313-8090 | N2: giovano@dmconstrutora.com.br | T2: 1.7805218e+08 | U2: B | V2: =IFERROR(VLOOKUP(U2,Assumptions!$A$7:$D$11,2,FALSE),0) | W2: =MAX(0.5,IFERROR(VLOOKUP(U2,Assumptions!$A$7:$D$11,3,FALSE),3)+IFERROR(VLOOKUP(U2,Assumptions!$A$7:$D$11,4,FALSE),8)/2-IF(AN2="",0,YEAR(TODAY())-AN2)) | X2: =T2*V2/(1+Assumptions!$B$3)^W2 | Y2: =IF(T2=0,"",ROUND(X2/T2*100,1)) | Z2: =X2*Assumptions!$B$4 | AA2: =IF(T2=0,"",ROUND(Z2/T2*100,1)) | AB2: =X2-Z2 | AC2: =IF(T2=0,"",ROUND((X2-Z2)/T2*100,1)) | AD2: ESTIMATED | AE2: https://marquesadmjudicial.com.br/sgc/download.php?file=files/processo_documento/processo_documento19270817122025_1_.pdf&nome=Relação Nominal de Credores AJ | AF2: p4 r8 | AG2: p4: R$ 178.052.183,86 | AH2: AJ_LIST | AI2: 2025-12-17 | AJ2: OK | AK2: 0016033-22.2025.8.16.0017 | AL2: TJPR | AM2: ACTIVE | AN2: 2025 | AO2: live case, no plan document yet | AP2: CURITIBA | AQ2: PR | AR2: Construção de rodovias e ferrovias | AS2: DEMAIS | AT2: MID-MARKET | AU2: 76483726 | AV2: 1 | AW2: ROWS:p4r8
A3: PETROLEO BRASILEIRO S A PETROBRAS | B3: 3.3005476e+08 | C3: EGESA ENGENHARIA S/A (Consórcio ETDI) | D3: NEW | I3: MAGDA MARIA DE REGINA CHAMBRIARD | J3: Presidente | K3: (21) 2166-0000 | P3: ANGELICA GARCIA COBAS LAUREANO | Q3: Diretor | R3: (21) 2166-0000 | T3: 3.3005476e+08 | U3: ? | V3: =IFERROR(VLOOKUP(U3,Assumptions!$A$7:$D$11,2,FALSE),0) | W3: =MAX(0.5,IFERROR(VLOOKUP(U3,Assumptions!$A$7:$D$11,3,FALSE),3)+IFERROR(VLOOKUP(U3,Assumptions!$A$7:$D$11,4,FALSE),8)/2-IF(AN3="",0,YEAR(TODAY())-AN3)) | X3: =T3*V3/(1+Assumptions!$B$3)^W3 | Y3: =IF(T3=0,"",ROUND(X3/T3*100,1)) | Z3: =X3*Assumptions!$B$4 | AA3: =IF(T3=0,"",ROUND(Z3/T3*100,1)) | AB3: =X3-Z3 | AC3: =IF(T3=0,"",ROUND((X3-Z3)/T3*100,1)) | AD3: UNKNOWN | AE3: https://scalzilliaj.com.br/sgc/download.php?file=files/processo_documento/processo_documento09514021082025_1_.pdf&nome=04 - Relação de credores das Recuperandas | AF3: p71 r9 | AG3: p71: R$ 330.054.762,86 | AH3: DEBTOR_LIST | AJ3: OK | AK3: (not printed) | AO3: RJ case number not identified on the document | AP3: RIO DE JANEIRO | AQ3: RJ | AR3: Extração de petróleo e gás natural | AS3: DEMAIS | AT3: LARGE CORP | AU3: 33000167 | AV3: 1 | AW3: ROWS:p71r9 VALUE_COL:Valor_Atualizado CASE_NUMBER_CORRECTED
A4: TAG INDUSTRIA E LAMINACAO LTDA | B4: 64713515 | C4: Conduscabos Brasil Indústria Comércio de | D4: NEW | I4: TIAGO RODRIGO DETTILIO | J4: Administrador | K4: (11) 4463-4833 | P4: WEBER MICAEL DA SILVA | Q4: Administrador | R4: (11) 4463-4833 | T4: 64713515 | U4: B | V4: =IFERROR(VLOOKUP(U4,Assumptions!$A$7:$D$11,2,FALSE),0) | W4: =MAX(0.5,IFERROR(VLOOKUP(U4,Assumptions!$A$7:$D$11,3,FALSE),3)+IFERROR(VLOOKUP(U4,Assumptions!$A$7:$D$11,4,FALSE),8)/2-IF(AN4="",0,YEAR(TODAY())-AN4)) | X4: =T4*V4/(1+Assumptions!$B$3)^W4 | Y4: =IF(T4=0,"",ROUND(X4/T4*100,1)) | Z4: =X4*Assumptions!$B$4 | AA4: =IF(T4=0,"",ROUND(Z4/T4*100,1)) | AB4: =X4-Z4 | AC4: =IF(T4=0,"",ROUND((X4-Z4)/T4*100,1)) | AD4: ESTIMATED | AE4: https://assistjud.com.br/wp-content/uploads/elementor/forms/65098c80a5824.pdf | AF4: p10 r4; p19 r8 | AG4: p10: R$ 32.731.819,08; p19: R$ 31.981.695,98 | AH4: AJ_LIST | AI4: 2023-09-18 | AJ4: OK_NO_TOTALS | AK4: 8005129-09.2023.8.05.0039 | AL4: TJBA | AM4: ACTIVE | AN4: 2023 | AO4: live case, no plan document yet | AP4: SAO PAULO | AQ4: SP | AR4: Outras atividades profissionais, científicas e técnicas não especificadas anteriormente | AS4: DEMAIS | AT4: MID-MARKET | AU4: 33233778 | AV4: 2 | AW4: ROWS:p10r4,p19r8 UNRECONCILED_SOURCE
A5: COMPANHIA ESTADUAL DE DISTRIBUICAO DE ENERGIA ELETRICA - CEEE-D | B5: 31446844 | C5: ASSOCIACAO DE CARIDADE SANTA CASA DE RIO GRANDE | D5: NEW | I5: Willian Maeda | J5: Gerente de Planejamento e Controle Financeiro - CEEE Equatorial | K5: (98) 3217-8000 | N5: willian.maeda@equatorialenergia.com.br | P5: Nairton Iwen | Q5: Controller IOP | T5: 31446844 | U5: B | V5: =IFERROR(VLOOKUP(U5,Assumptions!$A$7:$D$11,2,FALSE),0) | W5: =MAX(0.5,IFERROR(VLOOKUP(U5,Assumptions!$A$7:$D$11,3,FALSE),3)+IFERROR(VLOOKUP(U5,Assumptions!$A$7:$D$11,4,FALSE),8)/2-IF(AN5="",0,YEAR(TODAY())-AN5)) | X5: =T5*V5/(1+Assumptions!$B$3)^W5 | Y5: =IF(T5=0,"",ROUND(X5/T5*100,1)) | Z5: =X5*Assumptions!$B$4 | AA5: =IF(T5=0,"",ROUND(Z5/T5*100,1)) | AB5: =X5-Z5 | AC5: =IF(T5=0,"",ROUND((X5-Z5)/T5*100,1)) | AD5: ESTIMATED | AE5: https://scalzilliaj.com.br/sgc/download.php?file=files/processo_documento/processo_documento09120721032023_1_.pdf&nome=15 - Edital do art. 7º, §2º e 53 da Lei 11.101/2005 (segunda lista de credores e recebimento do plano)) | AF5: p26 r26 | AG5: p26: R$ 31.446.843,91 | AH5: AJ_LIST | AI5: 2023-03-21 | AJ5: OK_NO_TOTALS | AK5: 5012306-16.2022.8.21.0023 | AL5: TJRS | AM5: ACTIVE | AN5: 2022 | AO5: live case, no plan document yet | AP5: PORTO ALEGRE | AQ5: RS | AR5: Distribuição de energia elétrica | AS5: DEMAIS | AT5: LARGE CORP | AU5: 08467115 | AV5: 1 | AW5: ROWS:p26r26 UNRECONCILED_SOURCE
A6: HYPERA S.A. | B6: 25912508 | C6: VEV COMERCIO DE MEDICAMENTOS LTDA EM RECUPERACAO JUDICIAL | D6: NEW | I6: BRENO TOLEDO PIRES DE OLIVEIRA | J6: Presidente | K6: (62) 3878-8150 | P6: ADALMARIO GHOVATTO SATHELER DO COUTO | Q6: Diretor | R6: (62) 3878-8150 | T6: 25912508 | U6: B | V6: =IFERROR(VLOOKUP(U6,Assumptions!$A$7:$D$11,2,FALSE),0) | W6: =MAX(0.5,IFERROR(VLOOKUP(U6,Assumptions!$A$7:$D$11,3,FALSE),3)+IFERROR(VLOOKUP(U6,Assumptions!$A$7:$D$11,4,FALSE),8)/2-IF(AN6="",0,YEAR(TODAY())-AN6)) | X6: =T6*V6/(1+Assumptions!$B$3)^W6 | Y6: =IF(T6=0,"",ROUND(X6/T6*100,1)) | Z6: =X6*Assumptions!$B$4 | AA6: =IF(T6=0,"",ROUND(Z6/T6*100,1)) | AB6: =X6-Z6 | AC6: =IF(T6=0,"",ROUND((X6-Z6)/T6*100,1)) | AD6: ESTIMATED | AE6: https://marquesadmjudicial.com.br/sgc/download.php?file=files/processo_documento/processo_documento15293208032024_1_.pdf&nome=Relação Nominal de Credores da AJ-Sintética | AF6: p26 r9 | AG6: p26: R$ 25.912.507,68 | AH6: AJ_LIST | AI6: 2023-03-02 | AJ6: QUARANTINED | AK6: 0005010-98.2023.8.16.0001 | AL6: TJPR | AM6: ACTIVE | AN6: 2023 | AO6: live case, no plan document yet | AP6: SAO PAULO | AQ6: SP | AR6: Comércio atacadista de medicamentos e drogas de uso humano | AS6: DEMAIS | AT6: LARGE CORP | AU6: 02932074 | AV6: 1 | AW6: PARTIAL_DOC_CLASS_III_RECONCILED ROWS:p26r9
A7: COMPANHIA RIOGRANDENSE DE SANEAMENTO - CORSAN | B7: 18555955 | C7: ASSOCIACAO DE CARIDADE SANTA CASA DE RIO GRANDE | D7: NEW | I7: Luiz Pereira | J7: Financial Planning Manager | K7: (05) 1215-5789 | O7: rafaela.milione@corsan.com.br | P7: Rafaela Milione | Q7: Especialista de Tesouraria | S7: rafaela.milione@corsan.com.br | T7: 18555955 | U7: B | V7: =IFERROR(VLOOKUP(U7,Assumptions!$A$7:$D$11,2,FALSE),0) | W7: =MAX(0.5,IFERROR(VLOOKUP(U7,Assumptions!$A$7:$D$11,3,FALSE),3)+IFERROR(VLOOKUP(U7,Assumptions!$A$7:$D$11,4,FALSE),8)/2-IF(AN7="",0,YEAR(TODAY())-AN7)) | X7: =T7*V7/(1+Assumptions!$B$3)^W7 | Y7: =IF(T7=0,"",ROUND(X7/T7*100,1)) | Z7: =X7*Assumptions!$B$4 | AA7: =IF(T7=0,"",ROUND(Z7/T7*100,1)) | AB7: =X7-Z7 | AC7: =IF(T7=0,"",ROUND((X7-Z7)/T7*100,1)) | AD7: ESTIMATED | AE7: https://scalzilliaj.com.br/sgc/download.php?file=files/processo_documento/processo_documento09120721032023_1_.pdf&nome=15 - Edital do art. 7º, §2º e 53 da Lei 11.101/2005 (segunda lista de credores e recebimento do plano)) | AF7: p26 r27 | AG7: p26: R$ 18.555.954,55 | AH7: AJ_LIST | AI7: 2023-03-21 | AJ7: OK_NO_TOTALS | AK7: 5012306-16.2022.8.21.0023 | AL7: TJRS | AM7: ACTIVE | AN7: 2022 | AO7: live case, no plan document yet | AP7: PORTO ALEGRE | AQ7: RS | AR7: Captação, tratamento e distribuição de água | AS7: DEMAIS | AT7: LARGE CORP | AU7: 92802784 | AV7: 1 | AW7: ROWS:p26r27 UNRECONCILED_SOURCE
A8: ADLIM-TERCEIRIZACAO EM SERVICOS LTDA - EM RECUPERACAO JUDICIAL | B8: 20647588 | C8: GRUPO ADLIM – LRF Líderes em Recuperação Judicial e Falência | D8: NEW | I8: Santana Leoterio | J8: Analyst | N8: santana.leoterio@adlim.com.br | T8: 20647588 | U8: B | V8: =IFERROR(VLOOKUP(U8,Assumptions!$A$7:$D$11,2,FALSE),0) | W8: =MAX(0.5,IFERROR(VLOOKUP(U8,Assumptions!$A$7:$D$11,3,FALSE),3)+IFERROR(VLOOKUP(U8,Assumptions!$A$7:$D$11,4,FALSE),8)/2-IF(AN8="",0,YEAR(TODAY())-AN8)) | X8: =T8*V8/(1+Assumptions!$B$3)^W8 | Y8: =IF(T8=0,"",ROUND(X8/T8*100,1)) | Z8: =X8*Assumptions!$B$4 | AA8: =IF(T8=0,"",ROUND(Z8/T8*100,1)) | AB8: =X8-Z8 | AC8: =IF(T8=0,"",ROUND((X8-Z8)/T8*100,1)) | AD8: ESTIMATED | AE8: https://lrflideres.com.br/wp-content/plugins/download-attachments/includes/download.php?id=6051 | AF8: p85 r37; p97 r26 | AG8: p85: R$ 13674501,07; p97: R$ 6973087,07 | AH8: AJ_LIST | AI8: 2024-08-12 | AJ8: QUARANTINED | AK8: 0019761-43.2024.8.17.2001 | AL8: TJPE | AM8: ACTIVE | AN8: 2024 | AO8: live case, no plan document yet | AP8: BEZERROS | AQ8: PE | AR8: Fornecimento e gestão de recursos humanos para terceiros | AS8: DEMAIS | AT8: MID-MARKET | AU8: 11436813 | AV8: 2 | AW8: PARTIAL_DOC_CLASS_III_RECONCILED ROWS:p85r37,p97r26
A9: IBIPORA NEGOCIOS IMOBILIARIOS S.A. | B9: 45075483 | C9: EGESA ENGENHARIA S/A (Consórcio ETDI) | D9: NEW | I9: JOSE JULIO COSTA NETO | J9: Presidente | K9: (31) 3586-9418 | P9: BRUNA GODINHO RESENDE FERREIRA | Q9: Diretor | R9: (31) 3586-9418 | T9: 45075483 | U9: ? | V9: =IFERROR(VLOOKUP(U9,Assumptions!$A$7:$D$11,2,FALSE),0) | W9: =MAX(0.5,IFERROR(VLOOKUP(U9,Assumptions!$A$7:$D$11,3,FALSE),3)+IFERROR(VLOOKUP(U9,Assumptions!$A$7:$D$11,4,FALSE),8)/2-IF(AN9="",0,YEAR(TODAY())-AN9)) | X9: =T9*V9/(1+Assumptions!$B$3)^W9 | Y9: =IF(T9=0,"",ROUND(X9/T9*100,1)) | Z9: =X9*Assumptions!$B$4 | AA9: =IF(T9=0,"",ROUND(Z9/T9*100,1)) | AB9: =X9-Z9 | AC9: =IF(T9=0,"",ROUND((X9-Z9)/T9*100,1)) | AD9: UNKNOWN | AE9: https://scalzilliaj.com.br/sgc/download.php?file=files/processo_documento/processo_documento09514021082025_1_.pdf&nome=04 - Relação de credores das Recuperandas | AF9: p68 r4 | AG9: p68: R$ 45.075.482,57 | AH9: DEBTOR_LIST | AJ9: OK | AK9: (not printed) | AO9: RJ case number not identified on the document | AP9: NOVA LIMA | AQ9: MG | AR9: Compra e venda de imóveis próprios | AS9: DEMAIS | AT9: MID-MARKET | AU9: 19256534 | AV9: 1 | AW9: ROWS:p68r4 VALUE_COL:Valor_Atualizado CASE_NUMBER_CORRECTED
A10: DC COMERCIO, REPRESENTACOES, INVESTIMENTOS E PARTICIPACOES LTDA. | B10: 11125000 | C10: R W CONSTRUCOES LTDA | D10: NEW | I10: FERNANDO MELO CATAO | J10: Sócio-Administrador | K10: (81) 3032-8400 | L10: (81) 3419-8550 | T10: 11125000 | U10: B | V10: =IFERROR(VLOOKUP(U10,Assumptions!$A$7:$D$11,2,FALSE),0) | W10: =MAX(0.5,IFERROR(VLOOKUP(U10,Assumptions!$A$7:$D$11,3,FALSE),3)+IFERROR(VLOOKUP(U10,Assumptions!$A$7:$D$11,4,FALSE),8)/2-IF(AN10="",0,YEAR(TODAY())-AN10)) | X10: =T10*V10/(1+Assumptions!$B$3)^W10 | Y10: =IF(T10=0,"",ROUND(X10/T10*100,1)) | Z10: =X10*Assumptions!$B$4 | AA10: =IF(T10=0,"",ROUND(Z10/T10*100,1)) | AB10: =X10-Z10 | AC10: =IF(T10=0,"",ROUND((X10-Z10)/T10*100,1)) | AD10: ESTIMATED | AE10: https://lrflideres.com.br/wp-content/plugins/download-attachments/includes/download.php?id=4023 | AF10: p4 r68; p7 r92; p9 r68 | AG10: p4: R$ 1.150.000,00; p7: R$ 9.715.000,00; p9: R$ 260.000,00 | AH10: DEBTOR_LIST | AJ10: QUARANTINED | AK10: 0002484-82.2022.8.17.2001 | AL10: TJPE | AM10: ACTIVE | AN10: 2022 | AO10: live case, no plan document yet | AP10: RECIFE | AQ10: PE | AR10: Aluguel de imóveis próprios | AS10: DEMAIS | AT10: MID-MARKET | AU10: 09036221 | AV10: 3 | AW10: PARTIAL_DOC_CLASS_III_RECONCILED ROWS:p4r68,p7r92,p9r68
A11: GREE ELECTRIC APPLIANCES DO BRASIL LTDA. | B11: 13499976 | C11: REAL DISTRIBUIDORA ÚNICA RIO COMÉRCIO DE REFRIGERAÇÃO LTDA | D11: NEW | I11: Nicolaus Cheng | J11: Commercial Director | K11: (92) 2123-6900 | N11: nicolaus@gree.com.br | O11: carlos.murano@gree-am.com.br | P11: Carlos Murano | Q11: Executive Sales Manager | S11: carlos.murano@gree-am.com.br | T11: 13499976 | U11: B | V11: =IFERROR(VLOOKUP(U11,Assumptions!$A$7:$D$11,2,FALSE),0) | W11: =MAX(0.5,IFERROR(VLOOKUP(U11,Assumptions!$A$7:$D$11,3,FALSE),3)+IFERROR(VLOOKUP(U11,Assumptions!$A$7:$D$11,4,FALSE),8)/2-IF(AN11="",0,YEAR(TODAY())-AN11)) | X11: =T11*V11/(1+Assumptions!$B$3)^W11 | Y11: =IF(T11=0,"",ROUND(X11/T11*100,1)) | Z11: =X11*Assumptions!$B$4 | AA11: =IF(T11=0,"",ROUND(Z11/T11*100,1)) | AB11: =X11-Z11 | AC11: =IF(T11=0,"",ROUND((X11-Z11)/T11*100,1)) | AD11: UNKNOWN | AE11: https://inova-aj.com.br/wp-content/uploads/2026/08/1a-Relacao-de-Credores-Real.pdf | AF11: p1 r32 | AG11: p1: R$ 13.499.976,37 | AH11: AJ_LIST | AI11: 2023-06-05 | AJ11: OK | AK11: 0873061-47.2023.8.19.0001 | AL11: TJ | AN11: 2023 | AO11: live case, no plan document yet | AP11: MANAUS | AQ11: AM | AR11: Fabricação de aparelhos e equipamentos de ar condicionado para uso não-industrial | AS11: DEMAIS | AT11: LARGE CORP | AU11: 03519135 | AV11: 1 | AW11: ALT_VALUE:R$9.815.941,50 ROWS:p1r32
A12: LOUIS DREYFUS COMPANY SUCOS S.A | B12: 13129218 | D12: NEW | I12: Paula Peixoto | J12: Gerente Adm Controladoria - Originação Sucos | K12: (11) 3039-7160 | L12: (13) 2127-9893 | N12: paula.peixoto@ldc.com | O12: bruno.nunes@ldc.com | P12: Bruno Nunes | Q12: Gerente Executivo de Engenharia & Projetos - Plataforma Sucos | S12: bruno.nunes@ldc.com | T12: 13129218 | U12: C | V12: =IFERROR(VLOOKUP(U12,Assumptions!$A$7:$D$11,2,FALSE),0) | W12: =MAX(0.5,IFERROR(VLOOKUP(U12,Assumptions!$A$7:$D$11,3,FALSE),3)+IFERROR(VLOOKUP(U12,Assumptions!$A$7:$D$11,4,FALSE),8)/2-IF(AN12="",0,YEAR(TODAY())-AN12)) | X12: =T12*V12/(1+Assumptions!$B$3)^W12 | Y12: =IF(T12=0,"",ROUND(X12/T12*100,1)) | Z12: =X12*Assumptions!$B$4 | AA12: =IF(T12=0,"",ROUND(Z12/T12*100,1)) | AB12: =X12-Z12 | AC12: =IF(T12=0,"",ROUND((X12-Z12)/T12*100,1)) | AD12: UNKNOWN | AE12: https://violet-wolf-754008.hostingersite.com/wp-content/uploads/2022/10/Primeiro-Edital-de-Credores-Integral-com-creditos.pdf | AF12: p4 r1 | AG12: p4: R$ 13.129.217,80 | AH12: UNKNOWN | AJ12: OK | AK12: 0000941-21.2012.8.26.0101 | AL12: TJ | AN12: 2012 | AO12: 14y since filing, no plan document | AP12: SAO PAULO | AQ12: SP | AR12: Fabricação de sucos concentrados de frutas, hortaliças e legumes | AS12: DEMAIS | AT12: LARGE CORP | AU12: 00831373 | AV12: 1 | AW12: ROWS:p4r1 VALUE_COL:Valor
A13: AGUIA SERVICOS DE VIGILANCIA LTDA - EM RECUPERACAO JUDICIAL | B13: 13645092 | C13: GRUPO ADLIM – LRF Líderes em Recuperação Judicial e Falência | D13: NEW | I13: JONAS ALVARENGA DA SILVA | J13: Sócio-Administrador | K13: (81) 3252-6115 | L13: (81) 3252-6117 | T13: 13645092 | U13: B | V13: =IFERROR(VLOOKUP(U13,Assumptions!$A$7:$D$11,2,FALSE),0) | W13: =MAX(0.5,IFERROR(VLOOKUP(U13,Assumptions!$A$7:$D$11,3,FALSE),3)+IFERROR(VLOOKUP(U13,Assumptions!$A$7:$D$11,4,FALSE),8)/2-IF(AN13="",0,YEAR(TODAY())-AN13)) | X13: =T13*V13/(1+Assumptions!$B$3)^W13 | Y13: =IF(T13=0,"",ROUND(X13/T13*100,1)) | Z13: =X13*Assumptions!$B$4 | AA13: =IF(T13=0,"",ROUND(Z13/T13*100,1)) | AB13: =X13-Z13 | AC13: =IF(T13=0,"",ROUND((X13-Z13)/T13*100,1)) | AD13: ESTIMATED | AE13: https://lrflideres.com.br/wp-content/plugins/download-attachments/includes/download.php?id=6051 | AF13: p97 r27 | AG13: p97: R$ 13645091,92 | AH13: AJ_LIST | AI13: 2024-08-12 | AJ13: QUARANTINED | AK13: 0019761-43.2024.8.17.2001 | AL13: TJPE | AM13: ACTIVE | AN13: 2024 | AO13: live case, no plan document yet | AP13: RECIFE | AQ13: PE | AR13: Atividades de vigilância e segurança privada | AS13: DEMAIS | AT13: MID-MARKET | AU13: 11516861 | AV13: 1 | AW13: PARTIAL_DOC_CLASS_III_RECONCILED ROWS:p97r27
A14: SANDOZ DO BRASIL INDUSTRIA FARMACEUTICA LTDA. | B14: 10696834 | C14: VEV COMERCIO DE MEDICAMENTOS LTDA EM RECUPERACAO JUDICIAL | D14: NEW | I14: BRUNO PETENUCI | J14: Administrador | K14: (43) 3174-8000 | P14: DANIELA DE ALMEIDA COUTO BONCIANI | Q14: Administrador | R14: (43) 3174-8000 | T14: 10696834 | U14: B | V14: =IFERROR(VLOOKUP(U14,Assumptions!$A$7:$D$11,2,FALSE),0) | W14: =MAX(0.5,IFERROR(VLOOKUP(U14,Assumptions!$A$7:$D$11,3,FALSE),3)+IFERROR(VLOOKUP(U14,Assumptions!$A$7:$D$11,4,FALSE),8)/2-IF(AN14="",0,YEAR(TODAY())-AN14)) | X14: =T14*V14/(1+Assumptions!$B$3)^W14 | Y14: =IF(T14=0,"",ROUND(X14/T14*100,1)) | Z14: =X14*Assumptions!$B$4 | AA14: =IF(T14=0,"",ROUND(Z14/T14*100,1)) | AB14: =X14-Z14 | AC14: =IF(T14=0,"",ROUND((X14-Z14)/T14*100,1)) | AD14: ESTIMATED | AE14: https://marquesadmjudicial.com.br/sgc/download.php?file=files/processo_documento/processo_documento15293208032024_1_.pdf&nome=Relação Nominal de Credores da AJ-Sintética | AF14: p31 r4 | AG14: p31: R$ 10.696.833,99 | AH14: AJ_LIST | AI14: 2023-03-02 | AJ14: QUARANTINED | AK14: 0005010-98.2023.8.16.0001 | AL14: TJPR | AM14: ACTIVE | AN14: 2023 | AO14: live case, no plan document yet | AP14: CAMBE | AQ14: PR | AR14: Fabricação de medicamentos alopáticos para uso humano | AS14: DEMAIS | AT14: LARGE CORP | AU14: 61286647 | AV14: 1 | AW14: PARTIAL_DOC_CLASS_III_RECONCILED ROWS:p31r4
A15: BASTON INDUSTRIA DE AEROSSOIS LTDA | B15: 10636330 | C15: VEV COMERCIO DE MEDICAMENTOS LTDA EM RECUPERACAO JUDICIAL | D15: NEW | I15: Ronaldo Santos | J15: Chief Financial Officer | K15: (42) 3252-8120 | L15: (42) 3252-1705 | O15: filipe.lusana@baston.com.br | P15: Filipe Lusana | Q15: Vice Presidente Comercial | S15: filipe.lusana@baston.com.br | T15: 10636330 | U15: B | V15: =IFERROR(VLOOKUP(U15,Assumptions!$A$7:$D$11,2,FALSE),0) | W15: =MAX(0.5,IFERROR(VLOOKUP(U15,Assumptions!$A$7:$D$11,3,FALSE),3)+IFERROR(VLOOKUP(U15,Assumptions!$A$7:$D$11,4,FALSE),8)/2-IF(AN15="",0,YEAR(TODAY())-AN15)) | X15: =T15*V15/(1+Assumptions!$B$3)^W15 | Y15: =IF(T15=0,"",ROUND(X15/T15*100,1)) | Z15: =X15*Assumptions!$B$4 | AA15: =IF(T15=0,"",ROUND(Z15/T15*100,1)) | AB15: =X15-Z15 | AC15: =IF(T15=0,"",ROUND((X15-Z15)/T15*100,1)) | AD15: ESTIMATED | AE15: https://marquesadmjudicial.com.br/sgc/download.php?file=files/processo_documento/processo_documento15293208032024_1_.pdf&nome=Relação Nominal de Credores da AJ-Sintética | AF15: p21 r8 | AG15: p21: R$ 10.636.330,31 | AH15: AJ_LIST | AI15: 2023-03-02 | AJ15: QUARANTINED | AK15: 0005010-98.2023.8.16.0001 | AL15: TJPR | AM15: ACTIVE | AN15: 2023 | AO15: live case, no plan document yet | AP15: PALMEIRA | AQ15: PR | AR15: Fabricação de outros produtos químicos não especificados anteriormente | AS15: DEMAIS | AT15: LARGE CORP | AU15: 05855974 | AV15: 1 | AW15: PARTIAL_DOC_CLASS_III_RECONCILED ROWS:p21r8
A16: SPC BRASIL S.A. | B16: 18875474 | C16: E FALENCIA | D16: NEW | I16: Yago Nunes | J16: Analista de Controladoria e Pricing Sênior | K16: (11) 3549-6800 | N16: yago.nunes@spcbrasil.com.br | O16: marcio.bauer@spcbrasil.com.br | P16: Marcio Bauer | Q16: Head Comercial Sul no SPC Brasil | S16: marcio.bauer@spcbrasil.com.br | T16: 18875474 | U16: B | V16: =IFERROR(VLOOKUP(U16,Assumptions!$A$7:$D$11,2,FALSE),0) | W16: =MAX(0.5,IFERROR(VLOOKUP(U16,Assumptions!$A$7:$D$11,3,FALSE),3)+IFERROR(VLOOKUP(U16,Assumptions!$A$7:$D$11,4,FALSE),8)/2-IF(AN16="",0,YEAR(TODAY())-AN16)) | X16: =T16*V16/(1+Assumptions!$B$3)^W16 | Y16: =IF(T16=0,"",ROUND(X16/T16*100,1)) | Z16: =X16*Assumptions!$B$4 | AA16: =IF(T16=0,"",ROUND(Z16/T16*100,1)) | AB16: =X16-Z16 | AC16: =IF(T16=0,"",ROUND((X16-Z16)/T16*100,1)) | AD16: ESTIMATED | AE16: https://recuperasolucoes.com/wp-content/plugins/download-attachments/includes/download.php?id=1597 | AF16: p13 r8 | AG16: p13: R$ 18.875.473,82 | AH16: DEBTOR_LIST | AI16: 2026-05-21 | AJ16: OK | AK16: 0001639-09.2026.8.17.2810 | AL16: TJPE | AM16: ACTIVE | AN16: 2026 | AO16: live case, no plan document yet | AP16: BARUERI | AQ16: SP | AR16: Portais, provedores de conteúdo e outros serviços de informação na internet | AS16: DEMAIS | AT16: MID-MARKET | AU16: 29341643 | AV16: 1 | AW16: ROWS:p13r8
A17: DANONE LTDA | B17: 9093937.7 | C17: VEV COMERCIO DE MEDICAMENTOS LTDA EM RECUPERACAO JUDICIAL | D17: NEW | I17: GEOVANI VIEIRA MANZANO | J17: Administrador | K17: (35) 3729-7901 | P17: TIAGO CARNEIRO DOS SANTOS | Q17: Administrador | R17: (35) 3729-7901 | T17: 9093937.7 | U17: B | V17: =IFERROR(VLOOKUP(U17,Assumptions!$A$7:$D$11,2,FALSE),0) | W17: =MAX(0.5,IFERROR(VLOOKUP(U17,Assumptions!$A$7:$D$11,3,FALSE),3)+IFERROR(VLOOKUP(U17,Assumptions!$A$7:$D$11,4,FALSE),8)/2-IF(AN17="",0,YEAR(TODAY())-AN17)) | X17: =T17*V17/(1+Assumptions!$B$3)^W17 | Y17: =IF(T17=0,"",ROUND(X17/T17*100,1)) | Z17: =X17*Assumptions!$B$4 | AA17: =IF(T17=0,"",ROUND(Z17/T17*100,1)) | AB17: =X17-Z17 | AC17: =IF(T17=0,"",ROUND((X17-Z17)/T17*100,1)) | AD17: ESTIMATED | AE17: https://marquesadmjudicial.com.br/sgc/download.php?file=files/processo_documento/processo_documento15293208032024_1_.pdf&nome=Relação Nominal de Credores da AJ-Sintética | AF17: p24 r6 | AG17: p24: R$ 9.093.937,71 | AH17: AJ_LIST | AI17: 2023-03-02 | AJ17: QUARANTINED | AK17: 0005010-98.2023.8.16.0001 | AL17: TJPR | AM17: ACTIVE | AN17: 2023 | AO17: live case, no plan document yet | AP17: SAO PAULO | AQ17: SP | AR17: Fabricação de laticínios | AS17: DEMAIS | AT17: LARGE CORP | AU17: 23643315 | AV17: 1 | AW17: PARTIAL_DOC_CLASS_III_RECONCILED ROWS:p24r6
A18: VINICOLA CAMPESTRE LTDA | B18: 13980346 | C18: ARRUDA & MELO COMERCIO E DISTRIBUICAO DE ALIMENTOS E BEBIDAS LTDA | D18: NEW | I18: Carlos Quintus | J18: Commercial Director | K18: (54) 3511-6050 | L18: (54) 3511-6052 | N18: carlos.quintus@pergola.com.br | P18: Camila Treptow | Q18: Financial Analyst | T18: 13980346 | U18: B | V18: =IFERROR(VLOOKUP(U18,Assumptions!$A$7:$D$11,2,FALSE),0) | W18: =MAX(0.5,IFERROR(VLOOKUP(U18,Assumptions!$A$7:$D$11,3,FALSE),3)+IFERROR(VLOOKUP(U18,Assumptions!$A$7:$D$11,4,FALSE),8)/2-IF(AN18="",0,YEAR(TODAY())-AN18)) | X18: =T18*V18/(1+Assumptions!$B$3)^W18 | Y18: =IF(T18=0,"",ROUND(X18/T18*100,1)) | Z18: =X18*Assumptions!$B$4 | AA18: =IF(T18=0,"",ROUND(Z18/T18*100,1)) | AB18: =X18-Z18 | AC18: =IF(T18=0,"",ROUND((X18-Z18)/T18*100,1)) | AD18: ESTIMATED | AE18: https://diligence.adm.br/wp-content/uploads/2025/06/Edital-1a-Lista-de-Credores.pdf | AF18: p5 r60; p5 r61 | AG18: p5: R$ 4.421.862,65; p5: R$ 9.558.482,85 | AH18: DEBTOR_LIST | AI18: 2025-06-10 | AJ18: OK | AK18: 0008526-45.2025.8.17.2001 | AL18: TJPE | AM18: ACTIVE | AN18: 2025 | AO18: live case, no plan document yet | AP18: CAMPESTRE DA SERRA | AQ18: RS | AR18: Fabricação de vinho | AS18: DEMAIS | AT18: LARGE CORP | AU18: 98521909 | AV18: 2 | AW18: ROWS:p5r60,p5r61
A19: CLIMAZON INDUSTRIAL LTDA | B19: 8012248.6 | C19: REAL DISTRIBUIDORA ÚNICA RIO COMÉRCIO DE REFRIGERAÇÃO LTDA | D19: NEW | I19: ADRIANO ZACCARI FORTUNA | J19: Administrador | K19: (51) 3477-9873 | L19: (51) 3477-9684 | P19: LUCIANO FREITAS DE OLIVEIRA | Q19: Administrador | R19: (51) 3477-9684 | T19: 8012248.6 | U19: B | V19: =IFERROR(VLOOKUP(U19,Assumptions!$A$7:$D$11,2,FALSE),0) | W19: =MAX(0.5,IFERROR(VLOOKUP(U19,Assumptions!$A$7:$D$11,3,FALSE),3)+IFERROR(VLOOKUP(U19,Assumptions!$A$7:$D$11,4,FALSE),8)/2-IF(AN19="",0,YEAR(TODAY())-AN19)) | X19: =T19*V19/(1+Assumptions!$B$3)^W19 | Y19: =IF(T19=0,"",ROUND(X19/T19*100,1)) | Z19: =X19*Assumptions!$B$4 | AA19: =IF(T19=0,"",ROUND(Z19/T19*100,1)) | AB19: =X19-Z19 | AC19: =IF(T19=0,"",ROUND((X19-Z19)/T19*100,1)) | AD19: UNKNOWN | AE19: https://inova-aj.com.br/wp-content/uploads/2026/08/1a-Relacao-de-Credores-Real.pdf | AF19: p1 r25 | AG19: p1: R$ 8.012.248,57 | AH19: AJ_LIST | AI19: 2023-06-05 | AJ19: OK | AK19: 0873061-47.2023.8.19.0001 | AL19: TJ | AN19: 2023 | AO19: live case, no plan document yet | AP19: MANAUS | AQ19: AM | AR19: Fabricação de aparelhos e equipamentos de ar condicionado para uso não-industrial | AS19: DEMAIS | AT19: MID-MARKET | AU19: 04222931 | AV19: 1 | AW19: ALT_VALUE:R$5.825.770,44 ROWS:p1r25
A20: LEGRAND PHARMA INDUSTRIA FARMACEUTICA LTDA | B20: 7715049.7 | C20: VEV COMERCIO DE MEDICAMENTOS LTDA EM RECUPERACAO JUDICIAL | D20: NEW | I20: Edgar Figueiredo | J20: Gerente Nacional de Distribuição | K20: (19) 3887-9800 | N20: edgar.figueiredo@legrandpharma.com.br | P20: TATIANA AZEVEDO VILLELA SANTOS FONTES | Q20: Administrador | R20: (19) 3887-9800 | T20: 7715049.7 | U20: B | V20: =IFERROR(VLOOKUP(U20,Assumptions!$A$7:$D$11,2,FALSE),0) | W20: =MAX(0.5,IFERROR(VLOOKUP(U20,Assumptions!$A$7:$D$11,3,FALSE),3)+IFERROR(VLOOKUP(U20,Assumptions!$A$7:$D$11,4,FALSE),8)/2-IF(AN20="",0,YEAR(TODAY())-AN20)) | X20: =T20*V20/(1+Assumptions!$B$3)^W20 | Y20: =IF(T20=0,"",ROUND(X20/T20*100,1)) | Z20: =X20*Assumptions!$B$4 | AA20: =IF(T20=0,"",ROUND(Z20/T20*100,1)) | AB20: =X20-Z20 | AC20: =IF(T20=0,"",ROUND((X20-Z20)/T20*100,1)) | AD20: ESTIMATED | AE20: https://marquesadmjudicial.com.br/sgc/download.php?file=files/processo_documento/processo_documento15293208032024_1_.pdf&nome=Relação Nominal de Credores da AJ-Sintética | AF20: p28 r5 | AG20: p28: R$ 7.715.049,72 | AH20: AJ_LIST | AI20: 2023-03-02 | AJ20: QUARANTINED | AK20: 0005010-98.2023.8.16.0001 | AL20: TJPR | AM20: ACTIVE | AN20: 2023 | AO20: live case, no plan document yet | AP20: HORTOLANDIA | AQ20: SP | AR20: Fabricação de medicamentos alopáticos para uso humano | AS20: DEMAIS | AT20: MID-MARKET | AU20: 05044984 | AV20: 1 | AW20: PARTIAL_DOC_CLASS_III_RECONCILED ROWS:p28r5
A21: ALBAUGH AGRO BRASIL LTDA. | B21: 11525550 | C21: NORTESUL COMERCIAL AGRICOLA LTDA EM RECUPERACAO JUDICIAL | D21: NEW | I21: CESAR EMILIANO ROJAS RUIZ | J21: Administrador | K21: (11) 3076-4243 | P21: MARCELO PACE | Q21: Administrador | R21: (11) 3076-4243 | T21: 11525550 | U21: B | V21: =IFERROR(VLOOKUP(U21,Assumptions!$A$7:$D$11,2,FALSE),0) | W21: =MAX(0.5,IFERROR(VLOOKUP(U21,Assumptions!$A$7:$D$11,3,FALSE),3)+IFERROR(VLOOKUP(U21,Assumptions!$A$7:$D$11,4,FALSE),8)/2-IF(AN21="",0,YEAR(TODAY())-AN21)) | X21: =T21*V21/(1+Assumptions!$B$3)^W21 | Y21: =IF(T21=0,"",ROUND(X21/T21*100,1)) | Z21: =X21*Assumptions!$B$4 | AA21: =IF(T21=0,"",ROUND(Z21/T21*100,1)) | AB21: =X21-Z21 | AC21: =IF(T21=0,"",ROUND((X21-Z21)/T21*100,1)) | AD21: ESTIMATED | AE21: https://lrflideres.com.br/wp-content/plugins/download-attachments/includes/download.php?id=6879 | AF21: p1 r4 | AG21: p1: R$ 11.525.550,26 | AH21: AJ_LIST | AI21: 2026-01-15 | AJ21: OK | AK21: 0804401-51.2025.8.14.0039 | AL21: TJPA | AM21: ACTIVE | AN21: 2025 | AO21: live case, no plan document yet | AP21: SAO PAULO | AQ21: SP | AR21: Fabricação de defensivos agrícolas | AS21: DEMAIS | AT21: LARGE CORP | AU21: 01789121 | AV21: 1 | AW21: ROWS:p1r4
A22: CATAO CONFECCOES LTDA - EM RECUPERACAO JUDICIAL | B22: 5843155.8 | C22: R W CONSTRUCOES LTDA | D22: NEW | I22: FLAVIO DANTAS CATAO | J22: Sócio-Administrador | K22: 000000000000 | T22: 5843155.8 | U22: B | V22: =IFERROR(VLOOKUP(U22,Assumptions!$A$7:$D$11,2,FALSE),0) | W22: =MAX(0.5,IFERROR(VLOOKUP(U22,Assumptions!$A$7:$D$11,3,FALSE),3)+IFERROR(VLOOKUP(U22,Assumptions!$A$7:$D$11,4,FALSE),8)/2-IF(AN22="",0,YEAR(TODAY())-AN22)) | X22: =T22*V22/(1+Assumptions!$B$3)^W22 | Y22: =IF(T22=0,"",ROUND(X22/T22*100,1)) | Z22: =X22*Assumptions!$B$4 | AA22: =IF(T22=0,"",ROUND(Z22/T22*100,1)) | AB22: =X22-Z22 | AC22: =IF(T22=0,"",ROUND((X22-Z22)/T22*100,1)) | AD22: ESTIMATED | AE22: https://lrflideres.com.br/wp-content/plugins/download-attachments/includes/download.php?id=4023 | AF22: p4 r60; p9 r62 | AG22: p4: R$ 1.447.463,41; p9: R$ 4.395.692,34 | AH22: DEBTOR_LIST | AJ22: QUARANTINED | AK22: 0002484-82.2022.8.17.2001 | AL22: TJPE | AM22: ACTIVE | AN22: 2022 | AO22: live case, no plan document yet | AP22: RECIFE | AQ22: PE | AR22: Comércio varejista de artigos do vestuário e acessórios | AS22: DEMAIS | AT22: MID-MARKET | AU22: 10775286 | AV22: 2 | AW22: PARTIAL_DOC_CLASS_III_RECONCILED ROWS:p4r60,p9r62
A23: FEDERACAO PERNAMBUCANA DE FUTEBOL | B23: 7251967.1 | C23: CLUBE NAUTICO CAPIBARIBE - EM RECUPERACAO JUDICIAL | D23: NEW | I23: Pedro Lacerda | J23: Diretor de Governança e Compliance | N23: pedro.lacerda@fpf-pe.com.br | T23: 7251967.1 | U23: B | V23: =IFERROR(VLOOKUP(U23,Assumptions!$A$7:$D$11,2,FALSE),0) | W23: =MAX(0.5,IFERROR(VLOOKUP(U23,Assumptions!$A$7:$D$11,3,FALSE),3)+IFERROR(VLOOKUP(U23,Assumptions!$A$7:$D$11,4,FALSE),8)/2-IF(AN23="",0,YEAR(TODAY())-AN23)) | X23: =T23*V23/(1+Assumptions!$B$3)^W23 | Y23: =IF(T23=0,"",ROUND(X23/T23*100,1)) | Z23: =X23*Assumptions!$B$4 | AA23: =IF(T23=0,"",ROUND(Z23/T23*100,1)) | AB23: =X23-Z23 | AC23: =IF(T23=0,"",ROUND((X23-Z23)/T23*100,1)) | AD23: ESTIMATED | AE23: https://lrflideres.com.br/wp-content/plugins/download-attachments/includes/download.php?id=5589 | AF23: p12 r9 | AG23: p12: R$ 7.251.967,09 | AH23: AJ_LIST | AI23: 2023-11-27 | AJ23: QUARANTINED | AK23: 0011283-80.2023.8.17.2001 | AL23: TJPE | AM23: ACTIVE | AN23: 2023 | AO23: live case, no plan document yet | AP23: RECIFE | AQ23: PE | AR23: Produção e promoção de eventos esportivos | AS23: DEMAIS | AT23: MID-MARKET | AU23: 10956258 | AV23: 1 | AW23: PARTIAL_DOC_CLASS_III_RECONCILED ROWS:p12r9
A24: TABLEROS IND. E COM. DE PAINEIS LTDA | B24: 12966350 | C24: FORMAPLAN FORMAS PLANEJADAS INDUSTRIA E COMERCIO LTDA EM RECUPERACAO JUDICIAL | D24: NEW | I24: MARCIO GERALDO ROSA | J24: Sócio-Administrador | K24: (46) 3263-8500 | T24: 12966350 | U24: C | V24: =IFERROR(VLOOKUP(U24,Assumptions!$A$7:$D$11,2,FALSE),0) | W24: =MAX(0.5,IFERROR(VLOOKUP(U24,Assumptions!$A$7:$D$11,3,FALSE),3)+IFERROR(VLOOKUP(U24,Assumptions!$A$7:$D$11,4,FALSE),8)/2-IF(AN24="",0,YEAR(TODAY())-AN24)) | X24: =T24*V24/(1+Assumptions!$B$3)^W24 | Y24: =IF(T24=0,"",ROUND(X24/T24*100,1)) | Z24: =X24*Assumptions!$B$4 | AA24: =IF(T24=0,"",ROUND(Z24/T24*100,1)) | AB24: =X24-Z24 | AC24: =IF(T24=0,"",ROUND((X24-Z24)/T24*100,1)) | AD24: ESTIMATED | AE24: https://marquesadmjudicial.com.br/sgc/download.php?file=files/processo_documento/processo_documento15232121112024_1_.pdf&nome=Relação de Credores | AF24: p16 r3 | AG24: p16: R$ 12.966.349,62 | AH24: AJ_LIST | AI24: 2021-01-22 | AJ24: QUARANTINED | AK24: 0000410-68.2021.8.16.0174 | AL24: TJPR | AM24: ACTIVE | AN24: 2021 | AO24: 5y since filing, no plan document | AP24: PALMAS | AQ24: PR | AR24: Fabricação de madeira laminada e de chapas de madeira compensada, prensada e aglomerada | AS24: DEMAIS | AT24: MID-MARKET | AU24: 09402999 | AV24: 1 | AW24: PARTIAL_DOC_CLASS_III_RECONCILED ROWS:p16r3
A25: L'OREAL BRASIL COMERCIAL DE COSMETICOS LTDA | B25: 5955264.1 | C25: VEV COMERCIO DE MEDICAMENTOS LTDA EM RECUPERACAO JUDICIAL | D25: NEW | I25: MARCELO ZIMET | J25: Administrador | K25: (21) 4505-9616 | T25: 5955264.1 | U25: B | V25: =IFERROR(VLOOKUP(U25,Assumptions!$A$7:$D$11,2,FALSE),0) | W25: =MAX(0.5,IFERROR(VLOOKUP(U25,Assumptions!$A$7:$D$11,3,FALSE),3)+IFERROR(VLOOKUP(U25,Assumptions!$A$7:$D$11,4,FALSE),8)/2-IF(AN25="",0,YEAR(TODAY())-AN25)) | X25: =T25*V25/(1+Assumptions!$B$3)^W25 | Y25: =IF(T25=0,"",ROUND(X25/T25*100,1)) | Z25: =X25*Assumptions!$B$4 | AA25: =IF(T25=0,"",ROUND(Z25/T25*100,1)) | AB25: =X25-Z25 | AC25: =IF(T25=0,"",ROUND((X25-Z25)/T25*100,1)) | AD25: ESTIMATED | AE25: https://marquesadmjudicial.com.br/sgc/download.php?file=files/processo_documento/processo_documento15293208032024_1_.pdf&nome=Relação Nominal de Credores da AJ-Sintética | AF25: p28 r10 | AG25: p28: R$ 5.955.264,10 | AH25: AJ_LIST | AI25: 2023-03-02 | AJ25: QUARANTINED | AK25: 0005010-98.2023.8.16.0001 | AL25: TJPR | AM25: ACTIVE | AN25: 2023 | AO25: live case, no plan document yet | AP25: RIO DE JANEIRO | AQ25: RJ | AR25: Comércio atacadista de cosméticos e produtos de perfumaria | AS25: DEMAIS | AT25: LARGE CORP | AU25: 30278428 | AV25: 1 | AW25: PARTIAL_DOC_CLASS_III_RECONCILED ROWS:p28r10
A26: AGROFIELD ASSESSORIA ADMINISTRATIVA LTDA | B26: 6434083.2 | C26: E FALENCIA | D26: NEW | I26: SERGIO LUIZ SILVA DA FONSECA LINS | J26: Sócio-Administrador | K26: (81) 3339-1977 | T26: 6434083.2 | U26: C | V26: =IFERROR(VLOOKUP(U26,Assumptions!$A$7:$D$11,2,FALSE),0) | W26: =MAX(0.5,IFERROR(VLOOKUP(U26,Assumptions!$A$7:$D$11,3,FALSE),3)+IFERROR(VLOOKUP(U26,Assumptions!$A$7:$D$11,4,FALSE),8)/2-IF(AN26="",0,YEAR(TODAY())-AN26)) | X26: =T26*V26/(1+Assumptions!$B$3)^W26 | Y26: =IF(T26=0,"",ROUND(X26/T26*100,1)) | Z26: =X26*Assumptions!$B$4 | AA26: =IF(T26=0,"",ROUND(Z26/T26*100,1)) | AB26: =X26-Z26 | AC26: =IF(T26=0,"",ROUND((X26-Z26)/T26*100,1)) | AD26: UNKNOWN | AE26: https://diligence.adm.br/wp-content/plugins/download-attachments/includes/download.php?id=4579 | AF26: p8 r2 | AG26: p8: R$ 6.434.083,18 | AH26: AJ_LIST | AI26: 2024-06-11 | AJ26: OK_NO_TOTALS | AK26: 0032731-52.2010.8.17.0001 | AL26: TJ | AN26: 2010 | AO26: 16y since filing, no plan document | AP26: RECIFE | AQ26: PE | AR26: Atividades de intermediação e agenciamento de serviços e negócios em geral, exceto imobiliários | AS26: DEMAIS | AT26: MID-MARKET | AU26: 06284974 | AV26: 1 | AW26: ROWS:p8r2 UNRECONCILED_SOURCE VALUE_COL:Crédito_1ª_Lista
A27: FIRST S/A | B27: 8354815.1 | D27: NEW | I27: NATANAEL SANTOS DE SOUZA | J27: Presidente | K27: (11) 5054-8110 | P27: MARA HELENA MARTINI DE SOUZA | Q27: Diretor | R27: (11) 5054-8110 | T27: 8354815.1 | U27: B | V27: =IFERROR(VLOOKUP(U27,Assumptions!$A$7:$D$11,2,FALSE),0) | W27: =MAX(0.5,IFERROR(VLOOKUP(U27,Assumptions!$A$7:$D$11,3,FALSE),3)+IFERROR(VLOOKUP(U27,Assumptions!$A$7:$D$11,4,FALSE),8)/2-IF(AN27="",0,YEAR(TODAY())-AN27)) | X27: =T27*V27/(1+Assumptions!$B$3)^W27 | Y27: =IF(T27=0,"",ROUND(X27/T27*100,1)) | Z27: =X27*Assumptions!$B$4 | AA27: =IF(T27=0,"",ROUND(Z27/T27*100,1)) | AB27: =X27-Z27 | AC27: =IF(T27=0,"",ROUND((X27-Z27)/T27*100,1)) | AD27: UNKNOWN | AE27: https://credibilita.com.br/wp-content/uploads/2025/09/Relacao-Credores-29.04.2026.pdf | AF27: p1 r23 | AG27: p1: R$ 8.354.815,13 | AH27: UNKNOWN | AJ27: OK_NO_TOTALS | AK27: 5057720-48.2025.8.24.0023 | AL27: TJ | AN27: 2025 | AO27: live case, no plan document yet | AP27: SAO PAULO | AQ27: SP | AR27: Comércio atacadista especializado em outros produtos intermediários não especificados anteriormente | AS27: DEMAIS | AT27: MID-MARKET | AU27: 00802235 | AV27: 1 | AW27: ROWS:p1r23 UNRECONCILED_SOURCE VALUE_COL:Valor_Após_Analise
A28: IPESA DO BRASIL COMERCIO DE PRODUTOS PLASTICOS LTDA | B28: 8353250 | D28: NEW | I28: Virginia Kumvich | J28: Diretora Comercial, de Negócios & Estratégia | K28: (11) 5524-2877 | P28: Pedro Santos | Q28: Financial Analyst | T28: 8353250 | U28: B | V28: =IFERROR(VLOOKUP(U28,Assumptions!$A$7:$D$11,2,FALSE),0) | W28: =MAX(0.5,IFERROR(VLOOKUP(U28,Assumptions!$A$7:$D$11,3,FALSE),3)+IFERROR(VLOOKUP(U28,Assumptions!$A$7:$D$11,4,FALSE),8)/2-IF(AN28="",0,YEAR(TODAY())-AN28)) | X28: =T28*V28/(1+Assumptions!$B$3)^W28 | Y28: =IF(T28=0,"",ROUND(X28/T28*100,1)) | Z28: =X28*Assumptions!$B$4 | AA28: =IF(T28=0,"",ROUND(Z28/T28*100,1)) | AB28: =X28-Z28 | AC28: =IF(T28=0,"",ROUND((X28-Z28)/T28*100,1)) | AD28: UNKNOWN | AE28: https://credibilita.com.br/wp-content/uploads/2025/09/Relacao-Credores-29.04.2026.pdf | AF28: p1 r27 | AG28: p1: R$ 8.353.250,00 | AH28: UNKNOWN | AJ28: OK_NO_TOTALS | AK28: 5057720-48.2025.8.24.0023 | AL28: TJ | AN28: 2025 | AO28: live case, no plan document yet | AP28: SAO PAULO | AQ28: SP | AR28: Comércio atacadista especializado em outros produtos intermediários não especificados anteriormente | AS28: DEMAIS | AT28: MID-MARKET | AU28: 05607230 | AV28: 1 | AW28: ROWS:p1r27 UNRECONCILED_SOURCE VALUE_COL:Valor_Após_Analise
A29: MINERACAO AURORA LTDA | B29: 8433590 | C29: CONSTRUTORA ANDRADE GUEDES LDTA – Diligence Administração em Recuperação Judicial e Falência | D29: NEW | I29: Jorge Ferraz | J29: Administrator | K29: (81) 3972-4964 | P29: Raphael Calafange | Q29: Sales Manager | T29: 8433590 | U29: C | V29: =IFERROR(VLOOKUP(U29,Assumptions!$A$7:$D$11,2,FALSE),0) | W29: =MAX(0.5,IFERROR(VLOOKUP(U29,Assumptions!$A$7:$D$11,3,FALSE),3)+IFERROR(VLOOKUP(U29,Assumptions!$A$7:$D$11,4,FALSE),8)/2-IF(AN29="",0,YEAR(TODAY())-AN29)) | X29: =T29*V29/(1+Assumptions!$B$3)^W29 | Y29: =IF(T29=0,"",ROUND(X29/T29*100,1)) | Z29: =X29*Assumptions!$B$4 | AA29: =IF(T29=0,"",ROUND(Z29/T29*100,1)) | AB29: =X29-Z29 | AC29: =IF(T29=0,"",ROUND((X29-Z29)/T29*100,1)) | AD29: ESTIMATED | AE29: https://diligence.adm.br/wp-content/plugins/download-attachments/includes/download.php?id=4599 | AF29: p10 r60 | AG29: p10: R$ 8.433.590,01 | AH29: AJ_LIST | AI29: 2024-06-25 | AJ29: OK_NO_TOTALS | AK29: 0000880-57.2020.8.17.2001 | AL29: TJPE | AM29: ACTIVE | AN29: 2020 | AO29: 6y since filing, no plan document | AP29: JABOATAO DOS GUARARAPES | AQ29: PE | AR29: Extração e britamento de pedras e outros materiais para construção e beneficiamento associado | AS29: DEMAIS | AT29: MID-MARKET | AU29: 10509915 | AV29: 1 | AW29: ALT_VALUE:R$2.710.146,67 ALT_VALUE:R$5.723.443,34 ROWS:p10r60 UNRECONCILED_SOURCE VALUE_COL:2ª_Lista
A30: DREYMOOR BRASIL COMERCIO DE FERTILIZANTES LTDA | B30: 15134865 | D30: NEW | I30: MAURICIO GIORDANI BODANESE | J30: Administrador | K30: (41) 3209-6613 | T30: 15134865 | U30: ? | V30: =IFERROR(VLOOKUP(U30,Assumptions!$A$7:$D$11,2,FALSE),0) | W30: =MAX(0.5,IFERROR(VLOOKUP(U30,Assumptions!$A$7:$D$11,3,FALSE),3)+IFERROR(VLOOKUP(U30,Assumptions!$A$7:$D$11,4,FALSE),8)/2-IF(AN30="",0,YEAR(TODAY())-AN30)) | X30: =T30*V30/(1+Assumptions!$B$3)^W30 | Y30: =IF(T30=0,"",ROUND(X30/T30*100,1)) | Z30: =X30*Assumptions!$B$4 | AA30: =IF(T30=0,"",ROUND(Z30/T30*100,1)) | AB30: =X30-Z30 | AC30: =IF(T30=0,"",ROUND((X30-Z30)/T30*100,1)) | AD30: UNKNOWN | AE30: https://scalzilliaj.com.br/sgc/download.php?file=files/processo_documento/processo_documento13183320052026_1_.pdf&nome=10 - QGC Provisório - atualizado até Maio de 2026 | AF30: p1 r9 | AG30: p1: R$ 15.134.865,10 | AH30: QGC | AJ30: OK_NO_TOTALS | AK30: (not printed) | AO30: RJ case number not identified on the document | AP30: CURITIBA | AQ30: PR | AR30: Comércio atacadista de defensivos agrícolas, adubos, fertilizantes e corretivos do solo | AS30: DEMAIS | AT30: MID-MARKET | AU30: 26419229 | AV30: 1 | AW30: CASE_NUMBER_MISSING ROWS:p1r9 UNRECONCILED_SOURCE VALUE_COL:Valor_Do_Crédito
A31: BOSCH HOME COMFORT DO BRASIL LTDA | B31: 5064633.8 | C31: REAL DISTRIBUIDORA ÚNICA RIO COMÉRCIO DE REFRIGERAÇÃO LTDA | D31: NEW | I31: Jaqueline Santos | J31: Finance Director Latam | K31: (92) 3301-5000 | O31: vanessa.idalgo@bosch-hcgroup.com | P31: Vanessa Leite | Q31: Gerente de Tesouraria, Finanças e Compliance | S31: vanessa.idalgo@bosch-hcgroup.com | T31: 5064633.8 | U31: B | V31: =IFERROR(VLOOKUP(U31,Assumptions!$A$7:$D$11,2,FALSE),0) | W31: =MAX(0.5,IFERROR(VLOOKUP(U31,Assumptions!$A$7:$D$11,3,FALSE),3)+IFERROR(VLOOKUP(U31,Assumptions!$A$7:$D$11,4,FALSE),8)/2-IF(AN31="",0,YEAR(TODAY())-AN31)) | X31: =T31*V31/(1+Assumptions!$B$3)^W31 | Y31: =IF(T31=0,"",ROUND(X31/T31*100,1)) | Z31: =X31*Assumptions!$B$4 | AA31: =IF(T31=0,"",ROUND(Z31/T31*100,1)) | AB31: =X31-Z31 | AC31: =IF(T31=0,"",ROUND((X31-Z31)/T31*100,1)) | AD31: UNKNOWN | AE31: https://inova-aj.com.br/wp-content/uploads/2026/08/1a-Relacao-de-Credores-Real.pdf | AF31: p1 r35 | AG31: p1: R$ 5.064.633,83 | AH31: AJ_LIST | AI31: 2023-06-05 | AJ31: OK | AK31: 0873061-47.2023.8.19.0001 | AL31: TJ | AN31: 2023 | AO31: live case, no plan document yet | AP31: MANAUS | AQ31: AM | AR31: Serviços combinados de escritório e apoio administrativo | AS31: DEMAIS | AT31: LARGE CORP | AU31: 33284522 | AV31: 1 | AW31: ALT_VALUE:R$3.682.536,03 ROWS:p1r35
A32: FRESENIUS MEDICAL CARE LTDA | B32: 14567734 | D32: NEW | I32: ANA LUCIA ZENKNER PERCIA | J32: Administrador | K32: (19) 3847-9700 | L32: (19) 3847-9700 | P32: JORGE ALEXANDRE CUNHA DE BARROS FRANCO | Q32: Administrador | R32: (19) 3847-9700 | T32: 14567734 | U32: ? | V32: =IFERROR(VLOOKUP(U32,Assumptions!$A$7:$D$11,2,FALSE),0) | W32: =MAX(0.5,IFERROR(VLOOKUP(U32,Assumptions!$A$7:$D$11,3,FALSE),3)+IFERROR(VLOOKUP(U32,Assumptions!$A$7:$D$11,4,FALSE),8)/2-IF(AN32="",0,YEAR(TODAY())-AN32)) | X32: =T32*V32/(1+Assumptions!$B$3)^W32 | Y32: =IF(T32=0,"",ROUND(X32/T32*100,1)) | Z32: =X32*Assumptions!$B$4 | AA32: =IF(T32=0,"",ROUND(Z32/T32*100,1)) | AB32: =X32-Z32 | AC32: =IF(T32=0,"",ROUND((X32-Z32)/T32*100,1)) | AD32: UNKNOWN | AE32: http://bernardobicalho.com.br/login/app/documents/Rela%C3%A7%C3%A3o%20de%20Credores/6.%20RVC-%20Nutricium%20-%20simplificada.pdf | AF32: p3 r16 | AG32: p3: R$ 14.567.733,99 | AH32: AJ_LIST | AJ32: OK | AK32: (not printed) | AO32: RJ case number not identified on the document | AP32: JAGUARIUNA | AQ32: SP | AR32: Fabricação de medicamentos alopáticos para uso humano | AS32: DEMAIS | AT32: LARGE CORP | AU32: 01440590 | AV32: 1 | AW32: CASE_NUMBER_MISSING ROWS:p3r16
A33: JF PASQUA CONDUTORES ELETRICOS LTDA | B33: 4940520.9 | C33: Conduscabos Brasil Indústria Comércio de | D33: NEW | I33: Joao Pasqua | J33: JF Pasqua Condutores Elétricos | K33: (35) 3559-6789 | P33: ROBERTO LEOPOLDO PASQUA | Q33: Administrador | R33: (35) 3559-6789 | T33: 4940520.9 | U33: B | V33: =IFERROR(VLOOKUP(U33,Assumptions!$A$7:$D$11,2,FALSE),0) | W33: =MAX(0.5,IFERROR(VLOOKUP(U33,Assumptions!$A$7:$D$11,3,FALSE),3)+IFERROR(VLOOKUP(U33,Assumptions!$A$7:$D$11,4,FALSE),8)/2-IF(AN33="",0,YEAR(TODAY())-AN33)) | X33: =T33*V33/(1+Assumptions!$B$3)^W33 | Y33: =IF(T33=0,"",ROUND(X33/T33*100,1)) | Z33: =X33*Assumptions!$B$4 | AA33: =IF(T33=0,"",ROUND(Z33/T33*100,1)) | AB33: =X33-Z33 | AC33: =IF(T33=0,"",ROUND((X33-Z33)/T33*100,1)) | AD33: ESTIMATED | AE33: https://assistjud.com.br/wp-content/uploads/elementor/forms/65098c80a5824.pdf | AF33: p8 r4; p18 r6 | AG33: p8: R$ 2.217.364,91; p18: R$ 2.723.156,00 | AH33: AJ_LIST | AI33: 2023-09-18 | AJ33: OK_NO_TOTALS | AK33: 8005129-09.2023.8.05.0039 | AL33: TJBA | AM33: ACTIVE | AN33: 2023 | AO33: live case, no plan document yet | AP33: GUAXUPE | AQ33: MG | AR33: Metalurgia do cobre | AS33: DEMAIS | AT33: MID-MARKET | AU33: 03981899 | AV33: 2 | AW33: ROWS:p8r4,p18r6 UNRECONCILED_SOURCE
A34: CENTRO AVANCADO DE NEUROLOGIA E NEUROCIRURGIA S/S | B34: 3947275.5 | C34: ASSOCIACAO DE CARIDADE SANTA CASA DE RIO GRANDE | D34: NEW | I34: GUSTAVO RASSIER ISOLAN | J34: Sócio-Administrador | K34: (51) 3276-7818 | T34: 3947275.5 | U34: B | V34: =IFERROR(VLOOKUP(U34,Assumptions!$A$7:$D$11,2,FALSE),0) | W34: =MAX(0.5,IFERROR(VLOOKUP(U34,Assumptions!$A$7:$D$11,3,FALSE),3)+IFERROR(VLOOKUP(U34,Assumptions!$A$7:$D$11,4,FALSE),8)/2-IF(AN34="",0,YEAR(TODAY())-AN34)) | X34: =T34*V34/(1+Assumptions!$B$3)^W34 | Y34: =IF(T34=0,"",ROUND(X34/T34*100,1)) | Z34: =X34*Assumptions!$B$4 | AA34: =IF(T34=0,"",ROUND(Z34/T34*100,1)) | AB34: =X34-Z34 | AC34: =IF(T34=0,"",ROUND((X34-Z34)/T34*100,1)) | AD34: ESTIMATED | AE34: https://scalzilliaj.com.br/sgc/download.php?file=files/processo_documento/processo_documento09120721032023_1_.pdf&nome=15 - Edital do art. 7º, §2º e 53 da Lei 11.101/2005 (segunda lista de credores e recebimento do plano)) | AF34: p26 r23 | AG34: p26: R$ 3.947.275,50 | AH34: AJ_LIST | AI34: 2023-03-21 | AJ34: OK_NO_TOTALS | AK34: 5012306-16.2022.8.21.0023 | AL34: TJRS | AM34: ACTIVE | AN34: 2022 | AO34: live case, no plan document yet | AP34: PORTO ALEGRE | AQ34: RS | AR34: Atividades de atenção ambulatorial não especificadas anteriormente | AS34: DEMAIS | AT34: MID-MARKET | AU34: 18331491 | AV34: 1 | AW34: ROWS:p26r23 UNRECONCILED_SOURCE
A35: BRASIL ASFALTOS LTDA | B35: 7707516.4 | C35: CONSTRUTORA ANDRADE GUEDES LDTA – Diligence Administração em Recuperação Judicial e Falência | D35: NEW | I35: ALBERTO GARRIDO PINON | J35: Administrador | K35: (71) 3118-2100 | L35: (71) 3176-2828 | P35: DANIELA GARRIDO PINON | Q35: Administrador | R35: (71) 3176-2828 | T35: 7707516.4 | U35: C | V35: =IFERROR(VLOOKUP(U35,Assumptions!$A$7:$D$11,2,FALSE),0) | W35: =MAX(0.5,IFERROR(VLOOKUP(U35,Assumptions!$A$7:$D$11,3,FALSE),3)+IFERROR(VLOOKUP(U35,Assumptions!$A$7:$D$11,4,FALSE),8)/2-IF(AN35="",0,YEAR(TODAY())-AN35)) | X35: =T35*V35/(1+Assumptions!$B$3)^W35 | Y35: =IF(T35=0,"",ROUND(X35/T35*100,1)) | Z35: =X35*Assumptions!$B$4 | AA35: =IF(T35=0,"",ROUND(Z35/T35*100,1)) | AB35: =X35-Z35 | AC35: =IF(T35=0,"",ROUND((X35-Z35)/T35*100,1)) | AD35: ESTIMATED | AE35: https://diligence.adm.br/wp-content/plugins/download-attachments/includes/download.php?id=4599 | AF35: p10 r9 | AG35: p10: R$ 7.707.516,40 | AH35: AJ_LIST | AI35: 2024-06-25 | AJ35: OK_NO_TOTALS | AK35: 0000880-57.2020.8.17.2001 | AL35: TJPE | AM35: ACTIVE | AN35: 2020 | AO35: 6y since filing, no plan document | AP35: CANDEIAS | AQ35: BA | AR35: Fabricação de outros produtos de minerais não-metálicos não especificados anteriormente | AS35: DEMAIS | AT35: MID-MARKET | AU35: 12447077 | AV35: 1 | AW35: ALT_VALUE:R$613.244,70 ALT_VALUE:R$7.094.271,70 ROWS:p10r9 UNRECONCILED_SOURCE VALUE_COL:2ª_Lista
A36: TITAN PNEUS DO BRASIL LTDA | B36: 7525940 | D36: NEW | I36: WALTER JOSE CHIOSINI | J36: Administrador | K36: (11) 2177-7360 | L36: (11) 2177-7201 | T36: 7525940 | U36: B | V36: =IFERROR(VLOOKUP(U36,Assumptions!$A$7:$D$11,2,FALSE),0) | W36: =MAX(0.5,IFERROR(VLOOKUP(U36,Assumptions!$A$7:$D$11,3,FALSE),3)+IFERROR(VLOOKUP(U36,Assumptions!$A$7:$D$11,4,FALSE),8)/2-IF(AN36="",0,YEAR(TODAY())-AN36)) | X36: =T36*V36/(1+Assumptions!$B$3)^W36 | Y36: =IF(T36=0,"",ROUND(X36/T36*100,1)) | Z36: =X36*Assumptions!$B$4 | AA36: =IF(T36=0,"",ROUND(Z36/T36*100,1)) | AB36: =X36-Z36 | AC36: =IF(T36=0,"",ROUND((X36-Z36)/T36*100,1)) | AD36: UNKNOWN | AE36: https://credibilita.com.br/wp-content/uploads/2025/09/Relacao-Credores-29.04.2026.pdf | AF36: p2 r23 | AG36: p2: R$ 7.525.940,00 | AH36: UNKNOWN | AJ36: OK_NO_TOTALS | AK36: 5057720-48.2025.8.24.0023 | AL36: TJ | AN36: 2025 | AO36: live case, no plan document yet | AP36: SAO PAULO | AQ36: SP | AR36: Fabricação de pneumáticos e de câmaras-de-ar | AS36: DEMAIS | AT36: LARGE CORP | AU36: 11385941 | AV36: 1 | AW36: ROWS:p2r23 UNRECONCILED_SOURCE VALUE_COL:Valor_Após_Analise
A37: PRO NOVA DISTRIBUIDORA E COMERCIO DE COSMETICOS LTDA | B37: 4694462.5 | C37: VEV COMERCIO DE MEDICAMENTOS LTDA EM RECUPERACAO JUDICIAL | D37: NEW | I37: ANA CLAUDIA GALVAO CARICATI | J37: Sócio-Administrador | K37: (11) 4772-8024 | P37: GABRIELLA CARICATI MENDES | Q37: Administrador | R37: (11) 4772-8024 | T37: 4694462.5 | U37: B | V37: =IFERROR(VLOOKUP(U37,Assumptions!$A$7:$D$11,2,FALSE),0) | W37: =MAX(0.5,IFERROR(VLOOKUP(U37,Assumptions!$A$7:$D$11,3,FALSE),3)+IFERROR(VLOOKUP(U37,Assumptions!$A$7:$D$11,4,FALSE),8)/2-IF(AN37="",0,YEAR(TODAY())-AN37)) | X37: =T37*V37/(1+Assumptions!$B$3)^W37 | Y37: =IF(T37=0,"",ROUND(X37/T37*100,1)) | Z37: =X37*Assumptions!$B$4 | AA37: =IF(T37=0,"",ROUND(Z37/T37*100,1)) | AB37: =X37-Z37 | AC37: =IF(T37=0,"",ROUND((X37-Z37)/T37*100,1)) | AD37: ESTIMATED | AE37: https://marquesadmjudicial.com.br/sgc/download.php?file=files/processo_documento/processo_documento15293208032024_1_.pdf&nome=Relação Nominal de Credores da AJ-Sintética | AF37: p30 r9 | AG37: p30: R$ 4.694.462,47 | AH37: AJ_LIST | AI37: 2023-03-02 | AJ37: QUARANTINED | AK37: 0005010-98.2023.8.16.0001 | AL37: TJPR | AM37: ACTIVE | AN37: 2023 | AO37: live case, no plan document yet | AP37: JANDIRA | AQ37: SP | AR37: Comércio atacadista de cosméticos e produtos de perfumaria | AS37: DEMAIS | AT37: MID-MARKET | AU37: 21998451 | AV37: 1 | AW37: PARTIAL_DOC_CLASS_III_RECONCILED ROWS:p30r9
A38: NORTEBAG INDUSTRIA DE EMBALAGENS S.A. | B38: 4680282.8 | D38: NEW | I38: MARCO ANTONIO GARCIA | J38: Diretor | K38: (92) 3396-6621 | P38: MARCOS VINICIUS SPITZNER FILHO | Q38: Diretor | R38: (92) 3396-6621 | T38: 4680282.8 | U38: B | V38: =IFERROR(VLOOKUP(U38,Assumptions!$A$7:$D$11,2,FALSE),0) | W38: =MAX(0.5,IFERROR(VLOOKUP(U38,Assumptions!$A$7:$D$11,3,FALSE),3)+IFERROR(VLOOKUP(U38,Assumptions!$A$7:$D$11,4,FALSE),8)/2-IF(AN38="",0,YEAR(TODAY())-AN38)) | X38: =T38*V38/(1+Assumptions!$B$3)^W38 | Y38: =IF(T38=0,"",ROUND(X38/T38*100,1)) | Z38: =X38*Assumptions!$B$4 | AA38: =IF(T38=0,"",ROUND(Z38/T38*100,1)) | AB38: =X38-Z38 | AC38: =IF(T38=0,"",ROUND((X38-Z38)/T38*100,1)) | AD38: ESTIMATED | AE38: https://cataliseaj.com.br/sgc/download.php?file=files/processo_documento/processo_documento15092204102024_1_.pdf&nome=02. RELAÇÃO DE CREDORES | AF38: p2 r66 | AG38: p2: R$ 4.680.282,82 | AH38: DEBTOR_LIST | AJ38: OK_NO_TOTALS | AK38: 5011460-87.2023.8.24.0020 | AL38: TJSC | AM38: ACTIVE | AN38: 2023 | AO38: live case, no plan document yet | AP38: MANAUS | AQ38: AM | AR38: Fabricação de outros produtos têxteis não especificados anteriormente | AS38: DEMAIS | AT38: MID-MARKET | AU38: 05399071 | AV38: 1 | AW38: ROWS:p2r66 UNRECONCILED_SOURCE
A39: SERRINHA AMBIENTAL TRANSPORTES LTDA | B39: 4672725.1 | C39: BBR AGRO SUPLEMENTOS LTDA EM RECUPERACAO JUDICIAL | D39: NEW | I39: VOLNEI DOS SANTOS | J39: Administrador | K39: (49) 9914-4317 | T39: 4672725.1 | U39: B | V39: =IFERROR(VLOOKUP(U39,Assumptions!$A$7:$D$11,2,FALSE),0) | W39: =MAX(0.5,IFERROR(VLOOKUP(U39,Assumptions!$A$7:$D$11,3,FALSE),3)+IFERROR(VLOOKUP(U39,Assumptions!$A$7:$D$11,4,FALSE),8)/2-IF(AN39="",0,YEAR(TODAY())-AN39)) | X39: =T39*V39/(1+Assumptions!$B$3)^W39 | Y39: =IF(T39=0,"",ROUND(X39/T39*100,1)) | Z39: =X39*Assumptions!$B$4 | AA39: =IF(T39=0,"",ROUND(Z39/T39*100,1)) | AB39: =X39-Z39 | AC39: =IF(T39=0,"",ROUND((X39-Z39)/T39*100,1)) | AD39: ESTIMATED | AE39: https://ajruiz.com.br/sites/default/files/public/arquivos-processos/2026-06/alto_uruguai_qgc_junho.2026.pdf | AF39: p1 r35 | AG39: p1: R$ 4.672.725,10 | AH39: UNKNOWN | AJ39: OK | AK39: 5012743-51.2023.8.24.0019 | AL39: TJSC | AM39: ACTIVE | AN39: 2023 | AO39: live case, no plan document yet | AP39: CHAPECO | AQ39: SC | AR39: Transporte rodoviário de carga, exceto produtos perigosos e mudanças, intermunicipal, interestadual e internacional | AS39: DEMAIS | AT39: MID-MARKET | AU39: 32851823 | AV39: 1 | AW39: ROWS:p1r35 VALUE_COL:Valor_Do_Crédito
A40: COPA ENERGIA S.A. | B40: 9000000 | C40: E FALENCIA | D40: NEW | I40: Eduardo Souza | J40: Gerente de Crédito e Cobrança | K40: (11) 5505-4077 | N40: eduardo.souza@copaenergia.com.br | O40: carlos.martins@copaenergia.com.br | P40: Carlos Martins | Q40: Treasury Manager | S40: carlos.martins@copaenergia.com.br | T40: 9000000 | U40: B | V40: =IFERROR(VLOOKUP(U40,Assumptions!$A$7:$D$11,2,FALSE),0) | W40: =MAX(0.5,IFERROR(VLOOKUP(U40,Assumptions!$A$7:$D$11,3,FALSE),3)+IFERROR(VLOOKUP(U40,Assumptions!$A$7:$D$11,4,FALSE),8)/2-IF(AN40="",0,YEAR(TODAY())-AN40)) | X40: =T40*V40/(1+Assumptions!$B$3)^W40 | Y40: =IF(T40=0,"",ROUND(X40/T40*100,1)) | Z40: =X40*Assumptions!$B$4 | AA40: =IF(T40=0,"",ROUND(Z40/T40*100,1)) | AB40: =X40-Z40 | AC40: =IF(T40=0,"",ROUND((X40-Z40)/T40*100,1)) | AD40: ESTIMATED | AE40: https://recuperasolucoes.com/wp-content/plugins/download-attachments/includes/download.php?id=1597 | AF40: p13 r12 | AG40: p13: R$ 9.000.000,00 | AH40: DEBTOR_LIST | AI40: 2026-05-21 | AJ40: OK | AK40: 0001639-09.2026.8.17.2810 | AL40: TJPE | AM40: ACTIVE | AN40: 2026 | AO40: live case, no plan document yet | AP40: SAO PAULO | AQ40: SP | AR40: Comércio atacadista de gás liqüefeito de petróleo (GLP) | AS40: DEMAIS | AT40: LARGE CORP | AU40: 03237583 | AV40: 1 | AW40: ROWS:p13r12
A41: ADDIANTE S.A | B41: 7135517 | C41: NORTESUL COMERCIAL AGRICOLA LTDA EM RECUPERACAO JUDICIAL | D41: NEW | I41: Fabio Leite | J41: CEO at Addiante | K41: (41) 9571-0152 | N41: fabio.leite@addiante.com.br | O41: ernani.ferreira@addiante.com.br | P41: Ernani Ferreira | Q41: Gerente de Crédito e Cobrança | S41: ernani.ferreira@addiante.com.br | T41: 7135517 | U41: B | V41: =IFERROR(VLOOKUP(U41,Assumptions!$A$7:$D$11,2,FALSE),0) | W41: =MAX(0.5,IFERROR(VLOOKUP(U41,Assumptions!$A$7:$D$11,3,FALSE),3)+IFERROR(VLOOKUP(U41,Assumptions!$A$7:$D$11,4,FALSE),8)/2-IF(AN41="",0,YEAR(TODAY())-AN41)) | X41: =T41*V41/(1+Assumptions!$B$3)^W41 | Y41: =IF(T41=0,"",ROUND(X41/T41*100,1)) | Z41: =X41*Assumptions!$B$4 | AA41: =IF(T41=0,"",ROUND(Z41/T41*100,1)) | AB41: =X41-Z41 | AC41: =IF(T41=0,"",ROUND((X41-Z41)/T41*100,1)) | AD41: ESTIMATED | AE41: https://lrflideres.com.br/wp-content/plugins/download-attachments/includes/download.php?id=6879 | AF41: p1 r2 | AG41: p1: R$ 7.135.516,97 | AH41: AJ_LIST | AI41: 2026-01-15 | AJ41: OK | AK41: 0804401-51.2025.8.14.0039 | AL41: TJPA | AM41: ACTIVE | AN41: 2025 | AO41: live case, no plan document yet | AP41: CURITIBA | AQ41: PR | AR41: Locação de outros meios de transporte não especificados anteriormente, sem condutor | AS41: DEMAIS | AT41: LARGE CORP | AU41: 48430290 | AV41: 1 | AW41: ROWS:p1r2
A42: COMERCIO RACOES BEM BOM LTDA | B42: 6642119 | C42: COMERCIO RACOES BEM BOM LTDA | D42: NEW | I42: EDSON VIANDELLI LOPES | J42: Sócio-Administrador | K42: (62) 3389-9200 | L42: (62) 8115-0283 | T42: 6642119 | U42: A | V42: =IFERROR(VLOOKUP(U42,Assumptions!$A$7:$D$11,2,FALSE),0) | W42: =MAX(0.5,IFERROR(VLOOKUP(U42,Assumptions!$A$7:$D$11,3,FALSE),3)+IFERROR(VLOOKUP(U42,Assumptions!$A$7:$D$11,4,FALSE),8)/2-IF(AN42="",0,YEAR(TODAY())-AN42)) | X42: =T42*V42/(1+Assumptions!$B$3)^W42 | Y42: =IF(T42=0,"",ROUND(X42/T42*100,1)) | Z42: =X42*Assumptions!$B$4 | AA42: =IF(T42=0,"",ROUND(Z42/T42*100,1)) | AB42: =X42-Z42 | AC42: =IF(T42=0,"",ROUND((X42-Z42)/T42*100,1)) | AD42: CONFIRMED | AE42: https://stenius.com.br/wp-content/uploads/2026/06/EDITAL-GRUPO-3E.pdf | AF42: p13 r19 | AG42: p13: R$ 6.642.118,99 | AH42: DEBTOR_LIST | AI42: 2026-06-22 | AJ42: OK_NO_TOTALS | AK42: 5341375-33.2026.8.09.0049 | AL42: TJGO | AM42: ACTIVE | AN42: 2026 | AO42: plan/homologation document found | AP42: GOIANESIA | AQ42: GO | AR42: Fabricação de alimentos para animais | AS42: DEMAIS | AT42: MID-MARKET | AU42: 41324359 | AV42: 1 | AW42: ROWS:p13r19 UNRECONCILED_SOURCE
A43: SOLUS DO BRASIL LTDA | B43: 7058181.5 | C43: NORTESUL COMERCIAL AGRICOLA LTDA EM RECUPERACAO JUDICIAL | D43: NEW | I43: Antonio Guimaraes | J43: Financial Director | K43: (43) 3162-2715 | P43: Alcides Aires | Q43: CEO | T43: 7058181.5 | U43: B | V43: =IFERROR(VLOOKUP(U43,Assumptions!$A$7:$D$11,2,FALSE),0) | W43: =MAX(0.5,IFERROR(VLOOKUP(U43,Assumptions!$A$7:$D$11,3,FALSE),3)+IFERROR(VLOOKUP(U43,Assumptions!$A$7:$D$11,4,FALSE),8)/2-IF(AN43="",0,YEAR(TODAY())-AN43)) | X43: =T43*V43/(1+Assumptions!$B$3)^W43 | Y43: =IF(T43=0,"",ROUND(X43/T43*100,1)) | Z43: =X43*Assumptions!$B$4 | AA43: =IF(T43=0,"",ROUND(Z43/T43*100,1)) | AB43: =X43-Z43 | AC43: =IF(T43=0,"",ROUND((X43-Z43)/T43*100,1)) | AD43: ESTIMATED | AE43: https://lrflideres.com.br/wp-content/plugins/download-attachments/includes/download.php?id=6879 | AF43: p2 r10 | AG43: p2: R$ 7.058.181,50 | AH43: AJ_LIST | AI43: 2026-01-15 | AJ43: OK | AK43: 0804401-51.2025.8.14.0039 | AL43: TJPA | AM43: ACTIVE | AN43: 2025 | AO43: live case, no plan document yet | AP43: APUCARANA | AQ43: PR | AR43: Fabricação de defensivos agrícolas | AS43: DEMAIS | AT43: MID-MARKET | AU43: 21203489 | AV43: 1 | AW43: ROWS:p2r10
A44: M.K. GALONE CONFECCOES E COMERCIO DE ROUPAS LTDA | B44: 3309751.3 | C44: R W CONSTRUCOES LTDA | D44: NEW | I44: LEANDRO AKIYOSHI HASHIGUTI | J44: Sócio-Administrador | K44: (11) 7213-9030 | P44: THIAGO ISSAMI HASHIGUTI | Q44: Sócio-Administrador | R44: (11) 7213-9030 | T44: 3309751.3 | U44: B | V44: =IFERROR(VLOOKUP(U44,Assumptions!$A$7:$D$11,2,FALSE),0) | W44: =MAX(0.5,IFERROR(VLOOKUP(U44,Assumptions!$A$7:$D$11,3,FALSE),3)+IFERROR(VLOOKUP(U44,Assumptions!$A$7:$D$11,4,FALSE),8)/2-IF(AN44="",0,YEAR(TODAY())-AN44)) | X44: =T44*V44/(1+Assumptions!$B$3)^W44 | Y44: =IF(T44=0,"",ROUND(X44/T44*100,1)) | Z44: =X44*Assumptions!$B$4 | AA44: =IF(T44=0,"",ROUND(Z44/T44*100,1)) | AB44: =X44-Z44 | AC44: =IF(T44=0,"",ROUND((X44-Z44)/T44*100,1)) | AD44: ESTIMATED | AE44: https://lrflideres.com.br/wp-content/plugins/download-attachments/includes/download.php?id=4023 | AF44: p4 r87; p7 r111; p9 r84 | AG44: p4: R$ 2.265.469,65; p7: R$ 879.396,72; p9: R$ 164.884,92 | AH44: DEBTOR_LIST | AJ44: QUARANTINED | AK44: 0002484-82.2022.8.17.2001 | AL44: TJPE | AM44: ACTIVE | AN44: 2022 | AO44: live case, no plan document yet | AP44: SAO PAULO | AQ44: SP | AR44: Confecção de peças de vestuário, exceto roupas íntimas e as confeccionadas sob medida | AS44: DEMAIS | AT44: MID-MARKET | AU44: 05784234 | AV44: 3 | AW44: PARTIAL_DOC_CLASS_III_RECONCILED ROWS:p4r87,p7r111,p9r84
A45: COOPERATIVA DOS PLANTADORES DE CANA DO ESTADO SAO PAULO | B45: 8000000 | D45: NEW | I45: Jose Pavao | J45: Administrative Director | K45: (19) 3401-2200 | P45: Marcelo Gil | Q45: Commercial Manager | T45: 8000000 | U45: B | V45: =IFERROR(VLOOKUP(U45,Assumptions!$A$7:$D$11,2,FALSE),0) | W45: =MAX(0.5,IFERROR(VLOOKUP(U45,Assumptions!$A$7:$D$11,3,FALSE),3)+IFERROR(VLOOKUP(U45,Assumptions!$A$7:$D$11,4,FALSE),8)/2-IF(AN45="",0,YEAR(TODAY())-AN45)) | X45: =T45*V45/(1+Assumptions!$B$3)^W45 | Y45: =IF(T45=0,"",ROUND(X45/T45*100,1)) | Z45: =X45*Assumptions!$B$4 | AA45: =IF(T45=0,"",ROUND(Z45/T45*100,1)) | AB45: =X45-Z45 | AC45: =IF(T45=0,"",ROUND((X45-Z45)/T45*100,1)) | AD45: ESTIMATED | AE45: https://vtladm.com.br/wp-content/uploads/2026/06/02-–-Relacao-de-Credores-–-NAIR-AKICO-KAWAKAMI-MORIOKA-E-OUTROS.pdf | AF45: p4 r1 | AG45: p4: R$ 8.000.000,00 | AH45: UNKNOWN | AJ45: OK_NO_TOTALS | AK45: 4000807-49.2026.8.26.0354 | AL45: TJSP | AM45: ACTIVE | AN45: 2026 | AO45: live case, no plan document yet | AP45: PIRACICABA | AQ45: SP | AR45: Comércio atacadista de defensivos agrícolas, adubos, fertilizantes e corretivos do solo | AS45: DEMAIS | AT45: MID-MARKET | AU45: 54366547 | AV45: 1 | AW45: LONG_CHUNK MULTI_ROOT ROWS:p4r1 UNRECONCILED_SOURCE
A46: NORTESUL COMERCIAL AGRICOLA LTDA EM RECUPERACAO JUDICIAL | B46: 6258845.3 | C46: NORTESUL COMERCIAL AGRICOLA LTDA EM RECUPERACAO JUDICIAL | D46: NEW | I46: Lidiane C | J46: Administrative Manager | K46: (63) 3602-4239 | P46: Wesley Medeiros | Q46: Financial Analyst | T46: 6258845.3 | U46: B | V46: =IFERROR(VLOOKUP(U46,Assumptions!$A$7:$D$11,2,FALSE),0) | W46: =MAX(0.5,IFERROR(VLOOKUP(U46,Assumptions!$A$7:$D$11,3,FALSE),3)+IFERROR(VLOOKUP(U46,Assumptions!$A$7:$D$11,4,FALSE),8)/2-IF(AN46="",0,YEAR(TODAY())-AN46)) | X46: =T46*V46/(1+Assumptions!$B$3)^W46 | Y46: =IF(T46=0,"",ROUND(X46/T46*100,1)) | Z46: =X46*Assumptions!$B$4 | AA46: =IF(T46=0,"",ROUND(Z46/T46*100,1)) | AB46: =X46-Z46 | AC46: =IF(T46=0,"",ROUND((X46-Z46)/T46*100,1)) | AD46: ESTIMATED | AE46: https://lrflideres.com.br/wp-content/plugins/download-attachments/includes/download.php?id=6879 | AF46: p2 r5 | AG46: p2: R$ 6.258.845,34 | AH46: AJ_LIST | AI46: 2026-01-15 | AJ46: OK | AK46: 0804401-51.2025.8.14.0039 | AL46: TJPA | AM46: ACTIVE | AN46: 2025 | AO46: live case, no plan document yet | AP46: PALMAS | AQ46: TO | AR46: Comércio atacadista de matérias-primas agrícolas não especificadas anteriormente | AS46: DEMAIS | AT46: MID-MARKET | AU46: 15626673 | AV46: 1 | AW46: ROWS:p2r5
A47: GRANELES BRASIL COMERCIAL IMPORTADORA EXPORTADORA AGRICOLA S.A EM RECUPERACAO JUDICIAL | B47: 11676960 | D47: NEW | I47: Gabriel Machado | J47: CMO | K47: (41) 9539-0828 | N47: gmachado@granelesbrasil.com | O47: mgaensly@granelesbrasil.com | P47: Mauricio Gaensly | Q47: Financial Analyst | S47: mgaensly@granelesbrasil.com | T47: 11676960 | U47: ? | V47: =IFERROR(VLOOKUP(U47,Assumptions!$A$7:$D$11,2,FALSE),0) | W47: =MAX(0.5,IFERROR(VLOOKUP(U47,Assumptions!$A$7:$D$11,3,FALSE),3)+IFERROR(VLOOKUP(U47,Assumptions!$A$7:$D$11,4,FALSE),8)/2-IF(AN47="",0,YEAR(TODAY())-AN47)) | X47: =T47*V47/(1+Assumptions!$B$3)^W47 | Y47: =IF(T47=0,"",ROUND(X47/T47*100,1)) | Z47: =X47*Assumptions!$B$4 | AA47: =IF(T47=0,"",ROUND(Z47/T47*100,1)) | AB47: =X47-Z47 | AC47: =IF(T47=0,"",ROUND((X47-Z47)/T47*100,1)) | AD47: UNKNOWN | AE47: https://scalzilliaj.com.br/sgc/download.php?file=files/processo_documento/processo_documento13183320052026_1_.pdf&nome=10 - QGC Provisório - atualizado até Maio de 2026 | AF47: p1 r10 | AG47: p1: R$ 11.676.960,19 | AH47: QGC | AJ47: OK_NO_TOTALS | AK47: (not printed) | AO47: RJ case number not identified on the document | AP47: SAO PAULO | AQ47: SP | AR47: Comércio atacadista de produtos alimentícios em geral | AS47: DEMAIS | AT47: MID-MARKET | AU47: 24785274 | AV47: 1 | AW47: CASE_NUMBER_MISSING ROWS:p1r10 UNRECONCILED_SOURCE VALUE_COL:Valor_Do_Crédito
A48: ALFANI CONFECCOES E COMERCIO LTDA - EM RECUPERACAO JUDICIAL | B48: 3140000 | C48: R W CONSTRUCOES LTDA | D48: NEW | I48: FLAVIO DANTAS CATAO | J48: Sócio-Administrador | K48: (81) 3419-8550 | L48: (81) 3032-8400 | T48: 3140000 | U48: B | V48: =IFERROR(VLOOKUP(U48,Assumptions!$A$7:$D$11,2,FALSE),0) | W48: =MAX(0.5,IFERROR(VLOOKUP(U48,Assumptions!$A$7:$D$11,3,FALSE),3)+IFERROR(VLOOKUP(U48,Assumptions!$A$7:$D$11,4,FALSE),8)/2-IF(AN48="",0,YEAR(TODAY())-AN48)) | X48: =T48*V48/(1+Assumptions!$B$3)^W48 | Y48: =IF(T48=0,"",ROUND(X48/T48*100,1)) | Z48: =X48*Assumptions!$B$4 | AA48: =IF(T48=0,"",ROUND(Z48/T48*100,1)) | AB48: =X48-Z48 | AC48: =IF(T48=0,"",ROUND((X48-Z48)/T48*100,1)) | AD48: ESTIMATED | AE48: https://lrflideres.com.br/wp-content/plugins/download-attachments/includes/download.php?id=4023 | AF48: p9 r52 | AG48: p9: R$ 3.140.000,00 | AH48: DEBTOR_LIST | AJ48: QUARANTINED | AK48: 0002484-82.2022.8.17.2001 | AL48: TJPE | AM48: ACTIVE | AN48: 2022 | AO48: live case, no plan document yet | AP48: RECIFE | AQ48: PE | AR48: Comércio varejista de artigos do vestuário e acessórios | AS48: DEMAIS | AT48: MID-MARKET | AU48: 02524216 | AV48: 1 | AW48: PARTIAL_DOC_CLASS_III_RECONCILED ROWS:p9r52
A49: VIANMAQ EQUIPAMENTOS LTDA | B49: 3083893.6 | C49: CPX DISTRIBUIDORA S.A. | D49: NEW | I49: Emerson Moraes | J49: Vendedor Equipamentos | K49: (41) 3555-2161 | L49: (41) 9707-0679 | N49: emerson.moraes@vianmaq.com.br | P49: THIERRY FERNAND VIAN | Q49: Sócio-Administrador | R49: (41) 9707-0679 | T49: 3083893.6 | U49: B | V49: =IFERROR(VLOOKUP(U49,Assumptions!$A$7:$D$11,2,FALSE),0) | W49: =MAX(0.5,IFERROR(VLOOKUP(U49,Assumptions!$A$7:$D$11,3,FALSE),3)+IFERROR(VLOOKUP(U49,Assumptions!$A$7:$D$11,4,FALSE),8)/2-IF(AN49="",0,YEAR(TODAY())-AN49)) | X49: =T49*V49/(1+Assumptions!$B$3)^W49 | Y49: =IF(T49=0,"",ROUND(X49/T49*100,1)) | Z49: =X49*Assumptions!$B$4 | AA49: =IF(T49=0,"",ROUND(Z49/T49*100,1)) | AB49: =X49-Z49 | AC49: =IF(T49=0,"",ROUND((X49-Z49)/T49*100,1)) | AD49: ESTIMATED | AE49: https://marquesadmjudicial.com.br/sgc/download.php?file=files/processo_documento/processo_documento16562707032024_1_.pdf&nome=2º Edital-Relação de Credores do art. 7, §2 da LREF e do Plano de Recuperação Judicial | AF49: p1 r45 | AG49: p1: R$ 3.083.893,62 | AH49: AJ_LIST | AI49: 2022-11-17 | AJ49: OK_NO_TOTALS | AK49: 0037411-27.2022.8.16.0021 | AL49: TJPR | AM49: ACTIVE | AN49: 2022 | AO49: live case, no plan document yet | AP49: CAMPO LARGO | AQ49: PR | AR49: Comércio atacadista de outras máquinas e equipamentos não especificados anteriormente; partes e peças | AS49: DEMAIS | AT49: MID-MARKET | AU49: 01631022 | AV49: 1 | AW49: MULTI_ROOT ROWS:p1r45 UNRECONCILED_SOURCE
A50: INVISTA LOTEADORA E INCORPORADORA LTDA | B50: 5875236.1 | D50: NEW | I50: JONES FERNANDES | J50: Sócio-Administrador | K50: (55) 3524-1044 | L50: (55) 3524-1143 | T50: 5875236.1 | U50: B | V50: =IFERROR(VLOOKUP(U50,Assumptions!$A$7:$D$11,2,FALSE),0) | W50: =MAX(0.5,IFERROR(VLOOKUP(U50,Assumptions!$A$7:$D$11,3,FALSE),3)+IFERROR(VLOOKUP(U50,Assumptions!$A$7:$D$11,4,FALSE),8)/2-IF(AN50="",0,YEAR(TODAY())-AN50)) | X50: =T50*V50/(1+Assumptions!$B$3)^W50 | Y50: =IF(T50=0,"",ROUND(X50/T50*100,1)) | Z50: =X50*Assumptions!$B$4 | AA50: =IF(T50=0,"",ROUND(Z50/T50*100,1)) | AB50: =X50-Z50 | AC50: =IF(T50=0,"",ROUND((X50-Z50)/T50*100,1)) | AD50: UNKNOWN | AE50: https://credibilita.com.br/wp-content/uploads/2025/09/Relacao-Credores-29.04.2026.pdf | AF50: p1 r26 | AG50: p1: R$ 5.875.236,13 | AH50: UNKNOWN | AJ50: OK_NO_TOTALS | AK50: 5057720-48.2025.8.24.0023 | AL50: TJ | AN50: 2025 | AO50: live case, no plan document yet | AP50: HORIZONTINA | AQ50: RS | AR50: Incorporação de empreendimentos imobiliários | AS50: MICRO EMPRESA | AT50: SMALL | AU50: 18871750 | AV50: 1 | AW50: ROWS:p1r26 UNRECONCILED_SOURCE VALUE_COL:Valor_Após_Analise
A51: COMPANHIA DE AGUA E ESGOTOS DA PARAIBA CAGEPA | B51: 3641949.7 | C51: TREZE FUTEBOL CLUBE | D51: NEW | I51: Dilvany Marcos | J51: Subgerencia de Cobranças de Órg. Públicos | K51: (83) 3218-1200 | L51: (83) 3218-1225 | O51: alecsandro@cagepa.pb.gov.br | P51: Alecsandro Gomes | Q51: Técnico Em Contabilidade | S51: alecsandro@cagepa.pb.gov.br | T51: 3641949.7 | U51: B | V51: =IFERROR(VLOOKUP(U51,Assumptions!$A$7:$D$11,2,FALSE),0) | W51: =MAX(0.5,IFERROR(VLOOKUP(U51,Assumptions!$A$7:$D$11,3,FALSE),3)+IFERROR(VLOOKUP(U51,Assumptions!$A$7:$D$11,4,FALSE),8)/2-IF(AN51="",0,YEAR(TODAY())-AN51)) | X51: =T51*V51/(1+Assumptions!$B$3)^W51 | Y51: =IF(T51=0,"",ROUND(X51/T51*100,1)) | Z51: =X51*Assumptions!$B$4 | AA51: =IF(T51=0,"",ROUND(Z51/T51*100,1)) | AB51: =X51-Z51 | AC51: =IF(T51=0,"",ROUND((X51-Z51)/T51*100,1)) | AD51: ESTIMATED | AE51: https://lrflideres.com.br/wp-content/plugins/download-attachments/includes/download.php?id=5828 | AF51: p3 r16 | AG51: p3: R$ 3.641.949,67 | AH51: AJ_LIST | AI51: 2024-04-18 | AJ51: OK | AK51: 0829315-43.2023.8.15.0001 | AL51: TJPB | AM51: ACTIVE | AN51: 2023 | AO51: live case, no plan document yet | AP51: JOAO PESSOA | AQ51: PB | AR51: Captação, tratamento e distribuição de água | AS51: DEMAIS | AT51: LARGE CORP | AU51: 09123654 | AV51: 1 | AW51: ROWS:p3r16
A52: ENVTECH DO BRASIL DESCONTAMINACOES INDUSTRIAIS LTDA | B52: 10310429 | C52: EGESA ENGENHARIA S/A (Consórcio ETDI) | D52: NEW | I52: FREDDY VLADIMIR RADA COVALOVA | J52: Sócio-Administrador | K52: (31) 8447-7021 | T52: 10310429 | U52: ? | V52: =IFERROR(VLOOKUP(U52,Assumptions!$A$7:$D$11,2,FALSE),0) | W52: =MAX(0.5,IFERROR(VLOOKUP(U52,Assumptions!$A$7:$D$11,3,FALSE),3)+IFERROR(VLOOKUP(U52,Assumptions!$A$7:$D$11,4,FALSE),8)/2-IF(AN52="",0,YEAR(TODAY())-AN52)) | X52: =T52*V52/(1+Assumptions!$B$3)^W52 | Y52: =IF(T52=0,"",ROUND(X52/T52*100,1)) | Z52: =X52*Assumptions!$B$4 | AA52: =IF(T52=0,"",ROUND(Z52/T52*100,1)) | AB52: =X52-Z52 | AC52: =IF(T52=0,"",ROUND((X52-Z52)/T52*100,1)) | AD52: UNKNOWN | AE52: https://scalzilliaj.com.br/sgc/download.php?file=files/processo_documento/processo_documento09514021082025_1_.pdf&nome=04 - Relação de credores das Recuperandas | AF52: p66 r6 | AG52: p66: R$ 10.310.428,56 | AH52: DEBTOR_LIST | AJ52: OK | AK52: (not printed) | AO52: RJ case number not identified on the document | AP52: PETROPOLIS | AQ52: RJ | AR52: Manutenção e reparação de outras máquinas e equipamentos para usos industriais não especificados anteriormente | AS52: DEMAIS | AT52: MID-MARKET | AU52: 11486977 | AV52: 1 | AW52: ROWS:p66r6 VALUE_COL:Valor_Atualizado CASE_NUMBER_CORRECTED
A53: BACUPARI AGROINDUSTRIA LTDA | B53: 4500000 | C53: COMERCIO RACOES BEM BOM LTDA | D53: NEW | I53: ANA PAOLA BRANDAO RAZEM ABRAO | J53: Sócio-Administrador | K53: (61) 9655-6611 | P53: RAUL FRANCISCO MADUREIRA DE LIMA | Q53: Sócio-Administrador | R53: (61) 9655-6611 | T53: 4500000 | U53: A | V53: =IFERROR(VLOOKUP(U53,Assumptions!$A$7:$D$11,2,FALSE),0) | W53: =MAX(0.5,IFERROR(VLOOKUP(U53,Assumptions!$A$7:$D$11,3,FALSE),3)+IFERROR(VLOOKUP(U53,Assumptions!$A$7:$D$11,4,FALSE),8)/2-IF(AN53="",0,YEAR(TODAY())-AN53)) | X53: =T53*V53/(1+Assumptions!$B$3)^W53 | Y53: =IF(T53=0,"",ROUND(X53/T53*100,1)) | Z53: =X53*Assumptions!$B$4 | AA53: =IF(T53=0,"",ROUND(Z53/T53*100,1)) | AB53: =X53-Z53 | AC53: =IF(T53=0,"",ROUND((X53-Z53)/T53*100,1)) | AD53: CONFIRMED | AE53: https://stenius.com.br/wp-content/uploads/2026/06/EDITAL-GRUPO-3E.pdf | AF53: p10 r29 | AG53: p10: R$ 4.500.000,00 | AH53: DEBTOR_LIST | AI53: 2026-06-22 | AJ53: OK_NO_TOTALS | AK53: 5341375-33.2026.8.09.0049 | AL53: TJGO | AM53: ACTIVE | AN53: 2026 | AO53: plan/homologation document found | AP53: BRASILIA | AQ53: DF | AR53: Compra e venda de imóveis próprios | AS53: DEMAIS | AT53: MID-MARKET | AU53: 19907274 | AV53: 1 | AW53: ROWS:p10r29 UNRECONCILED_SOURCE
A54: BALDAN IMPLEMENTOS AGRICOLAS S A | B54: 4681142.4 | D54: NEW | I54: Wolney Netto | J54: Chief Financial Officer, CFO | K54: (16) 3221-6500 | L54: (16) 3221-6581 | N54: winetto@baldan.com.br | O54: avieira@baldan.com.br | P54: Aguinaldo Vieira | Q54: Financial Manager | S54: avieira@baldan.com.br | T54: 4681142.4 | U54: B | V54: =IFERROR(VLOOKUP(U54,Assumptions!$A$7:$D$11,2,FALSE),0) | W54: =MAX(0.5,IFERROR(VLOOKUP(U54,Assumptions!$A$7:$D$11,3,FALSE),3)+IFERROR(VLOOKUP(U54,Assumptions!$A$7:$D$11,4,FALSE),8)/2-IF(AN54="",0,YEAR(TODAY())-AN54)) | X54: =T54*V54/(1+Assumptions!$B$3)^W54 | Y54: =IF(T54=0,"",ROUND(X54/T54*100,1)) | Z54: =X54*Assumptions!$B$4 | AA54: =IF(T54=0,"",ROUND(Z54/T54*100,1)) | AB54: =X54-Z54 | AC54: =IF(T54=0,"",ROUND((X54-Z54)/T54*100,1)) | AD54: UNKNOWN | AE54: https://credibilita.com.br/wp-content/uploads/2025/09/Relacao-Credores-29.04.2026.pdf | AF54: p1 r3 | AG54: p1: R$ 4.681.142,41 | AH54: UNKNOWN | AJ54: OK_NO_TOTALS | AK54: 5057720-48.2025.8.24.0023 | AL54: TJ | AN54: 2025 | AO54: live case, no plan document yet | AP54: MATAO | AQ54: SP | AR54: Fabricação de máquinas e equipamentos para a agricultura e pecuária, peças e acessórios, exceto para irrigação | AS54: DEMAIS | AT54: LARGE CORP | AU54: 52311347 | AV54: 1 | AW54: ROWS:p1r3 UNRECONCILED_SOURCE VALUE_COL:Valor_Após_Analise
A55: BIOTRONIK COMERCIAL MEDICA LTDA. | B55: 2311648.4 | C55: ASSOCIACAO DE CARIDADE SANTA CASA DE RIO GRANDE | D55: NEW | I55: CARLOS EDUARDO CAUTERUCCI FIGUEIREDO | J55: Administrador | K55: (11) 5694-7755 | T55: 2311648.4 | U55: B | V55: =IFERROR(VLOOKUP(U55,Assumptions!$A$7:$D$11,2,FALSE),0) | W55: =MAX(0.5,IFERROR(VLOOKUP(U55,Assumptions!$A$7:$D$11,3,FALSE),3)+IFERROR(VLOOKUP(U55,Assumptions!$A$7:$D$11,4,FALSE),8)/2-IF(AN55="",0,YEAR(TODAY())-AN55)) | X55: =T55*V55/(1+Assumptions!$B$3)^W55 | Y55: =IF(T55=0,"",ROUND(X55/T55*100,1)) | Z55: =X55*Assumptions!$B$4 | AA55: =IF(T55=0,"",ROUND(Z55/T55*100,1)) | AB55: =X55-Z55 | AC55: =IF(T55=0,"",ROUND((X55-Z55)/T55*100,1)) | AD55: ESTIMATED | AE55: https://scalzilliaj.com.br/sgc/download.php?file=files/processo_documento/processo_documento09120721032023_1_.pdf&nome=15 - Edital do art. 7º, §2º e 53 da Lei 11.101/2005 (segunda lista de credores e recebimento do plano)) | AF55: p26 r10 | AG55: p26: R$ 2.311.648,44 | AH55: AJ_LIST | AI55: 2023-03-21 | AJ55: OK_NO_TOTALS | AK55: 5012306-16.2022.8.21.0023 | AL55: TJRS | AM55: ACTIVE | AN55: 2022 | AO55: live case, no plan document yet | AP55: SAO PAULO | AQ55: SP | AR55: Comércio atacadista de instrumentos e materiais para uso médico, cirúrgico, hospitalar e de laboratórios | AS55: DEMAIS | AT55: LARGE CORP | AU55: 50595271 | AV55: 1 | AW55: ROWS:p26r10 UNRECONCILED_SOURCE
A56: SPORT CLUB CORINTHIANS PAULISTA | B56: 2823611.8 | C56: CLUBE NAUTICO CAPIBARIBE - EM RECUPERACAO JUDICIAL | D56: NEW | I56: Joana Saragoca | J56: Gerente Sênior Financeiro e Administrativo | N56: joana.saragoca@sccorinthians.com.br | P56: Danyel Reis | Q56: Encarregado de Tesouraria | T56: 2823611.8 | U56: B | V56: =IFERROR(VLOOKUP(U56,Assumptions!$A$7:$D$11,2,FALSE),0) | W56: =MAX(0.5,IFERROR(VLOOKUP(U56,Assumptions!$A$7:$D$11,3,FALSE),3)+IFERROR(VLOOKUP(U56,Assumptions!$A$7:$D$11,4,FALSE),8)/2-IF(AN56="",0,YEAR(TODAY())-AN56)) | X56: =T56*V56/(1+Assumptions!$B$3)^W56 | Y56: =IF(T56=0,"",ROUND(X56/T56*100,1)) | Z56: =X56*Assumptions!$B$4 | AA56: =IF(T56=0,"",ROUND(Z56/T56*100,1)) | AB56: =X56-Z56 | AC56: =IF(T56=0,"",ROUND((X56-Z56)/T56*100,1)) | AD56: ESTIMATED | AE56: https://lrflideres.com.br/wp-content/plugins/download-attachments/includes/download.php?id=5589 | AF56: p12 r44 | AG56: p12: R$ 2.823.611,80 | AH56: AJ_LIST | AI56: 2023-11-27 | AJ56: QUARANTINED | AK56: 0011283-80.2023.8.17.2001 | AL56: TJPE | AM56: ACTIVE | AN56: 2023 | AO56: live case, no plan document yet | AP56: SAO PAULO | AQ56: SP | AR56: Clubes sociais, esportivos e similares | AS56: DEMAIS | AT56: MID-MARKET | AU56: 61902722 | AV56: 1 | AW56: PARTIAL_DOC_CLASS_III_RECONCILED ROWS:p12r44
A57: VR BENEFICIOS E SERVICOS DE PROCESSAMENTO INSTITUICAO DE PAGAMENTO S.A. | B57: 2731258.5 | D57: NEW | I57: ANDRE TAKEMOTO | J57: Diretor | K57: (11) 4134-4100 | P57: ANDRE VINICIUS BATALINI MENOSSE | Q57: Diretor | R57: (11) 4134-4100 | T57: 2731258.5 | U57: B | V57: =IFERROR(VLOOKUP(U57,Assumptions!$A$7:$D$11,2,FALSE),0) | W57: =MAX(0.5,IFERROR(VLOOKUP(U57,Assumptions!$A$7:$D$11,3,FALSE),3)+IFERROR(VLOOKUP(U57,Assumptions!$A$7:$D$11,4,FALSE),8)/2-IF(AN57="",0,YEAR(TODAY())-AN57)) | X57: =T57*V57/(1+Assumptions!$B$3)^W57 | Y57: =IF(T57=0,"",ROUND(X57/T57*100,1)) | Z57: =X57*Assumptions!$B$4 | AA57: =IF(T57=0,"",ROUND(Z57/T57*100,1)) | AB57: =X57-Z57 | AC57: =IF(T57=0,"",ROUND((X57-Z57)/T57*100,1)) | AD57: UNKNOWN | AE57: https://bbsadvogados.com.br/wp-content/uploads/2025/04/Equipseg-Edital-Relacao-de-Credores-da-Administradora-Judicial-art.-7o2o-da-LRF.pdf | AF57: p42 r8 | AG57: p42: R$ 2.731.258,45 | AH57: AJ_LIST | AI57: 2025-04-08 | AJ57: OK_NO_TOTALS | AK57: 0033736-15.2023.8.16.0185 | AL57: TJ | AN57: 2023 | AO57: live case, no plan document yet | AP57: SAO PAULO | AQ57: SP | AR57: Emissão de vales-alimentação, vales-transporte e similares | AS57: DEMAIS | AT57: LARGE CORP | AU57: 02535864 | AV57: 1 | AW57: ROWS:p42r8 UNRECONCILED_SOURCE
A58: SRJ INDUSTRIA COMERCIO E EXPORTACAO DE CONFECCOES LTDA | B58: 2113920 | C58: R W CONSTRUCOES LTDA | D58: NEW | I58: JOAQUIM COELHO DE MAGALHAES | J58: Administrador | P58: RAFAEL COELHO DANTAS | Q58: Administrador | T58: 2113920 | U58: B | V58: =IFERROR(VLOOKUP(U58,Assumptions!$A$7:$D$11,2,FALSE),0) | W58: =MAX(0.5,IFERROR(VLOOKUP(U58,Assumptions!$A$7:$D$11,3,FALSE),3)+IFERROR(VLOOKUP(U58,Assumptions!$A$7:$D$11,4,FALSE),8)/2-IF(AN58="",0,YEAR(TODAY())-AN58)) | X58: =T58*V58/(1+Assumptions!$B$3)^W58 | Y58: =IF(T58=0,"",ROUND(X58/T58*100,1)) | Z58: =X58*Assumptions!$B$4 | AA58: =IF(T58=0,"",ROUND(Z58/T58*100,1)) | AB58: =X58-Z58 | AC58: =IF(T58=0,"",ROUND((X58-Z58)/T58*100,1)) | AD58: ESTIMATED | AE58: https://lrflideres.com.br/wp-content/plugins/download-attachments/includes/download.php?id=4023 | AF58: p4 r92; p7 r121 | AG58: p4: R$ 2.113.920,00; p7: R$ 2.113.920,00 | AH58: DEBTOR_LIST | AJ58: QUARANTINED | AK58: 0002484-82.2022.8.17.2001 | AL58: TJPE | AM58: ACTIVE | AN58: 2022 | AO58: live case, no plan document yet | AP58: CARUARU | AQ58: PE | AR58: Confecção de peças de vestuário, exceto roupas íntimas e as confeccionadas sob medida | AS58: DEMAIS | AT58: MID-MARKET | AU58: 05554669 | AV58: 1 | AW58: PARTIAL_DOC_CLASS_III_RECONCILED ROWS:p4r92
A59: DIVINA INDUSTRIA DE COURO LTDA - EM RECUPERACAO JUDICIAL | B59: 3206338.8 | C59: DIVINA INDUSTRIA DE COURO LTDA - EM RECUPERACAO JUDICIAL | D59: NEW | I59: ADRIANO FERRAZ GOMES | J59: Sócio-Administrador | K59: (81) 9411-3643 | T59: 3206338.8 | U59: B | V59: =IFERROR(VLOOKUP(U59,Assumptions!$A$7:$D$11,2,FALSE),0) | W59: =MAX(0.5,IFERROR(VLOOKUP(U59,Assumptions!$A$7:$D$11,3,FALSE),3)+IFERROR(VLOOKUP(U59,Assumptions!$A$7:$D$11,4,FALSE),8)/2-IF(AN59="",0,YEAR(TODAY())-AN59)) | X59: =T59*V59/(1+Assumptions!$B$3)^W59 | Y59: =IF(T59=0,"",ROUND(X59/T59*100,1)) | Z59: =X59*Assumptions!$B$4 | AA59: =IF(T59=0,"",ROUND(Z59/T59*100,1)) | AB59: =X59-Z59 | AC59: =IF(T59=0,"",ROUND((X59-Z59)/T59*100,1)) | AD59: ESTIMATED | AE59: https://lrflideres.com.br/wp-content/plugins/download-attachments/includes/download.php?id=6252 | AF59: p2 r34 | AG59: p2: R$ 3.206.338,81 | AH59: AJ_LIST | AI59: 2024-11-27 | AJ59: QUARANTINED | AK59: 0000721-61.2024.8.17.2620 | AL59: TJPE | AM59: ACTIVE | AN59: 2024 | AO59: live case, no plan document yet | AP59: FLORESTA | AQ59: PE | AR59: Fabricação de calçados de couro | AS59: DEMAIS | AT59: MID-MARKET | AU59: 08785522 | AV59: 1 | AW59: PARTIAL_DOC_CLASS_III_RECONCILED ROWS:p2r34
A60: BRASQUIMICA PRODUTOS ASFALTICOS LTDA | B60: 3879789.5 | C60: CONSTRUTORA ANDRADE GUEDES LDTA – Diligence Administração em Recuperação Judicial e Falência | D60: NEW | I60: Ronan Drumond | J60: Commercial Director | K60: (71) 3118-2100 | P60: Kelmara Pereira | Q60: Technical Manager | T60: 3879789.5 | U60: C | V60: =IFERROR(VLOOKUP(U60,Assumptions!$A$7:$D$11,2,FALSE),0) | W60: =MAX(0.5,IFERROR(VLOOKUP(U60,Assumptions!$A$7:$D$11,3,FALSE),3)+IFERROR(VLOOKUP(U60,Assumptions!$A$7:$D$11,4,FALSE),8)/2-IF(AN60="",0,YEAR(TODAY())-AN60)) | X60: =T60*V60/(1+Assumptions!$B$3)^W60 | Y60: =IF(T60=0,"",ROUND(X60/T60*100,1)) | Z60: =X60*Assumptions!$B$4 | AA60: =IF(T60=0,"",ROUND(Z60/T60*100,1)) | AB60: =X60-Z60 | AC60: =IF(T60=0,"",ROUND((X60-Z60)/T60*100,1)) | AD60: ESTIMATED | AE60: https://diligence.adm.br/wp-content/plugins/download-attachments/includes/download.php?id=4599 | AF60: p10 r10 | AG60: p10: R$ 3.879.789,49 | AH60: AJ_LIST | AI60: 2024-06-25 | AJ60: OK_NO_TOTALS | AK60: 0000880-57.2020.8.17.2001 | AL60: TJPE | AM60: ACTIVE | AN60: 2020 | AO60: 6y since filing, no plan document | AP60: SALVADOR | AQ60: BA | AR60: Comércio atacadista de outros produtos químicos e petroquímicos não especificados anteriormente | AS60: DEMAIS | AT60: MID-MARKET | AU60: 13829957 | AV60: 1 | AW60: ALT_VALUE:R$3.849.447,97 ALT_VALUE:R$30.341,52 ROWS:p10r10 UNRECONCILED_SOURCE VALUE_COL:2ª_Lista
A61: YARA BRASIL FERTILIZANTES S/A | B61: 4591380 | D61: NEW | I61: Adriana Nunez | J61: CFO Yara Brazil | K61: (51) 3230-1300 | N61: adriana.nunez@yara.com | O61: michele.kabov@yara.com | P61: Michele Kabov | Q61: Credito | S61: michele.kabov@yara.com | T61: 4591380 | U61: B | V61: =IFERROR(VLOOKUP(U61,Assumptions!$A$7:$D$11,2,FALSE),0) | W61: =MAX(0.5,IFERROR(VLOOKUP(U61,Assumptions!$A$7:$D$11,3,FALSE),3)+IFERROR(VLOOKUP(U61,Assumptions!$A$7:$D$11,4,FALSE),8)/2-IF(AN61="",0,YEAR(TODAY())-AN61)) | X61: =T61*V61/(1+Assumptions!$B$3)^W61 | Y61: =IF(T61=0,"",ROUND(X61/T61*100,1)) | Z61: =X61*Assumptions!$B$4 | AA61: =IF(T61=0,"",ROUND(Z61/T61*100,1)) | AB61: =X61-Z61 | AC61: =IF(T61=0,"",ROUND((X61-Z61)/T61*100,1)) | AD61: ESTIMATED | AE61: https://scalzilliaj.com.br/sgc/download.php?file=files/processo_documento/processo_documento11421222052026_1_.pdf&nome=08. Lista de credores do edital do art. 52, §1º da LREF | AF61: p3 r7 | AG61: p3: R$ 4.591.380,00 | AH61: UNKNOWN | AJ61: OK_NO_TOTALS | AK61: 5011369-81.2026.8.09.0093 | AL61: TJGO | AM61: ACTIVE | AN61: 2026 | AO61: live case, no plan document yet | AP61: PORTO ALEGRE | AQ61: RS | AR61: Fabricação de adubos e fertilizantes, exceto organo-minerais | AS61: DEMAIS | AT61: LARGE CORP | AU61: 92660604 | AV61: 1 | AW61: ROWS:p3r7 UNRECONCILED_SOURCE
A62: MISTRAS SOUTH AMERICA COMERCIO E SERVICOS LTDA | B62: 6623625.2 | C62: EGESA ENGENHARIA S/A (Consórcio ETDI) | D62: NEW | I62: Caio Martins | J62: Head of Finance | K62: (11) 2061-8626 | N62: caio.martins@mistras.com.br | O62: pedro@mistras.com.br | P62: Pedro Filho | Q62: Mistras South America CEO | S62: pedro@mistras.com.br | T62: 6623625.2 | U62: ? | V62: =IFERROR(VLOOKUP(U62,Assumptions!$A$7:$D$11,2,FALSE),0) | W62: =MAX(0.5,IFERROR(VLOOKUP(U62,Assumptions!$A$7:$D$11,3,FALSE),3)+IFERROR(VLOOKUP(U62,Assumptions!$A$7:$D$11,4,FALSE),8)/2-IF(AN62="",0,YEAR(TODAY())-AN62)) | X62: =T62*V62/(1+Assumptions!$B$3)^W62 | Y62: =IF(T62=0,"",ROUND(X62/T62*100,1)) | Z62: =X62*Assumptions!$B$4 | AA62: =IF(T62=0,"",ROUND(Z62/T62*100,1)) | AB62: =X62-Z62 | AC62: =IF(T62=0,"",ROUND((X62-Z62)/T62*100,1)) | AD62: UNKNOWN | AE62: https://scalzilliaj.com.br/sgc/download.php?file=files/processo_documento/processo_documento09514021082025_1_.pdf&nome=04 - Relação de credores das Recuperandas | AF62: p70 r9 | AG62: p70: R$ 6.623.625,24 | AH62: DEBTOR_LIST | AJ62: OK | AK62: (not printed) | AO62: RJ case number not identified on the document | AP62: SAO PAULO | AQ62: SP | AR62: Testes e análises técnicas | AS62: DEMAIS | AT62: MID-MARKET | AU62: 61615191 | AV62: 1 | AW62: ROWS:p70r9 VALUE_COL:Valor_Atualizado CASE_NUMBER_CORRECTED
A63: FLEXIVEL INDUSTRIA E COMERCIO LTDA | B63: 2550639.6 | D63: NEW | I63: ANGELA VILMA GADOTTI JUNKES | J63: Administrador | K63: (47) 3270-1900 | P63: LEODATO CHRISTIANO JUNKES | Q63: Administrador | R63: (47) 3270-1900 | T63: 2550639.6 | U63: C | V63: =IFERROR(VLOOKUP(U63,Assumptions!$A$7:$D$11,2,FALSE),0) | W63: =MAX(0.5,IFERROR(VLOOKUP(U63,Assumptions!$A$7:$D$11,3,FALSE),3)+IFERROR(VLOOKUP(U63,Assumptions!$A$7:$D$11,4,FALSE),8)/2-IF(AN63="",0,YEAR(TODAY())-AN63)) | X63: =T63*V63/(1+Assumptions!$B$3)^W63 | Y63: =IF(T63=0,"",ROUND(X63/T63*100,1)) | Z63: =X63*Assumptions!$B$4 | AA63: =IF(T63=0,"",ROUND(Z63/T63*100,1)) | AB63: =X63-Z63 | AC63: =IF(T63=0,"",ROUND((X63-Z63)/T63*100,1)) | AD63: UNKNOWN | AE63: https://administradorajudicialgs.com.br/wp-content/uploads/2024/12/relacao-de-credores-da-falida.pdf | AF63: p14 r49 | AG63: p14: R$ 2.550.639,65 | AH63: UNKNOWN | AI63: 2025-03-25 | AJ63: OK_NO_TOTALS | AK63: 0005010-50.2013.8.24.0026 | AL63: TJ | AN63: 2013 | AO63: 13y since filing, no plan document | AP63: JARAGUA DO SUL | AQ63: SC | AR63: Fabricação de outros produtos químicos não especificados anteriormente | AS63: DEMAIS | AT63: MID-MARKET | AU63: 03076832 | AV63: 1 | AW63: ROWS:p14r49 UNRECONCILED_SOURCE
A64: FALCON DISTRIBUICAO, ARMAZENAMENTO E TRANSPORTES S.A. | B64: 2199541.2 | C64: VEV COMERCIO DE MEDICAMENTOS LTDA EM RECUPERACAO JUDICIAL | D64: NEW | I64: ADRIANO DE CONTI BERNARDI | J64: Diretor | K64: (11) 9177-5953 | P64: CELSO UBIRAJARA BLANCO DOS SANTOS | Q64: Diretor | R64: (11) 9177-5953 | T64: 2199541.2 | U64: B | V64: =IFERROR(VLOOKUP(U64,Assumptions!$A$7:$D$11,2,FALSE),0) | W64: =MAX(0.5,IFERROR(VLOOKUP(U64,Assumptions!$A$7:$D$11,3,FALSE),3)+IFERROR(VLOOKUP(U64,Assumptions!$A$7:$D$11,4,FALSE),8)/2-IF(AN64="",0,YEAR(TODAY())-AN64)) | X64: =T64*V64/(1+Assumptions!$B$3)^W64 | Y64: =IF(T64=0,"",ROUND(X64/T64*100,1)) | Z64: =X64*Assumptions!$B$4 | AA64: =IF(T64=0,"",ROUND(Z64/T64*100,1)) | AB64: =X64-Z64 | AC64: =IF(T64=0,"",ROUND((X64-Z64)/T64*100,1)) | AD64: ESTIMATED | AE64: https://marquesadmjudicial.com.br/sgc/download.php?file=files/processo_documento/processo_documento15293208032024_1_.pdf&nome=Relação Nominal de Credores da AJ-Sintética | AF64: p25 r5 | AG64: p25: R$ 2.199.541,23 | AH64: AJ_LIST | AI64: 2023-03-02 | AJ64: QUARANTINED | AK64: 0005010-98.2023.8.16.0001 | AL64: TJPR | AM64: ACTIVE | AN64: 2023 | AO64: live case, no plan document yet | AP64: GOIANIA | AQ64: GO | AR64: Comércio atacadista de produtos de higiene pessoal | AS64: DEMAIS | AT64: LARGE CORP | AU64: 23191831 | AV64: 1 | AW64: PARTIAL_DOC_CLASS_III_RECONCILED ROWS:p25r5
A65: LOROTTI EMPREENDIMENTOS IMOBILIARIOS LTDA | B65: 3159739.6 | C65: COMERCIO RACOES BEM BOM LTDA | D65: NEW | I65: ALINE RAZEM ABRAO | J65: Sócio-Administrador | K65: (61) 3366-4288 | P65: ANA PAOLA BRANDAO RAZEM ABRAO | Q65: Sócio-Administrador | R65: (61) 3366-4288 | T65: 3159739.6 | U65: A | V65: =IFERROR(VLOOKUP(U65,Assumptions!$A$7:$D$11,2,FALSE),0) | W65: =MAX(0.5,IFERROR(VLOOKUP(U65,Assumptions!$A$7:$D$11,3,FALSE),3)+IFERROR(VLOOKUP(U65,Assumptions!$A$7:$D$11,4,FALSE),8)/2-IF(AN65="",0,YEAR(TODAY())-AN65)) | X65: =T65*V65/(1+Assumptions!$B$3)^W65 | Y65: =IF(T65=0,"",ROUND(X65/T65*100,1)) | Z65: =X65*Assumptions!$B$4 | AA65: =IF(T65=0,"",ROUND(Z65/T65*100,1)) | AB65: =X65-Z65 | AC65: =IF(T65=0,"",ROUND((X65-Z65)/T65*100,1)) | AD65: CONFIRMED | AE65: https://stenius.com.br/wp-content/uploads/2026/06/EDITAL-GRUPO-3E.pdf | AF65: p15 r31 | AG65: p15: R$ 3.159.739,59 | AH65: DEBTOR_LIST | AI65: 2026-06-22 | AJ65: OK_NO_TOTALS | AK65: 5341375-33.2026.8.09.0049 | AL65: TJGO | AM65: ACTIVE | AN65: 2026 | AO65: plan/homologation document found | AP65: BRASILIA | AQ65: DF | AR65: Construção de edifícios | AS65: DEMAIS | AT65: MID-MARKET | AU65: 10505803 | AV65: 1 | AW65: ROWS:p15r31 UNRECONCILED_SOURCE
A66: SALESFORCE TECNOLOGIA LTDA | B66: 3349893.5 | D66: NEW | I66: Alexandre Costa | J66: Controller Director | K66: (11) 2110-3141 | N66: alexandre.costa@salesforce.com | O66: mmendes@salesforce.com | P66: Marcio Mendes | Q66: Finance Controller | S66: mmendes@salesforce.com | T66: 3349893.5 | U66: B | V66: =IFERROR(VLOOKUP(U66,Assumptions!$A$7:$D$11,2,FALSE),0) | W66: =MAX(0.5,IFERROR(VLOOKUP(U66,Assumptions!$A$7:$D$11,3,FALSE),3)+IFERROR(VLOOKUP(U66,Assumptions!$A$7:$D$11,4,FALSE),8)/2-IF(AN66="",0,YEAR(TODAY())-AN66)) | X66: =T66*V66/(1+Assumptions!$B$3)^W66 | Y66: =IF(T66=0,"",ROUND(X66/T66*100,1)) | Z66: =X66*Assumptions!$B$4 | AA66: =IF(T66=0,"",ROUND(Z66/T66*100,1)) | AB66: =X66-Z66 | AC66: =IF(T66=0,"",ROUND((X66-Z66)/T66*100,1)) | AD66: UNKNOWN | AE66: https://credibilita.com.br/wp-content/uploads/2025/09/Relacao-Credores-29.04.2026.pdf | AF66: p2 r16 | AG66: p2: R$ 3.349.893,45 | AH66: UNKNOWN | AJ66: OK_NO_TOTALS | AK66: 5057720-48.2025.8.24.0023 | AL66: TJ | AN66: 2025 | AO66: live case, no plan document yet | AP66: SAO PAULO | AQ66: SP | AR66: Desenvolvimento e licenciamento de programas de computador customizáveis | AS66: DEMAIS | AT66: MID-MARKET | AU66: 01080512 | AV66: 1 | AW66: ROWS:p2r16 UNRECONCILED_SOURCE VALUE_COL:Valor_Após_Analise
A67: VENTISOL DA AMAZONIA INDUSTRIA DE APARELHOS ELETRICOS LTDA | B67: 2121705.9 | C67: REAL DISTRIBUIDORA ÚNICA RIO COMÉRCIO DE REFRIGERAÇÃO LTDA | D67: NEW | I67: Marcos Bittencourt | J67: Financial Manager | K67: (92) 3029-1000 | N67: marcos@ventisol.com.br | O67: fernanda@ventisol.com.br | P67: Fernanda Candido | Q67: Commercial Director | S67: fernanda@ventisol.com.br | T67: 2121705.9 | U67: B | V67: =IFERROR(VLOOKUP(U67,Assumptions!$A$7:$D$11,2,FALSE),0) | W67: =MAX(0.5,IFERROR(VLOOKUP(U67,Assumptions!$A$7:$D$11,3,FALSE),3)+IFERROR(VLOOKUP(U67,Assumptions!$A$7:$D$11,4,FALSE),8)/2-IF(AN67="",0,YEAR(TODAY())-AN67)) | X67: =T67*V67/(1+Assumptions!$B$3)^W67 | Y67: =IF(T67=0,"",ROUND(X67/T67*100,1)) | Z67: =X67*Assumptions!$B$4 | AA67: =IF(T67=0,"",ROUND(Z67/T67*100,1)) | AB67: =X67-Z67 | AC67: =IF(T67=0,"",ROUND((X67-Z67)/T67*100,1)) | AD67: UNKNOWN | AE67: https://inova-aj.com.br/wp-content/uploads/2026/08/1a-Relacao-de-Credores-Real.pdf | AF67: p2 r16 | AG67: p2: R$ 2.121.705,89 | AH67: AJ_LIST | AI67: 2023-06-05 | AJ67: OK | AK67: 0873061-47.2023.8.19.0001 | AL67: TJ | AN67: 2023 | AO67: live case, no plan document yet | AP67: MANAUS | AQ67: AM | AR67: Fabricação de aparelhos e equipamentos de ar condicionado para uso industrial | AS67: DEMAIS | AT67: LARGE CORP | AU67: 17417928 | AV67: 1 | AW67: ALT_VALUE:R$1.542.709,43 ROWS:p2r16
A68: NUTRIEN SOLUCOES AGRICOLAS LTDA | B68: 3009813.4 | C68: COMERCIO RACOES BEM BOM LTDA | D68: NEW | I68: Thiago Costa | J68: Gerente Contas a Receber e Centro de Serviços Compartilhados | K68: (11) 5400-0021 | N68: thiago.costa@nutrien.com | O68: emerson.freitas@nutrien.com | P68: Emerson Freitas | Q68: Gerente de Tesouraria | Tesouraria Estratégica | S68: emerson.freitas@nutrien.com | T68: 3009813.4 | U68: A | V68: =IFERROR(VLOOKUP(U68,Assumptions!$A$7:$D$11,2,FALSE),0) | W68: =MAX(0.5,IFERROR(VLOOKUP(U68,Assumptions!$A$7:$D$11,3,FALSE),3)+IFERROR(VLOOKUP(U68,Assumptions!$A$7:$D$11,4,FALSE),8)/2-IF(AN68="",0,YEAR(TODAY())-AN68)) | X68: =T68*V68/(1+Assumptions!$B$3)^W68 | Y68: =IF(T68=0,"",ROUND(X68/T68*100,1)) | Z68: =X68*Assumptions!$B$4 | AA68: =IF(T68=0,"",ROUND(Z68/T68*100,1)) | AB68: =X68-Z68 | AC68: =IF(T68=0,"",ROUND((X68-Z68)/T68*100,1)) | AD68: CONFIRMED | AE68: https://stenius.com.br/wp-content/uploads/2026/06/EDITAL-GRUPO-3E.pdf | AF68: p16 r30 | AG68: p16: R$ 3.009.813,42 | AH68: DEBTOR_LIST | AI68: 2026-06-22 | AJ68: OK_NO_TOTALS | AK68: 5341375-33.2026.8.09.0049 | AL68: TJGO | AM68: ACTIVE | AN68: 2026 | AO68: plan/homologation document found | AP68: SAO PAULO | AQ68: SP | AR68: Comércio atacadista de defensivos agrícolas, adubos, fertilizantes e corretivos do solo | AS68: DEMAIS | AT68: LARGE CORP | AU68: 88305859 | AV68: 1 | AW68: ROWS:p16r30 UNRECONCILED_SOURCE
A69: REICHENBACH EQUIPAMENTOS INDUSTRIA E COMERCIO LTDA | B69: 2002544.3 | C69: Conduscabos Brasil Indústria Comércio de | D69: NEW | I69: Curt Reichenbach | J69: General Manager | K69: (11) 4181-5054 | N69: curt@reichenbach.com.br | O69: allan@reichenbach.com.br | P69: Allan Reichenbach | Q69: Business Development Manager (ex Controller, owner family) | S69: allan@reichenbach.com.br | T69: 2002544.3 | U69: B | V69: =IFERROR(VLOOKUP(U69,Assumptions!$A$7:$D$11,2,FALSE),0) | W69: =MAX(0.5,IFERROR(VLOOKUP(U69,Assumptions!$A$7:$D$11,3,FALSE),3)+IFERROR(VLOOKUP(U69,Assumptions!$A$7:$D$11,4,FALSE),8)/2-IF(AN69="",0,YEAR(TODAY())-AN69)) | X69: =T69*V69/(1+Assumptions!$B$3)^W69 | Y69: =IF(T69=0,"",ROUND(X69/T69*100,1)) | Z69: =X69*Assumptions!$B$4 | AA69: =IF(T69=0,"",ROUND(Z69/T69*100,1)) | AB69: =X69-Z69 | AC69: =IF(T69=0,"",ROUND((X69-Z69)/T69*100,1)) | AD69: ESTIMATED | AE69: https://assistjud.com.br/wp-content/uploads/elementor/forms/65098c80a5824.pdf | AF69: p19 r6 | AG69: p19: R$ 2.002.544,34 | AH69: AJ_LIST | AI69: 2023-09-18 | AJ69: OK_NO_TOTALS | AK69: 8005129-09.2023.8.05.0039 | AL69: TJBA | AM69: ACTIVE | AN69: 2023 | AO69: live case, no plan document yet | AP69: CARAPICUIBA | AQ69: SP | AR69: Fabricação de outras máquinas e equipamentos de uso geral não especificados anteriormente, peças e acessórios | AS69: DEMAIS | AT69: MID-MARKET | AU69: 71799001 | AV69: 1 | AW69: ROWS:p19r6 UNRECONCILED_SOURCE
A70: AGRO INDUSTRIA NUTRIHORTO LTDA | B70: 1993755.4 | C70: BBR AGRO SUPLEMENTOS LTDA EM RECUPERACAO JUDICIAL | D70: NEW | I70: Valeria Zuca | J70: Director | K70: (19) 3199-1270 | T70: 1993755.4 | U70: B | V70: =IFERROR(VLOOKUP(U70,Assumptions!$A$7:$D$11,2,FALSE),0) | W70: =MAX(0.5,IFERROR(VLOOKUP(U70,Assumptions!$A$7:$D$11,3,FALSE),3)+IFERROR(VLOOKUP(U70,Assumptions!$A$7:$D$11,4,FALSE),8)/2-IF(AN70="",0,YEAR(TODAY())-AN70)) | X70: =T70*V70/(1+Assumptions!$B$3)^W70 | Y70: =IF(T70=0,"",ROUND(X70/T70*100,1)) | Z70: =X70*Assumptions!$B$4 | AA70: =IF(T70=0,"",ROUND(Z70/T70*100,1)) | AB70: =X70-Z70 | AC70: =IF(T70=0,"",ROUND((X70-Z70)/T70*100,1)) | AD70: ESTIMATED | AE70: https://ajruiz.com.br/sites/default/files/public/arquivos-processos/2026-06/alto_uruguai_qgc_junho.2026.pdf | AF70: p1 r3 | AG70: p1: R$ 1.993.755,38 | AH70: UNKNOWN | AJ70: OK | AK70: 5012743-51.2023.8.24.0019 | AL70: TJSC | AM70: ACTIVE | AN70: 2023 | AO70: live case, no plan document yet | AP70: MONTE MOR | AQ70: SP | AR70: Recuperação de materiais não especificados anteriormente | AS70: DEMAIS | AT70: MID-MARKET | AU70: 29652131 | AV70: 1 | AW70: ROWS:p1r3 VALUE_COL:Valor_Do_Crédito
A71: SUZANO S.A. | B71: 5686333.3 | D71: NEW | I71: Erik Santos | J71: Analista Contas a Receber Sênior - CSC | K71: (11) 3636-5000 | O71: fabiolira@suzano.com.br | P71: Fabio Lira | Q71: Analista de Contas a Receber Jr | S71: fabiolira@suzano.com.br | T71: 5686333.3 | U71: ? | V71: =IFERROR(VLOOKUP(U71,Assumptions!$A$7:$D$11,2,FALSE),0) | W71: =MAX(0.5,IFERROR(VLOOKUP(U71,Assumptions!$A$7:$D$11,3,FALSE),3)+IFERROR(VLOOKUP(U71,Assumptions!$A$7:$D$11,4,FALSE),8)/2-IF(AN71="",0,YEAR(TODAY())-AN71)) | X71: =T71*V71/(1+Assumptions!$B$3)^W71 | Y71: =IF(T71=0,"",ROUND(X71/T71*100,1)) | Z71: =X71*Assumptions!$B$4 | AA71: =IF(T71=0,"",ROUND(Z71/T71*100,1)) | AB71: =X71-Z71 | AC71: =IF(T71=0,"",ROUND((X71-Z71)/T71*100,1)) | AD71: UNKNOWN | AE71: https://ajruiz.com.br/sites/default/files/public/arquivos-processos/2023-11/4_relacao_de_credores_analitica_art._51_iii_da_lre.pdf | AF71: p4 r14 | AG71: p4: R$ 5.686.333,34 | AH71: UNKNOWN | AJ71: OK | AK71: (not printed) | AO71: RJ case number not identified on the document | AP71: SALVADOR | AQ71: BA | AR71: Fabricação de celulose e outras pastas para a fabricação de papel | AS71: DEMAIS | AT71: LARGE CORP | AU71: 16404287 | AV71: 1 | AW71: ROWS:p4r14 CASE_NUMBER_CORRECTED
A72: VEGETAL AGRONEGOCIOS LTDA | B72: 3014807.2 | C72: NORTESUL COMERCIAL AGRICOLA LTDA EM RECUPERACAO JUDICIAL | D72: NEW | I72: Phelipy Goulart | J72: Administrative and Financial Manager | K72: (61) 3234-8485 | N72: phelipy@vegetalagro.com.br | O72: lidiane@vegetalagro.com.br | P72: Lidiane Fernandes | Q72: Gestora de Crédito e Cobrança. | S72: lidiane@vegetalagro.com.br | T72: 3014807.2 | U72: B | V72: =IFERROR(VLOOKUP(U72,Assumptions!$A$7:$D$11,2,FALSE),0) | W72: =MAX(0.5,IFERROR(VLOOKUP(U72,Assumptions!$A$7:$D$11,3,FALSE),3)+IFERROR(VLOOKUP(U72,Assumptions!$A$7:$D$11,4,FALSE),8)/2-IF(AN72="",0,YEAR(TODAY())-AN72)) | X72: =T72*V72/(1+Assumptions!$B$3)^W72 | Y72: =IF(T72=0,"",ROUND(X72/T72*100,1)) | Z72: =X72*Assumptions!$B$4 | AA72: =IF(T72=0,"",ROUND(Z72/T72*100,1)) | AB72: =X72-Z72 | AC72: =IF(T72=0,"",ROUND((X72-Z72)/T72*100,1)) | AD72: ESTIMATED | AE72: https://lrflideres.com.br/wp-content/plugins/download-attachments/includes/download.php?id=6879 | AF72: p2 r13 | AG72: p2: R$ 3.014.807,20 | AH72: AJ_LIST | AI72: 2026-01-15 | AJ72: OK | AK72: 0804401-51.2025.8.14.0039 | AL72: TJPA | AM72: ACTIVE | AN72: 2025 | AO72: live case, no plan document yet | AP72: BRASILIA | AQ72: DF | AR72: Comércio atacadista de defensivos agrícolas, adubos, fertilizantes e corretivos do solo | AS72: DEMAIS | AT72: MID-MARKET | AU72: 05429994 | AV72: 1 | AW72: ROWS:p2r13
A73: TRESBOMM COMERCIO E EXPORTACAO DE GRAOS LTDA EM RECUPERACAO JUDICIAL | B73: 2398511.3 | D73: NEW | I73: Rafaela Radtke | J73: Coordenadora de Controladoria | K73: (44) 3649-1240 | N73: rafaela.sereniski@bomm.com.br | O73: leandro@bomm.com.br | P73: Leandro Rosa | Q73: Gerente de Agropecuária | S73: leandro@bomm.com.br | T73: 2398511.3 | U73: B | V73: =IFERROR(VLOOKUP(U73,Assumptions!$A$7:$D$11,2,FALSE),0) | W73: =MAX(0.5,IFERROR(VLOOKUP(U73,Assumptions!$A$7:$D$11,3,FALSE),3)+IFERROR(VLOOKUP(U73,Assumptions!$A$7:$D$11,4,FALSE),8)/2-IF(AN73="",0,YEAR(TODAY())-AN73)) | X73: =T73*V73/(1+Assumptions!$B$3)^W73 | Y73: =IF(T73=0,"",ROUND(X73/T73*100,1)) | Z73: =X73*Assumptions!$B$4 | AA73: =IF(T73=0,"",ROUND(Z73/T73*100,1)) | AB73: =X73-Z73 | AC73: =IF(T73=0,"",ROUND((X73-Z73)/T73*100,1)) | AD73: ESTIMATED | AE73: https://rlg-aj.com.br/wp-content/uploads/2024/11/07.-Relação-de-credores.pdf | AF73: p1 r36 | AG73: p1: R$ 2.398.511,33 | AH73: UNKNOWN | AJ73: OK_NO_TOTALS | AK73: 5009149-92.2024.8.24.0019 | AL73: TJSC | AM73: ACTIVE | AN73: 2024 | AO73: live case, no plan document yet | AP73: PALOTINA | AQ73: PR | AR73: Comércio atacadista de matérias-primas agrícolas não especificadas anteriormente | AS73: DEMAIS | AT73: MID-MARKET | AU73: 15660513 | AV73: 1 | AW73: ROWS:p1r36 UNRECONCILED_SOURCE
A74: GEOLAB INDUSTRIA FARMACEUTICA S/A | B74: 1918724.7 | C74: VEV COMERCIO DE MEDICAMENTOS LTDA EM RECUPERACAO JUDICIAL | D74: NEW | I74: GEORGES HAJJAR JUNIOR | J74: Presidente | K74: (62) 4015-4000 | P74: ANDRE LUIZ HAJJAR | Q74: Diretor | R74: (62) 4015-4000 | T74: 1918724.7 | U74: B | V74: =IFERROR(VLOOKUP(U74,Assumptions!$A$7:$D$11,2,FALSE),0) | W74: =MAX(0.5,IFERROR(VLOOKUP(U74,Assumptions!$A$7:$D$11,3,FALSE),3)+IFERROR(VLOOKUP(U74,Assumptions!$A$7:$D$11,4,FALSE),8)/2-IF(AN74="",0,YEAR(TODAY())-AN74)) | X74: =T74*V74/(1+Assumptions!$B$3)^W74 | Y74: =IF(T74=0,"",ROUND(X74/T74*100,1)) | Z74: =X74*Assumptions!$B$4 | AA74: =IF(T74=0,"",ROUND(Z74/T74*100,1)) | AB74: =X74-Z74 | AC74: =IF(T74=0,"",ROUND((X74-Z74)/T74*100,1)) | AD74: ESTIMATED | AE74: https://marquesadmjudicial.com.br/sgc/download.php?file=files/processo_documento/processo_documento15293208032024_1_.pdf&nome=Relação Nominal de Credores da AJ-Sintética | AF74: p26 r3 | AG74: p26: R$ 1.918.724,72 | AH74: AJ_LIST | AI74: 2023-03-02 | AJ74: QUARANTINED | AK74: 0005010-98.2023.8.16.0001 | AL74: TJPR | AM74: ACTIVE | AN74: 2023 | AO74: live case, no plan document yet | AP74: ANAPOLIS | AQ74: GO | AR74: Fabricação de medicamentos alopáticos para uso humano | AS74: DEMAIS | AT74: LARGE CORP | AU74: 03485572 | AV74: 1 | AW74: PARTIAL_DOC_CLASS_III_RECONCILED ROWS:p26r3
A75: SOCIEDADE ESPORTIVA PALMEIRAS | B75: 1867912.2 | C75: CLUBE NAUTICO CAPIBARIBE - EM RECUPERACAO JUDICIAL | D75: NEW | I75: Luciano Cavalli | J75: Diretor Executivo Administrativo | K75: (11) 3874-6500 | L75: (11) 3679-7859 | N75: luciano.cavalli@palmeiras.com.br | T75: 1867912.2 | U75: B | V75: =IFERROR(VLOOKUP(U75,Assumptions!$A$7:$D$11,2,FALSE),0) | W75: =MAX(0.5,IFERROR(VLOOKUP(U75,Assumptions!$A$7:$D$11,3,FALSE),3)+IFERROR(VLOOKUP(U75,Assumptions!$A$7:$D$11,4,FALSE),8)/2-IF(AN75="",0,YEAR(TODAY())-AN75)) | X75: =T75*V75/(1+Assumptions!$B$3)^W75 | Y75: =IF(T75=0,"",ROUND(X75/T75*100,1)) | Z75: =X75*Assumptions!$B$4 | AA75: =IF(T75=0,"",ROUND(Z75/T75*100,1)) | AB75: =X75-Z75 | AC75: =IF(T75=0,"",ROUND((X75-Z75)/T75*100,1)) | AD75: ESTIMATED | AE75: https://lrflideres.com.br/wp-content/plugins/download-attachments/includes/download.php?id=5589 | AF75: p12 r43 | AG75: p12: R$ 1.867.912,24 | AH75: AJ_LIST | AI75: 2023-11-27 | AJ75: QUARANTINED | AK75: 0011283-80.2023.8.17.2001 | AL75: TJPE | AM75: ACTIVE | AN75: 2023 | AO75: live case, no plan document yet | AP75: SAO PAULO | AQ75: SP | AR75: Clubes sociais, esportivos e similares | AS75: DEMAIS | AT75: MID-MARKET | AU75: 61750345 | AV75: 1 | AW75: PARTIAL_DOC_CLASS_III_RECONCILED ROWS:p12r43
A76: IRANY COMERCIO EXTERIOR LTDA | B76: 2916553.7 | C76: BACKES SOLUCOES LTDA | D76: NEW | I76: IRANY GASPAR PACHECO DOS SANTOS | J76: Sócio-Administrador | K76: (42) 9871-7035 | T76: 2916553.7 | U76: B | V76: =IFERROR(VLOOKUP(U76,Assumptions!$A$7:$D$11,2,FALSE),0) | W76: =MAX(0.5,IFERROR(VLOOKUP(U76,Assumptions!$A$7:$D$11,3,FALSE),3)+IFERROR(VLOOKUP(U76,Assumptions!$A$7:$D$11,4,FALSE),8)/2-IF(AN76="",0,YEAR(TODAY())-AN76)) | X76: =T76*V76/(1+Assumptions!$B$3)^W76 | Y76: =IF(T76=0,"",ROUND(X76/T76*100,1)) | Z76: =X76*Assumptions!$B$4 | AA76: =IF(T76=0,"",ROUND(Z76/T76*100,1)) | AB76: =X76-Z76 | AC76: =IF(T76=0,"",ROUND((X76-Z76)/T76*100,1)) | AD76: ESTIMATED | AE76: https://marquesadmjudicial.com.br/sgc/download.php?file=files/processo_documento/processo_documento18581929042026_1_.pdf&nome=3º Edital - Relação de Credores e PRJ | AF76: p1 r46 | AG76: p1: R$ 2.916.553,74 | AH76: AJ_LIST | AI76: 2025-09-12 | AJ76: OK_NO_TOTALS | AK76: 0043030-30.2025.8.16.0021 | AL76: TJPR | AM76: ACTIVE | AN76: 2025 | AO76: live case, no plan document yet | AP76: ITAPOA | AQ76: SC | AR76: Comércio atacadista de cereais e leguminosas beneficiados | AS76: DEMAIS | AT76: MID-MARKET | AU76: 47320705 | AV76: 1 | AW76: ROWS:p1r46 UNRECONCILED_SOURCE
A77: B S DISTRIBUIDORA DE PRODUTOS DE HIGIENE LTDA | B77: 1819744.5 | C77: VEV COMERCIO DE MEDICAMENTOS LTDA EM RECUPERACAO JUDICIAL | D77: NEW | I77: ANA CAROLINA DE MORAES FRANZINE | J77: Sócio-Administrador | K77: (11) 5103-5350 | P77: RODRIGO REBELO DE MORAES | Q77: Sócio-Administrador | R77: (11) 5103-5350 | T77: 1819744.5 | U77: B | V77: =IFERROR(VLOOKUP(U77,Assumptions!$A$7:$D$11,2,FALSE),0) | W77: =MAX(0.5,IFERROR(VLOOKUP(U77,Assumptions!$A$7:$D$11,3,FALSE),3)+IFERROR(VLOOKUP(U77,Assumptions!$A$7:$D$11,4,FALSE),8)/2-IF(AN77="",0,YEAR(TODAY())-AN77)) | X77: =T77*V77/(1+Assumptions!$B$3)^W77 | Y77: =IF(T77=0,"",ROUND(X77/T77*100,1)) | Z77: =X77*Assumptions!$B$4 | AA77: =IF(T77=0,"",ROUND(Z77/T77*100,1)) | AB77: =X77-Z77 | AC77: =IF(T77=0,"",ROUND((X77-Z77)/T77*100,1)) | AD77: ESTIMATED | AE77: https://marquesadmjudicial.com.br/sgc/download.php?file=files/processo_documento/processo_documento15293208032024_1_.pdf&nome=Relação Nominal de Credores da AJ-Sintética | AF77: p20 r3 | AG77: p20: R$ 1.819.744,46 | AH77: AJ_LIST | AI77: 2023-03-02 | AJ77: QUARANTINED | AK77: 0005010-98.2023.8.16.0001 | AL77: TJPR | AM77: ACTIVE | AN77: 2023 | AO77: live case, no plan document yet | AP77: SAO PAULO | AQ77: SP | AR77: Comércio atacadista de cosméticos e produtos de perfumaria | AS77: DEMAIS | AT77: MID-MARKET | AU77: 43587344 | AV77: 1 | AW77: PARTIAL_DOC_CLASS_III_RECONCILED ROWS:p20r3
A78: AGRO SAFRA INDUSTRIA E COMERCIO DE ADUBOS LTDA | B78: 1685996.3 | C78: JOAQUIM JOSE XAVIER ISAAC | D78: NEW | I78: Almir Souza | J78: Manager | K78: (01) 13687-5766 | N78: rh@agro-safra.com.br | P78: JOAQUIM JOSE XAVIER ISAAC | Q78: Sócio-Administrador | R78: (01) 13687-5766 | T78: 1685996.3 | U78: A | V78: =IFERROR(VLOOKUP(U78,Assumptions!$A$7:$D$11,2,FALSE),0) | W78: =MAX(0.5,IFERROR(VLOOKUP(U78,Assumptions!$A$7:$D$11,3,FALSE),3)+IFERROR(VLOOKUP(U78,Assumptions!$A$7:$D$11,4,FALSE),8)/2-IF(AN78="",0,YEAR(TODAY())-AN78)) | X78: =T78*V78/(1+Assumptions!$B$3)^W78 | Y78: =IF(T78=0,"",ROUND(X78/T78*100,1)) | Z78: =X78*Assumptions!$B$4 | AA78: =IF(T78=0,"",ROUND(Z78/T78*100,1)) | AB78: =X78-Z78 | AC78: =IF(T78=0,"",ROUND((X78-Z78)/T78*100,1)) | AD78: CONFIRMED | AE78: https://vivanteaj.com.br/wp-content/uploads/2025/02/2a-lista-de-credores-Agro-Safra-e-outros.pdf | AF78: p3 r2 | AG78: p3: R$ 1.685.996,32 | AH78: UNKNOWN | AJ78: OK_NO_TOTALS | AK78: 1003322-70.2024.8.26.0260 | AL78: TJSP | AM78: ACTIVE | AN78: 2024 | AO78: plan/homologation document found | AP78: OSASCO | AQ78: SP | AR78: Fabricação de adubos e fertilizantes, exceto organo-minerais | AS78: DEMAIS | AT78: MID-MARKET | AU78: 47827332 | AV78: 1 | AW78: LONG_CHUNK MULTI_ROOT ROWS:p3r2 UNRECONCILED_SOURCE
A79: CAMBUCI S/A | B79: 1782661.2 | C79: CLUBE NAUTICO CAPIBARIBE - EM RECUPERACAO JUDICIAL | D79: NEW | I79: ALEXANDRE SCHULER | J79: Presidente | K79: (11) 4713-9500 | P79: EMERSON TSUNEJI SHIROMARU | Q79: Diretor | R79: (11) 4713-9500 | T79: 1782661.2 | U79: B | V79: =IFERROR(VLOOKUP(U79,Assumptions!$A$7:$D$11,2,FALSE),0) | W79: =MAX(0.5,IFERROR(VLOOKUP(U79,Assumptions!$A$7:$D$11,3,FALSE),3)+IFERROR(VLOOKUP(U79,Assumptions!$A$7:$D$11,4,FALSE),8)/2-IF(AN79="",0,YEAR(TODAY())-AN79)) | X79: =T79*V79/(1+Assumptions!$B$3)^W79 | Y79: =IF(T79=0,"",ROUND(X79/T79*100,1)) | Z79: =X79*Assumptions!$B$4 | AA79: =IF(T79=0,"",ROUND(Z79/T79*100,1)) | AB79: =X79-Z79 | AC79: =IF(T79=0,"",ROUND((X79-Z79)/T79*100,1)) | AD79: ESTIMATED | AE79: https://lrflideres.com.br/wp-content/plugins/download-attachments/includes/download.php?id=5589 | AF79: p11 r68 | AG79: p11: R$ 1.782.661,24 | AH79: AJ_LIST | AI79: 2023-11-27 | AJ79: QUARANTINED | AK79: 0011283-80.2023.8.17.2001 | AL79: TJPE | AM79: ACTIVE | AN79: 2023 | AO79: live case, no plan document yet | AP79: SAO PAULO | AQ79: SP | AR79: Fabricação de artefatos de couro não especificados anteriormente | AS79: DEMAIS | AT79: LARGE CORP | AU79: 61088894 | AV79: 1 | AW79: PARTIAL_DOC_CLASS_III_RECONCILED ROWS:p11r68
A80: DISCOMED COMERCIO DE PRODUTOS HOSPITALARES LTDA | B80: 1372648.4 | C80: ASSOCIACAO DE CARIDADE SANTA CASA DE RIO GRANDE | D80: NEW | I80: David Feijo | J80: Financial Coordinator | N80: david@discomed.com.br | O80: juliana@discomed.com.br | P80: Juliana Silveira | Q80: Financial / Controladoria | S80: juliana@discomed.com.br | T80: 1372648.4 | U80: B | V80: =IFERROR(VLOOKUP(U80,Assumptions!$A$7:$D$11,2,FALSE),0) | W80: =MAX(0.5,IFERROR(VLOOKUP(U80,Assumptions!$A$7:$D$11,3,FALSE),3)+IFERROR(VLOOKUP(U80,Assumptions!$A$7:$D$11,4,FALSE),8)/2-IF(AN80="",0,YEAR(TODAY())-AN80)) | X80: =T80*V80/(1+Assumptions!$B$3)^W80 | Y80: =IF(T80=0,"",ROUND(X80/T80*100,1)) | Z80: =X80*Assumptions!$B$4 | AA80: =IF(T80=0,"",ROUND(Z80/T80*100,1)) | AB80: =X80-Z80 | AC80: =IF(T80=0,"",ROUND((X80-Z80)/T80*100,1)) | AD80: ESTIMATED | AE80: https://scalzilliaj.com.br/sgc/download.php?file=files/processo_documento/processo_documento09120721032023_1_.pdf&nome=15 - Edital do art. 7º, §2º e 53 da Lei 11.101/2005 (segunda lista de credores e recebimento do plano)) | AF80: p27 r9 | AG80: p27: R$ 1.372.648,38 | AH80: AJ_LIST | AI80: 2023-03-21 | AJ80: OK_NO_TOTALS | AK80: 5012306-16.2022.8.21.0023 | AL80: TJRS | AM80: ACTIVE | AN80: 2022 | AO80: live case, no plan document yet | AP80: PORTO ALEGRE | AQ80: RS | AR80: Comércio atacadista de instrumentos e materiais para uso médico, cirúrgico, hospitalar e de laboratórios | AS80: DEMAIS | AT80: MID-MARKET | AU80: 00417145 | AV80: 1 | AW80: ROWS:p27r9 UNRECONCILED_SOURCE
A81: VIBRA ENERGIA S.A | B81: 5004769.6 | C81: EGESA ENGENHARIA S/A (Consórcio ETDI) | D81: NEW | I81: ERNESTO PERES POUSADA JUNIOR | J81: Presidente | K81: (21) 2354-3151 | L81: (21) 2354-3146 | P81: DANIEL DRUMOND CAMPOS E SILVA | Q81: Diretor | R81: (21) 2354-3146 | T81: 5004769.6 | U81: ? | V81: =IFERROR(VLOOKUP(U81,Assumptions!$A$7:$D$11,2,FALSE),0) | W81: =MAX(0.5,IFERROR(VLOOKUP(U81,Assumptions!$A$7:$D$11,3,FALSE),3)+IFERROR(VLOOKUP(U81,Assumptions!$A$7:$D$11,4,FALSE),8)/2-IF(AN81="",0,YEAR(TODAY())-AN81)) | X81: =T81*V81/(1+Assumptions!$B$3)^W81 | Y81: =IF(T81=0,"",ROUND(X81/T81*100,1)) | Z81: =X81*Assumptions!$B$4 | AA81: =IF(T81=0,"",ROUND(Z81/T81*100,1)) | AB81: =X81-Z81 | AC81: =IF(T81=0,"",ROUND((X81-Z81)/T81*100,1)) | AD81: UNKNOWN | AE81: https://scalzilliaj.com.br/sgc/download.php?file=files/processo_documento/processo_documento09514021082025_1_.pdf&nome=04 - Relação de credores das Recuperandas | AF81: p71 r8; p76 r5 | AG81: p71: R$ 396.274,51; p76: R$ 4.608.495,09 | AH81: DEBTOR_LIST | AJ81: OK | AK81: (not printed) | AO81: RJ case number not identified on the document | AP81: RIO DE JANEIRO | AQ81: RJ | AR81: Comércio atacadista de álcool carburante, biodiesel, gasolina e demais derivados de petróleo, exceto lubrificantes, não realizado por transportador re | AS81: DEMAIS | AT81: LARGE CORP | AU81: 34274233 | AV81: 2 | AW81: ROWS:p71r8,p76r5 VALUE_COL:Valor_Atualizado CASE_NUMBER_CORRECTED
A82: GERMED FARMACEUTICA LTDA | B82: 1695831.1 | C82: VEV COMERCIO DE MEDICAMENTOS LTDA EM RECUPERACAO JUDICIAL | D82: NEW | I82: GUSTAVO ANDRE REGIS DUTRA SVENSSON | J82: Administrador | K82: (19) 3887-9800 | P82: TATIANA AZEVEDO VILLELA SANTOS FONTES | Q82: Administrador | R82: (19) 3887-9800 | T82: 1695831.1 | U82: B | V82: =IFERROR(VLOOKUP(U82,Assumptions!$A$7:$D$11,2,FALSE),0) | W82: =MAX(0.5,IFERROR(VLOOKUP(U82,Assumptions!$A$7:$D$11,3,FALSE),3)+IFERROR(VLOOKUP(U82,Assumptions!$A$7:$D$11,4,FALSE),8)/2-IF(AN82="",0,YEAR(TODAY())-AN82)) | X82: =T82*V82/(1+Assumptions!$B$3)^W82 | Y82: =IF(T82=0,"",ROUND(X82/T82*100,1)) | Z82: =X82*Assumptions!$B$4 | AA82: =IF(T82=0,"",ROUND(Z82/T82*100,1)) | AB82: =X82-Z82 | AC82: =IF(T82=0,"",ROUND((X82-Z82)/T82*100,1)) | AD82: ESTIMATED | AE82: https://marquesadmjudicial.com.br/sgc/download.php?file=files/processo_documento/processo_documento15293208032024_1_.pdf&nome=Relação Nominal de Credores da AJ-Sintética | AF82: p26 r5 | AG82: p26: R$ 1.695.831,10 | AH82: AJ_LIST | AI82: 2023-03-02 | AJ82: QUARANTINED | AK82: 0005010-98.2023.8.16.0001 | AL82: TJPR | AM82: ACTIVE | AN82: 2023 | AO82: live case, no plan document yet | AP82: HORTOLANDIA | AQ82: SP | AR82: Fabricação de medicamentos alopáticos para uso humano | AS82: DEMAIS | AT82: MID-MARKET | AU82: 45992062 | AV82: 1 | AW82: PARTIAL_DOC_CLASS_III_RECONCILED ROWS:p26r5
A83: WHITE MARTINS GASES INDUSTRIAIS LTDA | B83: 1341862.7 | C83: ASSOCIACAO DE CARIDADE SANTA CASA DE RIO GRANDE | D83: NEW | I83: Claudio Ferreira | J83: Supervisor Contas a Receber | K83: (21) 3279-9000 | P83: Livia Pestana | Q83: Supervisor de Cobrança / Contas a Receber | T83: 1341862.7 | U83: B | V83: =IFERROR(VLOOKUP(U83,Assumptions!$A$7:$D$11,2,FALSE),0) | W83: =MAX(0.5,IFERROR(VLOOKUP(U83,Assumptions!$A$7:$D$11,3,FALSE),3)+IFERROR(VLOOKUP(U83,Assumptions!$A$7:$D$11,4,FALSE),8)/2-IF(AN83="",0,YEAR(TODAY())-AN83)) | X83: =T83*V83/(1+Assumptions!$B$3)^W83 | Y83: =IF(T83=0,"",ROUND(X83/T83*100,1)) | Z83: =X83*Assumptions!$B$4 | AA83: =IF(T83=0,"",ROUND(Z83/T83*100,1)) | AB83: =X83-Z83 | AC83: =IF(T83=0,"",ROUND((X83-Z83)/T83*100,1)) | AD83: ESTIMATED | AE83: https://scalzilliaj.com.br/sgc/download.php?file=files/processo_documento/processo_documento09120721032023_1_.pdf&nome=15 - Edital do art. 7º, §2º e 53 da Lei 11.101/2005 (segunda lista de credores e recebimento do plano)) | AF83: p30 r37 | AG83: p30: R$ 1.341.862,73 | AH83: AJ_LIST | AI83: 2023-03-21 | AJ83: OK_NO_TOTALS | AK83: 5012306-16.2022.8.21.0023 | AL83: TJRS | AM83: ACTIVE | AN83: 2022 | AO83: live case, no plan document yet | AP83: RIO DE JANEIRO | AQ83: RJ | AR83: Atividades de consultoria em gestão empresarial, exceto consultoria técnica específica | AS83: DEMAIS | AT83: LARGE CORP | AU83: 35820448 | AV83: 1 | AW83: ROWS:p30r37 UNRECONCILED_SOURCE
A84: ADM DO BRASIL LTDA | B84: 2086675 | D84: NEW | I84: ANDREIELI RIBEIRO PINTO | J84: Administrador | K84: (11) 5185-3500 | L84: (11) 5185-3649 | P84: DOMINGO ALEJANDRO LASTRA | Q84: Administrador | R84: (11) 5185-3649 | T84: 2086675 | U84: B | V84: =IFERROR(VLOOKUP(U84,Assumptions!$A$7:$D$11,2,FALSE),0) | W84: =MAX(0.5,IFERROR(VLOOKUP(U84,Assumptions!$A$7:$D$11,3,FALSE),3)+IFERROR(VLOOKUP(U84,Assumptions!$A$7:$D$11,4,FALSE),8)/2-IF(AN84="",0,YEAR(TODAY())-AN84)) | X84: =T84*V84/(1+Assumptions!$B$3)^W84 | Y84: =IF(T84=0,"",ROUND(X84/T84*100,1)) | Z84: =X84*Assumptions!$B$4 | AA84: =IF(T84=0,"",ROUND(Z84/T84*100,1)) | AB84: =X84-Z84 | AC84: =IF(T84=0,"",ROUND((X84-Z84)/T84*100,1)) | AD84: ESTIMATED | AE84: https://rlg-aj.com.br/wp-content/uploads/2024/11/07.-Relação-de-credores.pdf | AF84: p1 r21 | AG84: p1: R$ 2.086.675,04 | AH84: UNKNOWN | AJ84: OK_NO_TOTALS | AK84: 5009149-92.2024.8.24.0019 | AL84: TJSC | AM84: ACTIVE | AN84: 2024 | AO84: live case, no plan document yet | AP84: VITORIA | AQ84: ES | AR84: Comércio atacadista de matérias-primas agrícolas não especificadas anteriormente | AS84: DEMAIS | AT84: LARGE CORP | AU84: 02003402 | AV84: 1 | AW84: ROWS:p1r21 UNRECONCILED_SOURCE
A85: TRES TENTOS AGROINDUSTRIAL S/A | B85: 2076705.8 | D85: NEW | I85: Cristiano Costa | J85: CFO | K85: (55) 3372-3700 | L85: (55) 3372-3718 | N85: cristiano.costa@3tentos.com.br | O85: everson.ribas@3tentos.com.br | P85: Everson Ribas | Q85: Analista de Crédito e Cobrança - Pleno | S85: everson.ribas@3tentos.com.br | T85: 2076705.8 | U85: B | V85: =IFERROR(VLOOKUP(U85,Assumptions!$A$7:$D$11,2,FALSE),0) | W85: =MAX(0.5,IFERROR(VLOOKUP(U85,Assumptions!$A$7:$D$11,3,FALSE),3)+IFERROR(VLOOKUP(U85,Assumptions!$A$7:$D$11,4,FALSE),8)/2-IF(AN85="",0,YEAR(TODAY())-AN85)) | X85: =T85*V85/(1+Assumptions!$B$3)^W85 | Y85: =IF(T85=0,"",ROUND(X85/T85*100,1)) | Z85: =X85*Assumptions!$B$4 | AA85: =IF(T85=0,"",ROUND(Z85/T85*100,1)) | AB85: =X85-Z85 | AC85: =IF(T85=0,"",ROUND((X85-Z85)/T85*100,1)) | AD85: ESTIMATED | AE85: https://rlg-aj.com.br/wp-content/uploads/2024/11/07.-Relação-de-credores.pdf | AF85: p1 r20 | AG85: p1: R$ 2.076.705,80 | AH85: UNKNOWN | AJ85: OK_NO_TOTALS | AK85: 5009149-92.2024.8.24.0019 | AL85: TJSC | AM85: ACTIVE | AN85: 2024 | AO85: live case, no plan document yet | AP85: SANTA BARBARA DO SUL | AQ85: RS | AR85: Comércio atacadista de cereais e leguminosas beneficiados | AS85: DEMAIS | AT85: LARGE CORP | AU85: 94813102 | AV85: 1 | AW85: ROWS:p1r20 UNRECONCILED_SOURCE
A86: DACARTO INDUSTRIA E COMERCIO DE PLASTICOS LTDA | B86: 1624039.2 | C86: Conduscabos Brasil Indústria Comércio de | D86: NEW | I86: Barbara Alauck | J86: Analista de Tesouraria Sênior | K86: (11) 3658-9459 | N86: barbara.alauck@dacarto.com.br | O86: andre.pacheco@dacarto.com.br | P86: Andre Pacheco | Q86: Gerente de Contas Pleno | S86: andre.pacheco@dacarto.com.br | T86: 1624039.2 | U86: B | V86: =IFERROR(VLOOKUP(U86,Assumptions!$A$7:$D$11,2,FALSE),0) | W86: =MAX(0.5,IFERROR(VLOOKUP(U86,Assumptions!$A$7:$D$11,3,FALSE),3)+IFERROR(VLOOKUP(U86,Assumptions!$A$7:$D$11,4,FALSE),8)/2-IF(AN86="",0,YEAR(TODAY())-AN86)) | X86: =T86*V86/(1+Assumptions!$B$3)^W86 | Y86: =IF(T86=0,"",ROUND(X86/T86*100,1)) | Z86: =X86*Assumptions!$B$4 | AA86: =IF(T86=0,"",ROUND(Z86/T86*100,1)) | AB86: =X86-Z86 | AC86: =IF(T86=0,"",ROUND((X86-Z86)/T86*100,1)) | AD86: ESTIMATED | AE86: https://assistjud.com.br/wp-content/uploads/elementor/forms/65098c80a5824.pdf | AF86: p6 r12; p6 r13 | AG86: p6: R$ 534.318,75; p6: R$ 1.089.720,44 | AH86: AJ_LIST | AI86: 2023-09-18 | AJ86: OK_NO_TOTALS | AK86: 8005129-09.2023.8.05.0039 | AL86: TJBA | AM86: ACTIVE | AN86: 2023 | AO86: live case, no plan document yet | AP86: OSASCO | AQ86: SP | AR86: Fabricação de artefatos de material plástico para outros usos não especificados anteriormente | AS86: DEMAIS | AT86: MID-MARKET | AU86: 62143847 | AV86: 2 | AW86: ROWS:p6r12,p6r13 UNRECONCILED_SOURCE
A87: TRANSPORTADORA MARCAN LTDA. | B87: 4757313 | C87: EGESA ENGENHARIA S/A (Consórcio ETDI) | D87: NEW | I87: GERVASIO TASSI FILHO | J87: Sócio-Administrador | K87: (81) 3543-0330 | L87: (81) 9267-7488 | P87: MARIA EDUARDA QUEIROZ TASSI | Q87: Sócio-Administrador | R87: (81) 9267-7488 | T87: 4757313 | U87: ? | V87: =IFERROR(VLOOKUP(U87,Assumptions!$A$7:$D$11,2,FALSE),0) | W87: =MAX(0.5,IFERROR(VLOOKUP(U87,Assumptions!$A$7:$D$11,3,FALSE),3)+IFERROR(VLOOKUP(U87,Assumptions!$A$7:$D$11,4,FALSE),8)/2-IF(AN87="",0,YEAR(TODAY())-AN87)) | X87: =T87*V87/(1+Assumptions!$B$3)^W87 | Y87: =IF(T87=0,"",ROUND(X87/T87*100,1)) | Z87: =X87*Assumptions!$B$4 | AA87: =IF(T87=0,"",ROUND(Z87/T87*100,1)) | AB87: =X87-Z87 | AC87: =IF(T87=0,"",ROUND((X87-Z87)/T87*100,1)) | AD87: UNKNOWN | AE87: https://scalzilliaj.com.br/sgc/download.php?file=files/processo_documento/processo_documento09514021082025_1_.pdf&nome=04 - Relação de credores das Recuperandas | AF87: p74 r13 | AG87: p74: R$ 4.757.312,99 | AH87: DEBTOR_LIST | AJ87: OK | AK87: (not printed) | AO87: RJ case number not identified on the document | AP87: IGARASSU | AQ87: PE | AR87: Transporte rodoviário coletivo de passageiros, com itinerário fixo, intermunicipal em região metropolitana | AS87: DEMAIS | AT87: MID-MARKET | AU87: 19709369 | AV87: 1 | AW87: ROWS:p74r13 VALUE_COL:Valor_Atualizado CASE_NUMBER_CORRECTED
A88: FARMAX S.A. | B88: 1610365.5 | C88: VEV COMERCIO DE MEDICAMENTOS LTDA EM RECUPERACAO JUDICIAL | D88: NEW | I88: Rodrigo Amoroso | J88: Head de Tesouraria e Controladoria | K88: (37) 2101-9696 | L88: (37) 2101-9603 | O88: joziane.rachid@farmax.com.br | P88: Joziane Rachid | Q88: Analista Crédito e Cobrança | S88: joziane.rachid@farmax.com.br | T88: 1610365.5 | U88: B | V88: =IFERROR(VLOOKUP(U88,Assumptions!$A$7:$D$11,2,FALSE),0) | W88: =MAX(0.5,IFERROR(VLOOKUP(U88,Assumptions!$A$7:$D$11,3,FALSE),3)+IFERROR(VLOOKUP(U88,Assumptions!$A$7:$D$11,4,FALSE),8)/2-IF(AN88="",0,YEAR(TODAY())-AN88)) | X88: =T88*V88/(1+Assumptions!$B$3)^W88 | Y88: =IF(T88=0,"",ROUND(X88/T88*100,1)) | Z88: =X88*Assumptions!$B$4 | AA88: =IF(T88=0,"",ROUND(Z88/T88*100,1)) | AB88: =X88-Z88 | AC88: =IF(T88=0,"",ROUND((X88-Z88)/T88*100,1)) | AD88: ESTIMATED | AE88: https://marquesadmjudicial.com.br/sgc/download.php?file=files/processo_documento/processo_documento15293208032024_1_.pdf&nome=Relação Nominal de Credores da AJ-Sintética | AF88: p25 r6 | AG88: p25: R$ 1.610.365,54 | AH88: AJ_LIST | AI88: 2023-03-02 | AJ88: QUARANTINED | AK88: 0005010-98.2023.8.16.0001 | AL88: TJPR | AM88: ACTIVE | AN88: 2023 | AO88: live case, no plan document yet | AP88: DIVINOPOLIS | AQ88: MG | AR88: Fabricação de cosméticos, produtos de perfumaria e de higiene pessoal | AS88: DEMAIS | AT88: LARGE CORP | AU88: 21759758 | AV88: 1 | AW88: PARTIAL_DOC_CLASS_III_RECONCILED ROWS:p25r6
A89: ROCHE DIABETES CARE BRASIL LTDA | B89: 1608447.8 | C89: VEV COMERCIO DE MEDICAMENTOS LTDA EM RECUPERACAO JUDICIAL | D89: NEW | I89: ANA TUNON ORRICO | J89: Administrador | K89: (11) 3719-8888 | P89: CAMILA HERNANDEZ MUSLEH | Q89: Administrador | R89: (11) 3719-8888 | T89: 1608447.8 | U89: B | V89: =IFERROR(VLOOKUP(U89,Assumptions!$A$7:$D$11,2,FALSE),0) | W89: =MAX(0.5,IFERROR(VLOOKUP(U89,Assumptions!$A$7:$D$11,3,FALSE),3)+IFERROR(VLOOKUP(U89,Assumptions!$A$7:$D$11,4,FALSE),8)/2-IF(AN89="",0,YEAR(TODAY())-AN89)) | X89: =T89*V89/(1+Assumptions!$B$3)^W89 | Y89: =IF(T89=0,"",ROUND(X89/T89*100,1)) | Z89: =X89*Assumptions!$B$4 | AA89: =IF(T89=0,"",ROUND(Z89/T89*100,1)) | AB89: =X89-Z89 | AC89: =IF(T89=0,"",ROUND((X89-Z89)/T89*100,1)) | AD89: ESTIMATED | AE89: https://marquesadmjudicial.com.br/sgc/download.php?file=files/processo_documento/processo_documento15293208032024_1_.pdf&nome=Relação Nominal de Credores da AJ-Sintética | AF89: p30 r12 | AG89: p30: R$ 1.608.447,77 | AH89: AJ_LIST | AI89: 2023-03-02 | AJ89: QUARANTINED | AK89: 0005010-98.2023.8.16.0001 | AL89: TJPR | AM89: ACTIVE | AN89: 2023 | AO89: live case, no plan document yet | AP89: SAO PAULO | AQ89: SP | AR89: Serviços combinados de escritório e apoio administrativo | AS89: DEMAIS | AT89: MID-MARKET | AU89: 23552212 | AV89: 1 | AW89: PARTIAL_DOC_CLASS_III_RECONCILED ROWS:p30r12
A90: TECELAGEM JOLITEX LTDA | B90: 1828397.2 | D90: NEW | I90: Natalia Nery | J90: Coordenadora Financeira – Crédito e Cobrança | N90: natalia.nery@jolitex.com | P90: Moise Sutton | Q90: Gerente Financeiro & Planejamento de Custos | T90: 1828397.2 | U90: C | V90: =IFERROR(VLOOKUP(U90,Assumptions!$A$7:$D$11,2,FALSE),0) | W90: =MAX(0.5,IFERROR(VLOOKUP(U90,Assumptions!$A$7:$D$11,3,FALSE),3)+IFERROR(VLOOKUP(U90,Assumptions!$A$7:$D$11,4,FALSE),8)/2-IF(AN90="",0,YEAR(TODAY())-AN90)) | X90: =T90*V90/(1+Assumptions!$B$3)^W90 | Y90: =IF(T90=0,"",ROUND(X90/T90*100,1)) | Z90: =X90*Assumptions!$B$4 | AA90: =IF(T90=0,"",ROUND(Z90/T90*100,1)) | AB90: =X90-Z90 | AC90: =IF(T90=0,"",ROUND((X90-Z90)/T90*100,1)) | AD90: UNKNOWN | AE90: https://administradorajudicialgs.com.br/wp-content/uploads/2024/12/relacao-de-credores-da-falida.pdf | AF90: p18 r50 | AG90: p18: R$ 1.828.397,18 | AH90: UNKNOWN | AI90: 2025-03-25 | AJ90: OK_NO_TOTALS | AK90: 0005010-50.2013.8.24.0026 | AL90: TJ | AN90: 2013 | AO90: 13y since filing, no plan document | AP90: AMERICANA | AQ90: SP | AR90: Preparação e fiação de fibras de algodão | AS90: DEMAIS | AT90: MID-MARKET | AU90: 43237254 | AV90: 1 | AW90: ROWS:p18r50 UNRECONCILED_SOURCE
A91: IPIRANGA PRODUTOS DE PETROLEO S.A. | B91: 4589364.3 | D91: NEW | I91: CARLOS FREDERICO RESENDE | J91: Administrador | K91: (21) 2574-5858 | P91: CRISTIANE SILVA LEITE | Q91: Diretor | R91: (21) 2574-5858 | T91: 4589364.3 | U91: ? | V91: =IFERROR(VLOOKUP(U91,Assumptions!$A$7:$D$11,2,FALSE),0) | W91: =MAX(0.5,IFERROR(VLOOKUP(U91,Assumptions!$A$7:$D$11,3,FALSE),3)+IFERROR(VLOOKUP(U91,Assumptions!$A$7:$D$11,4,FALSE),8)/2-IF(AN91="",0,YEAR(TODAY())-AN91)) | X91: =T91*V91/(1+Assumptions!$B$3)^W91 | Y91: =IF(T91=0,"",ROUND(X91/T91*100,1)) | Z91: =X91*Assumptions!$B$4 | AA91: =IF(T91=0,"",ROUND(Z91/T91*100,1)) | AB91: =X91-Z91 | AC91: =IF(T91=0,"",ROUND((X91-Z91)/T91*100,1)) | AD91: UNKNOWN | AE91: https://ajruiz.com.br/sites/default/files/public/arquivos-processos/2023-11/4_relacao_de_credores_analitica_art._51_iii_da_lre.pdf | AF91: p3 r20 | AG91: p3: R$ 4.589.364,33 | AH91: UNKNOWN | AJ91: OK | AK91: (not printed) | AO91: RJ case number not identified on the document | AP91: RIO DE JANEIRO | AQ91: RJ | AR91: Comércio atacadista de álcool carburante, biodiesel, gasolina e demais derivados de petróleo, exceto lubrificantes, não realizado por transportador re | AS91: DEMAIS | AT91: LARGE CORP | AU91: 33337122 | AV91: 1 | AW91: ROWS:p3r20 CASE_NUMBER_CORRECTED
A92: KARINA PLASTICOS LTDA | B92: 1557723.7 | C92: Conduscabos Brasil Indústria Comércio de | D92: NEW | I92: Camila Sartori | J92: Coordenadora de Crédito e Cobrança | K92: (11) 2440-8477 | L92: (11) 2463-2920 | O92: fernando.costa@karina.com.br | P92: Fernando Costa | Q92: Director | S92: fernando.costa@karina.com.br | T92: 1557723.7 | U92: B | V92: =IFERROR(VLOOKUP(U92,Assumptions!$A$7:$D$11,2,FALSE),0) | W92: =MAX(0.5,IFERROR(VLOOKUP(U92,Assumptions!$A$7:$D$11,3,FALSE),3)+IFERROR(VLOOKUP(U92,Assumptions!$A$7:$D$11,4,FALSE),8)/2-IF(AN92="",0,YEAR(TODAY())-AN92)) | X92: =T92*V92/(1+Assumptions!$B$3)^W92 | Y92: =IF(T92=0,"",ROUND(X92/T92*100,1)) | Z92: =X92*Assumptions!$B$4 | AA92: =IF(T92=0,"",ROUND(Z92/T92*100,1)) | AB92: =X92-Z92 | AC92: =IF(T92=0,"",ROUND((X92-Z92)/T92*100,1)) | AD92: ESTIMATED | AE92: https://assistjud.com.br/wp-content/uploads/elementor/forms/65098c80a5824.pdf | AF92: p8 r5 | AG92: p8: R$ 1.557.723,71 | AH92: AJ_LIST | AI92: 2023-09-18 | AJ92: OK_NO_TOTALS | AK92: 8005129-09.2023.8.05.0039 | AL92: TJBA | AM92: ACTIVE | AN92: 2023 | AO92: live case, no plan document yet | AP92: GUARULHOS | AQ92: SP | AR92: Fabricação de resinas termoplásticas | AS92: DEMAIS | AT92: MID-MARKET | AU92: 51254159 | AV92: 1 | AW92: ROWS:p8r5 UNRECONCILED_SOURCE
A93: RECYCLE BAG INDUSTRIA E SERVICOS LTDA | B93: 1547270.3 | D93: NEW | I93: LUIZA CRISTHINA MIRANDA CORREA | J93: Sócio-Administrador | K93: (33) 3339-1000 | T93: 1547270.3 | U93: B | V93: =IFERROR(VLOOKUP(U93,Assumptions!$A$7:$D$11,2,FALSE),0) | W93: =MAX(0.5,IFERROR(VLOOKUP(U93,Assumptions!$A$7:$D$11,3,FALSE),3)+IFERROR(VLOOKUP(U93,Assumptions!$A$7:$D$11,4,FALSE),8)/2-IF(AN93="",0,YEAR(TODAY())-AN93)) | X93: =T93*V93/(1+Assumptions!$B$3)^W93 | Y93: =IF(T93=0,"",ROUND(X93/T93*100,1)) | Z93: =X93*Assumptions!$B$4 | AA93: =IF(T93=0,"",ROUND(Z93/T93*100,1)) | AB93: =X93-Z93 | AC93: =IF(T93=0,"",ROUND((X93-Z93)/T93*100,1)) | AD93: ESTIMATED | AE93: https://cataliseaj.com.br/sgc/download.php?file=files/processo_documento/processo_documento15092204102024_1_.pdf&nome=02. RELAÇÃO DE CREDORES | AF93: p3 r10 | AG93: p3: R$ 1.547.270,31 | AH93: DEBTOR_LIST | AJ93: OK_NO_TOTALS | AK93: 5011460-87.2023.8.24.0020 | AL93: TJSC | AM93: ACTIVE | AN93: 2023 | AO93: live case, no plan document yet | AP93: MANHUACU | AQ93: MG | AR93: Fabricação de outros produtos têxteis não especificados anteriormente | AS93: EMPRESA DE PEQUENO PORTE | AT93: SMALL | AU93: 23141884 | AV93: 1 | AW93: ROWS:p3r10 UNRECONCILED_SOURCE
A94: CROMO INDUSTRIA QUIMICA S.A. | B94: 2406485.6 | C94: NORTESUL COMERCIAL AGRICOLA LTDA EM RECUPERACAO JUDICIAL | D94: NEW | I94: Jessica Stacke | J94: Coordenadora de FP&A | K94: (11) 4130-8138 | N94: jessica.stacke@cromoquimica.com.br | O94: bruna.santos@cromoquimica.com.br | P94: Bruna Santos | Q94: Technical Sales Representative | S94: bruna.santos@cromoquimica.com.br | T94: 2406485.6 | U94: B | V94: =IFERROR(VLOOKUP(U94,Assumptions!$A$7:$D$11,2,FALSE),0) | W94: =MAX(0.5,IFERROR(VLOOKUP(U94,Assumptions!$A$7:$D$11,3,FALSE),3)+IFERROR(VLOOKUP(U94,Assumptions!$A$7:$D$11,4,FALSE),8)/2-IF(AN94="",0,YEAR(TODAY())-AN94)) | X94: =T94*V94/(1+Assumptions!$B$3)^W94 | Y94: =IF(T94=0,"",ROUND(X94/T94*100,1)) | Z94: =X94*Assumptions!$B$4 | AA94: =IF(T94=0,"",ROUND(Z94/T94*100,1)) | AB94: =X94-Z94 | AC94: =IF(T94=0,"",ROUND((X94-Z94)/T94*100,1)) | AD94: ESTIMATED | AE94: https://lrflideres.com.br/wp-content/plugins/download-attachments/includes/download.php?id=6879 | AF94: p1 r11 | AG94: p1: R$ 2.406.485,64 | AH94: AJ_LIST | AI94: 2026-01-15 | AJ94: OK | AK94: 0804401-51.2025.8.14.0039 | AL94: TJPA | AM94: ACTIVE | AN94: 2025 | AO94: live case, no plan document yet | AP94: ESTRELA | AQ94: RS | AR94: Fabricação de outros produtos químicos não especificados anteriormente | AS94: DEMAIS | AT94: MID-MARKET | AU94: 31281962 | AV94: 1 | AW94: ROWS:p1r11
A95: FML INCORPORADORA LTDA | B95: 1535860.1 | C95: VEV COMERCIO DE MEDICAMENTOS LTDA EM RECUPERACAO JUDICIAL | D95: NEW | I95: JOSE CARLOS SALVADORI | J95: Administrador | K95: (41) 2169-2874 | L95: (41) 2169-2800 | T95: 1535860.1 | U95: B | V95: =IFERROR(VLOOKUP(U95,Assumptions!$A$7:$D$11,2,FALSE),0) | W95: =MAX(0.5,IFERROR(VLOOKUP(U95,Assumptions!$A$7:$D$11,3,FALSE),3)+IFERROR(VLOOKUP(U95,Assumptions!$A$7:$D$11,4,FALSE),8)/2-IF(AN95="",0,YEAR(TODAY())-AN95)) | X95: =T95*V95/(1+Assumptions!$B$3)^W95 | Y95: =IF(T95=0,"",ROUND(X95/T95*100,1)) | Z95: =X95*Assumptions!$B$4 | AA95: =IF(T95=0,"",ROUND(Z95/T95*100,1)) | AB95: =X95-Z95 | AC95: =IF(T95=0,"",ROUND((X95-Z95)/T95*100,1)) | AD95: ESTIMATED | AE95: https://marquesadmjudicial.com.br/sgc/download.php?file=files/processo_documento/processo_documento15293208032024_1_.pdf&nome=Relação Nominal de Credores da AJ-Sintética | AF95: p25 r10 | AG95: p25: R$ 1.535.860,08 | AH95: AJ_LIST | AI95: 2023-03-02 | AJ95: QUARANTINED | AK95: 0005010-98.2023.8.16.0001 | AL95: TJPR | AM95: ACTIVE | AN95: 2023 | AO95: live case, no plan document yet | AP95: CURITIBA | AQ95: PR | AR95: Incorporação de empreendimentos imobiliários | AS95: DEMAIS | AT95: MID-MARKET | AU95: 75724070 | AV95: 1 | AW95: PARTIAL_DOC_CLASS_III_RECONCILED ROWS:p25r10
A96: DIMACI MATERIAL CIRURGICO LTDA | B96: 1222974 | C96: ASSOCIACAO DE CARIDADE SANTA CASA DE RIO GRANDE | D96: NEW | I96: Sabrina Rosa | J96: Sales Coordinator | K96: (51) 3330-6111 | P96: PAULO CESAR LAPINSCKI | Q96: Administrador | R96: (51) 3330-6111 | T96: 1222974 | U96: B | V96: =IFERROR(VLOOKUP(U96,Assumptions!$A$7:$D$11,2,FALSE),0) | W96: =MAX(0.5,IFERROR(VLOOKUP(U96,Assumptions!$A$7:$D$11,3,FALSE),3)+IFERROR(VLOOKUP(U96,Assumptions!$A$7:$D$11,4,FALSE),8)/2-IF(AN96="",0,YEAR(TODAY())-AN96)) | X96: =T96*V96/(1+Assumptions!$B$3)^W96 | Y96: =IF(T96=0,"",ROUND(X96/T96*100,1)) | Z96: =X96*Assumptions!$B$4 | AA96: =IF(T96=0,"",ROUND(Z96/T96*100,1)) | AB96: =X96-Z96 | AC96: =IF(T96=0,"",ROUND((X96-Z96)/T96*100,1)) | AD96: ESTIMATED | AE96: https://scalzilliaj.com.br/sgc/download.php?file=files/processo_documento/processo_documento09120721032023_1_.pdf&nome=15 - Edital do art. 7º, §2º e 53 da Lei 11.101/2005 (segunda lista de credores e recebimento do plano)) | AF96: p27 r6 | AG96: p27: R$ 1.222.974,01 | AH96: AJ_LIST | AI96: 2023-03-21 | AJ96: OK_NO_TOTALS | AK96: 5012306-16.2022.8.21.0023 | AL96: TJRS | AM96: ACTIVE | AN96: 2022 | AO96: live case, no plan document yet | AP96: ELDORADO DO SUL | AQ96: RS | AR96: Comércio atacadista de medicamentos e drogas de uso humano | AS96: DEMAIS | AT96: MID-MARKET | AU96: 90251109 | AV96: 1 | AW96: ROWS:p27r6 UNRECONCILED_SOURCE
A97: ITM LATIN AMERICA INDUSTRIA DE PECAS PARA TRATORES LTDA. | B97: 2360226.7 | D97: NEW | I97: Anderson Miranda | J97: Director of Finance and Administration | K97: (11) 4417-7700 | N97: amiranda@group-itm.com | O97: csordi@group-itm.com | P97: Cesar Sordi | Q97: CEO | S97: csordi@group-itm.com | T97: 2360226.7 | U97: B | V97: =IFERROR(VLOOKUP(U97,Assumptions!$A$7:$D$11,2,FALSE),0) | W97: =MAX(0.5,IFERROR(VLOOKUP(U97,Assumptions!$A$7:$D$11,3,FALSE),3)+IFERROR(VLOOKUP(U97,Assumptions!$A$7:$D$11,4,FALSE),8)/2-IF(AN97="",0,YEAR(TODAY())-AN97)) | X97: =T97*V97/(1+Assumptions!$B$3)^W97 | Y97: =IF(T97=0,"",ROUND(X97/T97*100,1)) | Z97: =X97*Assumptions!$B$4 | AA97: =IF(T97=0,"",ROUND(Z97/T97*100,1)) | AB97: =X97-Z97 | AC97: =IF(T97=0,"",ROUND((X97-Z97)/T97*100,1)) | AD97: UNKNOWN | AE97: https://credibilita.com.br/wp-content/uploads/2025/09/Relacao-Credores-29.04.2026.pdf | AF97: p1 r29 | AG97: p1: R$ 2.360.226,69 | AH97: UNKNOWN | AJ97: OK_NO_TOTALS | AK97: 5057720-48.2025.8.24.0023 | AL97: TJ | AN97: 2025 | AO97: live case, no plan document yet | AP97: ATIBAIA | AQ97: SP | AR97: Fabricação de outras peças e acessórios para veículos automotores não especificadas anteriormente | AS97: DEMAIS | AT97: MID-MARKET | AU97: 61352050 | AV97: 1 | AW97: ROWS:p1r29 UNRECONCILED_SOURCE VALUE_COL:Valor_Após_Analise
A98: NATULAB LABORATORIO S.A | B98: 1481337.9 | C98: VEV COMERCIO DE MEDICAMENTOS LTDA EM RECUPERACAO JUDICIAL | D98: NEW | I98: Alexandre Yazbek | J98: CFO | Diretor Financeiro | K98: (75) 3311-5555 | N98: alexandreyazbek@natulab.com.br | O98: emersonpimentel@natulab.com.br | P98: Emerson Pimentel | Q98: Analista de Crédito e Cobrança Sênior | S98: emersonpimentel@natulab.com.br | T98: 1481337.9 | U98: B | V98: =IFERROR(VLOOKUP(U98,Assumptions!$A$7:$D$11,2,FALSE),0) | W98: =MAX(0.5,IFERROR(VLOOKUP(U98,Assumptions!$A$7:$D$11,3,FALSE),3)+IFERROR(VLOOKUP(U98,Assumptions!$A$7:$D$11,4,FALSE),8)/2-IF(AN98="",0,YEAR(TODAY())-AN98)) | X98: =T98*V98/(1+Assumptions!$B$3)^W98 | Y98: =IF(T98=0,"",ROUND(X98/T98*100,1)) | Z98: =X98*Assumptions!$B$4 | AA98: =IF(T98=0,"",ROUND(Z98/T98*100,1)) | AB98: =X98-Z98 | AC98: =IF(T98=0,"",ROUND((X98-Z98)/T98*100,1)) | AD98: ESTIMATED | AE98: https://marquesadmjudicial.com.br/sgc/download.php?file=files/processo_documento/processo_documento15293208032024_1_.pdf&nome=Relação Nominal de Credores da AJ-Sintética | AF98: p29 r10 | AG98: p29: R$ 1.481.337,86 | AH98: AJ_LIST | AI98: 2023-03-02 | AJ98: QUARANTINED | AK98: 0005010-98.2023.8.16.0001 | AL98: TJPR | AM98: ACTIVE | AN98: 2023 | AO98: live case, no plan document yet | AP98: SANTO ANTONIO DE JESUS | AQ98: BA | AR98: Fabricação de medicamentos alopáticos para uso humano | AS98: DEMAIS | AT98: LARGE CORP | AU98: 02456955 | AV98: 1 | AW98: PARTIAL_DOC_CLASS_III_RECONCILED ROWS:p29r10
A99: NNC NORTE E NORDESTE COMMODITIES LTDA | B99: 2859701.3 | D99: NEW | I99: OZILDE LOPES | J99: Administrador | K99: (37) 3271-9801 | T99: 2859701.3 | U99: B | V99: =IFERROR(VLOOKUP(U99,Assumptions!$A$7:$D$11,2,FALSE),0) | W99: =MAX(0.5,IFERROR(VLOOKUP(U99,Assumptions!$A$7:$D$11,3,FALSE),3)+IFERROR(VLOOKUP(U99,Assumptions!$A$7:$D$11,4,FALSE),8)/2-IF(AN99="",0,YEAR(TODAY())-AN99)) | X99: =T99*V99/(1+Assumptions!$B$3)^W99 | Y99: =IF(T99=0,"",ROUND(X99/T99*100,1)) | Z99: =X99*Assumptions!$B$4 | AA99: =IF(T99=0,"",ROUND(Z99/T99*100,1)) | AB99: =X99-Z99 | AC99: =IF(T99=0,"",ROUND((X99-Z99)/T99*100,1)) | AD99: ESTIMATED | AE99: https://scalzilliaj.com.br/sgc/download.php?file=files/processo_documento/processo_documento11421222052026_1_.pdf&nome=08. Lista de credores do edital do art. 52, §1º da LREF | AF99: p3 r9 | AG99: p3: R$ 2.859.701,32 | AH99: UNKNOWN | AJ99: OK_NO_TOTALS | AK99: 5011369-81.2026.8.09.0093 | AL99: TJGO | AM99: ACTIVE | AN99: 2026 | AO99: live case, no plan document yet | AP99: BALSAS | AQ99: MA | AR99: Comércio atacadista de cereais e leguminosas beneficiados | AS99: DEMAIS | AT99: MID-MARKET | AU99: 40910399 | AV99: 1 | AW99: ROWS:p3r9 UNRECONCILED_SOURCE
A100: FRONTEIRA COMERCIO E REPRESENTACAO DE PRODUTOS AGROPECUARIOS LTDA | B100: 2120225.1 | C100: COMERCIO RACOES BEM BOM LTDA | D100: NEW | I100: Thiago Costa | J100: Gerente Contas a Receber e Centro de Serviços Compartilhados | K100: (11) 5400-0021 | N100: thiago.costa@nutrien.com | O100: emerson.freitas@nutrien.com | P100: Emerson Freitas | Q100: Gerente de Tesouraria | Tesouraria Estratégica | S100: emerson.freitas@nutrien.com | T100: 2120225.1 | U100: A | V100: =IFERROR(VLOOKUP(U100,Assumptions!$A$7:$D$11,2,FALSE),0) | W100: =MAX(0.5,IFERROR(VLOOKUP(U100,Assumptions!$A$7:$D$11,3,FALSE),3)+IFERROR(VLOOKUP(U100,Assumptions!$A$7:$D$11,4,FALSE),8)/2-IF(AN100="",0,YEAR(TODAY())-AN100)) | X100: =T100*V100/(1+Assumptions!$B$3)^W100 | Y100: =IF(T100=0,"",ROUND(X100/T100*100,1)) | Z100: =X100*Assumptions!$B$4 | AA100: =IF(T100=0,"",ROUND(Z100/T100*100,1)) | AB100: =X100-Z100 | AC100: =IF(T100=0,"",ROUND((X100-Z100)/T100*100,1)) | AD100: CONFIRMED | AE100: https://stenius.com.br/wp-content/uploads/2026/06/EDITAL-GRUPO-3E.pdf | AF100: p16 r31 | AG100: p16: R$ 2.120.225,10 | AH100: DEBTOR_LIST | AI100: 2026-06-22 | AJ100: OK_NO_TOTALS | AK100: 5341375-33.2026.8.09.0049 | AL100: TJGO | AM100: ACTIVE | AN100: 2026 | AO100: plan/homologation document found | AP100: RIO VERDE | AQ100: GO | AR100: Comércio atacadista de mercadorias em geral, com predominância de insumos agropecuários | AS100: DEMAIS | AT100: LARGE CORP | AU100: 36854495 | AV100: 1 | AW100: ROWS:p16r31 UNRECONCILED_SOURCE
...

Sheet FINANCIAL CREDITORS
A1: CREDITOR — company owed money | B1: AMOUNT OWED (R$) | C1: DEBTOR — company in RJ | D1: STATUS | E1: LAST TOUCH | F1: NEXT ACTION | G1: NEXT DATE | H1: NOTES | I1: DECISION MAKER | J1: Role | K1: Phone 1 | L1: Phone 2 | M1: Mobile (Apollo) | N1: Email | O1: Email 2 | P1: BACKUP CONTACT | Q1: Backup role | R1: Backup phone | S1: Backup email | T1: FACE VALUE (as printed) | U1: DEBTOR BAND | V1: Exp. recovery % | W1: Years to payment | X1: FUND PRICE @ IRR (R$) | Y1: cents | Z1: OUR QUOTE (R$) | AA1: cents | AB1: OUR ÁGIO (R$) | AC1: Ágio pts of face | AD1: Plan status | AE1: PROOF: source document | AF1: Page / row | AG1: Value as printed | AH1: Which list | AI1: Published | AJ1: Reconciled | AK1: Case number | AL1: Court | AM1: Stage | AN1: Filed | AO1: Band reason | AP1: City | AQ1: UF | AR1: Sector | AS1: Size | AT1: Seller fit | AU1: CNPJ root | AV1: Claims | AW1: Flags
A2: TRAVESSIA SECURITIZADORA DE CREDITOS MERCANTIS XXV S.A. | B2: 8.602097e+08 | C2: EGESA ENGENHARIA S/A (Consórcio ETDI) | D2: NEW | I2: VINICIUS BERNARDES BASILE SILVEIRA STOPA | J2: Presidente | K2: (11) 4115-8700 | P2: CAMILA MARIA OLIVEIRA | Q2: Diretor | R2: (11) 4115-8700 | T2: 8.602097e+08 | U2: ? | V2: =IFERROR(VLOOKUP(U2,Assumptions!$A$7:$D$11,2,FALSE),0) | W2: =MAX(0.5,IFERROR(VLOOKUP(U2,Assumptions!$A$7:$D$11,3,FALSE),3)+IFERROR(VLOOKUP(U2,Assumptions!$A$7:$D$11,4,FALSE),8)/2-IF(AN2="",0,YEAR(TODAY())-AN2)) | X2: =T2*V2/(1+Assumptions!$B$3)^W2 | Y2: =IF(T2=0,"",ROUND(X2/T2*100,1)) | Z2: =X2*Assumptions!$B$4 | AA2: =IF(T2=0,"",ROUND(Z2/T2*100,1)) | AB2: =X2-Z2 | AC2: =IF(T2=0,"",ROUND((X2-Z2)/T2*100,1)) | AD2: UNKNOWN | AE2: https://scalzilliaj.com.br/sgc/download.php?file=files/processo_documento/processo_documento09514021082025_1_.pdf&nome=04 - Relação de credores das Recuperandas | AF2: p74 r14; p74 r15; p75 r1; p75 r2; p75 r3 | AG2: p74: R$ 353.866.498,00; p74: R$ 298.441.197,42; p75: R$ 135.449.857,00; p75: R$ 46.031.397,00; p75: R$ 26.420.754,00 | AH2: DEBTOR_LIST | AJ2: OK | AK2: (not printed) | AO2: RJ case number not identified on the document | AP2: SAO PAULO | AQ2: SP | AR2: Securitização de créditos | AS2: DEMAIS | AT2: MID-MARKET | AU2: 45741898 | AV2: 5 | AW2: LIKELY_FINANCIAL_BY_NAME ROWS:p74r14,p74r15,p75r1,p75r2,p75r3 VALUE_COL:Valor_Atualizado CASE_NUMBER_CORRECTED
A3: CAIXA ECONOMICA FEDERAL | B3: 4.2601895e+08 | C3: EGESA ENGENHARIA S/A (Consórcio ETDI) | D3: NEW | I3: ADRIANO ASSIS MATIAS | J3: Administrador | K3: (00) 4004-0104 | P3: HENRIETE ALEXANDRA SARTORI BERNABE | Q3: Administrador | R3: (00) 4004-0104 | T3: 4.2601895e+08 | U3: ? | V3: =IFERROR(VLOOKUP(U3,Assumptions!$A$7:$D$11,2,FALSE),0) | W3: =MAX(0.5,IFERROR(VLOOKUP(U3,Assumptions!$A$7:$D$11,3,FALSE),3)+IFERROR(VLOOKUP(U3,Assumptions!$A$7:$D$11,4,FALSE),8)/2-IF(AN3="",0,YEAR(TODAY())-AN3)) | X3: =T3*V3/(1+Assumptions!$B$3)^W3 | Y3: =IF(T3=0,"",ROUND(X3/T3*100,1)) | Z3: =X3*Assumptions!$B$4 | AA3: =IF(T3=0,"",ROUND(Z3/T3*100,1)) | AB3: =X3-Z3 | AC3: =IF(T3=0,"",ROUND((X3-Z3)/T3*100,1)) | AD3: UNKNOWN | AE3: https://scalzilliaj.com.br/sgc/download.php?file=files/processo_documento/processo_documento09514021082025_1_.pdf&nome=04 - Relação de credores das Recuperandas | AF3: p63 r17 | AG3: p63: R$ 426.018.950,32 | AH3: DEBTOR_LIST | AJ3: OK | AK3: (not printed) | AO3: RJ case number not identified on the document | AP3: BRASILIA | AQ3: DF | AR3: Caixas econômicas | AS3: DEMAIS | AT3: LARGE CORP | AU3: 00360305 | AV3: 1 | AW3: LIKELY_FINANCIAL_BY_NAME ROWS:p63r17 VALUE_COL:Valor_Atualizado CASE_NUMBER_CORRECTED
A4: CAIXA ECONOMICA FEDERAL | B4: 62052412 | C4: ASSOCIACAO DE CARIDADE SANTA CASA DE RIO GRANDE | D4: NEW | I4: ADRIANO ASSIS MATIAS | J4: Administrador | K4: (00) 4004-0104 | P4: HENRIETE ALEXANDRA SARTORI BERNABE | Q4: Administrador | R4: (00) 4004-0104 | T4: 62052412 | U4: B | V4: =IFERROR(VLOOKUP(U4,Assumptions!$A$7:$D$11,2,FALSE),0) | W4: =MAX(0.5,IFERROR(VLOOKUP(U4,Assumptions!$A$7:$D$11,3,FALSE),3)+IFERROR(VLOOKUP(U4,Assumptions!$A$7:$D$11,4,FALSE),8)/2-IF(AN4="",0,YEAR(TODAY())-AN4)) | X4: =T4*V4/(1+Assumptions!$B$3)^W4 | Y4: =IF(T4=0,"",ROUND(X4/T4*100,1)) | Z4: =X4*Assumptions!$B$4 | AA4: =IF(T4=0,"",ROUND(Z4/T4*100,1)) | AB4: =X4-Z4 | AC4: =IF(T4=0,"",ROUND((X4-Z4)/T4*100,1)) | AD4: ESTIMATED | AE4: https://scalzilliaj.com.br/sgc/download.php?file=files/processo_documento/processo_documento09120721032023_1_.pdf&nome=15 - Edital do art. 7º, §2º e 53 da Lei 11.101/2005 (segunda lista de credores e recebimento do plano)) | AF4: p26 r16 | AG4: p26: R$ 62.052.412,02 | AH4: AJ_LIST | AI4: 2023-03-21 | AJ4: OK_NO_TOTALS | AK4: 5012306-16.2022.8.21.0023 | AL4: TJRS | AM4: ACTIVE | AN4: 2022 | AO4: live case, no plan document yet | AP4: BRASILIA | AQ4: DF | AR4: Caixas econômicas | AS4: DEMAIS | AT4: LARGE CORP | AU4: 00360305 | AV4: 1 | AW4: LIKELY_FINANCIAL_BY_NAME ROWS:p26r16 UNRECONCILED_SOURCE
A5: BANCO BRADESCO S.A. | B5: 1.667452e+08 | C5: EGESA ENGENHARIA S/A (Consórcio ETDI) | D5: NEW | I5: MARCELO DE ARAUJO NORONHA | J5: Presidente | K5: (11) 3684-5122 | P5: AFRANIO CARLOS CAMARGO DANTZGER | Q5: Diretor | R5: (11) 3684-5122 | T5: 1.667452e+08 | U5: ? | V5: =IFERROR(VLOOKUP(U5,Assumptions!$A$7:$D$11,2,FALSE),0) | W5: =MAX(0.5,IFERROR(VLOOKUP(U5,Assumptions!$A$7:$D$11,3,FALSE),3)+IFERROR(VLOOKUP(U5,Assumptions!$A$7:$D$11,4,FALSE),8)/2-IF(AN5="",0,YEAR(TODAY())-AN5)) | X5: =T5*V5/(1+Assumptions!$B$3)^W5 | Y5: =IF(T5=0,"",ROUND(X5/T5*100,1)) | Z5: =X5*Assumptions!$B$4 | AA5: =IF(T5=0,"",ROUND(Z5/T5*100,1)) | AB5: =X5-Z5 | AC5: =IF(T5=0,"",ROUND((X5-Z5)/T5*100,1)) | AD5: UNKNOWN | AE5: https://scalzilliaj.com.br/sgc/download.php?file=files/processo_documento/processo_documento09514021082025_1_.pdf&nome=04 - Relação de credores das Recuperandas | AF5: p62 r14 | AG5: p62: R$ 166.745.196,81 | AH5: DEBTOR_LIST | AJ5: OK | AK5: (not printed) | AO5: RJ case number not identified on the document | AP5: OSASCO | AQ5: SP | AR5: Bancos múltiplos, com carteira comercial | AS5: DEMAIS | AT5: LARGE CORP | AU5: 60746948 | AV5: 1 | AW5: LIKELY_FINANCIAL_BY_NAME ROWS:p62r14 VALUE_COL:Valor_Atualizado CASE_NUMBER_CORRECTED
A6: BANCO DO BRASIL SA | B6: 43161498 | C6: Conduscabos Brasil Indústria Comércio de | D6: NEW | I6: TARCIANA PAULA GOMES MEDEIROS | J6: Presidente | K6: (61) 3493-9002 | P6: ALAN CARLOS GUEDES DE OLIVEIRA | Q6: Diretor | R6: (61) 3493-9002 | T6: 43161498 | U6: B | V6: =IFERROR(VLOOKUP(U6,Assumptions!$A$7:$D$11,2,FALSE),0) | W6: =MAX(0.5,IFERROR(VLOOKUP(U6,Assumptions!$A$7:$D$11,3,FALSE),3)+IFERROR(VLOOKUP(U6,Assumptions!$A$7:$D$11,4,FALSE),8)/2-IF(AN6="",0,YEAR(TODAY())-AN6)) | X6: =T6*V6/(1+Assumptions!$B$3)^W6 | Y6: =IF(T6=0,"",ROUND(X6/T6*100,1)) | Z6: =X6*Assumptions!$B$4 | AA6: =IF(T6=0,"",ROUND(Z6/T6*100,1)) | AB6: =X6-Z6 | AC6: =IF(T6=0,"",ROUND((X6-Z6)/T6*100,1)) | AD6: ESTIMATED | AE6: https://assistjud.com.br/wp-content/uploads/elementor/forms/65098c80a5824.pdf | AF6: p5 r9; p17 r3 | AG6: p5: R$ 34.976.748,87; p17: R$ 8.184.748,74 | AH6: AJ_LIST | AI6: 2023-09-18 | AJ6: OK_NO_TOTALS | AK6: 8005129-09.2023.8.05.0039 | AL6: TJBA | AM6: ACTIVE | AN6: 2023 | AO6: live case, no plan document yet | AP6: BRASILIA | AQ6: DF | AR6: Bancos múltiplos, com carteira comercial | AS6: DEMAIS | AT6: LARGE CORP | AU6: 00000000 | AV6: 2 | AW6: LIKELY_FINANCIAL_BY_NAME ROWS:p5r9,p17r3 UNRECONCILED_SOURCE VALUE_COL:Valor_Do_Crédito_2º_Edital_De_Credores
A7: BANCO SANTANDER (BRASIL) S.A. | B7: 53119918 | D7: NEW | I7: GILSON FINKELSZTAIN | J7: Presidente | K7: (11) 4004-3535 | P7: ALESSANDRO CHAGAS FARIAS | Q7: Diretor | R7: (11) 4004-3535 | T7: 53119918 | U7: B | V7: =IFERROR(VLOOKUP(U7,Assumptions!$A$7:$D$11,2,FALSE),0) | W7: =MAX(0.5,IFERROR(VLOOKUP(U7,Assumptions!$A$7:$D$11,3,FALSE),3)+IFERROR(VLOOKUP(U7,Assumptions!$A$7:$D$11,4,FALSE),8)/2-IF(AN7="",0,YEAR(TODAY())-AN7)) | X7: =T7*V7/(1+Assumptions!$B$3)^W7 | Y7: =IF(T7=0,"",ROUND(X7/T7*100,1)) | Z7: =X7*Assumptions!$B$4 | AA7: =IF(T7=0,"",ROUND(Z7/T7*100,1)) | AB7: =X7-Z7 | AC7: =IF(T7=0,"",ROUND((X7-Z7)/T7*100,1)) | AD7: UNKNOWN | AE7: https://credibilita.com.br/wp-content/uploads/2025/09/Relacao-Credores-29.04.2026.pdf | AF7: p1 r13 | AG7: p1: R$ 53.119.917,67 | AH7: UNKNOWN | AJ7: OK_NO_TOTALS | AK7: 5057720-48.2025.8.24.0023 | AL7: TJ | AN7: 2025 | AO7: live case, no plan document yet | AP7: SAO PAULO | AQ7: SP | AR7: Bancos múltiplos, com carteira comercial | AS7: DEMAIS | AT7: LARGE CORP | AU7: 90400888 | AV7: 1 | AW7: ROWS:p1r13 UNRECONCILED_SOURCE VALUE_COL:Valor_Após_Analise
A8: BANCO DO BRASIL SA | B8: 49456864 | D8: NEW | I8: TARCIANA PAULA GOMES MEDEIROS | J8: Presidente | K8: (61) 3493-9002 | P8: ALAN CARLOS GUEDES DE OLIVEIRA | Q8: Diretor | R8: (61) 3493-9002 | T8: 49456864 | U8: B | V8: =IFERROR(VLOOKUP(U8,Assumptions!$A$7:$D$11,2,FALSE),0) | W8: =MAX(0.5,IFERROR(VLOOKUP(U8,Assumptions!$A$7:$D$11,3,FALSE),3)+IFERROR(VLOOKUP(U8,Assumptions!$A$7:$D$11,4,FALSE),8)/2-IF(AN8="",0,YEAR(TODAY())-AN8)) | X8: =T8*V8/(1+Assumptions!$B$3)^W8 | Y8: =IF(T8=0,"",ROUND(X8/T8*100,1)) | Z8: =X8*Assumptions!$B$4 | AA8: =IF(T8=0,"",ROUND(Z8/T8*100,1)) | AB8: =X8-Z8 | AC8: =IF(T8=0,"",ROUND((X8-Z8)/T8*100,1)) | AD8: UNKNOWN | AE8: https://credibilita.com.br/wp-content/uploads/2025/09/Relacao-Credores-29.04.2026.pdf | AF8: p1 r10 | AG8: p1: R$ 49.456.863,81 | AH8: UNKNOWN | AJ8: OK_NO_TOTALS | AK8: 5057720-48.2025.8.24.0023 | AL8: TJ | AN8: 2025 | AO8: live case, no plan document yet | AP8: BRASILIA | AQ8: DF | AR8: Bancos múltiplos, com carteira comercial | AS8: DEMAIS | AT8: LARGE CORP | AU8: 00000000 | AV8: 1 | AW8: ROWS:p1r10 UNRECONCILED_SOURCE VALUE_COL:Valor_Após_Analise
A9: BANCO RURAL S.A - EM LIQUIDACAO EXTRAJUDICIAL | B9: 91334196 | C9: EGESA ENGENHARIA S/A (Consórcio ETDI) | D9: NEW | I9: OSMAR BRASIL DE ALMEIDA | J9: Diretor | K9: (31) 2126-5207 | T9: 91334196 | U9: ? | V9: =IFERROR(VLOOKUP(U9,Assumptions!$A$7:$D$11,2,FALSE),0) | W9: =MAX(0.5,IFERROR(VLOOKUP(U9,Assumptions!$A$7:$D$11,3,FALSE),3)+IFERROR(VLOOKUP(U9,Assumptions!$A$7:$D$11,4,FALSE),8)/2-IF(AN9="",0,YEAR(TODAY())-AN9)) | X9: =T9*V9/(1+Assumptions!$B$3)^W9 | Y9: =IF(T9=0,"",ROUND(X9/T9*100,1)) | Z9: =X9*Assumptions!$B$4 | AA9: =IF(T9=0,"",ROUND(Z9/T9*100,1)) | AB9: =X9-Z9 | AC9: =IF(T9=0,"",ROUND((X9-Z9)/T9*100,1)) | AD9: UNKNOWN | AE9: https://scalzilliaj.com.br/sgc/download.php?file=files/processo_documento/processo_documento09514021082025_1_.pdf&nome=04 - Relação de credores das Recuperandas | AF9: p62 r16 | AG9: p62: R$ 91.334.195,52 | AH9: DEBTOR_LIST | AJ9: OK | AK9: (not printed) | AO9: RJ case number not identified on the document | AP9: BELO HORIZONTE | AQ9: MG | AR9: Bancos múltiplos, com carteira comercial | AS9: DEMAIS | AT9: LARGE CORP | AU9: 33124959 | AV9: 1 | AW9: LIKELY_FINANCIAL_BY_NAME ROWS:p62r16 VALUE_COL:Valor_Atualizado CASE_NUMBER_CORRECTED
A10: ITAU UNIBANCO S.A. | B10: 46224793 | D10: NEW | I10: FELIPE SAMPAIO NABUCO | J10: Administrador | K10: (11) 3003-4828 | P10: MILTON MALUHY FILHO | Q10: Presidente | R10: (11) 3003-4828 | T10: 46224793 | U10: B | V10: =IFERROR(VLOOKUP(U10,Assumptions!$A$7:$D$11,2,FALSE),0) | W10: =MAX(0.5,IFERROR(VLOOKUP(U10,Assumptions!$A$7:$D$11,3,FALSE),3)+IFERROR(VLOOKUP(U10,Assumptions!$A$7:$D$11,4,FALSE),8)/2-IF(AN10="",0,YEAR(TODAY())-AN10)) | X10: =T10*V10/(1+Assumptions!$B$3)^W10 | Y10: =IF(T10=0,"",ROUND(X10/T10*100,1)) | Z10: =X10*Assumptions!$B$4 | AA10: =IF(T10=0,"",ROUND(Z10/T10*100,1)) | AB10: =X10-Z10 | AC10: =IF(T10=0,"",ROUND((X10-Z10)/T10*100,1)) | AD10: UNKNOWN | AE10: https://credibilita.com.br/wp-content/uploads/2025/09/Relacao-Credores-29.04.2026.pdf | AF10: p1 r28 | AG10: p1: R$ 46.224.793,46 | AH10: UNKNOWN | AJ10: OK_NO_TOTALS | AK10: 5057720-48.2025.8.24.0023 | AL10: TJ | AN10: 2025 | AO10: live case, no plan document yet | AP10: SAO PAULO | AQ10: SP | AR10: Bancos comerciais | AS10: DEMAIS | AT10: LARGE CORP | AU10: 60701190 | AV10: 1 | AW10: ROWS:p1r28 UNRECONCILED_SOURCE VALUE_COL:Valor_Após_Analise
A11: BANK OF CHINA (BRASIL) BANCO MULTIPLO S/A | B11: 84072313 | C11: EGESA ENGENHARIA S/A (Consórcio ETDI) | D11: NEW | I11: CLAUDIO AUGUSTO ROTOLO | J11: Diretor | K11: (11) 2173-9000 | P11: DEMING LI | Q11: Diretor | R11: (11) 2173-9000 | T11: 84072313 | U11: ? | V11: =IFERROR(VLOOKUP(U11,Assumptions!$A$7:$D$11,2,FALSE),0) | W11: =MAX(0.5,IFERROR(VLOOKUP(U11,Assumptions!$A$7:$D$11,3,FALSE),3)+IFERROR(VLOOKUP(U11,Assumptions!$A$7:$D$11,4,FALSE),8)/2-IF(AN11="",0,YEAR(TODAY())-AN11)) | X11: =T11*V11/(1+Assumptions!$B$3)^W11 | Y11: =IF(T11=0,"",ROUND(X11/T11*100,1)) | Z11: =X11*Assumptions!$B$4 | AA11: =IF(T11=0,"",ROUND(Z11/T11*100,1)) | AB11: =X11-Z11 | AC11: =IF(T11=0,"",ROUND((X11-Z11)/T11*100,1)) | AD11: UNKNOWN | AE11: https://scalzilliaj.com.br/sgc/download.php?file=files/processo_documento/processo_documento09514021082025_1_.pdf&nome=04 - Relação de credores das Recuperandas | AF11: p64 r8 | AG11: p64: R$ 84.072.313,37 | AH11: DEBTOR_LIST | AJ11: OK | AK11: (not printed) | AO11: RJ case number not identified on the document | AP11: SAO PAULO | AQ11: SP | AR11: Bancos múltiplos, com carteira comercial | AS11: DEMAIS | AT11: LARGE CORP | AU11: 07450604 | AV11: 1 | AW11: LIKELY_FINANCIAL_BY_NAME ROWS:p64r8 VALUE_COL:Valor_Atualizado CASE_NUMBER_CORRECTED
A12: BANCO SANTANDER (BRASIL) S.A. | B12: 81755024 | C12: EGESA ENGENHARIA S/A (Consórcio ETDI) | D12: NEW | I12: GILSON FINKELSZTAIN | J12: Presidente | K12: (11) 4004-3535 | P12: ALESSANDRO CHAGAS FARIAS | Q12: Diretor | R12: (11) 4004-3535 | T12: 81755024 | U12: ? | V12: =IFERROR(VLOOKUP(U12,Assumptions!$A$7:$D$11,2,FALSE),0) | W12: =MAX(0.5,IFERROR(VLOOKUP(U12,Assumptions!$A$7:$D$11,3,FALSE),3)+IFERROR(VLOOKUP(U12,Assumptions!$A$7:$D$11,4,FALSE),8)/2-IF(AN12="",0,YEAR(TODAY())-AN12)) | X12: =T12*V12/(1+Assumptions!$B$3)^W12 | Y12: =IF(T12=0,"",ROUND(X12/T12*100,1)) | Z12: =X12*Assumptions!$B$4 | AA12: =IF(T12=0,"",ROUND(Z12/T12*100,1)) | AB12: =X12-Z12 | AC12: =IF(T12=0,"",ROUND((X12-Z12)/T12*100,1)) | AD12: UNKNOWN | AE12: https://scalzilliaj.com.br/sgc/download.php?file=files/processo_documento/processo_documento09514021082025_1_.pdf&nome=04 - Relação de credores das Recuperandas | AF12: p62 r17 | AG12: p62: R$ 81.755.024,22 | AH12: DEBTOR_LIST | AJ12: OK | AK12: (not printed) | AO12: RJ case number not identified on the document | AP12: SAO PAULO | AQ12: SP | AR12: Bancos múltiplos, com carteira comercial | AS12: DEMAIS | AT12: LARGE CORP | AU12: 90400888 | AV12: 1 | AW12: LIKELY_FINANCIAL_BY_NAME ROWS:p62r17 VALUE_COL:Valor_Atualizado CASE_NUMBER_CORRECTED
A13: Banco do Veneza Equipamentos Sul Comercio LTDA (CNPJ nº | B13: 19901499 | C13: CPX DISTRIBUIDORA S.A. | D13: NEW | T13: 19901499 | U13: B | V13: =IFERROR(VLOOKUP(U13,Assumptions!$A$7:$D$11,2,FALSE),0) | W13: =MAX(0.5,IFERROR(VLOOKUP(U13,Assumptions!$A$7:$D$11,3,FALSE),3)+IFERROR(VLOOKUP(U13,Assumptions!$A$7:$D$11,4,FALSE),8)/2-IF(AN13="",0,YEAR(TODAY())-AN13)) | X13: =T13*V13/(1+Assumptions!$B$3)^W13 | Y13: =IF(T13=0,"",ROUND(X13/T13*100,1)) | Z13: =X13*Assumptions!$B$4 | AA13: =IF(T13=0,"",ROUND(Z13/T13*100,1)) | AB13: =X13-Z13 | AC13: =IF(T13=0,"",ROUND((X13-Z13)/T13*100,1)) | AD13: ESTIMATED | AE13: https://marquesadmjudicial.com.br/sgc/download.php?file=files/processo_documento/processo_documento16562707032024_1_.pdf&nome=2º Edital-Relação de Credores do art. 7, §2 da LREF e do Plano de Recuperação Judicial | AF13: p1 r43 | AG13: p1: R$ 19.901.498,91 | AH13: AJ_LIST | AI13: 2022-11-17 | AJ13: OK_NO_TOTALS | AK13: 0037411-27.2022.8.16.0021 | AL13: TJPR | AM13: ACTIVE | AN13: 2022 | AO13: live case, no plan document yet | AT13: MID-MARKET | AU13: 29644666 | AV13: 1 | AW13: LIKELY_FINANCIAL_BY_NAME MULTI_ROOT ROWS:p1r43 UNRECONCILED_SOURCE
A14: BANCO VOTORANTIM S.A. | B14: 65326447 | C14: EGESA ENGENHARIA S/A (Consórcio ETDI) | D14: NEW | I14: GUSTAVO HENRIQUE SANTOS DE SOUSA | J14: Presidente | K14: (11) 5171-2672 | L14: (11) 5171-2488 | P14: ALBERTO WAGNER TEIXEIRA CAMPOS | Q14: Diretor | R14: (11) 5171-2488 | T14: 65326447 | U14: ? | V14: =IFERROR(VLOOKUP(U14,Assumptions!$A$7:$D$11,2,FALSE),0) | W14: =MAX(0.5,IFERROR(VLOOKUP(U14,Assumptions!$A$7:$D$11,3,FALSE),3)+IFERROR(VLOOKUP(U14,Assumptions!$A$7:$D$11,4,FALSE),8)/2-IF(AN14="",0,YEAR(TODAY())-AN14)) | X14: =T14*V14/(1+Assumptions!$B$3)^W14 | Y14: =IF(T14=0,"",ROUND(X14/T14*100,1)) | Z14: =X14*Assumptions!$B$4 | AA14: =IF(T14=0,"",ROUND(Z14/T14*100,1)) | AB14: =X14-Z14 | AC14: =IF(T14=0,"",ROUND((X14-Z14)/T14*100,1)) | AD14: UNKNOWN | AE14: https://scalzilliaj.com.br/sgc/download.php?file=files/processo_documento/processo_documento09514021082025_1_.pdf&nome=04 - Relação de credores das Recuperandas | AF14: p63 r1 | AG14: p63: R$ 65.326.446,86 | AH14: DEBTOR_LIST | AJ14: OK | AK14: (not printed) | AO14: RJ case number not identified on the document | AP14: SAO PAULO | AQ14: SP | AR14: Bancos múltiplos, com carteira comercial | AS14: DEMAIS | AT14: LARGE CORP | AU14: 59588111 | AV14: 1 | AW14: LIKELY_FINANCIAL_BY_NAME ROWS:p63r1 VALUE_COL:Valor_Atualizado CASE_NUMBER_CORRECTED
A15: BANCO DO BRASIL SA | B15: 29399789 | C15: COMERCIO RACOES BEM BOM LTDA | D15: NEW | I15: TARCIANA PAULA GOMES MEDEIROS | J15: Presidente | K15: (61) 3493-9002 | P15: ALAN CARLOS GUEDES DE OLIVEIRA | Q15: Diretor | R15: (61) 3493-9002 | T15: 29399789 | U15: A | V15: =IFERROR(VLOOKUP(U15,Assumptions!$A$7:$D$11,2,FALSE),0) | W15: =MAX(0.5,IFERROR(VLOOKUP(U15,Assumptions!$A$7:$D$11,3,FALSE),3)+IFERROR(VLOOKUP(U15,Assumptions!$A$7:$D$11,4,FALSE),8)/2-IF(AN15="",0,YEAR(TODAY())-AN15)) | X15: =T15*V15/(1+Assumptions!$B$3)^W15 | Y15: =IF(T15=0,"",ROUND(X15/T15*100,1)) | Z15: =X15*Assumptions!$B$4 | AA15: =IF(T15=0,"",ROUND(Z15/T15*100,1)) | AB15: =X15-Z15 | AC15: =IF(T15=0,"",ROUND((X15-Z15)/T15*100,1)) | AD15: CONFIRMED | AE15: https://stenius.com.br/wp-content/uploads/2026/06/EDITAL-GRUPO-3E.pdf | AF15: p10 r35 | AG15: p10: R$ 29.399.788,89 | AH15: DEBTOR_LIST | AI15: 2026-06-22 | AJ15: OK_NO_TOTALS | AK15: 5341375-33.2026.8.09.0049 | AL15: TJGO | AM15: ACTIVE | AN15: 2026 | AO15: plan/homologation document found | AP15: BRASILIA | AQ15: DF | AR15: Bancos múltiplos, com carteira comercial | AS15: DEMAIS | AT15: LARGE CORP | AU15: 00000000 | AV15: 1 | AW15: LIKELY_FINANCIAL_BY_NAME ROWS:p10r35 UNRECONCILED_SOURCE
A16: CAIXA ECONOMICA FEDERAL | B16: 31052221 | D16: NEW | I16: ADRIANO ASSIS MATIAS | J16: Administrador | K16: (00) 4004-0104 | P16: HENRIETE ALEXANDRA SARTORI BERNABE | Q16: Administrador | R16: (00) 4004-0104 | T16: 31052221 | U16: B | V16: =IFERROR(VLOOKUP(U16,Assumptions!$A$7:$D$11,2,FALSE),0) | W16: =MAX(0.5,IFERROR(VLOOKUP(U16,Assumptions!$A$7:$D$11,3,FALSE),3)+IFERROR(VLOOKUP(U16,Assumptions!$A$7:$D$11,4,FALSE),8)/2-IF(AN16="",0,YEAR(TODAY())-AN16)) | X16: =T16*V16/(1+Assumptions!$B$3)^W16 | Y16: =IF(T16=0,"",ROUND(X16/T16*100,1)) | Z16: =X16*Assumptions!$B$4 | AA16: =IF(T16=0,"",ROUND(Z16/T16*100,1)) | AB16: =X16-Z16 | AC16: =IF(T16=0,"",ROUND((X16-Z16)/T16*100,1)) | AD16: UNKNOWN | AE16: https://credibilita.com.br/wp-content/uploads/2025/09/Relacao-Credores-29.04.2026.pdf | AF16: p1 r18 | AG16: p1: R$ 31.052.221,17 | AH16: UNKNOWN | AJ16: OK_NO_TOTALS | AK16: 5057720-48.2025.8.24.0023 | AL16: TJ | AN16: 2025 | AO16: live case, no plan document yet | AP16: BRASILIA | AQ16: DF | AR16: Caixas econômicas | AS16: DEMAIS | AT16: LARGE CORP | AU16: 00360305 | AV16: 1 | AW16: ROWS:p1r18 UNRECONCILED_SOURCE VALUE_COL:Valor_Após_Analise
A17: COOPERATIVA DE CREDITO DE LIVRE ADMISSAO DO CENTRO NORTE BRASILEIRO | B17: 25688384 | C17: COMERCIO RACOES BEM BOM LTDA | D17: NEW | I17: ANGELICA ARAUJO DINIZ CALDEIRA | J17: Diretor | K17: (62) 3311-3810 | P17: ARNALDO DE SOUSA TEIXEIRA JUNIOR | Q17: Diretor | R17: (62) 3311-3810 | T17: 25688384 | U17: A | V17: =IFERROR(VLOOKUP(U17,Assumptions!$A$7:$D$11,2,FALSE),0) | W17: =MAX(0.5,IFERROR(VLOOKUP(U17,Assumptions!$A$7:$D$11,3,FALSE),3)+IFERROR(VLOOKUP(U17,Assumptions!$A$7:$D$11,4,FALSE),8)/2-IF(AN17="",0,YEAR(TODAY())-AN17)) | X17: =T17*V17/(1+Assumptions!$B$3)^W17 | Y17: =IF(T17=0,"",ROUND(X17/T17*100,1)) | Z17: =X17*Assumptions!$B$4 | AA17: =IF(T17=0,"",ROUND(Z17/T17*100,1)) | AB17: =X17-Z17 | AC17: =IF(T17=0,"",ROUND((X17-Z17)/T17*100,1)) | AD17: CONFIRMED | AE17: https://stenius.com.br/wp-content/uploads/2026/06/EDITAL-GRUPO-3E.pdf | AF17: p12 r8 | AG17: p12: R$ 25.688.383,88 | AH17: DEBTOR_LIST | AI17: 2026-06-22 | AJ17: OK_NO_TOTALS | AK17: 5341375-33.2026.8.09.0049 | AL17: TJGO | AM17: ACTIVE | AN17: 2026 | AO17: plan/homologation document found | AP17: ANAPOLIS | AQ17: GO | AR17: Cooperativas de crédito mútuo | AS17: DEMAIS | AT17: MID-MARKET | AU17: 02282709 | AV17: 1 | AW17: LIKELY_FINANCIAL_BY_NAME ROWS:p12r8 UNRECONCILED_SOURCE
A18: BANCO FIBRA SA | B18: 45662832 | C18: EGESA ENGENHARIA S/A (Consórcio ETDI) | D18: NEW | I18: ARNO SCHWARZ | J18: Presidente | K18: (11) 3847-6943 | P18: ANDRE CADIME DE GODOI | Q18: Diretor | R18: (11) 3847-6943 | T18: 45662832 | U18: ? | V18: =IFERROR(VLOOKUP(U18,Assumptions!$A$7:$D$11,2,FALSE),0) | W18: =MAX(0.5,IFERROR(VLOOKUP(U18,Assumptions!$A$7:$D$11,3,FALSE),3)+IFERROR(VLOOKUP(U18,Assumptions!$A$7:$D$11,4,FALSE),8)/2-IF(AN18="",0,YEAR(TODAY())-AN18)) | X18: =T18*V18/(1+Assumptions!$B$3)^W18 | Y18: =IF(T18=0,"",ROUND(X18/T18*100,1)) | Z18: =X18*Assumptions!$B$4 | AA18: =IF(T18=0,"",ROUND(Z18/T18*100,1)) | AB18: =X18-Z18 | AC18: =IF(T18=0,"",ROUND((X18-Z18)/T18*100,1)) | AD18: UNKNOWN | AE18: https://scalzilliaj.com.br/sgc/download.php?file=files/processo_documento/processo_documento09514021082025_1_.pdf&nome=04 - Relação de credores das Recuperandas | AF18: p62 r15 | AG18: p62: R$ 45.662.831,72 | AH18: DEBTOR_LIST | AJ18: OK | AK18: (not printed) | AO18: RJ case number not identified on the document | AP18: SAO PAULO | AQ18: SP | AR18: Bancos múltiplos, com carteira comercial | AS18: DEMAIS | AT18: LARGE CORP | AU18: 58616418 | AV18: 1 | AW18: LIKELY_FINANCIAL_BY_NAME ROWS:p62r15 VALUE_COL:Valor_Atualizado CASE_NUMBER_CORRECTED
A19: CAIXA ECONOMICA FEDERAL | B19: 29895475 | C19: E FALENCIA | D19: NEW | I19: ADRIANO ASSIS MATIAS | J19: Administrador | K19: (00) 4004-0104 | P19: HENRIETE ALEXANDRA SARTORI BERNABE | Q19: Administrador | R19: (00) 4004-0104 | T19: 29895475 | U19: B | V19: =IFERROR(VLOOKUP(U19,Assumptions!$A$7:$D$11,2,FALSE),0) | W19: =MAX(0.5,IFERROR(VLOOKUP(U19,Assumptions!$A$7:$D$11,3,FALSE),3)+IFERROR(VLOOKUP(U19,Assumptions!$A$7:$D$11,4,FALSE),8)/2-IF(AN19="",0,YEAR(TODAY())-AN19)) | X19: =T19*V19/(1+Assumptions!$B$3)^W19 | Y19: =IF(T19=0,"",ROUND(X19/T19*100,1)) | Z19: =X19*Assumptions!$B$4 | AA19: =IF(T19=0,"",ROUND(Z19/T19*100,1)) | AB19: =X19-Z19 | AC19: =IF(T19=0,"",ROUND((X19-Z19)/T19*100,1)) | AD19: ESTIMATED | AE19: https://recuperasolucoes.com/wp-content/plugins/download-attachments/includes/download.php?id=1597 | AF19: p13 r10 | AG19: p13: R$ 29.895.475,21 | AH19: DEBTOR_LIST | AI19: 2026-05-21 | AJ19: OK | AK19: 0001639-09.2026.8.17.2810 | AL19: TJPE | AM19: ACTIVE | AN19: 2026 | AO19: live case, no plan document yet | AP19: BRASILIA | AQ19: DF | AR19: Caixas econômicas | AS19: DEMAIS | AT19: LARGE CORP | AU19: 00360305 | AV19: 1 | AW19: LIKELY_FINANCIAL_BY_NAME ROWS:p13r10
A20: FUNDO DE INVESTIMENTO EM DIREITOS CREDITÓRIOS NÃO PADRONIZADOS MULTISSETORIA L BS NP | B20: 14857605 | C20: Conduscabos Brasil Indústria Comércio de | D20: NEW | T20: 14857605 | U20: B | V20: =IFERROR(VLOOKUP(U20,Assumptions!$A$7:$D$11,2,FALSE),0) | W20: =MAX(0.5,IFERROR(VLOOKUP(U20,Assumptions!$A$7:$D$11,3,FALSE),3)+IFERROR(VLOOKUP(U20,Assumptions!$A$7:$D$11,4,FALSE),8)/2-IF(AN20="",0,YEAR(TODAY())-AN20)) | X20: =T20*V20/(1+Assumptions!$B$3)^W20 | Y20: =IF(T20=0,"",ROUND(X20/T20*100,1)) | Z20: =X20*Assumptions!$B$4 | AA20: =IF(T20=0,"",ROUND(Z20/T20*100,1)) | AB20: =X20-Z20 | AC20: =IF(T20=0,"",ROUND((X20-Z20)/T20*100,1)) | AD20: ESTIMATED | AE20: https://assistjud.com.br/wp-content/uploads/elementor/forms/65098c80a5824.pdf | AF20: p7 r8; p10 r1; p18 r2 | AG20: p7: R$ 10.954.112,61; p10: R$ 1.455.516,44; p18: R$ 2.447.975,63 | AH20: AJ_LIST | AI20: 2023-09-18 | AJ20: OK_NO_TOTALS | AK20: 8005129-09.2023.8.05.0039 | AL20: TJBA | AM20: ACTIVE | AN20: 2023 | AO20: live case, no plan document yet | AT20: MID-MARKET | AU20: 12428086 | AV20: 3 | AW20: LIKELY_FINANCIAL_BY_NAME ROWS:p7r8,p10r1,p18r2 UNRECONCILED_SOURCE
A21: Cooperativa de Crédito de Livre Admissão do Vale do São Patrício Ltda - Sicoob Coopercred | B21: 20802132 | C21: COMERCIO RACOES BEM BOM LTDA | D21: NEW | T21: 20802132 | U21: A | V21: =IFERROR(VLOOKUP(U21,Assumptions!$A$7:$D$11,2,FALSE),0) | W21: =MAX(0.5,IFERROR(VLOOKUP(U21,Assumptions!$A$7:$D$11,3,FALSE),3)+IFERROR(VLOOKUP(U21,Assumptions!$A$7:$D$11,4,FALSE),8)/2-IF(AN21="",0,YEAR(TODAY())-AN21)) | X21: =T21*V21/(1+Assumptions!$B$3)^W21 | Y21: =IF(T21=0,"",ROUND(X21/T21*100,1)) | Z21: =X21*Assumptions!$B$4 | AA21: =IF(T21=0,"",ROUND(Z21/T21*100,1)) | AB21: =X21-Z21 | AC21: =IF(T21=0,"",ROUND((X21-Z21)/T21*100,1)) | AD21: CONFIRMED | AE21: https://stenius.com.br/wp-content/uploads/2026/06/EDITAL-GRUPO-3E.pdf | AF21: p12 r9 | AG21: p12: R$ 20.802.131,71 | AH21: DEBTOR_LIST | AI21: 2026-06-22 | AJ21: OK_NO_TOTALS | AK21: 5341375-33.2026.8.09.0049 | AL21: TJGO | AM21: ACTIVE | AN21: 2026 | AO21: plan/homologation document found | AT21: MID-MARKET | AU21: 00968602 | AV21: 1 | AW21: LIKELY_FINANCIAL_BY_NAME ROWS:p12r9 UNRECONCILED_SOURCE
A22: KLT PARTICIPACOES SA | B22: 20417361 | D22: NEW | I22: GILBERTO RECH | J22: Presidente | K22: (47) 3062-8301 | P22: DENIZE CRISTINA MARTINS RECH | Q22: Diretor | R22: (47) 3062-8301 | T22: 20417361 | U22: B | V22: =IFERROR(VLOOKUP(U22,Assumptions!$A$7:$D$11,2,FALSE),0) | W22: =MAX(0.5,IFERROR(VLOOKUP(U22,Assumptions!$A$7:$D$11,3,FALSE),3)+IFERROR(VLOOKUP(U22,Assumptions!$A$7:$D$11,4,FALSE),8)/2-IF(AN22="",0,YEAR(TODAY())-AN22)) | X22: =T22*V22/(1+Assumptions!$B$3)^W22 | Y22: =IF(T22=0,"",ROUND(X22/T22*100,1)) | Z22: =X22*Assumptions!$B$4 | AA22: =IF(T22=0,"",ROUND(Z22/T22*100,1)) | AB22: =X22-Z22 | AC22: =IF(T22=0,"",ROUND((X22-Z22)/T22*100,1)) | AD22: UNKNOWN | AE22: https://credibilita.com.br/wp-content/uploads/2025/09/Relacao-Credores-29.04.2026.pdf | AF22: p1 r31 | AG22: p1: R$ 20.417.361,13 | AH22: UNKNOWN | AJ22: OK_NO_TOTALS | AK22: 5057720-48.2025.8.24.0023 | AL22: TJ | AN22: 2025 | AO22: live case, no plan document yet | AP22: ITAJAI | AQ22: SC | AR22: Holdings de instituições não-financeiras | AS22: DEMAIS | AT22: MID-MARKET | AU22: 11303092 | AV22: 1 | AW22: ROWS:p1r31 UNRECONCILED_SOURCE VALUE_COL:Valor_Após_Analise
A23: ITAU UNIBANCO S.A. | B23: 10230308 | C23: R W CONSTRUCOES LTDA | D23: NEW | I23: FELIPE SAMPAIO NABUCO | J23: Administrador | K23: (11) 3003-4828 | P23: MILTON MALUHY FILHO | Q23: Presidente | R23: (11) 3003-4828 | T23: 10230308 | U23: B | V23: =IFERROR(VLOOKUP(U23,Assumptions!$A$7:$D$11,2,FALSE),0) | W23: =MAX(0.5,IFERROR(VLOOKUP(U23,Assumptions!$A$7:$D$11,3,FALSE),3)+IFERROR(VLOOKUP(U23,Assumptions!$A$7:$D$11,4,FALSE),8)/2-IF(AN23="",0,YEAR(TODAY())-AN23)) | X23: =T23*V23/(1+Assumptions!$B$3)^W23 | Y23: =IF(T23=0,"",ROUND(X23/T23*100,1)) | Z23: =X23*Assumptions!$B$4 | AA23: =IF(T23=0,"",ROUND(Z23/T23*100,1)) | AB23: =X23-Z23 | AC23: =IF(T23=0,"",ROUND((X23-Z23)/T23*100,1)) | AD23: ESTIMATED | AE23: https://lrflideres.com.br/wp-content/plugins/download-attachments/includes/download.php?id=4023 | AF23: p4 r79; p7 r104; p8 r83; p9 r78 | AG23: p4: R$ 1.877.913,26; p7: R$ 5.246.171,01; p8: R$ 2.428.571,55; p9: R$ 677.652,22 | AH23: DEBTOR_LIST | AJ23: QUARANTINED | AK23: 0002484-82.2022.8.17.2001 | AL23: TJPE | AM23: ACTIVE | AN23: 2022 | AO23: live case, no plan document yet | AP23: SAO PAULO | AQ23: SP | AR23: Bancos comerciais | AS23: DEMAIS | AT23: LARGE CORP | AU23: 60701190 | AV23: 4 | AW23: LIKELY_FINANCIAL_BY_NAME PARTIAL_DOC_CLASS_III_RECONCILED ROWS:p4r79,p7r104,p8r83,p9r78
A24: CAIXA ECONOMICA FEDERAL | B24: 12089695 | C24: VEV COMERCIO DE MEDICAMENTOS LTDA EM RECUPERACAO JUDICIAL | D24: NEW | I24: ADRIANO ASSIS MATIAS | J24: Administrador | K24: (00) 4004-0104 | P24: HENRIETE ALEXANDRA SARTORI BERNABE | Q24: Administrador | R24: (00) 4004-0104 | T24: 12089695 | U24: B | V24: =IFERROR(VLOOKUP(U24,Assumptions!$A$7:$D$11,2,FALSE),0) | W24: =MAX(0.5,IFERROR(VLOOKUP(U24,Assumptions!$A$7:$D$11,3,FALSE),3)+IFERROR(VLOOKUP(U24,Assumptions!$A$7:$D$11,4,FALSE),8)/2-IF(AN24="",0,YEAR(TODAY())-AN24)) | X24: =T24*V24/(1+Assumptions!$B$3)^W24 | Y24: =IF(T24=0,"",ROUND(X24/T24*100,1)) | Z24: =X24*Assumptions!$B$4 | AA24: =IF(T24=0,"",ROUND(Z24/T24*100,1)) | AB24: =X24-Z24 | AC24: =IF(T24=0,"",ROUND((X24-Z24)/T24*100,1)) | AD24: ESTIMATED | AE24: https://marquesadmjudicial.com.br/sgc/download.php?file=files/processo_documento/processo_documento15293208032024_1_.pdf&nome=Relação Nominal de Credores da AJ-Sintética | AF24: p22 r10 | AG24: p22: R$ 12.089.694,64 | AH24: AJ_LIST | AI24: 2023-03-02 | AJ24: QUARANTINED | AK24: 0005010-98.2023.8.16.0001 | AL24: TJPR | AM24: ACTIVE | AN24: 2023 | AO24: live case, no plan document yet | AP24: BRASILIA | AQ24: DF | AR24: Caixas econômicas | AS24: DEMAIS | AT24: LARGE CORP | AU24: 00360305 | AV24: 1 | AW24: LIKELY_FINANCIAL_BY_NAME PARTIAL_DOC_CLASS_III_RECONCILED ROWS:p22r10
A25: BANCO ABC BRASIL S.A. | B25: 18590200 | D25: NEW | I25: SERGIO LULIA JACOB | J25: Presidente | K25: (11) 3170-2000 | P25: ADRIANA FERNANDES PERES | Q25: Diretor | R25: (11) 3170-2000 | T25: 18590200 | U25: B | V25: =IFERROR(VLOOKUP(U25,Assumptions!$A$7:$D$11,2,FALSE),0) | W25: =MAX(0.5,IFERROR(VLOOKUP(U25,Assumptions!$A$7:$D$11,3,FALSE),3)+IFERROR(VLOOKUP(U25,Assumptions!$A$7:$D$11,4,FALSE),8)/2-IF(AN25="",0,YEAR(TODAY())-AN25)) | X25: =T25*V25/(1+Assumptions!$B$3)^W25 | Y25: =IF(T25=0,"",ROUND(X25/T25*100,1)) | Z25: =X25*Assumptions!$B$4 | AA25: =IF(T25=0,"",ROUND(Z25/T25*100,1)) | AB25: =X25-Z25 | AC25: =IF(T25=0,"",ROUND((X25-Z25)/T25*100,1)) | AD25: UNKNOWN | AE25: https://credibilita.com.br/wp-content/uploads/2025/09/Relacao-Credores-29.04.2026.pdf | AF25: p1 r4; p1 r5 | AG25: p1: R$ 16.575.188,17; p1: R$ 2.015.012,12 | AH25: UNKNOWN | AJ25: OK_NO_TOTALS | AK25: 5057720-48.2025.8.24.0023 | AL25: TJ | AN25: 2025 | AO25: live case, no plan document yet | AP25: SAO PAULO | AQ25: SP | AR25: Bancos múltiplos, com carteira comercial | AS25: DEMAIS | AT25: LARGE CORP | AU25: 28195667 | AV25: 2 | AW25: ROWS:p1r4,p1r5 UNRECONCILED_SOURCE VALUE_COL:Valor_Após_Analise
A26: BANCO NACIONAL DE DESENVOLVIMENTO ECONOMICO E SOCIAL | B26: 14441559 | C26: Grupo Arnon de Mello — Lindoso e Araujo | D26: NEW | T26: 14441559 | U26: C | V26: =IFERROR(VLOOKUP(U26,Assumptions!$A$7:$D$11,2,FALSE),0) | W26: =MAX(0.5,IFERROR(VLOOKUP(U26,Assumptions!$A$7:$D$11,3,FALSE),3)+IFERROR(VLOOKUP(U26,Assumptions!$A$7:$D$11,4,FALSE),8)/2-IF(AN26="",0,YEAR(TODAY())-AN26)) | X26: =T26*V26/(1+Assumptions!$B$3)^W26 | Y26: =IF(T26=0,"",ROUND(X26/T26*100,1)) | Z26: =X26*Assumptions!$B$4 | AA26: =IF(T26=0,"",ROUND(Z26/T26*100,1)) | AB26: =X26-Z26 | AC26: =IF(T26=0,"",ROUND((X26-Z26)/T26*100,1)) | AD26: UNKNOWN | AE26: https://recuperacaojudicial.squarespace.com/s/RJ-Grupo-Arnon-de-Melo-Lista-de-Credores-Consolidada-abril-2022.pdf | AF26: p7 r21 | AG26: p7: R$ 14.441.558,60 | AH26: AJ_LIST | AJ26: OK_NO_TOTALS | AK26: 0700256-03.2019.8.02.0066 | AL26: TJ | AN26: 2019 | AO26: 7y since filing, no plan document | AT26: MID-MARKET | AU26: 33657248 | AV26: 1 | AW26: LIKELY_FINANCIAL_BY_NAME ROWS:p7r21 UNRECONCILED_SOURCE
A27: JGM EMPREENDIMENTOS E PARTICIPACOES LTDA | B27: 12841448 | D27: NEW | I27: TCHARLA FRANCOISE MENEL | J27: Sócio-Administrador | K27: (04) 7371-0099 | T27: 12841448 | U27: C | V27: =IFERROR(VLOOKUP(U27,Assumptions!$A$7:$D$11,2,FALSE),0) | W27: =MAX(0.5,IFERROR(VLOOKUP(U27,Assumptions!$A$7:$D$11,3,FALSE),3)+IFERROR(VLOOKUP(U27,Assumptions!$A$7:$D$11,4,FALSE),8)/2-IF(AN27="",0,YEAR(TODAY())-AN27)) | X27: =T27*V27/(1+Assumptions!$B$3)^W27 | Y27: =IF(T27=0,"",ROUND(X27/T27*100,1)) | Z27: =X27*Assumptions!$B$4 | AA27: =IF(T27=0,"",ROUND(Z27/T27*100,1)) | AB27: =X27-Z27 | AC27: =IF(T27=0,"",ROUND((X27-Z27)/T27*100,1)) | AD27: UNKNOWN | AE27: https://administradorajudicialgs.com.br/wp-content/uploads/2024/12/relacao-de-credores-da-falida.pdf | AF27: p15 r42 | AG27: p15: R$ 12.841.448,00 | AH27: UNKNOWN | AI27: 2025-03-25 | AJ27: OK_NO_TOTALS | AK27: 0005010-50.2013.8.24.0026 | AL27: TJ | AN27: 2013 | AO27: 13y since filing, no plan document | AP27: JARAGUA DO SUL | AQ27: SC | AR27: Holdings de instituições não-financeiras | AS27: DEMAIS | AT27: MID-MARKET | AU27: 02553526 | AV27: 1 | AW27: ROWS:p15r42 UNRECONCILED_SOURCE
A28: BANCO ABC BRASIL S.A. | B28: 11070396 | C28: REAL DISTRIBUIDORA ÚNICA RIO COMÉRCIO DE REFRIGERAÇÃO LTDA | D28: NEW | I28: SERGIO LULIA JACOB | J28: Presidente | K28: (11) 3170-2000 | P28: ADRIANA FERNANDES PERES | Q28: Diretor | R28: (11) 3170-2000 | T28: 11070396 | U28: B | V28: =IFERROR(VLOOKUP(U28,Assumptions!$A$7:$D$11,2,FALSE),0) | W28: =MAX(0.5,IFERROR(VLOOKUP(U28,Assumptions!$A$7:$D$11,3,FALSE),3)+IFERROR(VLOOKUP(U28,Assumptions!$A$7:$D$11,4,FALSE),8)/2-IF(AN28="",0,YEAR(TODAY())-AN28)) | X28: =T28*V28/(1+Assumptions!$B$3)^W28 | Y28: =IF(T28=0,"",ROUND(X28/T28*100,1)) | Z28: =X28*Assumptions!$B$4 | AA28: =IF(T28=0,"",ROUND(Z28/T28*100,1)) | AB28: =X28-Z28 | AC28: =IF(T28=0,"",ROUND((X28-Z28)/T28*100,1)) | AD28: UNKNOWN | AE28: https://inova-aj.com.br/wp-content/uploads/2026/08/1a-Relacao-de-Credores-Real.pdf | AF28: p1 r14 | AG28: p1: R$ 11.070.395,80 | AH28: AJ_LIST | AI28: 2023-06-05 | AJ28: OK | AK28: 0873061-47.2023.8.19.0001 | AL28: TJ | AN28: 2023 | AO28: live case, no plan document yet | AP28: SAO PAULO | AQ28: SP | AR28: Bancos múltiplos, com carteira comercial | AS28: DEMAIS | AT28: LARGE CORP | AU28: 28195667 | AV28: 1 | AW28: ALT_VALUE:R$8.049.373,91 ROWS:p1r14
A29: STONE SOCIEDADE DE CREDITO DIRETO S.A. | B29: 16005897 | C29: COMERCIO RACOES BEM BOM LTDA | D29: NEW | I29: DIEGO VENTURA SALGADO | J29: Diretor | K29: (11) 3568-6318 | P29: EDUARDO VICENTE Y SILVA DOS SANTOS | Q29: Diretor | R29: (11) 3568-6318 | T29: 16005897 | U29: A | V29: =IFERROR(VLOOKUP(U29,Assumptions!$A$7:$D$11,2,FALSE),0) | W29: =MAX(0.5,IFERROR(VLOOKUP(U29,Assumptions!$A$7:$D$11,3,FALSE),3)+IFERROR(VLOOKUP(U29,Assumptions!$A$7:$D$11,4,FALSE),8)/2-IF(AN29="",0,YEAR(TODAY())-AN29)) | X29: =T29*V29/(1+Assumptions!$B$3)^W29 | Y29: =IF(T29=0,"",ROUND(X29/T29*100,1)) | Z29: =X29*Assumptions!$B$4 | AA29: =IF(T29=0,"",ROUND(Z29/T29*100,1)) | AB29: =X29-Z29 | AC29: =IF(T29=0,"",ROUND((X29-Z29)/T29*100,1)) | AD29: CONFIRMED | AE29: https://stenius.com.br/wp-content/uploads/2026/06/EDITAL-GRUPO-3E.pdf | AF29: p18 r11 | AG29: p18: R$ 16.005.897,08 | AH29: DEBTOR_LIST | AI29: 2026-06-22 | AJ29: OK_NO_TOTALS | AK29: 5341375-33.2026.8.09.0049 | AL29: TJGO | AM29: ACTIVE | AN29: 2026 | AO29: plan/homologation document found | AP29: SAO PAULO | AQ29: SP | AR29: Outras atividades de serviços financeiros não especificadas anteriormente | AS29: DEMAIS | AT29: LARGE CORP | AU29: 34590184 | AV29: 1 | AW29: ROWS:p18r11 UNRECONCILED_SOURCE
A30: BANCO SANTANDER (BRASIL) S.A. | B30: 13569297 | C30: IMOBI DESENVOLVIMENTO URBANO LTDA - EM RECUPERACAO JUDICIAL | D30: NEW | I30: GILSON FINKELSZTAIN | J30: Presidente | K30: (11) 4004-3535 | P30: ALESSANDRO CHAGAS FARIAS | Q30: Diretor | R30: (11) 4004-3535 | T30: 13569297 | U30: B | V30: =IFERROR(VLOOKUP(U30,Assumptions!$A$7:$D$11,2,FALSE),0) | W30: =MAX(0.5,IFERROR(VLOOKUP(U30,Assumptions!$A$7:$D$11,3,FALSE),3)+IFERROR(VLOOKUP(U30,Assumptions!$A$7:$D$11,4,FALSE),8)/2-IF(AN30="",0,YEAR(TODAY())-AN30)) | X30: =T30*V30/(1+Assumptions!$B$3)^W30 | Y30: =IF(T30=0,"",ROUND(X30/T30*100,1)) | Z30: =X30*Assumptions!$B$4 | AA30: =IF(T30=0,"",ROUND(Z30/T30*100,1)) | AB30: =X30-Z30 | AC30: =IF(T30=0,"",ROUND((X30-Z30)/T30*100,1)) | AD30: ESTIMATED | AE30: https://lrflideres.com.br/wp-content/plugins/download-attachments/includes/download.php?id=6273 | AF30: p3 r95 | AG30: p3: R$ 13.569.297,24 | AH30: AJ_LIST | AI30: 2024-11-14 | AJ30: OK | AK30: 0074500-63.2024.8.17.2001 | AL30: TJPE | AM30: ACTIVE | AN30: 2024 | AO30: live case, no plan document yet | AP30: SAO PAULO | AQ30: SP | AR30: Bancos múltiplos, com carteira comercial | AS30: DEMAIS | AT30: LARGE CORP | AU30: 90400888 | AV30: 1 | AW30: LIKELY_FINANCIAL_BY_NAME ROWS:p3r95
A31: BANCO SANTANDER (BRASIL) S.A. | B31: 21041903 | C31: E FALENCIA | D31: NEW | I31: GILSON FINKELSZTAIN | J31: Presidente | K31: (11) 4004-3535 | P31: ALESSANDRO CHAGAS FARIAS | Q31: Diretor | R31: (11) 4004-3535 | T31: 21041903 | U31: B | V31: =IFERROR(VLOOKUP(U31,Assumptions!$A$7:$D$11,2,FALSE),0) | W31: =MAX(0.5,IFERROR(VLOOKUP(U31,Assumptions!$A$7:$D$11,3,FALSE),3)+IFERROR(VLOOKUP(U31,Assumptions!$A$7:$D$11,4,FALSE),8)/2-IF(AN31="",0,YEAR(TODAY())-AN31)) | X31: =T31*V31/(1+Assumptions!$B$3)^W31 | Y31: =IF(T31=0,"",ROUND(X31/T31*100,1)) | Z31: =X31*Assumptions!$B$4 | AA31: =IF(T31=0,"",ROUND(Z31/T31*100,1)) | AB31: =X31-Z31 | AC31: =IF(T31=0,"",ROUND((X31-Z31)/T31*100,1)) | AD31: ESTIMATED | AE31: https://recuperasolucoes.com/wp-content/plugins/download-attachments/includes/download.php?id=1597 | AF31: p13 r19 | AG31: p13: R$ 21.041.903,06 | AH31: DEBTOR_LIST | AI31: 2026-05-21 | AJ31: OK | AK31: 0001639-09.2026.8.17.2810 | AL31: TJPE | AM31: ACTIVE | AN31: 2026 | AO31: live case, no plan document yet | AP31: SAO PAULO | AQ31: SP | AR31: Bancos múltiplos, com carteira comercial | AS31: DEMAIS | AT31: LARGE CORP | AU31: 90400888 | AV31: 1 | AW31: LIKELY_FINANCIAL_BY_NAME ROWS:p13r19
A32: CAIXA ECONOMICA FEDERAL | B32: 13335952 | C32: GRUPO ADLIM – LRF Líderes em Recuperação Judicial e Falência | D32: NEW | I32: ADRIANO ASSIS MATIAS | J32: Administrador | K32: (00) 4004-0104 | P32: HENRIETE ALEXANDRA SARTORI BERNABE | Q32: Administrador | R32: (00) 4004-0104 | T32: 13335952 | U32: B | V32: =IFERROR(VLOOKUP(U32,Assumptions!$A$7:$D$11,2,FALSE),0) | W32: =MAX(0.5,IFERROR(VLOOKUP(U32,Assumptions!$A$7:$D$11,3,FALSE),3)+IFERROR(VLOOKUP(U32,Assumptions!$A$7:$D$11,4,FALSE),8)/2-IF(AN32="",0,YEAR(TODAY())-AN32)) | X32: =T32*V32/(1+Assumptions!$B$3)^W32 | Y32: =IF(T32=0,"",ROUND(X32/T32*100,1)) | Z32: =X32*Assumptions!$B$4 | AA32: =IF(T32=0,"",ROUND(Z32/T32*100,1)) | AB32: =X32-Z32 | AC32: =IF(T32=0,"",ROUND((X32-Z32)/T32*100,1)) | AD32: ESTIMATED | AE32: https://lrflideres.com.br/wp-content/plugins/download-attachments/includes/download.php?id=6051 | AF32: p66 r74; p85 r24; p97 r23 | AG32: p66: R$ 8997846,92; p85: R$ 743735,91; p97: R$ 3594369,00 | AH32: AJ_LIST | AI32: 2024-08-12 | AJ32: QUARANTINED | AK32: 0019761-43.2024.8.17.2001 | AL32: TJPE | AM32: ACTIVE | AN32: 2024 | AO32: live case, no plan document yet | AP32: BRASILIA | AQ32: DF | AR32: Caixas econômicas | AS32: DEMAIS | AT32: LARGE CORP | AU32: 00360305 | AV32: 3 | AW32: LIKELY_FINANCIAL_BY_NAME PARTIAL_DOC_CLASS_III_RECONCILED ROWS:p66r74,p85r24,p97r23
A33: BOCOM BBM CORPORATE CREDIT HIGH YIELD FIF - CLASSE DE INVESTIMENTO MULT CRED PRIV - RESP LIMITADA | B33: 14500489 | D33: NEW | K33: (11) 3684-5122 | T33: 14500489 | U33: B | V33: =IFERROR(VLOOKUP(U33,Assumptions!$A$7:$D$11,2,FALSE),0) | W33: =MAX(0.5,IFERROR(VLOOKUP(U33,Assumptions!$A$7:$D$11,3,FALSE),3)+IFERROR(VLOOKUP(U33,Assumptions!$A$7:$D$11,4,FALSE),8)/2-IF(AN33="",0,YEAR(TODAY())-AN33)) | X33: =T33*V33/(1+Assumptions!$B$3)^W33 | Y33: =IF(T33=0,"",ROUND(X33/T33*100,1)) | Z33: =X33*Assumptions!$B$4 | AA33: =IF(T33=0,"",ROUND(Z33/T33*100,1)) | AB33: =X33-Z33 | AC33: =IF(T33=0,"",ROUND((X33-Z33)/T33*100,1)) | AD33: UNKNOWN | AE33: https://credibilita.com.br/wp-content/uploads/2025/09/Relacao-Credores-29.04.2026.pdf | AF33: p1 r15 | AG33: p1: R$ 14.500.488,51 | AH33: UNKNOWN | AJ33: OK_NO_TOTALS | AK33: 5057720-48.2025.8.24.0023 | AL33: TJ | AN33: 2025 | AO33: live case, no plan document yet | AP33: OSASCO | AQ33: SP | AR33: Fundos de investimento, exceto previdenciários e imobiliários | AS33: DEMAIS | AT33: MID-MARKET | AU33: 34799393 | AV33: 1 | AW33: ROWS:p1r15 UNRECONCILED_SOURCE VALUE_COL:Valor_Após_Analise
A34: Itaú Unibanco Holding S.A. | B34: 12852152 | C34: COMERCIO RACOES BEM BOM LTDA | D34: NEW | T34: 12852152 | U34: A | V34: =IFERROR(VLOOKUP(U34,Assumptions!$A$7:$D$11,2,FALSE),0) | W34: =MAX(0.5,IFERROR(VLOOKUP(U34,Assumptions!$A$7:$D$11,3,FALSE),3)+IFERROR(VLOOKUP(U34,Assumptions!$A$7:$D$11,4,FALSE),8)/2-IF(AN34="",0,YEAR(TODAY())-AN34)) | X34: =T34*V34/(1+Assumptions!$B$3)^W34 | Y34: =IF(T34=0,"",ROUND(X34/T34*100,1)) | Z34: =X34*Assumptions!$B$4 | AA34: =IF(T34=0,"",ROUND(Z34/T34*100,1)) | AB34: =X34-Z34 | AC34: =IF(T34=0,"",ROUND((X34-Z34)/T34*100,1)) | AD34: CONFIRMED | AE34: https://stenius.com.br/wp-content/uploads/2026/06/EDITAL-GRUPO-3E.pdf | AF34: p14 r63 | AG34: p14: R$ 12.852.151,77 | AH34: DEBTOR_LIST | AI34: 2026-06-22 | AJ34: OK_NO_TOTALS | AK34: 5341375-33.2026.8.09.0049 | AL34: TJGO | AM34: ACTIVE | AN34: 2026 | AO34: plan/homologation document found | AT34: MID-MARKET | AU34: 60872504 | AV34: 1 | AW34: LIKELY_FINANCIAL_BY_NAME ROWS:p14r63 UNRECONCILED_SOURCE
A35: BANCO DO BRASIL SA | B35: 10935148 | C35: BANCO DO BRASIL SA | D35: NEW | I35: TARCIANA PAULA GOMES MEDEIROS | J35: Presidente | K35: (61) 3493-9002 | P35: ALAN CARLOS GUEDES DE OLIVEIRA | Q35: Diretor | R35: (61) 3493-9002 | T35: 10935148 | U35: B | V35: =IFERROR(VLOOKUP(U35,Assumptions!$A$7:$D$11,2,FALSE),0) | W35: =MAX(0.5,IFERROR(VLOOKUP(U35,Assumptions!$A$7:$D$11,3,FALSE),3)+IFERROR(VLOOKUP(U35,Assumptions!$A$7:$D$11,4,FALSE),8)/2-IF(AN35="",0,YEAR(TODAY())-AN35)) | X35: =T35*V35/(1+Assumptions!$B$3)^W35 | Y35: =IF(T35=0,"",ROUND(X35/T35*100,1)) | Z35: =X35*Assumptions!$B$4 | AA35: =IF(T35=0,"",ROUND(Z35/T35*100,1)) | AB35: =X35-Z35 | AC35: =IF(T35=0,"",ROUND((X35-Z35)/T35*100,1)) | AD35: ESTIMATED | AE35: https://marquesadmjudicial.com.br/sgc/download.php?file=files/processo_documento/processo_documento09391327032025_1_.pdf&nome=Relação Nominal de Credores AJ | AF35: p4 r4 | AG35: p4: R$ 10.935.147,95 | AH35: AJ_LIST | AI35: 2025-03-21 | AJ35: QUARANTINED | AK35: 0044747-14.2024.8.16.0021 | AL35: TJPR | AM35: ACTIVE | AN35: 2024 | AO35: live case, no plan document yet | AP35: BRASILIA | AQ35: DF | AR35: Bancos múltiplos, com carteira comercial | AS35: DEMAIS | AT35: LARGE CORP | AU35: 00000000 | AV35: 1 | AW35: NAME_MISSING PARTIAL_DOC_CLASS_III_RECONCILED ROWS:p4r4
A36: BANCO DAYCOVAL S.A. | B36: 8739976.1 | C36: VEV COMERCIO DE MEDICAMENTOS LTDA EM RECUPERACAO JUDICIAL | D36: NEW | I36: ADELY DAYAN HAMOUI | J36: Diretor | K36: (11) 3138-0500 | P36: ALBERT ROUBEN | Q36: Diretor | R36: (11) 3138-0500 | T36: 8739976.1 | U36: B | V36: =IFERROR(VLOOKUP(U36,Assumptions!$A$7:$D$11,2,FALSE),0) | W36: =MAX(0.5,IFERROR(VLOOKUP(U36,Assumptions!$A$7:$D$11,3,FALSE),3)+IFERROR(VLOOKUP(U36,Assumptions!$A$7:$D$11,4,FALSE),8)/2-IF(AN36="",0,YEAR(TODAY())-AN36)) | X36: =T36*V36/(1+Assumptions!$B$3)^W36 | Y36: =IF(T36=0,"",ROUND(X36/T36*100,1)) | Z36: =X36*Assumptions!$B$4 | AA36: =IF(T36=0,"",ROUND(Z36/T36*100,1)) | AB36: =X36-Z36 | AC36: =IF(T36=0,"",ROUND((X36-Z36)/T36*100,1)) | AD36: ESTIMATED | AE36: https://marquesadmjudicial.com.br/sgc/download.php?file=files/processo_documento/processo_documento15293208032024_1_.pdf&nome=Relação Nominal de Credores da AJ-Sintética | AF36: p20 r9 | AG36: p20: R$ 8.739.976,12 | AH36: AJ_LIST | AI36: 2023-03-02 | AJ36: QUARANTINED | AK36: 0005010-98.2023.8.16.0001 | AL36: TJPR | AM36: ACTIVE | AN36: 2023 | AO36: live case, no plan document yet | AP36: SAO PAULO | AQ36: SP | AR36: Bancos múltiplos, com carteira comercial | AS36: DEMAIS | AT36: LARGE CORP | AU36: 62232889 | AV36: 1 | AW36: LIKELY_FINANCIAL_BY_NAME PARTIAL_DOC_CLASS_III_RECONCILED ROWS:p20r9
A37: BANCO BOCOM BBM S.A. | B37: 12763083 | D37: NEW | I37: ALEXANDRE LOWENKRON | J37: Diretor | K37: (71) 3243-2666 | P37: ALEXANDRE MOSCOSO CABRAL | Q37: Diretor | R37: (71) 3243-2666 | T37: 12763083 | U37: B | V37: =IFERROR(VLOOKUP(U37,Assumptions!$A$7:$D$11,2,FALSE),0) | W37: =MAX(0.5,IFERROR(VLOOKUP(U37,Assumptions!$A$7:$D$11,3,FALSE),3)+IFERROR(VLOOKUP(U37,Assumptions!$A$7:$D$11,4,FALSE),8)/2-IF(AN37="",0,YEAR(TODAY())-AN37)) | X37: =T37*V37/(1+Assumptions!$B$3)^W37 | Y37: =IF(T37=0,"",ROUND(X37/T37*100,1)) | Z37: =X37*Assumptions!$B$4 | AA37: =IF(T37=0,"",ROUND(Z37/T37*100,1)) | AB37: =X37-Z37 | AC37: =IF(T37=0,"",ROUND((X37-Z37)/T37*100,1)) | AD37: UNKNOWN | AE37: https://credibilita.com.br/wp-content/uploads/2025/09/Relacao-Credores-29.04.2026.pdf | AF37: p1 r7; p1 r8 | AG37: p1: R$ 11.190.064,90; p1: R$ 1.573.018,57 | AH37: UNKNOWN | AJ37: OK_NO_TOTALS | AK37: 5057720-48.2025.8.24.0023 | AL37: TJ | AN37: 2025 | AO37: live case, no plan document yet | AP37: SALVADOR | AQ37: BA | AR37: Bancos múltiplos, com carteira comercial | AS37: DEMAIS | AT37: LARGE CORP | AU37: 15114366 | AV37: 2 | AW37: ROWS:p1r7,p1r8 UNRECONCILED_SOURCE VALUE_COL:Valor_Após_Analise
A38: BANCO ALFA DE INVESTIMENTO S.A. | B38: 12737379 | D38: NEW | I38: MARCOS LIMA MONTEIRO | J38: Presidente | K38: (11) 3175-7575 | P38: ALBERTO MONTEIRO DE QUEIROZ NETTO | Q38: Diretor | R38: (11) 3175-7575 | T38: 12737379 | U38: B | V38: =IFERROR(VLOOKUP(U38,Assumptions!$A$7:$D$11,2,FALSE),0) | W38: =MAX(0.5,IFERROR(VLOOKUP(U38,Assumptions!$A$7:$D$11,3,FALSE),3)+IFERROR(VLOOKUP(U38,Assumptions!$A$7:$D$11,4,FALSE),8)/2-IF(AN38="",0,YEAR(TODAY())-AN38)) | X38: =T38*V38/(1+Assumptions!$B$3)^W38 | Y38: =IF(T38=0,"",ROUND(X38/T38*100,1)) | Z38: =X38*Assumptions!$B$4 | AA38: =IF(T38=0,"",ROUND(Z38/T38*100,1)) | AB38: =X38-Z38 | AC38: =IF(T38=0,"",ROUND((X38-Z38)/T38*100,1)) | AD38: UNKNOWN | AE38: https://credibilita.com.br/wp-content/uploads/2025/09/Relacao-Credores-29.04.2026.pdf | AF38: p1 r6 | AG38: p1: R$ 12.737.378,82 | AH38: UNKNOWN | AJ38: OK_NO_TOTALS | AK38: 5057720-48.2025.8.24.0023 | AL38: TJ | AN38: 2025 | AO38: live case, no plan document yet | AP38: SAO PAULO | AQ38: SP | AR38: Bancos de investimento | AS38: DEMAIS | AT38: LARGE CORP | AU38: 60770336 | AV38: 1 | AW38: ROWS:p1r6 UNRECONCILED_SOURCE VALUE_COL:Valor_Após_Analise
A39: BANCO SANTANDER (BRASIL) S.A. | B39: 10130566 | C39: GRUPO ADLIM – LRF Líderes em Recuperação Judicial e Falência | D39: NEW | I39: GILSON FINKELSZTAIN | J39: Presidente | K39: (11) 4004-3535 | P39: ALESSANDRO CHAGAS FARIAS | Q39: Diretor | R39: (11) 4004-3535 | T39: 10130566 | U39: B | V39: =IFERROR(VLOOKUP(U39,Assumptions!$A$7:$D$11,2,FALSE),0) | W39: =MAX(0.5,IFERROR(VLOOKUP(U39,Assumptions!$A$7:$D$11,3,FALSE),3)+IFERROR(VLOOKUP(U39,Assumptions!$A$7:$D$11,4,FALSE),8)/2-IF(AN39="",0,YEAR(TODAY())-AN39)) | X39: =T39*V39/(1+Assumptions!$B$3)^W39 | Y39: =IF(T39=0,"",ROUND(X39/T39*100,1)) | Z39: =X39*Assumptions!$B$4 | AA39: =IF(T39=0,"",ROUND(Z39/T39*100,1)) | AB39: =X39-Z39 | AC39: =IF(T39=0,"",ROUND((X39-Z39)/T39*100,1)) | AD39: ESTIMATED | AE39: https://lrflideres.com.br/wp-content/plugins/download-attachments/includes/download.php?id=6051 | AF39: p66 r71; p85 r23; p97 r22 | AG39: p66: R$ 5124521,38; p85: R$ 5006044,87; p97: R$ 5006044,87 | AH39: AJ_LIST | AI39: 2024-08-12 | AJ39: QUARANTINED | AK39: 0019761-43.2024.8.17.2001 | AL39: TJPE | AM39: ACTIVE | AN39: 2024 | AO39: live case, no plan document yet | AP39: SAO PAULO | AQ39: SP | AR39: Bancos múltiplos, com carteira comercial | AS39: DEMAIS | AT39: LARGE CORP | AU39: 90400888 | AV39: 2 | AW39: LIKELY_FINANCIAL_BY_NAME PARTIAL_DOC_CLASS_III_RECONCILED ROWS:p66r71,p85r23
A40: BANCO BRADESCO S.A. | B40: 12430000 | C40: Cerealista Sa | D40: NEW | I40: MARCELO DE ARAUJO NORONHA | J40: Presidente | K40: (11) 3684-5122 | P40: AFRANIO CARLOS CAMARGO DANTZGER | Q40: Diretor | R40: (11) 3684-5122 | T40: 12430000 | U40: B | V40: =IFERROR(VLOOKUP(U40,Assumptions!$A$7:$D$11,2,FALSE),0) | W40: =MAX(0.5,IFERROR(VLOOKUP(U40,Assumptions!$A$7:$D$11,3,FALSE),3)+IFERROR(VLOOKUP(U40,Assumptions!$A$7:$D$11,4,FALSE),8)/2-IF(AN40="",0,YEAR(TODAY())-AN40)) | X40: =T40*V40/(1+Assumptions!$B$3)^W40 | Y40: =IF(T40=0,"",ROUND(X40/T40*100,1)) | Z40: =X40*Assumptions!$B$4 | AA40: =IF(T40=0,"",ROUND(Z40/T40*100,1)) | AB40: =X40-Z40 | AC40: =IF(T40=0,"",ROUND((X40-Z40)/T40*100,1)) | AD40: ESTIMATED | AE40: https://ajruiz.com.br/sites/default/files/public/arquivos-processos/2026-01/safrasul_relacao_de_credores_recuperanda.pdf | AF40: p8 r16; p8 r17; p8 r18; p8 r19 | AG40: p8: R$ 4.000.000,00; p8: R$ 8.000.000,00; p8: R$ 400.000,00; p8: R$ 30.000,00 | AH40: AJ_LIST | AI40: 2026-01-14 | AJ40: OK_NO_TOTALS | AK40: 4000167-23.2025.8.26.0373 | AL40: TJSP | AM40: ACTIVE | AN40: 2025 | AO40: live case, no plan document yet | AP40: OSASCO | AQ40: SP | AR40: Bancos múltiplos, com carteira comercial | AS40: DEMAIS | AT40: LARGE CORP | AU40: 60746948 | AV40: 4 | AW40: LIKELY_FINANCIAL_BY_NAME ROWS:p8r16,p8r17,p8r18,p8r19 UNRECONCILED_SOURCE
